Workbook

Sheet INSTRUCTIONS
A1: TEMPLATE_30d_matrix -- CRYSTAL CLEAR INSTRUCTIONS (2026-09-11) -- ANY DUMB AGENT CAN EXECUTE *** ON S1 NEVER ON MACBOOK *** If you are reading this, YOU MUST FOLLOW EVERY LINE. No skipping, no guessing, no inventing numbers. This tab + FILTER_DICTIONARY_V2 + v14_sequential_filler.py + v12_quick_engine/backtest_v12_engine are LAW.
A2: ⚠️ MACHINE RULE -- MAC ONLY TRADES LIVE (ez_manage / tradier_manage) AND NEVER TESTS. MAC has 5 NPZs and NO NVDA.npz / NO CRWD.npz → any S1 vector returns 'no NPZ' in 0.2s. S1 = 157.180.125.52 (s1-int via gateway 157.90.168.35) has 1000+ NPZs (42-49M) and is ONLY test host (S2 for mega sweeps only). If on MacBook, SSH FIRST: ssh 157.180.125.52 OR ssh -fNT s1-sftp && ssh s1-int. Verify: ls /home/niels/binance-sandbox/backtest_v8/indicators/NVDA.npz must exist. If not, STOP.
A3: ⚠️ SYNC & BACKUP RULE -- KEEP ALL FIXES synced Mac <-> S1 via rsync -avz -e 'ssh -p 2201' and KEEP BACKUPS before EVERY edit: cp <file> backups/before_<desc>_$(date +%Y%m%d%H%M).py . Autosave launchd commits git every 15min. /backups/ ONLY reliable history. After BACKTEST_BIBLE.md edit run tools/sync_backtest_bible.sh (SHA256). NEVER edit S1 copy directly without rsync back.
A4: ⚠️ INSTRUCTIONS ARE LAW — v12_pilot.py MUST READ THIS TAB AT STARTUP. DEPRECATED 2026-09-11: v12_pilot_sheet_runner.py / v14_sequential_filler.py are DISABLED (empty L:BI, 408-row waste). CORRECT PIPELINE: tools/simple_switch_filter_calculator.py (26-col, 9291×26, resumable, <0.7s/NPZ) → data/reports/BNB_GLD_FULL_*.csv → tools/fill_template_from_csv.py → SPREADSHEETS/TEMPLATE_*_FILLED.xlsx (BASELINE + Results 9291 + L:IL 6503). This tab wins over code if conflict.
A5: 0) PRECONDITION -- DO NOT START UNTIL DEFAULTS ARE BOLD. Every row where B == live default (config.py Config for crypto / config_tradier.py TradierConfig for stocks = 1118 fields) must have A and B bold. ~50% rows bold. NEVER edit B (candidate value in col B). You only write C (override), E (baseline gain), F (delta vs E), G (variant gain), and L:BI per-filter deltas.
A6: 1) CREATE BASELINE WITH per_sym OVERRIDES for EXACT sym_side. GET OVERRIDES = union of data/hourly_reconfig/trb/active_config.json AND data/hourly_reconfig/per_sym_active_config.json for YOUR EXACT SYM_SIDE (SYMBOL+_LONG vs _SHORT are DIFFERENT, NEVER reuse). Example NVDA_LONG 8 overrides (BOUNCE_AUGMENT...), CRWD_SHORT 0. For each switch in union, find row where A==switch name and write override into C, BOLD GREEN font 006100 on fill C6EFCE. Do ALL overrides BEFORE baseline calc. Then baseline = vector_evaluate(sym_side, overrides) AND live_evaluate(sym_side, overrides) — they must parity (trades 0.80..1.25, gain 0.5pp|15%, sharpe 0.25). Write TEMPLATE_BASELINE_METRICS!B2 = gain, B? = bh. Verify WT_15M_BOUNCE True adds >100 trades/mo (fix in v12_quick_engine:5894 MAX_BARS_AGO=100). If trades 0 or <30, STOP and spawn agent to fix v12_quick_engine (6817/9010).
A7: 1b) BASELINE E2 = TEMPLATE_BASELINE_METRICS!B2 (gain). E3 = IF(F3>0,E2+F3,"") chain. Never repeat E. First pilot: WT_15M_BOUNCE True must be first positive delta or calculation BROKEN.
A8: 2) FOR EVERY ROW (EVERY SWITCH) TEST EVERY APPLICABLE FILTER × EVERY SETTING. MANDATORY until >100 sym_sides tested (see rule 9). Applicable = FILTER_DICTIONARY_V2 row where (sheets_app contains this tab lifecycle ENTRY/EXIT/REENTRY/AUGMENT/REDUCE or GLOBAL_CHECK) AND (gates token overlap with this switch OR rec is GENERAL). Use get_opportune_filters(switch, sheet) — it already implements this. For WT_15M_BOUNCE_OPEN_ENABLED True you MUST test its 12 sub-filters (BB_MIN 0.05/0.1/0.2, BB_MAX 0.95/0.9/0.8, LOW_1H True/False, HIGH_1H True/False, REL_VOL True/False) even if WT alone delta is NEG — they are FILTERS in FILTER_DICTIONARY, not switches. Do NOT discard. COL J lists per-switch opportune filters (up to 6 shown), COL L:BI holds per-filter deltas (one column per filter=opt).
A9: 2a) EVALUATION: For this row, build candidates: [switch alone] + [switch+each single filter distinct opt (skip opt==cur)] . If best single delta <=0, also test ALL combos of 2 and 3 among top-8 singles (C8,2=28 + C8,3=56 =84 combos). Each candidate = sanitize_overrides(variant, defaults) then vector_evaluate via prepare_batch/evaluate_prepared_sanitized (70-136ms, million/hour). NEVER use per-cell load_npz (3.65s) — use prepare_batch once per sym_side. Log every candidate: [CANDIDATE] switch=cand[+filter=opt] vec_gain delta vs cum trades sharpe. Pick MAX delta (beating-ideas-to-death, not first positive).
A10: 2b) DUPLICATE/0.0 CHECK — Immediately flag DUPLICATE (same delta for 2 different switches → formula bug, e.g. shared adx gate) or 0.0 (dead switch or >5s VECTOR_STALL). If duplicate/0.0, revise v12_quick_engine wiring to exact live numpy (622 not-causal) and run live_evaluate for parity. Fix before promoting.
A11: 2c) PROGRESS REPORT every 5min: count filled F cells per sheet (e.g. NVDA 2790/2823=98.8% — one baseline empty per sheet expected). Write data/reports/lifecycle_pilot/*_pilot_progress.json and SPREADSHEETS/*_pilot_progress.html refreshed 60s. Also log [ROW] sheet!r switch=cand[+filter] delta vs cum -> NEG/POSITIVE candidate.
A12: 3) PROMOTION: Only if best delta >0 AND live_evaluate parity passes (trades 0.80..1.25, gain 0.5pp|15%, sharpe 0.25) AND (vector_only deferred → final cumulative live check). Then write C = cand (bold green 006100 on C6EFCE), cumulative_gain = vec_gain, cumulative_overrides[switch]=cand and if filter best exists also [filter]=fval. Write Results_30d_Deltas row: key=switch=cand, col5=delta, col6=variant_gain, col8=variant_gain, col10=trades, col11=max_dd, col12=tim. Also batch write L:BI deltas for this row (one col per filter=opt = delta). E for this row = IF(F>0,Eprev+F,Eprev) — only F>0 gets bold green E/F/G and C. F/G written even if <=0 for audit, but E stays empty.
... A26: 15) CORRECT PIPELINE 2026-09-11 — S1 ONLY: timeout 1800 python -u tools/simple_switch_filter_calculator.py --symside SYM_SIDE --window-days 30 --max-switches 0 --max-filters 10 → wc -l 9291 26 cols → scp -P 2201 to Mac → python3 tools/fill_template_from_csv.py data/reports/BNB_GLD_FULL_SYM.csv SPREADSHEETS/TEMPLATE_SYM_FILLED.xlsx → verify E3/F3/L3 via openpyxl data_only. See SPREADSHEETS/TEMPLATE_BNBUSDC_LONG_30D_FILLED.xlsx as reference (148,640 Results cells).

Sheet FILTERS_EXPLAINED
A1: Filter | B1: Type | C1: What it does (plain English) | D1: Sheets | E1: Gated Switch | F1: Rec | G1: Tested As | H1: Options | I1: Default | J1: Example
A2: ADX_RANGING_THRESHOLD | B2: Threshold | C2: Blocks signal unless value > threshold (tunable level) | D2: ENTRY, GLOBAL, STOCKS_EXIT | E2: ADX_RANGING_THRESHOL | F2: GENERAL | G2: Blanket (page end) | H2: 20.0, ±25%, ±50% (4) | I2: 20.0 | J2: ADX_RANGING_THRESHOLD=20 -> delta vs cum
A3: ADX_RANGING_THRESHOLD | B3: Threshold | C3: Blocks signal unless value > threshold (tunable level) | D3: ENTRY, GLOBAL, STOCKS_EXIT | E3: ADX_RANGING_THRESHOL | F3: GENERAL | G3: Blanket (page end) | H3: 20.0, ±25%, ±50% (4) | I3: 20.0 | J3: ADX_RANGING_THRESHOLD=25 -> delta vs cum
A4: ADX_RANGING_THRESHOLD | B4: Threshold | C4: Blocks signal unless value > threshold (tunable level) | D4: ENTRY, GLOBAL, STOCKS_EXIT | E4: ADX_RANGING_THRESHOL | F4: GENERAL | G4: Blanket (page end) | H4: 20.0, ±25%, ±50% (4) | I4: 20.0 | J4: ADX_RANGING_THRESHOLD=15 -> delta vs cum
A5: ADX_RANGING_THRESHOLD | B5: Threshold | C5: Blocks signal unless value > threshold (tunable level) | D5: ENTRY, GLOBAL, STOCKS_EXIT | E5: ADX_RANGING_THRESHOL | F5: GENERAL | G5: Blanket (page end) | H5: 20.0, ±25%, ±50% (4) | I5: 20.0 | J5: ADX_RANGING_THRESHOLD=10 -> delta vs cum
A6: ATR_TRAIL_FILTER_TF | B6: MTF Gate | C6: Requires confirmation on multiple timeframes (e.g., 1h+4h) before signal counts | D6: EXIT | E6: ATR trail exits | F6: SPECIFIC — only gate | G6: Per-switch (with switch) | H6: OFF, 15m, 1h, 4h, D (5 options) | I6: 15m | J6: ATR_TRAIL_FILTER_TF=OFF -> delta vs cum
A7: ATR_TRAIL_FILTER_TF | B7: MTF Gate | C7: Requires confirmation on multiple timeframes (e.g., 1h+4h) before signal counts | D7: EXIT | E7: ATR trail exits | F7: SPECIFIC — only gate | G7: Per-switch (with switch) | H7: OFF, 15m, 1h, 4h, D (5 options) | I7: 15m | J7: ATR_TRAIL_FILTER_TF=D -> delta vs cum
A8: ATR_TRAIL_FILTER_TF | B8: MTF Gate | C8: Requires confirmation on multiple timeframes (e.g., 1h+4h) before signal counts | D8: EXIT | E8: ATR trail exits | F8: SPECIFIC — only gate | G8: Per-switch (with switch) | H8: OFF, 15m, 1h, 4h, D (5 options) | I8: 15m | J8: ATR_TRAIL_FILTER_TF=4h -> delta vs cum
A9: ATR_TRAIL_FILTER_TF | B9: MTF Gate | C9: Requires confirmation on multiple timeframes (e.g., 1h+4h) before signal counts | D9: EXIT | E9: ATR trail exits | F9: SPECIFIC — only gate | G9: Per-switch (with switch) | H9: OFF, 15m, 1h, 4h, D (5 options) | I9: 15m | J9: ATR_TRAIL_FILTER_TF=1h -> delta vs cum
A10: ATR_TRAIL_FILTER_TF | B10: MTF Gate | C10: Requires confirmation on multiple timeframes (e.g., 1h+4h) before signal counts | D10: EXIT | E10: ATR trail exits | F10: SPECIFIC — only gate | G10: Per-switch (with switch) | H10: OFF, 15m, 1h, 4h, D (5 options) | I10: 15m | J10: ATR_TRAIL_FILTER_TF=15m -> delta vs cum
A11: BANDAID_OFF_LOSER_RECOVER_PCT | B11: Threshold | C11: Blocks signal unless value > threshold (tunable level) | D11: AUGMENT, ENTRY, EXIT, GLOBAL, | E11: BANDAID_OFF_LOSER_RE | F11: GENERAL | G11: Blanket (page end) | H11: 0.0, ±25%, ±50% (4) | I11: 0.0 | J11: BANDAID_OFF_LOSER_RECOVER_PCT=0 -> delta vs cum
A12: BANDAID_OFF_LOSER_RECOVER_PCT | B12: Threshold | C12: Blocks signal unless value > threshold (tunable level) | D12: AUGMENT, ENTRY, EXIT, GLOBAL, | E12: BANDAID_OFF_LOSER_RE | F12: GENERAL | G12: Blanket (page end) | H12: 0.0, ±25%, ±50% (4) | I12: 0.0 | J12: BANDAID_OFF_LOSER_RECOVER_PCT=2.0 -> delta vs cum
... A303: LR_BAND_LADDER_STOCH_EXTREME | B303: Other | C303: Blocks signal unless value > threshold (tunable level) | D303: GLOBAL, STOCKS_EXIT | E303: LR_BAND_LADDER_STOCH | F303: GENERAL | G303: Blanket (page end) | H303: 30.0, alt | I303: 30.0 | J303: LR_BAND_LADDER_STOCH_EXTREME=30.0_ALT -> delta vs cum
A304: LR_BAND_LADDER_TF_BOTTOM | B304: MTF Gate | C304: Blocks signal unless value > threshold (tunable level) | D304: GLOBAL, STOCKS_EXIT | E304: LR_BAND_LADDER_TF_BO | F304: GENERAL | G304: Blanket (page end) | H304: , alt | J304: LR_BAND_LADDER_TF_BOTTOM=0 -> delta vs cum
A305: LR_BAND_LADDER_TF_BOTTOM | B305: MTF Gate | C305: Blocks signal unless value > threshold (tunable level) | D305: GLOBAL, STOCKS_EXIT | E305: LR_BAND_LADDER_TF_BO | F305: GENERAL | G305: Blanket (page end) | H305: , alt | J305: LR_BAND_LADDER_TF_BOTTOM=1 -> delta vs cum
A306: LR_BAND_LADDER_TF_TOP | B306: MTF Gate | C306: Blocks signal unless value > threshold (tunable level) | D306: GLOBAL, STOCKS_EXIT | E306: LR_BAND_LADDER_TF_TO | F306: GENERAL | G306: Blanket (page end) | H306: , alt | J306: LR_BAND_LADDER_TF_TOP=0 -> delta vs cum
A307: LR_BAND_LADDER_TF_TOP | B307: MTF Gate | C307: Blocks signal unless value > threshold (tunable level) | D307: GLOBAL, STOCKS_EXIT | E307: LR_BAND_LADDER_TF_TO | F307: GENERAL | G307: Blanket (page end) | H307: , alt | J307: LR_BAND_LADDER_TF_TOP=1 -> delta vs cum
A308: MANDATORY_REENTRY_WT_FILTER_MIN_TFS | B308: MTF Gate | C308: Blocks signal unless value > threshold (tunable level) | D308: GLOBAL, STOCKS_EXIT | E308: MANDATORY_REENTRY_WT | F308: GENERAL | G308: Blanket (page end) | H308: 1, +1, +2 (3) | I308: 1 | J308: MANDATORY_REENTRY_WT_FILTER_MIN_TFS=1 -> delta vs cum
A309: MANDATORY_REENTRY_WT_FILTER_MIN_TFS | B309: MTF Gate | C309: Blocks signal unless value > threshold (tunable level) | D309: GLOBAL, STOCKS_EXIT | E309: MANDATORY_REENTRY_WT | F309: GENERAL | G309: Blanket (page end) | H309: 1, +1, +2 (3) | I309: 1 | J309: MANDATORY_REENTRY_WT_FILTER_MIN_TFS=3 -> delta vs cum
A310: MANDATORY_REENTRY_WT_FILTER_MIN_TFS | B310: MTF Gate | C310: Blocks signal unless value > threshold (tunable level) | D310: GLOBAL, STOCKS_EXIT | E310: MANDATORY_REENTRY_WT | F310: GENERAL | G310: Blanket (page end) | H310: 1, +1, +2 (3) | I310: 1 | J310: MANDATORY_REENTRY_WT_FILTER_MIN_TFS=2 -> delta vs cum
A311: MANDATORY_REENTRY_WT_FILTER_MIN_VELOCITY | B311: Other | C311: Blocks signal unless value > threshold (tunable level) | D311: GLOBAL, STOCKS_EXIT | E311: MANDATORY_REENTRY_WT | F311: GENERAL | G311: Blanket (page end) | H311: 0.0, alt | I311: 0.0 | J311: MANDATORY_REENTRY_WT_FILTER_MIN_VELOCITY=0.0 -> delta vs cum
A312: MANDATORY_REENTRY_WT_FILTER_MIN_VELOCITY | B312: Other | C312: Blocks signal unless value > threshold (tunable level) | D312: GLOBAL, STOCKS_EXIT | E312: MANDATORY_REENTRY_WT | F312: GENERAL | G312: Blanket (page end) | H312: 0.0, alt | I312: 0.0 | J312: MANDATORY_REENTRY_WT_FILTER_MIN_VELOCITY=0.0_ALT -> delta vs cum
A313: MANDATORY_REENTRY_WT_FILTER_REQUIRE_FLIP | B313: Other | C313: Blocks signal unless value > threshold (tunable level) | D313: GLOBAL, STOCKS_EXIT | E313: MANDATORY_REENTRY_WT | F313: GENERAL | G313: Blanket (page end) | H313: False, alt | I313: False | J313: MANDATORY_REENTRY_WT_FILTER_REQUIRE_FLIP=False -> delta vs cum
A314: MANDATORY_REENTRY_WT_FILTER_REQUIRE_FLIP | B314: Other | C314: Blocks signal unless value > threshold (tunable level) | D314: GLOBAL, STOCKS_EXIT | E314: MANDATORY_REENTRY_WT | F314: GENERAL | G314: Blanket (page end) | H314: False, alt | I314: False | J314: MANDATORY_REENTRY_WT_FILTER_REQUIRE_FLIP=False_ALT -> delta vs cum
A315: MANDATORY_REENTRY_WT_FILTER_TF_MODE | B315: MTF Gate | C315: WT filter mode for mandatory reentry (e.g. 5m_or_15m). | Live read: `RANTEED_REE | D315: GLOBAL, STOCKS_EXIT | E315: MANDATORY_REENTRY_WT | F315: SPECIFIC — only gate | G315: Per-switch (with switch) | H315: 15m_only, alt | I315: 15m_only | J315: MANDATORY_REENTRY_WT_FILTER_TF_MODE=15m_only -> delta vs cum
A316: MANDATORY_REENTRY_WT_FILTER_TF_MODE | B316: MTF Gate | C316: WT filter mode for mandatory reentry (e.g. 5m_or_15m). | Live read: `RANTEED_REE | D316: GLOBAL, STOCKS_EXIT | E316: MANDATORY_REENTRY_WT | F316: SPECIFIC — only gate | G316: Per-switch (with switch) | H316: 15m_only, alt | I316: 15m_only | J316: MANDATORY_REENTRY_WT_FILTER_TF_MODE=15m_only_ALT -> delta vs cum
A317: MANDATORY_REENTRY_WT_FILTER_VELOCITY_RATIO | B317: Other | C317: Blocks signal unless value > threshold (tunable level) | D317: GLOBAL, STOCKS_EXIT | E317: MANDATORY_REENTRY_WT | F317: GENERAL | G317: Blanket (page end) | H317: 0.90, alt | I317: 0.90 | J317: MANDATORY_REENTRY_WT_FILTER_VELOCITY_RATIO=0.90 -> delta vs cum
A318: MANDATORY_REENTRY_WT_FILTER_VELOCITY_RATIO | B318: Other | C318: Blocks signal unless value > threshold (tunable level) | D318: GLOBAL, STOCKS_EXIT | E318: MANDATORY_REENTRY_WT | F318: GENERAL | G318: Blanket (page end) | H318: 0.90, alt | I318: 0.90 | J318: MANDATORY_REENTRY_WT_FILTER_VELOCITY_RATIO=0.90_ALT -> delta vs cum
A319: MARKET_QUALITY_SCORE_ENABLED | B319: Bool Flag | C319: Market quality score gate (choppiness). | Live read: `'MARKET_QUALITY_SCORE_ENAB | D319: ENTRY, GLOBAL, STOCKS_EXIT | E319: MARKET_QUALITY_SCORE | F319: GENERAL — uniform | G319: Blanket (page end) | H319: False, True (2) | I319: False | J319: MARKET_QUALITY_SCORE_ENABLED=False -> delta vs cum
... A415: PEAK_GIVEBACK_BE_EROSION_FILTER_TF | B415: MTF Gate | C415: Peak giveback / breakeven erosion filter TF. | Live read: `OCH_EXTREME', 'LR_BAN | D415: GLOBAL | E415: PEAK_GIVEBACK_BE_ERO | F415: SPECIFIC — only gate | G415: Per-switch (with switch) | H415: OFF, 15m, 1h, 4h, D (5 options) | I415: 15m | J415: PEAK_GIVEBACK_BE_EROSION_FILTER_TF=15m -> delta vs cum
A416: WT_15M_BOUNCE_BB_MIN | B416: Other | C416: WT 15m bounce: tightens/loosens bounce detection (BB width, vol, prev bar) | D416: REV_BOUNCE | E416: WT_15M_BOUNCE_OPEN_E | F416: SPECIFIC — only gate | G416: Per-switch (with switch) | J416: WT_15M_BOUNCE_BB_MIN=0.05 -> delta vs cum
A417: WT_15M_BOUNCE_BB_MIN | B417: Other | C417: WT 15m bounce: tightens/loosens bounce detection (BB width, vol, prev bar) | D417: REV_BOUNCE | E417: WT_15M_BOUNCE_OPEN_E | F417: SPECIFIC — only gate | G417: Per-switch (with switch) | J417: WT_15M_BOUNCE_BB_MIN=0.1 -> delta vs cum
A418: WT_15M_BOUNCE_BB_MIN | B418: Other | C418: WT 15m bounce: tightens/loosens bounce detection (BB width, vol, prev bar) | D418: REV_BOUNCE | E418: WT_15M_BOUNCE_OPEN_E | F418: SPECIFIC — only gate | G418: Per-switch (with switch) | J418: WT_15M_BOUNCE_BB_MIN=0.2 -> delta vs cum
A419: WT_15M_BOUNCE_BB_MAX | B419: Other | C419: WT 15m bounce: tightens/loosens bounce detection (BB width, vol, prev bar) | D419: REV_BOUNCE | E419: WT_15M_BOUNCE_OPEN_E | F419: SPECIFIC — only gate | G419: Per-switch (with switch) | J419: WT_15M_BOUNCE_BB_MAX=0.95 -> delta vs cum
A420: WT_15M_BOUNCE_BB_MAX | B420: Other | C420: WT 15m bounce: tightens/loosens bounce detection (BB width, vol, prev bar) | D420: REV_BOUNCE | E420: WT_15M_BOUNCE_OPEN_E | F420: SPECIFIC — only gate | G420: Per-switch (with switch) | J420: WT_15M_BOUNCE_BB_MAX=0.9 -> delta vs cum
A421: WT_15M_BOUNCE_BB_MAX | B421: Other | C421: WT 15m bounce: tightens/loosens bounce detection (BB width, vol, prev bar) | D421: REV_BOUNCE | E421: WT_15M_BOUNCE_OPEN_E | F421: SPECIFIC — only gate | G421: Per-switch (with switch) | J421: WT_15M_BOUNCE_BB_MAX=0.8 -> delta vs cum
A422: WT_15M_BOUNCE_LOW_1H_GT_PREV | B422: Other | C422: WT 15m bounce: tightens/loosens bounce detection (BB width, vol, prev bar) | D422: REV_BOUNCE | E422: WT_15M_BOUNCE_OPEN_E | F422: SPECIFIC — only gate | G422: Per-switch (with switch) | J422: WT_15M_BOUNCE_LOW_1H_GT_PREV=True -> delta vs cum
A423: WT_15M_BOUNCE_LOW_1H_GT_PREV | B423: Other | C423: WT 15m bounce: tightens/loosens bounce detection (BB width, vol, prev bar) | D423: REV_BOUNCE | E423: WT_15M_BOUNCE_OPEN_E | F423: SPECIFIC — only gate | G423: Per-switch (with switch) | J423: WT_15M_BOUNCE_LOW_1H_GT_PREV= -> delta vs cum
A424: WT_15M_BOUNCE_HIGH_1H_GT_PREV | B424: Other | C424: WT 15m bounce: tightens/loosens bounce detection (BB width, vol, prev bar) | D424: REV_BOUNCE | E424: WT_15M_BOUNCE_OPEN_E | F424: SPECIFIC — only gate | G424: Per-switch (with switch) | J424: WT_15M_BOUNCE_HIGH_1H_GT_PREV=True -> delta vs cum
A425: WT_15M_BOUNCE_HIGH_1H_GT_PREV | B425: Other | C425: WT 15m bounce: tightens/loosens bounce detection (BB width, vol, prev bar) | D425: REV_BOUNCE | E425: WT_15M_BOUNCE_OPEN_E | F425: SPECIFIC — only gate | G425: Per-switch (with switch) | J425: WT_15M_BOUNCE_HIGH_1H_GT_PREV= -> delta vs cum
A426: WT_15M_BOUNCE_REL_VOL_GT_1 | B426: Other | C426: WT 15m bounce: tightens/loosens bounce detection (BB width, vol, prev bar) | D426: REV_BOUNCE | E426: WT_15M_BOUNCE_OPEN_E | F426: SPECIFIC — only gate | G426: Per-switch (with switch) | J426: WT_15M_BOUNCE_REL_VOL_GT_1=True -> delta vs cum
A427: WT_15M_BOUNCE_REL_VOL_GT_1 | B427: Other | C427: WT 15m bounce: tightens/loosens bounce detection (BB width, vol, prev bar) | D427: REV_BOUNCE | E427: WT_15M_BOUNCE_OPEN_E | F427: SPECIFIC — only gate | G427: Per-switch (with switch) | J427: WT_15M_BOUNCE_REL_VOL_GT_1= -> delta vs cum

Sheet INSTRUCTIONS_V2
A1: TEMPLATE_V2_IDEA_GROUPED 231 per-row FULLY CONNECTED 2026-09-08 - every numpy identical to live
A2: Retraced from early today 231 L:IH (TEMPLATE.xlsx 1.7M) - Sep 5 114 per-row was synthetic/disconnected. This file keeps 231 per-row L:IH (every filter TF OFF/D/4h/1h/15m wired).
A3: 01. ENTRY_REVERSAL_BOUNCE - 8 bases -> 21 rows - 231 per-row
A4: 02. ENTRY_BREAKOUT_CHANNEL - 54 bases -> 210 rows - 231 per-row
A5: 03. ENTRY_CONFIRMATION_GATES - 4 bases -> 11 rows - 231 per-row
A6: 04. EXIT_STRUCTURAL - 2 bases -> 6 rows - 231 per-row
A7: 05. EXIT_VELOCITY - 26 bases -> 80 rows - 231 per-row
A8: 06. REENTRY_WINDOWED - 68 bases -> 249 rows - 231 per-row
A9: 07. REENTRY_ADAPTIVE - 10 bases -> 38 rows - 231 per-row
A10: 08. AUGMENT_TREND - 5 bases -> 24 rows - 231 per-row
A11: 09. AUGMENT_RISK_SIZING - 17 bases -> 56 rows - 231 per-row
A12: 10. REDUCE_PROFIT_LOCK - 19 bases -> 53 rows - 231 per-row
... A15: 2026-09-11 UPDATE: See INSTRUCTIONS tab rows 9,12,14 for >100 sym_sides threshold, blanket at end of each tab, and green/blue/darker proven colors. v14 implements get_opportune_filters + 84 combos + blanket GENERAL. ALL filters until 100, then useful per universe.

Sheet ENTRY_REVERSAL_BOUNCE
A1: 01 ENTRY_REVERSAL_BOUNCE - 8 bases -> 21 rows - 231 per-row FULLY CONNECTED
A2: Switch | B2: default | C2: override | D2: Family | E2: BASELINE | F2: VECTOR_DELTA | G2: LIVE_DELTA | H2: LIVE_SHARPE | I2: REAL_COMPLETE | J2: PER_ROW_FILTERS | K2: is_default (backup if bold lost) | L2: ATR_TRAIL_FILTER_TF=OFF | M2: ATR_TRAIL_FILTER_TF=D | N2: ATR_TRAIL_FILTER_TF=4h | O2: ATR_TRAIL_FILTER_TF=1h | P2: ATR_TRAIL_FILTER_TF=15m | Q2: BAR_PATTERNS_FILTER_TF=OFF | R2: BAR_PATTERNS_FILTER_TF=D | S2: BAR_PATTERNS_FILTER_TF=4h | T2: BAR_PATTERNS_FILTER_TF=1h | U2: BAR_PATTERNS_FILTER_TF=15m | V2: BB_PULLBACK_GATE_FILTER_TF=OFF | W2: BB_PULLBACK_GATE_FILTER_TF=D | X2: BB_PULLBACK_GATE_FILTER_TF=4h | Y2: BB_PULLBACK_GATE_FILTER_TF=1h | Z2: BB_PULLBACK_GATE_FILTER_TF=15m | AA2: BB_RECOVERY_ENTRY_FILTER_TF=OFF | AB2: BB_RECOVERY_ENTRY_FILTER_TF=D | AC2: BB_RECOVERY_ENTRY_FILTER_TF=4h | AD2: BB_RECOVERY_ENTRY_FILTER_TF=1h | AE2: BB_RECOVERY_ENTRY_FILTER_TF=15m | AF2: BB_RECOVERY_FILTER_TF=OFF | AG2: BB_RECOVERY_FILTER_TF=D | AH2: BB_RECOVERY_FILTER_TF=4h | AI2: BB_RECOVERY_FILTER_TF=1h | AJ2: BB_RECOVERY_FILTER_TF=15m | AK2: BREAKEVEN_GAIN_EROSION_FILTER_TF=OFF | AL2: BREAKEVEN_GAIN_EROSION_FILTER_TF=D | AM2: BREAKEVEN_GAIN_EROSION_FILTER_TF=4h | AN2: BREAKEVEN_GAIN_EROSION_FILTER_TF=1h | AO2: BREAKEVEN_GAIN_EROSION_FILTER_TF=15m | AP2: BREAKOUT_RETEST_FILTER_TF=OFF | AQ2: BREAKOUT_RETEST_FILTER_TF=D | AR2: BREAKOUT_RETEST_FILTER_TF=4h | AS2: BREAKOUT_RETEST_FILTER_TF=1h | AT2: BREAKOUT_RETEST_FILTER_TF=15m | AU2: BT_WT_CROSS_LADDER_FILTER_TF=OFF | AV2: BT_WT_CROSS_LADDER_FILTER_TF=D | AW2: BT_WT_CROSS_LADDER_FILTER_TF=4h | AX2: BT_WT_CROSS_LADDER_FILTER_TF=1h | AY2: BT_WT_CROSS_LADDER_FILTER_TF=15m | AZ2: CANDLE_PATTERN_STOPS_FILTER_TF=OFF | BA2: CANDLE_PATTERN_STOPS_FILTER_TF=D | BB2: CANDLE_PATTERN_STOPS_FILTER_TF=4h | BC2: CANDLE_PATTERN_STOPS_FILTER_TF=1h | BD2: CANDLE_PATTERN_STOPS_FILTER_TF=15m | BE2: CIRCUIT_SHARPE_GATES_FILTER_TF=OFF | BF2: CIRCUIT_SHARPE_GATES_FILTER_TF=D | BG2: CIRCUIT_SHARPE_GATES_FILTER_TF=4h | BH2: CIRCUIT_SHARPE_GATES_FILTER_TF=1h | BI2: CIRCUIT_SHARPE_GATES_FILTER_TF=15m | BJ2: DC_BREACH_REDUCE_FILTER_TF=OFF | BK2: DC_BREACH_REDUCE_FILTER_TF=D | BL2: DC_BREACH_REDUCE_FILTER_TF=4h | BM2: DC_BREACH_REDUCE_FILTER_TF=1h | BN2: DC_BREACH_REDUCE_FILTER_TF=15m | BO2: DC_BREAK_FILTER_TF=OFF | BP2: DC_BREAK_FILTER_TF=D | BQ2: DC_BREAK_FILTER_TF=4h | BR2: DC_BREAK_FILTER_TF=1h | BS2: DC_BREAK_FILTER_TF=15m | BT2: DC_MOMENTUM_BOTA_SCORER_FILTER_TF=OFF | BU2: DC_MOMENTUM_BOTA_SCORER_FILTER_TF=D | BV2: DC_MOMENTUM_BOTA_SCORER_FILTER_TF=4h | BW2: DC_MOMENTUM_BOTA_SCORER_FILTER_TF=1h | BX2: DC_MOMENTUM_BOTA_SCORER_FILTER_TF=15m | BY2: DELTA_ENGINE_FILTER_TF=OFF | BZ2: DELTA_ENGINE_FILTER_TF=D | CA2: DELTA_ENGINE_FILTER_TF=4h | CB2: DELTA_ENGINE_FILTER_TF=1h | CC2: DELTA_ENGINE_FILTER_TF=15m | CD2: EMA_9_21_FILTER_FILTER_TF=OFF | CE2: EMA_9_21_FILTER_FILTER_TF=D | CF2: EMA_9_21_FILTER_FILTER_TF=4h | CG2: EMA_9_21_FILTER_FILTER_TF=1h | CH2: EMA_9_21_FILTER_FILTER_TF=15m | CI2: EMA_BLANKET_FILTER_FILTER_TF=OFF | CJ2: EMA_BLANKET_FILTER_FILTER_TF=D | CK2: EMA_BLANKET_FILTER_FILTER_TF=4h | CL2: EMA_BLANKET_FILTER_FILTER_TF=1h | CM2: EMA_BLANKET_FILTER_FILTER_TF=15m | CN2: EMERGENCY_BRAKE_FILTER_TF=OFF | CO2: EMERGENCY_BRAKE_FILTER_TF=D | CP2: EMERGENCY_BRAKE_FILTER_TF=4h | CQ2: EMERGENCY_BRAKE_FILTER_TF=1h | CR2: EMERGENCY_BRAKE_FILTER_TF=15m | CS2: EXIT_R1_R2_FILTER_TF=OFF | CT2: EXIT_R1_R2_FILTER_TF=D | CU2: EXIT_R1_R2_FILTER_TF=4h | CV2: EXIT_R1_R2_FILTER_TF=1h | CW2: EXIT_R1_R2_FILTER_TF=15m | CX2: EXIT_TIGHT_BREAKOUT_SCORER_FILTER_TF=OFF | CY2: EXIT_TIGHT_BREAKOUT_SCORER_FILTER_TF=D | CZ2: EXIT_TIGHT_BREAKOUT_SCORER_FILTER_TF=4h | DA2: EXIT_TIGHT_BREAKOUT_SCORER_FILTER_TF=1h | DB2: EXIT_TIGHT_BREAKOUT_SCORER_FILTER_TF=15m | DC2: EXIT_TOP_FADE_FILTER_TF=OFF | DD2: EXIT_TOP_FADE_FILTER_TF=D | DE2: EXIT_TOP_FADE_FILTER_TF=4h | DF2: EXIT_TOP_FADE_FILTER_TF=1h | DG2: EXIT_TOP_FADE_FILTER_TF=15m | DH2: EXIT_TO_REDUCE_ADAPTER_FILTER_TF=OFF | DI2: EXIT_TO_REDUCE_ADAPTER_FILTER_TF=D | DJ2: EXIT_TO_REDUCE_ADAPTER_FILTER_TF=4h | DK2: EXIT_TO_REDUCE_ADAPTER_FILTER_TF=1h | DL2: EXIT_TO_REDUCE_ADAPTER_FILTER_TF=15m | DM2: FAST_RISER_FILTER_TF=OFF | DN2: FAST_RISER_FILTER_TF=D | DO2: FAST_RISER_FILTER_TF=4h | DP2: FAST_RISER_FILTER_TF=1h | DQ2: FAST_RISER_FILTER_TF=15m | DR2: FH_MOMENTUM_FILTER_TF=OFF | DS2: FH_MOMENTUM_FILTER_TF=D | DT2: FH_MOMENTUM_FILTER_TF=4h | DU2: FH_MOMENTUM_FILTER_TF=1h | DV2: FH_MOMENTUM_FILTER_TF=15m | DW2: FIRST_OPEN_THROTTLE_FILTER_TF=OFF | DX2: FIRST_OPEN_THROTTLE_FILTER_TF=D | DY2: FIRST_OPEN_THROTTLE_FILTER_TF=4h | DZ2: FIRST_OPEN_THROTTLE_FILTER_TF=1h | EA2: FIRST_OPEN_THROTTLE_FILTER_TF=15m | EB2: FROZEN_STOP_FILTER_TF=OFF | EC2: FROZEN_STOP_FILTER_TF=D | ED2: FROZEN_STOP_FILTER_TF=4h | EE2: FROZEN_STOP_FILTER_TF=1h | EF2: FROZEN_STOP_FILTER_TF=15m | EG2: GOLDEN_RULE_ENFORCE_FILTER_TF=OFF | EH2: GOLDEN_RULE_ENFORCE_FILTER_TF=D | EI2: GOLDEN_RULE_ENFORCE_FILTER_TF=4h | EJ2: GOLDEN_RULE_ENFORCE_FILTER_TF=1h | EK2: GOLDEN_RULE_ENFORCE_FILTER_TF=15m | EL2: GOLDEN_RULE_HTF_VOTE_FILTER_TF=OFF | EM2: GOLDEN_RULE_HTF_VOTE_FILTER_TF=D | EN2: GOLDEN_RULE_HTF_VOTE_FILTER_TF=4h | EO2: GOLDEN_RULE_HTF_VOTE_FILTER_TF=1h | EP2: GOLDEN_RULE_HTF_VOTE_FILTER_TF=15m | EQ2: GR_FILTER_VEC_FILTER_TF=OFF | ER2: GR_FILTER_VEC_FILTER_TF=D | ES2: GR_FILTER_VEC_FILTER_TF=4h | ET2: GR_FILTER_VEC_FILTER_TF=1h | EU2: GR_FILTER_VEC_FILTER_TF=15m | EV2: GR_V5_STATE_FILTER_TF=OFF | EW2: GR_V5_STATE_FILTER_TF=D | EX2: GR_V5_STATE_FILTER_TF=4h | EY2: GR_V5_STATE_FILTER_TF=1h | EZ2: GR_V5_STATE_FILTER_TF=15m | FA2: HAIKU_WINNER_FILTER_TF=OFF | FB2: HAIKU_WINNER_FILTER_TF=D | FC2: HAIKU_WINNER_FILTER_TF=4h | FD2: HAIKU_WINNER_FILTER_TF=1h | FE2: HAIKU_WINNER_FILTER_TF=15m | FF2: LH_HL_FILTER_TF_REQ=2 | FG2: LH_HL_FILTER_TF_REQ=2_ALT | FH2: LIVE_ENTRY_ENGINE_FILTER_TF=OFF | FI2: LIVE_ENTRY_ENGINE_FILTER_TF=D | FJ2: LIVE_ENTRY_ENGINE_FILTER_TF=4h | FK2: LIVE_ENTRY_ENGINE_FILTER_TF=1h | FL2: LIVE_ENTRY_ENGINE_FILTER_TF=15m | FM2: LIVE_ONLY_SIGNALS_BATCH5_FILTER_TF=OFF | FN2: LIVE_ONLY_SIGNALS_BATCH5_FILTER_TF=D | FO2: LIVE_ONLY_SIGNALS_BATCH5_FILTER_TF=4h | FP2: LIVE_ONLY_SIGNALS_BATCH5_FILTER_TF=1h | FQ2: LIVE_ONLY_SIGNALS_BATCH5_FILTER_TF=15m | FR2: MANDATORY_REENTRY_WT_FILTER_TF_MODE=15m_only | FS2: MANDATORY_REENTRY_WT_FILTER_TF_MODE=15m_only_ALT | FT2: MOM3_FILTER_TF=OFF | FU2: MOM3_FILTER_TF=D | FV2: MOM3_FILTER_TF=4h | FW2: MOM3_FILTER_TF=1h | FX2: MOM3_FILTER_TF=15m | FY2: MOMENTUM_BREAKOUT_FILTER_TF=OFF | FZ2: MOMENTUM_BREAKOUT_FILTER_TF=D | GA2: MOMENTUM_BREAKOUT_FILTER_TF=4h | GB2: MOMENTUM_BREAKOUT_FILTER_TF=1h | GC2: MOMENTUM_BREAKOUT_FILTER_TF=15m | GD2: MTF_ARMED_ENTRIES_FILTER_TF=OFF | GE2: MTF_ARMED_ENTRIES_FILTER_TF=D | GF2: MTF_ARMED_ENTRIES_FILTER_TF=4h | GG2: MTF_ARMED_ENTRIES_FILTER_TF=1h | GH2: MTF_ARMED_ENTRIES_FILTER_TF=15m | GI2: MTF_ATR_TRAIL_FILTER_TF=OFF | GJ2: MTF_ATR_TRAIL_FILTER_TF=D | GK2: MTF_ATR_TRAIL_FILTER_TF=4h | GL2: MTF_ATR_TRAIL_FILTER_TF=1h | GM2: MTF_ATR_TRAIL_FILTER_TF=15m | GN2: MTF_DC_REJECT_FILTER_TF=OFF | GO2: MTF_DC_REJECT_FILTER_TF=D | GP2: MTF_DC_REJECT_FILTER_TF=4h | GQ2: MTF_DC_REJECT_FILTER_TF=1h | GR2: MTF_DC_REJECT_FILTER_TF=15m | GS2: NEWBORN_LOSS_KILL_FILTER_TF=OFF | GT2: NEWBORN_LOSS_KILL_FILTER_TF=D | GU2: NEWBORN_LOSS_KILL_FILTER_TF=4h | GV2: NEWBORN_LOSS_KILL_FILTER_TF=1h | GW2: NEWBORN_LOSS_KILL_FILTER_TF=15m | GX2: NEWBORN_PROTECT_FILTER_TF=OFF | GY2: NEWBORN_PROTECT_FILTER_TF=D | GZ2: NEWBORN_PROTECT_FILTER_TF=4h | HA2: NEWBORN_PROTECT_FILTER_TF=1h | HB2: NEWBORN_PROTECT_FILTER_TF=15m | HC2: NOLOSS_BYPASS_WT5OF5_FILTER_TF=OFF | HD2: NOLOSS_BYPASS_WT5OF5_FILTER_TF=D | HE2: NOLOSS_BYPASS_WT5OF5_FILTER_TF=4h | HF2: NOLOSS_BYPASS_WT5OF5_FILTER_TF=1h | HG2: NOLOSS_BYPASS_WT5OF5_FILTER_TF=15m | HH2: OPEN_INTENT_SIZE_GATES_FILTER_TF=OFF | HI2: OPEN_INTENT_SIZE_GATES_FILTER_TF=D | HJ2: OPEN_INTENT_SIZE_GATES_FILTER_TF=4h | HK2: OPEN_INTENT_SIZE_GATES_FILTER_TF=1h | HL2: OPEN_INTENT_SIZE_GATES_FILTER_TF=15m | HM2: PARTIAL_PROFIT_LOCK_V2_FILTER_TF=OFF | HN2: PARTIAL_PROFIT_LOCK_V2_FILTER_TF=D | HO2: PARTIAL_PROFIT_LOCK_V2_FILTER_TF=4h | HP2: PARTIAL_PROFIT_LOCK_V2_FILTER_TF=1h | HQ2: PARTIAL_PROFIT_LOCK_V2_FILTER_TF=15m | HR2: PEAK_GIVEBACK_BE_EROSION_FILTER_TF=OFF | HS2: PEAK_GIVEBACK_BE_EROSION_FILTER_TF=D | HT2: PEAK_GIVEBACK_BE_EROSION_FILTER_TF=4h | HU2: PEAK_GIVEBACK_BE_EROSION_FILTER_TF=1h | HV2: PEAK_GIVEBACK_BE_EROSION_FILTER_TF=15m | HW2: WT_15M_BOUNCE_BB_MAX=0.95 | HX2: WT_15M_BOUNCE_BB_MAX=0.9 | HY2: WT_15M_BOUNCE_BB_MAX=0.8 | HZ2: WT_15M_BOUNCE_BB_MIN=0.05 | IA2: WT_15M_BOUNCE_BB_MIN=0.1 | IB2: WT_15M_BOUNCE_BB_MIN=0.2 | IC2: WT_15M_BOUNCE_HIGH_1H_GT_PREV=True | ID2: WT_15M_BOUNCE_HIGH_1H_GT_PREV=False | IE2: WT_15M_BOUNCE_LOW_1H_GT_PREV=True | IF2: WT_15M_BOUNCE_LOW_1H_GT_PREV=False | IG2: WT_15M_BOUNCE_REL_VOL_GT_1=True | IH2: WT_15M_BOUNCE_REL_VOL_GT_1=False | II2: Live Location | IJ2: Vec Hook | IK2: Type | IL2: Correct Options
A3: WT_15M_BOUNCE_OPEN_ENABLED | B3: False | C3: WT_15M_BOUNCE_OPEN_ENABLED=False + WT_15M_BOUNCE_BB_MAX=0.8 + BB_WT_TF=15m + GR=18 + BB_RECOVERY_FILTER_TF=OFF + DC_BREAK_FILTER_TF=1h | E3: 19.6481 | F3: 35.5836 | G3: =IFERROR(VLOOKUP($A3,Results_30d_Deltas!$A$2:$H$5000,7,FALSE)-E3,"") | H3: =IFERROR(VLOOKUP($A3,Results_30d_Deltas!$A$2:$H$5000,6,FALSE),"") | K3: =IF(B3=C3,"YES","NO") | IJ3: ez_manage.py:6076 top() | IK3: v12_quick_engine.py:4288 x7
A4: WT_15M_BOUNCE_OPEN_ENABLED | B4: True | E4: -13.3501 | F4: 2.5853 | G4: =IFERROR(VLOOKUP($A4,Results_30d_Deltas!$A$2:$H$5000,7,FALSE)-E3,"") | H4: =IFERROR(VLOOKUP($A4,Results_30d_Deltas!$A$2:$H$5000,6,FALSE),"") | K4: =IF(B4=C4,"YES","NO") | IJ4: ez_manage.py:6076 top() | IK4: v12_quick_engine.py:4288 x7
A5: BB_SQUEEZE_ENTRY_ENABLED | B5: True | E5: -13.3501 | F5: 2.5853 | G5: =IFERROR(VLOOKUP($A5,Results_30d_Deltas!$A$2:$H$5000,7,FALSE)-E4,"") | H5: =IFERROR(VLOOKUP($A5,Results_30d_Deltas!$A$2:$H$5000,6,FALSE),"") | K5: =IF(B5=C5,"YES","NO") | IJ5: ez_manage.py:4371 top() | IK5: v12_quick_engine.py:889 x9
A6: BB_PULLBACK_GATE_TF | B6: OFF | E6: -12.1759 | F6: 3.7596 | G6: =IFERROR(VLOOKUP($A6,Results_30d_Deltas!$A$2:$H$5000,7,FALSE)-E5,"") | H6: =IFERROR(VLOOKUP($A6,Results_30d_Deltas!$A$2:$H$5000,6,FALSE),"") | K6: =IF(B6=C6,"YES","NO") | V6: 2.1874 | W6: 3.7596 | X6: 0.8638 | IJ6: ez_manage.py:4361 top() | IK6: v12_quick_engine.py:288 x12
A7: BB_PULLBACK_GATE_TF | B7: D | E7: -12.1759 | F7: 3.7596 | G7: =IFERROR(VLOOKUP($A7,Results_30d_Deltas!$A$2:$H$5000,7,FALSE)-E6,"") | H7: =IFERROR(VLOOKUP($A7,Results_30d_Deltas!$A$2:$H$5000,6,FALSE),"") | K7: =IF(B7=C7,"YES","NO") | V7: 2.1874 | W7: 3.7596 | X7: 0.8638 | IJ7: ez_manage.py:4361 top() | IK7: v12_quick_engine.py:288 x12
A8: BB_PULLBACK_GATE_TF | B8: 4h | E8: -12.1759 | F8: 3.7596 | G8: =IFERROR(VLOOKUP($A8,Results_30d_Deltas!$A$2:$H$5000,7,FALSE)-E7,"") | H8: =IFERROR(VLOOKUP($A8,Results_30d_Deltas!$A$2:$H$5000,6,FALSE),"") | K8: =IF(B8=C8,"YES","NO") | V8: 2.1874 | W8: 3.7596 | X8: 0.8638 | IJ8: ez_manage.py:4361 top() | IK8: v12_quick_engine.py:288 x12
A9: BB_PULLBACK_GATE_TF | B9: 1h | E9: -12.1759 | F9: 3.7596 | G9: =IFERROR(VLOOKUP($A9,Results_30d_Deltas!$A$2:$H$5000,7,FALSE)-E8,"") | H9: =IFERROR(VLOOKUP($A9,Results_30d_Deltas!$A$2:$H$5000,6,FALSE),"") | K9: =IF(B9=C9,"YES","NO") | V9: 2.1874 | W9: 3.7596 | X9: 0.8638 | IJ9: ez_manage.py:4361 top() | IK9: v12_quick_engine.py:288 x12
A10: BB_PULLBACK_GATE_TF | B10: 15m | E10: -12.1759 | F10: 3.7596 | G10: =IFERROR(VLOOKUP($A10,Results_30d_Deltas!$A$2:$H$5000,7,FALSE)-E9,"") | H10: =IFERROR(VLOOKUP($A10,Results_30d_Deltas!$A$2:$H$5000,6,FALSE),"") | K10: =IF(B10=C10,"YES","NO") | V10: 2.1874 | W10: 3.7596 | X10: 0.8638 | IJ10: ez_manage.py:4361 top() | IK10: v12_quick_engine.py:288 x12
A11: DELTA_GATE_BB_SQUEEZE | B11: True | E11: -12.1759 | F11: 3.7596 | G11: =IFERROR(VLOOKUP($A11,Results_30d_Deltas!$A$2:$H$5000,7,FALSE)-E10,"") | H11: =IFERROR(VLOOKUP($A11,Results_30d_Deltas!$A$2:$H$5000,6,FALSE),"") | K11: =IF(B11=C11,"YES","NO") | IJ11: ez_manage.py:4603 top() | IK11: v12_quick_engine.py:969 x9
A12: BB_SQUEEZE_WIDTH_PERCENTILE | B12: 0.1 | E12: -13.3501 | F12: 2.5853 | G12: =IFERROR(VLOOKUP($A12,Results_30d_Deltas!$A$2:$H$5000,7,FALSE)-E11,"") | H12: =IFERROR(VLOOKUP($A12,Results_30d_Deltas!$A$2:$H$5000,6,FALSE),"") | K12: =IF(B12=C12,"YES","NO") | IJ12: ez_manage.py:4375 top() | IK12: v12_quick_engine.py:1285 x7
A13: BB_SQUEEZE_WIDTH_PERCENTILE | B13: 0.15 | E13: -13.3501 | F13: 2.5853 | G13: =IFERROR(VLOOKUP($A13,Results_30d_Deltas!$A$2:$H$5000,7,FALSE)-E12,"") | H13: =IFERROR(VLOOKUP($A13,Results_30d_Deltas!$A$2:$H$5000,6,FALSE),"") | K13: =IF(B13=C13,"YES","NO") | IJ13: ez_manage.py:4375 top() | IK13: v12_quick_engine.py:1285 x7
A14: BB_SQUEEZE_WIDTH_PERCENTILE | B14: 0.2 | E14: -13.3501 | F14: 2.5853 | G14: =IFERROR(VLOOKUP($A14,Results_30d_Deltas!$A$2:$H$5000,7,FALSE)-E13,"") | H14: =IFERROR(VLOOKUP($A14,Results_30d_Deltas!$A$2:$H$5000,6,FALSE),"") | K14: =IF(B14=C14,"YES","NO") | IJ14: ez_manage.py:4375 top() | IK14: v12_quick_engine.py:1285 x7
A15: BB_SQUEEZE_WIDTH_PERCENTILE | B15: 0.25 | E15: -13.3501 | F15: 2.5853 | G15: =IFERROR(VLOOKUP($A15,Results_30d_Deltas!$A$2:$H$5000,7,FALSE)-E14,"") | H15: =IFERROR(VLOOKUP($A15,Results_30d_Deltas!$A$2:$H$5000,6,FALSE),"") | K15: =IF(B15=C15,"YES","NO") | IJ15: ez_manage.py:4375 top() | IK15: v12_quick_engine.py:1285 x7
A16: BB_SQUEEZE_WIDTH_PERCENTILE | B16: 0.3 | E16: -13.3501 | F16: 2.5853 | G16: =IFERROR(VLOOKUP($A16,Results_30d_Deltas!$A$2:$H$5000,7,FALSE)-E15,"") | H16: =IFERROR(VLOOKUP($A16,Results_30d_Deltas!$A$2:$H$5000,6,FALSE),"") | K16: =IF(B16=C16,"YES","NO") | IJ16: ez_manage.py:4375 top() | IK16: v12_quick_engine.py:1285 x7
A17: WT_DIV_EXIT_ENABLED | B17: False | E17: -13.3501 | F17: 2.5853 | G17: =IFERROR(VLOOKUP($A17,Results_30d_Deltas!$A$2:$H$5000,7,FALSE)-E16,"") | H17: =IFERROR(VLOOKUP($A17,Results_30d_Deltas!$A$2:$H$5000,6,FALSE),"") | K17: =IF(B17=C17,"YES","NO") | IJ17: ez_manage.py:6086 top() | IK17: v12_quick_engine.py:4292 x3
A18: WT_DIV_EXIT_ENABLED | B18: True | E18: -12.1759 | F18: 3.7596 | G18: =IFERROR(VLOOKUP($A18,Results_30d_Deltas!$A$2:$H$5000,7,FALSE)-E17,"") | H18: =IFERROR(VLOOKUP($A18,Results_30d_Deltas!$A$2:$H$5000,6,FALSE),"") | K18: =IF(B18=C18,"YES","NO") | IJ18: ez_manage.py:6086 top() | IK18: v12_quick_engine.py:4292 x3
A19: WT_MOMENTUM_EXIT_THRESHOLD | B19: 0 | E19: -13.3501 | F19: 2.5853 | G19: =IFERROR(VLOOKUP($A19,Results_30d_Deltas!$A$2:$H$5000,7,FALSE)-E18,"") | H19: =IFERROR(VLOOKUP($A19,Results_30d_Deltas!$A$2:$H$5000,6,FALSE),"") | K19: =IF(B19=C19,"YES","NO") | IJ19: ez_manage.py:6087 top() | IK19: v12_quick_engine.py:4293 x3
A20: WT_MOMENTUM_EXIT_THRESHOLD | B20: 1 | E20: -13.3501 | F20: 2.5853 | G20: =IFERROR(VLOOKUP($A20,Results_30d_Deltas!$A$2:$H$5000,7,FALSE)-E19,"") | H20: =IFERROR(VLOOKUP($A20,Results_30d_Deltas!$A$2:$H$5000,6,FALSE),"") | K20: =IF(B20=C20,"YES","NO") | IJ20: ez_manage.py:6087 top() | IK20: v12_quick_engine.py:4293 x3
A21: WT_MOMENTUM_EXIT_THRESHOLD | B21: 2 | E21: -13.3501 | F21: 2.5853 | G21: =IFERROR(VLOOKUP($A21,Results_30d_Deltas!$A$2:$H$5000,7,FALSE)-E20,"") | H21: =IFERROR(VLOOKUP($A21,Results_30d_Deltas!$A$2:$H$5000,6,FALSE),"") | K21: =IF(B21=C21,"YES","NO") | IJ21: ez_manage.py:6087 top() | IK21: v12_quick_engine.py:4293 x3
A22: WT_ACCEL_EXIT_ENABLED | B22: False | E22: -13.3501 | F22: 2.5853 | G22: =IFERROR(VLOOKUP($A22,Results_30d_Deltas!$A$2:$H$5000,7,FALSE)-E21,"") | H22: =IFERROR(VLOOKUP($A22,Results_30d_Deltas!$A$2:$H$5000,6,FALSE),"") | K22: =IF(B22=C22,"YES","NO") | IJ22: ez_manage.py:6083 top() | IK22: v12_quick_engine.py:4290 x3
A23: WT_ACCEL_EXIT_ENABLED | B23: True | E23: -13.748 | F23: 2.1874 | G23: =IFERROR(VLOOKUP($A23,Results_30d_Deltas!$A$2:$H$5000,7,FALSE)-E22,"") | H23: =IFERROR(VLOOKUP($A23,Results_30d_Deltas!$A$2:$H$5000,6,FALSE),"") | K23: =IF(B23=C23,"YES","NO") | IJ23: ez_manage.py:6083 top() | IK23: v12_quick_engine.py:4290 x3

Sheet ENTRY_BREAKOUT_CHANNEL
A1: 02 ENTRY_BREAKOUT_CHANNEL - 54 bases -> 210 rows - 231 per-row FULLY CONNECTED
A2: Switch | B2: default | C2: override | D2: Family | E2: BASELINE | F2: VECTOR_DELTA | G2: LIVE_DELTA | H2: LIVE_SHARPE | I2: REAL_COMPLETE | J2: PER_ROW_FILTERS | K2: is_default (backup if bold lost) | L2: ATR_TRAIL_FILTER_TF=OFF | M2: ATR_TRAIL_FILTER_TF=D | N2: ATR_TRAIL_FILTER_TF=4h | O2: ATR_TRAIL_FILTER_TF=1h | P2: ATR_TRAIL_FILTER_TF=15m | Q2: BAR_PATTERNS_FILTER_TF=OFF | R2: BAR_PATTERNS_FILTER_TF=D | S2: BAR_PATTERNS_FILTER_TF=4h | T2: BAR_PATTERNS_FILTER_TF=1h | U2: BAR_PATTERNS_FILTER_TF=15m | V2: BB_PULLBACK_GATE_FILTER_TF=OFF | W2: BB_PULLBACK_GATE_FILTER_TF=D | X2: BB_PULLBACK_GATE_FILTER_TF=4h | Y2: BB_PULLBACK_GATE_FILTER_TF=1h | Z2: BB_PULLBACK_GATE_FILTER_TF=15m | AA2: BB_RECOVERY_ENTRY_FILTER_TF=OFF | AB2: BB_RECOVERY_ENTRY_FILTER_TF=D | AC2: BB_RECOVERY_ENTRY_FILTER_TF=4h | AD2: BB_RECOVERY_ENTRY_FILTER_TF=1h | AE2: BB_RECOVERY_ENTRY_FILTER_TF=15m | AF2: BB_RECOVERY_FILTER_TF=OFF | AG2: BB_RECOVERY_FILTER_TF=D | AH2: BB_RECOVERY_FILTER_TF=4h | AI2: BB_RECOVERY_FILTER_TF=1h | AJ2: BB_RECOVERY_FILTER_TF=15m | AK2: BREAKEVEN_GAIN_EROSION_FILTER_TF=OFF | AL2: BREAKEVEN_GAIN_EROSION_FILTER_TF=D | AM2: BREAKEVEN_GAIN_EROSION_FILTER_TF=4h | AN2: BREAKEVEN_GAIN_EROSION_FILTER_TF=1h | AO2: BREAKEVEN_GAIN_EROSION_FILTER_TF=15m | AP2: BREAKOUT_RETEST_FILTER_TF=OFF | AQ2: BREAKOUT_RETEST_FILTER_TF=D | AR2: BREAKOUT_RETEST_FILTER_TF=4h | AS2: BREAKOUT_RETEST_FILTER_TF=1h | AT2: BREAKOUT_RETEST_FILTER_TF=15m | AU2: BT_WT_CROSS_LADDER_FILTER_TF=OFF | AV2: BT_WT_CROSS_LADDER_FILTER_TF=D | AW2: BT_WT_CROSS_LADDER_FILTER_TF=4h | AX2: BT_WT_CROSS_LADDER_FILTER_TF=1h | AY2: BT_WT_CROSS_LADDER_FILTER_TF=15m | AZ2: CANDLE_PATTERN_STOPS_FILTER_TF=OFF | BA2: CANDLE_PATTERN_STOPS_FILTER_TF=D | BB2: CANDLE_PATTERN_STOPS_FILTER_TF=4h | BC2: CANDLE_PATTERN_STOPS_FILTER_TF=1h | BD2: CANDLE_PATTERN_STOPS_FILTER_TF=15m | BE2: CIRCUIT_SHARPE_GATES_FILTER_TF=OFF | BF2: CIRCUIT_SHARPE_GATES_FILTER_TF=D | BG2: CIRCUIT_SHARPE_GATES_FILTER_TF=4h | BH2: CIRCUIT_SHARPE_GATES_FILTER_TF=1h | BI2: CIRCUIT_SHARPE_GATES_FILTER_TF=15m | BJ2: DC_BREACH_REDUCE_FILTER_TF=OFF | BK2: DC_BREACH_REDUCE_FILTER_TF=D | BL2: DC_BREACH_REDUCE_FILTER_TF=4h | BM2: DC_BREACH_REDUCE_FILTER_TF=1h | BN2: DC_BREACH_REDUCE_FILTER_TF=15m | BO2: DC_BREAK_FILTER_TF=OFF | BP2: DC_BREAK_FILTER_TF=D | BQ2: DC_BREAK_FILTER_TF=4h | BR2: DC_BREAK_FILTER_TF=1h | BS2: DC_BREAK_FILTER_TF=15m | BT2: DC_MOMENTUM_BOTA_SCORER_FILTER_TF=OFF | BU2: DC_MOMENTUM_BOTA_SCORER_FILTER_TF=D | BV2: DC_MOMENTUM_BOTA_SCORER_FILTER_TF=4h | BW2: DC_MOMENTUM_BOTA_SCORER_FILTER_TF=1h | BX2: DC_MOMENTUM_BOTA_SCORER_FILTER_TF=15m | BY2: DELTA_ENGINE_FILTER_TF=OFF | BZ2: DELTA_ENGINE_FILTER_TF=D | CA2: DELTA_ENGINE_FILTER_TF=4h | CB2: DELTA_ENGINE_FILTER_TF=1h | CC2: DELTA_ENGINE_FILTER_TF=15m | CD2: EMA_9_21_FILTER_FILTER_TF=OFF | CE2: EMA_9_21_FILTER_FILTER_TF=D | CF2: EMA_9_21_FILTER_FILTER_TF=4h | CG2: EMA_9_21_FILTER_FILTER_TF=1h | CH2: EMA_9_21_FILTER_FILTER_TF=15m | CI2: EMA_BLANKET_FILTER_FILTER_TF=OFF | CJ2: EMA_BLANKET_FILTER_FILTER_TF=D | CK2: EMA_BLANKET_FILTER_FILTER_TF=4h | CL2: EMA_BLANKET_FILTER_FILTER_TF=1h | CM2: EMA_BLANKET_FILTER_FILTER_TF=15m | CN2: EMERGENCY_BRAKE_FILTER_TF=OFF | CO2: EMERGENCY_BRAKE_FILTER_TF=D | CP2: EMERGENCY_BRAKE_FILTER_TF=4h | CQ2: EMERGENCY_BRAKE_FILTER_TF=1h | CR2: EMERGENCY_BRAKE_FILTER_TF=15m | CS2: EXIT_R1_R2_FILTER_TF=OFF | CT2: EXIT_R1_R2_FILTER_TF=D | CU2: EXIT_R1_R2_FILTER_TF=4h | CV2: EXIT_R1_R2_FILTER_TF=1h | CW2: EXIT_R1_R2_FILTER_TF=15m | CX2: EXIT_TIGHT_BREAKOUT_SCORER_FILTER_TF=OFF | CY2: EXIT_TIGHT_BREAKOUT_SCORER_FILTER_TF=D | CZ2: EXIT_TIGHT_BREAKOUT_SCORER_FILTER_TF=4h | DA2: EXIT_TIGHT_BREAKOUT_SCORER_FILTER_TF=1h | DB2: EXIT_TIGHT_BREAKOUT_SCORER_FILTER_TF=15m | DC2: EXIT_TOP_FADE_FILTER_TF=OFF | DD2: EXIT_TOP_FADE_FILTER_TF=D | DE2: EXIT_TOP_FADE_FILTER_TF=4h | DF2: EXIT_TOP_FADE_FILTER_TF=1h | DG2: EXIT_TOP_FADE_FILTER_TF=15m | DH2: EXIT_TO_REDUCE_ADAPTER_FILTER_TF=OFF | DI2: EXIT_TO_REDUCE_ADAPTER_FILTER_TF=D | DJ2: EXIT_TO_REDUCE_ADAPTER_FILTER_TF=4h | DK2: EXIT_TO_REDUCE_ADAPTER_FILTER_TF=1h | DL2: EXIT_TO_REDUCE_ADAPTER_FILTER_TF=15m | DM2: FAST_RISER_FILTER_TF=OFF | DN2: FAST_RISER_FILTER_TF=D | DO2: FAST_RISER_FILTER_TF=4h | DP2: FAST_RISER_FILTER_TF=1h | DQ2: FAST_RISER_FILTER_TF=15m | DR2: FH_MOMENTUM_FILTER_TF=OFF | DS2: FH_MOMENTUM_FILTER_TF=D | DT2: FH_MOMENTUM_FILTER_TF=4h | DU2: FH_MOMENTUM_FILTER_TF=1h | DV2: FH_MOMENTUM_FILTER_TF=15m | DW2: FIRST_OPEN_THROTTLE_FILTER_TF=OFF | DX2: FIRST_OPEN_THROTTLE_FILTER_TF=D | DY2: FIRST_OPEN_THROTTLE_FILTER_TF=4h | DZ2: FIRST_OPEN_THROTTLE_FILTER_TF=1h | EA2: FIRST_OPEN_THROTTLE_FILTER_TF=15m | EB2: FROZEN_STOP_FILTER_TF=OFF | EC2: FROZEN_STOP_FILTER_TF=D | ED2: FROZEN_STOP_FILTER_TF=4h | EE2: FROZEN_STOP_FILTER_TF=1h | EF2: FROZEN_STOP_FILTER_TF=15m | EG2: GOLDEN_RULE_ENFORCE_FILTER_TF=OFF | EH2: GOLDEN_RULE_ENFORCE_FILTER_TF=D | EI2: GOLDEN_RULE_ENFORCE_FILTER_TF=4h | EJ2: GOLDEN_RULE_ENFORCE_FILTER_TF=1h | EK2: GOLDEN_RULE_ENFORCE_FILTER_TF=15m | EL2: GOLDEN_RULE_HTF_VOTE_FILTER_TF=OFF | EM2: GOLDEN_RULE_HTF_VOTE_FILTER_TF=D | EN2: GOLDEN_RULE_HTF_VOTE_FILTER_TF=4h | EO2: GOLDEN_RULE_HTF_VOTE_FILTER_TF=1h | EP2: GOLDEN_RULE_HTF_VOTE_FILTER_TF=15m | EQ2: GR_FILTER_VEC_FILTER_TF=OFF | ER2: GR_FILTER_VEC_FILTER_TF=D | ES2: GR_FILTER_VEC_FILTER_TF=4h | ET2: GR_FILTER_VEC_FILTER_TF=1h | EU2: GR_FILTER_VEC_FILTER_TF=15m | EV2: GR_V5_STATE_FILTER_TF=OFF | EW2: GR_V5_STATE_FILTER_TF=D | EX2: GR_V5_STATE_FILTER_TF=4h | EY2: GR_V5_STATE_FILTER_TF=1h | EZ2: GR_V5_STATE_FILTER_TF=15m | FA2: HAIKU_WINNER_FILTER_TF=OFF | FB2: HAIKU_WINNER_FILTER_TF=D | FC2: HAIKU_WINNER_FILTER_TF=4h | FD2: HAIKU_WINNER_FILTER_TF=1h | FE2: HAIKU_WINNER_FILTER_TF=15m | FF2: LH_HL_FILTER_TF_REQ=2 | FG2: LH_HL_FILTER_TF_REQ=2_ALT | FH2: LIVE_ENTRY_ENGINE_FILTER_TF=OFF | FI2: LIVE_ENTRY_ENGINE_FILTER_TF=D | FJ2: LIVE_ENTRY_ENGINE_FILTER_TF=4h | FK2: LIVE_ENTRY_ENGINE_FILTER_TF=1h | FL2: LIVE_ENTRY_ENGINE_FILTER_TF=15m | FM2: LIVE_ONLY_SIGNALS_BATCH5_FILTER_TF=OFF | FN2: LIVE_ONLY_SIGNALS_BATCH5_FILTER_TF=D | FO2: LIVE_ONLY_SIGNALS_BATCH5_FILTER_TF=4h | FP2: LIVE_ONLY_SIGNALS_BATCH5_FILTER_TF=1h | FQ2: LIVE_ONLY_SIGNALS_BATCH5_FILTER_TF=15m | FR2: MANDATORY_REENTRY_WT_FILTER_TF_MODE=15m_only | FS2: MANDATORY_REENTRY_WT_FILTER_TF_MODE=15m_only_ALT | FT2: MOM3_FILTER_TF=OFF | FU2: MOM3_FILTER_TF=D | FV2: MOM3_FILTER_TF=4h | FW2: MOM3_FILTER_TF=1h | FX2: MOM3_FILTER_TF=15m | FY2: MOMENTUM_BREAKOUT_FILTER_TF=OFF | FZ2: MOMENTUM_BREAKOUT_FILTER_TF=D | GA2: MOMENTUM_BREAKOUT_FILTER_TF=4h | GB2: MOMENTUM_BREAKOUT_FILTER_TF=1h | GC2: MOMENTUM_BREAKOUT_FILTER_TF=15m | GD2: MTF_ARMED_ENTRIES_FILTER_TF=OFF | GE2: MTF_ARMED_ENTRIES_FILTER_TF=D | GF2: MTF_ARMED_ENTRIES_FILTER_TF=4h | GG2: MTF_ARMED_ENTRIES_FILTER_TF=1h | GH2: MTF_ARMED_ENTRIES_FILTER_TF=15m | GI2: MTF_ATR_TRAIL_FILTER_TF=OFF | GJ2: MTF_ATR_TRAIL_FILTER_TF=D | GK2: MTF_ATR_TRAIL_FILTER_TF=4h | GL2: MTF_ATR_TRAIL_FILTER_TF=1h | GM2: MTF_ATR_TRAIL_FILTER_TF=15m | GN2: MTF_DC_REJECT_FILTER_TF=OFF | GO2: MTF_DC_REJECT_FILTER_TF=D | GP2: MTF_DC_REJECT_FILTER_TF=4h | GQ2: MTF_DC_REJECT_FILTER_TF=1h | GR2: MTF_DC_REJECT_FILTER_TF=15m | GS2: NEWBORN_LOSS_KILL_FILTER_TF=OFF | GT2: NEWBORN_LOSS_KILL_FILTER_TF=D | GU2: NEWBORN_LOSS_KILL_FILTER_TF=4h | GV2: NEWBORN_LOSS_KILL_FILTER_TF=1h | GW2: NEWBORN_LOSS_KILL_FILTER_TF=15m | GX2: NEWBORN_PROTECT_FILTER_TF=OFF | GY2: NEWBORN_PROTECT_FILTER_TF=D | GZ2: NEWBORN_PROTECT_FILTER_TF=4h | HA2: NEWBORN_PROTECT_FILTER_TF=1h | HB2: NEWBORN_PROTECT_FILTER_TF=15m | HC2: NOLOSS_BYPASS_WT5OF5_FILTER_TF=OFF | HD2: NOLOSS_BYPASS_WT5OF5_FILTER_TF=D | HE2: NOLOSS_BYPASS_WT5OF5_FILTER_TF=4h | HF2: NOLOSS_BYPASS_WT5OF5_FILTER_TF=1h | HG2: NOLOSS_BYPASS_WT5OF5_FILTER_TF=15m | HH2: OPEN_INTENT_SIZE_GATES_FILTER_TF=OFF | HI2: OPEN_INTENT_SIZE_GATES_FILTER_TF=D | HJ2: OPEN_INTENT_SIZE_GATES_FILTER_TF=4h | HK2: OPEN_INTENT_SIZE_GATES_FILTER_TF=1h | HL2: OPEN_INTENT_SIZE_GATES_FILTER_TF=15m | HM2: PARTIAL_PROFIT_LOCK_V2_FILTER_TF=OFF | HN2: PARTIAL_PROFIT_LOCK_V2_FILTER_TF=D | HO2: PARTIAL_PROFIT_LOCK_V2_FILTER_TF=4h | HP2: PARTIAL_PROFIT_LOCK_V2_FILTER_TF=1h | HQ2: PARTIAL_PROFIT_LOCK_V2_FILTER_TF=15m | HR2: PEAK_GIVEBACK_BE_EROSION_FILTER_TF=OFF | HS2: PEAK_GIVEBACK_BE_EROSION_FILTER_TF=D | HT2: PEAK_GIVEBACK_BE_EROSION_FILTER_TF=4h | HU2: PEAK_GIVEBACK_BE_EROSION_FILTER_TF=1h | HV2: PEAK_GIVEBACK_BE_EROSION_FILTER_TF=15m | HW2: WT_15M_BOUNCE_BB_MAX=0.95 | HX2: WT_15M_BOUNCE_BB_MAX=0.9 | HY2: WT_15M_BOUNCE_BB_MAX=0.8 | HZ2: WT_15M_BOUNCE_BB_MIN=0.05 | IA2: WT_15M_BOUNCE_BB_MIN=0.1 | IB2: WT_15M_BOUNCE_BB_MIN=0.2 | IC2: WT_15M_BOUNCE_HIGH_1H_GT_PREV=True | ID2: WT_15M_BOUNCE_HIGH_1H_GT_PREV=False | IE2: WT_15M_BOUNCE_LOW_1H_GT_PREV=True | IF2: WT_15M_BOUNCE_LOW_1H_GT_PREV=False | IG2: WT_15M_BOUNCE_REL_VOL_GT_1=True | IH2: WT_15M_BOUNCE_REL_VOL_GT_1=False | II2: Live Location | IJ2: Vec Hook | IK2: Type | IL2: Correct Options
A3: DC_BREAKOUT_TF | B3: OFF | E3: -13.3501 | F3: 2.5853 | G3: =IFERROR(VLOOKUP($A3,Results_30d_Deltas!$A$2:$H$5000,7,FALSE)-E3,"") | H3: =IFERROR(VLOOKUP($A3,Results_30d_Deltas!$A$2:$H$5000,6,FALSE),"") | K3: =IF(B3=C3,"YES","NO") | AP3: 0.8725 | AQ3: 0.4886 | AR3: 0.4347 | IJ3: ez_manage.py:3078 top() | IK3: v12_quick_engine.py:1518 x5
A4: DC_BREAKOUT_TF | B4: D | E4: -13.3501 | F4: 2.5853 | G4: =IFERROR(VLOOKUP($A4,Results_30d_Deltas!$A$2:$H$5000,7,FALSE)-E3,"") | H4: =IFERROR(VLOOKUP($A4,Results_30d_Deltas!$A$2:$H$5000,6,FALSE),"") | K4: =IF(B4=C4,"YES","NO") | AP4: 0.8725 | AQ4: 0.4886 | AR4: 0.4347 | IJ4: ez_manage.py:3078 top() | IK4: v12_quick_engine.py:1518 x5
A5: DC_BREAKOUT_TF | B5: 4h | E5: -13.3501 | F5: 2.5853 | G5: =IFERROR(VLOOKUP($A5,Results_30d_Deltas!$A$2:$H$5000,7,FALSE)-E4,"") | H5: =IFERROR(VLOOKUP($A5,Results_30d_Deltas!$A$2:$H$5000,6,FALSE),"") | K5: =IF(B5=C5,"YES","NO") | AP5: 0.8725 | AQ5: 0.4886 | AR5: 0.4347 | IJ5: ez_manage.py:3078 top() | IK5: v12_quick_engine.py:1518 x5
A6: DC_BREAKOUT_TF | B6: 1h | E6: -13.3501 | F6: 2.5853 | G6: =IFERROR(VLOOKUP($A6,Results_30d_Deltas!$A$2:$H$5000,7,FALSE)-E5,"") | H6: =IFERROR(VLOOKUP($A6,Results_30d_Deltas!$A$2:$H$5000,6,FALSE),"") | K6: =IF(B6=C6,"YES","NO") | AP6: 0.8725 | AQ6: 0.4886 | AR6: 0.4347 | IJ6: ez_manage.py:3078 top() | IK6: v12_quick_engine.py:1518 x5
A7: DC_BREAKOUT_TF | B7: 15m | E7: -13.3501 | F7: 2.5853 | G7: =IFERROR(VLOOKUP($A7,Results_30d_Deltas!$A$2:$H$5000,7,FALSE)-E6,"") | H7: =IFERROR(VLOOKUP($A7,Results_30d_Deltas!$A$2:$H$5000,6,FALSE),"") | K7: =IF(B7=C7,"YES","NO") | AP7: 0.8725 | AQ7: 0.4886 | AR7: 0.4347 | IJ7: ez_manage.py:3078 top() | IK7: v12_quick_engine.py:1518 x5
A8: DC_BREAKOUT_SCORE | B8: 10 | E8: -12.2254 | F8: 3.7101 | G8: =IFERROR(VLOOKUP($A8,Results_30d_Deltas!$A$2:$H$5000,7,FALSE)-E7,"") | H8: =IFERROR(VLOOKUP($A8,Results_30d_Deltas!$A$2:$H$5000,6,FALSE),"") | K8: =IF(B8=C8,"YES","NO") | AP8: 0.4886 | AQ8: 0.8725 | AR8: 2.4718 | IJ8: ez_manage.py:3077 top() | IK8: v12_quick_engine.py:1517 x18
A9: DC_BREAKOUT_SCORE | B9: 15 | E9: -12.2254 | F9: 3.7101 | G9: =IFERROR(VLOOKUP($A9,Results_30d_Deltas!$A$2:$H$5000,7,FALSE)-E8,"") | H9: =IFERROR(VLOOKUP($A9,Results_30d_Deltas!$A$2:$H$5000,6,FALSE),"") | K9: =IF(B9=C9,"YES","NO") | AP9: 0.4886 | AQ9: 0.8725 | AR9: 2.4718 | IJ9: ez_manage.py:3077 top() | IK9: v12_quick_engine.py:1517 x18
A10: DC_BREAKOUT_SCORE | B10: 20 | E10: -12.2254 | F10: 3.7101 | G10: =IFERROR(VLOOKUP($A10,Results_30d_Deltas!$A$2:$H$5000,7,FALSE)-E9,"") | H10: =IFERROR(VLOOKUP($A10,Results_30d_Deltas!$A$2:$H$5000,6,FALSE),"") | K10: =IF(B10=C10,"YES","NO") | AP10: 0.4886 | AQ10: 0.8725 | AR10: 2.4718 | IJ10: ez_manage.py:3077 top() | IK10: v12_quick_engine.py:1517 x18
A11: DC_BREAKOUT_SCORE | B11: 25 | E11: -12.2254 | F11: 3.7101 | G11: =IFERROR(VLOOKUP($A11,Results_30d_Deltas!$A$2:$H$5000,7,FALSE)-E10,"") | H11: =IFERROR(VLOOKUP($A11,Results_30d_Deltas!$A$2:$H$5000,6,FALSE),"") | K11: =IF(B11=C11,"YES","NO") | AP11: 0.4886 | AQ11: 0.8725 | AR11: 2.4718 | IJ11: ez_manage.py:3077 top() | IK11: v12_quick_engine.py:1517 x18
A12: DC_BREAKOUT_SCORE | B12: 30 | E12: -12.2254 | F12: 3.7101 | G12: =IFERROR(VLOOKUP($A12,Results_30d_Deltas!$A$2:$H$5000,7,FALSE)-E11,"") | H12: =IFERROR(VLOOKUP($A12,Results_30d_Deltas!$A$2:$H$5000,6,FALSE),"") | K12: =IF(B12=C12,"YES","NO") | AP12: 0.4886 | AQ12: 0.8725 | AR12: 2.4718 | IJ12: ez_manage.py:3077 top() | IK12: v12_quick_engine.py:1517 x18
A13: BB_BREAKOUT_SCORE | B13: 10 | E13: -13.3501 | F13: 2.5853 | G13: =IFERROR(VLOOKUP($A13,Results_30d_Deltas!$A$2:$H$5000,7,FALSE)-E12,"") | H13: =IFERROR(VLOOKUP($A13,Results_30d_Deltas!$A$2:$H$5000,6,FALSE),"") | K13: =IF(B13=C13,"YES","NO") | AP13: 0.8638 | AQ13: 0 | AR13: 2.5853 | IJ13: ez_manage.py:2963 top() | IK13: v12_quick_engine.py:1255 x6
A14: BB_BREAKOUT_SCORE | B14: 15 | E14: -13.3501 | F14: 2.5853 | G14: =IFERROR(VLOOKUP($A14,Results_30d_Deltas!$A$2:$H$5000,7,FALSE)-E13,"") | H14: =IFERROR(VLOOKUP($A14,Results_30d_Deltas!$A$2:$H$5000,6,FALSE),"") | K14: =IF(B14=C14,"YES","NO") | AP14: 0.8638 | AQ14: 0 | AR14: 2.5853 | IJ14: ez_manage.py:2963 top() | IK14: v12_quick_engine.py:1255 x6
A15: BB_BREAKOUT_SCORE | B15: 20 | E15: -13.3501 | F15: 2.5853 | G15: =IFERROR(VLOOKUP($A15,Results_30d_Deltas!$A$2:$H$5000,7,FALSE)-E14,"") | H15: =IFERROR(VLOOKUP($A15,Results_30d_Deltas!$A$2:$H$5000,6,FALSE),"") | K15: =IF(B15=C15,"YES","NO") | AP15: 0.8638 | AQ15: 0 | AR15: 2.5853 | IJ15: ez_manage.py:2963 top() | IK15: v12_quick_engine.py:1255 x6
... A23: RZ_BREAKOUT_ENTRY_ENABLED | B23: True | E23: -13.3501 | F23: 2.5853 | G23: =IFERROR(VLOOKUP($A23,Results_30d_Deltas!$A$2:$H$5000,7,FALSE)-E22,"") | H23: =IFERROR(VLOOKUP($A23,Results_30d_Deltas!$A$2:$H$5000,6,FALSE),"") | K23: =IF(B23=C23,"YES","NO") | AP23: 0.8638 | AQ23: 0.4347 | AR23: 0 | IJ23: ez_manage.py:5398 top() | IK23: v12_quick_engine.py:3021 x3
A24: ATR_ADAPTIVE_SIZING_TARGET_PCT | B24: 1.0 | E24: -13.3501 | F24: 2.5853 | G24: =IFERROR(VLOOKUP($A24,Results_30d_Deltas!$A$2:$H$5000,7,FALSE)-E23,"") | H24: =IFERROR(VLOOKUP($A24,Results_30d_Deltas!$A$2:$H$5000,6,FALSE),"") | K24: =IF(B24=C24,"YES","NO") | IJ24: ez_manage.py:4327 top() | IK24: v12_quick_engine.py:1209 x7
A25: ATR_ADAPTIVE_SIZING_TARGET_PCT | B25: 1.5 | E25: -13.3501 | F25: 2.5853 | G25: =IFERROR(VLOOKUP($A25,Results_30d_Deltas!$A$2:$H$5000,7,FALSE)-E24,"") | H25: =IFERROR(VLOOKUP($A25,Results_30d_Deltas!$A$2:$H$5000,6,FALSE),"") | K25: =IF(B25=C25,"YES","NO") | IJ25: ez_manage.py:4327 top() | IK25: v12_quick_engine.py:1209 x7
A26: ATR_ADAPTIVE_SIZING_TARGET_PCT | B26: 2.0 | E26: -13.3501 | F26: 2.5853 | G26: =IFERROR(VLOOKUP($A26,Results_30d_Deltas!$A$2:$H$5000,7,FALSE)-E25,"") | H26: =IFERROR(VLOOKUP($A26,Results_30d_Deltas!$A$2:$H$5000,6,FALSE),"") | K26: =IF(B26=C26,"YES","NO") | IJ26: ez_manage.py:4327 top() | IK26: v12_quick_engine.py:1209 x7
A27: ATR_ADAPTIVE_SIZING_TARGET_PCT | B27: 2.5 | E27: -13.3501 | F27: 2.5853 | G27: =IFERROR(VLOOKUP($A27,Results_30d_Deltas!$A$2:$H$5000,7,FALSE)-E26,"") | H27: =IFERROR(VLOOKUP($A27,Results_30d_Deltas!$A$2:$H$5000,6,FALSE),"") | K27: =IF(B27=C27,"YES","NO") | IJ27: ez_manage.py:4327 top() | IK27: v12_quick_engine.py:1209 x7
A28: ATR_ADAPTIVE_SIZING_TARGET_PCT | B28: 3.0 | E28: -13.3501 | F28: 2.5853 | G28: =IFERROR(VLOOKUP($A28,Results_30d_Deltas!$A$2:$H$5000,7,FALSE)-E27,"") | H28: =IFERROR(VLOOKUP($A28,Results_30d_Deltas!$A$2:$H$5000,6,FALSE),"") | K28: =IF(B28=C28,"YES","NO") | IJ28: ez_manage.py:4327 top() | IK28: v12_quick_engine.py:1209 x7
A29: ATR_ADAPTIVE_STOP_MULT | B29: 1.0 | E29: -13.3501 | F29: 2.5853 | G29: =IFERROR(VLOOKUP($A29,Results_30d_Deltas!$A$2:$H$5000,7,FALSE)-E28,"") | H29: =IFERROR(VLOOKUP($A29,Results_30d_Deltas!$A$2:$H$5000,6,FALSE),"") | K29: =IF(B29=C29,"YES","NO") | IJ29: ez_manage.py:4329 top() | IK29: v12_quick_engine.py:1211 x6
A30: ATR_ADAPTIVE_STOP_MULT | B30: 1.5 | E30: -13.3501 | F30: 2.5853 | G30: =IFERROR(VLOOKUP($A30,Results_30d_Deltas!$A$2:$H$5000,7,FALSE)-E29,"") | H30: =IFERROR(VLOOKUP($A30,Results_30d_Deltas!$A$2:$H$5000,6,FALSE),"") | K30: =IF(B30=C30,"YES","NO") | IJ30: ez_manage.py:4329 top() | IK30: v12_quick_engine.py:1211 x6
A31: ATR_ADAPTIVE_STOP_MULT | B31: 2.0 | E31: -13.3501 | F31: 2.5853 | G31: =IFERROR(VLOOKUP($A31,Results_30d_Deltas!$A$2:$H$5000,7,FALSE)-E30,"") | H31: =IFERROR(VLOOKUP($A31,Results_30d_Deltas!$A$2:$H$5000,6,FALSE),"") | K31: =IF(B31=C31,"YES","NO") | IJ31: ez_manage.py:4329 top() | IK31: v12_quick_engine.py:1211 x6
A32: ATR_ADAPTIVE_STOP_MULT | B32: 2.5 | E32: -13.3501 | F32: 2.5853 | G32: =IFERROR(VLOOKUP($A32,Results_30d_Deltas!$A$2:$H$5000,7,FALSE)-E31,"") | H32: =IFERROR(VLOOKUP($A32,Results_30d_Deltas!$A$2:$H$5000,6,FALSE),"") | K32: =IF(B32=C32,"YES","NO") | IJ32: ez_manage.py:4329 top() | IK32: v12_quick_engine.py:1211 x6
A33: ATR_ADAPTIVE_STOP_MULT | B33: 3.0 | E33: -13.3501 | F33: 2.5853 | G33: =IFERROR(VLOOKUP($A33,Results_30d_Deltas!$A$2:$H$5000,7,FALSE)-E32,"") | H33: =IFERROR(VLOOKUP($A33,Results_30d_Deltas!$A$2:$H$5000,6,FALSE),"") | K33: =IF(B33=C33,"YES","NO") | IJ33: ez_manage.py:4329 top() | IK33: v12_quick_engine.py:1211 x6
A34: ATR_LONG_WINDOW | B34: 50 | E34: -12.2254 | F34: 3.7101 | G34: =IFERROR(VLOOKUP($A34,Results_30d_Deltas!$A$2:$H$5000,7,FALSE)-E33,"") | H34: =IFERROR(VLOOKUP($A34,Results_30d_Deltas!$A$2:$H$5000,6,FALSE),"") | K34: =IF(B34=C34,"YES","NO") | IJ34: ez_manage.py:4330 top() | IK34: v12_quick_engine.py:199 x5
A35: ATR_LONG_WINDOW | B35: 75 | E35: -12.2254 | F35: 3.7101 | G35: =IFERROR(VLOOKUP($A35,Results_30d_Deltas!$A$2:$H$5000,7,FALSE)-E34,"") | H35: =IFERROR(VLOOKUP($A35,Results_30d_Deltas!$A$2:$H$5000,6,FALSE),"") | K35: =IF(B35=C35,"YES","NO") | IJ35: ez_manage.py:4330 top() | IK35: v12_quick_engine.py:199 x5
... A85: MACD_ZERO_CROSS_TF | B85: 15m | E85: -14.3964 | F85: 1.539 | G85: =IFERROR(VLOOKUP($A85,Results_30d_Deltas!$A$2:$H$5000,7,FALSE)-E84,"") | H85: =IFERROR(VLOOKUP($A85,Results_30d_Deltas!$A$2:$H$5000,6,FALSE),"") | K85: =IF(B85=C85,"YES","NO") | IJ85: ez_manage.py:3501 top() | IK85: v12_quick_engine.py:2236 x2
A86: MI_MIN_GAIN_EXIT | B86: 0 | E86: -12.2254 | F86: 3.7101 | G86: =IFERROR(VLOOKUP($A86,Results_30d_Deltas!$A$2:$H$5000,7,FALSE)-E85,"") | H86: =IFERROR(VLOOKUP($A86,Results_30d_Deltas!$A$2:$H$5000,6,FALSE),"") | K86: =IF(B86=C86,"YES","NO") | AK86: 0.8638 | AL86: 0.436 | AM86: 3.7101 | IJ86: ez_manage.py:3565 top() | IK86: v12_quick_engine.py:2342 x8
A87: MI_MIN_GAIN_EXIT | B87: 0.5 | E87: -12.2254 | F87: 3.7101 | G87: =IFERROR(VLOOKUP($A87,Results_30d_Deltas!$A$2:$H$5000,7,FALSE)-E86,"") | H87: =IFERROR(VLOOKUP($A87,Results_30d_Deltas!$A$2:$H$5000,6,FALSE),"") | K87: =IF(B87=C87,"YES","NO") | AK87: 0.8638 | AL87: 0.436 | AM87: 3.7101 | IJ87: ez_manage.py:3565 top() | IK87: v12_quick_engine.py:2342 x8
A88: MI_MIN_GAIN_EXIT | B88: 1.0 | E88: -12.2254 | F88: 3.7101 | G88: =IFERROR(VLOOKUP($A88,Results_30d_Deltas!$A$2:$H$5000,7,FALSE)-E87,"") | H88: =IFERROR(VLOOKUP($A88,Results_30d_Deltas!$A$2:$H$5000,6,FALSE),"") | K88: =IF(B88=C88,"YES","NO") | AK88: 0.8638 | AL88: 0.436 | AM88: 3.7101 | IJ88: ez_manage.py:3565 top() | IK88: v12_quick_engine.py:2342 x8
A89: MI_MIN_GAIN_EXIT | B89: 2.0 | E89: -12.2254 | F89: 3.7101 | G89: =IFERROR(VLOOKUP($A89,Results_30d_Deltas!$A$2:$H$5000,7,FALSE)-E88,"") | H89: =IFERROR(VLOOKUP($A89,Results_30d_Deltas!$A$2:$H$5000,6,FALSE),"") | K89: =IF(B89=C89,"YES","NO") | AK89: 0.8638 | AL89: 0.436 | AM89: 3.7101 | IJ89: ez_manage.py:3565 top() | IK89: v12_quick_engine.py:2342 x8
A90: PARTIAL_EXIT_FRAC | B90: 0 | E90: -12.2254 | F90: 3.7101 | G90: =IFERROR(VLOOKUP($A90,Results_30d_Deltas!$A$2:$H$5000,7,FALSE)-E89,"") | H90: =IFERROR(VLOOKUP($A90,Results_30d_Deltas!$A$2:$H$5000,6,FALSE),"") | K90: =IF(B90=C90,"YES","NO") | IJ90: ez_manage.py:6038 top() | IK90: v12_quick_engine.py:4280 x2
A91: PARTIAL_EXIT_FRAC | B91: 0.5 | E91: -12.2254 | F91: 3.7101 | G91: =IFERROR(VLOOKUP($A91,Results_30d_Deltas!$A$2:$H$5000,7,FALSE)-E90,"") | H91: =IFERROR(VLOOKUP($A91,Results_30d_Deltas!$A$2:$H$5000,6,FALSE),"") | K91: =IF(B91=C91,"YES","NO") | IJ91: ez_manage.py:6038 top() | IK91: v12_quick_engine.py:4280 x2
A92: PARTIAL_EXIT_FRAC | B92: 1.0 | E92: -12.2254 | F92: 3.7101 | G92: =IFERROR(VLOOKUP($A92,Results_30d_Deltas!$A$2:$H$5000,7,FALSE)-E91,"") | H92: =IFERROR(VLOOKUP($A92,Results_30d_Deltas!$A$2:$H$5000,6,FALSE),"") | K92: =IF(B92=C92,"YES","NO") | IJ92: ez_manage.py:6038 top() | IK92: v12_quick_engine.py:4280 x2
A93: PARTIAL_EXIT_FRAC | B93: 2.0 | E93: -12.2254 | F93: 3.7101 | G93: =IFERROR(VLOOKUP($A93,Results_30d_Deltas!$A$2:$H$5000,7,FALSE)-E92,"") | H93: =IFERROR(VLOOKUP($A93,Results_30d_Deltas!$A$2:$H$5000,6,FALSE),"") | K93: =IF(B93=C93,"YES","NO") | IJ93: ez_manage.py:6038 top() | IK93: v12_quick_engine.py:4280 x2
A94: QUICK_REENTRY_60MIN_MIN_PCT | B94: 0 | E94: -12.2254 | F94: 3.7101 | G94: =IFERROR(VLOOKUP($A94,Results_30d_Deltas!$A$2:$H$5000,7,FALSE)-E93,"") | H94: =IFERROR(VLOOKUP($A94,Results_30d_Deltas!$A$2:$H$5000,6,FALSE),"") | K94: =IF(B94=C94,"YES","NO") | IJ94: ez_manage.py:6042 top() | IK94: v12_quick_engine.py:4283 x4
A95: QUICK_REENTRY_60MIN_MIN_PCT | B95: 0.5 | E95: -12.2254 | F95: 3.7101 | G95: =IFERROR(VLOOKUP($A95,Results_30d_Deltas!$A$2:$H$5000,7,FALSE)-E94,"") | H95: =IFERROR(VLOOKUP($A95,Results_30d_Deltas!$A$2:$H$5000,6,FALSE),"") | K95: =IF(B95=C95,"YES","NO") | IJ95: ez_manage.py:6042 top() | IK95: v12_quick_engine.py:4283 x4
A96: QUICK_REENTRY_60MIN_MIN_PCT | B96: 1.0 | E96: -12.2254 | F96: 3.7101 | G96: =IFERROR(VLOOKUP($A96,Results_30d_Deltas!$A$2:$H$5000,7,FALSE)-E95,"") | H96: =IFERROR(VLOOKUP($A96,Results_30d_Deltas!$A$2:$H$5000,6,FALSE),"") | K96: =IF(B96=C96,"YES","NO") | IJ96: ez_manage.py:6042 top() | IK96: v12_quick_engine.py:4283 x4
A97: QUICK_REENTRY_60MIN_MIN_PCT | B97: 2.0 | E97: -12.2254 | F97: 3.7101 | G97: =IFERROR(VLOOKUP($A97,Results_30d_Deltas!$A$2:$H$5000,7,FALSE)-E96,"") | H97: =IFERROR(VLOOKUP($A97,Results_30d_Deltas!$A$2:$H$5000,6,FALSE),"") | K97: =IF(B97=C97,"YES","NO") | IJ97: ez_manage.py:6042 top() | IK97: v12_quick_engine.py:4283 x4
A98: REENTRY2_STOCH_CROSS_ENABLED | B98: False | E98: -12.2254 | F98: 3.7101 | G98: =IFERROR(VLOOKUP($A98,Results_30d_Deltas!$A$2:$H$5000,7,FALSE)-E97,"") | H98: =IFERROR(VLOOKUP($A98,Results_30d_Deltas!$A$2:$H$5000,6,FALSE),"") | K98: =IF(B98=C98,"YES","NO") | IJ98: ez_manage.py:5285 top() | IK98: v12_quick_engine.py:2842 x10
A99: REENTRY2_STOCH_CROSS_ENABLED | B99: True | E99: -13.3501 | F99: 2.5853 | G99: =IFERROR(VLOOKUP($A99,Results_30d_Deltas!$A$2:$H$5000,7,FALSE)-E98,"") | H99: =IFERROR(VLOOKUP($A99,Results_30d_Deltas!$A$2:$H$5000,6,FALSE),"") | K99: =IF(B99=C99,"YES","NO") | IJ99: ez_manage.py:5285 top() | IK99: v12_quick_engine.py:2842 x10
A100: REENTRY_K15M_PARTIAL_MULT | B100: 0.125 | E100: -12.2254 | F100: 3.7101 | G100: =IFERROR(VLOOKUP($A100,Results_30d_Deltas!$A$2:$H$5000,7,FALSE)-E99,"") | H100: =IFERROR(VLOOKUP($A100,Results_30d_Deltas!$A$2:$H$5000,6,FALSE),"") | K100: =IF(B100=C100,"YES","NO") | IJ100: ez_manage.py:3860 top() | IK100: v12_quick_engine.py:2884 x8
A101: REENTRY_K15M_PARTIAL_MULT | B101: 0.1875 | E101: -12.2254 | F101: 3.7101 | G101: =IFERROR(VLOOKUP($A101,Results_30d_Deltas!$A$2:$H$5000,7,FALSE)-E100,"") | H101: =IFERROR(VLOOKUP($A101,Results_30d_Deltas!$A$2:$H$5000,6,FALSE),"") | K101: =IF(B101=C101,"YES","NO") | IJ101: ez_manage.py:3860 top() | IK101: v12_quick_engine.py:2884 x8
... A109: REENTRY_RALLY_K15M_MAX | B109: 150.0 | E109: -13.4636 | F109: 2.4718 | G109: =IFERROR(VLOOKUP($A109,Results_30d_Deltas!$A$2:$H$5000,7,FALSE)-E108,"") | H109: =IFERROR(VLOOKUP($A109,Results_30d_Deltas!$A$2:$H$5000,6,FALSE),"") | K109: =IF(B109=C109,"YES","NO") | IJ109: ez_manage.py:3869 top() | IK109: v12_quick_engine.py:2902 x8
A110: REGIME_TRENDING_EXIT_GAIN_MIN | B110: 1.0 | E110: -12.1759 | F110: 3.7596 | G110: =IFERROR(VLOOKUP($A110,Results_30d_Deltas!$A$2:$H$5000,7,FALSE)-E109,"") | H110: =IFERROR(VLOOKUP($A110,Results_30d_Deltas!$A$2:$H$5000,6,FALSE),"") | K110: =IF(B110=C110,"YES","NO") | AK110: 0.505 | AL110: 0.436 | AM110: 3.7596 | IJ110: ez_manage.py:5359 top() | IK110: v12_quick_engine.py:2951 x5
A111: REGIME_TRENDING_EXIT_GAIN_MIN | B111: 1.5 | E111: -12.1759 | F111: 3.7596 | G111: =IFERROR(VLOOKUP($A111,Results_30d_Deltas!$A$2:$H$5000,7,FALSE)-E110,"") | H111: =IFERROR(VLOOKUP($A111,Results_30d_Deltas!$A$2:$H$5000,6,FALSE),"") | K111: =IF(B111=C111,"YES","NO") | AK111: 0.505 | AL111: 0.436 | AM111: 3.7596 | IJ111: ez_manage.py:5359 top() | IK111: v12_quick_engine.py:2951 x5
A112: REGIME_TRENDING_EXIT_GAIN_MIN | B112: 2.0 | E112: -12.1759 | F112: 3.7596 | G112: =IFERROR(VLOOKUP($A112,Results_30d_Deltas!$A$2:$H$5000,7,FALSE)-E111,"") | H112: =IFERROR(VLOOKUP($A112,Results_30d_Deltas!$A$2:$H$5000,6,FALSE),"") | K112: =IF(B112=C112,"YES","NO") | AK112: 0.505 | AL112: 0.436 | AM112: 3.7596 | IJ112: ez_manage.py:5359 top() | IK112: v12_quick_engine.py:2951 x5
A113: REGIME_TRENDING_EXIT_GAIN_MIN | B113: 2.5 | E113: -12.1759 | F113: 3.7596 | G113: =IFERROR(VLOOKUP($A113,Results_30d_Deltas!$A$2:$H$5000,7,FALSE)-E112,"") | H113: =IFERROR(VLOOKUP($A113,Results_30d_Deltas!$A$2:$H$5000,6,FALSE),"") | K113: =IF(B113=C113,"YES","NO") | AK113: 0.505 | AL113: 0.436 | AM113: 3.7596 | IJ113: ez_manage.py:5359 top() | IK113: v12_quick_engine.py:2951 x5
A114: REGIME_TRENDING_EXIT_GAIN_MIN | B114: 3.0 | E114: -12.1759 | F114: 3.7596 | G114: =IFERROR(VLOOKUP($A114,Results_30d_Deltas!$A$2:$H$5000,7,FALSE)-E113,"") | H114: =IFERROR(VLOOKUP($A114,Results_30d_Deltas!$A$2:$H$5000,6,FALSE),"") | K114: =IF(B114=C114,"YES","NO") | AK114: 0.505 | AL114: 0.436 | AM114: 3.7596 | IJ114: ez_manage.py:5359 top() | IK114: v12_quick_engine.py:2951 x5
A115: REVERSE_ON_EXIT_ENABLED | B115: False | E115: -12.1759 | F115: 3.7596 | G115: =IFERROR(VLOOKUP($A115,Results_30d_Deltas!$A$2:$H$5000,7,FALSE)-E114,"") | H115: =IFERROR(VLOOKUP($A115,Results_30d_Deltas!$A$2:$H$5000,6,FALSE),"") | K115: =IF(B115=C115,"YES","NO") | IJ115: ez_manage.py:1219 top() | IK115: v12_quick_engine.py:1420 x3
A116: REVERSE_ON_EXIT_ENABLED | B116: True | E116: -13.3501 | F116: 2.5853 | G116: =IFERROR(VLOOKUP($A116,Results_30d_Deltas!$A$2:$H$5000,7,FALSE)-E115,"") | H116: =IFERROR(VLOOKUP($A116,Results_30d_Deltas!$A$2:$H$5000,6,FALSE),"") | K116: =IF(B116=C116,"YES","NO") | IJ116: ez_manage.py:1219 top() | IK116: v12_quick_engine.py:1420 x3
A117: RZ_BOT_BB_THRESHOLD | B117: 0.075 | E117: -12.2254 | F117: 3.7101 | G117: =IFERROR(VLOOKUP($A117,Results_30d_Deltas!$A$2:$H$5000,7,FALSE)-E116,"") | H117: =IFERROR(VLOOKUP($A117,Results_30d_Deltas!$A$2:$H$5000,6,FALSE),"") | K117: =IF(B117=C117,"YES","NO") | IJ117: ez_manage.py:3928 top() | IK117: v12_quick_engine.py:3020 x6
A118: RZ_BOT_BB_THRESHOLD | B118: 0.1125 | E118: -12.2254 | F118: 3.7101 | G118: =IFERROR(VLOOKUP($A118,Results_30d_Deltas!$A$2:$H$5000,7,FALSE)-E117,"") | H118: =IFERROR(VLOOKUP($A118,Results_30d_Deltas!$A$2:$H$5000,6,FALSE),"") | K118: =IF(B118=C118,"YES","NO") | IJ118: ez_manage.py:3928 top() | IK118: v12_quick_engine.py:3020 x6
A119: RZ_BOT_BB_THRESHOLD | B119: 0.15 | E119: -12.2254 | F119: 3.7101 | G119: =IFERROR(VLOOKUP($A119,Results_30d_Deltas!$A$2:$H$5000,7,FALSE)-E118,"") | H119: =IFERROR(VLOOKUP($A119,Results_30d_Deltas!$A$2:$H$5000,6,FALSE),"") | K119: =IF(B119=C119,"YES","NO") | IJ119: ez_manage.py:3928 top() | IK119: v12_quick_engine.py:3020 x6
A120: RZ_BOT_BB_THRESHOLD | B120: 0.1875 | E120: -12.2254 | F120: 3.7101 | G120: =IFERROR(VLOOKUP($A120,Results_30d_Deltas!$A$2:$H$5000,7,FALSE)-E119,"") | H120: =IFERROR(VLOOKUP($A120,Results_30d_Deltas!$A$2:$H$5000,6,FALSE),"") | K120: =IF(B120=C120,"YES","NO") | IJ120: ez_manage.py:3928 top() | IK120: v12_quick_engine.py:3020 x6
A121: RZ_BOT_BB_THRESHOLD | B121: 0.225 | E121: -12.2254 | F121: 3.7101 | G121: =IFERROR(VLOOKUP($A121,Results_30d_Deltas!$A$2:$H$5000,7,FALSE)-E120,"") | H121: =IFERROR(VLOOKUP($A121,Results_30d_Deltas!$A$2:$H$5000,6,FALSE),"") | K121: =IF(B121=C121,"YES","NO") | IJ121: ez_manage.py:3928 top() | IK121: v12_quick_engine.py:3020 x6
A122: RZ_BREAKOUT_BAND | B122: 0 | E122: -12.1759 | F122: 3.7596 | G122: =IFERROR(VLOOKUP($A122,Results_30d_Deltas!$A$2:$H$5000,7,FALSE)-E121,"") | H122: =IFERROR(VLOOKUP($A122,Results_30d_Deltas!$A$2:$H$5000,6,FALSE),"") | K122: =IF(B122=C122,"YES","NO") | AP122: 2.4718 | AQ122: 0.8725 | AR122: 3.7596 | IJ122: ez_manage.py:5397 top() | IK122: v12_quick_engine.py:4036 x3
A123: RZ_BREAKOUT_BAND | B123: 0.5 | E123: -12.1759 | F123: 3.7596 | G123: =IFERROR(VLOOKUP($A123,Results_30d_Deltas!$A$2:$H$5000,7,FALSE)-E122,"") | H123: =IFERROR(VLOOKUP($A123,Results_30d_Deltas!$A$2:$H$5000,6,FALSE),"") | K123: =IF(B123=C123,"YES","NO") | AP123: 2.4718 | AQ123: 0.8725 | AR123: 3.7596 | IJ123: ez_manage.py:5397 top() | IK123: v12_quick_engine.py:4036 x3
A124: RZ_BREAKOUT_BAND | B124: 1.0 | E124: -12.1759 | F124: 3.7596 | G124: =IFERROR(VLOOKUP($A124,Results_30d_Deltas!$A$2:$H$5000,7,FALSE)-E123,"") | H124: =IFERROR(VLOOKUP($A124,Results_30d_Deltas!$A$2:$H$5000,6,FALSE),"") | K124: =IF(B124=C124,"YES","NO") | AP124: 2.4718 | AQ124: 0.8725 | AR124: 3.7596 | IJ124: ez_manage.py:5397 top() | IK124: v12_quick_engine.py:4036 x3
A125: RZ_BREAKOUT_BAND | B125: 2.0 | E125: -12.1759 | F125: 3.7596 | G125: =IFERROR(VLOOKUP($A125,Results_30d_Deltas!$A$2:$H$5000,7,FALSE)-E124,"") | H125: =IFERROR(VLOOKUP($A125,Results_30d_Deltas!$A$2:$H$5000,6,FALSE),"") | K125: =IF(B125=C125,"YES","NO") | AP125: 2.4718 | AQ125: 0.8725 | AR125: 3.7596 | IJ125: ez_manage.py:5397 top() | IK125: v12_quick_engine.py:4036 x3
A126: SCALP_V3_K_OB_EXIT_K15M_HI | B126: 0 | E126: -12.1759 | F126: 3.7596 | G126: =IFERROR(VLOOKUP($A126,Results_30d_Deltas!$A$2:$H$5000,7,FALSE)-E125,"") | H126: =IFERROR(VLOOKUP($A126,Results_30d_Deltas!$A$2:$H$5000,6,FALSE),"") | K126: =IF(B126=C126,"YES","NO") | IJ126: ez_manage.py:5551 top() | IK126: v12_quick_engine.py:3179 x4
A127: SCALP_V3_K_OB_EXIT_K15M_HI | B127: 0.5 | E127: -12.1759 | F127: 3.7596 | G127: =IFERROR(VLOOKUP($A127,Results_30d_Deltas!$A$2:$H$5000,7,FALSE)-E126,"") | H127: =IFERROR(VLOOKUP($A127,Results_30d_Deltas!$A$2:$H$5000,6,FALSE),"") | K127: =IF(B127=C127,"YES","NO") | IJ127: ez_manage.py:5551 top() | IK127: v12_quick_engine.py:3179 x4
A128: SCALP_V3_K_OB_EXIT_K15M_HI | B128: 1.0 | E128: -12.1759 | F128: 3.7596 | G128: =IFERROR(VLOOKUP($A128,Results_30d_Deltas!$A$2:$H$5000,7,FALSE)-E127,"") | H128: =IFERROR(VLOOKUP($A128,Results_30d_Deltas!$A$2:$H$5000,6,FALSE),"") | K128: =IF(B128=C128,"YES","NO") | IJ128: ez_manage.py:5551 top() | IK128: v12_quick_engine.py:3179 x4
A129: SCALP_V3_K_OB_EXIT_K15M_HI | B129: 2.0 | E129: -12.1759 | F129: 3.7596 | G129: =IFERROR(VLOOKUP($A129,Results_30d_Deltas!$A$2:$H$5000,7,FALSE)-E128,"") | H129: =IFERROR(VLOOKUP($A129,Results_30d_Deltas!$A$2:$H$5000,6,FALSE),"") | K129: =IF(B129=C129,"YES","NO") | IJ129: ez_manage.py:5551 top() | IK129: v12_quick_engine.py:3179 x4
A130: SCALP_V3_K_OB_EXIT_K15M_LO | B130: 0 | E130: -12.1759 | F130: 3.7596 | G130: =IFERROR(VLOOKUP($A130,Results_30d_Deltas!$A$2:$H$5000,7,FALSE)-E129,"") | H130: =IFERROR(VLOOKUP($A130,Results_30d_Deltas!$A$2:$H$5000,6,FALSE),"") | K130: =IF(B130=C130,"YES","NO") | IJ130: ez_manage.py:5552 top() | IK130: v12_quick_engine.py:3180 x4
A131: SCALP_V3_K_OB_EXIT_K15M_LO | B131: 0.5 | E131: -12.1759 | F131: 3.7596 | G131: =IFERROR(VLOOKUP($A131,Results_30d_Deltas!$A$2:$H$5000,7,FALSE)-E130,"") | H131: =IFERROR(VLOOKUP($A131,Results_30d_Deltas!$A$2:$H$5000,6,FALSE),"") | K131: =IF(B131=C131,"YES","NO") | IJ131: ez_manage.py:5552 top() | IK131: v12_quick_engine.py:3180 x4
A132: SCALP_V3_K_OB_EXIT_K15M_LO | B132: 1.0 | E132: -12.1759 | F132: 3.7596 | G132: =IFERROR(VLOOKUP($A132,Results_30d_Deltas!$A$2:$H$5000,7,FALSE)-E131,"") | H132: =IFERROR(VLOOKUP($A132,Results_30d_Deltas!$A$2:$H$5000,6,FALSE),"") | K132: =IF(B132=C132,"YES","NO") | IJ132: ez_manage.py:5552 top() | IK132: v12_quick_engine.py:3180 x4
A133: SCALP_V3_K_OB_EXIT_K15M_LO | B133: 2.0 | E133: -12.1759 | F133: 3.7596 | G133: =IFERROR(VLOOKUP($A133,Results_30d_Deltas!$A$2:$H$5000,7,FALSE)-E132,"") | H133: =IFERROR(VLOOKUP($A133,Results_30d_Deltas!$A$2:$H$5000,6,FALSE),"") | K133: =IF(B133=C133,"YES","NO") | IJ133: ez_manage.py:5552 top() | IK133: v12_quick_engine.py:3180 x4
A134: SCALP_V3_K_OB_EXIT_K3M_HI | B134: 0 | E134: -12.2254 | F134: 3.7101 | G134: =IFERROR(VLOOKUP($A134,Results_30d_Deltas!$A$2:$H$5000,7,FALSE)-E133,"") | H134: =IFERROR(VLOOKUP($A134,Results_30d_Deltas!$A$2:$H$5000,6,FALSE),"") | K134: =IF(B134=C134,"YES","NO") | IJ134: ez_manage.py:5553 top() | IK134: v12_quick_engine.py:3181 x4
A135: SCALP_V3_K_OB_EXIT_K3M_HI | B135: 0.5 | E135: -12.2254 | F135: 3.7101 | G135: =IFERROR(VLOOKUP($A135,Results_30d_Deltas!$A$2:$H$5000,7,FALSE)-E134,"") | H135: =IFERROR(VLOOKUP($A135,Results_30d_Deltas!$A$2:$H$5000,6,FALSE),"") | K135: =IF(B135=C135,"YES","NO") | IJ135: ez_manage.py:5553 top() | IK135: v12_quick_engine.py:3181 x4
A136: SCALP_V3_K_OB_EXIT_K3M_HI | B136: 1.0 | E136: -12.2254 | F136: 3.7101 | G136: =IFERROR(VLOOKUP($A136,Results_30d_Deltas!$A$2:$H$5000,7,FALSE)-E135,"") | H136: =IFERROR(VLOOKUP($A136,Results_30d_Deltas!$A$2:$H$5000,6,FALSE),"") | K136: =IF(B136=C136,"YES","NO") | IJ136: ez_manage.py:5553 top() | IK136: v12_quick_engine.py:3181 x4
A137: SCALP_V3_K_OB_EXIT_K3M_HI | B137: 2.0 | E137: -12.2254 | F137: 3.7101 | G137: =IFERROR(VLOOKUP($A137,Results_30d_Deltas!$A$2:$H$5000,7,FALSE)-E136,"") | H137: =IFERROR(VLOOKUP($A137,Results_30d_Deltas!$A$2:$H$5000,6,FALSE),"") | K137: =IF(B137=C137,"YES","NO") | IJ137: ez_manage.py:5553 top() | IK137: v12_quick_engine.py:3181 x4
... A149: SCALP_V3_OB_WALL_TOO_CLOSE_PCT | B149: 2.0 | E149: -12.1759 | F149: 3.7596 | G149: =IFERROR(VLOOKUP($A149,Results_30d_Deltas!$A$2:$H$5000,7,FALSE)-E148,"") | H149: =IFERROR(VLOOKUP($A149,Results_30d_Deltas!$A$2:$H$5000,6,FALSE),"") | K149: =IF(B149=C149,"YES","NO") | IJ149: ez_manage.py:5575 top() | IK149: v12_quick_engine.py:3189 x4
A150: STDEV_BREAKOUT_PCTB_LONG | B150: 0 | E150: -13.3501 | F150: 2.5853 | G150: =IFERROR(VLOOKUP($A150,Results_30d_Deltas!$A$2:$H$5000,7,FALSE)-E149,"") | H150: =IFERROR(VLOOKUP($A150,Results_30d_Deltas!$A$2:$H$5000,6,FALSE),"") | K150: =IF(B150=C150,"YES","NO") | AP150: 0.8725 | AQ150: 2.4718 | AR150: 0.4886 | IJ150: ez_manage.py:4044 top() | IK150: v12_quick_engine.py:3280 x3
A151: STDEV_BREAKOUT_PCTB_LONG | B151: 0.5 | E151: -13.3501 | F151: 2.5853 | G151: =IFERROR(VLOOKUP($A151,Results_30d_Deltas!$A$2:$H$5000,7,FALSE)-E150,"") | H151: =IFERROR(VLOOKUP($A151,Results_30d_Deltas!$A$2:$H$5000,6,FALSE),"") | K151: =IF(B151=C151,"YES","NO") | AP151: 0.8725 | AQ151: 2.4718 | AR151: 0.4886 | IJ151: ez_manage.py:4044 top() | IK151: v12_quick_engine.py:3280 x3
A152: STDEV_BREAKOUT_PCTB_LONG | B152: 1.0 | E152: -13.3501 | F152: 2.5853 | G152: =IFERROR(VLOOKUP($A152,Results_30d_Deltas!$A$2:$H$5000,7,FALSE)-E151,"") | H152: =IFERROR(VLOOKUP($A152,Results_30d_Deltas!$A$2:$H$5000,6,FALSE),"") | K152: =IF(B152=C152,"YES","NO") | AP152: 0.8725 | AQ152: 2.4718 | AR152: 0.4886 | IJ152: ez_manage.py:4044 top() | IK152: v12_quick_engine.py:3280 x3
A153: STDEV_BREAKOUT_PCTB_LONG | B153: 2.0 | E153: -13.3501 | F153: 2.5853 | G153: =IFERROR(VLOOKUP($A153,Results_30d_Deltas!$A$2:$H$5000,7,FALSE)-E152,"") | H153: =IFERROR(VLOOKUP($A153,Results_30d_Deltas!$A$2:$H$5000,6,FALSE),"") | K153: =IF(B153=C153,"YES","NO") | AP153: 0.8725 | AQ153: 2.4718 | AR153: 0.4886 | IJ153: ez_manage.py:4044 top() | IK153: v12_quick_engine.py:3280 x3
A154: STDEV_BREAKOUT_PCTB_SHORT | B154: 0 | E154: -12.2254 | F154: 3.7101 | G154: =IFERROR(VLOOKUP($A154,Results_30d_Deltas!$A$2:$H$5000,7,FALSE)-E153,"") | H154: =IFERROR(VLOOKUP($A154,Results_30d_Deltas!$A$2:$H$5000,6,FALSE),"") | K154: =IF(B154=C154,"YES","NO") | AP154: 0.505 | AQ154: 0 | AR154: 2.1874 | IJ154: ez_manage.py:4045 top() | IK154: v12_quick_engine.py:3281 x3
A155: STDEV_BREAKOUT_PCTB_SHORT | B155: 0.5 | E155: -12.2254 | F155: 3.7101 | G155: =IFERROR(VLOOKUP($A155,Results_30d_Deltas!$A$2:$H$5000,7,FALSE)-E154,"") | H155: =IFERROR(VLOOKUP($A155,Results_30d_Deltas!$A$2:$H$5000,6,FALSE),"") | K155: =IF(B155=C155,"YES","NO") | AP155: 0.505 | AQ155: 0 | AR155: 2.1874 | IJ155: ez_manage.py:4045 top() | IK155: v12_quick_engine.py:3281 x3
A156: STDEV_BREAKOUT_PCTB_SHORT | B156: 1.0 | E156: -12.2254 | F156: 3.7101 | G156: =IFERROR(VLOOKUP($A156,Results_30d_Deltas!$A$2:$H$5000,7,FALSE)-E155,"") | H156: =IFERROR(VLOOKUP($A156,Results_30d_Deltas!$A$2:$H$5000,6,FALSE),"") | K156: =IF(B156=C156,"YES","NO") | AP156: 0.505 | AQ156: 0 | AR156: 2.1874 | IJ156: ez_manage.py:4045 top() | IK156: v12_quick_engine.py:3281 x3
A157: STDEV_BREAKOUT_PCTB_SHORT | B157: 2.0 | E157: -12.2254 | F157: 3.7101 | G157: =IFERROR(VLOOKUP($A157,Results_30d_Deltas!$A$2:$H$5000,7,FALSE)-E156,"") | H157: =IFERROR(VLOOKUP($A157,Results_30d_Deltas!$A$2:$H$5000,6,FALSE),"") | K157: =IF(B157=C157,"YES","NO") | AP157: 0.505 | AQ157: 0 | AR157: 2.1874 | IJ157: ez_manage.py:4045 top() | IK157: v12_quick_engine.py:3281 x3
A158: STDEV_SUPPRESS_EARLY_EXIT | B158: 0 | E158: -12.1759 | F158: 3.7596 | G158: =IFERROR(VLOOKUP($A158,Results_30d_Deltas!$A$2:$H$5000,7,FALSE)-E157,"") | H158: =IFERROR(VLOOKUP($A158,Results_30d_Deltas!$A$2:$H$5000,6,FALSE),"") | K158: =IF(B158=C158,"YES","NO") | IJ158: ez_manage.py:4060 top() | IK158: v12_quick_engine.py:3300 x2
A159: STDEV_SUPPRESS_EARLY_EXIT | B159: 0.5 | E159: -12.1759 | F159: 3.7596 | G159: =IFERROR(VLOOKUP($A159,Results_30d_Deltas!$A$2:$H$5000,7,FALSE)-E158,"") | H159: =IFERROR(VLOOKUP($A159,Results_30d_Deltas!$A$2:$H$5000,6,FALSE),"") | K159: =IF(B159=C159,"YES","NO") | IJ159: ez_manage.py:4060 top() | IK159: v12_quick_engine.py:3300 x2
A160: STDEV_SUPPRESS_EARLY_EXIT | B160: 1.0 | E160: -12.1759 | F160: 3.7596 | G160: =IFERROR(VLOOKUP($A160,Results_30d_Deltas!$A$2:$H$5000,7,FALSE)-E159,"") | H160: =IFERROR(VLOOKUP($A160,Results_30d_Deltas!$A$2:$H$5000,6,FALSE),"") | K160: =IF(B160=C160,"YES","NO") | IJ160: ez_manage.py:4060 top() | IK160: v12_quick_engine.py:3300 x2
A161: STDEV_SUPPRESS_EARLY_EXIT | B161: 2.0 | E161: -12.1759 | F161: 3.7596 | G161: =IFERROR(VLOOKUP($A161,Results_30d_Deltas!$A$2:$H$5000,7,FALSE)-E160,"") | H161: =IFERROR(VLOOKUP($A161,Results_30d_Deltas!$A$2:$H$5000,6,FALSE),"") | K161: =IF(B161=C161,"YES","NO") | IJ161: ez_manage.py:4060 top() | IK161: v12_quick_engine.py:3300 x2
A162: STOCH_CROSS_ENTRY_TRADIER | B162: False | E162: -13.3501 | F162: 2.5853 | G162: =IFERROR(VLOOKUP($A162,Results_30d_Deltas!$A$2:$H$5000,7,FALSE)-E161,"") | H162: =IFERROR(VLOOKUP($A162,Results_30d_Deltas!$A$2:$H$5000,6,FALSE),"") | K162: =IF(B162=C162,"YES","NO") | IJ162: ez_manage.py:5661 top() | IK162: v12_quick_engine.py:3305 x8
A163: STOCH_CROSS_ENTRY_TRADIER | B163: True | E163: -12.2254 | F163: 3.7101 | G163: =IFERROR(VLOOKUP($A163,Results_30d_Deltas!$A$2:$H$5000,7,FALSE)-E162,"") | H163: =IFERROR(VLOOKUP($A163,Results_30d_Deltas!$A$2:$H$5000,6,FALSE),"") | K163: =IF(B163=C163,"YES","NO") | IJ163: ez_manage.py:5661 top() | IK163: v12_quick_engine.py:3305 x8
A164: TRADIER_MFI_ENTRY_LONG_ENABLED | B164: False | E164: -12.2254 | F164: 3.7101 | G164: =IFERROR(VLOOKUP($A164,Results_30d_Deltas!$A$2:$H$5000,7,FALSE)-E163,"") | H164: =IFERROR(VLOOKUP($A164,Results_30d_Deltas!$A$2:$H$5000,6,FALSE),"") | K164: =IF(B164=C164,"YES","NO") | IJ164: ez_manage.py:5734 top() | IK164: v12_quick_engine.py:3411 x7
A165: TRADIER_MFI_ENTRY_LONG_ENABLED | B165: True | E165: -13.3501 | F165: 2.5853 | G165: =IFERROR(VLOOKUP($A165,Results_30d_Deltas!$A$2:$H$5000,7,FALSE)-E164,"") | H165: =IFERROR(VLOOKUP($A165,Results_30d_Deltas!$A$2:$H$5000,6,FALSE),"") | K165: =IF(B165=C165,"YES","NO") | IJ165: ez_manage.py:5734 top() | IK165: v12_quick_engine.py:3411 x7
A166: TRADIER_RSI2_EXIT_THRESHOLD_LONG | B166: 45.0 | E166: -12.1759 | F166: 3.7596 | G166: =IFERROR(VLOOKUP($A166,Results_30d_Deltas!$A$2:$H$5000,7,FALSE)-E165,"") | H166: =IFERROR(VLOOKUP($A166,Results_30d_Deltas!$A$2:$H$5000,6,FALSE),"") | K166: =IF(B166=C166,"YES","NO") | IJ166: ez_manage.py:5740 top() | IK166: v12_quick_engine.py:3437 x9
A167: TRADIER_RSI2_EXIT_THRESHOLD_LONG | B167: 67.5 | E167: -12.1759 | F167: 3.7596 | G167: =IFERROR(VLOOKUP($A167,Results_30d_Deltas!$A$2:$H$5000,7,FALSE)-E166,"") | H167: =IFERROR(VLOOKUP($A167,Results_30d_Deltas!$A$2:$H$5000,6,FALSE),"") | K167: =IF(B167=C167,"YES","NO") | IJ167: ez_manage.py:5740 top() | IK167: v12_quick_engine.py:3437 x9
A168: TRADIER_RSI2_EXIT_THRESHOLD_LONG | B168: 90.0 | E168: -12.1759 | F168: 3.7596 | G168: =IFERROR(VLOOKUP($A168,Results_30d_Deltas!$A$2:$H$5000,7,FALSE)-E167,"") | H168: =IFERROR(VLOOKUP($A168,Results_30d_Deltas!$A$2:$H$5000,6,FALSE),"") | K168: =IF(B168=C168,"YES","NO") | IJ168: ez_manage.py:5740 top() | IK168: v12_quick_engine.py:3437 x9
A169: TRADIER_RSI2_EXIT_THRESHOLD_LONG | B169: 112.5 | E169: -12.1759 | F169: 3.7596 | G169: =IFERROR(VLOOKUP($A169,Results_30d_Deltas!$A$2:$H$5000,7,FALSE)-E168,"") | H169: =IFERROR(VLOOKUP($A169,Results_30d_Deltas!$A$2:$H$5000,6,FALSE),"") | K169: =IF(B169=C169,"YES","NO") | IJ169: ez_manage.py:5740 top() | IK169: v12_quick_engine.py:3437 x9
... A175: TRADIER_RSI2_EXIT_THRESHOLD_SHORT | B175: 15.0 | E175: -13.4636 | F175: 2.4718 | G175: =IFERROR(VLOOKUP($A175,Results_30d_Deltas!$A$2:$H$5000,7,FALSE)-E174,"") | H175: =IFERROR(VLOOKUP($A175,Results_30d_Deltas!$A$2:$H$5000,6,FALSE),"") | K175: =IF(B175=C175,"YES","NO") | IJ175: ez_manage.py:5741 top() | IK175: v12_quick_engine.py:3438 x9
A176: TREND_MIN_GAIN_EXIT | B176: 0 | E176: -12.1759 | F176: 3.7596 | G176: =IFERROR(VLOOKUP($A176,Results_30d_Deltas!$A$2:$H$5000,7,FALSE)-E175,"") | H176: =IFERROR(VLOOKUP($A176,Results_30d_Deltas!$A$2:$H$5000,6,FALSE),"") | K176: =IF(B176=C176,"YES","NO") | AK176: 0.436 | AL176: 3.7596 | AM176: 0.8725 | IJ176: ez_manage.py:4205 top() | IK176: v12_quick_engine.py:3545 x2
A177: TREND_MIN_GAIN_EXIT | B177: 0.5 | E177: -12.1759 | F177: 3.7596 | G177: =IFERROR(VLOOKUP($A177,Results_30d_Deltas!$A$2:$H$5000,7,FALSE)-E176,"") | H177: =IFERROR(VLOOKUP($A177,Results_30d_Deltas!$A$2:$H$5000,6,FALSE),"") | K177: =IF(B177=C177,"YES","NO") | AK177: 0.436 | AL177: 3.7596 | AM177: 0.8725 | IJ177: ez_manage.py:4205 top() | IK177: v12_quick_engine.py:3545 x2
A178: TREND_MIN_GAIN_EXIT | B178: 1.0 | E178: -12.1759 | F178: 3.7596 | G178: =IFERROR(VLOOKUP($A178,Results_30d_Deltas!$A$2:$H$5000,7,FALSE)-E177,"") | H178: =IFERROR(VLOOKUP($A178,Results_30d_Deltas!$A$2:$H$5000,6,FALSE),"") | K178: =IF(B178=C178,"YES","NO") | AK178: 0.436 | AL178: 3.7596 | AM178: 0.8725 | IJ178: ez_manage.py:4205 top() | IK178: v12_quick_engine.py:3545 x2
A179: TREND_MIN_GAIN_EXIT | B179: 2.0 | E179: -12.1759 | F179: 3.7596 | G179: =IFERROR(VLOOKUP($A179,Results_30d_Deltas!$A$2:$H$5000,7,FALSE)-E178,"") | H179: =IFERROR(VLOOKUP($A179,Results_30d_Deltas!$A$2:$H$5000,6,FALSE),"") | K179: =IF(B179=C179,"YES","NO") | AK179: 0.436 | AL179: 3.7596 | AM179: 0.8725 | IJ179: ez_manage.py:4205 top() | IK179: v12_quick_engine.py:3545 x2
...

Sheet ENTRY_CONFIRMATION_GATES
A1: 03 ENTRY_CONFIRMATION_GATES - 4 bases -> 11 rows - 231 per-row FULLY CONNECTED
A2: Switch | B2: default | C2: override | D2: Family | E2: BASELINE | F2: VECTOR_DELTA | G2: LIVE_DELTA | H2: LIVE_SHARPE | I2: REAL_COMPLETE | J2: PER_ROW_FILTERS | K2: is_default (backup if bold lost) | L2: ATR_TRAIL_FILTER_TF=OFF | M2: ATR_TRAIL_FILTER_TF=D | N2: ATR_TRAIL_FILTER_TF=4h | O2: ATR_TRAIL_FILTER_TF=1h | P2: ATR_TRAIL_FILTER_TF=15m | Q2: BAR_PATTERNS_FILTER_TF=OFF | R2: BAR_PATTERNS_FILTER_TF=D | S2: BAR_PATTERNS_FILTER_TF=4h | T2: BAR_PATTERNS_FILTER_TF=1h | U2: BAR_PATTERNS_FILTER_TF=15m | V2: BB_PULLBACK_GATE_FILTER_TF=OFF | W2: BB_PULLBACK_GATE_FILTER_TF=D | X2: BB_PULLBACK_GATE_FILTER_TF=4h | Y2: BB_PULLBACK_GATE_FILTER_TF=1h | Z2: BB_PULLBACK_GATE_FILTER_TF=15m | AA2: BB_RECOVERY_ENTRY_FILTER_TF=OFF | AB2: BB_RECOVERY_ENTRY_FILTER_TF=D | AC2: BB_RECOVERY_ENTRY_FILTER_TF=4h | AD2: BB_RECOVERY_ENTRY_FILTER_TF=1h | AE2: BB_RECOVERY_ENTRY_FILTER_TF=15m | AF2: BB_RECOVERY_FILTER_TF=OFF | AG2: BB_RECOVERY_FILTER_TF=D | AH2: BB_RECOVERY_FILTER_TF=4h | AI2: BB_RECOVERY_FILTER_TF=1h | AJ2: BB_RECOVERY_FILTER_TF=15m | AK2: BREAKEVEN_GAIN_EROSION_FILTER_TF=OFF | AL2: BREAKEVEN_GAIN_EROSION_FILTER_TF=D | AM2: BREAKEVEN_GAIN_EROSION_FILTER_TF=4h | AN2: BREAKEVEN_GAIN_EROSION_FILTER_TF=1h | AO2: BREAKEVEN_GAIN_EROSION_FILTER_TF=15m | AP2: BREAKOUT_RETEST_FILTER_TF=OFF | AQ2: BREAKOUT_RETEST_FILTER_TF=D | AR2: BREAKOUT_RETEST_FILTER_TF=4h | AS2: BREAKOUT_RETEST_FILTER_TF=1h | AT2: BREAKOUT_RETEST_FILTER_TF=15m | AU2: BT_WT_CROSS_LADDER_FILTER_TF=OFF | AV2: BT_WT_CROSS_LADDER_FILTER_TF=D | AW2: BT_WT_CROSS_LADDER_FILTER_TF=4h | AX2: BT_WT_CROSS_LADDER_FILTER_TF=1h | AY2: BT_WT_CROSS_LADDER_FILTER_TF=15m | AZ2: CANDLE_PATTERN_STOPS_FILTER_TF=OFF | BA2: CANDLE_PATTERN_STOPS_FILTER_TF=D | BB2: CANDLE_PATTERN_STOPS_FILTER_TF=4h | BC2: CANDLE_PATTERN_STOPS_FILTER_TF=1h | BD2: CANDLE_PATTERN_STOPS_FILTER_TF=15m | BE2: CIRCUIT_SHARPE_GATES_FILTER_TF=OFF | BF2: CIRCUIT_SHARPE_GATES_FILTER_TF=D | BG2: CIRCUIT_SHARPE_GATES_FILTER_TF=4h | BH2: CIRCUIT_SHARPE_GATES_FILTER_TF=1h | BI2: CIRCUIT_SHARPE_GATES_FILTER_TF=15m | BJ2: DC_BREACH_REDUCE_FILTER_TF=OFF | BK2: DC_BREACH_REDUCE_FILTER_TF=D | BL2: DC_BREACH_REDUCE_FILTER_TF=4h | BM2: DC_BREACH_REDUCE_FILTER_TF=1h | BN2: DC_BREACH_REDUCE_FILTER_TF=15m | BO2: DC_BREAK_FILTER_TF=OFF | BP2: DC_BREAK_FILTER_TF=D | BQ2: DC_BREAK_FILTER_TF=4h | BR2: DC_BREAK_FILTER_TF=1h | BS2: DC_BREAK_FILTER_TF=15m | BT2: DC_MOMENTUM_BOTA_SCORER_FILTER_TF=OFF | BU2: DC_MOMENTUM_BOTA_SCORER_FILTER_TF=D | BV2: DC_MOMENTUM_BOTA_SCORER_FILTER_TF=4h | BW2: DC_MOMENTUM_BOTA_SCORER_FILTER_TF=1h | BX2: DC_MOMENTUM_BOTA_SCORER_FILTER_TF=15m | BY2: DELTA_ENGINE_FILTER_TF=OFF | BZ2: DELTA_ENGINE_FILTER_TF=D | CA2: DELTA_ENGINE_FILTER_TF=4h | CB2: DELTA_ENGINE_FILTER_TF=1h | CC2: DELTA_ENGINE_FILTER_TF=15m | CD2: EMA_9_21_FILTER_FILTER_TF=OFF | CE2: EMA_9_21_FILTER_FILTER_TF=D | CF2: EMA_9_21_FILTER_FILTER_TF=4h | CG2: EMA_9_21_FILTER_FILTER_TF=1h | CH2: EMA_9_21_FILTER_FILTER_TF=15m | CI2: EMA_BLANKET_FILTER_FILTER_TF=OFF | CJ2: EMA_BLANKET_FILTER_FILTER_TF=D | CK2: EMA_BLANKET_FILTER_FILTER_TF=4h | CL2: EMA_BLANKET_FILTER_FILTER_TF=1h | CM2: EMA_BLANKET_FILTER_FILTER_TF=15m | CN2: EMERGENCY_BRAKE_FILTER_TF=OFF | CO2: EMERGENCY_BRAKE_FILTER_TF=D | CP2: EMERGENCY_BRAKE_FILTER_TF=4h | CQ2: EMERGENCY_BRAKE_FILTER_TF=1h | CR2: EMERGENCY_BRAKE_FILTER_TF=15m | CS2: EXIT_R1_R2_FILTER_TF=OFF | CT2: EXIT_R1_R2_FILTER_TF=D | CU2: EXIT_R1_R2_FILTER_TF=4h | CV2: EXIT_R1_R2_FILTER_TF=1h | CW2: EXIT_R1_R2_FILTER_TF=15m | CX2: EXIT_TIGHT_BREAKOUT_SCORER_FILTER_TF=OFF | CY2: EXIT_TIGHT_BREAKOUT_SCORER_FILTER_TF=D | CZ2: EXIT_TIGHT_BREAKOUT_SCORER_FILTER_TF=4h | DA2: EXIT_TIGHT_BREAKOUT_SCORER_FILTER_TF=1h | DB2: EXIT_TIGHT_BREAKOUT_SCORER_FILTER_TF=15m | DC2: EXIT_TOP_FADE_FILTER_TF=OFF | DD2: EXIT_TOP_FADE_FILTER_TF=D | DE2: EXIT_TOP_FADE_FILTER_TF=4h | DF2: EXIT_TOP_FADE_FILTER_TF=1h | DG2: EXIT_TOP_FADE_FILTER_TF=15m | DH2: EXIT_TO_REDUCE_ADAPTER_FILTER_TF=OFF | DI2: EXIT_TO_REDUCE_ADAPTER_FILTER_TF=D | DJ2: EXIT_TO_REDUCE_ADAPTER_FILTER_TF=4h | DK2: EXIT_TO_REDUCE_ADAPTER_FILTER_TF=1h | DL2: EXIT_TO_REDUCE_ADAPTER_FILTER_TF=15m | DM2: FAST_RISER_FILTER_TF=OFF | DN2: FAST_RISER_FILTER_TF=D | DO2: FAST_RISER_FILTER_TF=4h | DP2: FAST_RISER_FILTER_TF=1h | DQ2: FAST_RISER_FILTER_TF=15m | DR2: FH_MOMENTUM_FILTER_TF=OFF | DS2: FH_MOMENTUM_FILTER_TF=D | DT2: FH_MOMENTUM_FILTER_TF=4h | DU2: FH_MOMENTUM_FILTER_TF=1h | DV2: FH_MOMENTUM_FILTER_TF=15m | DW2: FIRST_OPEN_THROTTLE_FILTER_TF=OFF | DX2: FIRST_OPEN_THROTTLE_FILTER_TF=D | DY2: FIRST_OPEN_THROTTLE_FILTER_TF=4h | DZ2: FIRST_OPEN_THROTTLE_FILTER_TF=1h | EA2: FIRST_OPEN_THROTTLE_FILTER_TF=15m | EB2: FROZEN_STOP_FILTER_TF=OFF | EC2: FROZEN_STOP_FILTER_TF=D | ED2: FROZEN_STOP_FILTER_TF=4h | EE2: FROZEN_STOP_FILTER_TF=1h | EF2: FROZEN_STOP_FILTER_TF=15m | EG2: GOLDEN_RULE_ENFORCE_FILTER_TF=OFF | EH2: GOLDEN_RULE_ENFORCE_FILTER_TF=D | EI2: GOLDEN_RULE_ENFORCE_FILTER_TF=4h | EJ2: GOLDEN_RULE_ENFORCE_FILTER_TF=1h | EK2: GOLDEN_RULE_ENFORCE_FILTER_TF=15m | EL2: GOLDEN_RULE_HTF_VOTE_FILTER_TF=OFF | EM2: GOLDEN_RULE_HTF_VOTE_FILTER_TF=D | EN2: GOLDEN_RULE_HTF_VOTE_FILTER_TF=4h | EO2: GOLDEN_RULE_HTF_VOTE_FILTER_TF=1h | EP2: GOLDEN_RULE_HTF_VOTE_FILTER_TF=15m | EQ2: GR_FILTER_VEC_FILTER_TF=OFF | ER2: GR_FILTER_VEC_FILTER_TF=D | ES2: GR_FILTER_VEC_FILTER_TF=4h | ET2: GR_FILTER_VEC_FILTER_TF=1h | EU2: GR_FILTER_VEC_FILTER_TF=15m | EV2: GR_V5_STATE_FILTER_TF=OFF | EW2: GR_V5_STATE_FILTER_TF=D | EX2: GR_V5_STATE_FILTER_TF=4h | EY2: GR_V5_STATE_FILTER_TF=1h | EZ2: GR_V5_STATE_FILTER_TF=15m | FA2: HAIKU_WINNER_FILTER_TF=OFF | FB2: HAIKU_WINNER_FILTER_TF=D | FC2: HAIKU_WINNER_FILTER_TF=4h | FD2: HAIKU_WINNER_FILTER_TF=1h | FE2: HAIKU_WINNER_FILTER_TF=15m | FF2: LH_HL_FILTER_TF_REQ=2 | FG2: LH_HL_FILTER_TF_REQ=2_ALT | FH2: LIVE_ENTRY_ENGINE_FILTER_TF=OFF | FI2: LIVE_ENTRY_ENGINE_FILTER_TF=D | FJ2: LIVE_ENTRY_ENGINE_FILTER_TF=4h | FK2: LIVE_ENTRY_ENGINE_FILTER_TF=1h | FL2: LIVE_ENTRY_ENGINE_FILTER_TF=15m | FM2: LIVE_ONLY_SIGNALS_BATCH5_FILTER_TF=OFF | FN2: LIVE_ONLY_SIGNALS_BATCH5_FILTER_TF=D | FO2: LIVE_ONLY_SIGNALS_BATCH5_FILTER_TF=4h | FP2: LIVE_ONLY_SIGNALS_BATCH5_FILTER_TF=1h | FQ2: LIVE_ONLY_SIGNALS_BATCH5_FILTER_TF=15m | FR2: MANDATORY_REENTRY_WT_FILTER_TF_MODE=15m_only | FS2: MANDATORY_REENTRY_WT_FILTER_TF_MODE=15m_only_ALT | FT2: MOM3_FILTER_TF=OFF | FU2: MOM3_FILTER_TF=D | FV2: MOM3_FILTER_TF=4h | FW2: MOM3_FILTER_TF=1h | FX2: MOM3_FILTER_TF=15m | FY2: MOMENTUM_BREAKOUT_FILTER_TF=OFF | FZ2: MOMENTUM_BREAKOUT_FILTER_TF=D | GA2: MOMENTUM_BREAKOUT_FILTER_TF=4h | GB2: MOMENTUM_BREAKOUT_FILTER_TF=1h | GC2: MOMENTUM_BREAKOUT_FILTER_TF=15m | GD2: MTF_ARMED_ENTRIES_FILTER_TF=OFF | GE2: MTF_ARMED_ENTRIES_FILTER_TF=D | GF2: MTF_ARMED_ENTRIES_FILTER_TF=4h | GG2: MTF_ARMED_ENTRIES_FILTER_TF=1h | GH2: MTF_ARMED_ENTRIES_FILTER_TF=15m | GI2: MTF_ATR_TRAIL_FILTER_TF=OFF | GJ2: MTF_ATR_TRAIL_FILTER_TF=D | GK2: MTF_ATR_TRAIL_FILTER_TF=4h | GL2: MTF_ATR_TRAIL_FILTER_TF=1h | GM2: MTF_ATR_TRAIL_FILTER_TF=15m | GN2: MTF_DC_REJECT_FILTER_TF=OFF | GO2: MTF_DC_REJECT_FILTER_TF=D | GP2: MTF_DC_REJECT_FILTER_TF=4h | GQ2: MTF_DC_REJECT_FILTER_TF=1h | GR2: MTF_DC_REJECT_FILTER_TF=15m | GS2: NEWBORN_LOSS_KILL_FILTER_TF=OFF | GT2: NEWBORN_LOSS_KILL_FILTER_TF=D | GU2: NEWBORN_LOSS_KILL_FILTER_TF=4h | GV2: NEWBORN_LOSS_KILL_FILTER_TF=1h | GW2: NEWBORN_LOSS_KILL_FILTER_TF=15m | GX2: NEWBORN_PROTECT_FILTER_TF=OFF | GY2: NEWBORN_PROTECT_FILTER_TF=D | GZ2: NEWBORN_PROTECT_FILTER_TF=4h | HA2: NEWBORN_PROTECT_FILTER_TF=1h | HB2: NEWBORN_PROTECT_FILTER_TF=15m | HC2: NOLOSS_BYPASS_WT5OF5_FILTER_TF=OFF | HD2: NOLOSS_BYPASS_WT5OF5_FILTER_TF=D | HE2: NOLOSS_BYPASS_WT5OF5_FILTER_TF=4h | HF2: NOLOSS_BYPASS_WT5OF5_FILTER_TF=1h | HG2: NOLOSS_BYPASS_WT5OF5_FILTER_TF=15m | HH2: OPEN_INTENT_SIZE_GATES_FILTER_TF=OFF | HI2: OPEN_INTENT_SIZE_GATES_FILTER_TF=D | HJ2: OPEN_INTENT_SIZE_GATES_FILTER_TF=4h | HK2: OPEN_INTENT_SIZE_GATES_FILTER_TF=1h | HL2: OPEN_INTENT_SIZE_GATES_FILTER_TF=15m | HM2: PARTIAL_PROFIT_LOCK_V2_FILTER_TF=OFF | HN2: PARTIAL_PROFIT_LOCK_V2_FILTER_TF=D | HO2: PARTIAL_PROFIT_LOCK_V2_FILTER_TF=4h | HP2: PARTIAL_PROFIT_LOCK_V2_FILTER_TF=1h | HQ2: PARTIAL_PROFIT_LOCK_V2_FILTER_TF=15m | HR2: PEAK_GIVEBACK_BE_EROSION_FILTER_TF=OFF | HS2: PEAK_GIVEBACK_BE_EROSION_FILTER_TF=D | HT2: PEAK_GIVEBACK_BE_EROSION_FILTER_TF=4h | HU2: PEAK_GIVEBACK_BE_EROSION_FILTER_TF=1h | HV2: PEAK_GIVEBACK_BE_EROSION_FILTER_TF=15m | HW2: WT_15M_BOUNCE_BB_MAX=0.95 | HX2: WT_15M_BOUNCE_BB_MAX=0.9 | HY2: WT_15M_BOUNCE_BB_MAX=0.8 | HZ2: WT_15M_BOUNCE_BB_MIN=0.05 | IA2: WT_15M_BOUNCE_BB_MIN=0.1 | IB2: WT_15M_BOUNCE_BB_MIN=0.2 | IC2: WT_15M_BOUNCE_HIGH_1H_GT_PREV=True | ID2: WT_15M_BOUNCE_HIGH_1H_GT_PREV=False | IE2: WT_15M_BOUNCE_LOW_1H_GT_PREV=True | IF2: WT_15M_BOUNCE_LOW_1H_GT_PREV=False | IG2: WT_15M_BOUNCE_REL_VOL_GT_1=True | IH2: WT_15M_BOUNCE_REL_VOL_GT_1=False | II2: Live Location | IJ2: Vec Hook | IK2: Type | IL2: Correct Options
A3: GR_FILTER_ALL_ENTRIES | B3: 0.0 | E3: -12.1759 | F3: 3.7596 | G3: =IFERROR(VLOOKUP($A3,Results_30d_Deltas!$A$2:$H$5000,7,FALSE)-E3,"") | H3: =IFERROR(VLOOKUP($A3,Results_30d_Deltas!$A$2:$H$5000,6,FALSE),"") | K3: =IF(B3=C3,"YES","NO") | V3: 2.4718 | W3: 0.8725 | X3: 3.7596 | IJ3: ez_manage.py:4768 top() | IK3: v12_quick_engine.py:1912 x3
A4: GR_FILTER_ALL_ENTRIES | B4: 0.0_ALT | E4: -12.1759 | F4: 3.7596 | G4: =IFERROR(VLOOKUP($A4,Results_30d_Deltas!$A$2:$H$5000,7,FALSE)-E3,"") | H4: =IFERROR(VLOOKUP($A4,Results_30d_Deltas!$A$2:$H$5000,6,FALSE),"") | K4: =IF(B4=C4,"YES","NO") | V4: 2.4718 | W4: 0.8725 | X4: 3.7596 | IJ4: ez_manage.py:4768 top() | IK4: v12_quick_engine.py:1912 x3
A5: GR_FILTER_VEC_ENABLED | B5: False | E5: -12.1759 | F5: 3.7596 | G5: =IFERROR(VLOOKUP($A5,Results_30d_Deltas!$A$2:$H$5000,7,FALSE)-E4,"") | H5: =IFERROR(VLOOKUP($A5,Results_30d_Deltas!$A$2:$H$5000,6,FALSE),"") | K5: =IF(B5=C5,"YES","NO") | IJ5: ez_manage.py:6003 top() | IK5: v12_quick_engine.py:4261 x2
A6: GR_FILTER_VEC_ENABLED | B6: True | E6: -13.3501 | F6: 2.5853 | G6: =IFERROR(VLOOKUP($A6,Results_30d_Deltas!$A$2:$H$5000,7,FALSE)-E5,"") | H6: =IFERROR(VLOOKUP($A6,Results_30d_Deltas!$A$2:$H$5000,6,FALSE),"") | K6: =IF(B6=C6,"YES","NO") | IJ6: ez_manage.py:6003 top() | IK6: v12_quick_engine.py:4261 x2
A7: GR_FILTER_VEC_FILTER_TF | B7: OFF | E7: -12.1759 | F7: 3.7596 | G7: =IFERROR(VLOOKUP($A7,Results_30d_Deltas!$A$2:$H$5000,7,FALSE)-E6,"") | H7: =IFERROR(VLOOKUP($A7,Results_30d_Deltas!$A$2:$H$5000,6,FALSE),"") | K7: =IF(B7=C7,"YES","NO") | IJ7: ez_manage.py:6004 top() | IK7: v12_quick_engine.py:112 x3
A8: GR_FILTER_VEC_FILTER_TF | B8: D | E8: -12.1759 | F8: 3.7596 | G8: =IFERROR(VLOOKUP($A8,Results_30d_Deltas!$A$2:$H$5000,7,FALSE)-E7,"") | H8: =IFERROR(VLOOKUP($A8,Results_30d_Deltas!$A$2:$H$5000,6,FALSE),"") | K8: =IF(B8=C8,"YES","NO") | IJ8: ez_manage.py:6004 top() | IK8: v12_quick_engine.py:112 x3
A9: GR_FILTER_VEC_FILTER_TF | B9: 4h | E9: -12.1759 | F9: 3.7596 | G9: =IFERROR(VLOOKUP($A9,Results_30d_Deltas!$A$2:$H$5000,7,FALSE)-E8,"") | H9: =IFERROR(VLOOKUP($A9,Results_30d_Deltas!$A$2:$H$5000,6,FALSE),"") | K9: =IF(B9=C9,"YES","NO") | IJ9: ez_manage.py:6004 top() | IK9: v12_quick_engine.py:112 x3
A10: GR_FILTER_VEC_FILTER_TF | B10: 1h | E10: -12.1759 | F10: 3.7596 | G10: =IFERROR(VLOOKUP($A10,Results_30d_Deltas!$A$2:$H$5000,7,FALSE)-E9,"") | H10: =IFERROR(VLOOKUP($A10,Results_30d_Deltas!$A$2:$H$5000,6,FALSE),"") | K10: =IF(B10=C10,"YES","NO") | IJ10: ez_manage.py:6004 top() | IK10: v12_quick_engine.py:112 x3
A11: GR_FILTER_VEC_FILTER_TF | B11: 15m | E11: -12.1759 | F11: 3.7596 | G11: =IFERROR(VLOOKUP($A11,Results_30d_Deltas!$A$2:$H$5000,7,FALSE)-E10,"") | H11: =IFERROR(VLOOKUP($A11,Results_30d_Deltas!$A$2:$H$5000,6,FALSE),"") | K11: =IF(B11=C11,"YES","NO") | IJ11: ez_manage.py:6004 top() | IK11: v12_quick_engine.py:112 x3
A12: WT_AGAINST_FILTER_ENABLED | B12: False | E12: -13.4689 | F12: 2.4666 | G12: =IFERROR(VLOOKUP($A12,Results_30d_Deltas!$A$2:$H$5000,7,FALSE)-E11,"") | H12: =IFERROR(VLOOKUP($A12,Results_30d_Deltas!$A$2:$H$5000,6,FALSE),"") | K12: =IF(B12=C12,"YES","NO") | IJ12: ez_manage.py:6084 top() | IK12: v12_quick_engine.py:4291 x2
A13: WT_AGAINST_FILTER_ENABLED | B13: True | E13: -13.3501 | F13: 2.5853 | G13: =IFERROR(VLOOKUP($A13,Results_30d_Deltas!$A$2:$H$5000,7,FALSE)-E12,"") | H13: =IFERROR(VLOOKUP($A13,Results_30d_Deltas!$A$2:$H$5000,6,FALSE),"") | K13: =IF(B13=C13,"YES","NO") | IJ13: ez_manage.py:6084 top() | IK13: v12_quick_engine.py:4291 x2

Sheet EXIT_STRUCTURAL
A1: 04 EXIT_STRUCTURAL - 2 bases -> 6 rows - 231 per-row FULLY CONNECTED
A2: Switch | B2: default | C2: override | D2: Family | E2: BASELINE | F2: VECTOR_DELTA | G2: LIVE_DELTA | H2: LIVE_SHARPE | I2: REAL_COMPLETE | J2: PER_ROW_FILTERS | K2: is_default (backup if bold lost) | L2: ATR_TRAIL_FILTER_TF=OFF | M2: ATR_TRAIL_FILTER_TF=D | N2: ATR_TRAIL_FILTER_TF=4h | O2: ATR_TRAIL_FILTER_TF=1h | P2: ATR_TRAIL_FILTER_TF=15m | Q2: BAR_PATTERNS_FILTER_TF=OFF | R2: BAR_PATTERNS_FILTER_TF=D | S2: BAR_PATTERNS_FILTER_TF=4h | T2: BAR_PATTERNS_FILTER_TF=1h | U2: BAR_PATTERNS_FILTER_TF=15m | V2: BB_PULLBACK_GATE_FILTER_TF=OFF | W2: BB_PULLBACK_GATE_FILTER_TF=D | X2: BB_PULLBACK_GATE_FILTER_TF=4h | Y2: BB_PULLBACK_GATE_FILTER_TF=1h | Z2: BB_PULLBACK_GATE_FILTER_TF=15m | AA2: BB_RECOVERY_ENTRY_FILTER_TF=OFF | AB2: BB_RECOVERY_ENTRY_FILTER_TF=D | AC2: BB_RECOVERY_ENTRY_FILTER_TF=4h | AD2: BB_RECOVERY_ENTRY_FILTER_TF=1h | AE2: BB_RECOVERY_ENTRY_FILTER_TF=15m | AF2: BB_RECOVERY_FILTER_TF=OFF | AG2: BB_RECOVERY_FILTER_TF=D | AH2: BB_RECOVERY_FILTER_TF=4h | AI2: BB_RECOVERY_FILTER_TF=1h | AJ2: BB_RECOVERY_FILTER_TF=15m | AK2: BREAKEVEN_GAIN_EROSION_FILTER_TF=OFF | AL2: BREAKEVEN_GAIN_EROSION_FILTER_TF=D | AM2: BREAKEVEN_GAIN_EROSION_FILTER_TF=4h | AN2: BREAKEVEN_GAIN_EROSION_FILTER_TF=1h | AO2: BREAKEVEN_GAIN_EROSION_FILTER_TF=15m | AP2: BREAKOUT_RETEST_FILTER_TF=OFF | AQ2: BREAKOUT_RETEST_FILTER_TF=D | AR2: BREAKOUT_RETEST_FILTER_TF=4h | AS2: BREAKOUT_RETEST_FILTER_TF=1h | AT2: BREAKOUT_RETEST_FILTER_TF=15m | AU2: BT_WT_CROSS_LADDER_FILTER_TF=OFF | AV2: BT_WT_CROSS_LADDER_FILTER_TF=D | AW2: BT_WT_CROSS_LADDER_FILTER_TF=4h | AX2: BT_WT_CROSS_LADDER_FILTER_TF=1h | AY2: BT_WT_CROSS_LADDER_FILTER_TF=15m | AZ2: CANDLE_PATTERN_STOPS_FILTER_TF=OFF | BA2: CANDLE_PATTERN_STOPS_FILTER_TF=D | BB2: CANDLE_PATTERN_STOPS_FILTER_TF=4h | BC2: CANDLE_PATTERN_STOPS_FILTER_TF=1h | BD2: CANDLE_PATTERN_STOPS_FILTER_TF=15m | BE2: CIRCUIT_SHARPE_GATES_FILTER_TF=OFF | BF2: CIRCUIT_SHARPE_GATES_FILTER_TF=D | BG2: CIRCUIT_SHARPE_GATES_FILTER_TF=4h | BH2: CIRCUIT_SHARPE_GATES_FILTER_TF=1h | BI2: CIRCUIT_SHARPE_GATES_FILTER_TF=15m | BJ2: DC_BREACH_REDUCE_FILTER_TF=OFF | BK2: DC_BREACH_REDUCE_FILTER_TF=D | BL2: DC_BREACH_REDUCE_FILTER_TF=4h | BM2: DC_BREACH_REDUCE_FILTER_TF=1h | BN2: DC_BREACH_REDUCE_FILTER_TF=15m | BO2: DC_BREAK_FILTER_TF=OFF | BP2: DC_BREAK_FILTER_TF=D | BQ2: DC_BREAK_FILTER_TF=4h | BR2: DC_BREAK_FILTER_TF=1h | BS2: DC_BREAK_FILTER_TF=15m | BT2: DC_MOMENTUM_BOTA_SCORER_FILTER_TF=OFF | BU2: DC_MOMENTUM_BOTA_SCORER_FILTER_TF=D | BV2: DC_MOMENTUM_BOTA_SCORER_FILTER_TF=4h | BW2: DC_MOMENTUM_BOTA_SCORER_FILTER_TF=1h | BX2: DC_MOMENTUM_BOTA_SCORER_FILTER_TF=15m | BY2: DELTA_ENGINE_FILTER_TF=OFF | BZ2: DELTA_ENGINE_FILTER_TF=D | CA2: DELTA_ENGINE_FILTER_TF=4h | CB2: DELTA_ENGINE_FILTER_TF=1h | CC2: DELTA_ENGINE_FILTER_TF=15m | CD2: EMA_9_21_FILTER_FILTER_TF=OFF | CE2: EMA_9_21_FILTER_FILTER_TF=D | CF2: EMA_9_21_FILTER_FILTER_TF=4h | CG2: EMA_9_21_FILTER_FILTER_TF=1h | CH2: EMA_9_21_FILTER_FILTER_TF=15m | CI2: EMA_BLANKET_FILTER_FILTER_TF=OFF | CJ2: EMA_BLANKET_FILTER_FILTER_TF=D | CK2: EMA_BLANKET_FILTER_FILTER_TF=4h | CL2: EMA_BLANKET_FILTER_FILTER_TF=1h | CM2: EMA_BLANKET_FILTER_FILTER_TF=15m | CN2: EMERGENCY_BRAKE_FILTER_TF=OFF | CO2: EMERGENCY_BRAKE_FILTER_TF=D | CP2: EMERGENCY_BRAKE_FILTER_TF=4h | CQ2: EMERGENCY_BRAKE_FILTER_TF=1h | CR2: EMERGENCY_BRAKE_FILTER_TF=15m | CS2: EXIT_R1_R2_FILTER_TF=OFF | CT2: EXIT_R1_R2_FILTER_TF=D | CU2: EXIT_R1_R2_FILTER_TF=4h | CV2: EXIT_R1_R2_FILTER_TF=1h | CW2: EXIT_R1_R2_FILTER_TF=15m | CX2: EXIT_TIGHT_BREAKOUT_SCORER_FILTER_TF=OFF | CY2: EXIT_TIGHT_BREAKOUT_SCORER_FILTER_TF=D | CZ2: EXIT_TIGHT_BREAKOUT_SCORER_FILTER_TF=4h | DA2: EXIT_TIGHT_BREAKOUT_SCORER_FILTER_TF=1h | DB2: EXIT_TIGHT_BREAKOUT_SCORER_FILTER_TF=15m | DC2: EXIT_TOP_FADE_FILTER_TF=OFF | DD2: EXIT_TOP_FADE_FILTER_TF=D | DE2: EXIT_TOP_FADE_FILTER_TF=4h | DF2: EXIT_TOP_FADE_FILTER_TF=1h | DG2: EXIT_TOP_FADE_FILTER_TF=15m | DH2: EXIT_TO_REDUCE_ADAPTER_FILTER_TF=OFF | DI2: EXIT_TO_REDUCE_ADAPTER_FILTER_TF=D | DJ2: EXIT_TO_REDUCE_ADAPTER_FILTER_TF=4h | DK2: EXIT_TO_REDUCE_ADAPTER_FILTER_TF=1h | DL2: EXIT_TO_REDUCE_ADAPTER_FILTER_TF=15m | DM2: FAST_RISER_FILTER_TF=OFF | DN2: FAST_RISER_FILTER_TF=D | DO2: FAST_RISER_FILTER_TF=4h | DP2: FAST_RISER_FILTER_TF=1h | DQ2: FAST_RISER_FILTER_TF=15m | DR2: FH_MOMENTUM_FILTER_TF=OFF | DS2: FH_MOMENTUM_FILTER_TF=D | DT2: FH_MOMENTUM_FILTER_TF=4h | DU2: FH_MOMENTUM_FILTER_TF=1h | DV2: FH_MOMENTUM_FILTER_TF=15m | DW2: FIRST_OPEN_THROTTLE_FILTER_TF=OFF | DX2: FIRST_OPEN_THROTTLE_FILTER_TF=D | DY2: FIRST_OPEN_THROTTLE_FILTER_TF=4h | DZ2: FIRST_OPEN_THROTTLE_FILTER_TF=1h | EA2: FIRST_OPEN_THROTTLE_FILTER_TF=15m | EB2: FROZEN_STOP_FILTER_TF=OFF | EC2: FROZEN_STOP_FILTER_TF=D | ED2: FROZEN_STOP_FILTER_TF=4h | EE2: FROZEN_STOP_FILTER_TF=1h | EF2: FROZEN_STOP_FILTER_TF=15m | EG2: GOLDEN_RULE_ENFORCE_FILTER_TF=OFF | EH2: GOLDEN_RULE_ENFORCE_FILTER_TF=D | EI2: GOLDEN_RULE_ENFORCE_FILTER_TF=4h | EJ2: GOLDEN_RULE_ENFORCE_FILTER_TF=1h | EK2: GOLDEN_RULE_ENFORCE_FILTER_TF=15m | EL2: GOLDEN_RULE_HTF_VOTE_FILTER_TF=OFF | EM2: GOLDEN_RULE_HTF_VOTE_FILTER_TF=D | EN2: GOLDEN_RULE_HTF_VOTE_FILTER_TF=4h | EO2: GOLDEN_RULE_HTF_VOTE_FILTER_TF=1h | EP2: GOLDEN_RULE_HTF_VOTE_FILTER_TF=15m | EQ2: GR_FILTER_VEC_FILTER_TF=OFF | ER2: GR_FILTER_VEC_FILTER_TF=D | ES2: GR_FILTER_VEC_FILTER_TF=4h | ET2: GR_FILTER_VEC_FILTER_TF=1h | EU2: GR_FILTER_VEC_FILTER_TF=15m | EV2: GR_V5_STATE_FILTER_TF=OFF | EW2: GR_V5_STATE_FILTER_TF=D | EX2: GR_V5_STATE_FILTER_TF=4h | EY2: GR_V5_STATE_FILTER_TF=1h | EZ2: GR_V5_STATE_FILTER_TF=15m | FA2: HAIKU_WINNER_FILTER_TF=OFF | FB2: HAIKU_WINNER_FILTER_TF=D | FC2: HAIKU_WINNER_FILTER_TF=4h | FD2: HAIKU_WINNER_FILTER_TF=1h | FE2: HAIKU_WINNER_FILTER_TF=15m | FF2: LH_HL_FILTER_TF_REQ=2 | FG2: LH_HL_FILTER_TF_REQ=2_ALT | FH2: LIVE_ENTRY_ENGINE_FILTER_TF=OFF | FI2: LIVE_ENTRY_ENGINE_FILTER_TF=D | FJ2: LIVE_ENTRY_ENGINE_FILTER_TF=4h | FK2: LIVE_ENTRY_ENGINE_FILTER_TF=1h | FL2: LIVE_ENTRY_ENGINE_FILTER_TF=15m | FM2: LIVE_ONLY_SIGNALS_BATCH5_FILTER_TF=OFF | FN2: LIVE_ONLY_SIGNALS_BATCH5_FILTER_TF=D | FO2: LIVE_ONLY_SIGNALS_BATCH5_FILTER_TF=4h | FP2: LIVE_ONLY_SIGNALS_BATCH5_FILTER_TF=1h | FQ2: LIVE_ONLY_SIGNALS_BATCH5_FILTER_TF=15m | FR2: MANDATORY_REENTRY_WT_FILTER_TF_MODE=15m_only | FS2: MANDATORY_REENTRY_WT_FILTER_TF_MODE=15m_only_ALT | FT2: MOM3_FILTER_TF=OFF | FU2: MOM3_FILTER_TF=D | FV2: MOM3_FILTER_TF=4h | FW2: MOM3_FILTER_TF=1h | FX2: MOM3_FILTER_TF=15m | FY2: MOMENTUM_BREAKOUT_FILTER_TF=OFF | FZ2: MOMENTUM_BREAKOUT_FILTER_TF=D | GA2: MOMENTUM_BREAKOUT_FILTER_TF=4h | GB2: MOMENTUM_BREAKOUT_FILTER_TF=1h | GC2: MOMENTUM_BREAKOUT_FILTER_TF=15m | GD2: MTF_ARMED_ENTRIES_FILTER_TF=OFF | GE2: MTF_ARMED_ENTRIES_FILTER_TF=D | GF2: MTF_ARMED_ENTRIES_FILTER_TF=4h | GG2: MTF_ARMED_ENTRIES_FILTER_TF=1h | GH2: MTF_ARMED_ENTRIES_FILTER_TF=15m | GI2: MTF_ATR_TRAIL_FILTER_TF=OFF | GJ2: MTF_ATR_TRAIL_FILTER_TF=D | GK2: MTF_ATR_TRAIL_FILTER_TF=4h | GL2: MTF_ATR_TRAIL_FILTER_TF=1h | GM2: MTF_ATR_TRAIL_FILTER_TF=15m | GN2: MTF_DC_REJECT_FILTER_TF=OFF | GO2: MTF_DC_REJECT_FILTER_TF=D | GP2: MTF_DC_REJECT_FILTER_TF=4h | GQ2: MTF_DC_REJECT_FILTER_TF=1h | GR2: MTF_DC_REJECT_FILTER_TF=15m | GS2: NEWBORN_LOSS_KILL_FILTER_TF=OFF | GT2: NEWBORN_LOSS_KILL_FILTER_TF=D | GU2: NEWBORN_LOSS_KILL_FILTER_TF=4h | GV2: NEWBORN_LOSS_KILL_FILTER_TF=1h | GW2: NEWBORN_LOSS_KILL_FILTER_TF=15m | GX2: NEWBORN_PROTECT_FILTER_TF=OFF | GY2: NEWBORN_PROTECT_FILTER_TF=D | GZ2: NEWBORN_PROTECT_FILTER_TF=4h | HA2: NEWBORN_PROTECT_FILTER_TF=1h | HB2: NEWBORN_PROTECT_FILTER_TF=15m | HC2: NOLOSS_BYPASS_WT5OF5_FILTER_TF=OFF | HD2: NOLOSS_BYPASS_WT5OF5_FILTER_TF=D | HE2: NOLOSS_BYPASS_WT5OF5_FILTER_TF=4h | HF2: NOLOSS_BYPASS_WT5OF5_FILTER_TF=1h | HG2: NOLOSS_BYPASS_WT5OF5_FILTER_TF=15m | HH2: OPEN_INTENT_SIZE_GATES_FILTER_TF=OFF | HI2: OPEN_INTENT_SIZE_GATES_FILTER_TF=D | HJ2: OPEN_INTENT_SIZE_GATES_FILTER_TF=4h | HK2: OPEN_INTENT_SIZE_GATES_FILTER_TF=1h | HL2: OPEN_INTENT_SIZE_GATES_FILTER_TF=15m | HM2: PARTIAL_PROFIT_LOCK_V2_FILTER_TF=OFF | HN2: PARTIAL_PROFIT_LOCK_V2_FILTER_TF=D | HO2: PARTIAL_PROFIT_LOCK_V2_FILTER_TF=4h | HP2: PARTIAL_PROFIT_LOCK_V2_FILTER_TF=1h | HQ2: PARTIAL_PROFIT_LOCK_V2_FILTER_TF=15m | HR2: PEAK_GIVEBACK_BE_EROSION_FILTER_TF=OFF | HS2: PEAK_GIVEBACK_BE_EROSION_FILTER_TF=D | HT2: PEAK_GIVEBACK_BE_EROSION_FILTER_TF=4h | HU2: PEAK_GIVEBACK_BE_EROSION_FILTER_TF=1h | HV2: PEAK_GIVEBACK_BE_EROSION_FILTER_TF=15m | HW2: WT_15M_BOUNCE_BB_MAX=0.95 | HX2: WT_15M_BOUNCE_BB_MAX=0.9 | HY2: WT_15M_BOUNCE_BB_MAX=0.8 | HZ2: WT_15M_BOUNCE_BB_MIN=0.05 | IA2: WT_15M_BOUNCE_BB_MIN=0.1 | IB2: WT_15M_BOUNCE_BB_MIN=0.2 | IC2: WT_15M_BOUNCE_HIGH_1H_GT_PREV=True | ID2: WT_15M_BOUNCE_HIGH_1H_GT_PREV=False | IE2: WT_15M_BOUNCE_LOW_1H_GT_PREV=True | IF2: WT_15M_BOUNCE_LOW_1H_GT_PREV=False | IG2: WT_15M_BOUNCE_REL_VOL_GT_1=True | IH2: WT_15M_BOUNCE_REL_VOL_GT_1=False | II2: Live Location | IJ2: Vec Hook | IK2: Type | IL2: Correct Options
A3: STDEV_BREAKOUT_EXIT_PCTB_FAIL | B3: 0 | E3: -12.1759 | F3: 3.7596 | G3: =IFERROR(VLOOKUP($A3,Results_30d_Deltas!$A$2:$H$5000,7,FALSE)-E3,"") | H3: =IFERROR(VLOOKUP($A3,Results_30d_Deltas!$A$2:$H$5000,6,FALSE),"") | K3: =IF(B3=C3,"YES","NO") | AP3: 2.4666 | AQ3: 3.7596 | AR3: 0.8638 | IJ3: ez_manage.py:4040 top() | IK3: v12_quick_engine.py:3276 x2
A4: STDEV_BREAKOUT_EXIT_PCTB_FAIL | B4: 0.5 | E4: -12.1759 | F4: 3.7596 | G4: =IFERROR(VLOOKUP($A4,Results_30d_Deltas!$A$2:$H$5000,7,FALSE)-E3,"") | H4: =IFERROR(VLOOKUP($A4,Results_30d_Deltas!$A$2:$H$5000,6,FALSE),"") | K4: =IF(B4=C4,"YES","NO") | AP4: 2.4666 | AQ4: 3.7596 | AR4: 0.8638 | IJ4: ez_manage.py:4040 top() | IK4: v12_quick_engine.py:3276 x2
A5: STDEV_BREAKOUT_EXIT_PCTB_FAIL | B5: 1.0 | E5: -12.1759 | F5: 3.7596 | G5: =IFERROR(VLOOKUP($A5,Results_30d_Deltas!$A$2:$H$5000,7,FALSE)-E4,"") | H5: =IFERROR(VLOOKUP($A5,Results_30d_Deltas!$A$2:$H$5000,6,FALSE),"") | K5: =IF(B5=C5,"YES","NO") | AP5: 2.4666 | AQ5: 3.7596 | AR5: 0.8638 | IJ5: ez_manage.py:4040 top() | IK5: v12_quick_engine.py:3276 x2
A6: STDEV_BREAKOUT_EXIT_PCTB_FAIL | B6: 2.0 | E6: -12.1759 | F6: 3.7596 | G6: =IFERROR(VLOOKUP($A6,Results_30d_Deltas!$A$2:$H$5000,7,FALSE)-E5,"") | H6: =IFERROR(VLOOKUP($A6,Results_30d_Deltas!$A$2:$H$5000,6,FALSE),"") | K6: =IF(B6=C6,"YES","NO") | AP6: 2.4666 | AQ6: 3.7596 | AR6: 0.8638 | IJ6: ez_manage.py:4040 top() | IK6: v12_quick_engine.py:3276 x2
A7: ALL_TF_AGAINST_CLOSE_ENABLED | B7: False | E7: -13.3501 | F7: 2.5853 | G7: =IFERROR(VLOOKUP($A7,Results_30d_Deltas!$A$2:$H$5000,7,FALSE)-E6,"") | H7: =IFERROR(VLOOKUP($A7,Results_30d_Deltas!$A$2:$H$5000,6,FALSE),"") | K7: =IF(B7=C7,"YES","NO") | IJ7: ez_manage.py:4325 top() | IK7: v12_quick_engine.py:174 x6
A8: ALL_TF_AGAINST_CLOSE_ENABLED | B8: True | E8: -12.2254 | F8: 3.7101 | G8: =IFERROR(VLOOKUP($A8,Results_30d_Deltas!$A$2:$H$5000,7,FALSE)-E7,"") | H8: =IFERROR(VLOOKUP($A8,Results_30d_Deltas!$A$2:$H$5000,6,FALSE),"") | K8: =IF(B8=C8,"YES","NO") | IJ8: ez_manage.py:4325 top() | IK8: v12_quick_engine.py:174 x6

Sheet EXIT_VELOCITY
A1: 05 EXIT_VELOCITY - 26 bases -> 80 rows - 231 per-row FULLY CONNECTED
A2: Switch | B2: default | C2: override | D2: Family | E2: BASELINE | F2: VECTOR_DELTA | G2: LIVE_DELTA | H2: LIVE_SHARPE | I2: REAL_COMPLETE | J2: PER_ROW_FILTERS | K2: is_default (backup if bold lost) | L2: ATR_TRAIL_FILTER_TF=OFF | M2: ATR_TRAIL_FILTER_TF=D | N2: ATR_TRAIL_FILTER_TF=4h | O2: ATR_TRAIL_FILTER_TF=1h | P2: ATR_TRAIL_FILTER_TF=15m | Q2: BAR_PATTERNS_FILTER_TF=OFF | R2: BAR_PATTERNS_FILTER_TF=D | S2: BAR_PATTERNS_FILTER_TF=4h | T2: BAR_PATTERNS_FILTER_TF=1h | U2: BAR_PATTERNS_FILTER_TF=15m | V2: BB_PULLBACK_GATE_FILTER_TF=OFF | W2: BB_PULLBACK_GATE_FILTER_TF=D | X2: BB_PULLBACK_GATE_FILTER_TF=4h | Y2: BB_PULLBACK_GATE_FILTER_TF=1h | Z2: BB_PULLBACK_GATE_FILTER_TF=15m | AA2: BB_RECOVERY_ENTRY_FILTER_TF=OFF | AB2: BB_RECOVERY_ENTRY_FILTER_TF=D | AC2: BB_RECOVERY_ENTRY_FILTER_TF=4h | AD2: BB_RECOVERY_ENTRY_FILTER_TF=1h | AE2: BB_RECOVERY_ENTRY_FILTER_TF=15m | AF2: BB_RECOVERY_FILTER_TF=OFF | AG2: BB_RECOVERY_FILTER_TF=D | AH2: BB_RECOVERY_FILTER_TF=4h | AI2: BB_RECOVERY_FILTER_TF=1h | AJ2: BB_RECOVERY_FILTER_TF=15m | AK2: BREAKEVEN_GAIN_EROSION_FILTER_TF=OFF | AL2: BREAKEVEN_GAIN_EROSION_FILTER_TF=D | AM2: BREAKEVEN_GAIN_EROSION_FILTER_TF=4h | AN2: BREAKEVEN_GAIN_EROSION_FILTER_TF=1h | AO2: BREAKEVEN_GAIN_EROSION_FILTER_TF=15m | AP2: BREAKOUT_RETEST_FILTER_TF=OFF | AQ2: BREAKOUT_RETEST_FILTER_TF=D | AR2: BREAKOUT_RETEST_FILTER_TF=4h | AS2: BREAKOUT_RETEST_FILTER_TF=1h | AT2: BREAKOUT_RETEST_FILTER_TF=15m | AU2: BT_WT_CROSS_LADDER_FILTER_TF=OFF | AV2: BT_WT_CROSS_LADDER_FILTER_TF=D | AW2: BT_WT_CROSS_LADDER_FILTER_TF=4h | AX2: BT_WT_CROSS_LADDER_FILTER_TF=1h | AY2: BT_WT_CROSS_LADDER_FILTER_TF=15m | AZ2: CANDLE_PATTERN_STOPS_FILTER_TF=OFF | BA2: CANDLE_PATTERN_STOPS_FILTER_TF=D | BB2: CANDLE_PATTERN_STOPS_FILTER_TF=4h | BC2: CANDLE_PATTERN_STOPS_FILTER_TF=1h | BD2: CANDLE_PATTERN_STOPS_FILTER_TF=15m | BE2: CIRCUIT_SHARPE_GATES_FILTER_TF=OFF | BF2: CIRCUIT_SHARPE_GATES_FILTER_TF=D | BG2: CIRCUIT_SHARPE_GATES_FILTER_TF=4h | BH2: CIRCUIT_SHARPE_GATES_FILTER_TF=1h | BI2: CIRCUIT_SHARPE_GATES_FILTER_TF=15m | BJ2: DC_BREACH_REDUCE_FILTER_TF=OFF | BK2: DC_BREACH_REDUCE_FILTER_TF=D | BL2: DC_BREACH_REDUCE_FILTER_TF=4h | BM2: DC_BREACH_REDUCE_FILTER_TF=1h | BN2: DC_BREACH_REDUCE_FILTER_TF=15m | BO2: DC_BREAK_FILTER_TF=OFF | BP2: DC_BREAK_FILTER_TF=D | BQ2: DC_BREAK_FILTER_TF=4h | BR2: DC_BREAK_FILTER_TF=1h | BS2: DC_BREAK_FILTER_TF=15m | BT2: DC_MOMENTUM_BOTA_SCORER_FILTER_TF=OFF | BU2: DC_MOMENTUM_BOTA_SCORER_FILTER_TF=D | BV2: DC_MOMENTUM_BOTA_SCORER_FILTER_TF=4h | BW2: DC_MOMENTUM_BOTA_SCORER_FILTER_TF=1h | BX2: DC_MOMENTUM_BOTA_SCORER_FILTER_TF=15m | BY2: DELTA_ENGINE_FILTER_TF=OFF | BZ2: DELTA_ENGINE_FILTER_TF=D | CA2: DELTA_ENGINE_FILTER_TF=4h | CB2: DELTA_ENGINE_FILTER_TF=1h | CC2: DELTA_ENGINE_FILTER_TF=15m | CD2: EMA_9_21_FILTER_FILTER_TF=OFF | CE2: EMA_9_21_FILTER_FILTER_TF=D | CF2: EMA_9_21_FILTER_FILTER_TF=4h | CG2: EMA_9_21_FILTER_FILTER_TF=1h | CH2: EMA_9_21_FILTER_FILTER_TF=15m | CI2: EMA_BLANKET_FILTER_FILTER_TF=OFF | CJ2: EMA_BLANKET_FILTER_FILTER_TF=D | CK2: EMA_BLANKET_FILTER_FILTER_TF=4h | CL2: EMA_BLANKET_FILTER_FILTER_TF=1h | CM2: EMA_BLANKET_FILTER_FILTER_TF=15m | CN2: EMERGENCY_BRAKE_FILTER_TF=OFF | CO2: EMERGENCY_BRAKE_FILTER_TF=D | CP2: EMERGENCY_BRAKE_FILTER_TF=4h | CQ2: EMERGENCY_BRAKE_FILTER_TF=1h | CR2: EMERGENCY_BRAKE_FILTER_TF=15m | CS2: EXIT_R1_R2_FILTER_TF=OFF | CT2: EXIT_R1_R2_FILTER_TF=D | CU2: EXIT_R1_R2_FILTER_TF=4h | CV2: EXIT_R1_R2_FILTER_TF=1h | CW2: EXIT_R1_R2_FILTER_TF=15m | CX2: EXIT_TIGHT_BREAKOUT_SCORER_FILTER_TF=OFF | CY2: EXIT_TIGHT_BREAKOUT_SCORER_FILTER_TF=D | CZ2: EXIT_TIGHT_BREAKOUT_SCORER_FILTER_TF=4h | DA2: EXIT_TIGHT_BREAKOUT_SCORER_FILTER_TF=1h | DB2: EXIT_TIGHT_BREAKOUT_SCORER_FILTER_TF=15m | DC2: EXIT_TOP_FADE_FILTER_TF=OFF | DD2: EXIT_TOP_FADE_FILTER_TF=D | DE2: EXIT_TOP_FADE_FILTER_TF=4h | DF2: EXIT_TOP_FADE_FILTER_TF=1h | DG2: EXIT_TOP_FADE_FILTER_TF=15m | DH2: EXIT_TO_REDUCE_ADAPTER_FILTER_TF=OFF | DI2: EXIT_TO_REDUCE_ADAPTER_FILTER_TF=D | DJ2: EXIT_TO_REDUCE_ADAPTER_FILTER_TF=4h | DK2: EXIT_TO_REDUCE_ADAPTER_FILTER_TF=1h | DL2: EXIT_TO_REDUCE_ADAPTER_FILTER_TF=15m | DM2: FAST_RISER_FILTER_TF=OFF | DN2: FAST_RISER_FILTER_TF=D | DO2: FAST_RISER_FILTER_TF=4h | DP2: FAST_RISER_FILTER_TF=1h | DQ2: FAST_RISER_FILTER_TF=15m | DR2: FH_MOMENTUM_FILTER_TF=OFF | DS2: FH_MOMENTUM_FILTER_TF=D | DT2: FH_MOMENTUM_FILTER_TF=4h | DU2: FH_MOMENTUM_FILTER_TF=1h | DV2: FH_MOMENTUM_FILTER_TF=15m | DW2: FIRST_OPEN_THROTTLE_FILTER_TF=OFF | DX2: FIRST_OPEN_THROTTLE_FILTER_TF=D | DY2: FIRST_OPEN_THROTTLE_FILTER_TF=4h | DZ2: FIRST_OPEN_THROTTLE_FILTER_TF=1h | EA2: FIRST_OPEN_THROTTLE_FILTER_TF=15m | EB2: FROZEN_STOP_FILTER_TF=OFF | EC2: FROZEN_STOP_FILTER_TF=D | ED2: FROZEN_STOP_FILTER_TF=4h | EE2: FROZEN_STOP_FILTER_TF=1h | EF2: FROZEN_STOP_FILTER_TF=15m | EG2: GOLDEN_RULE_ENFORCE_FILTER_TF=OFF | EH2: GOLDEN_RULE_ENFORCE_FILTER_TF=D | EI2: GOLDEN_RULE_ENFORCE_FILTER_TF=4h | EJ2: GOLDEN_RULE_ENFORCE_FILTER_TF=1h | EK2: GOLDEN_RULE_ENFORCE_FILTER_TF=15m | EL2: GOLDEN_RULE_HTF_VOTE_FILTER_TF=OFF | EM2: GOLDEN_RULE_HTF_VOTE_FILTER_TF=D | EN2: GOLDEN_RULE_HTF_VOTE_FILTER_TF=4h | EO2: GOLDEN_RULE_HTF_VOTE_FILTER_TF=1h | EP2: GOLDEN_RULE_HTF_VOTE_FILTER_TF=15m | EQ2: GR_FILTER_VEC_FILTER_TF=OFF | ER2: GR_FILTER_VEC_FILTER_TF=D | ES2: GR_FILTER_VEC_FILTER_TF=4h | ET2: GR_FILTER_VEC_FILTER_TF=1h | EU2: GR_FILTER_VEC_FILTER_TF=15m | EV2: GR_V5_STATE_FILTER_TF=OFF | EW2: GR_V5_STATE_FILTER_TF=D | EX2: GR_V5_STATE_FILTER_TF=4h | EY2: GR_V5_STATE_FILTER_TF=1h | EZ2: GR_V5_STATE_FILTER_TF=15m | FA2: HAIKU_WINNER_FILTER_TF=OFF | FB2: HAIKU_WINNER_FILTER_TF=D | FC2: HAIKU_WINNER_FILTER_TF=4h | FD2: HAIKU_WINNER_FILTER_TF=1h | FE2: HAIKU_WINNER_FILTER_TF=15m | FF2: LH_HL_FILTER_TF_REQ=2 | FG2: LH_HL_FILTER_TF_REQ=2_ALT | FH2: LIVE_ENTRY_ENGINE_FILTER_TF=OFF | FI2: LIVE_ENTRY_ENGINE_FILTER_TF=D | FJ2: LIVE_ENTRY_ENGINE_FILTER_TF=4h | FK2: LIVE_ENTRY_ENGINE_FILTER_TF=1h | FL2: LIVE_ENTRY_ENGINE_FILTER_TF=15m | FM2: LIVE_ONLY_SIGNALS_BATCH5_FILTER_TF=OFF | FN2: LIVE_ONLY_SIGNALS_BATCH5_FILTER_TF=D | FO2: LIVE_ONLY_SIGNALS_BATCH5_FILTER_TF=4h | FP2: LIVE_ONLY_SIGNALS_BATCH5_FILTER_TF=1h | FQ2: LIVE_ONLY_SIGNALS_BATCH5_FILTER_TF=15m | FR2: MANDATORY_REENTRY_WT_FILTER_TF_MODE=15m_only | FS2: MANDATORY_REENTRY_WT_FILTER_TF_MODE=15m_only_ALT | FT2: MOM3_FILTER_TF=OFF | FU2: MOM3_FILTER_TF=D | FV2: MOM3_FILTER_TF=4h | FW2: MOM3_FILTER_TF=1h | FX2: MOM3_FILTER_TF=15m | FY2: MOMENTUM_BREAKOUT_FILTER_TF=OFF | FZ2: MOMENTUM_BREAKOUT_FILTER_TF=D | GA2: MOMENTUM_BREAKOUT_FILTER_TF=4h | GB2: MOMENTUM_BREAKOUT_FILTER_TF=1h | GC2: MOMENTUM_BREAKOUT_FILTER_TF=15m | GD2: MTF_ARMED_ENTRIES_FILTER_TF=OFF | GE2: MTF_ARMED_ENTRIES_FILTER_TF=D | GF2: MTF_ARMED_ENTRIES_FILTER_TF=4h | GG2: MTF_ARMED_ENTRIES_FILTER_TF=1h | GH2: MTF_ARMED_ENTRIES_FILTER_TF=15m | GI2: MTF_ATR_TRAIL_FILTER_TF=OFF | GJ2: MTF_ATR_TRAIL_FILTER_TF=D | GK2: MTF_ATR_TRAIL_FILTER_TF=4h | GL2: MTF_ATR_TRAIL_FILTER_TF=1h | GM2: MTF_ATR_TRAIL_FILTER_TF=15m | GN2: MTF_DC_REJECT_FILTER_TF=OFF | GO2: MTF_DC_REJECT_FILTER_TF=D | GP2: MTF_DC_REJECT_FILTER_TF=4h | GQ2: MTF_DC_REJECT_FILTER_TF=1h | GR2: MTF_DC_REJECT_FILTER_TF=15m | GS2: NEWBORN_LOSS_KILL_FILTER_TF=OFF | GT2: NEWBORN_LOSS_KILL_FILTER_TF=D | GU2: NEWBORN_LOSS_KILL_FILTER_TF=4h | GV2: NEWBORN_LOSS_KILL_FILTER_TF=1h | GW2: NEWBORN_LOSS_KILL_FILTER_TF=15m | GX2: NEWBORN_PROTECT_FILTER_TF=OFF | GY2: NEWBORN_PROTECT_FILTER_TF=D | GZ2: NEWBORN_PROTECT_FILTER_TF=4h | HA2: NEWBORN_PROTECT_FILTER_TF=1h | HB2: NEWBORN_PROTECT_FILTER_TF=15m | HC2: NOLOSS_BYPASS_WT5OF5_FILTER_TF=OFF | HD2: NOLOSS_BYPASS_WT5OF5_FILTER_TF=D | HE2: NOLOSS_BYPASS_WT5OF5_FILTER_TF=4h | HF2: NOLOSS_BYPASS_WT5OF5_FILTER_TF=1h | HG2: NOLOSS_BYPASS_WT5OF5_FILTER_TF=15m | HH2: OPEN_INTENT_SIZE_GATES_FILTER_TF=OFF | HI2: OPEN_INTENT_SIZE_GATES_FILTER_TF=D | HJ2: OPEN_INTENT_SIZE_GATES_FILTER_TF=4h | HK2: OPEN_INTENT_SIZE_GATES_FILTER_TF=1h | HL2: OPEN_INTENT_SIZE_GATES_FILTER_TF=15m | HM2: PARTIAL_PROFIT_LOCK_V2_FILTER_TF=OFF | HN2: PARTIAL_PROFIT_LOCK_V2_FILTER_TF=D | HO2: PARTIAL_PROFIT_LOCK_V2_FILTER_TF=4h | HP2: PARTIAL_PROFIT_LOCK_V2_FILTER_TF=1h | HQ2: PARTIAL_PROFIT_LOCK_V2_FILTER_TF=15m | HR2: PEAK_GIVEBACK_BE_EROSION_FILTER_TF=OFF | HS2: PEAK_GIVEBACK_BE_EROSION_FILTER_TF=D | HT2: PEAK_GIVEBACK_BE_EROSION_FILTER_TF=4h | HU2: PEAK_GIVEBACK_BE_EROSION_FILTER_TF=1h | HV2: PEAK_GIVEBACK_BE_EROSION_FILTER_TF=15m | HW2: WT_15M_BOUNCE_BB_MAX=0.95 | HX2: WT_15M_BOUNCE_BB_MAX=0.9 | HY2: WT_15M_BOUNCE_BB_MAX=0.8 | HZ2: WT_15M_BOUNCE_BB_MIN=0.05 | IA2: WT_15M_BOUNCE_BB_MIN=0.1 | IB2: WT_15M_BOUNCE_BB_MIN=0.2 | IC2: WT_15M_BOUNCE_HIGH_1H_GT_PREV=True | ID2: WT_15M_BOUNCE_HIGH_1H_GT_PREV=False | IE2: WT_15M_BOUNCE_LOW_1H_GT_PREV=True | IF2: WT_15M_BOUNCE_LOW_1H_GT_PREV=False | IG2: WT_15M_BOUNCE_REL_VOL_GT_1=True | IH2: WT_15M_BOUNCE_REL_VOL_GT_1=False | II2: Live Location | IJ2: Vec Hook | IK2: Type | IL2: Correct Options
A3: WT_CROSS_EXIT_ENABLED | B3: False | E3: -12.1759 | F3: 3.7596 | G3: =IFERROR(VLOOKUP($A3,Results_30d_Deltas!$A$2:$H$5000,7,FALSE)-E3,"") | H3: =IFERROR(VLOOKUP($A3,Results_30d_Deltas!$A$2:$H$5000,6,FALSE),"") | K3: =IF(B3=C3,"YES","NO") | IJ3: ez_manage.py:1751 top() | IK3: v12_quick_engine.py:2439 x5
A4: WT_CROSS_EXIT_ENABLED | B4: True | E4: -13.3501 | F4: 2.5853 | G4: =IFERROR(VLOOKUP($A4,Results_30d_Deltas!$A$2:$H$5000,7,FALSE)-E3,"") | H4: =IFERROR(VLOOKUP($A4,Results_30d_Deltas!$A$2:$H$5000,6,FALSE),"") | K4: =IF(B4=C4,"YES","NO") | IJ4: ez_manage.py:1751 top() | IK4: v12_quick_engine.py:2439 x5
A5: BB_SQUEEZE_EXIT_ENABLED | B5: False | E5: -13.4689 | F5: 2.4666 | G5: =IFERROR(VLOOKUP($A5,Results_30d_Deltas!$A$2:$H$5000,7,FALSE)-E4,"") | H5: =IFERROR(VLOOKUP($A5,Results_30d_Deltas!$A$2:$H$5000,6,FALSE),"") | K5: =IF(B5=C5,"YES","NO") | IJ5: ez_manage.py:6163 top() | IK5: v12_quick_engine.py:891 x4
A6: BB_SQUEEZE_EXIT_ENABLED | B6: True | E6: -13.3501 | F6: 2.5853 | G6: =IFERROR(VLOOKUP($A6,Results_30d_Deltas!$A$2:$H$5000,7,FALSE)-E5,"") | H6: =IFERROR(VLOOKUP($A6,Results_30d_Deltas!$A$2:$H$5000,6,FALSE),"") | K6: =IF(B6=C6,"YES","NO") | IJ6: ez_manage.py:6163 top() | IK6: v12_quick_engine.py:891 x4
A7: BTC_DIVERGENCE_EXIT_AGAINST | B7: 0 | E7: -12.1759 | F7: 3.7596 | G7: =IFERROR(VLOOKUP($A7,Results_30d_Deltas!$A$2:$H$5000,7,FALSE)-E6,"") | H7: =IFERROR(VLOOKUP($A7,Results_30d_Deltas!$A$2:$H$5000,6,FALSE),"") | K7: =IF(B7=C7,"YES","NO") | IJ7: ez_manage.py:4448 top() | IK7: v12_quick_engine.py:408 x8
A8: BTC_DIVERGENCE_EXIT_AGAINST | B8: 0.5 | E8: -12.1759 | F8: 3.7596 | G8: =IFERROR(VLOOKUP($A8,Results_30d_Deltas!$A$2:$H$5000,7,FALSE)-E7,"") | H8: =IFERROR(VLOOKUP($A8,Results_30d_Deltas!$A$2:$H$5000,6,FALSE),"") | K8: =IF(B8=C8,"YES","NO") | IJ8: ez_manage.py:4448 top() | IK8: v12_quick_engine.py:408 x8
A9: BTC_DIVERGENCE_EXIT_AGAINST | B9: 1.0 | E9: -12.1759 | F9: 3.7596 | G9: =IFERROR(VLOOKUP($A9,Results_30d_Deltas!$A$2:$H$5000,7,FALSE)-E8,"") | H9: =IFERROR(VLOOKUP($A9,Results_30d_Deltas!$A$2:$H$5000,6,FALSE),"") | K9: =IF(B9=C9,"YES","NO") | IJ9: ez_manage.py:4448 top() | IK9: v12_quick_engine.py:408 x8
A10: BTC_DIVERGENCE_EXIT_AGAINST | B10: 2.0 | E10: -12.1759 | F10: 3.7596 | G10: =IFERROR(VLOOKUP($A10,Results_30d_Deltas!$A$2:$H$5000,7,FALSE)-E9,"") | H10: =IFERROR(VLOOKUP($A10,Results_30d_Deltas!$A$2:$H$5000,6,FALSE),"") | K10: =IF(B10=C10,"YES","NO") | IJ10: ez_manage.py:4448 top() | IK10: v12_quick_engine.py:408 x8
A11: DELTA_EXIT_DC_FLOOR | B11: False | E11: -13.3501 | F11: 2.5853 | G11: =IFERROR(VLOOKUP($A11,Results_30d_Deltas!$A$2:$H$5000,7,FALSE)-E10,"") | H11: =IFERROR(VLOOKUP($A11,Results_30d_Deltas!$A$2:$H$5000,6,FALSE),"") | K11: =IF(B11=C11,"YES","NO") | IJ11: ez_manage.py:4596 top() | IK11: v12_quick_engine.py:967 x8
A12: DELTA_EXIT_DC_FLOOR | B12: True | E12: -13.748 | F12: 2.1874 | G12: =IFERROR(VLOOKUP($A12,Results_30d_Deltas!$A$2:$H$5000,7,FALSE)-E11,"") | H12: =IFERROR(VLOOKUP($A12,Results_30d_Deltas!$A$2:$H$5000,6,FALSE),"") | K12: =IF(B12=C12,"YES","NO") | IJ12: ez_manage.py:4596 top() | IK12: v12_quick_engine.py:967 x8
A13: E_1_WT_EXIT_USE_DELTA_ENABLED | B13: False | E13: -12.1759 | F13: 3.7596 | G13: =IFERROR(VLOOKUP($A13,Results_30d_Deltas!$A$2:$H$5000,7,FALSE)-E12,"") | H13: =IFERROR(VLOOKUP($A13,Results_30d_Deltas!$A$2:$H$5000,6,FALSE),"") | K13: =IF(B13=C13,"YES","NO") | IJ13: ez_manage.py:4699 top() | IK13: v12_quick_engine.py:1818 x7
A14: E_1_WT_EXIT_USE_DELTA_ENABLED | B14: True | E14: -13.3501 | F14: 2.5853 | G14: =IFERROR(VLOOKUP($A14,Results_30d_Deltas!$A$2:$H$5000,7,FALSE)-E13,"") | H14: =IFERROR(VLOOKUP($A14,Results_30d_Deltas!$A$2:$H$5000,6,FALSE),"") | K14: =IF(B14=C14,"YES","NO") | IJ14: ez_manage.py:4699 top() | IK14: v12_quick_engine.py:1818 x7
A15: E_3_USE_WT_STRUCTURE_EXIT_MODE | B15: 0 | E15: -12.1759 | F15: 3.7596 | G15: =IFERROR(VLOOKUP($A15,Results_30d_Deltas!$A$2:$H$5000,7,FALSE)-E14,"") | H15: =IFERROR(VLOOKUP($A15,Results_30d_Deltas!$A$2:$H$5000,6,FALSE),"") | K15: =IF(B15=C15,"YES","NO") | IJ15: ez_manage.py:4700 top() | IK15: v12_quick_engine.py:1819 x8
... A18: E_3_USE_WT_STRUCTURE_EXIT_MODE | B18: 2.0 | E18: -12.1759 | F18: 3.7596 | G18: =IFERROR(VLOOKUP($A18,Results_30d_Deltas!$A$2:$H$5000,7,FALSE)-E17,"") | H18: =IFERROR(VLOOKUP($A18,Results_30d_Deltas!$A$2:$H$5000,6,FALSE),"") | K18: =IF(B18=C18,"YES","NO") | IJ18: ez_manage.py:4700 top() | IK18: v12_quick_engine.py:1819 x8
A19: HARD_BREAKEVEN_FLOOR_ENABLED | B19: False | E19: -13.3501 | F19: 2.5853 | G19: =IFERROR(VLOOKUP($A19,Results_30d_Deltas!$A$2:$H$5000,7,FALSE)-E18,"") | H19: =IFERROR(VLOOKUP($A19,Results_30d_Deltas!$A$2:$H$5000,6,FALSE),"") | K19: =IF(B19=C19,"YES","NO") | AK19: 2.4666 | AL19: 0.8638 | AM19: 0.505 | IJ19: ez_manage.py:4783 top() | IK19: v12_quick_engine.py:856 x6
A20: HARD_BREAKEVEN_FLOOR_ENABLED | B20: True | E20: -13.4636 | F20: 2.4718 | G20: =IFERROR(VLOOKUP($A20,Results_30d_Deltas!$A$2:$H$5000,7,FALSE)-E19,"") | H20: =IFERROR(VLOOKUP($A20,Results_30d_Deltas!$A$2:$H$5000,6,FALSE),"") | K20: =IF(B20=C20,"YES","NO") | AK20: 2.4718 | AL20: 0.4347 | AM20: 0.8725 | IJ20: ez_manage.py:4783 top() | IK20: v12_quick_engine.py:856 x6
A21: HARD_BREAKEVEN_MIN_PEAK_PCT | B21: 0.25 | E21: -13.4636 | F21: 2.4718 | G21: =IFERROR(VLOOKUP($A21,Results_30d_Deltas!$A$2:$H$5000,7,FALSE)-E20,"") | H21: =IFERROR(VLOOKUP($A21,Results_30d_Deltas!$A$2:$H$5000,6,FALSE),"") | K21: =IF(B21=C21,"YES","NO") | AK21: 2.4666 | AL21: 0 | AM21: 0.4347 | IJ21: ez_manage.py:4784 top() | IK21: v12_quick_engine.py:858 x8
A22: HARD_BREAKEVEN_MIN_PEAK_PCT | B22: 0.375 | E22: -13.4636 | F22: 2.4718 | G22: =IFERROR(VLOOKUP($A22,Results_30d_Deltas!$A$2:$H$5000,7,FALSE)-E21,"") | H22: =IFERROR(VLOOKUP($A22,Results_30d_Deltas!$A$2:$H$5000,6,FALSE),"") | K22: =IF(B22=C22,"YES","NO") | AK22: 2.4666 | AL22: 0 | AM22: 0.4347 | IJ22: ez_manage.py:4784 top() | IK22: v12_quick_engine.py:858 x8
A23: HARD_BREAKEVEN_MIN_PEAK_PCT | B23: 0.5 | E23: -13.4636 | F23: 2.4718 | G23: =IFERROR(VLOOKUP($A23,Results_30d_Deltas!$A$2:$H$5000,7,FALSE)-E22,"") | H23: =IFERROR(VLOOKUP($A23,Results_30d_Deltas!$A$2:$H$5000,6,FALSE),"") | K23: =IF(B23=C23,"YES","NO") | AK23: 2.4666 | AL23: 0 | AM23: 0.4347 | IJ23: ez_manage.py:4784 top() | IK23: v12_quick_engine.py:858 x8
A24: HARD_BREAKEVEN_MIN_PEAK_PCT | B24: 0.625 | E24: -13.4636 | F24: 2.4718 | G24: =IFERROR(VLOOKUP($A24,Results_30d_Deltas!$A$2:$H$5000,7,FALSE)-E23,"") | H24: =IFERROR(VLOOKUP($A24,Results_30d_Deltas!$A$2:$H$5000,6,FALSE),"") | K24: =IF(B24=C24,"YES","NO") | AK24: 2.4666 | AL24: 0 | AM24: 0.4347 | IJ24: ez_manage.py:4784 top() | IK24: v12_quick_engine.py:858 x8
A25: HARD_BREAKEVEN_MIN_PEAK_PCT | B25: 0.75 | E25: -13.4636 | F25: 2.4718 | G25: =IFERROR(VLOOKUP($A25,Results_30d_Deltas!$A$2:$H$5000,7,FALSE)-E24,"") | H25: =IFERROR(VLOOKUP($A25,Results_30d_Deltas!$A$2:$H$5000,6,FALSE),"") | K25: =IF(B25=C25,"YES","NO") | AK25: 2.4666 | AL25: 0 | AM25: 0.4347 | IJ25: ez_manage.py:4784 top() | IK25: v12_quick_engine.py:858 x8
A26: LOSS_TECHNICAL_EXIT_NO_STALE_BLOCK | B26: 0 | E26: -13.3501 | F26: 2.5853 | G26: =IFERROR(VLOOKUP($A26,Results_30d_Deltas!$A$2:$H$5000,7,FALSE)-E25,"") | H26: =IFERROR(VLOOKUP($A26,Results_30d_Deltas!$A$2:$H$5000,6,FALSE),"") | K26: =IF(B26=C26,"YES","NO") | IJ26: ez_manage.py:4933 top() | IK26: v12_quick_engine.py:2172 x2
A27: LOSS_TECHNICAL_EXIT_NO_STALE_BLOCK | B27: 0.5 | E27: -13.3501 | F27: 2.5853 | G27: =IFERROR(VLOOKUP($A27,Results_30d_Deltas!$A$2:$H$5000,7,FALSE)-E26,"") | H27: =IFERROR(VLOOKUP($A27,Results_30d_Deltas!$A$2:$H$5000,6,FALSE),"") | K27: =IF(B27=C27,"YES","NO") | IJ27: ez_manage.py:4933 top() | IK27: v12_quick_engine.py:2172 x2
A28: LOSS_TECHNICAL_EXIT_NO_STALE_BLOCK | B28: 1.0 | E28: -13.3501 | F28: 2.5853 | G28: =IFERROR(VLOOKUP($A28,Results_30d_Deltas!$A$2:$H$5000,7,FALSE)-E27,"") | H28: =IFERROR(VLOOKUP($A28,Results_30d_Deltas!$A$2:$H$5000,6,FALSE),"") | K28: =IF(B28=C28,"YES","NO") | IJ28: ez_manage.py:4933 top() | IK28: v12_quick_engine.py:2172 x2
A29: LOSS_TECHNICAL_EXIT_NO_STALE_BLOCK | B29: 2.0 | E29: -13.3501 | F29: 2.5853 | G29: =IFERROR(VLOOKUP($A29,Results_30d_Deltas!$A$2:$H$5000,7,FALSE)-E28,"") | H29: =IFERROR(VLOOKUP($A29,Results_30d_Deltas!$A$2:$H$5000,6,FALSE),"") | K29: =IF(B29=C29,"YES","NO") | IJ29: ez_manage.py:4933 top() | IK29: v12_quick_engine.py:2172 x2
A30: MI_STRUCT_EXIT_ENABLED | B30: False | E30: -13.4689 | F30: 2.4666 | G30: =IFERROR(VLOOKUP($A30,Results_30d_Deltas!$A$2:$H$5000,7,FALSE)-E29,"") | H30: =IFERROR(VLOOKUP($A30,Results_30d_Deltas!$A$2:$H$5000,6,FALSE),"") | K30: =IF(B30=C30,"YES","NO") | IJ30: ez_manage.py:3566 top() | IK30: v12_quick_engine.py:2344 x8
A31: MI_STRUCT_EXIT_ENABLED | B31: True | E31: -13.3501 | F31: 2.5853 | G31: =IFERROR(VLOOKUP($A31,Results_30d_Deltas!$A$2:$H$5000,7,FALSE)-E30,"") | H31: =IFERROR(VLOOKUP($A31,Results_30d_Deltas!$A$2:$H$5000,6,FALSE),"") | K31: =IF(B31=C31,"YES","NO") | IJ31: ez_manage.py:3566 top() | IK31: v12_quick_engine.py:2344 x8
A32: MI_VELOCITY_EXIT_ENABLED | B32: False | E32: -13.3501 | F32: 2.5853 | G32: =IFERROR(VLOOKUP($A32,Results_30d_Deltas!$A$2:$H$5000,7,FALSE)-E31,"") | H32: =IFERROR(VLOOKUP($A32,Results_30d_Deltas!$A$2:$H$5000,6,FALSE),"") | K32: =IF(B32=C32,"YES","NO") | IJ32: ez_manage.py:3568 top() | IK32: v12_quick_engine.py:2347 x8
A33: MI_VELOCITY_EXIT_ENABLED | B33: True | E33: -13.3501 | F33: 2.5853 | G33: =IFERROR(VLOOKUP($A33,Results_30d_Deltas!$A$2:$H$5000,7,FALSE)-E32,"") | H33: =IFERROR(VLOOKUP($A33,Results_30d_Deltas!$A$2:$H$5000,6,FALSE),"") | K33: =IF(B33=C33,"YES","NO") | IJ33: ez_manage.py:3568 top() | IK33: v12_quick_engine.py:2347 x8
A34: MI_WAVE_EXIT_ENABLED | B34: False | E34: -12.1759 | F34: 3.7596 | G34: =IFERROR(VLOOKUP($A34,Results_30d_Deltas!$A$2:$H$5000,7,FALSE)-E33,"") | H34: =IFERROR(VLOOKUP($A34,Results_30d_Deltas!$A$2:$H$5000,6,FALSE),"") | K34: =IF(B34=C34,"YES","NO") | IJ34: ez_manage.py:3569 top() | IK34: v12_quick_engine.py:2349 x8
A35: MI_WAVE_EXIT_ENABLED | B35: True | E35: -13.3501 | F35: 2.5853 | G35: =IFERROR(VLOOKUP($A35,Results_30d_Deltas!$A$2:$H$5000,7,FALSE)-E34,"") | H35: =IFERROR(VLOOKUP($A35,Results_30d_Deltas!$A$2:$H$5000,6,FALSE),"") | K35: =IF(B35=C35,"YES","NO") | IJ35: ez_manage.py:3569 top() | IK35: v12_quick_engine.py:2349 x8
A36: MU_CORRECTION_EXIT_ENABLED | B36: False | E36: -12.1759 | F36: 3.7596 | G36: =IFERROR(VLOOKUP($A36,Results_30d_Deltas!$A$2:$H$5000,7,FALSE)-E35,"") | H36: =IFERROR(VLOOKUP($A36,Results_30d_Deltas!$A$2:$H$5000,6,FALSE),"") | K36: =IF(B36=C36,"YES","NO") | IJ36: ez_manage.py:5068 top() | IK36: v12_quick_engine.py:2454 x3
A37: MU_CORRECTION_EXIT_ENABLED | B37: True | E37: -13.3501 | F37: 2.5853 | G37: =IFERROR(VLOOKUP($A37,Results_30d_Deltas!$A$2:$H$5000,7,FALSE)-E36,"") | H37: =IFERROR(VLOOKUP($A37,Results_30d_Deltas!$A$2:$H$5000,6,FALSE),"") | K37: =IF(B37=C37,"YES","NO") | IJ37: ez_manage.py:5068 top() | IK37: v12_quick_engine.py:2454 x3
... A82: WT_CROSS_EXIT_REQUIRE_15M_CONFIRM | B82: 2.0 | E82: -12.1759 | F82: 3.7596 | G82: =IFERROR(VLOOKUP($A82,Results_30d_Deltas!$A$2:$H$5000,7,FALSE)-E81,"") | H82: =IFERROR(VLOOKUP($A82,Results_30d_Deltas!$A$2:$H$5000,6,FALSE),"") | K82: =IF(B82=C82,"YES","NO") | IJ82: ez_manage.py:5904 top() | IK82: v12_quick_engine.py:3725 x5

Sheet REENTRY_WINDOWED
A1: 06 REENTRY_WINDOWED - 68 bases -> 249 rows - 231 per-row FULLY CONNECTED
A2: Switch | B2: default | C2: override | D2: Family | E2: BASELINE | F2: VECTOR_DELTA | G2: LIVE_DELTA | H2: LIVE_SHARPE | I2: REAL_COMPLETE | J2: PER_ROW_FILTERS | K2: is_default (backup if bold lost) | L2: ATR_TRAIL_FILTER_TF=OFF | M2: ATR_TRAIL_FILTER_TF=D | N2: ATR_TRAIL_FILTER_TF=4h | O2: ATR_TRAIL_FILTER_TF=1h | P2: ATR_TRAIL_FILTER_TF=15m | Q2: BAR_PATTERNS_FILTER_TF=OFF | R2: BAR_PATTERNS_FILTER_TF=D | S2: BAR_PATTERNS_FILTER_TF=4h | T2: BAR_PATTERNS_FILTER_TF=1h | U2: BAR_PATTERNS_FILTER_TF=15m | V2: BB_PULLBACK_GATE_FILTER_TF=OFF | W2: BB_PULLBACK_GATE_FILTER_TF=D | X2: BB_PULLBACK_GATE_FILTER_TF=4h | Y2: BB_PULLBACK_GATE_FILTER_TF=1h | Z2: BB_PULLBACK_GATE_FILTER_TF=15m | AA2: BB_RECOVERY_ENTRY_FILTER_TF=OFF | AB2: BB_RECOVERY_ENTRY_FILTER_TF=D | AC2: BB_RECOVERY_ENTRY_FILTER_TF=4h | AD2: BB_RECOVERY_ENTRY_FILTER_TF=1h | AE2: BB_RECOVERY_ENTRY_FILTER_TF=15m | AF2: BB_RECOVERY_FILTER_TF=OFF | AG2: BB_RECOVERY_FILTER_TF=D | AH2: BB_RECOVERY_FILTER_TF=4h | AI2: BB_RECOVERY_FILTER_TF=1h | AJ2: BB_RECOVERY_FILTER_TF=15m | AK2: BREAKEVEN_GAIN_EROSION_FILTER_TF=OFF | AL2: BREAKEVEN_GAIN_EROSION_FILTER_TF=D | AM2: BREAKEVEN_GAIN_EROSION_FILTER_TF=4h | AN2: BREAKEVEN_GAIN_EROSION_FILTER_TF=1h | AO2: BREAKEVEN_GAIN_EROSION_FILTER_TF=15m | AP2: BREAKOUT_RETEST_FILTER_TF=OFF | AQ2: BREAKOUT_RETEST_FILTER_TF=D | AR2: BREAKOUT_RETEST_FILTER_TF=4h | AS2: BREAKOUT_RETEST_FILTER_TF=1h | AT2: BREAKOUT_RETEST_FILTER_TF=15m | AU2: BT_WT_CROSS_LADDER_FILTER_TF=OFF | AV2: BT_WT_CROSS_LADDER_FILTER_TF=D | AW2: BT_WT_CROSS_LADDER_FILTER_TF=4h | AX2: BT_WT_CROSS_LADDER_FILTER_TF=1h | AY2: BT_WT_CROSS_LADDER_FILTER_TF=15m | AZ2: CANDLE_PATTERN_STOPS_FILTER_TF=OFF | BA2: CANDLE_PATTERN_STOPS_FILTER_TF=D | BB2: CANDLE_PATTERN_STOPS_FILTER_TF=4h | BC2: CANDLE_PATTERN_STOPS_FILTER_TF=1h | BD2: CANDLE_PATTERN_STOPS_FILTER_TF=15m | BE2: CIRCUIT_SHARPE_GATES_FILTER_TF=OFF | BF2: CIRCUIT_SHARPE_GATES_FILTER_TF=D | BG2: CIRCUIT_SHARPE_GATES_FILTER_TF=4h | BH2: CIRCUIT_SHARPE_GATES_FILTER_TF=1h | BI2: CIRCUIT_SHARPE_GATES_FILTER_TF=15m | BJ2: DC_BREACH_REDUCE_FILTER_TF=OFF | BK2: DC_BREACH_REDUCE_FILTER_TF=D | BL2: DC_BREACH_REDUCE_FILTER_TF=4h | BM2: DC_BREACH_REDUCE_FILTER_TF=1h | BN2: DC_BREACH_REDUCE_FILTER_TF=15m | BO2: DC_BREAK_FILTER_TF=OFF | BP2: DC_BREAK_FILTER_TF=D | BQ2: DC_BREAK_FILTER_TF=4h | BR2: DC_BREAK_FILTER_TF=1h | BS2: DC_BREAK_FILTER_TF=15m | BT2: DC_MOMENTUM_BOTA_SCORER_FILTER_TF=OFF | BU2: DC_MOMENTUM_BOTA_SCORER_FILTER_TF=D | BV2: DC_MOMENTUM_BOTA_SCORER_FILTER_TF=4h | BW2: DC_MOMENTUM_BOTA_SCORER_FILTER_TF=1h | BX2: DC_MOMENTUM_BOTA_SCORER_FILTER_TF=15m | BY2: DELTA_ENGINE_FILTER_TF=OFF | BZ2: DELTA_ENGINE_FILTER_TF=D | CA2: DELTA_ENGINE_FILTER_TF=4h | CB2: DELTA_ENGINE_FILTER_TF=1h | CC2: DELTA_ENGINE_FILTER_TF=15m | CD2: EMA_9_21_FILTER_FILTER_TF=OFF | CE2: EMA_9_21_FILTER_FILTER_TF=D | CF2: EMA_9_21_FILTER_FILTER_TF=4h | CG2: EMA_9_21_FILTER_FILTER_TF=1h | CH2: EMA_9_21_FILTER_FILTER_TF=15m | CI2: EMA_BLANKET_FILTER_FILTER_TF=OFF | CJ2: EMA_BLANKET_FILTER_FILTER_TF=D | CK2: EMA_BLANKET_FILTER_FILTER_TF=4h | CL2: EMA_BLANKET_FILTER_FILTER_TF=1h | CM2: EMA_BLANKET_FILTER_FILTER_TF=15m | CN2: EMERGENCY_BRAKE_FILTER_TF=OFF | CO2: EMERGENCY_BRAKE_FILTER_TF=D | CP2: EMERGENCY_BRAKE_FILTER_TF=4h | CQ2: EMERGENCY_BRAKE_FILTER_TF=1h | CR2: EMERGENCY_BRAKE_FILTER_TF=15m | CS2: EXIT_R1_R2_FILTER_TF=OFF | CT2: EXIT_R1_R2_FILTER_TF=D | CU2: EXIT_R1_R2_FILTER_TF=4h | CV2: EXIT_R1_R2_FILTER_TF=1h | CW2: EXIT_R1_R2_FILTER_TF=15m | CX2: EXIT_TIGHT_BREAKOUT_SCORER_FILTER_TF=OFF | CY2: EXIT_TIGHT_BREAKOUT_SCORER_FILTER_TF=D | CZ2: EXIT_TIGHT_BREAKOUT_SCORER_FILTER_TF=4h | DA2: EXIT_TIGHT_BREAKOUT_SCORER_FILTER_TF=1h | DB2: EXIT_TIGHT_BREAKOUT_SCORER_FILTER_TF=15m | DC2: EXIT_TOP_FADE_FILTER_TF=OFF | DD2: EXIT_TOP_FADE_FILTER_TF=D | DE2: EXIT_TOP_FADE_FILTER_TF=4h | DF2: EXIT_TOP_FADE_FILTER_TF=1h | DG2: EXIT_TOP_FADE_FILTER_TF=15m | DH2: EXIT_TO_REDUCE_ADAPTER_FILTER_TF=OFF | DI2: EXIT_TO_REDUCE_ADAPTER_FILTER_TF=D | DJ2: EXIT_TO_REDUCE_ADAPTER_FILTER_TF=4h | DK2: EXIT_TO_REDUCE_ADAPTER_FILTER_TF=1h | DL2: EXIT_TO_REDUCE_ADAPTER_FILTER_TF=15m | DM2: FAST_RISER_FILTER_TF=OFF | DN2: FAST_RISER_FILTER_TF=D | DO2: FAST_RISER_FILTER_TF=4h | DP2: FAST_RISER_FILTER_TF=1h | DQ2: FAST_RISER_FILTER_TF=15m | DR2: FH_MOMENTUM_FILTER_TF=OFF | DS2: FH_MOMENTUM_FILTER_TF=D | DT2: FH_MOMENTUM_FILTER_TF=4h | DU2: FH_MOMENTUM_FILTER_TF=1h | DV2: FH_MOMENTUM_FILTER_TF=15m | DW2: FIRST_OPEN_THROTTLE_FILTER_TF=OFF | DX2: FIRST_OPEN_THROTTLE_FILTER_TF=D | DY2: FIRST_OPEN_THROTTLE_FILTER_TF=4h | DZ2: FIRST_OPEN_THROTTLE_FILTER_TF=1h | EA2: FIRST_OPEN_THROTTLE_FILTER_TF=15m | EB2: FROZEN_STOP_FILTER_TF=OFF | EC2: FROZEN_STOP_FILTER_TF=D | ED2: FROZEN_STOP_FILTER_TF=4h | EE2: FROZEN_STOP_FILTER_TF=1h | EF2: FROZEN_STOP_FILTER_TF=15m | EG2: GOLDEN_RULE_ENFORCE_FILTER_TF=OFF | EH2: GOLDEN_RULE_ENFORCE_FILTER_TF=D | EI2: GOLDEN_RULE_ENFORCE_FILTER_TF=4h | EJ2: GOLDEN_RULE_ENFORCE_FILTER_TF=1h | EK2: GOLDEN_RULE_ENFORCE_FILTER_TF=15m | EL2: GOLDEN_RULE_HTF_VOTE_FILTER_TF=OFF | EM2: GOLDEN_RULE_HTF_VOTE_FILTER_TF=D | EN2: GOLDEN_RULE_HTF_VOTE_FILTER_TF=4h | EO2: GOLDEN_RULE_HTF_VOTE_FILTER_TF=1h | EP2: GOLDEN_RULE_HTF_VOTE_FILTER_TF=15m | EQ2: GR_FILTER_VEC_FILTER_TF=OFF | ER2: GR_FILTER_VEC_FILTER_TF=D | ES2: GR_FILTER_VEC_FILTER_TF=4h | ET2: GR_FILTER_VEC_FILTER_TF=1h | EU2: GR_FILTER_VEC_FILTER_TF=15m | EV2: GR_V5_STATE_FILTER_TF=OFF | EW2: GR_V5_STATE_FILTER_TF=D | EX2: GR_V5_STATE_FILTER_TF=4h | EY2: GR_V5_STATE_FILTER_TF=1h | EZ2: GR_V5_STATE_FILTER_TF=15m | FA2: HAIKU_WINNER_FILTER_TF=OFF | FB2: HAIKU_WINNER_FILTER_TF=D | FC2: HAIKU_WINNER_FILTER_TF=4h | FD2: HAIKU_WINNER_FILTER_TF=1h | FE2: HAIKU_WINNER_FILTER_TF=15m | FF2: LH_HL_FILTER_TF_REQ=2 | FG2: LH_HL_FILTER_TF_REQ=2_ALT | FH2: LIVE_ENTRY_ENGINE_FILTER_TF=OFF | FI2: LIVE_ENTRY_ENGINE_FILTER_TF=D | FJ2: LIVE_ENTRY_ENGINE_FILTER_TF=4h | FK2: LIVE_ENTRY_ENGINE_FILTER_TF=1h | FL2: LIVE_ENTRY_ENGINE_FILTER_TF=15m | FM2: LIVE_ONLY_SIGNALS_BATCH5_FILTER_TF=OFF | FN2: LIVE_ONLY_SIGNALS_BATCH5_FILTER_TF=D | FO2: LIVE_ONLY_SIGNALS_BATCH5_FILTER_TF=4h | FP2: LIVE_ONLY_SIGNALS_BATCH5_FILTER_TF=1h | FQ2: LIVE_ONLY_SIGNALS_BATCH5_FILTER_TF=15m | FR2: MANDATORY_REENTRY_WT_FILTER_TF_MODE=15m_only | FS2: MANDATORY_REENTRY_WT_FILTER_TF_MODE=15m_only_ALT | FT2: MOM3_FILTER_TF=OFF | FU2: MOM3_FILTER_TF=D | FV2: MOM3_FILTER_TF=4h | FW2: MOM3_FILTER_TF=1h | FX2: MOM3_FILTER_TF=15m | FY2: MOMENTUM_BREAKOUT_FILTER_TF=OFF | FZ2: MOMENTUM_BREAKOUT_FILTER_TF=D | GA2: MOMENTUM_BREAKOUT_FILTER_TF=4h | GB2: MOMENTUM_BREAKOUT_FILTER_TF=1h | GC2: MOMENTUM_BREAKOUT_FILTER_TF=15m | GD2: MTF_ARMED_ENTRIES_FILTER_TF=OFF | GE2: MTF_ARMED_ENTRIES_FILTER_TF=D | GF2: MTF_ARMED_ENTRIES_FILTER_TF=4h | GG2: MTF_ARMED_ENTRIES_FILTER_TF=1h | GH2: MTF_ARMED_ENTRIES_FILTER_TF=15m | GI2: MTF_ATR_TRAIL_FILTER_TF=OFF | GJ2: MTF_ATR_TRAIL_FILTER_TF=D | GK2: MTF_ATR_TRAIL_FILTER_TF=4h | GL2: MTF_ATR_TRAIL_FILTER_TF=1h | GM2: MTF_ATR_TRAIL_FILTER_TF=15m | GN2: MTF_DC_REJECT_FILTER_TF=OFF | GO2: MTF_DC_REJECT_FILTER_TF=D | GP2: MTF_DC_REJECT_FILTER_TF=4h | GQ2: MTF_DC_REJECT_FILTER_TF=1h | GR2: MTF_DC_REJECT_FILTER_TF=15m | GS2: NEWBORN_LOSS_KILL_FILTER_TF=OFF | GT2: NEWBORN_LOSS_KILL_FILTER_TF=D | GU2: NEWBORN_LOSS_KILL_FILTER_TF=4h | GV2: NEWBORN_LOSS_KILL_FILTER_TF=1h | GW2: NEWBORN_LOSS_KILL_FILTER_TF=15m | GX2: NEWBORN_PROTECT_FILTER_TF=OFF | GY2: NEWBORN_PROTECT_FILTER_TF=D | GZ2: NEWBORN_PROTECT_FILTER_TF=4h | HA2: NEWBORN_PROTECT_FILTER_TF=1h | HB2: NEWBORN_PROTECT_FILTER_TF=15m | HC2: NOLOSS_BYPASS_WT5OF5_FILTER_TF=OFF | HD2: NOLOSS_BYPASS_WT5OF5_FILTER_TF=D | HE2: NOLOSS_BYPASS_WT5OF5_FILTER_TF=4h | HF2: NOLOSS_BYPASS_WT5OF5_FILTER_TF=1h | HG2: NOLOSS_BYPASS_WT5OF5_FILTER_TF=15m | HH2: OPEN_INTENT_SIZE_GATES_FILTER_TF=OFF | HI2: OPEN_INTENT_SIZE_GATES_FILTER_TF=D | HJ2: OPEN_INTENT_SIZE_GATES_FILTER_TF=4h | HK2: OPEN_INTENT_SIZE_GATES_FILTER_TF=1h | HL2: OPEN_INTENT_SIZE_GATES_FILTER_TF=15m | HM2: PARTIAL_PROFIT_LOCK_V2_FILTER_TF=OFF | HN2: PARTIAL_PROFIT_LOCK_V2_FILTER_TF=D | HO2: PARTIAL_PROFIT_LOCK_V2_FILTER_TF=4h | HP2: PARTIAL_PROFIT_LOCK_V2_FILTER_TF=1h | HQ2: PARTIAL_PROFIT_LOCK_V2_FILTER_TF=15m | HR2: PEAK_GIVEBACK_BE_EROSION_FILTER_TF=OFF | HS2: PEAK_GIVEBACK_BE_EROSION_FILTER_TF=D | HT2: PEAK_GIVEBACK_BE_EROSION_FILTER_TF=4h | HU2: PEAK_GIVEBACK_BE_EROSION_FILTER_TF=1h | HV2: PEAK_GIVEBACK_BE_EROSION_FILTER_TF=15m | HW2: WT_15M_BOUNCE_BB_MAX=0.95 | HX2: WT_15M_BOUNCE_BB_MAX=0.9 | HY2: WT_15M_BOUNCE_BB_MAX=0.8 | HZ2: WT_15M_BOUNCE_BB_MIN=0.05 | IA2: WT_15M_BOUNCE_BB_MIN=0.1 | IB2: WT_15M_BOUNCE_BB_MIN=0.2 | IC2: WT_15M_BOUNCE_HIGH_1H_GT_PREV=True | ID2: WT_15M_BOUNCE_HIGH_1H_GT_PREV=False | IE2: WT_15M_BOUNCE_LOW_1H_GT_PREV=True | IF2: WT_15M_BOUNCE_LOW_1H_GT_PREV=False | IG2: WT_15M_BOUNCE_REL_VOL_GT_1=True | IH2: WT_15M_BOUNCE_REL_VOL_GT_1=False | II2: Live Location | IJ2: Vec Hook | IK2: Type | IL2: Correct Options
A3: GUARANTEED_REENTRY_K_FAVORABLE_HIGH | B3: 35.0 | E3: -12.1759 | F3: 3.7596 | G3: =IFERROR(VLOOKUP($A3,Results_30d_Deltas!$A$2:$H$5000,7,FALSE)-E3,"") | H3: =IFERROR(VLOOKUP($A3,Results_30d_Deltas!$A$2:$H$5000,6,FALSE),"") | K3: =IF(B3=C3,"YES","NO") | IJ3: ez_manage.py:4774 top() | IK3: v12_quick_engine.py:1941 x4
A4: GUARANTEED_REENTRY_K_FAVORABLE_HIGH | B4: 52.5 | E4: -12.1759 | F4: 3.7596 | G4: =IFERROR(VLOOKUP($A4,Results_30d_Deltas!$A$2:$H$5000,7,FALSE)-E3,"") | H4: =IFERROR(VLOOKUP($A4,Results_30d_Deltas!$A$2:$H$5000,6,FALSE),"") | K4: =IF(B4=C4,"YES","NO") | IJ4: ez_manage.py:4774 top() | IK4: v12_quick_engine.py:1941 x4
A5: GUARANTEED_REENTRY_K_FAVORABLE_HIGH | B5: 70.0 | E5: -12.1759 | F5: 3.7596 | G5: =IFERROR(VLOOKUP($A5,Results_30d_Deltas!$A$2:$H$5000,7,FALSE)-E4,"") | H5: =IFERROR(VLOOKUP($A5,Results_30d_Deltas!$A$2:$H$5000,6,FALSE),"") | K5: =IF(B5=C5,"YES","NO") | IJ5: ez_manage.py:4774 top() | IK5: v12_quick_engine.py:1941 x4
A6: GUARANTEED_REENTRY_K_FAVORABLE_HIGH | B6: 87.5 | E6: -12.1759 | F6: 3.7596 | G6: =IFERROR(VLOOKUP($A6,Results_30d_Deltas!$A$2:$H$5000,7,FALSE)-E5,"") | H6: =IFERROR(VLOOKUP($A6,Results_30d_Deltas!$A$2:$H$5000,6,FALSE),"") | K6: =IF(B6=C6,"YES","NO") | IJ6: ez_manage.py:4774 top() | IK6: v12_quick_engine.py:1941 x4
A7: GUARANTEED_REENTRY_K_FAVORABLE_HIGH | B7: 105.0 | E7: -12.1759 | F7: 3.7596 | G7: =IFERROR(VLOOKUP($A7,Results_30d_Deltas!$A$2:$H$5000,7,FALSE)-E6,"") | H7: =IFERROR(VLOOKUP($A7,Results_30d_Deltas!$A$2:$H$5000,6,FALSE),"") | K7: =IF(B7=C7,"YES","NO") | IJ7: ez_manage.py:4774 top() | IK7: v12_quick_engine.py:1941 x4
A8: GUARANTEED_REENTRY_K_FAVORABLE_LOW | B8: 15.0 | E8: -13.4689 | F8: 2.4666 | G8: =IFERROR(VLOOKUP($A8,Results_30d_Deltas!$A$2:$H$5000,7,FALSE)-E7,"") | H8: =IFERROR(VLOOKUP($A8,Results_30d_Deltas!$A$2:$H$5000,6,FALSE),"") | K8: =IF(B8=C8,"YES","NO") | IJ8: ez_manage.py:4775 top() | IK8: v12_quick_engine.py:1942 x4
A9: GUARANTEED_REENTRY_K_FAVORABLE_LOW | B9: 22.5 | E9: -13.4689 | F9: 2.4666 | G9: =IFERROR(VLOOKUP($A9,Results_30d_Deltas!$A$2:$H$5000,7,FALSE)-E8,"") | H9: =IFERROR(VLOOKUP($A9,Results_30d_Deltas!$A$2:$H$5000,6,FALSE),"") | K9: =IF(B9=C9,"YES","NO") | IJ9: ez_manage.py:4775 top() | IK9: v12_quick_engine.py:1942 x4
A10: GUARANTEED_REENTRY_K_FAVORABLE_LOW | B10: 30.0 | E10: -13.4689 | F10: 2.4666 | G10: =IFERROR(VLOOKUP($A10,Results_30d_Deltas!$A$2:$H$5000,7,FALSE)-E9,"") | H10: =IFERROR(VLOOKUP($A10,Results_30d_Deltas!$A$2:$H$5000,6,FALSE),"") | K10: =IF(B10=C10,"YES","NO") | IJ10: ez_manage.py:4775 top() | IK10: v12_quick_engine.py:1942 x4
A11: GUARANTEED_REENTRY_K_FAVORABLE_LOW | B11: 37.5 | E11: -13.4689 | F11: 2.4666 | G11: =IFERROR(VLOOKUP($A11,Results_30d_Deltas!$A$2:$H$5000,7,FALSE)-E10,"") | H11: =IFERROR(VLOOKUP($A11,Results_30d_Deltas!$A$2:$H$5000,6,FALSE),"") | K11: =IF(B11=C11,"YES","NO") | IJ11: ez_manage.py:4775 top() | IK11: v12_quick_engine.py:1942 x4
A12: GUARANTEED_REENTRY_K_FAVORABLE_LOW | B12: 45.0 | E12: -13.4689 | F12: 2.4666 | G12: =IFERROR(VLOOKUP($A12,Results_30d_Deltas!$A$2:$H$5000,7,FALSE)-E11,"") | H12: =IFERROR(VLOOKUP($A12,Results_30d_Deltas!$A$2:$H$5000,6,FALSE),"") | K12: =IF(B12=C12,"YES","NO") | IJ12: ez_manage.py:4775 top() | IK12: v12_quick_engine.py:1942 x4
A13: BOUNCE_REENTRY_ENABLED | B13: False | E13: -13.4689 | F13: 2.4666 | G13: =IFERROR(VLOOKUP($A13,Results_30d_Deltas!$A$2:$H$5000,7,FALSE)-E12,"") | H13: =IFERROR(VLOOKUP($A13,Results_30d_Deltas!$A$2:$H$5000,6,FALSE),"") | K13: =IF(B13=C13,"YES","NO") | IJ13: ez_manage.py:2985 top() | IK13: v12_quick_engine.py:315 x14
A14: BOUNCE_REENTRY_ENABLED | B14: True | E14: -13.3501 | F14: 2.5853 | G14: =IFERROR(VLOOKUP($A14,Results_30d_Deltas!$A$2:$H$5000,7,FALSE)-E13,"") | H14: =IFERROR(VLOOKUP($A14,Results_30d_Deltas!$A$2:$H$5000,6,FALSE),"") | K14: =IF(B14=C14,"YES","NO") | IJ14: ez_manage.py:2985 top() | IK14: v12_quick_engine.py:315 x14
A15: DELTA_EXIT_MANDATORY_REENTRY_ENABLED | B15: False | E15: -12.1759 | F15: 3.7596 | G15: =IFERROR(VLOOKUP($A15,Results_30d_Deltas!$A$2:$H$5000,7,FALSE)-E14,"") | H15: =IFERROR(VLOOKUP($A15,Results_30d_Deltas!$A$2:$H$5000,6,FALSE),"") | K15: =IF(B15=C15,"YES","NO") | IJ15: ez_manage.py:5975 top() | IK15: v12_quick_engine.py:4235 x4
... A91: LEGACY_REENTRY_PSR_K_DC_CROSSOVER | B91: 2.0 | E91: -13.748 | F91: 2.1874 | G91: =IFERROR(VLOOKUP($A91,Results_30d_Deltas!$A$2:$H$5000,7,FALSE)-E90,"") | H91: =IFERROR(VLOOKUP($A91,Results_30d_Deltas!$A$2:$H$5000,6,FALSE),"") | K91: =IF(B91=C91,"YES","NO") | IJ91: ez_manage.py:3424 top() | IK91: v12_quick_engine.py:2125 x5
A92: LEGACY_REENTRY_PSR_QUICK_RECOVERY | B92: 0 | E92: -13.3501 | F92: 2.5853 | G92: =IFERROR(VLOOKUP($A92,Results_30d_Deltas!$A$2:$H$5000,7,FALSE)-E91,"") | H92: =IFERROR(VLOOKUP($A92,Results_30d_Deltas!$A$2:$H$5000,6,FALSE),"") | K92: =IF(B92=C92,"YES","NO") | AA92: 0.8725 | AB92: 0.4886 | AC92: 0.436 | IJ92: ez_manage.py:3425 top() | IK92: v12_quick_engine.py:2126 x4
A93: LEGACY_REENTRY_PSR_QUICK_RECOVERY | B93: 0.5 | E93: -13.3501 | F93: 2.5853 | G93: =IFERROR(VLOOKUP($A93,Results_30d_Deltas!$A$2:$H$5000,7,FALSE)-E92,"") | H93: =IFERROR(VLOOKUP($A93,Results_30d_Deltas!$A$2:$H$5000,6,FALSE),"") | K93: =IF(B93=C93,"YES","NO") | AA93: 0.8725 | AB93: 0.4886 | AC93: 0.436 | IJ93: ez_manage.py:3425 top() | IK93: v12_quick_engine.py:2126 x4
A94: LEGACY_REENTRY_PSR_QUICK_RECOVERY | B94: 1.0 | E94: -13.3501 | F94: 2.5853 | G94: =IFERROR(VLOOKUP($A94,Results_30d_Deltas!$A$2:$H$5000,7,FALSE)-E93,"") | H94: =IFERROR(VLOOKUP($A94,Results_30d_Deltas!$A$2:$H$5000,6,FALSE),"") | K94: =IF(B94=C94,"YES","NO") | AA94: 0.8725 | AB94: 0.4886 | AC94: 0.436 | IJ94: ez_manage.py:3425 top() | IK94: v12_quick_engine.py:2126 x4
A95: LEGACY_REENTRY_PSR_QUICK_RECOVERY | B95: 2.0 | E95: -13.3501 | F95: 2.5853 | G95: =IFERROR(VLOOKUP($A95,Results_30d_Deltas!$A$2:$H$5000,7,FALSE)-E94,"") | H95: =IFERROR(VLOOKUP($A95,Results_30d_Deltas!$A$2:$H$5000,6,FALSE),"") | K95: =IF(B95=C95,"YES","NO") | AA95: 0.8725 | AB95: 0.4886 | AC95: 0.436 | IJ95: ez_manage.py:3425 top() | IK95: v12_quick_engine.py:2126 x4
A96: MANDATORY_REENTRY_ALLOW_WT0_STRONG_CROSS | B96: 0 | E96: -12.1759 | F96: 3.7596 | G96: =IFERROR(VLOOKUP($A96,Results_30d_Deltas!$A$2:$H$5000,7,FALSE)-E95,"") | H96: =IFERROR(VLOOKUP($A96,Results_30d_Deltas!$A$2:$H$5000,6,FALSE),"") | K96: =IF(B96=C96,"YES","NO") | IJ96: ez_manage.py:4960 top() | IK96: v12_quick_engine.py:2245 x4
A97: MANDATORY_REENTRY_ALLOW_WT0_STRONG_CROSS | B97: 0.5 | E97: -12.1759 | F97: 3.7596 | G97: =IFERROR(VLOOKUP($A97,Results_30d_Deltas!$A$2:$H$5000,7,FALSE)-E96,"") | H97: =IFERROR(VLOOKUP($A97,Results_30d_Deltas!$A$2:$H$5000,6,FALSE),"") | K97: =IF(B97=C97,"YES","NO") | IJ97: ez_manage.py:4960 top() | IK97: v12_quick_engine.py:2245 x4
A98: MANDATORY_REENTRY_ALLOW_WT0_STRONG_CROSS | B98: 1.0 | E98: -12.1759 | F98: 3.7596 | G98: =IFERROR(VLOOKUP($A98,Results_30d_Deltas!$A$2:$H$5000,7,FALSE)-E97,"") | H98: =IFERROR(VLOOKUP($A98,Results_30d_Deltas!$A$2:$H$5000,6,FALSE),"") | K98: =IF(B98=C98,"YES","NO") | IJ98: ez_manage.py:4960 top() | IK98: v12_quick_engine.py:2245 x4
A99: MANDATORY_REENTRY_ALLOW_WT0_STRONG_CROSS | B99: 2.0 | E99: -12.1759 | F99: 3.7596 | G99: =IFERROR(VLOOKUP($A99,Results_30d_Deltas!$A$2:$H$5000,7,FALSE)-E98,"") | H99: =IFERROR(VLOOKUP($A99,Results_30d_Deltas!$A$2:$H$5000,6,FALSE),"") | K99: =IF(B99=C99,"YES","NO") | IJ99: ez_manage.py:4960 top() | IK99: v12_quick_engine.py:2245 x4
A100: MANDATORY_REENTRY_K_HIGH_BLOCK | B100: 0 | E100: -12.1759 | F100: 3.7596 | G100: =IFERROR(VLOOKUP($A100,Results_30d_Deltas!$A$2:$H$5000,7,FALSE)-E99,"") | H100: =IFERROR(VLOOKUP($A100,Results_30d_Deltas!$A$2:$H$5000,6,FALSE),"") | K100: =IF(B100=C100,"YES","NO") | IJ100: ez_manage.py:4961 top() | IK100: v12_quick_engine.py:2247 x2
A101: MANDATORY_REENTRY_K_HIGH_BLOCK | B101: 0.5 | E101: -12.1759 | F101: 3.7596 | G101: =IFERROR(VLOOKUP($A101,Results_30d_Deltas!$A$2:$H$5000,7,FALSE)-E100,"") | H101: =IFERROR(VLOOKUP($A101,Results_30d_Deltas!$A$2:$H$5000,6,FALSE),"") | K101: =IF(B101=C101,"YES","NO") | IJ101: ez_manage.py:4961 top() | IK101: v12_quick_engine.py:2247 x2
A102: MANDATORY_REENTRY_K_HIGH_BLOCK | B102: 1.0 | E102: -12.1759 | F102: 3.7596 | G102: =IFERROR(VLOOKUP($A102,Results_30d_Deltas!$A$2:$H$5000,7,FALSE)-E101,"") | H102: =IFERROR(VLOOKUP($A102,Results_30d_Deltas!$A$2:$H$5000,6,FALSE),"") | K102: =IF(B102=C102,"YES","NO") | IJ102: ez_manage.py:4961 top() | IK102: v12_quick_engine.py:2247 x2
A103: MANDATORY_REENTRY_K_HIGH_BLOCK | B103: 2.0 | E103: -12.1759 | F103: 3.7596 | G103: =IFERROR(VLOOKUP($A103,Results_30d_Deltas!$A$2:$H$5000,7,FALSE)-E102,"") | H103: =IFERROR(VLOOKUP($A103,Results_30d_Deltas!$A$2:$H$5000,6,FALSE),"") | K103: =IF(B103=C103,"YES","NO") | IJ103: ez_manage.py:4961 top() | IK103: v12_quick_engine.py:2247 x2
A104: MANDATORY_REENTRY_K_LOW_BLOCK | B104: 0 | E104: -12.2254 | F104: 3.7101 | G104: =IFERROR(VLOOKUP($A104,Results_30d_Deltas!$A$2:$H$5000,7,FALSE)-E103,"") | H104: =IFERROR(VLOOKUP($A104,Results_30d_Deltas!$A$2:$H$5000,6,FALSE),"") | K104: =IF(B104=C104,"YES","NO") | IJ104: ez_manage.py:4962 top() | IK104: v12_quick_engine.py:2248 x2
A105: MANDATORY_REENTRY_K_LOW_BLOCK | B105: 0.5 | E105: -12.2254 | F105: 3.7101 | G105: =IFERROR(VLOOKUP($A105,Results_30d_Deltas!$A$2:$H$5000,7,FALSE)-E104,"") | H105: =IFERROR(VLOOKUP($A105,Results_30d_Deltas!$A$2:$H$5000,6,FALSE),"") | K105: =IF(B105=C105,"YES","NO") | IJ105: ez_manage.py:4962 top() | IK105: v12_quick_engine.py:2248 x2
A106: MANDATORY_REENTRY_K_LOW_BLOCK | B106: 1.0 | E106: -12.2254 | F106: 3.7101 | G106: =IFERROR(VLOOKUP($A106,Results_30d_Deltas!$A$2:$H$5000,7,FALSE)-E105,"") | H106: =IFERROR(VLOOKUP($A106,Results_30d_Deltas!$A$2:$H$5000,6,FALSE),"") | K106: =IF(B106=C106,"YES","NO") | IJ106: ez_manage.py:4962 top() | IK106: v12_quick_engine.py:2248 x2
A107: MANDATORY_REENTRY_K_LOW_BLOCK | B107: 2.0 | E107: -12.2254 | F107: 3.7101 | G107: =IFERROR(VLOOKUP($A107,Results_30d_Deltas!$A$2:$H$5000,7,FALSE)-E106,"") | H107: =IFERROR(VLOOKUP($A107,Results_30d_Deltas!$A$2:$H$5000,6,FALSE),"") | K107: =IF(B107=C107,"YES","NO") | IJ107: ez_manage.py:4962 top() | IK107: v12_quick_engine.py:2248 x2
... A195: REENTRY_B16_SMA200_PROX_PCT | B195: 2.0 | E195: -12.1759 | F195: 3.7596 | G195: =IFERROR(VLOOKUP($A195,Results_30d_Deltas!$A$2:$H$5000,7,FALSE)-E194,"") | H195: =IFERROR(VLOOKUP($A195,Results_30d_Deltas!$A$2:$H$5000,6,FALSE),"") | K195: =IF(B195=C195,"YES","NO") | IJ195: ez_manage.py:5299 top() | IK195: v12_quick_engine.py:2860 x4
A196: REENTRY_B16_SMA200_PULLBACK_ENABLED | B196: False | E196: -12.2254 | F196: 3.7101 | G196: =IFERROR(VLOOKUP($A196,Results_30d_Deltas!$A$2:$H$5000,7,FALSE)-E195,"") | H196: =IFERROR(VLOOKUP($A196,Results_30d_Deltas!$A$2:$H$5000,6,FALSE),"") | K196: =IF(B196=C196,"YES","NO") | V196: 0.4886 | W196: 3.7101 | X196: 0.4347 | IJ196: ez_manage.py:5300 top() | IK196: v12_quick_engine.py:2861 x4
A197: REENTRY_B16_SMA200_PULLBACK_ENABLED | B197: True | E197: -13.3501 | F197: 2.5853 | G197: =IFERROR(VLOOKUP($A197,Results_30d_Deltas!$A$2:$H$5000,7,FALSE)-E196,"") | H197: =IFERROR(VLOOKUP($A197,Results_30d_Deltas!$A$2:$H$5000,6,FALSE),"") | K197: =IF(B197=C197,"YES","NO") | V197: 2.4666 | W197: 0.505 | X197: 2.5853 | IJ197: ez_manage.py:5300 top() | IK197: v12_quick_engine.py:2861 x4
A198: REENTRY_CROSS_FRESHNESS_ENABLED | B198: False | E198: -13.4636 | F198: 2.4718 | G198: =IFERROR(VLOOKUP($A198,Results_30d_Deltas!$A$2:$H$5000,7,FALSE)-E197,"") | H198: =IFERROR(VLOOKUP($A198,Results_30d_Deltas!$A$2:$H$5000,6,FALSE),"") | K198: =IF(B198=C198,"YES","NO") | IJ198: ez_manage.py:5306 top() | IK198: v12_quick_engine.py:2869 x2
A199: REENTRY_CROSS_FRESHNESS_ENABLED | B199: True | E199: -13.3501 | F199: 2.5853 | G199: =IFERROR(VLOOKUP($A199,Results_30d_Deltas!$A$2:$H$5000,7,FALSE)-E198,"") | H199: =IFERROR(VLOOKUP($A199,Results_30d_Deltas!$A$2:$H$5000,6,FALSE),"") | K199: =IF(B199=C199,"YES","NO") | IJ199: ez_manage.py:5306 top() | IK199: v12_quick_engine.py:2869 x2
A200: REENTRY_EXHAUSTED_PARTIAL_ENABLED | B200: False | E200: -12.1759 | F200: 3.7596 | G200: =IFERROR(VLOOKUP($A200,Results_30d_Deltas!$A$2:$H$5000,7,FALSE)-E199,"") | H200: =IFERROR(VLOOKUP($A200,Results_30d_Deltas!$A$2:$H$5000,6,FALSE),"") | K200: =IF(B200=C200,"YES","NO") | IJ200: ez_manage.py:5308 top() | IK200: v12_quick_engine.py:2875 x2
A201: REENTRY_EXHAUSTED_PARTIAL_ENABLED | B201: True | E201: -13.3501 | F201: 2.5853 | G201: =IFERROR(VLOOKUP($A201,Results_30d_Deltas!$A$2:$H$5000,7,FALSE)-E200,"") | H201: =IFERROR(VLOOKUP($A201,Results_30d_Deltas!$A$2:$H$5000,6,FALSE),"") | K201: =IF(B201=C201,"YES","NO") | IJ201: ez_manage.py:5308 top() | IK201: v12_quick_engine.py:2875 x2
A202: REENTRY_EXIT_RECLAIM_BUFFER_PCT | B202: 0 | E202: -12.1759 | F202: 3.7596 | G202: =IFERROR(VLOOKUP($A202,Results_30d_Deltas!$A$2:$H$5000,7,FALSE)-E201,"") | H202: =IFERROR(VLOOKUP($A202,Results_30d_Deltas!$A$2:$H$5000,6,FALSE),"") | K202: =IF(B202=C202,"YES","NO") | IJ202: ez_manage.py:5309 top() | IK202: v12_quick_engine.py:2876 x3
A203: REENTRY_EXIT_RECLAIM_BUFFER_PCT | B203: 0.5 | E203: -12.1759 | F203: 3.7596 | G203: =IFERROR(VLOOKUP($A203,Results_30d_Deltas!$A$2:$H$5000,7,FALSE)-E202,"") | H203: =IFERROR(VLOOKUP($A203,Results_30d_Deltas!$A$2:$H$5000,6,FALSE),"") | K203: =IF(B203=C203,"YES","NO") | IJ203: ez_manage.py:5309 top() | IK203: v12_quick_engine.py:2876 x3
A204: REENTRY_EXIT_RECLAIM_BUFFER_PCT | B204: 1.0 | E204: -12.1759 | F204: 3.7596 | G204: =IFERROR(VLOOKUP($A204,Results_30d_Deltas!$A$2:$H$5000,7,FALSE)-E203,"") | H204: =IFERROR(VLOOKUP($A204,Results_30d_Deltas!$A$2:$H$5000,6,FALSE),"") | K204: =IF(B204=C204,"YES","NO") | IJ204: ez_manage.py:5309 top() | IK204: v12_quick_engine.py:2876 x3
A205: REENTRY_EXIT_RECLAIM_BUFFER_PCT | B205: 2.0 | E205: -12.1759 | F205: 3.7596 | G205: =IFERROR(VLOOKUP($A205,Results_30d_Deltas!$A$2:$H$5000,7,FALSE)-E204,"") | H205: =IFERROR(VLOOKUP($A205,Results_30d_Deltas!$A$2:$H$5000,6,FALSE),"") | K205: =IF(B205=C205,"YES","NO") | IJ205: ez_manage.py:5309 top() | IK205: v12_quick_engine.py:2876 x3
A206: REENTRY_EXIT_RECLAIM_ENABLED | B206: False | E206: -13.3501 | F206: 2.5853 | G206: =IFERROR(VLOOKUP($A206,Results_30d_Deltas!$A$2:$H$5000,7,FALSE)-E205,"") | H206: =IFERROR(VLOOKUP($A206,Results_30d_Deltas!$A$2:$H$5000,6,FALSE),"") | K206: =IF(B206=C206,"YES","NO") | IJ206: ez_manage.py:5310 top() | IK206: v12_quick_engine.py:2877 x3
A207: REENTRY_EXIT_RECLAIM_ENABLED | B207: True | E207: -13.3501 | F207: 2.5853 | G207: =IFERROR(VLOOKUP($A207,Results_30d_Deltas!$A$2:$H$5000,7,FALSE)-E206,"") | H207: =IFERROR(VLOOKUP($A207,Results_30d_Deltas!$A$2:$H$5000,6,FALSE),"") | K207: =IF(B207=C207,"YES","NO") | IJ207: ez_manage.py:5310 top() | IK207: v12_quick_engine.py:2877 x3
A208: REENTRY_POST_CONSOL_ATR_THRESHOLD | B208: 0 | E208: -13.4636 | F208: 2.4718 | G208: =IFERROR(VLOOKUP($A208,Results_30d_Deltas!$A$2:$H$5000,7,FALSE)-E207,"") | H208: =IFERROR(VLOOKUP($A208,Results_30d_Deltas!$A$2:$H$5000,6,FALSE),"") | K208: =IF(B208=C208,"YES","NO") | IJ208: ez_manage.py:5318 top() | IK208: v12_quick_engine.py:2896 x3
A209: REENTRY_POST_CONSOL_ATR_THRESHOLD | B209: 0.5 | E209: -13.4636 | F209: 2.4718 | G209: =IFERROR(VLOOKUP($A209,Results_30d_Deltas!$A$2:$H$5000,7,FALSE)-E208,"") | H209: =IFERROR(VLOOKUP($A209,Results_30d_Deltas!$A$2:$H$5000,6,FALSE),"") | K209: =IF(B209=C209,"YES","NO") | IJ209: ez_manage.py:5318 top() | IK209: v12_quick_engine.py:2896 x3
... A251: VEC_REENTRY_DC4_EXITPRICE_ENABLED | B251: True | E251: -13.3501 | F251: 2.5853 | G251: =IFERROR(VLOOKUP($A251,Results_30d_Deltas!$A$2:$H$5000,7,FALSE)-E250,"") | H251: =IFERROR(VLOOKUP($A251,Results_30d_Deltas!$A$2:$H$5000,6,FALSE),"") | K251: =IF(B251=C251,"YES","NO") | IJ251: ez_manage.py:6075 top() | IK251: v12_quick_engine.py:4287 x4

Sheet REENTRY_ADAPTIVE
A1: 07 REENTRY_ADAPTIVE - 10 bases -> 38 rows - 231 per-row FULLY CONNECTED
A2: Switch | B2: default | C2: override | D2: Family | E2: BASELINE | F2: VECTOR_DELTA | G2: LIVE_DELTA | H2: LIVE_SHARPE | I2: REAL_COMPLETE | J2: PER_ROW_FILTERS | K2: is_default (backup if bold lost) | L2: ATR_TRAIL_FILTER_TF=OFF | M2: ATR_TRAIL_FILTER_TF=D | N2: ATR_TRAIL_FILTER_TF=4h | O2: ATR_TRAIL_FILTER_TF=1h | P2: ATR_TRAIL_FILTER_TF=15m | Q2: BAR_PATTERNS_FILTER_TF=OFF | R2: BAR_PATTERNS_FILTER_TF=D | S2: BAR_PATTERNS_FILTER_TF=4h | T2: BAR_PATTERNS_FILTER_TF=1h | U2: BAR_PATTERNS_FILTER_TF=15m | V2: BB_PULLBACK_GATE_FILTER_TF=OFF | W2: BB_PULLBACK_GATE_FILTER_TF=D | X2: BB_PULLBACK_GATE_FILTER_TF=4h | Y2: BB_PULLBACK_GATE_FILTER_TF=1h | Z2: BB_PULLBACK_GATE_FILTER_TF=15m | AA2: BB_RECOVERY_ENTRY_FILTER_TF=OFF | AB2: BB_RECOVERY_ENTRY_FILTER_TF=D | AC2: BB_RECOVERY_ENTRY_FILTER_TF=4h | AD2: BB_RECOVERY_ENTRY_FILTER_TF=1h | AE2: BB_RECOVERY_ENTRY_FILTER_TF=15m | AF2: BB_RECOVERY_FILTER_TF=OFF | AG2: BB_RECOVERY_FILTER_TF=D | AH2: BB_RECOVERY_FILTER_TF=4h | AI2: BB_RECOVERY_FILTER_TF=1h | AJ2: BB_RECOVERY_FILTER_TF=15m | AK2: BREAKEVEN_GAIN_EROSION_FILTER_TF=OFF | AL2: BREAKEVEN_GAIN_EROSION_FILTER_TF=D | AM2: BREAKEVEN_GAIN_EROSION_FILTER_TF=4h | AN2: BREAKEVEN_GAIN_EROSION_FILTER_TF=1h | AO2: BREAKEVEN_GAIN_EROSION_FILTER_TF=15m | AP2: BREAKOUT_RETEST_FILTER_TF=OFF | AQ2: BREAKOUT_RETEST_FILTER_TF=D | AR2: BREAKOUT_RETEST_FILTER_TF=4h | AS2: BREAKOUT_RETEST_FILTER_TF=1h | AT2: BREAKOUT_RETEST_FILTER_TF=15m | AU2: BT_WT_CROSS_LADDER_FILTER_TF=OFF | AV2: BT_WT_CROSS_LADDER_FILTER_TF=D | AW2: BT_WT_CROSS_LADDER_FILTER_TF=4h | AX2: BT_WT_CROSS_LADDER_FILTER_TF=1h | AY2: BT_WT_CROSS_LADDER_FILTER_TF=15m | AZ2: CANDLE_PATTERN_STOPS_FILTER_TF=OFF | BA2: CANDLE_PATTERN_STOPS_FILTER_TF=D | BB2: CANDLE_PATTERN_STOPS_FILTER_TF=4h | BC2: CANDLE_PATTERN_STOPS_FILTER_TF=1h | BD2: CANDLE_PATTERN_STOPS_FILTER_TF=15m | BE2: CIRCUIT_SHARPE_GATES_FILTER_TF=OFF | BF2: CIRCUIT_SHARPE_GATES_FILTER_TF=D | BG2: CIRCUIT_SHARPE_GATES_FILTER_TF=4h | BH2: CIRCUIT_SHARPE_GATES_FILTER_TF=1h | BI2: CIRCUIT_SHARPE_GATES_FILTER_TF=15m | BJ2: DC_BREACH_REDUCE_FILTER_TF=OFF | BK2: DC_BREACH_REDUCE_FILTER_TF=D | BL2: DC_BREACH_REDUCE_FILTER_TF=4h | BM2: DC_BREACH_REDUCE_FILTER_TF=1h | BN2: DC_BREACH_REDUCE_FILTER_TF=15m | BO2: DC_BREAK_FILTER_TF=OFF | BP2: DC_BREAK_FILTER_TF=D | BQ2: DC_BREAK_FILTER_TF=4h | BR2: DC_BREAK_FILTER_TF=1h | BS2: DC_BREAK_FILTER_TF=15m | BT2: DC_MOMENTUM_BOTA_SCORER_FILTER_TF=OFF | BU2: DC_MOMENTUM_BOTA_SCORER_FILTER_TF=D | BV2: DC_MOMENTUM_BOTA_SCORER_FILTER_TF=4h | BW2: DC_MOMENTUM_BOTA_SCORER_FILTER_TF=1h | BX2: DC_MOMENTUM_BOTA_SCORER_FILTER_TF=15m | BY2: DELTA_ENGINE_FILTER_TF=OFF | BZ2: DELTA_ENGINE_FILTER_TF=D | CA2: DELTA_ENGINE_FILTER_TF=4h | CB2: DELTA_ENGINE_FILTER_TF=1h | CC2: DELTA_ENGINE_FILTER_TF=15m | CD2: EMA_9_21_FILTER_FILTER_TF=OFF | CE2: EMA_9_21_FILTER_FILTER_TF=D | CF2: EMA_9_21_FILTER_FILTER_TF=4h | CG2: EMA_9_21_FILTER_FILTER_TF=1h | CH2: EMA_9_21_FILTER_FILTER_TF=15m | CI2: EMA_BLANKET_FILTER_FILTER_TF=OFF | CJ2: EMA_BLANKET_FILTER_FILTER_TF=D | CK2: EMA_BLANKET_FILTER_FILTER_TF=4h | CL2: EMA_BLANKET_FILTER_FILTER_TF=1h | CM2: EMA_BLANKET_FILTER_FILTER_TF=15m | CN2: EMERGENCY_BRAKE_FILTER_TF=OFF | CO2: EMERGENCY_BRAKE_FILTER_TF=D | CP2: EMERGENCY_BRAKE_FILTER_TF=4h | CQ2: EMERGENCY_BRAKE_FILTER_TF=1h | CR2: EMERGENCY_BRAKE_FILTER_TF=15m | CS2: EXIT_R1_R2_FILTER_TF=OFF | CT2: EXIT_R1_R2_FILTER_TF=D | CU2: EXIT_R1_R2_FILTER_TF=4h | CV2: EXIT_R1_R2_FILTER_TF=1h | CW2: EXIT_R1_R2_FILTER_TF=15m | CX2: EXIT_TIGHT_BREAKOUT_SCORER_FILTER_TF=OFF | CY2: EXIT_TIGHT_BREAKOUT_SCORER_FILTER_TF=D | CZ2: EXIT_TIGHT_BREAKOUT_SCORER_FILTER_TF=4h | DA2: EXIT_TIGHT_BREAKOUT_SCORER_FILTER_TF=1h | DB2: EXIT_TIGHT_BREAKOUT_SCORER_FILTER_TF=15m | DC2: EXIT_TOP_FADE_FILTER_TF=OFF | DD2: EXIT_TOP_FADE_FILTER_TF=D | DE2: EXIT_TOP_FADE_FILTER_TF=4h | DF2: EXIT_TOP_FADE_FILTER_TF=1h | DG2: EXIT_TOP_FADE_FILTER_TF=15m | DH2: EXIT_TO_REDUCE_ADAPTER_FILTER_TF=OFF | DI2: EXIT_TO_REDUCE_ADAPTER_FILTER_TF=D | DJ2: EXIT_TO_REDUCE_ADAPTER_FILTER_TF=4h | DK2: EXIT_TO_REDUCE_ADAPTER_FILTER_TF=1h | DL2: EXIT_TO_REDUCE_ADAPTER_FILTER_TF=15m | DM2: FAST_RISER_FILTER_TF=OFF | DN2: FAST_RISER_FILTER_TF=D | DO2: FAST_RISER_FILTER_TF=4h | DP2: FAST_RISER_FILTER_TF=1h | DQ2: FAST_RISER_FILTER_TF=15m | DR2: FH_MOMENTUM_FILTER_TF=OFF | DS2: FH_MOMENTUM_FILTER_TF=D | DT2: FH_MOMENTUM_FILTER_TF=4h | DU2: FH_MOMENTUM_FILTER_TF=1h | DV2: FH_MOMENTUM_FILTER_TF=15m | DW2: FIRST_OPEN_THROTTLE_FILTER_TF=OFF | DX2: FIRST_OPEN_THROTTLE_FILTER_TF=D | DY2: FIRST_OPEN_THROTTLE_FILTER_TF=4h | DZ2: FIRST_OPEN_THROTTLE_FILTER_TF=1h | EA2: FIRST_OPEN_THROTTLE_FILTER_TF=15m | EB2: FROZEN_STOP_FILTER_TF=OFF | EC2: FROZEN_STOP_FILTER_TF=D | ED2: FROZEN_STOP_FILTER_TF=4h | EE2: FROZEN_STOP_FILTER_TF=1h | EF2: FROZEN_STOP_FILTER_TF=15m | EG2: GOLDEN_RULE_ENFORCE_FILTER_TF=OFF | EH2: GOLDEN_RULE_ENFORCE_FILTER_TF=D | EI2: GOLDEN_RULE_ENFORCE_FILTER_TF=4h | EJ2: GOLDEN_RULE_ENFORCE_FILTER_TF=1h | EK2: GOLDEN_RULE_ENFORCE_FILTER_TF=15m | EL2: GOLDEN_RULE_HTF_VOTE_FILTER_TF=OFF | EM2: GOLDEN_RULE_HTF_VOTE_FILTER_TF=D | EN2: GOLDEN_RULE_HTF_VOTE_FILTER_TF=4h | EO2: GOLDEN_RULE_HTF_VOTE_FILTER_TF=1h | EP2: GOLDEN_RULE_HTF_VOTE_FILTER_TF=15m | EQ2: GR_FILTER_VEC_FILTER_TF=OFF | ER2: GR_FILTER_VEC_FILTER_TF=D | ES2: GR_FILTER_VEC_FILTER_TF=4h | ET2: GR_FILTER_VEC_FILTER_TF=1h | EU2: GR_FILTER_VEC_FILTER_TF=15m | EV2: GR_V5_STATE_FILTER_TF=OFF | EW2: GR_V5_STATE_FILTER_TF=D | EX2: GR_V5_STATE_FILTER_TF=4h | EY2: GR_V5_STATE_FILTER_TF=1h | EZ2: GR_V5_STATE_FILTER_TF=15m | FA2: HAIKU_WINNER_FILTER_TF=OFF | FB2: HAIKU_WINNER_FILTER_TF=D | FC2: HAIKU_WINNER_FILTER_TF=4h | FD2: HAIKU_WINNER_FILTER_TF=1h | FE2: HAIKU_WINNER_FILTER_TF=15m | FF2: LH_HL_FILTER_TF_REQ=2 | FG2: LH_HL_FILTER_TF_REQ=2_ALT | FH2: LIVE_ENTRY_ENGINE_FILTER_TF=OFF | FI2: LIVE_ENTRY_ENGINE_FILTER_TF=D | FJ2: LIVE_ENTRY_ENGINE_FILTER_TF=4h | FK2: LIVE_ENTRY_ENGINE_FILTER_TF=1h | FL2: LIVE_ENTRY_ENGINE_FILTER_TF=15m | FM2: LIVE_ONLY_SIGNALS_BATCH5_FILTER_TF=OFF | FN2: LIVE_ONLY_SIGNALS_BATCH5_FILTER_TF=D | FO2: LIVE_ONLY_SIGNALS_BATCH5_FILTER_TF=4h | FP2: LIVE_ONLY_SIGNALS_BATCH5_FILTER_TF=1h | FQ2: LIVE_ONLY_SIGNALS_BATCH5_FILTER_TF=15m | FR2: MANDATORY_REENTRY_WT_FILTER_TF_MODE=15m_only | FS2: MANDATORY_REENTRY_WT_FILTER_TF_MODE=15m_only_ALT | FT2: MOM3_FILTER_TF=OFF | FU2: MOM3_FILTER_TF=D | FV2: MOM3_FILTER_TF=4h | FW2: MOM3_FILTER_TF=1h | FX2: MOM3_FILTER_TF=15m | FY2: MOMENTUM_BREAKOUT_FILTER_TF=OFF | FZ2: MOMENTUM_BREAKOUT_FILTER_TF=D | GA2: MOMENTUM_BREAKOUT_FILTER_TF=4h | GB2: MOMENTUM_BREAKOUT_FILTER_TF=1h | GC2: MOMENTUM_BREAKOUT_FILTER_TF=15m | GD2: MTF_ARMED_ENTRIES_FILTER_TF=OFF | GE2: MTF_ARMED_ENTRIES_FILTER_TF=D | GF2: MTF_ARMED_ENTRIES_FILTER_TF=4h | GG2: MTF_ARMED_ENTRIES_FILTER_TF=1h | GH2: MTF_ARMED_ENTRIES_FILTER_TF=15m | GI2: MTF_ATR_TRAIL_FILTER_TF=OFF | GJ2: MTF_ATR_TRAIL_FILTER_TF=D | GK2: MTF_ATR_TRAIL_FILTER_TF=4h | GL2: MTF_ATR_TRAIL_FILTER_TF=1h | GM2: MTF_ATR_TRAIL_FILTER_TF=15m | GN2: MTF_DC_REJECT_FILTER_TF=OFF | GO2: MTF_DC_REJECT_FILTER_TF=D | GP2: MTF_DC_REJECT_FILTER_TF=4h | GQ2: MTF_DC_REJECT_FILTER_TF=1h | GR2: MTF_DC_REJECT_FILTER_TF=15m | GS2: NEWBORN_LOSS_KILL_FILTER_TF=OFF | GT2: NEWBORN_LOSS_KILL_FILTER_TF=D | GU2: NEWBORN_LOSS_KILL_FILTER_TF=4h | GV2: NEWBORN_LOSS_KILL_FILTER_TF=1h | GW2: NEWBORN_LOSS_KILL_FILTER_TF=15m | GX2: NEWBORN_PROTECT_FILTER_TF=OFF | GY2: NEWBORN_PROTECT_FILTER_TF=D | GZ2: NEWBORN_PROTECT_FILTER_TF=4h | HA2: NEWBORN_PROTECT_FILTER_TF=1h | HB2: NEWBORN_PROTECT_FILTER_TF=15m | HC2: NOLOSS_BYPASS_WT5OF5_FILTER_TF=OFF | HD2: NOLOSS_BYPASS_WT5OF5_FILTER_TF=D | HE2: NOLOSS_BYPASS_WT5OF5_FILTER_TF=4h | HF2: NOLOSS_BYPASS_WT5OF5_FILTER_TF=1h | HG2: NOLOSS_BYPASS_WT5OF5_FILTER_TF=15m | HH2: OPEN_INTENT_SIZE_GATES_FILTER_TF=OFF | HI2: OPEN_INTENT_SIZE_GATES_FILTER_TF=D | HJ2: OPEN_INTENT_SIZE_GATES_FILTER_TF=4h | HK2: OPEN_INTENT_SIZE_GATES_FILTER_TF=1h | HL2: OPEN_INTENT_SIZE_GATES_FILTER_TF=15m | HM2: PARTIAL_PROFIT_LOCK_V2_FILTER_TF=OFF | HN2: PARTIAL_PROFIT_LOCK_V2_FILTER_TF=D | HO2: PARTIAL_PROFIT_LOCK_V2_FILTER_TF=4h | HP2: PARTIAL_PROFIT_LOCK_V2_FILTER_TF=1h | HQ2: PARTIAL_PROFIT_LOCK_V2_FILTER_TF=15m | HR2: PEAK_GIVEBACK_BE_EROSION_FILTER_TF=OFF | HS2: PEAK_GIVEBACK_BE_EROSION_FILTER_TF=D | HT2: PEAK_GIVEBACK_BE_EROSION_FILTER_TF=4h | HU2: PEAK_GIVEBACK_BE_EROSION_FILTER_TF=1h | HV2: PEAK_GIVEBACK_BE_EROSION_FILTER_TF=15m | HW2: WT_15M_BOUNCE_BB_MAX=0.95 | HX2: WT_15M_BOUNCE_BB_MAX=0.9 | HY2: WT_15M_BOUNCE_BB_MAX=0.8 | HZ2: WT_15M_BOUNCE_BB_MIN=0.05 | IA2: WT_15M_BOUNCE_BB_MIN=0.1 | IB2: WT_15M_BOUNCE_BB_MIN=0.2 | IC2: WT_15M_BOUNCE_HIGH_1H_GT_PREV=True | ID2: WT_15M_BOUNCE_HIGH_1H_GT_PREV=False | IE2: WT_15M_BOUNCE_LOW_1H_GT_PREV=True | IF2: WT_15M_BOUNCE_LOW_1H_GT_PREV=False | IG2: WT_15M_BOUNCE_REL_VOL_GT_1=True | IH2: WT_15M_BOUNCE_REL_VOL_GT_1=False | II2: Live Location | IJ2: Vec Hook | IK2: Type | IL2: Correct Options
A3: HLR_REENTRY_MULT_1H | B3: 0.75 | E3: -12.1759 | F3: 3.7596 | G3: =IFERROR(VLOOKUP($A3,Results_30d_Deltas!$A$2:$H$5000,7,FALSE)-E3,"") | H3: =IFERROR(VLOOKUP($A3,Results_30d_Deltas!$A$2:$H$5000,6,FALSE),"") | K3: =IF(B3=C3,"YES","NO") | IJ3: ez_manage.py:4846 top() | IK3: v12_quick_engine.py:2026 x7
A4: HLR_REENTRY_MULT_1H | B4: 1.125 | E4: -12.1759 | F4: 3.7596 | G4: =IFERROR(VLOOKUP($A4,Results_30d_Deltas!$A$2:$H$5000,7,FALSE)-E3,"") | H4: =IFERROR(VLOOKUP($A4,Results_30d_Deltas!$A$2:$H$5000,6,FALSE),"") | K4: =IF(B4=C4,"YES","NO") | IJ4: ez_manage.py:4846 top() | IK4: v12_quick_engine.py:2026 x7
A5: HLR_REENTRY_MULT_1H | B5: 1.5 | E5: -12.1759 | F5: 3.7596 | G5: =IFERROR(VLOOKUP($A5,Results_30d_Deltas!$A$2:$H$5000,7,FALSE)-E4,"") | H5: =IFERROR(VLOOKUP($A5,Results_30d_Deltas!$A$2:$H$5000,6,FALSE),"") | K5: =IF(B5=C5,"YES","NO") | IJ5: ez_manage.py:4846 top() | IK5: v12_quick_engine.py:2026 x7
A6: HLR_REENTRY_MULT_1H | B6: 1.875 | E6: -12.1759 | F6: 3.7596 | G6: =IFERROR(VLOOKUP($A6,Results_30d_Deltas!$A$2:$H$5000,7,FALSE)-E5,"") | H6: =IFERROR(VLOOKUP($A6,Results_30d_Deltas!$A$2:$H$5000,6,FALSE),"") | K6: =IF(B6=C6,"YES","NO") | IJ6: ez_manage.py:4846 top() | IK6: v12_quick_engine.py:2026 x7
A7: HLR_REENTRY_MULT_1H | B7: 2.25 | E7: -12.1759 | F7: 3.7596 | G7: =IFERROR(VLOOKUP($A7,Results_30d_Deltas!$A$2:$H$5000,7,FALSE)-E6,"") | H7: =IFERROR(VLOOKUP($A7,Results_30d_Deltas!$A$2:$H$5000,6,FALSE),"") | K7: =IF(B7=C7,"YES","NO") | IJ7: ez_manage.py:4846 top() | IK7: v12_quick_engine.py:2026 x7
A8: CHANNEL_REENTRY_STOP_ENABLED | B8: False | E8: -12.1759 | F8: 3.7596 | G8: =IFERROR(VLOOKUP($A8,Results_30d_Deltas!$A$2:$H$5000,7,FALSE)-E7,"") | H8: =IFERROR(VLOOKUP($A8,Results_30d_Deltas!$A$2:$H$5000,6,FALSE),"") | K8: =IF(B8=C8,"YES","NO") | IJ8: ez_manage.py:5968 top() | IK8: v12_quick_engine.py:482 x8
A9: CHANNEL_REENTRY_STOP_ENABLED | B9: True | E9: -13.3501 | F9: 2.5853 | G9: =IFERROR(VLOOKUP($A9,Results_30d_Deltas!$A$2:$H$5000,7,FALSE)-E8,"") | H9: =IFERROR(VLOOKUP($A9,Results_30d_Deltas!$A$2:$H$5000,6,FALSE),"") | K9: =IF(B9=C9,"YES","NO") | IJ9: ez_manage.py:5968 top() | IK9: v12_quick_engine.py:482 x8
A10: DAEMON_REENTRY_STALE_EXIT_ENABLED | B10: False | E10: -13.748 | F10: 2.1874 | G10: =IFERROR(VLOOKUP($A10,Results_30d_Deltas!$A$2:$H$5000,7,FALSE)-E9,"") | H10: =IFERROR(VLOOKUP($A10,Results_30d_Deltas!$A$2:$H$5000,6,FALSE),"") | K10: =IF(B10=C10,"YES","NO") | IJ10: ez_manage.py:4561 top() | IK10: v12_quick_engine.py:519 x9
A11: DAEMON_REENTRY_STALE_EXIT_ENABLED | B11: True | E11: -13.3501 | F11: 2.5853 | G11: =IFERROR(VLOOKUP($A11,Results_30d_Deltas!$A$2:$H$5000,7,FALSE)-E10,"") | H11: =IFERROR(VLOOKUP($A11,Results_30d_Deltas!$A$2:$H$5000,6,FALSE),"") | K11: =IF(B11=C11,"YES","NO") | IJ11: ez_manage.py:4561 top() | IK11: v12_quick_engine.py:519 x9
A12: BREAKOUT_LEASH_REENTRY_MULT | B12: 0 | E12: -12.1759 | F12: 3.7596 | G12: =IFERROR(VLOOKUP($A12,Results_30d_Deltas!$A$2:$H$5000,7,FALSE)-E11,"") | H12: =IFERROR(VLOOKUP($A12,Results_30d_Deltas!$A$2:$H$5000,6,FALSE),"") | K12: =IF(B12=C12,"YES","NO") | AP12: 3.7101 | AQ12: 2.4718 | AR12: 3.7596 | IJ12: ez_manage.py:2999 top() | IK12: v12_quick_engine.py:371 x12
A13: BREAKOUT_LEASH_REENTRY_MULT | B13: 0.5 | E13: -12.1759 | F13: 3.7596 | G13: =IFERROR(VLOOKUP($A13,Results_30d_Deltas!$A$2:$H$5000,7,FALSE)-E12,"") | H13: =IFERROR(VLOOKUP($A13,Results_30d_Deltas!$A$2:$H$5000,6,FALSE),"") | K13: =IF(B13=C13,"YES","NO") | AP13: 3.7101 | AQ13: 2.4718 | AR13: 3.7596 | IJ13: ez_manage.py:2999 top() | IK13: v12_quick_engine.py:371 x12
A14: BREAKOUT_LEASH_REENTRY_MULT | B14: 1.0 | E14: -12.1759 | F14: 3.7596 | G14: =IFERROR(VLOOKUP($A14,Results_30d_Deltas!$A$2:$H$5000,7,FALSE)-E13,"") | H14: =IFERROR(VLOOKUP($A14,Results_30d_Deltas!$A$2:$H$5000,6,FALSE),"") | K14: =IF(B14=C14,"YES","NO") | AP14: 3.7101 | AQ14: 2.4718 | AR14: 3.7596 | IJ14: ez_manage.py:2999 top() | IK14: v12_quick_engine.py:371 x12
A15: BREAKOUT_LEASH_REENTRY_MULT | B15: 2.0 | E15: -12.1759 | F15: 3.7596 | G15: =IFERROR(VLOOKUP($A15,Results_30d_Deltas!$A$2:$H$5000,7,FALSE)-E14,"") | H15: =IFERROR(VLOOKUP($A15,Results_30d_Deltas!$A$2:$H$5000,6,FALSE),"") | K15: =IF(B15=C15,"YES","NO") | AP15: 3.7101 | AQ15: 2.4718 | AR15: 3.7596 | IJ15: ez_manage.py:2999 top() | IK15: v12_quick_engine.py:371 x12
A16: DAEMON_REENTRY_SHORT_WT_XUNDER_GATE_ENABLED | B16: False | E16: -12.1759 | F16: 3.7596 | G16: =IFERROR(VLOOKUP($A16,Results_30d_Deltas!$A$2:$H$5000,7,FALSE)-E15,"") | H16: =IFERROR(VLOOKUP($A16,Results_30d_Deltas!$A$2:$H$5000,6,FALSE),"") | K16: =IF(B16=C16,"YES","NO") | IJ16: ez_manage.py:4560 top() | IK16: v12_quick_engine.py:513 x9
A17: DAEMON_REENTRY_SHORT_WT_XUNDER_GATE_ENABLED | B17: True | E17: -13.3501 | F17: 2.5853 | G17: =IFERROR(VLOOKUP($A17,Results_30d_Deltas!$A$2:$H$5000,7,FALSE)-E16,"") | H17: =IFERROR(VLOOKUP($A17,Results_30d_Deltas!$A$2:$H$5000,6,FALSE),"") | K17: =IF(B17=C17,"YES","NO") | IJ17: ez_manage.py:4560 top() | IK17: v12_quick_engine.py:513 x9
A18: HLR_REENTRY_MAX_AGE_S | B18: 0 | E18: -13.3501 | F18: 2.5853 | G18: =IFERROR(VLOOKUP($A18,Results_30d_Deltas!$A$2:$H$5000,7,FALSE)-E17,"") | H18: =IFERROR(VLOOKUP($A18,Results_30d_Deltas!$A$2:$H$5000,6,FALSE),"") | K18: =IF(B18=C18,"YES","NO") | IJ18: ez_manage.py:4844 top() | IK18: v12_quick_engine.py:2024 x4
A19: HLR_REENTRY_MAX_AGE_S | B19: 0.5 | E19: -13.3501 | F19: 2.5853 | G19: =IFERROR(VLOOKUP($A19,Results_30d_Deltas!$A$2:$H$5000,7,FALSE)-E18,"") | H19: =IFERROR(VLOOKUP($A19,Results_30d_Deltas!$A$2:$H$5000,6,FALSE),"") | K19: =IF(B19=C19,"YES","NO") | IJ19: ez_manage.py:4844 top() | IK19: v12_quick_engine.py:2024 x4
A20: HLR_REENTRY_MAX_AGE_S | B20: 1.0 | E20: -13.3501 | F20: 2.5853 | G20: =IFERROR(VLOOKUP($A20,Results_30d_Deltas!$A$2:$H$5000,7,FALSE)-E19,"") | H20: =IFERROR(VLOOKUP($A20,Results_30d_Deltas!$A$2:$H$5000,6,FALSE),"") | K20: =IF(B20=C20,"YES","NO") | IJ20: ez_manage.py:4844 top() | IK20: v12_quick_engine.py:2024 x4
A21: HLR_REENTRY_MAX_AGE_S | B21: 2.0 | E21: -13.3501 | F21: 2.5853 | G21: =IFERROR(VLOOKUP($A21,Results_30d_Deltas!$A$2:$H$5000,7,FALSE)-E20,"") | H21: =IFERROR(VLOOKUP($A21,Results_30d_Deltas!$A$2:$H$5000,6,FALSE),"") | K21: =IF(B21=C21,"YES","NO") | IJ21: ez_manage.py:4844 top() | IK21: v12_quick_engine.py:2024 x4
A22: HLR_REENTRY_MULT_4H | B22: 1.0 | E22: -13.3501 | F22: 2.5853 | G22: =IFERROR(VLOOKUP($A22,Results_30d_Deltas!$A$2:$H$5000,7,FALSE)-E21,"") | H22: =IFERROR(VLOOKUP($A22,Results_30d_Deltas!$A$2:$H$5000,6,FALSE),"") | K22: =IF(B22=C22,"YES","NO") | IJ22: ez_manage.py:4847 top() | IK22: v12_quick_engine.py:2027 x6
A23: HLR_REENTRY_MULT_4H | B23: 1.5 | E23: -13.3501 | F23: 2.5853 | G23: =IFERROR(VLOOKUP($A23,Results_30d_Deltas!$A$2:$H$5000,7,FALSE)-E22,"") | H23: =IFERROR(VLOOKUP($A23,Results_30d_Deltas!$A$2:$H$5000,6,FALSE),"") | K23: =IF(B23=C23,"YES","NO") | IJ23: ez_manage.py:4847 top() | IK23: v12_quick_engine.py:2027 x6
A24: HLR_REENTRY_MULT_4H | B24: 2.0 | E24: -13.3501 | F24: 2.5853 | G24: =IFERROR(VLOOKUP($A24,Results_30d_Deltas!$A$2:$H$5000,7,FALSE)-E23,"") | H24: =IFERROR(VLOOKUP($A24,Results_30d_Deltas!$A$2:$H$5000,6,FALSE),"") | K24: =IF(B24=C24,"YES","NO") | IJ24: ez_manage.py:4847 top() | IK24: v12_quick_engine.py:2027 x6
A25: HLR_REENTRY_MULT_4H | B25: 2.5 | E25: -13.3501 | F25: 2.5853 | G25: =IFERROR(VLOOKUP($A25,Results_30d_Deltas!$A$2:$H$5000,7,FALSE)-E24,"") | H25: =IFERROR(VLOOKUP($A25,Results_30d_Deltas!$A$2:$H$5000,6,FALSE),"") | K25: =IF(B25=C25,"YES","NO") | IJ25: ez_manage.py:4847 top() | IK25: v12_quick_engine.py:2027 x6
A26: HLR_REENTRY_MULT_4H | B26: 3.0 | E26: -13.3501 | F26: 2.5853 | G26: =IFERROR(VLOOKUP($A26,Results_30d_Deltas!$A$2:$H$5000,7,FALSE)-E25,"") | H26: =IFERROR(VLOOKUP($A26,Results_30d_Deltas!$A$2:$H$5000,6,FALSE),"") | K26: =IF(B26=C26,"YES","NO") | IJ26: ez_manage.py:4847 top() | IK26: v12_quick_engine.py:2027 x6
A27: HLR_REENTRY_MULT_D | B27: 1.25 | E27: -13.748 | F27: 2.1874 | G27: =IFERROR(VLOOKUP($A27,Results_30d_Deltas!$A$2:$H$5000,7,FALSE)-E26,"") | H27: =IFERROR(VLOOKUP($A27,Results_30d_Deltas!$A$2:$H$5000,6,FALSE),"") | K27: =IF(B27=C27,"YES","NO") | IJ27: ez_manage.py:4848 top() | IK27: v12_quick_engine.py:2028 x4
... A36: HLR_REENTRY_MULT_W | B36: 4.5 | E36: -12.1759 | F36: 3.7596 | G36: =IFERROR(VLOOKUP($A36,Results_30d_Deltas!$A$2:$H$5000,7,FALSE)-E35,"") | H36: =IFERROR(VLOOKUP($A36,Results_30d_Deltas!$A$2:$H$5000,6,FALSE),"") | K36: =IF(B36=C36,"YES","NO") | IJ36: ez_manage.py:4849 top() | IK36: v12_quick_engine.py:2029 x4
A37: REENTRY_SIZE_BREAKOUT_MULT | B37: 0 | E37: -13.3501 | F37: 2.5853 | G37: =IFERROR(VLOOKUP($A37,Results_30d_Deltas!$A$2:$H$5000,7,FALSE)-E36,"") | H37: =IFERROR(VLOOKUP($A37,Results_30d_Deltas!$A$2:$H$5000,6,FALSE),"") | K37: =IF(B37=C37,"YES","NO") | AP37: 0.4886 | AQ37: 2.1874 | AR37: 2.4718 | IJ37: ez_manage.py:3870 top() | IK37: v12_quick_engine.py:2903 x3
A38: REENTRY_SIZE_BREAKOUT_MULT | B38: 0.5 | E38: -13.3501 | F38: 2.5853 | G38: =IFERROR(VLOOKUP($A38,Results_30d_Deltas!$A$2:$H$5000,7,FALSE)-E37,"") | H38: =IFERROR(VLOOKUP($A38,Results_30d_Deltas!$A$2:$H$5000,6,FALSE),"") | K38: =IF(B38=C38,"YES","NO") | AP38: 0.4886 | AQ38: 2.1874 | AR38: 2.4718 | IJ38: ez_manage.py:3870 top() | IK38: v12_quick_engine.py:2903 x3
A39: REENTRY_SIZE_BREAKOUT_MULT | B39: 1.0 | E39: -13.3501 | F39: 2.5853 | G39: =IFERROR(VLOOKUP($A39,Results_30d_Deltas!$A$2:$H$5000,7,FALSE)-E38,"") | H39: =IFERROR(VLOOKUP($A39,Results_30d_Deltas!$A$2:$H$5000,6,FALSE),"") | K39: =IF(B39=C39,"YES","NO") | AP39: 0.4886 | AQ39: 2.1874 | AR39: 2.4718 | IJ39: ez_manage.py:3870 top() | IK39: v12_quick_engine.py:2903 x3
A40: REENTRY_SIZE_BREAKOUT_MULT | B40: 2.0 | E40: -13.3501 | F40: 2.5853 | G40: =IFERROR(VLOOKUP($A40,Results_30d_Deltas!$A$2:$H$5000,7,FALSE)-E39,"") | H40: =IFERROR(VLOOKUP($A40,Results_30d_Deltas!$A$2:$H$5000,6,FALSE),"") | K40: =IF(B40=C40,"YES","NO") | AP40: 0.4886 | AQ40: 2.1874 | AR40: 2.4718 | IJ40: ez_manage.py:3870 top() | IK40: v12_quick_engine.py:2903 x3

Sheet AUGMENT_TREND
A1: 08 AUGMENT_TREND - 5 bases -> 24 rows - 231 per-row FULLY CONNECTED
A2: Switch | B2: default | C2: override | D2: Family | E2: BASELINE | F2: VECTOR_DELTA | G2: LIVE_DELTA | H2: LIVE_SHARPE | I2: REAL_COMPLETE | J2: PER_ROW_FILTERS | K2: is_default (backup if bold lost) | L2: ATR_TRAIL_FILTER_TF=OFF | M2: ATR_TRAIL_FILTER_TF=D | N2: ATR_TRAIL_FILTER_TF=4h | O2: ATR_TRAIL_FILTER_TF=1h | P2: ATR_TRAIL_FILTER_TF=15m | Q2: BAR_PATTERNS_FILTER_TF=OFF | R2: BAR_PATTERNS_FILTER_TF=D | S2: BAR_PATTERNS_FILTER_TF=4h | T2: BAR_PATTERNS_FILTER_TF=1h | U2: BAR_PATTERNS_FILTER_TF=15m | V2: BB_PULLBACK_GATE_FILTER_TF=OFF | W2: BB_PULLBACK_GATE_FILTER_TF=D | X2: BB_PULLBACK_GATE_FILTER_TF=4h | Y2: BB_PULLBACK_GATE_FILTER_TF=1h | Z2: BB_PULLBACK_GATE_FILTER_TF=15m | AA2: BB_RECOVERY_ENTRY_FILTER_TF=OFF | AB2: BB_RECOVERY_ENTRY_FILTER_TF=D | AC2: BB_RECOVERY_ENTRY_FILTER_TF=4h | AD2: BB_RECOVERY_ENTRY_FILTER_TF=1h | AE2: BB_RECOVERY_ENTRY_FILTER_TF=15m | AF2: BB_RECOVERY_FILTER_TF=OFF | AG2: BB_RECOVERY_FILTER_TF=D | AH2: BB_RECOVERY_FILTER_TF=4h | AI2: BB_RECOVERY_FILTER_TF=1h | AJ2: BB_RECOVERY_FILTER_TF=15m | AK2: BREAKEVEN_GAIN_EROSION_FILTER_TF=OFF | AL2: BREAKEVEN_GAIN_EROSION_FILTER_TF=D | AM2: BREAKEVEN_GAIN_EROSION_FILTER_TF=4h | AN2: BREAKEVEN_GAIN_EROSION_FILTER_TF=1h | AO2: BREAKEVEN_GAIN_EROSION_FILTER_TF=15m | AP2: BREAKOUT_RETEST_FILTER_TF=OFF | AQ2: BREAKOUT_RETEST_FILTER_TF=D | AR2: BREAKOUT_RETEST_FILTER_TF=4h | AS2: BREAKOUT_RETEST_FILTER_TF=1h | AT2: BREAKOUT_RETEST_FILTER_TF=15m | AU2: BT_WT_CROSS_LADDER_FILTER_TF=OFF | AV2: BT_WT_CROSS_LADDER_FILTER_TF=D | AW2: BT_WT_CROSS_LADDER_FILTER_TF=4h | AX2: BT_WT_CROSS_LADDER_FILTER_TF=1h | AY2: BT_WT_CROSS_LADDER_FILTER_TF=15m | AZ2: CANDLE_PATTERN_STOPS_FILTER_TF=OFF | BA2: CANDLE_PATTERN_STOPS_FILTER_TF=D | BB2: CANDLE_PATTERN_STOPS_FILTER_TF=4h | BC2: CANDLE_PATTERN_STOPS_FILTER_TF=1h | BD2: CANDLE_PATTERN_STOPS_FILTER_TF=15m | BE2: CIRCUIT_SHARPE_GATES_FILTER_TF=OFF | BF2: CIRCUIT_SHARPE_GATES_FILTER_TF=D | BG2: CIRCUIT_SHARPE_GATES_FILTER_TF=4h | BH2: CIRCUIT_SHARPE_GATES_FILTER_TF=1h | BI2: CIRCUIT_SHARPE_GATES_FILTER_TF=15m | BJ2: DC_BREACH_REDUCE_FILTER_TF=OFF | BK2: DC_BREACH_REDUCE_FILTER_TF=D | BL2: DC_BREACH_REDUCE_FILTER_TF=4h | BM2: DC_BREACH_REDUCE_FILTER_TF=1h | BN2: DC_BREACH_REDUCE_FILTER_TF=15m | BO2: DC_BREAK_FILTER_TF=OFF | BP2: DC_BREAK_FILTER_TF=D | BQ2: DC_BREAK_FILTER_TF=4h | BR2: DC_BREAK_FILTER_TF=1h | BS2: DC_BREAK_FILTER_TF=15m | BT2: DC_MOMENTUM_BOTA_SCORER_FILTER_TF=OFF | BU2: DC_MOMENTUM_BOTA_SCORER_FILTER_TF=D | BV2: DC_MOMENTUM_BOTA_SCORER_FILTER_TF=4h | BW2: DC_MOMENTUM_BOTA_SCORER_FILTER_TF=1h | BX2: DC_MOMENTUM_BOTA_SCORER_FILTER_TF=15m | BY2: DELTA_ENGINE_FILTER_TF=OFF | BZ2: DELTA_ENGINE_FILTER_TF=D | CA2: DELTA_ENGINE_FILTER_TF=4h | CB2: DELTA_ENGINE_FILTER_TF=1h | CC2: DELTA_ENGINE_FILTER_TF=15m | CD2: EMA_9_21_FILTER_FILTER_TF=OFF | CE2: EMA_9_21_FILTER_FILTER_TF=D | CF2: EMA_9_21_FILTER_FILTER_TF=4h | CG2: EMA_9_21_FILTER_FILTER_TF=1h | CH2: EMA_9_21_FILTER_FILTER_TF=15m | CI2: EMA_BLANKET_FILTER_FILTER_TF=OFF | CJ2: EMA_BLANKET_FILTER_FILTER_TF=D | CK2: EMA_BLANKET_FILTER_FILTER_TF=4h | CL2: EMA_BLANKET_FILTER_FILTER_TF=1h | CM2: EMA_BLANKET_FILTER_FILTER_TF=15m | CN2: EMERGENCY_BRAKE_FILTER_TF=OFF | CO2: EMERGENCY_BRAKE_FILTER_TF=D | CP2: EMERGENCY_BRAKE_FILTER_TF=4h | CQ2: EMERGENCY_BRAKE_FILTER_TF=1h | CR2: EMERGENCY_BRAKE_FILTER_TF=15m | CS2: EXIT_R1_R2_FILTER_TF=OFF | CT2: EXIT_R1_R2_FILTER_TF=D | CU2: EXIT_R1_R2_FILTER_TF=4h | CV2: EXIT_R1_R2_FILTER_TF=1h | CW2: EXIT_R1_R2_FILTER_TF=15m | CX2: EXIT_TIGHT_BREAKOUT_SCORER_FILTER_TF=OFF | CY2: EXIT_TIGHT_BREAKOUT_SCORER_FILTER_TF=D | CZ2: EXIT_TIGHT_BREAKOUT_SCORER_FILTER_TF=4h | DA2: EXIT_TIGHT_BREAKOUT_SCORER_FILTER_TF=1h | DB2: EXIT_TIGHT_BREAKOUT_SCORER_FILTER_TF=15m | DC2: EXIT_TOP_FADE_FILTER_TF=OFF | DD2: EXIT_TOP_FADE_FILTER_TF=D | DE2: EXIT_TOP_FADE_FILTER_TF=4h | DF2: EXIT_TOP_FADE_FILTER_TF=1h | DG2: EXIT_TOP_FADE_FILTER_TF=15m | DH2: EXIT_TO_REDUCE_ADAPTER_FILTER_TF=OFF | DI2: EXIT_TO_REDUCE_ADAPTER_FILTER_TF=D | DJ2: EXIT_TO_REDUCE_ADAPTER_FILTER_TF=4h | DK2: EXIT_TO_REDUCE_ADAPTER_FILTER_TF=1h | DL2: EXIT_TO_REDUCE_ADAPTER_FILTER_TF=15m | DM2: FAST_RISER_FILTER_TF=OFF | DN2: FAST_RISER_FILTER_TF=D | DO2: FAST_RISER_FILTER_TF=4h | DP2: FAST_RISER_FILTER_TF=1h | DQ2: FAST_RISER_FILTER_TF=15m | DR2: FH_MOMENTUM_FILTER_TF=OFF | DS2: FH_MOMENTUM_FILTER_TF=D | DT2: FH_MOMENTUM_FILTER_TF=4h | DU2: FH_MOMENTUM_FILTER_TF=1h | DV2: FH_MOMENTUM_FILTER_TF=15m | DW2: FIRST_OPEN_THROTTLE_FILTER_TF=OFF | DX2: FIRST_OPEN_THROTTLE_FILTER_TF=D | DY2: FIRST_OPEN_THROTTLE_FILTER_TF=4h | DZ2: FIRST_OPEN_THROTTLE_FILTER_TF=1h | EA2: FIRST_OPEN_THROTTLE_FILTER_TF=15m | EB2: FROZEN_STOP_FILTER_TF=OFF | EC2: FROZEN_STOP_FILTER_TF=D | ED2: FROZEN_STOP_FILTER_TF=4h | EE2: FROZEN_STOP_FILTER_TF=1h | EF2: FROZEN_STOP_FILTER_TF=15m | EG2: GOLDEN_RULE_ENFORCE_FILTER_TF=OFF | EH2: GOLDEN_RULE_ENFORCE_FILTER_TF=D | EI2: GOLDEN_RULE_ENFORCE_FILTER_TF=4h | EJ2: GOLDEN_RULE_ENFORCE_FILTER_TF=1h | EK2: GOLDEN_RULE_ENFORCE_FILTER_TF=15m | EL2: GOLDEN_RULE_HTF_VOTE_FILTER_TF=OFF | EM2: GOLDEN_RULE_HTF_VOTE_FILTER_TF=D | EN2: GOLDEN_RULE_HTF_VOTE_FILTER_TF=4h | EO2: GOLDEN_RULE_HTF_VOTE_FILTER_TF=1h | EP2: GOLDEN_RULE_HTF_VOTE_FILTER_TF=15m | EQ2: GR_FILTER_VEC_FILTER_TF=OFF | ER2: GR_FILTER_VEC_FILTER_TF=D | ES2: GR_FILTER_VEC_FILTER_TF=4h | ET2: GR_FILTER_VEC_FILTER_TF=1h | EU2: GR_FILTER_VEC_FILTER_TF=15m | EV2: GR_V5_STATE_FILTER_TF=OFF | EW2: GR_V5_STATE_FILTER_TF=D | EX2: GR_V5_STATE_FILTER_TF=4h | EY2: GR_V5_STATE_FILTER_TF=1h | EZ2: GR_V5_STATE_FILTER_TF=15m | FA2: HAIKU_WINNER_FILTER_TF=OFF | FB2: HAIKU_WINNER_FILTER_TF=D | FC2: HAIKU_WINNER_FILTER_TF=4h | FD2: HAIKU_WINNER_FILTER_TF=1h | FE2: HAIKU_WINNER_FILTER_TF=15m | FF2: LH_HL_FILTER_TF_REQ=2 | FG2: LH_HL_FILTER_TF_REQ=2_ALT | FH2: LIVE_ENTRY_ENGINE_FILTER_TF=OFF | FI2: LIVE_ENTRY_ENGINE_FILTER_TF=D | FJ2: LIVE_ENTRY_ENGINE_FILTER_TF=4h | FK2: LIVE_ENTRY_ENGINE_FILTER_TF=1h | FL2: LIVE_ENTRY_ENGINE_FILTER_TF=15m | FM2: LIVE_ONLY_SIGNALS_BATCH5_FILTER_TF=OFF | FN2: LIVE_ONLY_SIGNALS_BATCH5_FILTER_TF=D | FO2: LIVE_ONLY_SIGNALS_BATCH5_FILTER_TF=4h | FP2: LIVE_ONLY_SIGNALS_BATCH5_FILTER_TF=1h | FQ2: LIVE_ONLY_SIGNALS_BATCH5_FILTER_TF=15m | FR2: MANDATORY_REENTRY_WT_FILTER_TF_MODE=15m_only | FS2: MANDATORY_REENTRY_WT_FILTER_TF_MODE=15m_only_ALT | FT2: MOM3_FILTER_TF=OFF | FU2: MOM3_FILTER_TF=D | FV2: MOM3_FILTER_TF=4h | FW2: MOM3_FILTER_TF=1h | FX2: MOM3_FILTER_TF=15m | FY2: MOMENTUM_BREAKOUT_FILTER_TF=OFF | FZ2: MOMENTUM_BREAKOUT_FILTER_TF=D | GA2: MOMENTUM_BREAKOUT_FILTER_TF=4h | GB2: MOMENTUM_BREAKOUT_FILTER_TF=1h | GC2: MOMENTUM_BREAKOUT_FILTER_TF=15m | GD2: MTF_ARMED_ENTRIES_FILTER_TF=OFF | GE2: MTF_ARMED_ENTRIES_FILTER_TF=D | GF2: MTF_ARMED_ENTRIES_FILTER_TF=4h | GG2: MTF_ARMED_ENTRIES_FILTER_TF=1h | GH2: MTF_ARMED_ENTRIES_FILTER_TF=15m | GI2: MTF_ATR_TRAIL_FILTER_TF=OFF | GJ2: MTF_ATR_TRAIL_FILTER_TF=D | GK2: MTF_ATR_TRAIL_FILTER_TF=4h | GL2: MTF_ATR_TRAIL_FILTER_TF=1h | GM2: MTF_ATR_TRAIL_FILTER_TF=15m | GN2: MTF_DC_REJECT_FILTER_TF=OFF | GO2: MTF_DC_REJECT_FILTER_TF=D | GP2: MTF_DC_REJECT_FILTER_TF=4h | GQ2: MTF_DC_REJECT_FILTER_TF=1h | GR2: MTF_DC_REJECT_FILTER_TF=15m | GS2: NEWBORN_LOSS_KILL_FILTER_TF=OFF | GT2: NEWBORN_LOSS_KILL_FILTER_TF=D | GU2: NEWBORN_LOSS_KILL_FILTER_TF=4h | GV2: NEWBORN_LOSS_KILL_FILTER_TF=1h | GW2: NEWBORN_LOSS_KILL_FILTER_TF=15m | GX2: NEWBORN_PROTECT_FILTER_TF=OFF | GY2: NEWBORN_PROTECT_FILTER_TF=D | GZ2: NEWBORN_PROTECT_FILTER_TF=4h | HA2: NEWBORN_PROTECT_FILTER_TF=1h | HB2: NEWBORN_PROTECT_FILTER_TF=15m | HC2: NOLOSS_BYPASS_WT5OF5_FILTER_TF=OFF | HD2: NOLOSS_BYPASS_WT5OF5_FILTER_TF=D | HE2: NOLOSS_BYPASS_WT5OF5_FILTER_TF=4h | HF2: NOLOSS_BYPASS_WT5OF5_FILTER_TF=1h | HG2: NOLOSS_BYPASS_WT5OF5_FILTER_TF=15m | HH2: OPEN_INTENT_SIZE_GATES_FILTER_TF=OFF | HI2: OPEN_INTENT_SIZE_GATES_FILTER_TF=D | HJ2: OPEN_INTENT_SIZE_GATES_FILTER_TF=4h | HK2: OPEN_INTENT_SIZE_GATES_FILTER_TF=1h | HL2: OPEN_INTENT_SIZE_GATES_FILTER_TF=15m | HM2: PARTIAL_PROFIT_LOCK_V2_FILTER_TF=OFF | HN2: PARTIAL_PROFIT_LOCK_V2_FILTER_TF=D | HO2: PARTIAL_PROFIT_LOCK_V2_FILTER_TF=4h | HP2: PARTIAL_PROFIT_LOCK_V2_FILTER_TF=1h | HQ2: PARTIAL_PROFIT_LOCK_V2_FILTER_TF=15m | HR2: PEAK_GIVEBACK_BE_EROSION_FILTER_TF=OFF | HS2: PEAK_GIVEBACK_BE_EROSION_FILTER_TF=D | HT2: PEAK_GIVEBACK_BE_EROSION_FILTER_TF=4h | HU2: PEAK_GIVEBACK_BE_EROSION_FILTER_TF=1h | HV2: PEAK_GIVEBACK_BE_EROSION_FILTER_TF=15m | HW2: WT_15M_BOUNCE_BB_MAX=0.95 | HX2: WT_15M_BOUNCE_BB_MAX=0.9 | HY2: WT_15M_BOUNCE_BB_MAX=0.8 | HZ2: WT_15M_BOUNCE_BB_MIN=0.05 | IA2: WT_15M_BOUNCE_BB_MIN=0.1 | IB2: WT_15M_BOUNCE_BB_MIN=0.2 | IC2: WT_15M_BOUNCE_HIGH_1H_GT_PREV=True | ID2: WT_15M_BOUNCE_HIGH_1H_GT_PREV=False | IE2: WT_15M_BOUNCE_LOW_1H_GT_PREV=True | IF2: WT_15M_BOUNCE_LOW_1H_GT_PREV=False | IG2: WT_15M_BOUNCE_REL_VOL_GT_1=True | IH2: WT_15M_BOUNCE_REL_VOL_GT_1=False | II2: Live Location | IJ2: Vec Hook | IK2: Type | IL2: Correct Options
A3: AUGMENT_MIN_GAIN_PCT | B3: 0.25 | E3: 1.4919 | F3: 17.4273 | G3: =IFERROR(VLOOKUP($A3,Results_30d_Deltas!$A$2:$H$5000,7,FALSE)-E3,"") | H3: =IFERROR(VLOOKUP($A3,Results_30d_Deltas!$A$2:$H$5000,6,FALSE),"") | K3: =IF(B3=C3,"YES","NO") | AK3: 17.4273 | AL3: 17.4273 | AM3: 16.6087 | IJ3: ez_manage.py:30417 top() | IK3: v12_quick_engine.py:4874 x5
A4: AUGMENT_MIN_GAIN_PCT | B4: 0.375 | E4: 1.4919 | F4: 17.4273 | G4: =IFERROR(VLOOKUP($A4,Results_30d_Deltas!$A$2:$H$5000,7,FALSE)-E3,"") | H4: =IFERROR(VLOOKUP($A4,Results_30d_Deltas!$A$2:$H$5000,6,FALSE),"") | K4: =IF(B4=C4,"YES","NO") | AK4: 17.4273 | AL4: 17.4273 | AM4: 16.6087 | IJ4: ez_manage.py:30417 top() | IK4: v12_quick_engine.py:4874 x5
A5: AUGMENT_MIN_GAIN_PCT | B5: 0.5 | E5: 1.4919 | F5: 17.4273 | G5: =IFERROR(VLOOKUP($A5,Results_30d_Deltas!$A$2:$H$5000,7,FALSE)-E4,"") | H5: =IFERROR(VLOOKUP($A5,Results_30d_Deltas!$A$2:$H$5000,6,FALSE),"") | K5: =IF(B5=C5,"YES","NO") | AK5: 17.4273 | AL5: 17.4273 | AM5: 16.6087 | IJ5: ez_manage.py:30417 top() | IK5: v12_quick_engine.py:4874 x5
A6: AUGMENT_MIN_GAIN_PCT | B6: 0.625 | E6: 1.4919 | F6: 17.4273 | G6: =IFERROR(VLOOKUP($A6,Results_30d_Deltas!$A$2:$H$5000,7,FALSE)-E5,"") | H6: =IFERROR(VLOOKUP($A6,Results_30d_Deltas!$A$2:$H$5000,6,FALSE),"") | K6: =IF(B6=C6,"YES","NO") | AK6: 17.4273 | AL6: 17.4273 | AM6: 16.6087 | IJ6: ez_manage.py:30417 top() | IK6: v12_quick_engine.py:4874 x5
A7: AUGMENT_MIN_GAIN_PCT | B7: 0.75 | E7: 1.4919 | F7: 17.4273 | G7: =IFERROR(VLOOKUP($A7,Results_30d_Deltas!$A$2:$H$5000,7,FALSE)-E6,"") | H7: =IFERROR(VLOOKUP($A7,Results_30d_Deltas!$A$2:$H$5000,6,FALSE),"") | K7: =IF(B7=C7,"YES","NO") | AK7: 17.4273 | AL7: 17.4273 | AM7: 16.6087 | IJ7: ez_manage.py:30417 top() | IK7: v12_quick_engine.py:4874 x5
A8: BOUNCE_AUGMENT_MIN_LOSS_PCT | B8: -0.75 | E8: -12.1759 | F8: 3.7596 | G8: =IFERROR(VLOOKUP($A8,Results_30d_Deltas!$A$2:$H$5000,7,FALSE)-E7,"") | H8: =IFERROR(VLOOKUP($A8,Results_30d_Deltas!$A$2:$H$5000,6,FALSE),"") | K8: =IF(B8=C8,"YES","NO") | IJ8: ez_manage.py:4390 top() | IK8: v12_quick_engine.py:1310 x9
A9: BOUNCE_AUGMENT_MIN_LOSS_PCT | B9: -0.625 | E9: -12.1759 | F9: 3.7596 | G9: =IFERROR(VLOOKUP($A9,Results_30d_Deltas!$A$2:$H$5000,7,FALSE)-E8,"") | H9: =IFERROR(VLOOKUP($A9,Results_30d_Deltas!$A$2:$H$5000,6,FALSE),"") | K9: =IF(B9=C9,"YES","NO") | IJ9: ez_manage.py:4390 top() | IK9: v12_quick_engine.py:1310 x9
A10: BOUNCE_AUGMENT_MIN_LOSS_PCT | B10: -0.5 | E10: -12.1759 | F10: 3.7596 | G10: =IFERROR(VLOOKUP($A10,Results_30d_Deltas!$A$2:$H$5000,7,FALSE)-E9,"") | H10: =IFERROR(VLOOKUP($A10,Results_30d_Deltas!$A$2:$H$5000,6,FALSE),"") | K10: =IF(B10=C10,"YES","NO") | IJ10: ez_manage.py:4390 top() | IK10: v12_quick_engine.py:1310 x9
A11: BOUNCE_AUGMENT_MIN_LOSS_PCT | B11: -0.375 | E11: -12.1759 | F11: 3.7596 | G11: =IFERROR(VLOOKUP($A11,Results_30d_Deltas!$A$2:$H$5000,7,FALSE)-E10,"") | H11: =IFERROR(VLOOKUP($A11,Results_30d_Deltas!$A$2:$H$5000,6,FALSE),"") | K11: =IF(B11=C11,"YES","NO") | IJ11: ez_manage.py:4390 top() | IK11: v12_quick_engine.py:1310 x9
A12: BOUNCE_AUGMENT_MIN_LOSS_PCT | B12: -0.25 | E12: -12.1759 | F12: 3.7596 | G12: =IFERROR(VLOOKUP($A12,Results_30d_Deltas!$A$2:$H$5000,7,FALSE)-E11,"") | H12: =IFERROR(VLOOKUP($A12,Results_30d_Deltas!$A$2:$H$5000,6,FALSE),"") | K12: =IF(B12=C12,"YES","NO") | IJ12: ez_manage.py:4390 top() | IK12: v12_quick_engine.py:1310 x9
A13: AUGMENT_BOUNCE_MIN_GAIN_PCT | B13: 0.25 | E13: 1.3736 | F13: 17.309 | G13: =IFERROR(VLOOKUP($A13,Results_30d_Deltas!$A$2:$H$5000,7,FALSE)-E12,"") | H13: =IFERROR(VLOOKUP($A13,Results_30d_Deltas!$A$2:$H$5000,6,FALSE),"") | K13: =IF(B13=C13,"YES","NO") | AK13: 16.4556 | AL13: 16.4197 | AM13: 16.4506 | IJ13: ez_manage.py:56856 top() | IK13: v12_quick_engine.py:4872 x2
A14: AUGMENT_BOUNCE_MIN_GAIN_PCT | B14: 0.375 | E14: 1.3736 | F14: 17.309 | G14: =IFERROR(VLOOKUP($A14,Results_30d_Deltas!$A$2:$H$5000,7,FALSE)-E13,"") | H14: =IFERROR(VLOOKUP($A14,Results_30d_Deltas!$A$2:$H$5000,6,FALSE),"") | K14: =IF(B14=C14,"YES","NO") | AK14: 16.4556 | AL14: 16.4197 | AM14: 16.4506 | IJ14: ez_manage.py:56856 top() | IK14: v12_quick_engine.py:4872 x2
A15: AUGMENT_BOUNCE_MIN_GAIN_PCT | B15: 0.5 | E15: 1.3736 | F15: 17.309 | G15: =IFERROR(VLOOKUP($A15,Results_30d_Deltas!$A$2:$H$5000,7,FALSE)-E14,"") | H15: =IFERROR(VLOOKUP($A15,Results_30d_Deltas!$A$2:$H$5000,6,FALSE),"") | K15: =IF(B15=C15,"YES","NO") | AK15: 16.4556 | AL15: 16.4197 | AM15: 16.4506 | IJ15: ez_manage.py:56856 top() | IK15: v12_quick_engine.py:4872 x2
A16: AUGMENT_BOUNCE_MIN_GAIN_PCT | B16: 0.625 | E16: 1.3736 | F16: 17.309 | G16: =IFERROR(VLOOKUP($A16,Results_30d_Deltas!$A$2:$H$5000,7,FALSE)-E15,"") | H16: =IFERROR(VLOOKUP($A16,Results_30d_Deltas!$A$2:$H$5000,6,FALSE),"") | K16: =IF(B16=C16,"YES","NO") | AK16: 16.4556 | AL16: 16.4197 | AM16: 16.4506 | IJ16: ez_manage.py:56856 top() | IK16: v12_quick_engine.py:4872 x2
A17: AUGMENT_BOUNCE_MIN_GAIN_PCT | B17: 0.75 | E17: 1.3736 | F17: 17.309 | G17: =IFERROR(VLOOKUP($A17,Results_30d_Deltas!$A$2:$H$5000,7,FALSE)-E16,"") | H17: =IFERROR(VLOOKUP($A17,Results_30d_Deltas!$A$2:$H$5000,6,FALSE),"") | K17: =IF(B17=C17,"YES","NO") | AK17: 16.4556 | AL17: 16.4197 | AM17: 16.4506 | IJ17: ez_manage.py:56856 top() | IK17: v12_quick_engine.py:4872 x2
A18: AUGMENT_BREAKOUT_MIN_GAIN_PCT | B18: 0.25 | E18: 0.8125 | F18: 16.7479 | G18: =IFERROR(VLOOKUP($A18,Results_30d_Deltas!$A$2:$H$5000,7,FALSE)-E17,"") | H18: =IFERROR(VLOOKUP($A18,Results_30d_Deltas!$A$2:$H$5000,6,FALSE),"") | K18: =IF(B18=C18,"YES","NO") | AK18: 16.7467 | AL18: 16.6837 | AM18: 16.7167 | IJ18: ez_manage.py:56860 top() | IK18: v12_quick_engine.py:4873 x2
A19: AUGMENT_BREAKOUT_MIN_GAIN_PCT | B19: 0.375 | E19: 0.8125 | F19: 16.7479 | G19: =IFERROR(VLOOKUP($A19,Results_30d_Deltas!$A$2:$H$5000,7,FALSE)-E18,"") | H19: =IFERROR(VLOOKUP($A19,Results_30d_Deltas!$A$2:$H$5000,6,FALSE),"") | K19: =IF(B19=C19,"YES","NO") | AK19: 16.7467 | AL19: 16.6837 | AM19: 16.7167 | IJ19: ez_manage.py:56860 top() | IK19: v12_quick_engine.py:4873 x2
A20: AUGMENT_BREAKOUT_MIN_GAIN_PCT | B20: 0.5 | E20: 0.8125 | F20: 16.7479 | G20: =IFERROR(VLOOKUP($A20,Results_30d_Deltas!$A$2:$H$5000,7,FALSE)-E19,"") | H20: =IFERROR(VLOOKUP($A20,Results_30d_Deltas!$A$2:$H$5000,6,FALSE),"") | K20: =IF(B20=C20,"YES","NO") | AK20: 16.7467 | AL20: 16.6837 | AM20: 16.7167 | IJ20: ez_manage.py:56860 top() | IK20: v12_quick_engine.py:4873 x2
A21: AUGMENT_BREAKOUT_MIN_GAIN_PCT | B21: 0.625 | E21: 0.8125 | F21: 16.7479 | G21: =IFERROR(VLOOKUP($A21,Results_30d_Deltas!$A$2:$H$5000,7,FALSE)-E20,"") | H21: =IFERROR(VLOOKUP($A21,Results_30d_Deltas!$A$2:$H$5000,6,FALSE),"") | K21: =IF(B21=C21,"YES","NO") | AK21: 16.7467 | AL21: 16.6837 | AM21: 16.7167 | IJ21: ez_manage.py:56860 top() | IK21: v12_quick_engine.py:4873 x2
A22: AUGMENT_BREAKOUT_MIN_GAIN_PCT | B22: 0.75 | E22: 0.8125 | F22: 16.7479 | G22: =IFERROR(VLOOKUP($A22,Results_30d_Deltas!$A$2:$H$5000,7,FALSE)-E21,"") | H22: =IFERROR(VLOOKUP($A22,Results_30d_Deltas!$A$2:$H$5000,6,FALSE),"") | K22: =IF(B22=C22,"YES","NO") | AK22: 16.7467 | AL22: 16.6837 | AM22: 16.7167 | IJ22: ez_manage.py:56860 top() | IK22: v12_quick_engine.py:4873 x2
A23: HTF_GATE_APPLY_TO_AUGMENT | B23: 0 | E23: -12.1759 | F23: 3.7596 | G23: =IFERROR(VLOOKUP($A23,Results_30d_Deltas!$A$2:$H$5000,7,FALSE)-E22,"") | H23: =IFERROR(VLOOKUP($A23,Results_30d_Deltas!$A$2:$H$5000,6,FALSE),"") | K23: =IF(B23=C23,"YES","NO") | IJ23: ez_manage.py:4876 top() | IK23: v12_quick_engine.py:2052 x6
A24: HTF_GATE_APPLY_TO_AUGMENT | B24: 0.5 | E24: -12.1759 | F24: 3.7596 | G24: =IFERROR(VLOOKUP($A24,Results_30d_Deltas!$A$2:$H$5000,7,FALSE)-E23,"") | H24: =IFERROR(VLOOKUP($A24,Results_30d_Deltas!$A$2:$H$5000,6,FALSE),"") | K24: =IF(B24=C24,"YES","NO") | IJ24: ez_manage.py:4876 top() | IK24: v12_quick_engine.py:2052 x6
A25: HTF_GATE_APPLY_TO_AUGMENT | B25: 1.0 | E25: -12.1759 | F25: 3.7596 | G25: =IFERROR(VLOOKUP($A25,Results_30d_Deltas!$A$2:$H$5000,7,FALSE)-E24,"") | H25: =IFERROR(VLOOKUP($A25,Results_30d_Deltas!$A$2:$H$5000,6,FALSE),"") | K25: =IF(B25=C25,"YES","NO") | IJ25: ez_manage.py:4876 top() | IK25: v12_quick_engine.py:2052 x6
A26: HTF_GATE_APPLY_TO_AUGMENT | B26: 2.0 | E26: -12.1759 | F26: 3.7596 | G26: =IFERROR(VLOOKUP($A26,Results_30d_Deltas!$A$2:$H$5000,7,FALSE)-E25,"") | H26: =IFERROR(VLOOKUP($A26,Results_30d_Deltas!$A$2:$H$5000,6,FALSE),"") | K26: =IF(B26=C26,"YES","NO") | IJ26: ez_manage.py:4876 top() | IK26: v12_quick_engine.py:2052 x6

Sheet AUGMENT_RISK_SIZING
A1: 09 AUGMENT_RISK_SIZING - 17 bases -> 56 rows - 231 per-row FULLY CONNECTED
A2: Switch | B2: default | C2: override | D2: Family | E2: BASELINE | F2: VECTOR_DELTA | G2: LIVE_DELTA | H2: LIVE_SHARPE | I2: REAL_COMPLETE | J2: PER_ROW_FILTERS | K2: is_default (backup if bold lost) | L2: ATR_TRAIL_FILTER_TF=OFF | M2: ATR_TRAIL_FILTER_TF=D | N2: ATR_TRAIL_FILTER_TF=4h | O2: ATR_TRAIL_FILTER_TF=1h | P2: ATR_TRAIL_FILTER_TF=15m | Q2: BAR_PATTERNS_FILTER_TF=OFF | R2: BAR_PATTERNS_FILTER_TF=D | S2: BAR_PATTERNS_FILTER_TF=4h | T2: BAR_PATTERNS_FILTER_TF=1h | U2: BAR_PATTERNS_FILTER_TF=15m | V2: BB_PULLBACK_GATE_FILTER_TF=OFF | W2: BB_PULLBACK_GATE_FILTER_TF=D | X2: BB_PULLBACK_GATE_FILTER_TF=4h | Y2: BB_PULLBACK_GATE_FILTER_TF=1h | Z2: BB_PULLBACK_GATE_FILTER_TF=15m | AA2: BB_RECOVERY_ENTRY_FILTER_TF=OFF | AB2: BB_RECOVERY_ENTRY_FILTER_TF=D | AC2: BB_RECOVERY_ENTRY_FILTER_TF=4h | AD2: BB_RECOVERY_ENTRY_FILTER_TF=1h | AE2: BB_RECOVERY_ENTRY_FILTER_TF=15m | AF2: BB_RECOVERY_FILTER_TF=OFF | AG2: BB_RECOVERY_FILTER_TF=D | AH2: BB_RECOVERY_FILTER_TF=4h | AI2: BB_RECOVERY_FILTER_TF=1h | AJ2: BB_RECOVERY_FILTER_TF=15m | AK2: BREAKEVEN_GAIN_EROSION_FILTER_TF=OFF | AL2: BREAKEVEN_GAIN_EROSION_FILTER_TF=D | AM2: BREAKEVEN_GAIN_EROSION_FILTER_TF=4h | AN2: BREAKEVEN_GAIN_EROSION_FILTER_TF=1h | AO2: BREAKEVEN_GAIN_EROSION_FILTER_TF=15m | AP2: BREAKOUT_RETEST_FILTER_TF=OFF | AQ2: BREAKOUT_RETEST_FILTER_TF=D | AR2: BREAKOUT_RETEST_FILTER_TF=4h | AS2: BREAKOUT_RETEST_FILTER_TF=1h | AT2: BREAKOUT_RETEST_FILTER_TF=15m | AU2: BT_WT_CROSS_LADDER_FILTER_TF=OFF | AV2: BT_WT_CROSS_LADDER_FILTER_TF=D | AW2: BT_WT_CROSS_LADDER_FILTER_TF=4h | AX2: BT_WT_CROSS_LADDER_FILTER_TF=1h | AY2: BT_WT_CROSS_LADDER_FILTER_TF=15m | AZ2: CANDLE_PATTERN_STOPS_FILTER_TF=OFF | BA2: CANDLE_PATTERN_STOPS_FILTER_TF=D | BB2: CANDLE_PATTERN_STOPS_FILTER_TF=4h | BC2: CANDLE_PATTERN_STOPS_FILTER_TF=1h | BD2: CANDLE_PATTERN_STOPS_FILTER_TF=15m | BE2: CIRCUIT_SHARPE_GATES_FILTER_TF=OFF | BF2: CIRCUIT_SHARPE_GATES_FILTER_TF=D | BG2: CIRCUIT_SHARPE_GATES_FILTER_TF=4h | BH2: CIRCUIT_SHARPE_GATES_FILTER_TF=1h | BI2: CIRCUIT_SHARPE_GATES_FILTER_TF=15m | BJ2: DC_BREACH_REDUCE_FILTER_TF=OFF | BK2: DC_BREACH_REDUCE_FILTER_TF=D | BL2: DC_BREACH_REDUCE_FILTER_TF=4h | BM2: DC_BREACH_REDUCE_FILTER_TF=1h | BN2: DC_BREACH_REDUCE_FILTER_TF=15m | BO2: DC_BREAK_FILTER_TF=OFF | BP2: DC_BREAK_FILTER_TF=D | BQ2: DC_BREAK_FILTER_TF=4h | BR2: DC_BREAK_FILTER_TF=1h | BS2: DC_BREAK_FILTER_TF=15m | BT2: DC_MOMENTUM_BOTA_SCORER_FILTER_TF=OFF | BU2: DC_MOMENTUM_BOTA_SCORER_FILTER_TF=D | BV2: DC_MOMENTUM_BOTA_SCORER_FILTER_TF=4h | BW2: DC_MOMENTUM_BOTA_SCORER_FILTER_TF=1h | BX2: DC_MOMENTUM_BOTA_SCORER_FILTER_TF=15m | BY2: DELTA_ENGINE_FILTER_TF=OFF | BZ2: DELTA_ENGINE_FILTER_TF=D | CA2: DELTA_ENGINE_FILTER_TF=4h | CB2: DELTA_ENGINE_FILTER_TF=1h | CC2: DELTA_ENGINE_FILTER_TF=15m | CD2: EMA_9_21_FILTER_FILTER_TF=OFF | CE2: EMA_9_21_FILTER_FILTER_TF=D | CF2: EMA_9_21_FILTER_FILTER_TF=4h | CG2: EMA_9_21_FILTER_FILTER_TF=1h | CH2: EMA_9_21_FILTER_FILTER_TF=15m | CI2: EMA_BLANKET_FILTER_FILTER_TF=OFF | CJ2: EMA_BLANKET_FILTER_FILTER_TF=D | CK2: EMA_BLANKET_FILTER_FILTER_TF=4h | CL2: EMA_BLANKET_FILTER_FILTER_TF=1h | CM2: EMA_BLANKET_FILTER_FILTER_TF=15m | CN2: EMERGENCY_BRAKE_FILTER_TF=OFF | CO2: EMERGENCY_BRAKE_FILTER_TF=D | CP2: EMERGENCY_BRAKE_FILTER_TF=4h | CQ2: EMERGENCY_BRAKE_FILTER_TF=1h | CR2: EMERGENCY_BRAKE_FILTER_TF=15m | CS2: EXIT_R1_R2_FILTER_TF=OFF | CT2: EXIT_R1_R2_FILTER_TF=D | CU2: EXIT_R1_R2_FILTER_TF=4h | CV2: EXIT_R1_R2_FILTER_TF=1h | CW2: EXIT_R1_R2_FILTER_TF=15m | CX2: EXIT_TIGHT_BREAKOUT_SCORER_FILTER_TF=OFF | CY2: EXIT_TIGHT_BREAKOUT_SCORER_FILTER_TF=D | CZ2: EXIT_TIGHT_BREAKOUT_SCORER_FILTER_TF=4h | DA2: EXIT_TIGHT_BREAKOUT_SCORER_FILTER_TF=1h | DB2: EXIT_TIGHT_BREAKOUT_SCORER_FILTER_TF=15m | DC2: EXIT_TOP_FADE_FILTER_TF=OFF | DD2: EXIT_TOP_FADE_FILTER_TF=D | DE2: EXIT_TOP_FADE_FILTER_TF=4h | DF2: EXIT_TOP_FADE_FILTER_TF=1h | DG2: EXIT_TOP_FADE_FILTER_TF=15m | DH2: EXIT_TO_REDUCE_ADAPTER_FILTER_TF=OFF | DI2: EXIT_TO_REDUCE_ADAPTER_FILTER_TF=D | DJ2: EXIT_TO_REDUCE_ADAPTER_FILTER_TF=4h | DK2: EXIT_TO_REDUCE_ADAPTER_FILTER_TF=1h | DL2: EXIT_TO_REDUCE_ADAPTER_FILTER_TF=15m | DM2: FAST_RISER_FILTER_TF=OFF | DN2: FAST_RISER_FILTER_TF=D | DO2: FAST_RISER_FILTER_TF=4h | DP2: FAST_RISER_FILTER_TF=1h | DQ2: FAST_RISER_FILTER_TF=15m | DR2: FH_MOMENTUM_FILTER_TF=OFF | DS2: FH_MOMENTUM_FILTER_TF=D | DT2: FH_MOMENTUM_FILTER_TF=4h | DU2: FH_MOMENTUM_FILTER_TF=1h | DV2: FH_MOMENTUM_FILTER_TF=15m | DW2: FIRST_OPEN_THROTTLE_FILTER_TF=OFF | DX2: FIRST_OPEN_THROTTLE_FILTER_TF=D | DY2: FIRST_OPEN_THROTTLE_FILTER_TF=4h | DZ2: FIRST_OPEN_THROTTLE_FILTER_TF=1h | EA2: FIRST_OPEN_THROTTLE_FILTER_TF=15m | EB2: FROZEN_STOP_FILTER_TF=OFF | EC2: FROZEN_STOP_FILTER_TF=D | ED2: FROZEN_STOP_FILTER_TF=4h | EE2: FROZEN_STOP_FILTER_TF=1h | EF2: FROZEN_STOP_FILTER_TF=15m | EG2: GOLDEN_RULE_ENFORCE_FILTER_TF=OFF | EH2: GOLDEN_RULE_ENFORCE_FILTER_TF=D | EI2: GOLDEN_RULE_ENFORCE_FILTER_TF=4h | EJ2: GOLDEN_RULE_ENFORCE_FILTER_TF=1h | EK2: GOLDEN_RULE_ENFORCE_FILTER_TF=15m | EL2: GOLDEN_RULE_HTF_VOTE_FILTER_TF=OFF | EM2: GOLDEN_RULE_HTF_VOTE_FILTER_TF=D | EN2: GOLDEN_RULE_HTF_VOTE_FILTER_TF=4h | EO2: GOLDEN_RULE_HTF_VOTE_FILTER_TF=1h | EP2: GOLDEN_RULE_HTF_VOTE_FILTER_TF=15m | EQ2: GR_FILTER_VEC_FILTER_TF=OFF | ER2: GR_FILTER_VEC_FILTER_TF=D | ES2: GR_FILTER_VEC_FILTER_TF=4h | ET2: GR_FILTER_VEC_FILTER_TF=1h | EU2: GR_FILTER_VEC_FILTER_TF=15m | EV2: GR_V5_STATE_FILTER_TF=OFF | EW2: GR_V5_STATE_FILTER_TF=D | EX2: GR_V5_STATE_FILTER_TF=4h | EY2: GR_V5_STATE_FILTER_TF=1h | EZ2: GR_V5_STATE_FILTER_TF=15m | FA2: HAIKU_WINNER_FILTER_TF=OFF | FB2: HAIKU_WINNER_FILTER_TF=D | FC2: HAIKU_WINNER_FILTER_TF=4h | FD2: HAIKU_WINNER_FILTER_TF=1h | FE2: HAIKU_WINNER_FILTER_TF=15m | FF2: LH_HL_FILTER_TF_REQ=2 | FG2: LH_HL_FILTER_TF_REQ=2_ALT | FH2: LIVE_ENTRY_ENGINE_FILTER_TF=OFF | FI2: LIVE_ENTRY_ENGINE_FILTER_TF=D | FJ2: LIVE_ENTRY_ENGINE_FILTER_TF=4h | FK2: LIVE_ENTRY_ENGINE_FILTER_TF=1h | FL2: LIVE_ENTRY_ENGINE_FILTER_TF=15m | FM2: LIVE_ONLY_SIGNALS_BATCH5_FILTER_TF=OFF | FN2: LIVE_ONLY_SIGNALS_BATCH5_FILTER_TF=D | FO2: LIVE_ONLY_SIGNALS_BATCH5_FILTER_TF=4h | FP2: LIVE_ONLY_SIGNALS_BATCH5_FILTER_TF=1h | FQ2: LIVE_ONLY_SIGNALS_BATCH5_FILTER_TF=15m | FR2: MANDATORY_REENTRY_WT_FILTER_TF_MODE=15m_only | FS2: MANDATORY_REENTRY_WT_FILTER_TF_MODE=15m_only_ALT | FT2: MOM3_FILTER_TF=OFF | FU2: MOM3_FILTER_TF=D | FV2: MOM3_FILTER_TF=4h | FW2: MOM3_FILTER_TF=1h | FX2: MOM3_FILTER_TF=15m | FY2: MOMENTUM_BREAKOUT_FILTER_TF=OFF | FZ2: MOMENTUM_BREAKOUT_FILTER_TF=D | GA2: MOMENTUM_BREAKOUT_FILTER_TF=4h | GB2: MOMENTUM_BREAKOUT_FILTER_TF=1h | GC2: MOMENTUM_BREAKOUT_FILTER_TF=15m | GD2: MTF_ARMED_ENTRIES_FILTER_TF=OFF | GE2: MTF_ARMED_ENTRIES_FILTER_TF=D | GF2: MTF_ARMED_ENTRIES_FILTER_TF=4h | GG2: MTF_ARMED_ENTRIES_FILTER_TF=1h | GH2: MTF_ARMED_ENTRIES_FILTER_TF=15m | GI2: MTF_ATR_TRAIL_FILTER_TF=OFF | GJ2: MTF_ATR_TRAIL_FILTER_TF=D | GK2: MTF_ATR_TRAIL_FILTER_TF=4h | GL2: MTF_ATR_TRAIL_FILTER_TF=1h | GM2: MTF_ATR_TRAIL_FILTER_TF=15m | GN2: MTF_DC_REJECT_FILTER_TF=OFF | GO2: MTF_DC_REJECT_FILTER_TF=D | GP2: MTF_DC_REJECT_FILTER_TF=4h | GQ2: MTF_DC_REJECT_FILTER_TF=1h | GR2: MTF_DC_REJECT_FILTER_TF=15m | GS2: NEWBORN_LOSS_KILL_FILTER_TF=OFF | GT2: NEWBORN_LOSS_KILL_FILTER_TF=D | GU2: NEWBORN_LOSS_KILL_FILTER_TF=4h | GV2: NEWBORN_LOSS_KILL_FILTER_TF=1h | GW2: NEWBORN_LOSS_KILL_FILTER_TF=15m | GX2: NEWBORN_PROTECT_FILTER_TF=OFF | GY2: NEWBORN_PROTECT_FILTER_TF=D | GZ2: NEWBORN_PROTECT_FILTER_TF=4h | HA2: NEWBORN_PROTECT_FILTER_TF=1h | HB2: NEWBORN_PROTECT_FILTER_TF=15m | HC2: NOLOSS_BYPASS_WT5OF5_FILTER_TF=OFF | HD2: NOLOSS_BYPASS_WT5OF5_FILTER_TF=D | HE2: NOLOSS_BYPASS_WT5OF5_FILTER_TF=4h | HF2: NOLOSS_BYPASS_WT5OF5_FILTER_TF=1h | HG2: NOLOSS_BYPASS_WT5OF5_FILTER_TF=15m | HH2: OPEN_INTENT_SIZE_GATES_FILTER_TF=OFF | HI2: OPEN_INTENT_SIZE_GATES_FILTER_TF=D | HJ2: OPEN_INTENT_SIZE_GATES_FILTER_TF=4h | HK2: OPEN_INTENT_SIZE_GATES_FILTER_TF=1h | HL2: OPEN_INTENT_SIZE_GATES_FILTER_TF=15m | HM2: PARTIAL_PROFIT_LOCK_V2_FILTER_TF=OFF | HN2: PARTIAL_PROFIT_LOCK_V2_FILTER_TF=D | HO2: PARTIAL_PROFIT_LOCK_V2_FILTER_TF=4h | HP2: PARTIAL_PROFIT_LOCK_V2_FILTER_TF=1h | HQ2: PARTIAL_PROFIT_LOCK_V2_FILTER_TF=15m | HR2: PEAK_GIVEBACK_BE_EROSION_FILTER_TF=OFF | HS2: PEAK_GIVEBACK_BE_EROSION_FILTER_TF=D | HT2: PEAK_GIVEBACK_BE_EROSION_FILTER_TF=4h | HU2: PEAK_GIVEBACK_BE_EROSION_FILTER_TF=1h | HV2: PEAK_GIVEBACK_BE_EROSION_FILTER_TF=15m | HW2: WT_15M_BOUNCE_BB_MAX=0.95 | HX2: WT_15M_BOUNCE_BB_MAX=0.9 | HY2: WT_15M_BOUNCE_BB_MAX=0.8 | HZ2: WT_15M_BOUNCE_BB_MIN=0.05 | IA2: WT_15M_BOUNCE_BB_MIN=0.1 | IB2: WT_15M_BOUNCE_BB_MIN=0.2 | IC2: WT_15M_BOUNCE_HIGH_1H_GT_PREV=True | ID2: WT_15M_BOUNCE_HIGH_1H_GT_PREV=False | IE2: WT_15M_BOUNCE_LOW_1H_GT_PREV=True | IF2: WT_15M_BOUNCE_LOW_1H_GT_PREV=False | IG2: WT_15M_BOUNCE_REL_VOL_GT_1=True | IH2: WT_15M_BOUNCE_REL_VOL_GT_1=False | II2: Live Location | IJ2: Vec Hook | IK2: Type | IL2: Correct Options
A3: DD_BOUNCE_ENABLED | B3: True | E3: -13.3501 | F3: 2.5853 | G3: =IFERROR(VLOOKUP($A3,Results_30d_Deltas!$A$2:$H$5000,7,FALSE)-E3,"") | H3: =IFERROR(VLOOKUP($A3,Results_30d_Deltas!$A$2:$H$5000,6,FALSE),"") | K3: =IF(B3=C3,"YES","NO") | IJ3: ez_manage.py:4586 top() | IK3: v12_quick_engine.py:567 x9
A4: MAX_AUGMENTS_PER_POSITION | B4: 0 | E4: -12.1759 | F4: 3.7596 | G4: =IFERROR(VLOOKUP($A4,Results_30d_Deltas!$A$2:$H$5000,7,FALSE)-E3,"") | H4: =IFERROR(VLOOKUP($A4,Results_30d_Deltas!$A$2:$H$5000,6,FALSE),"") | K4: =IF(B4=C4,"YES","NO") | IJ4: ez_manage.py:3521 top() | IK4: v12_quick_engine.py:2267 x7
A5: MAX_AUGMENTS_PER_POSITION | B5: 0.5 | E5: -12.1759 | F5: 3.7596 | G5: =IFERROR(VLOOKUP($A5,Results_30d_Deltas!$A$2:$H$5000,7,FALSE)-E4,"") | H5: =IFERROR(VLOOKUP($A5,Results_30d_Deltas!$A$2:$H$5000,6,FALSE),"") | K5: =IF(B5=C5,"YES","NO") | IJ5: ez_manage.py:3521 top() | IK5: v12_quick_engine.py:2267 x7
A6: MAX_AUGMENTS_PER_POSITION | B6: 1.0 | E6: -12.1759 | F6: 3.7596 | G6: =IFERROR(VLOOKUP($A6,Results_30d_Deltas!$A$2:$H$5000,7,FALSE)-E5,"") | H6: =IFERROR(VLOOKUP($A6,Results_30d_Deltas!$A$2:$H$5000,6,FALSE),"") | K6: =IF(B6=C6,"YES","NO") | IJ6: ez_manage.py:3521 top() | IK6: v12_quick_engine.py:2267 x7
A7: MAX_AUGMENTS_PER_POSITION | B7: 2.0 | E7: -12.1759 | F7: 3.7596 | G7: =IFERROR(VLOOKUP($A7,Results_30d_Deltas!$A$2:$H$5000,7,FALSE)-E6,"") | H7: =IFERROR(VLOOKUP($A7,Results_30d_Deltas!$A$2:$H$5000,6,FALSE),"") | K7: =IF(B7=C7,"YES","NO") | IJ7: ez_manage.py:3521 top() | IK7: v12_quick_engine.py:2267 x7
A8: AUGMENTED_POSITIONS_GUARD_FLOOR_MULT | B8: 0 | E8: -13.4636 | F8: 2.4718 | G8: =IFERROR(VLOOKUP($A8,Results_30d_Deltas!$A$2:$H$5000,7,FALSE)-E7,"") | H8: =IFERROR(VLOOKUP($A8,Results_30d_Deltas!$A$2:$H$5000,6,FALSE),"") | K8: =IF(B8=C8,"YES","NO") | IJ8: ez_manage.py:4336 top() | IK8: v12_quick_engine.py:221 x13
A9: AUGMENTED_POSITIONS_GUARD_FLOOR_MULT | B9: 0.5 | E9: -13.4636 | F9: 2.4718 | G9: =IFERROR(VLOOKUP($A9,Results_30d_Deltas!$A$2:$H$5000,7,FALSE)-E8,"") | H9: =IFERROR(VLOOKUP($A9,Results_30d_Deltas!$A$2:$H$5000,6,FALSE),"") | K9: =IF(B9=C9,"YES","NO") | IJ9: ez_manage.py:4336 top() | IK9: v12_quick_engine.py:221 x13
A10: AUGMENTED_POSITIONS_GUARD_FLOOR_MULT | B10: 1.0 | E10: -13.4636 | F10: 2.4718 | G10: =IFERROR(VLOOKUP($A10,Results_30d_Deltas!$A$2:$H$5000,7,FALSE)-E9,"") | H10: =IFERROR(VLOOKUP($A10,Results_30d_Deltas!$A$2:$H$5000,6,FALSE),"") | K10: =IF(B10=C10,"YES","NO") | IJ10: ez_manage.py:4336 top() | IK10: v12_quick_engine.py:221 x13
A11: AUGMENTED_POSITIONS_GUARD_FLOOR_MULT | B11: 2.0 | E11: -13.4636 | F11: 2.4718 | G11: =IFERROR(VLOOKUP($A11,Results_30d_Deltas!$A$2:$H$5000,7,FALSE)-E10,"") | H11: =IFERROR(VLOOKUP($A11,Results_30d_Deltas!$A$2:$H$5000,6,FALSE),"") | K11: =IF(B11=C11,"YES","NO") | IJ11: ez_manage.py:4336 top() | IK11: v12_quick_engine.py:221 x13
A12: AUGMENT_AT_LOSS_ENABLED | B12: False | E12: -13.4689 | F12: 2.4666 | G12: =IFERROR(VLOOKUP($A12,Results_30d_Deltas!$A$2:$H$5000,7,FALSE)-E11,"") | H12: =IFERROR(VLOOKUP($A12,Results_30d_Deltas!$A$2:$H$5000,6,FALSE),"") | K12: =IF(B12=C12,"YES","NO") | IJ12: ez_manage.py:5956 top() | IK12: v12_quick_engine.py:228 x5
A13: AUGMENT_AT_LOSS_ENABLED | B13: True | E13: -13.3501 | F13: 2.5853 | G13: =IFERROR(VLOOKUP($A13,Results_30d_Deltas!$A$2:$H$5000,7,FALSE)-E12,"") | H13: =IFERROR(VLOOKUP($A13,Results_30d_Deltas!$A$2:$H$5000,6,FALSE),"") | K13: =IF(B13=C13,"YES","NO") | IJ13: ez_manage.py:5956 top() | IK13: v12_quick_engine.py:228 x5
A14: AUGMENT_FALLBACK_GAIN_PCT | B14: 0.5 | E14: -13.3501 | F14: 2.5853 | G14: =IFERROR(VLOOKUP($A14,Results_30d_Deltas!$A$2:$H$5000,7,FALSE)-E13,"") | H14: =IFERROR(VLOOKUP($A14,Results_30d_Deltas!$A$2:$H$5000,6,FALSE),"") | K14: =IF(B14=C14,"YES","NO") | AK14: 2.4666 | AL14: 0.8638 | AM14: 0.505 | IJ14: ez_manage.py:56864 top() | IK14: v12_quick_engine.py:4990 x4
A15: AUGMENT_FALLBACK_GAIN_PCT | B15: 0.75 | E15: -13.3501 | F15: 2.5853 | G15: =IFERROR(VLOOKUP($A15,Results_30d_Deltas!$A$2:$H$5000,7,FALSE)-E14,"") | H15: =IFERROR(VLOOKUP($A15,Results_30d_Deltas!$A$2:$H$5000,6,FALSE),"") | K15: =IF(B15=C15,"YES","NO") | AK15: 2.4666 | AL15: 0.8638 | AM15: 0.505 | IJ15: ez_manage.py:56864 top() | IK15: v12_quick_engine.py:4990 x4
A16: AUGMENT_FALLBACK_GAIN_PCT | B16: 1.0 | E16: -13.3501 | F16: 2.5853 | G16: =IFERROR(VLOOKUP($A16,Results_30d_Deltas!$A$2:$H$5000,7,FALSE)-E15,"") | H16: =IFERROR(VLOOKUP($A16,Results_30d_Deltas!$A$2:$H$5000,6,FALSE),"") | K16: =IF(B16=C16,"YES","NO") | AK16: 2.4666 | AL16: 0.8638 | AM16: 0.505 | IJ16: ez_manage.py:56864 top() | IK16: v12_quick_engine.py:4990 x4
A17: AUGMENT_FALLBACK_GAIN_PCT | B17: 1.25 | E17: -13.3501 | F17: 2.5853 | G17: =IFERROR(VLOOKUP($A17,Results_30d_Deltas!$A$2:$H$5000,7,FALSE)-E16,"") | H17: =IFERROR(VLOOKUP($A17,Results_30d_Deltas!$A$2:$H$5000,6,FALSE),"") | K17: =IF(B17=C17,"YES","NO") | AK17: 2.4666 | AL17: 0.8638 | AM17: 0.505 | IJ17: ez_manage.py:56864 top() | IK17: v12_quick_engine.py:4990 x4
A18: AUGMENT_FALLBACK_GAIN_PCT | B18: 1.5 | E18: -13.3501 | F18: 2.5853 | G18: =IFERROR(VLOOKUP($A18,Results_30d_Deltas!$A$2:$H$5000,7,FALSE)-E17,"") | H18: =IFERROR(VLOOKUP($A18,Results_30d_Deltas!$A$2:$H$5000,6,FALSE),"") | K18: =IF(B18=C18,"YES","NO") | AK18: 2.4666 | AL18: 0.8638 | AM18: 0.505 | IJ18: ez_manage.py:56864 top() | IK18: v12_quick_engine.py:4990 x4
A19: AUGMENT_FALLBACK_REDUCE_ENABLED | B19: False | E19: -12.1759 | F19: 3.7596 | G19: =IFERROR(VLOOKUP($A19,Results_30d_Deltas!$A$2:$H$5000,7,FALSE)-E18,"") | H19: =IFERROR(VLOOKUP($A19,Results_30d_Deltas!$A$2:$H$5000,6,FALSE),"") | K19: =IF(B19=C19,"YES","NO") | IJ19: ez_manage.py:56872 top() | IK19: v12_quick_engine.py:4988 x3
A20: AUGMENT_FALLBACK_REDUCE_ENABLED | B20: True | E20: -13.3501 | F20: 2.5853 | G20: =IFERROR(VLOOKUP($A20,Results_30d_Deltas!$A$2:$H$5000,7,FALSE)-E19,"") | H20: =IFERROR(VLOOKUP($A20,Results_30d_Deltas!$A$2:$H$5000,6,FALSE),"") | K20: =IF(B20=C20,"YES","NO") | IJ20: ez_manage.py:56872 top() | IK20: v12_quick_engine.py:4988 x3
A21: AUGMENT_FALLBACK_REDUCE_PCT | B21: 0.25 | E21: -13.4636 | F21: 2.4718 | G21: =IFERROR(VLOOKUP($A21,Results_30d_Deltas!$A$2:$H$5000,7,FALSE)-E20,"") | H21: =IFERROR(VLOOKUP($A21,Results_30d_Deltas!$A$2:$H$5000,6,FALSE),"") | K21: =IF(B21=C21,"YES","NO") | IJ21: ez_manage.py:56876 top() | IK21: v12_quick_engine.py:4989 x3
A22: AUGMENT_FALLBACK_REDUCE_PCT | B22: 0.375 | E22: -13.4636 | F22: 2.4718 | G22: =IFERROR(VLOOKUP($A22,Results_30d_Deltas!$A$2:$H$5000,7,FALSE)-E21,"") | H22: =IFERROR(VLOOKUP($A22,Results_30d_Deltas!$A$2:$H$5000,6,FALSE),"") | K22: =IF(B22=C22,"YES","NO") | IJ22: ez_manage.py:56876 top() | IK22: v12_quick_engine.py:4989 x3
A23: AUGMENT_FALLBACK_REDUCE_PCT | B23: 0.5 | E23: -13.4636 | F23: 2.4718 | G23: =IFERROR(VLOOKUP($A23,Results_30d_Deltas!$A$2:$H$5000,7,FALSE)-E22,"") | H23: =IFERROR(VLOOKUP($A23,Results_30d_Deltas!$A$2:$H$5000,6,FALSE),"") | K23: =IF(B23=C23,"YES","NO") | IJ23: ez_manage.py:56876 top() | IK23: v12_quick_engine.py:4989 x3
