Workbook

Sheet INSTRUCTIONS
A1: TEMPLATE_30d_matrix -- CRYSTAL CLEAR INSTRUCTIONS (2026-09-11) -- ANY DUMB AGENT CAN EXECUTE *** ON S1 NEVER ON MACBOOK *** If you are reading this, YOU MUST FOLLOW EVERY LINE. No skipping, no guessing, no inventing numbers. This tab + FILTER_DICTIONARY_V2 + v14_sequential_filler.py + v12_quick_engine/backtest_v12_engine are LAW.
A2: ⚠️ MACHINE RULE -- MAC ONLY TRADES LIVE (ez_manage / tradier_manage) AND NEVER TESTS. MAC has 5 NPZs and NO NVDA.npz / NO CRWD.npz → any S1 vector returns 'no NPZ' in 0.2s. S1 = 157.180.125.52 (s1-int via gateway 157.90.168.35) has 1000+ NPZs (42-49M) and is ONLY test host (S2 for mega sweeps only). If on MacBook, SSH FIRST: ssh 157.180.125.52 OR ssh -fNT s1-sftp && ssh s1-int. Verify: ls /home/niels/binance-sandbox/backtest_v8/indicators/NVDA.npz must exist. If not, STOP.
A3: ⚠️ SYNC & BACKUP RULE -- KEEP ALL FIXES synced Mac <-> S1 via rsync -avz -e 'ssh -p 2201' and KEEP BACKUPS before EVERY edit: cp <file> backups/before_<desc>_$(date +%Y%m%d%H%M).py . Autosave launchd commits git every 15min. /backups/ ONLY reliable history. After BACKTEST_BIBLE.md edit run tools/sync_backtest_bible.sh (SHA256). NEVER edit S1 copy directly without rsync back.
A4: ⚠️ INSTRUCTIONS ARE LAW -- v12_pilot.py, v12_pilot_sheet_runner.py, v14_sequential_filler.py, ANY agent MUST READ THIS TAB AT STARTUP and FOLLOW IT. This tab wins over code if conflict after 2026-09-11. Also read BACKTEST_BIBLE.md, QuickConfig (v12_quick_engine:5893 1118 fields, 851 causal), and FILTER_DICTIONARY_V2 (426 rows).
A5: 0) PRECONDITION -- DO NOT START UNTIL DEFAULTS ARE BOLD. Every row where B == live default (config.py Config for crypto / config_tradier.py TradierConfig for stocks = 1118 fields) must have A and B bold. ~50% rows bold. NEVER edit B (candidate value in col B). You only write C (override), E (baseline gain), F (delta vs E), G (variant gain), and L:BI per-filter deltas.
A6: 1) CREATE BASELINE WITH per_sym OVERRIDES for EXACT sym_side. GET OVERRIDES = union of data/hourly_reconfig/trb/active_config.json AND data/hourly_reconfig/per_sym_active_config.json for YOUR EXACT SYM_SIDE (SYMBOL+_LONG vs _SHORT are DIFFERENT, NEVER reuse). Example NVDA_LONG 8 overrides (BOUNCE_AUGMENT...), CRWD_SHORT 0. For each switch in union, find row where A==switch name and write override into C, BOLD GREEN font 006100 on fill C6EFCE. Do ALL overrides BEFORE baseline calc. Then baseline = vector_evaluate(sym_side, overrides) AND live_evaluate(sym_side, overrides) — they must parity (trades 0.80..1.25, gain 0.5pp|15%, sharpe 0.25). Write TEMPLATE_BASELINE_METRICS!B2 = gain, B? = bh. Verify WT_15M_BOUNCE True adds >100 trades/mo (fix in v12_quick_engine:5894 MAX_BARS_AGO=100). If trades 0 or <30, STOP and spawn agent to fix v12_quick_engine (6817/9010).
A7: 1b) BASELINE E2 = TEMPLATE_BASELINE_METRICS!B2 (gain). E3 = IF(F3>0,E2+F3,"") chain. Never repeat E. First pilot: WT_15M_BOUNCE True must be first positive delta or calculation BROKEN.
A8: 2) FOR EVERY ROW (EVERY SWITCH) TEST EVERY APPLICABLE FILTER × EVERY SETTING. MANDATORY until >100 sym_sides tested (see rule 9). Applicable = FILTER_DICTIONARY_V2 row where (sheets_app contains this tab lifecycle ENTRY/EXIT/REENTRY/AUGMENT/REDUCE or GLOBAL_CHECK) AND (gates token overlap with this switch OR rec is GENERAL). Use get_opportune_filters(switch, sheet) — it already implements this. For WT_15M_BOUNCE_OPEN_ENABLED True you MUST test its 12 sub-filters (BB_MIN 0.05/0.1/0.2, BB_MAX 0.95/0.9/0.8, LOW_1H True/False, HIGH_1H True/False, REL_VOL True/False) even if WT alone delta is NEG — they are FILTERS in FILTER_DICTIONARY, not switches. Do NOT discard. COL J lists per-switch opportune filters (up to 6 shown), COL L:BI holds per-filter deltas (one column per filter=opt).
A9: 2a) EVALUATION: For this row, build candidates: [switch alone] + [switch+each single filter distinct opt (skip opt==cur)] . If best single delta <=0, also test ALL combos of 2 and 3 among top-8 singles (C8,2=28 + C8,3=56 =84 combos). Each candidate = sanitize_overrides(variant, defaults) then vector_evaluate via prepare_batch/evaluate_prepared_sanitized (70-136ms, million/hour). NEVER use per-cell load_npz (3.65s) — use prepare_batch once per sym_side. Log every candidate: [CANDIDATE] switch=cand[+filter=opt] vec_gain delta vs cum trades sharpe. Pick MAX delta (beating-ideas-to-death, not first positive).
A10: 2b) DUPLICATE/0.0 CHECK — Immediately flag DUPLICATE (same delta for 2 different switches → formula bug, e.g. shared adx gate) or 0.0 (dead switch or >5s VECTOR_STALL). If duplicate/0.0, revise v12_quick_engine wiring to exact live numpy (622 not-causal) and run live_evaluate for parity. Fix before promoting.
A11: 2c) PROGRESS REPORT every 5min: count filled F cells per sheet (e.g. NVDA 2790/2823=98.8% — one baseline empty per sheet expected). Write data/reports/lifecycle_pilot/*_pilot_progress.json and SPREADSHEETS/*_pilot_progress.html refreshed 60s. Also log [ROW] sheet!r switch=cand[+filter] delta vs cum -> NEG/POSITIVE candidate.
A12: 3) PROMOTION: Only if best delta >0 AND live_evaluate parity passes (trades 0.80..1.25, gain 0.5pp|15%, sharpe 0.25) AND (vector_only deferred → final cumulative live check). Then write C = cand (bold green 006100 on C6EFCE), cumulative_gain = vec_gain, cumulative_overrides[switch]=cand and if filter best exists also [filter]=fval. Write Results_30d_Deltas row: key=switch=cand, col5=delta, col6=variant_gain, col8=variant_gain, col10=trades, col11=max_dd, col12=tim. Also batch write L:BI deltas for this row (one col per filter=opt = delta). E for this row = IF(F>0,Eprev+F,Eprev) — only F>0 gets bold green E/F/G and C. F/G written even if <=0 for audit, but E stays empty.
... A23: 14) FINAL CHECK -- Before declaring done, verify: (a) every row has F via Results key=switch=cand VLOOKUP $A&"="&$B, (b) L:BI columns exist for every applicable filter (R-W, 40 col cap), (c) Results_30d_Deltas has delta, gain, trades, sharpe for every pos, (d) filename bh/gain correct, (e) v14 where applicable, (f) >100 sym_sides threshold respected, (g) colors green/blue/darker per provenance.

Sheet INSTRUCTIONS_V2
A1: TEMPLATE_V2_IDEA_GROUPED 231 per-row FULLY CONNECTED 2026-09-08 - every numpy identical to live
A2: Retraced from early today 231 L:IH (TEMPLATE.xlsx 1.7M) - Sep 5 114 per-row was synthetic/disconnected. This file keeps 231 per-row L:IH (every filter TF OFF/D/4h/1h/15m wired).
A3: 01. ENTRY_REVERSAL_BOUNCE - 8 bases -> 21 rows - 231 per-row
A4: 02. ENTRY_BREAKOUT_CHANNEL - 54 bases -> 210 rows - 231 per-row
A5: 03. ENTRY_CONFIRMATION_GATES - 4 bases -> 11 rows - 231 per-row
A6: 04. EXIT_STRUCTURAL - 2 bases -> 6 rows - 231 per-row
A7: 05. EXIT_VELOCITY - 26 bases -> 80 rows - 231 per-row
A8: 06. REENTRY_WINDOWED - 68 bases -> 249 rows - 231 per-row
A9: 07. REENTRY_ADAPTIVE - 10 bases -> 38 rows - 231 per-row
A10: 08. AUGMENT_TREND - 5 bases -> 24 rows - 231 per-row
A11: 09. AUGMENT_RISK_SIZING - 17 bases -> 56 rows - 231 per-row
A12: 10. REDUCE_PROFIT_LOCK - 19 bases -> 53 rows - 231 per-row
... A15: 2026-09-11 UPDATE: See INSTRUCTIONS tab rows 9,12,14 for >100 sym_sides threshold, blanket at end of each tab, and green/blue/darker proven colors. v14 implements get_opportune_filters + 84 combos + blanket GENERAL. ALL filters until 100, then useful per universe.

Sheet ENTRY_REVERSAL_BOUNCE
A1: 01 ENTRY_REVERSAL_BOUNCE - 8 bases -> 21 rows - 231 per-row FULLY CONNECTED
A2: Switch | B2: default | C2: override | D2: Family | E2: BASELINE | F2: VECTOR_DELTA | G2: LIVE_DELTA | H2: LIVE_SHARPE | I2: REAL_COMPLETE | J2: PER_ROW_FILTERS | K2: is_default (backup if bold lost) | L2: ATR_TRAIL_FILTER_TF=OFF | M2: ATR_TRAIL_FILTER_TF=D | N2: ATR_TRAIL_FILTER_TF=4h | O2: ATR_TRAIL_FILTER_TF=1h | P2: ATR_TRAIL_FILTER_TF=15m | Q2: BAR_PATTERNS_FILTER_TF=OFF | R2: BAR_PATTERNS_FILTER_TF=D | S2: BAR_PATTERNS_FILTER_TF=4h | T2: BAR_PATTERNS_FILTER_TF=1h | U2: BAR_PATTERNS_FILTER_TF=15m | V2: BB_PULLBACK_GATE_FILTER_TF=OFF | W2: BB_PULLBACK_GATE_FILTER_TF=D | X2: BB_PULLBACK_GATE_FILTER_TF=4h | Y2: BB_PULLBACK_GATE_FILTER_TF=1h | Z2: BB_PULLBACK_GATE_FILTER_TF=15m | AA2: BB_RECOVERY_ENTRY_FILTER_TF=OFF | AB2: BB_RECOVERY_ENTRY_FILTER_TF=D | AC2: BB_RECOVERY_ENTRY_FILTER_TF=4h | AD2: BB_RECOVERY_ENTRY_FILTER_TF=1h | AE2: BB_RECOVERY_ENTRY_FILTER_TF=15m | AF2: BB_RECOVERY_FILTER_TF=OFF | AG2: BB_RECOVERY_FILTER_TF=D | AH2: BB_RECOVERY_FILTER_TF=4h | AI2: BB_RECOVERY_FILTER_TF=1h | AJ2: BB_RECOVERY_FILTER_TF=15m | AK2: BREAKEVEN_GAIN_EROSION_FILTER_TF=OFF | AL2: BREAKEVEN_GAIN_EROSION_FILTER_TF=D | AM2: BREAKEVEN_GAIN_EROSION_FILTER_TF=4h | AN2: BREAKEVEN_GAIN_EROSION_FILTER_TF=1h | AO2: BREAKEVEN_GAIN_EROSION_FILTER_TF=15m | AP2: BREAKOUT_RETEST_FILTER_TF=OFF | AQ2: BREAKOUT_RETEST_FILTER_TF=D | AR2: BREAKOUT_RETEST_FILTER_TF=4h | AS2: BREAKOUT_RETEST_FILTER_TF=1h | AT2: BREAKOUT_RETEST_FILTER_TF=15m | AU2: BT_WT_CROSS_LADDER_FILTER_TF=OFF | AV2: BT_WT_CROSS_LADDER_FILTER_TF=D | AW2: BT_WT_CROSS_LADDER_FILTER_TF=4h | AX2: BT_WT_CROSS_LADDER_FILTER_TF=1h | AY2: BT_WT_CROSS_LADDER_FILTER_TF=15m | AZ2: CANDLE_PATTERN_STOPS_FILTER_TF=OFF | BA2: CANDLE_PATTERN_STOPS_FILTER_TF=D | BB2: CANDLE_PATTERN_STOPS_FILTER_TF=4h | BC2: CANDLE_PATTERN_STOPS_FILTER_TF=1h | BD2: CANDLE_PATTERN_STOPS_FILTER_TF=15m | BE2: CIRCUIT_SHARPE_GATES_FILTER_TF=OFF | BF2: CIRCUIT_SHARPE_GATES_FILTER_TF=D | BG2: CIRCUIT_SHARPE_GATES_FILTER_TF=4h | BH2: CIRCUIT_SHARPE_GATES_FILTER_TF=1h | BI2: CIRCUIT_SHARPE_GATES_FILTER_TF=15m | BJ2: DC_BREACH_REDUCE_FILTER_TF=OFF | BK2: DC_BREACH_REDUCE_FILTER_TF=D | BL2: DC_BREACH_REDUCE_FILTER_TF=4h | BM2: DC_BREACH_REDUCE_FILTER_TF=1h | BN2: DC_BREACH_REDUCE_FILTER_TF=15m | BO2: DC_BREAK_FILTER_TF=OFF | BP2: DC_BREAK_FILTER_TF=D | BQ2: DC_BREAK_FILTER_TF=4h | BR2: DC_BREAK_FILTER_TF=1h | BS2: DC_BREAK_FILTER_TF=15m | BT2: DC_MOMENTUM_BOTA_SCORER_FILTER_TF=OFF | BU2: DC_MOMENTUM_BOTA_SCORER_FILTER_TF=D | BV2: DC_MOMENTUM_BOTA_SCORER_FILTER_TF=4h | BW2: DC_MOMENTUM_BOTA_SCORER_FILTER_TF=1h | BX2: DC_MOMENTUM_BOTA_SCORER_FILTER_TF=15m | BY2: DELTA_ENGINE_FILTER_TF=OFF | BZ2: DELTA_ENGINE_FILTER_TF=D | CA2: DELTA_ENGINE_FILTER_TF=4h | CB2: DELTA_ENGINE_FILTER_TF=1h | CC2: DELTA_ENGINE_FILTER_TF=15m | CD2: EMA_9_21_FILTER_FILTER_TF=OFF | CE2: EMA_9_21_FILTER_FILTER_TF=D | CF2: EMA_9_21_FILTER_FILTER_TF=4h | CG2: EMA_9_21_FILTER_FILTER_TF=1h | CH2: EMA_9_21_FILTER_FILTER_TF=15m | CI2: EMA_BLANKET_FILTER_FILTER_TF=OFF | CJ2: EMA_BLANKET_FILTER_FILTER_TF=D | CK2: EMA_BLANKET_FILTER_FILTER_TF=4h | CL2: EMA_BLANKET_FILTER_FILTER_TF=1h | CM2: EMA_BLANKET_FILTER_FILTER_TF=15m | CN2: EMERGENCY_BRAKE_FILTER_TF=OFF | CO2: EMERGENCY_BRAKE_FILTER_TF=D | CP2: EMERGENCY_BRAKE_FILTER_TF=4h | CQ2: EMERGENCY_BRAKE_FILTER_TF=1h | CR2: EMERGENCY_BRAKE_FILTER_TF=15m | CS2: EXIT_R1_R2_FILTER_TF=OFF | CT2: EXIT_R1_R2_FILTER_TF=D | CU2: EXIT_R1_R2_FILTER_TF=4h | CV2: EXIT_R1_R2_FILTER_TF=1h | CW2: EXIT_R1_R2_FILTER_TF=15m | CX2: EXIT_TIGHT_BREAKOUT_SCORER_FILTER_TF=OFF | CY2: EXIT_TIGHT_BREAKOUT_SCORER_FILTER_TF=D | CZ2: EXIT_TIGHT_BREAKOUT_SCORER_FILTER_TF=4h | DA2: EXIT_TIGHT_BREAKOUT_SCORER_FILTER_TF=1h | DB2: EXIT_TIGHT_BREAKOUT_SCORER_FILTER_TF=15m | DC2: EXIT_TOP_FADE_FILTER_TF=OFF | DD2: EXIT_TOP_FADE_FILTER_TF=D | DE2: EXIT_TOP_FADE_FILTER_TF=4h | DF2: EXIT_TOP_FADE_FILTER_TF=1h | DG2: EXIT_TOP_FADE_FILTER_TF=15m | DH2: EXIT_TO_REDUCE_ADAPTER_FILTER_TF=OFF | DI2: EXIT_TO_REDUCE_ADAPTER_FILTER_TF=D | DJ2: EXIT_TO_REDUCE_ADAPTER_FILTER_TF=4h | DK2: EXIT_TO_REDUCE_ADAPTER_FILTER_TF=1h | DL2: EXIT_TO_REDUCE_ADAPTER_FILTER_TF=15m | DM2: FAST_RISER_FILTER_TF=OFF | DN2: FAST_RISER_FILTER_TF=D | DO2: FAST_RISER_FILTER_TF=4h | DP2: FAST_RISER_FILTER_TF=1h | DQ2: FAST_RISER_FILTER_TF=15m | DR2: FH_MOMENTUM_FILTER_TF=OFF | DS2: FH_MOMENTUM_FILTER_TF=D | DT2: FH_MOMENTUM_FILTER_TF=4h | DU2: FH_MOMENTUM_FILTER_TF=1h | DV2: FH_MOMENTUM_FILTER_TF=15m | DW2: FIRST_OPEN_THROTTLE_FILTER_TF=OFF | DX2: FIRST_OPEN_THROTTLE_FILTER_TF=D | DY2: FIRST_OPEN_THROTTLE_FILTER_TF=4h | DZ2: FIRST_OPEN_THROTTLE_FILTER_TF=1h | EA2: FIRST_OPEN_THROTTLE_FILTER_TF=15m | EB2: FROZEN_STOP_FILTER_TF=OFF | EC2: FROZEN_STOP_FILTER_TF=D | ED2: FROZEN_STOP_FILTER_TF=4h | EE2: FROZEN_STOP_FILTER_TF=1h | EF2: FROZEN_STOP_FILTER_TF=15m | EG2: GOLDEN_RULE_ENFORCE_FILTER_TF=OFF | EH2: GOLDEN_RULE_ENFORCE_FILTER_TF=D | EI2: GOLDEN_RULE_ENFORCE_FILTER_TF=4h | EJ2: GOLDEN_RULE_ENFORCE_FILTER_TF=1h | EK2: GOLDEN_RULE_ENFORCE_FILTER_TF=15m | EL2: GOLDEN_RULE_HTF_VOTE_FILTER_TF=OFF | EM2: GOLDEN_RULE_HTF_VOTE_FILTER_TF=D | EN2: GOLDEN_RULE_HTF_VOTE_FILTER_TF=4h | EO2: GOLDEN_RULE_HTF_VOTE_FILTER_TF=1h | EP2: GOLDEN_RULE_HTF_VOTE_FILTER_TF=15m | EQ2: GR_FILTER_VEC_FILTER_TF=OFF | ER2: GR_FILTER_VEC_FILTER_TF=D | ES2: GR_FILTER_VEC_FILTER_TF=4h | ET2: GR_FILTER_VEC_FILTER_TF=1h | EU2: GR_FILTER_VEC_FILTER_TF=15m | EV2: GR_V5_STATE_FILTER_TF=OFF | EW2: GR_V5_STATE_FILTER_TF=D | EX2: GR_V5_STATE_FILTER_TF=4h | EY2: GR_V5_STATE_FILTER_TF=1h | EZ2: GR_V5_STATE_FILTER_TF=15m | FA2: HAIKU_WINNER_FILTER_TF=OFF | FB2: HAIKU_WINNER_FILTER_TF=D | FC2: HAIKU_WINNER_FILTER_TF=4h | FD2: HAIKU_WINNER_FILTER_TF=1h | FE2: HAIKU_WINNER_FILTER_TF=15m | FF2: LH_HL_FILTER_TF_REQ=2 | FG2: LH_HL_FILTER_TF_REQ=2_ALT | FH2: LIVE_ENTRY_ENGINE_FILTER_TF=OFF | FI2: LIVE_ENTRY_ENGINE_FILTER_TF=D | FJ2: LIVE_ENTRY_ENGINE_FILTER_TF=4h | FK2: LIVE_ENTRY_ENGINE_FILTER_TF=1h | FL2: LIVE_ENTRY_ENGINE_FILTER_TF=15m | FM2: LIVE_ONLY_SIGNALS_BATCH5_FILTER_TF=OFF | FN2: LIVE_ONLY_SIGNALS_BATCH5_FILTER_TF=D | FO2: LIVE_ONLY_SIGNALS_BATCH5_FILTER_TF=4h | FP2: LIVE_ONLY_SIGNALS_BATCH5_FILTER_TF=1h | FQ2: LIVE_ONLY_SIGNALS_BATCH5_FILTER_TF=15m | FR2: MANDATORY_REENTRY_WT_FILTER_TF_MODE=15m_only | FS2: MANDATORY_REENTRY_WT_FILTER_TF_MODE=15m_only_ALT | FT2: MOM3_FILTER_TF=OFF | FU2: MOM3_FILTER_TF=D | FV2: MOM3_FILTER_TF=4h | FW2: MOM3_FILTER_TF=1h | FX2: MOM3_FILTER_TF=15m | FY2: MOMENTUM_BREAKOUT_FILTER_TF=OFF | FZ2: MOMENTUM_BREAKOUT_FILTER_TF=D | GA2: MOMENTUM_BREAKOUT_FILTER_TF=4h | GB2: MOMENTUM_BREAKOUT_FILTER_TF=1h | GC2: MOMENTUM_BREAKOUT_FILTER_TF=15m | GD2: MTF_ARMED_ENTRIES_FILTER_TF=OFF | GE2: MTF_ARMED_ENTRIES_FILTER_TF=D | GF2: MTF_ARMED_ENTRIES_FILTER_TF=4h | GG2: MTF_ARMED_ENTRIES_FILTER_TF=1h | GH2: MTF_ARMED_ENTRIES_FILTER_TF=15m | GI2: MTF_ATR_TRAIL_FILTER_TF=OFF | GJ2: MTF_ATR_TRAIL_FILTER_TF=D | GK2: MTF_ATR_TRAIL_FILTER_TF=4h | GL2: MTF_ATR_TRAIL_FILTER_TF=1h | GM2: MTF_ATR_TRAIL_FILTER_TF=15m | GN2: MTF_DC_REJECT_FILTER_TF=OFF | GO2: MTF_DC_REJECT_FILTER_TF=D | GP2: MTF_DC_REJECT_FILTER_TF=4h | GQ2: MTF_DC_REJECT_FILTER_TF=1h | GR2: MTF_DC_REJECT_FILTER_TF=15m | GS2: NEWBORN_LOSS_KILL_FILTER_TF=OFF | GT2: NEWBORN_LOSS_KILL_FILTER_TF=D | GU2: NEWBORN_LOSS_KILL_FILTER_TF=4h | GV2: NEWBORN_LOSS_KILL_FILTER_TF=1h | GW2: NEWBORN_LOSS_KILL_FILTER_TF=15m | GX2: NEWBORN_PROTECT_FILTER_TF=OFF | GY2: NEWBORN_PROTECT_FILTER_TF=D | GZ2: NEWBORN_PROTECT_FILTER_TF=4h | HA2: NEWBORN_PROTECT_FILTER_TF=1h | HB2: NEWBORN_PROTECT_FILTER_TF=15m | HC2: NOLOSS_BYPASS_WT5OF5_FILTER_TF=OFF | HD2: NOLOSS_BYPASS_WT5OF5_FILTER_TF=D | HE2: NOLOSS_BYPASS_WT5OF5_FILTER_TF=4h | HF2: NOLOSS_BYPASS_WT5OF5_FILTER_TF=1h | HG2: NOLOSS_BYPASS_WT5OF5_FILTER_TF=15m | HH2: OPEN_INTENT_SIZE_GATES_FILTER_TF=OFF | HI2: OPEN_INTENT_SIZE_GATES_FILTER_TF=D | HJ2: OPEN_INTENT_SIZE_GATES_FILTER_TF=4h | HK2: OPEN_INTENT_SIZE_GATES_FILTER_TF=1h | HL2: OPEN_INTENT_SIZE_GATES_FILTER_TF=15m | HM2: PARTIAL_PROFIT_LOCK_V2_FILTER_TF=OFF | HN2: PARTIAL_PROFIT_LOCK_V2_FILTER_TF=D | HO2: PARTIAL_PROFIT_LOCK_V2_FILTER_TF=4h | HP2: PARTIAL_PROFIT_LOCK_V2_FILTER_TF=1h | HQ2: PARTIAL_PROFIT_LOCK_V2_FILTER_TF=15m | HR2: PEAK_GIVEBACK_BE_EROSION_FILTER_TF=OFF | HS2: PEAK_GIVEBACK_BE_EROSION_FILTER_TF=D | HT2: PEAK_GIVEBACK_BE_EROSION_FILTER_TF=4h | HU2: PEAK_GIVEBACK_BE_EROSION_FILTER_TF=1h | HV2: PEAK_GIVEBACK_BE_EROSION_FILTER_TF=15m | HW2: WT_15M_BOUNCE_BB_MAX=0.95 | HX2: WT_15M_BOUNCE_BB_MAX=0.9 | HY2: WT_15M_BOUNCE_BB_MAX=0.8 | HZ2: WT_15M_BOUNCE_BB_MIN=0.05 | IA2: WT_15M_BOUNCE_BB_MIN=0.1 | IB2: WT_15M_BOUNCE_BB_MIN=0.2 | IC2: WT_15M_BOUNCE_HIGH_1H_GT_PREV=True | ID2: WT_15M_BOUNCE_HIGH_1H_GT_PREV=False | IE2: WT_15M_BOUNCE_LOW_1H_GT_PREV=True | IF2: WT_15M_BOUNCE_LOW_1H_GT_PREV=False | IG2: WT_15M_BOUNCE_REL_VOL_GT_1=True | IH2: WT_15M_BOUNCE_REL_VOL_GT_1=False | II2: Live Location | IJ2: Vec Hook | IK2: Type | IL2: Correct Options
A3: WT_15M_BOUNCE_OPEN_ENABLED | B3: False | C3: WT_15M_BOUNCE_OPEN_ENABLED=False + WT_15M_BOUNCE_BB_MAX=0.8 + BB_WT_TF=15m + GR=18 + BB_RECOVERY_FILTER_TF=OFF + DC_BREAK_FILTER_TF=1h | E3: ='TEMPLATE_BASELINE_METRICS'!B2 | F3: =IFERROR(VLOOKUP($A3&"="&$B3,Results_30d_Deltas!$A$2:$H$5000,5,FALSE),"") | G3: =IFERROR(VLOOKUP($A3,Results_30d_Deltas!$A$2:$H$5000,7,FALSE)-E3,"") | H3: =IFERROR(VLOOKUP($A3,Results_30d_Deltas!$A$2:$H$5000,6,FALSE),"") | K3: =IF(B3=C3,"YES","NO") | IJ3: ez_manage.py:6076 top() | IK3: v12_quick_engine.py:4288 x7
A4: WT_15M_BOUNCE_OPEN_ENABLED | B4: True | C4: WT_15M_BOUNCE_OPEN_ENABLED=True + WT_15M_BOUNCE_BB_MAX=0.8 + BB_WT_TF=15m + GR=18 + BB_RECOVERY_FILTER_TF=OFF + DC_BREAK_FILTER_TF=1h | E4: =IF(F4="",E3,IF(F4>0,E3+F4,E3)) | F4: -0.57559161 | G4: -2.2317455 | H4: =IFERROR(VLOOKUP($A4,Results_30d_Deltas!$A$2:$H$5000,6,FALSE),"") | K4: =IF(B4=C4,"YES","NO") | IJ4: ez_manage.py:6076 top() | IK4: v12_quick_engine.py:4288 x7
A5: BB_SQUEEZE_ENTRY_ENABLED | B5: True | C5: BB_SQUEEZE_ENTRY_ENABLED=True + ADX_RANGING_THRESHOLD=25 + BB_WT_TF=15m + GR=18 + BB_RECOVERY_FILTER_TF=OFF + DC_BREAK_FILTER_TF=1h | E5: =IF(F5="",E4,IF(F5>0,E4+F5,E4)) | F5: 0 | G5: -1.6561539 | H5: =IFERROR(VLOOKUP($A5,Results_30d_Deltas!$A$2:$H$5000,6,FALSE),"") | K5: =IF(B5=C5,"YES","NO") | IJ5: ez_manage.py:4371 top() | IK5: v12_quick_engine.py:889 x9
A6: BB_PULLBACK_GATE_TF | B6: OFF | C6: BB_PULLBACK_GATE_TF=OFF + MTS_BOTTOM_STRONG_THRESHOLD=20 + BB_WT_TF=15m + GR=18 + BB_RECOVERY_FILTER_TF=OFF + DC_BREAK_FILTER_TF=1h | E6: =IF(F6="",E5,IF(F6>0,E5+F6,E5)) | F6: -2.4538266 | G6: -4.1099804 | H6: =IFERROR(VLOOKUP($A6,Results_30d_Deltas!$A$2:$H$5000,6,FALSE),"") | K6: =IF(B6=C6,"YES","NO") | IJ6: ez_manage.py:4361 top() | IK6: v12_quick_engine.py:288 x12
A7: BB_PULLBACK_GATE_TF | B7: D | E7: =IF(F7="",E6,IF(F7>0,E6+F7,E6)) | F7: 0 | G7: -1.6561539 | H7: =IFERROR(VLOOKUP($A7,Results_30d_Deltas!$A$2:$H$5000,6,FALSE),"") | K7: =IF(B7=C7,"YES","NO") | IJ7: ez_manage.py:4361 top() | IK7: v12_quick_engine.py:288 x12
A8: BB_PULLBACK_GATE_TF | B8: 4h | E8: =IF(F8="",E7,IF(F8>0,E7+F8,E7)) | F8: 0 | G8: -1.6561539 | H8: =IFERROR(VLOOKUP($A8,Results_30d_Deltas!$A$2:$H$5000,6,FALSE),"") | K8: =IF(B8=C8,"YES","NO") | IJ8: ez_manage.py:4361 top() | IK8: v12_quick_engine.py:288 x12
A9: BB_PULLBACK_GATE_TF | B9: 1h | C9: BB_PULLBACK_GATE_TF=1h + MI_TF_AGREE_MIN=0.0_ALT + BB_WT_TF=15m + GR=18 + BB_RECOVERY_FILTER_TF=OFF + DC_BREAK_FILTER_TF=1h | E9: =IF(F9="",E8,IF(F9>0,E8+F9,E8)) | F9: -1.8526111 | G9: -3.508765 | H9: =IFERROR(VLOOKUP($A9,Results_30d_Deltas!$A$2:$H$5000,6,FALSE),"") | K9: =IF(B9=C9,"YES","NO") | IJ9: ez_manage.py:4361 top() | IK9: v12_quick_engine.py:288 x12
A10: BB_PULLBACK_GATE_TF | B10: 15m | E10: =IF(F10="",E9,IF(F10>0,E9+F10,E9)) | F10: =IFERROR(VLOOKUP($A10&"="&$B10,Results_30d_Deltas!$A$2:$H$5000,5,FALSE),"") | G10: =IFERROR(VLOOKUP($A10,Results_30d_Deltas!$A$2:$H$5000,7,FALSE)-E9,"") | H10: =IFERROR(VLOOKUP($A10,Results_30d_Deltas!$A$2:$H$5000,6,FALSE),"") | K10: =IF(B10=C10,"YES","NO") | IJ10: ez_manage.py:4361 top() | IK10: v12_quick_engine.py:288 x12
A11: DELTA_GATE_BB_SQUEEZE | B11: True | E11: =IF(F11="",E10,IF(F11>0,E10+F11,E10)) | F11: =IFERROR(VLOOKUP($A11&"="&$B11,Results_30d_Deltas!$A$2:$H$5000,5,FALSE),"") | G11: =IFERROR(VLOOKUP($A11,Results_30d_Deltas!$A$2:$H$5000,7,FALSE)-E10,"") | H11: =IFERROR(VLOOKUP($A11,Results_30d_Deltas!$A$2:$H$5000,6,FALSE),"") | K11: =IF(B11=C11,"YES","NO") | IJ11: ez_manage.py:4603 top() | IK11: v12_quick_engine.py:969 x9
A12: BB_SQUEEZE_WIDTH_PERCENTILE | B12: 0.1 | E12: =IF(F12="",E11,IF(F12>0,E11+F12,E11)) | F12: -1.8526111 | G12: -3.508765 | H12: =IFERROR(VLOOKUP($A12,Results_30d_Deltas!$A$2:$H$5000,6,FALSE),"") | K12: =IF(B12=C12,"YES","NO") | IJ12: ez_manage.py:4375 top() | IK12: v12_quick_engine.py:1285 x7
A13: BB_SQUEEZE_WIDTH_PERCENTILE | B13: 0.15 | E13: =IF(F13="",E12,IF(F13>0,E12+F13,E12)) | F13: 0 | G13: -1.6561539 | H13: =IFERROR(VLOOKUP($A13,Results_30d_Deltas!$A$2:$H$5000,6,FALSE),"") | K13: =IF(B13=C13,"YES","NO") | IJ13: ez_manage.py:4375 top() | IK13: v12_quick_engine.py:1285 x7
A14: BB_SQUEEZE_WIDTH_PERCENTILE | B14: 0.2 | E14: =IF(F14="",E13,IF(F14>0,E13+F14,E13)) | F14: 0 | G14: -1.6561539 | H14: =IFERROR(VLOOKUP($A14,Results_30d_Deltas!$A$2:$H$5000,6,FALSE),"") | K14: =IF(B14=C14,"YES","NO") | IJ14: ez_manage.py:4375 top() | IK14: v12_quick_engine.py:1285 x7
A15: BB_SQUEEZE_WIDTH_PERCENTILE | B15: 0.25 | E15: =IF(F15="",E14,IF(F15>0,E14+F15,E14)) | F15: -1.8542583 | G15: -3.5104122 | H15: =IFERROR(VLOOKUP($A15,Results_30d_Deltas!$A$2:$H$5000,6,FALSE),"") | K15: =IF(B15=C15,"YES","NO") | IJ15: ez_manage.py:4375 top() | IK15: v12_quick_engine.py:1285 x7
A16: BB_SQUEEZE_WIDTH_PERCENTILE | B16: 0.3 | E16: =IF(F16="",E15,IF(F16>0,E15+F16,E15)) | F16: -1.8526111 | G16: -3.508765 | H16: =IFERROR(VLOOKUP($A16,Results_30d_Deltas!$A$2:$H$5000,6,FALSE),"") | K16: =IF(B16=C16,"YES","NO") | IJ16: ez_manage.py:4375 top() | IK16: v12_quick_engine.py:1285 x7
A17: WT_DIV_EXIT_ENABLED | B17: False | E17: =IF(F17="",E16,IF(F17>0,E16+F17,E16)) | F17: -2.0610562 | G17: -3.7172101 | H17: =IFERROR(VLOOKUP($A17,Results_30d_Deltas!$A$2:$H$5000,6,FALSE),"") | K17: =IF(B17=C17,"YES","NO") | IJ17: ez_manage.py:6086 top() | IK17: v12_quick_engine.py:4292 x3
A18: WT_DIV_EXIT_ENABLED | B18: True | E18: =IF(F18="",E17,IF(F18>0,E17+F18,E17)) | F18: =IFERROR(VLOOKUP($A18&"="&$B18,Results_30d_Deltas!$A$2:$H$5000,5,FALSE),"") | G18: =IFERROR(VLOOKUP($A18,Results_30d_Deltas!$A$2:$H$5000,7,FALSE)-E17,"") | H18: =IFERROR(VLOOKUP($A18,Results_30d_Deltas!$A$2:$H$5000,6,FALSE),"") | K18: =IF(B18=C18,"YES","NO") | IJ18: ez_manage.py:6086 top() | IK18: v12_quick_engine.py:4292 x3
A19: WT_MOMENTUM_EXIT_THRESHOLD | B19: 0 | E19: =IF(F19="",E18,IF(F19>0,E18+F19,E18)) | F19: -1.8934256 | G19: -3.5495795 | H19: =IFERROR(VLOOKUP($A19,Results_30d_Deltas!$A$2:$H$5000,6,FALSE),"") | K19: =IF(B19=C19,"YES","NO") | IJ19: ez_manage.py:6087 top() | IK19: v12_quick_engine.py:4293 x3
A20: WT_MOMENTUM_EXIT_THRESHOLD | B20: 1 | E20: =IF(F20="",E19,IF(F20>0,E19+F20,E19)) | F20: 0 | G20: -1.6561539 | H20: =IFERROR(VLOOKUP($A20,Results_30d_Deltas!$A$2:$H$5000,6,FALSE),"") | K20: =IF(B20=C20,"YES","NO") | IJ20: ez_manage.py:6087 top() | IK20: v12_quick_engine.py:4293 x3
A21: WT_MOMENTUM_EXIT_THRESHOLD | B21: 2 | E21: =IF(F21="",E20,IF(F21>0,E20+F21,E20)) | F21: -1.8526111 | G21: -3.508765 | H21: =IFERROR(VLOOKUP($A21,Results_30d_Deltas!$A$2:$H$5000,6,FALSE),"") | K21: =IF(B21=C21,"YES","NO") | IJ21: ez_manage.py:6087 top() | IK21: v12_quick_engine.py:4293 x3
A22: WT_ACCEL_EXIT_ENABLED | B22: False | E22: =IF(F22="",E21,IF(F22>0,E21+F22,E21)) | F22: 0 | G22: -1.6561539 | H22: =IFERROR(VLOOKUP($A22,Results_30d_Deltas!$A$2:$H$5000,6,FALSE),"") | K22: =IF(B22=C22,"YES","NO") | IJ22: ez_manage.py:6083 top() | IK22: v12_quick_engine.py:4290 x3
A23: WT_ACCEL_EXIT_ENABLED | B23: True | E23: =IF(F23="",E22,IF(F23>0,E22+F23,E22)) | F23: =IFERROR(VLOOKUP($A23&"="&$B23,Results_30d_Deltas!$A$2:$H$5000,5,FALSE),"") | G23: =IFERROR(VLOOKUP($A23,Results_30d_Deltas!$A$2:$H$5000,7,FALSE)-E22,"") | H23: =IFERROR(VLOOKUP($A23,Results_30d_Deltas!$A$2:$H$5000,6,FALSE),"") | K23: =IF(B23=C23,"YES","NO") | IJ23: ez_manage.py:6083 top() | IK23: v12_quick_engine.py:4290 x3

Sheet ENTRY_BREAKOUT_CHANNEL
A1: 02 ENTRY_BREAKOUT_CHANNEL - 54 bases -> 210 rows - 231 per-row FULLY CONNECTED
A2: Switch | B2: default | C2: override | D2: Family | E2: BASELINE | F2: VECTOR_DELTA | G2: LIVE_DELTA | H2: LIVE_SHARPE | I2: REAL_COMPLETE | J2: PER_ROW_FILTERS | K2: is_default (backup if bold lost) | L2: ATR_TRAIL_FILTER_TF=OFF | M2: ATR_TRAIL_FILTER_TF=D | N2: ATR_TRAIL_FILTER_TF=4h | O2: ATR_TRAIL_FILTER_TF=1h | P2: ATR_TRAIL_FILTER_TF=15m | Q2: BAR_PATTERNS_FILTER_TF=OFF | R2: BAR_PATTERNS_FILTER_TF=D | S2: BAR_PATTERNS_FILTER_TF=4h | T2: BAR_PATTERNS_FILTER_TF=1h | U2: BAR_PATTERNS_FILTER_TF=15m | V2: BB_PULLBACK_GATE_FILTER_TF=OFF | W2: BB_PULLBACK_GATE_FILTER_TF=D | X2: BB_PULLBACK_GATE_FILTER_TF=4h | Y2: BB_PULLBACK_GATE_FILTER_TF=1h | Z2: BB_PULLBACK_GATE_FILTER_TF=15m | AA2: BB_RECOVERY_ENTRY_FILTER_TF=OFF | AB2: BB_RECOVERY_ENTRY_FILTER_TF=D | AC2: BB_RECOVERY_ENTRY_FILTER_TF=4h | AD2: BB_RECOVERY_ENTRY_FILTER_TF=1h | AE2: BB_RECOVERY_ENTRY_FILTER_TF=15m | AF2: BB_RECOVERY_FILTER_TF=OFF | AG2: BB_RECOVERY_FILTER_TF=D | AH2: BB_RECOVERY_FILTER_TF=4h | AI2: BB_RECOVERY_FILTER_TF=1h | AJ2: BB_RECOVERY_FILTER_TF=15m | AK2: BREAKEVEN_GAIN_EROSION_FILTER_TF=OFF | AL2: BREAKEVEN_GAIN_EROSION_FILTER_TF=D | AM2: BREAKEVEN_GAIN_EROSION_FILTER_TF=4h | AN2: BREAKEVEN_GAIN_EROSION_FILTER_TF=1h | AO2: BREAKEVEN_GAIN_EROSION_FILTER_TF=15m | AP2: BREAKOUT_RETEST_FILTER_TF=OFF | AQ2: BREAKOUT_RETEST_FILTER_TF=D | AR2: BREAKOUT_RETEST_FILTER_TF=4h | AS2: BREAKOUT_RETEST_FILTER_TF=1h | AT2: BREAKOUT_RETEST_FILTER_TF=15m | AU2: BT_WT_CROSS_LADDER_FILTER_TF=OFF | AV2: BT_WT_CROSS_LADDER_FILTER_TF=D | AW2: BT_WT_CROSS_LADDER_FILTER_TF=4h | AX2: BT_WT_CROSS_LADDER_FILTER_TF=1h | AY2: BT_WT_CROSS_LADDER_FILTER_TF=15m | AZ2: CANDLE_PATTERN_STOPS_FILTER_TF=OFF | BA2: CANDLE_PATTERN_STOPS_FILTER_TF=D | BB2: CANDLE_PATTERN_STOPS_FILTER_TF=4h | BC2: CANDLE_PATTERN_STOPS_FILTER_TF=1h | BD2: CANDLE_PATTERN_STOPS_FILTER_TF=15m | BE2: CIRCUIT_SHARPE_GATES_FILTER_TF=OFF | BF2: CIRCUIT_SHARPE_GATES_FILTER_TF=D | BG2: CIRCUIT_SHARPE_GATES_FILTER_TF=4h | BH2: CIRCUIT_SHARPE_GATES_FILTER_TF=1h | BI2: CIRCUIT_SHARPE_GATES_FILTER_TF=15m | BJ2: DC_BREACH_REDUCE_FILTER_TF=OFF | BK2: DC_BREACH_REDUCE_FILTER_TF=D | BL2: DC_BREACH_REDUCE_FILTER_TF=4h | BM2: DC_BREACH_REDUCE_FILTER_TF=1h | BN2: DC_BREACH_REDUCE_FILTER_TF=15m | BO2: DC_BREAK_FILTER_TF=OFF | BP2: DC_BREAK_FILTER_TF=D | BQ2: DC_BREAK_FILTER_TF=4h | BR2: DC_BREAK_FILTER_TF=1h | BS2: DC_BREAK_FILTER_TF=15m | BT2: DC_MOMENTUM_BOTA_SCORER_FILTER_TF=OFF | BU2: DC_MOMENTUM_BOTA_SCORER_FILTER_TF=D | BV2: DC_MOMENTUM_BOTA_SCORER_FILTER_TF=4h | BW2: DC_MOMENTUM_BOTA_SCORER_FILTER_TF=1h | BX2: DC_MOMENTUM_BOTA_SCORER_FILTER_TF=15m | BY2: DELTA_ENGINE_FILTER_TF=OFF | BZ2: DELTA_ENGINE_FILTER_TF=D | CA2: DELTA_ENGINE_FILTER_TF=4h | CB2: DELTA_ENGINE_FILTER_TF=1h | CC2: DELTA_ENGINE_FILTER_TF=15m | CD2: EMA_9_21_FILTER_FILTER_TF=OFF | CE2: EMA_9_21_FILTER_FILTER_TF=D | CF2: EMA_9_21_FILTER_FILTER_TF=4h | CG2: EMA_9_21_FILTER_FILTER_TF=1h | CH2: EMA_9_21_FILTER_FILTER_TF=15m | CI2: EMA_BLANKET_FILTER_FILTER_TF=OFF | CJ2: EMA_BLANKET_FILTER_FILTER_TF=D | CK2: EMA_BLANKET_FILTER_FILTER_TF=4h | CL2: EMA_BLANKET_FILTER_FILTER_TF=1h | CM2: EMA_BLANKET_FILTER_FILTER_TF=15m | CN2: EMERGENCY_BRAKE_FILTER_TF=OFF | CO2: EMERGENCY_BRAKE_FILTER_TF=D | CP2: EMERGENCY_BRAKE_FILTER_TF=4h | CQ2: EMERGENCY_BRAKE_FILTER_TF=1h | CR2: EMERGENCY_BRAKE_FILTER_TF=15m | CS2: EXIT_R1_R2_FILTER_TF=OFF | CT2: EXIT_R1_R2_FILTER_TF=D | CU2: EXIT_R1_R2_FILTER_TF=4h | CV2: EXIT_R1_R2_FILTER_TF=1h | CW2: EXIT_R1_R2_FILTER_TF=15m | CX2: EXIT_TIGHT_BREAKOUT_SCORER_FILTER_TF=OFF | CY2: EXIT_TIGHT_BREAKOUT_SCORER_FILTER_TF=D | CZ2: EXIT_TIGHT_BREAKOUT_SCORER_FILTER_TF=4h | DA2: EXIT_TIGHT_BREAKOUT_SCORER_FILTER_TF=1h | DB2: EXIT_TIGHT_BREAKOUT_SCORER_FILTER_TF=15m | DC2: EXIT_TOP_FADE_FILTER_TF=OFF | DD2: EXIT_TOP_FADE_FILTER_TF=D | DE2: EXIT_TOP_FADE_FILTER_TF=4h | DF2: EXIT_TOP_FADE_FILTER_TF=1h | DG2: EXIT_TOP_FADE_FILTER_TF=15m | DH2: EXIT_TO_REDUCE_ADAPTER_FILTER_TF=OFF | DI2: EXIT_TO_REDUCE_ADAPTER_FILTER_TF=D | DJ2: EXIT_TO_REDUCE_ADAPTER_FILTER_TF=4h | DK2: EXIT_TO_REDUCE_ADAPTER_FILTER_TF=1h | DL2: EXIT_TO_REDUCE_ADAPTER_FILTER_TF=15m | DM2: FAST_RISER_FILTER_TF=OFF | DN2: FAST_RISER_FILTER_TF=D | DO2: FAST_RISER_FILTER_TF=4h | DP2: FAST_RISER_FILTER_TF=1h | DQ2: FAST_RISER_FILTER_TF=15m | DR2: FH_MOMENTUM_FILTER_TF=OFF | DS2: FH_MOMENTUM_FILTER_TF=D | DT2: FH_MOMENTUM_FILTER_TF=4h | DU2: FH_MOMENTUM_FILTER_TF=1h | DV2: FH_MOMENTUM_FILTER_TF=15m | DW2: FIRST_OPEN_THROTTLE_FILTER_TF=OFF | DX2: FIRST_OPEN_THROTTLE_FILTER_TF=D | DY2: FIRST_OPEN_THROTTLE_FILTER_TF=4h | DZ2: FIRST_OPEN_THROTTLE_FILTER_TF=1h | EA2: FIRST_OPEN_THROTTLE_FILTER_TF=15m | EB2: FROZEN_STOP_FILTER_TF=OFF | EC2: FROZEN_STOP_FILTER_TF=D | ED2: FROZEN_STOP_FILTER_TF=4h | EE2: FROZEN_STOP_FILTER_TF=1h | EF2: FROZEN_STOP_FILTER_TF=15m | EG2: GOLDEN_RULE_ENFORCE_FILTER_TF=OFF | EH2: GOLDEN_RULE_ENFORCE_FILTER_TF=D | EI2: GOLDEN_RULE_ENFORCE_FILTER_TF=4h | EJ2: GOLDEN_RULE_ENFORCE_FILTER_TF=1h | EK2: GOLDEN_RULE_ENFORCE_FILTER_TF=15m | EL2: GOLDEN_RULE_HTF_VOTE_FILTER_TF=OFF | EM2: GOLDEN_RULE_HTF_VOTE_FILTER_TF=D | EN2: GOLDEN_RULE_HTF_VOTE_FILTER_TF=4h | EO2: GOLDEN_RULE_HTF_VOTE_FILTER_TF=1h | EP2: GOLDEN_RULE_HTF_VOTE_FILTER_TF=15m | EQ2: GR_FILTER_VEC_FILTER_TF=OFF | ER2: GR_FILTER_VEC_FILTER_TF=D | ES2: GR_FILTER_VEC_FILTER_TF=4h | ET2: GR_FILTER_VEC_FILTER_TF=1h | EU2: GR_FILTER_VEC_FILTER_TF=15m | EV2: GR_V5_STATE_FILTER_TF=OFF | EW2: GR_V5_STATE_FILTER_TF=D | EX2: GR_V5_STATE_FILTER_TF=4h | EY2: GR_V5_STATE_FILTER_TF=1h | EZ2: GR_V5_STATE_FILTER_TF=15m | FA2: HAIKU_WINNER_FILTER_TF=OFF | FB2: HAIKU_WINNER_FILTER_TF=D | FC2: HAIKU_WINNER_FILTER_TF=4h | FD2: HAIKU_WINNER_FILTER_TF=1h | FE2: HAIKU_WINNER_FILTER_TF=15m | FF2: LH_HL_FILTER_TF_REQ=2 | FG2: LH_HL_FILTER_TF_REQ=2_ALT | FH2: LIVE_ENTRY_ENGINE_FILTER_TF=OFF | FI2: LIVE_ENTRY_ENGINE_FILTER_TF=D | FJ2: LIVE_ENTRY_ENGINE_FILTER_TF=4h | FK2: LIVE_ENTRY_ENGINE_FILTER_TF=1h | FL2: LIVE_ENTRY_ENGINE_FILTER_TF=15m | FM2: LIVE_ONLY_SIGNALS_BATCH5_FILTER_TF=OFF | FN2: LIVE_ONLY_SIGNALS_BATCH5_FILTER_TF=D | FO2: LIVE_ONLY_SIGNALS_BATCH5_FILTER_TF=4h | FP2: LIVE_ONLY_SIGNALS_BATCH5_FILTER_TF=1h | FQ2: LIVE_ONLY_SIGNALS_BATCH5_FILTER_TF=15m | FR2: MANDATORY_REENTRY_WT_FILTER_TF_MODE=15m_only | FS2: MANDATORY_REENTRY_WT_FILTER_TF_MODE=15m_only_ALT | FT2: MOM3_FILTER_TF=OFF | FU2: MOM3_FILTER_TF=D | FV2: MOM3_FILTER_TF=4h | FW2: MOM3_FILTER_TF=1h | FX2: MOM3_FILTER_TF=15m | FY2: MOMENTUM_BREAKOUT_FILTER_TF=OFF | FZ2: MOMENTUM_BREAKOUT_FILTER_TF=D | GA2: MOMENTUM_BREAKOUT_FILTER_TF=4h | GB2: MOMENTUM_BREAKOUT_FILTER_TF=1h | GC2: MOMENTUM_BREAKOUT_FILTER_TF=15m | GD2: MTF_ARMED_ENTRIES_FILTER_TF=OFF | GE2: MTF_ARMED_ENTRIES_FILTER_TF=D | GF2: MTF_ARMED_ENTRIES_FILTER_TF=4h | GG2: MTF_ARMED_ENTRIES_FILTER_TF=1h | GH2: MTF_ARMED_ENTRIES_FILTER_TF=15m | GI2: MTF_ATR_TRAIL_FILTER_TF=OFF | GJ2: MTF_ATR_TRAIL_FILTER_TF=D | GK2: MTF_ATR_TRAIL_FILTER_TF=4h | GL2: MTF_ATR_TRAIL_FILTER_TF=1h | GM2: MTF_ATR_TRAIL_FILTER_TF=15m | GN2: MTF_DC_REJECT_FILTER_TF=OFF | GO2: MTF_DC_REJECT_FILTER_TF=D | GP2: MTF_DC_REJECT_FILTER_TF=4h | GQ2: MTF_DC_REJECT_FILTER_TF=1h | GR2: MTF_DC_REJECT_FILTER_TF=15m | GS2: NEWBORN_LOSS_KILL_FILTER_TF=OFF | GT2: NEWBORN_LOSS_KILL_FILTER_TF=D | GU2: NEWBORN_LOSS_KILL_FILTER_TF=4h | GV2: NEWBORN_LOSS_KILL_FILTER_TF=1h | GW2: NEWBORN_LOSS_KILL_FILTER_TF=15m | GX2: NEWBORN_PROTECT_FILTER_TF=OFF | GY2: NEWBORN_PROTECT_FILTER_TF=D | GZ2: NEWBORN_PROTECT_FILTER_TF=4h | HA2: NEWBORN_PROTECT_FILTER_TF=1h | HB2: NEWBORN_PROTECT_FILTER_TF=15m | HC2: NOLOSS_BYPASS_WT5OF5_FILTER_TF=OFF | HD2: NOLOSS_BYPASS_WT5OF5_FILTER_TF=D | HE2: NOLOSS_BYPASS_WT5OF5_FILTER_TF=4h | HF2: NOLOSS_BYPASS_WT5OF5_FILTER_TF=1h | HG2: NOLOSS_BYPASS_WT5OF5_FILTER_TF=15m | HH2: OPEN_INTENT_SIZE_GATES_FILTER_TF=OFF | HI2: OPEN_INTENT_SIZE_GATES_FILTER_TF=D | HJ2: OPEN_INTENT_SIZE_GATES_FILTER_TF=4h | HK2: OPEN_INTENT_SIZE_GATES_FILTER_TF=1h | HL2: OPEN_INTENT_SIZE_GATES_FILTER_TF=15m | HM2: PARTIAL_PROFIT_LOCK_V2_FILTER_TF=OFF | HN2: PARTIAL_PROFIT_LOCK_V2_FILTER_TF=D | HO2: PARTIAL_PROFIT_LOCK_V2_FILTER_TF=4h | HP2: PARTIAL_PROFIT_LOCK_V2_FILTER_TF=1h | HQ2: PARTIAL_PROFIT_LOCK_V2_FILTER_TF=15m | HR2: PEAK_GIVEBACK_BE_EROSION_FILTER_TF=OFF | HS2: PEAK_GIVEBACK_BE_EROSION_FILTER_TF=D | HT2: PEAK_GIVEBACK_BE_EROSION_FILTER_TF=4h | HU2: PEAK_GIVEBACK_BE_EROSION_FILTER_TF=1h | HV2: PEAK_GIVEBACK_BE_EROSION_FILTER_TF=15m | HW2: WT_15M_BOUNCE_BB_MAX=0.95 | HX2: WT_15M_BOUNCE_BB_MAX=0.9 | HY2: WT_15M_BOUNCE_BB_MAX=0.8 | HZ2: WT_15M_BOUNCE_BB_MIN=0.05 | IA2: WT_15M_BOUNCE_BB_MIN=0.1 | IB2: WT_15M_BOUNCE_BB_MIN=0.2 | IC2: WT_15M_BOUNCE_HIGH_1H_GT_PREV=True | ID2: WT_15M_BOUNCE_HIGH_1H_GT_PREV=False | IE2: WT_15M_BOUNCE_LOW_1H_GT_PREV=True | IF2: WT_15M_BOUNCE_LOW_1H_GT_PREV=False | IG2: WT_15M_BOUNCE_REL_VOL_GT_1=True | IH2: WT_15M_BOUNCE_REL_VOL_GT_1=False | II2: Live Location | IJ2: Vec Hook | IK2: Type | IL2: Correct Options
A3: DC_BREAKOUT_TF | B3: OFF | E3: =MAX('ENTRY_REVERSAL_BOUNCE'!E:E) | F3: -1.0393426 | G3: -2.6954965 | H3: =IFERROR(VLOOKUP($A3,Results_30d_Deltas!$A$2:$H$5000,6,FALSE),"") | K3: =IF(B3=C3,"YES","NO") | IJ3: ez_manage.py:3078 top() | IK3: v12_quick_engine.py:1518 x5
A4: DC_BREAKOUT_TF | B4: D | E4: =IF(F4="",E3,IF(F4>0,E3+F4,E3)) | F4: 0 | G4: -1.6561539 | H4: =IFERROR(VLOOKUP($A4,Results_30d_Deltas!$A$2:$H$5000,6,FALSE),"") | K4: =IF(B4=C4,"YES","NO") | IJ4: ez_manage.py:3078 top() | IK4: v12_quick_engine.py:1518 x5
A5: DC_BREAKOUT_TF | B5: 4h | E5: =IF(F5="",E4,IF(F5>0,E4+F5,E4)) | F5: 0 | G5: -1.6561539 | H5: =IFERROR(VLOOKUP($A5,Results_30d_Deltas!$A$2:$H$5000,6,FALSE),"") | K5: =IF(B5=C5,"YES","NO") | IJ5: ez_manage.py:3078 top() | IK5: v12_quick_engine.py:1518 x5
A6: DC_BREAKOUT_TF | B6: 1h | E6: =IF(F6="",E5,IF(F6>0,E5+F6,E5)) | F6: -2.0245238 | G6: -3.6806777 | H6: =IFERROR(VLOOKUP($A6,Results_30d_Deltas!$A$2:$H$5000,6,FALSE),"") | K6: =IF(B6=C6,"YES","NO") | IJ6: ez_manage.py:3078 top() | IK6: v12_quick_engine.py:1518 x5
A7: DC_BREAKOUT_TF | B7: 15m | E7: =IF(F7="",E6,IF(F7>0,E6+F7,E6)) | F7: =IFERROR(VLOOKUP($A7&"="&$B7,Results_30d_Deltas!$A$2:$H$5000,5,FALSE),"") | G7: =IFERROR(VLOOKUP($A7,Results_30d_Deltas!$A$2:$H$5000,7,FALSE)-E6,"") | H7: =IFERROR(VLOOKUP($A7,Results_30d_Deltas!$A$2:$H$5000,6,FALSE),"") | K7: =IF(B7=C7,"YES","NO") | IJ7: ez_manage.py:3078 top() | IK7: v12_quick_engine.py:1518 x5
A8: DC_BREAKOUT_SCORE | B8: 10 | E8: =IF(F8="",E7,IF(F8>0,E7+F8,E7)) | F8: -1.8526111 | G8: -3.508765 | H8: =IFERROR(VLOOKUP($A8,Results_30d_Deltas!$A$2:$H$5000,6,FALSE),"") | K8: =IF(B8=C8,"YES","NO") | IJ8: ez_manage.py:3077 top() | IK8: v12_quick_engine.py:1517 x18
A9: DC_BREAKOUT_SCORE | B9: 15 | E9: =IF(F9="",E8,IF(F9>0,E8+F9,E8)) | F9: 0 | G9: -1.6561539 | H9: =IFERROR(VLOOKUP($A9,Results_30d_Deltas!$A$2:$H$5000,6,FALSE),"") | K9: =IF(B9=C9,"YES","NO") | IJ9: ez_manage.py:3077 top() | IK9: v12_quick_engine.py:1517 x18
A10: DC_BREAKOUT_SCORE | B10: 20 | E10: =IF(F10="",E9,IF(F10>0,E9+F10,E9)) | F10: 0 | G10: -1.6561539 | H10: =IFERROR(VLOOKUP($A10,Results_30d_Deltas!$A$2:$H$5000,6,FALSE),"") | K10: =IF(B10=C10,"YES","NO") | IJ10: ez_manage.py:3077 top() | IK10: v12_quick_engine.py:1517 x18
A11: DC_BREAKOUT_SCORE | B11: 25 | E11: =IF(F11="",E10,IF(F11>0,E10+F11,E10)) | F11: -2.0245238 | G11: -3.6806777 | H11: =IFERROR(VLOOKUP($A11,Results_30d_Deltas!$A$2:$H$5000,6,FALSE),"") | K11: =IF(B11=C11,"YES","NO") | IJ11: ez_manage.py:3077 top() | IK11: v12_quick_engine.py:1517 x18
A12: DC_BREAKOUT_SCORE | B12: 30 | E12: =IF(F12="",E11,IF(F12>0,E11+F12,E11)) | F12: -2.0245238 | G12: -3.6806777 | H12: =IFERROR(VLOOKUP($A12,Results_30d_Deltas!$A$2:$H$5000,6,FALSE),"") | K12: =IF(B12=C12,"YES","NO") | IJ12: ez_manage.py:3077 top() | IK12: v12_quick_engine.py:1517 x18
A13: BB_BREAKOUT_SCORE | B13: 10 | E13: =IF(F13="",E12,IF(F13>0,E12+F13,E12)) | F13: 0 | G13: -1.6561539 | H13: =IFERROR(VLOOKUP($A13,Results_30d_Deltas!$A$2:$H$5000,6,FALSE),"") | K13: =IF(B13=C13,"YES","NO") | IJ13: ez_manage.py:2963 top() | IK13: v12_quick_engine.py:1255 x6
A14: BB_BREAKOUT_SCORE | B14: 15 | E14: =IF(F14="",E13,IF(F14>0,E13+F14,E13)) | F14: -2.0610562 | G14: -3.7172101 | H14: =IFERROR(VLOOKUP($A14,Results_30d_Deltas!$A$2:$H$5000,6,FALSE),"") | K14: =IF(B14=C14,"YES","NO") | IJ14: ez_manage.py:2963 top() | IK14: v12_quick_engine.py:1255 x6
A15: BB_BREAKOUT_SCORE | B15: 20 | E15: =IF(F15="",E14,IF(F15>0,E14+F15,E14)) | F15: -2.0610562 | G15: -3.7172101 | H15: =IFERROR(VLOOKUP($A15,Results_30d_Deltas!$A$2:$H$5000,6,FALSE),"") | K15: =IF(B15=C15,"YES","NO") | IJ15: ez_manage.py:2963 top() | IK15: v12_quick_engine.py:1255 x6
A16: BB_BREAKOUT_SCORE | B16: 25 | E16: =IF(F16="",E15,IF(F16>0,E15+F16,E15)) | F16: 0 | G16: -1.6561539 | H16: =IFERROR(VLOOKUP($A16,Results_30d_Deltas!$A$2:$H$5000,6,FALSE),"") | K16: =IF(B16=C16,"YES","NO") | IJ16: ez_manage.py:2963 top() | IK16: v12_quick_engine.py:1255 x6
A17: BB_BREAKOUT_SCORE | B17: 30 | E17: =IF(F17="",E16,IF(F17>0,E16+F17,E16)) | F17: 0 | G17: -1.6561539 | H17: =IFERROR(VLOOKUP($A17,Results_30d_Deltas!$A$2:$H$5000,6,FALSE),"") | K17: =IF(B17=C17,"YES","NO") | IJ17: ez_manage.py:2963 top() | IK17: v12_quick_engine.py:1255 x6
A18: STDEV_BREAKOUT_ENABLED | B18: False | E18: =IF(F18="",E17,IF(F18>0,E17+F18,E17)) | F18: =IFERROR(VLOOKUP($A18&"="&$B18,Results_30d_Deltas!$A$2:$H$5000,5,FALSE),"") | G18: =IFERROR(VLOOKUP($A18,Results_30d_Deltas!$A$2:$H$5000,7,FALSE)-E17,"") | H18: =IFERROR(VLOOKUP($A18,Results_30d_Deltas!$A$2:$H$5000,6,FALSE),"") | K18: =IF(B18=C18,"YES","NO") | IJ18: ez_manage.py:4039 top() | IK18: v12_quick_engine.py:3275 x6
A19: STDEV_BREAKOUT_ENABLED | B19: True | E19: =IF(F19="",E18,IF(F19>0,E18+F19,E18)) | F19: 0 | G19: -1.6561539 | H19: =IFERROR(VLOOKUP($A19,Results_30d_Deltas!$A$2:$H$5000,6,FALSE),"") | K19: =IF(B19=C19,"YES","NO") | IJ19: ez_manage.py:4039 top() | IK19: v12_quick_engine.py:3275 x6
A20: BTC_BREAKOUT_ENTRY_ENABLED | B20: False | E20: =IF(F20="",E19,IF(F20>0,E19+F20,E19)) | F20: =IFERROR(VLOOKUP($A20&"="&$B20,Results_30d_Deltas!$A$2:$H$5000,5,FALSE),"") | G20: =IFERROR(VLOOKUP($A20,Results_30d_Deltas!$A$2:$H$5000,7,FALSE)-E19,"") | H20: =IFERROR(VLOOKUP($A20,Results_30d_Deltas!$A$2:$H$5000,6,FALSE),"") | K20: =IF(B20=C20,"YES","NO") | IJ20: ez_manage.py:4432 top() | IK20: v12_quick_engine.py:393 x8
A21: BTC_BREAKOUT_ENTRY_ENABLED | B21: True | E21: =IF(F21="",E20,IF(F21>0,E20+F21,E20)) | F21: 0 | G21: -1.6561539 | H21: =IFERROR(VLOOKUP($A21,Results_30d_Deltas!$A$2:$H$5000,6,FALSE),"") | K21: =IF(B21=C21,"YES","NO") | IJ21: ez_manage.py:4432 top() | IK21: v12_quick_engine.py:393 x8
A22: RZ_BREAKOUT_ENTRY_ENABLED | B22: False | E22: =IF(F22="",E21,IF(F22>0,E21+F22,E21)) | F22: =IFERROR(VLOOKUP($A22&"="&$B22,Results_30d_Deltas!$A$2:$H$5000,5,FALSE),"") | G22: =IFERROR(VLOOKUP($A22,Results_30d_Deltas!$A$2:$H$5000,7,FALSE)-E21,"") | H22: =IFERROR(VLOOKUP($A22,Results_30d_Deltas!$A$2:$H$5000,6,FALSE),"") | K22: =IF(B22=C22,"YES","NO") | IJ22: ez_manage.py:5398 top() | IK22: v12_quick_engine.py:3021 x3
A23: RZ_BREAKOUT_ENTRY_ENABLED | B23: True | E23: =IF(F23="",E22,IF(F23>0,E22+F23,E22)) | F23: -2.0245238 | G23: -3.6806777 | H23: =IFERROR(VLOOKUP($A23,Results_30d_Deltas!$A$2:$H$5000,6,FALSE),"") | K23: =IF(B23=C23,"YES","NO") | IJ23: ez_manage.py:5398 top() | IK23: v12_quick_engine.py:3021 x3
A24: ATR_ADAPTIVE_SIZING_TARGET_PCT | B24: 1.0 | E24: =IF(F24="",E23,IF(F24>0,E23+F24,E23)) | F24: 0 | G24: -1.6561539 | H24: =IFERROR(VLOOKUP($A24,Results_30d_Deltas!$A$2:$H$5000,6,FALSE),"") | K24: =IF(B24=C24,"YES","NO") | IJ24: ez_manage.py:4327 top() | IK24: v12_quick_engine.py:1209 x7
A25: ATR_ADAPTIVE_SIZING_TARGET_PCT | B25: 1.5 | E25: =IF(F25="",E24,IF(F25>0,E24+F25,E24)) | F25: -1.7073607 | G25: -3.3635146 | H25: =IFERROR(VLOOKUP($A25,Results_30d_Deltas!$A$2:$H$5000,6,FALSE),"") | K25: =IF(B25=C25,"YES","NO") | IJ25: ez_manage.py:4327 top() | IK25: v12_quick_engine.py:1209 x7
A26: ATR_ADAPTIVE_SIZING_TARGET_PCT | B26: 2.0 | E26: =IF(F26="",E25,IF(F26>0,E25+F26,E25)) | F26: -2.0245238 | G26: -3.6806777 | H26: =IFERROR(VLOOKUP($A26,Results_30d_Deltas!$A$2:$H$5000,6,FALSE),"") | K26: =IF(B26=C26,"YES","NO") | IJ26: ez_manage.py:4327 top() | IK26: v12_quick_engine.py:1209 x7
A27: ATR_ADAPTIVE_SIZING_TARGET_PCT | B27: 2.5 | E27: =IF(F27="",E26,IF(F27>0,E26+F27,E26)) | F27: 0 | G27: -1.6561539 | H27: =IFERROR(VLOOKUP($A27,Results_30d_Deltas!$A$2:$H$5000,6,FALSE),"") | K27: =IF(B27=C27,"YES","NO") | IJ27: ez_manage.py:4327 top() | IK27: v12_quick_engine.py:1209 x7
A28: ATR_ADAPTIVE_SIZING_TARGET_PCT | B28: 3.0 | E28: =IF(F28="",E27,IF(F28>0,E27+F28,E27)) | F28: 0 | G28: -1.6561539 | H28: =IFERROR(VLOOKUP($A28,Results_30d_Deltas!$A$2:$H$5000,6,FALSE),"") | K28: =IF(B28=C28,"YES","NO") | IJ28: ez_manage.py:4327 top() | IK28: v12_quick_engine.py:1209 x7
A29: ATR_ADAPTIVE_STOP_MULT | B29: 1.0 | E29: =IF(F29="",E28,IF(F29>0,E28+F29,E28)) | F29: -2.4538266 | G29: -4.1099804 | H29: =IFERROR(VLOOKUP($A29,Results_30d_Deltas!$A$2:$H$5000,6,FALSE),"") | K29: =IF(B29=C29,"YES","NO") | IJ29: ez_manage.py:4329 top() | IK29: v12_quick_engine.py:1211 x6
A30: ATR_ADAPTIVE_STOP_MULT | B30: 1.5 | E30: =IF(F30="",E29,IF(F30>0,E29+F30,E29)) | F30: 0 | G30: -1.6561539 | H30: =IFERROR(VLOOKUP($A30,Results_30d_Deltas!$A$2:$H$5000,6,FALSE),"") | K30: =IF(B30=C30,"YES","NO") | IJ30: ez_manage.py:4329 top() | IK30: v12_quick_engine.py:1211 x6
A31: ATR_ADAPTIVE_STOP_MULT | B31: 2.0 | E31: =IF(F31="",E30,IF(F31>0,E30+F31,E30)) | F31: 0 | G31: -1.6561539 | H31: =IFERROR(VLOOKUP($A31,Results_30d_Deltas!$A$2:$H$5000,6,FALSE),"") | K31: =IF(B31=C31,"YES","NO") | IJ31: ez_manage.py:4329 top() | IK31: v12_quick_engine.py:1211 x6
A32: ATR_ADAPTIVE_STOP_MULT | B32: 2.5 | E32: =IF(F32="",E31,IF(F32>0,E31+F32,E31)) | F32: -2.4538266 | G32: -4.1099804 | H32: =IFERROR(VLOOKUP($A32,Results_30d_Deltas!$A$2:$H$5000,6,FALSE),"") | K32: =IF(B32=C32,"YES","NO") | IJ32: ez_manage.py:4329 top() | IK32: v12_quick_engine.py:1211 x6
A33: ATR_ADAPTIVE_STOP_MULT | B33: 3.0 | E33: =IF(F33="",E32,IF(F33>0,E32+F33,E32)) | F33: -1.8542583 | G33: -3.5104122 | H33: =IFERROR(VLOOKUP($A33,Results_30d_Deltas!$A$2:$H$5000,6,FALSE),"") | K33: =IF(B33=C33,"YES","NO") | IJ33: ez_manage.py:4329 top() | IK33: v12_quick_engine.py:1211 x6
A34: ATR_LONG_WINDOW | B34: 50 | E34: =IF(F34="",E33,IF(F34>0,E33+F34,E33)) | F34: 0 | G34: -1.6561539 | H34: =IFERROR(VLOOKUP($A34,Results_30d_Deltas!$A$2:$H$5000,6,FALSE),"") | K34: =IF(B34=C34,"YES","NO") | IJ34: ez_manage.py:4330 top() | IK34: v12_quick_engine.py:199 x5
... A48: ENTRY_PRIMARY_TF | B48: D | E48: =IF(F48="",E47,IF(F48>0,E47+F48,E47)) | F48: 0 | G48: -1.6561539 | H48: =IFERROR(VLOOKUP($A48,Results_30d_Deltas!$A$2:$H$5000,6,FALSE),"") | K48: =IF(B48=C48,"YES","NO") | IJ48: ez_manage.py:3216 top() | IK48: v12_quick_engine.py:1728 x4
A49: ENTRY_PRIMARY_TF | B49: 4h | E49: =IF(F49="",E48,IF(F49>0,E48+F49,E48)) | F49: =IFERROR(VLOOKUP($A49&"="&$B49,Results_30d_Deltas!$A$2:$H$5000,5,FALSE),"") | G49: =IFERROR(VLOOKUP($A49,Results_30d_Deltas!$A$2:$H$5000,7,FALSE)-E48,"") | H49: =IFERROR(VLOOKUP($A49,Results_30d_Deltas!$A$2:$H$5000,6,FALSE),"") | K49: =IF(B49=C49,"YES","NO") | IJ49: ez_manage.py:3216 top() | IK49: v12_quick_engine.py:1728 x4
A50: ENTRY_PRIMARY_TF | B50: 1h | E50: =IF(F50="",E49,IF(F50>0,E49+F50,E49)) | F50: -1.0393426 | G50: -2.6954965 | H50: =IFERROR(VLOOKUP($A50,Results_30d_Deltas!$A$2:$H$5000,6,FALSE),"") | K50: =IF(B50=C50,"YES","NO") | IJ50: ez_manage.py:3216 top() | IK50: v12_quick_engine.py:1728 x4
A51: ENTRY_PRIMARY_TF | B51: 15m | E51: =IF(F51="",E50,IF(F51>0,E50+F51,E50)) | F51: -1.0393426 | G51: -2.6954965 | H51: =IFERROR(VLOOKUP($A51,Results_30d_Deltas!$A$2:$H$5000,6,FALSE),"") | K51: =IF(B51=C51,"YES","NO") | IJ51: ez_manage.py:3216 top() | IK51: v12_quick_engine.py:1728 x4
A52: ENTRY_SCORE_THRESHOLD | B52: 9.0 | E52: =IF(F52="",E51,IF(F52>0,E51+F52,E51)) | F52: 0 | G52: -1.6561539 | H52: =IFERROR(VLOOKUP($A52,Results_30d_Deltas!$A$2:$H$5000,6,FALSE),"") | K52: =IF(B52=C52,"YES","NO") | IJ52: ez_manage.py:4644 top() | IK52: v12_quick_engine.py:3394 x9
A53: ENTRY_SCORE_THRESHOLD | B53: 13.5 | E53: =IF(F53="",E52,IF(F53>0,E52+F53,E52)) | F53: 0 | G53: -1.6561539 | H53: =IFERROR(VLOOKUP($A53,Results_30d_Deltas!$A$2:$H$5000,6,FALSE),"") | K53: =IF(B53=C53,"YES","NO") | IJ53: ez_manage.py:4644 top() | IK53: v12_quick_engine.py:3394 x9
A54: ENTRY_SCORE_THRESHOLD | B54: 18.0 | E54: =IF(F54="",E53,IF(F54>0,E53+F54,E53)) | F54: 0 | G54: -1.6561539 | H54: =IFERROR(VLOOKUP($A54,Results_30d_Deltas!$A$2:$H$5000,6,FALSE),"") | K54: =IF(B54=C54,"YES","NO") | IJ54: ez_manage.py:4644 top() | IK54: v12_quick_engine.py:3394 x9
A55: ENTRY_SCORE_THRESHOLD | B55: 22.5 | E55: =IF(F55="",E54,IF(F55>0,E54+F55,E54)) | F55: 0 | G55: -1.6561539 | H55: =IFERROR(VLOOKUP($A55,Results_30d_Deltas!$A$2:$H$5000,6,FALSE),"") | K55: =IF(B55=C55,"YES","NO") | IJ55: ez_manage.py:4644 top() | IK55: v12_quick_engine.py:3394 x9
A56: ENTRY_SCORE_THRESHOLD | B56: 27.0 | E56: =IF(F56="",E55,IF(F56>0,E55+F56,E55)) | F56: 0 | G56: -1.6561539 | H56: =IFERROR(VLOOKUP($A56,Results_30d_Deltas!$A$2:$H$5000,6,FALSE),"") | K56: =IF(B56=C56,"YES","NO") | IJ56: ez_manage.py:4644 top() | IK56: v12_quick_engine.py:3394 x9
A57: EXIT_SCORER_DC_EXTREME | B57: 0.2 | E57: =IF(F57="",E56,IF(F57>0,E56+F57,E56)) | F57: 0 | G57: -1.6561539 | H57: =IFERROR(VLOOKUP($A57,Results_30d_Deltas!$A$2:$H$5000,6,FALSE),"") | K57: =IF(B57=C57,"YES","NO") | IJ57: ez_manage.py:3252 top() | IK57: v12_quick_engine.py:1781 x6
A58: EXIT_SCORER_DC_EXTREME | B58: 0.3 | E58: =IF(F58="",E57,IF(F58>0,E57+F58,E57)) | F58: -1.8542583 | G58: -3.5104122 | H58: =IFERROR(VLOOKUP($A58,Results_30d_Deltas!$A$2:$H$5000,6,FALSE),"") | K58: =IF(B58=C58,"YES","NO") | IJ58: ez_manage.py:3252 top() | IK58: v12_quick_engine.py:1781 x6
A59: EXIT_SCORER_DC_EXTREME | B59: 0.4 | E59: =IF(F59="",E58,IF(F59>0,E58+F59,E58)) | F59: 0 | G59: -1.6561539 | H59: =IFERROR(VLOOKUP($A59,Results_30d_Deltas!$A$2:$H$5000,6,FALSE),"") | K59: =IF(B59=C59,"YES","NO") | IJ59: ez_manage.py:3252 top() | IK59: v12_quick_engine.py:1781 x6
A60: EXIT_SCORER_DC_EXTREME | B60: 0.5 | E60: =IF(F60="",E59,IF(F60>0,E59+F60,E59)) | F60: -2.4538266 | G60: -4.1099804 | H60: =IFERROR(VLOOKUP($A60,Results_30d_Deltas!$A$2:$H$5000,6,FALSE),"") | K60: =IF(B60=C60,"YES","NO") | IJ60: ez_manage.py:3252 top() | IK60: v12_quick_engine.py:1781 x6
A61: EXIT_SCORER_DC_EXTREME | B61: 0.6 | E61: =IF(F61="",E60,IF(F61>0,E60+F61,E60)) | F61: 0 | G61: -1.6561539 | H61: =IFERROR(VLOOKUP($A61,Results_30d_Deltas!$A$2:$H$5000,6,FALSE),"") | K61: =IF(B61=C61,"YES","NO") | IJ61: ez_manage.py:3252 top() | IK61: v12_quick_engine.py:1781 x6
... A65: E_1_EXIT_DELTA_THR | B65: 2.0 | E65: =IF(F65="",E64,IF(F65>0,E64+F65,E64)) | F65: 0 | G65: -1.6561539 | H65: =IFERROR(VLOOKUP($A65,Results_30d_Deltas!$A$2:$H$5000,6,FALSE),"") | K65: =IF(B65=C65,"YES","NO") | IJ65: ez_manage.py:4698 top() | IK65: v12_quick_engine.py:1817 x9
A66: HAIKU_ENTRY_GATE_ENABLED | B66: False | E66: =IF(F66="",E65,IF(F66>0,E65+F66,E65)) | F66: =IFERROR(VLOOKUP($A66&"="&$B66,Results_30d_Deltas!$A$2:$H$5000,5,FALSE),"") | G66: =IFERROR(VLOOKUP($A66,Results_30d_Deltas!$A$2:$H$5000,7,FALSE)-E65,"") | H66: =IFERROR(VLOOKUP($A66,Results_30d_Deltas!$A$2:$H$5000,6,FALSE),"") | K66: =IF(B66=C66,"YES","NO") | IJ66: ez_manage.py:6007 top() | IK66: v12_quick_engine.py:4265 x2
A67: HAIKU_ENTRY_GATE_ENABLED | B67: True | E67: =IF(F67="",E66,IF(F67>0,E66+F67,E66)) | F67: -2.471381 | G67: -4.1275348 | H67: =IFERROR(VLOOKUP($A67,Results_30d_Deltas!$A$2:$H$5000,6,FALSE),"") | K67: =IF(B67=C67,"YES","NO") | IJ67: ez_manage.py:6007 top() | IK67: v12_quick_engine.py:4265 x2
A68: HTF_GATE_SIGNALS_SMA200D | B68: False | E68: =IF(F68="",E67,IF(F68>0,E67+F68,E67)) | F68: -1.8526111 | G68: -3.508765 | H68: =IFERROR(VLOOKUP($A68,Results_30d_Deltas!$A$2:$H$5000,6,FALSE),"") | K68: =IF(B68=C68,"YES","NO") | IJ68: ez_manage.py:4881 top() | IK68: v12_quick_engine.py:2057 x7
A69: HTF_GATE_SIGNALS_SMA200D | B69: True | E69: =IF(F69="",E68,IF(F69>0,E68+F69,E68)) | F69: =IFERROR(VLOOKUP($A69&"="&$B69,Results_30d_Deltas!$A$2:$H$5000,5,FALSE),"") | G69: =IFERROR(VLOOKUP($A69,Results_30d_Deltas!$A$2:$H$5000,7,FALSE)-E68,"") | H69: =IFERROR(VLOOKUP($A69,Results_30d_Deltas!$A$2:$H$5000,6,FALSE),"") | K69: =IF(B69=C69,"YES","NO") | IJ69: ez_manage.py:4881 top() | IK69: v12_quick_engine.py:2057 x7
A70: INTRADAY_SESSION_FORCE_EXIT_UTC | B70: 0 | E70: =IF(F70="",E69,IF(F70>0,E69+F70,E69)) | F70: -1.7240473 | G70: -3.3802012 | H70: =IFERROR(VLOOKUP($A70,Results_30d_Deltas!$A$2:$H$5000,6,FALSE),"") | K70: =IF(B70=C70,"YES","NO") | IJ70: ez_manage.py:6014 top() | IK70: v12_quick_engine.py:4267 x4
A71: INTRADAY_SESSION_FORCE_EXIT_UTC | B71: 0.5 | E71: =IF(F71="",E70,IF(F71>0,E70+F71,E70)) | F71: 0 | G71: -1.6561539 | H71: =IFERROR(VLOOKUP($A71,Results_30d_Deltas!$A$2:$H$5000,6,FALSE),"") | K71: =IF(B71=C71,"YES","NO") | IJ71: ez_manage.py:6014 top() | IK71: v12_quick_engine.py:4267 x4
A72: INTRADAY_SESSION_FORCE_EXIT_UTC | B72: 1.0 | E72: =IF(F72="",E71,IF(F72>0,E71+F72,E71)) | F72: 0 | G72: -1.6561539 | H72: =IFERROR(VLOOKUP($A72,Results_30d_Deltas!$A$2:$H$5000,6,FALSE),"") | K72: =IF(B72=C72,"YES","NO") | IJ72: ez_manage.py:6014 top() | IK72: v12_quick_engine.py:4267 x4
A73: INTRADAY_SESSION_FORCE_EXIT_UTC | B73: 2.0 | E73: =IF(F73="",E72,IF(F73>0,E72+F73,E72)) | F73: -2.0610562 | G73: -3.7172101 | H73: =IFERROR(VLOOKUP($A73,Results_30d_Deltas!$A$2:$H$5000,6,FALSE),"") | K73: =IF(B73=C73,"YES","NO") | IJ73: ez_manage.py:6014 top() | IK73: v12_quick_engine.py:4267 x4
A74: MACD_ZERO_CROSS_ENABLED | B74: False | E74: =IF(F74="",E73,IF(F74>0,E73+F74,E73)) | F74: =IFERROR(VLOOKUP($A74&"="&$B74,Results_30d_Deltas!$A$2:$H$5000,5,FALSE),"") | G74: =IFERROR(VLOOKUP($A74,Results_30d_Deltas!$A$2:$H$5000,7,FALSE)-E73,"") | H74: =IFERROR(VLOOKUP($A74,Results_30d_Deltas!$A$2:$H$5000,6,FALSE),"") | K74: =IF(B74=C74,"YES","NO") | IJ74: ez_manage.py:3499 top() | IK74: v12_quick_engine.py:2234 x2
A75: MACD_ZERO_CROSS_ENABLED | B75: True | E75: =IF(F75="",E74,IF(F75>0,E74+F75,E74)) | F75: -1.7073607 | G75: -3.3635146 | H75: =IFERROR(VLOOKUP($A75,Results_30d_Deltas!$A$2:$H$5000,6,FALSE),"") | K75: =IF(B75=C75,"YES","NO") | IJ75: ez_manage.py:3499 top() | IK75: v12_quick_engine.py:2234 x2
A76: MACD_ZERO_CROSS_SCORE | B76: 8 | E76: =IF(F76="",E75,IF(F76>0,E75+F76,E75)) | F76: 0 | G76: -1.6561539 | H76: =IFERROR(VLOOKUP($A76,Results_30d_Deltas!$A$2:$H$5000,6,FALSE),"") | K76: =IF(B76=C76,"YES","NO") | IJ76: ez_manage.py:3500 top() | IK76: v12_quick_engine.py:2235 x2
A77: MACD_ZERO_CROSS_SCORE | B77: 11 | E77: =IF(F77="",E76,IF(F77>0,E76+F77,E76)) | F77: 0 | G77: -1.6561539 | H77: =IFERROR(VLOOKUP($A77,Results_30d_Deltas!$A$2:$H$5000,6,FALSE),"") | K77: =IF(B77=C77,"YES","NO") | IJ77: ez_manage.py:3500 top() | IK77: v12_quick_engine.py:2235 x2
A78: MACD_ZERO_CROSS_SCORE | B78: 15 | E78: =IF(F78="",E77,IF(F78>0,E77+F78,E77)) | F78: 0 | G78: -1.6561539 | H78: =IFERROR(VLOOKUP($A78,Results_30d_Deltas!$A$2:$H$5000,6,FALSE),"") | K78: =IF(B78=C78,"YES","NO") | IJ78: ez_manage.py:3500 top() | IK78: v12_quick_engine.py:2235 x2
A79: MACD_ZERO_CROSS_SCORE | B79: 19 | E79: =IF(F79="",E78,IF(F79>0,E78+F79,E78)) | F79: 0 | G79: -1.6561539 | H79: =IFERROR(VLOOKUP($A79,Results_30d_Deltas!$A$2:$H$5000,6,FALSE),"") | K79: =IF(B79=C79,"YES","NO") | IJ79: ez_manage.py:3500 top() | IK79: v12_quick_engine.py:2235 x2
A80: MACD_ZERO_CROSS_SCORE | B80: 22 | E80: =IF(F80="",E79,IF(F80>0,E79+F80,E79)) | F80: 0 | G80: -1.6561539 | H80: =IFERROR(VLOOKUP($A80,Results_30d_Deltas!$A$2:$H$5000,6,FALSE),"") | K80: =IF(B80=C80,"YES","NO") | IJ80: ez_manage.py:3500 top() | IK80: v12_quick_engine.py:2235 x2
A81: MACD_ZERO_CROSS_TF | B81: OFF | E81: =IF(F81="",E80,IF(F81>0,E80+F81,E80)) | F81: -1.8136634 | G81: -3.4698173 | H81: =IFERROR(VLOOKUP($A81,Results_30d_Deltas!$A$2:$H$5000,6,FALSE),"") | K81: =IF(B81=C81,"YES","NO") | IJ81: ez_manage.py:3501 top() | IK81: v12_quick_engine.py:2236 x2
A82: MACD_ZERO_CROSS_TF | B82: D | E82: =IF(F82="",E81,IF(F82>0,E81+F82,E81)) | F82: 0 | G82: -1.6561539 | H82: =IFERROR(VLOOKUP($A82,Results_30d_Deltas!$A$2:$H$5000,6,FALSE),"") | K82: =IF(B82=C82,"YES","NO") | IJ82: ez_manage.py:3501 top() | IK82: v12_quick_engine.py:2236 x2
A83: MACD_ZERO_CROSS_TF | B83: 4h | E83: =IF(F83="",E82,IF(F83>0,E82+F83,E82)) | F83: 0 | G83: -1.6561539 | H83: =IFERROR(VLOOKUP($A83,Results_30d_Deltas!$A$2:$H$5000,6,FALSE),"") | K83: =IF(B83=C83,"YES","NO") | IJ83: ez_manage.py:3501 top() | IK83: v12_quick_engine.py:2236 x2
A84: MACD_ZERO_CROSS_TF | B84: 1h | E84: =IF(F84="",E83,IF(F84>0,E83+F84,E83)) | F84: -1.8526111 | G84: -3.508765 | H84: =IFERROR(VLOOKUP($A84,Results_30d_Deltas!$A$2:$H$5000,6,FALSE),"") | K84: =IF(B84=C84,"YES","NO") | IJ84: ez_manage.py:3501 top() | IK84: v12_quick_engine.py:2236 x2
A85: MACD_ZERO_CROSS_TF | B85: 15m | E85: =IF(F85="",E84,IF(F85>0,E84+F85,E84)) | F85: =IFERROR(VLOOKUP($A85&"="&$B85,Results_30d_Deltas!$A$2:$H$5000,5,FALSE),"") | G85: =IFERROR(VLOOKUP($A85,Results_30d_Deltas!$A$2:$H$5000,7,FALSE)-E84,"") | H85: =IFERROR(VLOOKUP($A85,Results_30d_Deltas!$A$2:$H$5000,6,FALSE),"") | K85: =IF(B85=C85,"YES","NO") | IJ85: ez_manage.py:3501 top() | IK85: v12_quick_engine.py:2236 x2
A86: MI_MIN_GAIN_EXIT | B86: 0 | E86: =IF(F86="",E85,IF(F86>0,E85+F86,E85)) | F86: 0 | G86: -1.6561539 | H86: =IFERROR(VLOOKUP($A86,Results_30d_Deltas!$A$2:$H$5000,6,FALSE),"") | K86: =IF(B86=C86,"YES","NO") | IJ86: ez_manage.py:3565 top() | IK86: v12_quick_engine.py:2342 x8
A87: MI_MIN_GAIN_EXIT | B87: 0.5 | E87: =IF(F87="",E86,IF(F87>0,E86+F87,E86)) | F87: -2.0245238 | G87: -3.6806777 | H87: =IFERROR(VLOOKUP($A87,Results_30d_Deltas!$A$2:$H$5000,6,FALSE),"") | K87: =IF(B87=C87,"YES","NO") | IJ87: ez_manage.py:3565 top() | IK87: v12_quick_engine.py:2342 x8
A88: MI_MIN_GAIN_EXIT | B88: 1.0 | E88: =IF(F88="",E87,IF(F88>0,E87+F88,E87)) | F88: -1.8787217 | G88: -3.5348756 | H88: =IFERROR(VLOOKUP($A88,Results_30d_Deltas!$A$2:$H$5000,6,FALSE),"") | K88: =IF(B88=C88,"YES","NO") | IJ88: ez_manage.py:3565 top() | IK88: v12_quick_engine.py:2342 x8
A89: MI_MIN_GAIN_EXIT | B89: 2.0 | E89: =IF(F89="",E88,IF(F89>0,E88+F89,E88)) | F89: 0 | G89: -1.6561539 | H89: =IFERROR(VLOOKUP($A89,Results_30d_Deltas!$A$2:$H$5000,6,FALSE),"") | K89: =IF(B89=C89,"YES","NO") | IJ89: ez_manage.py:3565 top() | IK89: v12_quick_engine.py:2342 x8
A90: PARTIAL_EXIT_FRAC | B90: 0 | E90: =IF(F90="",E89,IF(F90>0,E89+F90,E89)) | F90: -2.0245238 | G90: -3.6806777 | H90: =IFERROR(VLOOKUP($A90,Results_30d_Deltas!$A$2:$H$5000,6,FALSE),"") | K90: =IF(B90=C90,"YES","NO") | IJ90: ez_manage.py:6038 top() | IK90: v12_quick_engine.py:4280 x2
A91: PARTIAL_EXIT_FRAC | B91: 0.5 | E91: =IF(F91="",E90,IF(F91>0,E90+F91,E90)) | F91: 0 | G91: -1.6561539 | H91: =IFERROR(VLOOKUP($A91,Results_30d_Deltas!$A$2:$H$5000,6,FALSE),"") | K91: =IF(B91=C91,"YES","NO") | IJ91: ez_manage.py:6038 top() | IK91: v12_quick_engine.py:4280 x2
A92: PARTIAL_EXIT_FRAC | B92: 1.0 | E92: =IF(F92="",E91,IF(F92>0,E91+F92,E91)) | F92: 0 | G92: -1.6561539 | H92: =IFERROR(VLOOKUP($A92,Results_30d_Deltas!$A$2:$H$5000,6,FALSE),"") | K92: =IF(B92=C92,"YES","NO") | IJ92: ez_manage.py:6038 top() | IK92: v12_quick_engine.py:4280 x2
A93: PARTIAL_EXIT_FRAC | B93: 2.0 | E93: =IF(F93="",E92,IF(F93>0,E92+F93,E92)) | F93: -1.8787217 | G93: -3.5348756 | H93: =IFERROR(VLOOKUP($A93,Results_30d_Deltas!$A$2:$H$5000,6,FALSE),"") | K93: =IF(B93=C93,"YES","NO") | IJ93: ez_manage.py:6038 top() | IK93: v12_quick_engine.py:4280 x2
A94: QUICK_REENTRY_60MIN_MIN_PCT | B94: 0 | E94: =IF(F94="",E93,IF(F94>0,E93+F94,E93)) | F94: -1.7073607 | G94: -3.3635146 | H94: =IFERROR(VLOOKUP($A94,Results_30d_Deltas!$A$2:$H$5000,6,FALSE),"") | K94: =IF(B94=C94,"YES","NO") | IJ94: ez_manage.py:6042 top() | IK94: v12_quick_engine.py:4283 x4
A95: QUICK_REENTRY_60MIN_MIN_PCT | B95: 0.5 | E95: =IF(F95="",E94,IF(F95>0,E94+F95,E94)) | F95: 0 | G95: -1.6561539 | H95: =IFERROR(VLOOKUP($A95,Results_30d_Deltas!$A$2:$H$5000,6,FALSE),"") | K95: =IF(B95=C95,"YES","NO") | IJ95: ez_manage.py:6042 top() | IK95: v12_quick_engine.py:4283 x4
A96: QUICK_REENTRY_60MIN_MIN_PCT | B96: 1.0 | E96: =IF(F96="",E95,IF(F96>0,E95+F96,E95)) | F96: 0 | G96: -1.6561539 | H96: =IFERROR(VLOOKUP($A96,Results_30d_Deltas!$A$2:$H$5000,6,FALSE),"") | K96: =IF(B96=C96,"YES","NO") | IJ96: ez_manage.py:6042 top() | IK96: v12_quick_engine.py:4283 x4
A97: QUICK_REENTRY_60MIN_MIN_PCT | B97: 2.0 | E97: =IF(F97="",E96,IF(F97>0,E96+F97,E96)) | F97: -1.0393426 | G97: -2.6954965 | H97: =IFERROR(VLOOKUP($A97,Results_30d_Deltas!$A$2:$H$5000,6,FALSE),"") | K97: =IF(B97=C97,"YES","NO") | IJ97: ez_manage.py:6042 top() | IK97: v12_quick_engine.py:4283 x4
A98: REENTRY2_STOCH_CROSS_ENABLED | B98: False | E98: =IF(F98="",E97,IF(F98>0,E97+F98,E97)) | F98: =IFERROR(VLOOKUP($A98&"="&$B98,Results_30d_Deltas!$A$2:$H$5000,5,FALSE),"") | G98: =IFERROR(VLOOKUP($A98,Results_30d_Deltas!$A$2:$H$5000,7,FALSE)-E97,"") | H98: =IFERROR(VLOOKUP($A98,Results_30d_Deltas!$A$2:$H$5000,6,FALSE),"") | K98: =IF(B98=C98,"YES","NO") | IJ98: ez_manage.py:5285 top() | IK98: v12_quick_engine.py:2842 x10
A99: REENTRY2_STOCH_CROSS_ENABLED | B99: True | E99: =IF(F99="",E98,IF(F99>0,E98+F99,E98)) | F99: 0 | G99: -1.6561539 | H99: =IFERROR(VLOOKUP($A99,Results_30d_Deltas!$A$2:$H$5000,6,FALSE),"") | K99: =IF(B99=C99,"YES","NO") | IJ99: ez_manage.py:5285 top() | IK99: v12_quick_engine.py:2842 x10
A100: REENTRY_K15M_PARTIAL_MULT | B100: 0.125 | E100: =IF(F100="",E99,IF(F100>0,E99+F100,E99)) | F100: -1.8787217 | G100: -3.5348756 | H100: =IFERROR(VLOOKUP($A100,Results_30d_Deltas!$A$2:$H$5000,6,FALSE),"") | K100: =IF(B100=C100,"YES","NO") | IJ100: ez_manage.py:3860 top() | IK100: v12_quick_engine.py:2884 x8
A101: REENTRY_K15M_PARTIAL_MULT | B101: 0.1875 | E101: =IF(F101="",E100,IF(F101>0,E100+F101,E100)) | F101: 0 | G101: -1.6561539 | H101: =IFERROR(VLOOKUP($A101,Results_30d_Deltas!$A$2:$H$5000,6,FALSE),"") | K101: =IF(B101=C101,"YES","NO") | IJ101: ez_manage.py:3860 top() | IK101: v12_quick_engine.py:2884 x8
A102: REENTRY_K15M_PARTIAL_MULT | B102: 0.25 | E102: =IF(F102="",E101,IF(F102>0,E101+F102,E101)) | F102: 0 | G102: -1.6561539 | H102: =IFERROR(VLOOKUP($A102,Results_30d_Deltas!$A$2:$H$5000,6,FALSE),"") | K102: =IF(B102=C102,"YES","NO") | IJ102: ez_manage.py:3860 top() | IK102: v12_quick_engine.py:2884 x8
A103: REENTRY_K15M_PARTIAL_MULT | B103: 0.3125 | E103: =IF(F103="",E102,IF(F103>0,E102+F103,E102)) | F103: 0 | G103: -1.6561539 | H103: =IFERROR(VLOOKUP($A103,Results_30d_Deltas!$A$2:$H$5000,6,FALSE),"") | K103: =IF(B103=C103,"YES","NO") | IJ103: ez_manage.py:3860 top() | IK103: v12_quick_engine.py:2884 x8
A104: REENTRY_K15M_PARTIAL_MULT | B104: 0.375 | E104: =IF(F104="",E103,IF(F104>0,E103+F104,E103)) | F104: -0.15388231 | G104: -1.8100362 | H104: =IFERROR(VLOOKUP($A104,Results_30d_Deltas!$A$2:$H$5000,6,FALSE),"") | K104: =IF(B104=C104,"YES","NO") | IJ104: ez_manage.py:3860 top() | IK104: v12_quick_engine.py:2884 x8
A105: REENTRY_RALLY_K15M_MAX | B105: 50.0 | E105: =IF(F105="",E104,IF(F105>0,E104+F105,E104)) | F105: -2.0610562 | G105: -3.7172101 | H105: =IFERROR(VLOOKUP($A105,Results_30d_Deltas!$A$2:$H$5000,6,FALSE),"") | K105: =IF(B105=C105,"YES","NO") | IJ105: ez_manage.py:3869 top() | IK105: v12_quick_engine.py:2902 x8
A106: REENTRY_RALLY_K15M_MAX | B106: 75.0 | E106: =IF(F106="",E105,IF(F106>0,E105+F106,E105)) | F106: 0 | G106: -1.6561539 | H106: =IFERROR(VLOOKUP($A106,Results_30d_Deltas!$A$2:$H$5000,6,FALSE),"") | K106: =IF(B106=C106,"YES","NO") | IJ106: ez_manage.py:3869 top() | IK106: v12_quick_engine.py:2902 x8
A107: REENTRY_RALLY_K15M_MAX | B107: 100.0 | E107: =IF(F107="",E106,IF(F107>0,E106+F107,E106)) | F107: -2.0610562 | G107: -3.7172101 | H107: =IFERROR(VLOOKUP($A107,Results_30d_Deltas!$A$2:$H$5000,6,FALSE),"") | K107: =IF(B107=C107,"YES","NO") | IJ107: ez_manage.py:3869 top() | IK107: v12_quick_engine.py:2902 x8
A108: REENTRY_RALLY_K15M_MAX | B108: 125.0 | E108: =IF(F108="",E107,IF(F108>0,E107+F108,E107)) | F108: 0 | G108: -1.6561539 | H108: =IFERROR(VLOOKUP($A108,Results_30d_Deltas!$A$2:$H$5000,6,FALSE),"") | K108: =IF(B108=C108,"YES","NO") | IJ108: ez_manage.py:3869 top() | IK108: v12_quick_engine.py:2902 x8
A109: REENTRY_RALLY_K15M_MAX | B109: 150.0 | E109: =IF(F109="",E108,IF(F109>0,E108+F109,E108)) | F109: 0 | G109: -1.6561539 | H109: =IFERROR(VLOOKUP($A109,Results_30d_Deltas!$A$2:$H$5000,6,FALSE),"") | K109: =IF(B109=C109,"YES","NO") | IJ109: ez_manage.py:3869 top() | IK109: v12_quick_engine.py:2902 x8
A110: REGIME_TRENDING_EXIT_GAIN_MIN | B110: 1.0 | E110: =IF(F110="",E109,IF(F110>0,E109+F110,E109)) | F110: 0 | G110: -1.6561539 | H110: =IFERROR(VLOOKUP($A110,Results_30d_Deltas!$A$2:$H$5000,6,FALSE),"") | K110: =IF(B110=C110,"YES","NO") | IJ110: ez_manage.py:5359 top() | IK110: v12_quick_engine.py:2951 x5
... A114: REGIME_TRENDING_EXIT_GAIN_MIN | B114: 3.0 | E114: =IF(F114="",E113,IF(F114>0,E113+F114,E113)) | F114: 0 | G114: -1.6561539 | H114: =IFERROR(VLOOKUP($A114,Results_30d_Deltas!$A$2:$H$5000,6,FALSE),"") | K114: =IF(B114=C114,"YES","NO") | IJ114: ez_manage.py:5359 top() | IK114: v12_quick_engine.py:2951 x5
A115: REVERSE_ON_EXIT_ENABLED | B115: False | E115: =IF(F115="",E114,IF(F115>0,E114+F115,E114)) | F115: =IFERROR(VLOOKUP($A115&"="&$B115,Results_30d_Deltas!$A$2:$H$5000,5,FALSE),"") | G115: =IFERROR(VLOOKUP($A115,Results_30d_Deltas!$A$2:$H$5000,7,FALSE)-E114,"") | H115: =IFERROR(VLOOKUP($A115,Results_30d_Deltas!$A$2:$H$5000,6,FALSE),"") | K115: =IF(B115=C115,"YES","NO") | IJ115: ez_manage.py:1219 top() | IK115: v12_quick_engine.py:1420 x3
A116: REVERSE_ON_EXIT_ENABLED | B116: True | E116: =IF(F116="",E115,IF(F116>0,E115+F116,E115)) | F116: -1.7345709 | G116: -3.3907247 | H116: =IFERROR(VLOOKUP($A116,Results_30d_Deltas!$A$2:$H$5000,6,FALSE),"") | K116: =IF(B116=C116,"YES","NO") | IJ116: ez_manage.py:1219 top() | IK116: v12_quick_engine.py:1420 x3
A117: RZ_BOT_BB_THRESHOLD | B117: 0.075 | E117: =IF(F117="",E116,IF(F117>0,E116+F117,E116)) | F117: -1.8526111 | G117: -3.508765 | H117: =IFERROR(VLOOKUP($A117,Results_30d_Deltas!$A$2:$H$5000,6,FALSE),"") | K117: =IF(B117=C117,"YES","NO") | IJ117: ez_manage.py:3928 top() | IK117: v12_quick_engine.py:3020 x6
A118: RZ_BOT_BB_THRESHOLD | B118: 0.1125 | E118: =IF(F118="",E117,IF(F118>0,E117+F118,E117)) | F118: 0 | G118: -1.6561539 | H118: =IFERROR(VLOOKUP($A118,Results_30d_Deltas!$A$2:$H$5000,6,FALSE),"") | K118: =IF(B118=C118,"YES","NO") | IJ118: ez_manage.py:3928 top() | IK118: v12_quick_engine.py:3020 x6
A119: RZ_BOT_BB_THRESHOLD | B119: 0.15 | E119: =IF(F119="",E118,IF(F119>0,E118+F119,E118)) | F119: -2.0610562 | G119: -3.7172101 | H119: =IFERROR(VLOOKUP($A119,Results_30d_Deltas!$A$2:$H$5000,6,FALSE),"") | K119: =IF(B119=C119,"YES","NO") | IJ119: ez_manage.py:3928 top() | IK119: v12_quick_engine.py:3020 x6
...

Sheet ENTRY_CONFIRMATION_GATES
A1: 03 ENTRY_CONFIRMATION_GATES - 4 bases -> 11 rows - 231 per-row FULLY CONNECTED
A2: Switch | B2: default | C2: override | D2: Family | E2: BASELINE | F2: VECTOR_DELTA | G2: LIVE_DELTA | H2: LIVE_SHARPE | I2: REAL_COMPLETE | J2: PER_ROW_FILTERS | K2: is_default (backup if bold lost) | L2: ATR_TRAIL_FILTER_TF=OFF | M2: ATR_TRAIL_FILTER_TF=D | N2: ATR_TRAIL_FILTER_TF=4h | O2: ATR_TRAIL_FILTER_TF=1h | P2: ATR_TRAIL_FILTER_TF=15m | Q2: BAR_PATTERNS_FILTER_TF=OFF | R2: BAR_PATTERNS_FILTER_TF=D | S2: BAR_PATTERNS_FILTER_TF=4h | T2: BAR_PATTERNS_FILTER_TF=1h | U2: BAR_PATTERNS_FILTER_TF=15m | V2: BB_PULLBACK_GATE_FILTER_TF=OFF | W2: BB_PULLBACK_GATE_FILTER_TF=D | X2: BB_PULLBACK_GATE_FILTER_TF=4h | Y2: BB_PULLBACK_GATE_FILTER_TF=1h | Z2: BB_PULLBACK_GATE_FILTER_TF=15m | AA2: BB_RECOVERY_ENTRY_FILTER_TF=OFF | AB2: BB_RECOVERY_ENTRY_FILTER_TF=D | AC2: BB_RECOVERY_ENTRY_FILTER_TF=4h | AD2: BB_RECOVERY_ENTRY_FILTER_TF=1h | AE2: BB_RECOVERY_ENTRY_FILTER_TF=15m | AF2: BB_RECOVERY_FILTER_TF=OFF | AG2: BB_RECOVERY_FILTER_TF=D | AH2: BB_RECOVERY_FILTER_TF=4h | AI2: BB_RECOVERY_FILTER_TF=1h | AJ2: BB_RECOVERY_FILTER_TF=15m | AK2: BREAKEVEN_GAIN_EROSION_FILTER_TF=OFF | AL2: BREAKEVEN_GAIN_EROSION_FILTER_TF=D | AM2: BREAKEVEN_GAIN_EROSION_FILTER_TF=4h | AN2: BREAKEVEN_GAIN_EROSION_FILTER_TF=1h | AO2: BREAKEVEN_GAIN_EROSION_FILTER_TF=15m | AP2: BREAKOUT_RETEST_FILTER_TF=OFF | AQ2: BREAKOUT_RETEST_FILTER_TF=D | AR2: BREAKOUT_RETEST_FILTER_TF=4h | AS2: BREAKOUT_RETEST_FILTER_TF=1h | AT2: BREAKOUT_RETEST_FILTER_TF=15m | AU2: BT_WT_CROSS_LADDER_FILTER_TF=OFF | AV2: BT_WT_CROSS_LADDER_FILTER_TF=D | AW2: BT_WT_CROSS_LADDER_FILTER_TF=4h | AX2: BT_WT_CROSS_LADDER_FILTER_TF=1h | AY2: BT_WT_CROSS_LADDER_FILTER_TF=15m | AZ2: CANDLE_PATTERN_STOPS_FILTER_TF=OFF | BA2: CANDLE_PATTERN_STOPS_FILTER_TF=D | BB2: CANDLE_PATTERN_STOPS_FILTER_TF=4h | BC2: CANDLE_PATTERN_STOPS_FILTER_TF=1h | BD2: CANDLE_PATTERN_STOPS_FILTER_TF=15m | BE2: CIRCUIT_SHARPE_GATES_FILTER_TF=OFF | BF2: CIRCUIT_SHARPE_GATES_FILTER_TF=D | BG2: CIRCUIT_SHARPE_GATES_FILTER_TF=4h | BH2: CIRCUIT_SHARPE_GATES_FILTER_TF=1h | BI2: CIRCUIT_SHARPE_GATES_FILTER_TF=15m | BJ2: DC_BREACH_REDUCE_FILTER_TF=OFF | BK2: DC_BREACH_REDUCE_FILTER_TF=D | BL2: DC_BREACH_REDUCE_FILTER_TF=4h | BM2: DC_BREACH_REDUCE_FILTER_TF=1h | BN2: DC_BREACH_REDUCE_FILTER_TF=15m | BO2: DC_BREAK_FILTER_TF=OFF | BP2: DC_BREAK_FILTER_TF=D | BQ2: DC_BREAK_FILTER_TF=4h | BR2: DC_BREAK_FILTER_TF=1h | BS2: DC_BREAK_FILTER_TF=15m | BT2: DC_MOMENTUM_BOTA_SCORER_FILTER_TF=OFF | BU2: DC_MOMENTUM_BOTA_SCORER_FILTER_TF=D | BV2: DC_MOMENTUM_BOTA_SCORER_FILTER_TF=4h | BW2: DC_MOMENTUM_BOTA_SCORER_FILTER_TF=1h | BX2: DC_MOMENTUM_BOTA_SCORER_FILTER_TF=15m | BY2: DELTA_ENGINE_FILTER_TF=OFF | BZ2: DELTA_ENGINE_FILTER_TF=D | CA2: DELTA_ENGINE_FILTER_TF=4h | CB2: DELTA_ENGINE_FILTER_TF=1h | CC2: DELTA_ENGINE_FILTER_TF=15m | CD2: EMA_9_21_FILTER_FILTER_TF=OFF | CE2: EMA_9_21_FILTER_FILTER_TF=D | CF2: EMA_9_21_FILTER_FILTER_TF=4h | CG2: EMA_9_21_FILTER_FILTER_TF=1h | CH2: EMA_9_21_FILTER_FILTER_TF=15m | CI2: EMA_BLANKET_FILTER_FILTER_TF=OFF | CJ2: EMA_BLANKET_FILTER_FILTER_TF=D | CK2: EMA_BLANKET_FILTER_FILTER_TF=4h | CL2: EMA_BLANKET_FILTER_FILTER_TF=1h | CM2: EMA_BLANKET_FILTER_FILTER_TF=15m | CN2: EMERGENCY_BRAKE_FILTER_TF=OFF | CO2: EMERGENCY_BRAKE_FILTER_TF=D | CP2: EMERGENCY_BRAKE_FILTER_TF=4h | CQ2: EMERGENCY_BRAKE_FILTER_TF=1h | CR2: EMERGENCY_BRAKE_FILTER_TF=15m | CS2: EXIT_R1_R2_FILTER_TF=OFF | CT2: EXIT_R1_R2_FILTER_TF=D | CU2: EXIT_R1_R2_FILTER_TF=4h | CV2: EXIT_R1_R2_FILTER_TF=1h | CW2: EXIT_R1_R2_FILTER_TF=15m | CX2: EXIT_TIGHT_BREAKOUT_SCORER_FILTER_TF=OFF | CY2: EXIT_TIGHT_BREAKOUT_SCORER_FILTER_TF=D | CZ2: EXIT_TIGHT_BREAKOUT_SCORER_FILTER_TF=4h | DA2: EXIT_TIGHT_BREAKOUT_SCORER_FILTER_TF=1h | DB2: EXIT_TIGHT_BREAKOUT_SCORER_FILTER_TF=15m | DC2: EXIT_TOP_FADE_FILTER_TF=OFF | DD2: EXIT_TOP_FADE_FILTER_TF=D | DE2: EXIT_TOP_FADE_FILTER_TF=4h | DF2: EXIT_TOP_FADE_FILTER_TF=1h | DG2: EXIT_TOP_FADE_FILTER_TF=15m | DH2: EXIT_TO_REDUCE_ADAPTER_FILTER_TF=OFF | DI2: EXIT_TO_REDUCE_ADAPTER_FILTER_TF=D | DJ2: EXIT_TO_REDUCE_ADAPTER_FILTER_TF=4h | DK2: EXIT_TO_REDUCE_ADAPTER_FILTER_TF=1h | DL2: EXIT_TO_REDUCE_ADAPTER_FILTER_TF=15m | DM2: FAST_RISER_FILTER_TF=OFF | DN2: FAST_RISER_FILTER_TF=D | DO2: FAST_RISER_FILTER_TF=4h | DP2: FAST_RISER_FILTER_TF=1h | DQ2: FAST_RISER_FILTER_TF=15m | DR2: FH_MOMENTUM_FILTER_TF=OFF | DS2: FH_MOMENTUM_FILTER_TF=D | DT2: FH_MOMENTUM_FILTER_TF=4h | DU2: FH_MOMENTUM_FILTER_TF=1h | DV2: FH_MOMENTUM_FILTER_TF=15m | DW2: FIRST_OPEN_THROTTLE_FILTER_TF=OFF | DX2: FIRST_OPEN_THROTTLE_FILTER_TF=D | DY2: FIRST_OPEN_THROTTLE_FILTER_TF=4h | DZ2: FIRST_OPEN_THROTTLE_FILTER_TF=1h | EA2: FIRST_OPEN_THROTTLE_FILTER_TF=15m | EB2: FROZEN_STOP_FILTER_TF=OFF | EC2: FROZEN_STOP_FILTER_TF=D | ED2: FROZEN_STOP_FILTER_TF=4h | EE2: FROZEN_STOP_FILTER_TF=1h | EF2: FROZEN_STOP_FILTER_TF=15m | EG2: GOLDEN_RULE_ENFORCE_FILTER_TF=OFF | EH2: GOLDEN_RULE_ENFORCE_FILTER_TF=D | EI2: GOLDEN_RULE_ENFORCE_FILTER_TF=4h | EJ2: GOLDEN_RULE_ENFORCE_FILTER_TF=1h | EK2: GOLDEN_RULE_ENFORCE_FILTER_TF=15m | EL2: GOLDEN_RULE_HTF_VOTE_FILTER_TF=OFF | EM2: GOLDEN_RULE_HTF_VOTE_FILTER_TF=D | EN2: GOLDEN_RULE_HTF_VOTE_FILTER_TF=4h | EO2: GOLDEN_RULE_HTF_VOTE_FILTER_TF=1h | EP2: GOLDEN_RULE_HTF_VOTE_FILTER_TF=15m | EQ2: GR_FILTER_VEC_FILTER_TF=OFF | ER2: GR_FILTER_VEC_FILTER_TF=D | ES2: GR_FILTER_VEC_FILTER_TF=4h | ET2: GR_FILTER_VEC_FILTER_TF=1h | EU2: GR_FILTER_VEC_FILTER_TF=15m | EV2: GR_V5_STATE_FILTER_TF=OFF | EW2: GR_V5_STATE_FILTER_TF=D | EX2: GR_V5_STATE_FILTER_TF=4h | EY2: GR_V5_STATE_FILTER_TF=1h | EZ2: GR_V5_STATE_FILTER_TF=15m | FA2: HAIKU_WINNER_FILTER_TF=OFF | FB2: HAIKU_WINNER_FILTER_TF=D | FC2: HAIKU_WINNER_FILTER_TF=4h | FD2: HAIKU_WINNER_FILTER_TF=1h | FE2: HAIKU_WINNER_FILTER_TF=15m | FF2: LH_HL_FILTER_TF_REQ=2 | FG2: LH_HL_FILTER_TF_REQ=2_ALT | FH2: LIVE_ENTRY_ENGINE_FILTER_TF=OFF | FI2: LIVE_ENTRY_ENGINE_FILTER_TF=D | FJ2: LIVE_ENTRY_ENGINE_FILTER_TF=4h | FK2: LIVE_ENTRY_ENGINE_FILTER_TF=1h | FL2: LIVE_ENTRY_ENGINE_FILTER_TF=15m | FM2: LIVE_ONLY_SIGNALS_BATCH5_FILTER_TF=OFF | FN2: LIVE_ONLY_SIGNALS_BATCH5_FILTER_TF=D | FO2: LIVE_ONLY_SIGNALS_BATCH5_FILTER_TF=4h | FP2: LIVE_ONLY_SIGNALS_BATCH5_FILTER_TF=1h | FQ2: LIVE_ONLY_SIGNALS_BATCH5_FILTER_TF=15m | FR2: MANDATORY_REENTRY_WT_FILTER_TF_MODE=15m_only | FS2: MANDATORY_REENTRY_WT_FILTER_TF_MODE=15m_only_ALT | FT2: MOM3_FILTER_TF=OFF | FU2: MOM3_FILTER_TF=D | FV2: MOM3_FILTER_TF=4h | FW2: MOM3_FILTER_TF=1h | FX2: MOM3_FILTER_TF=15m | FY2: MOMENTUM_BREAKOUT_FILTER_TF=OFF | FZ2: MOMENTUM_BREAKOUT_FILTER_TF=D | GA2: MOMENTUM_BREAKOUT_FILTER_TF=4h | GB2: MOMENTUM_BREAKOUT_FILTER_TF=1h | GC2: MOMENTUM_BREAKOUT_FILTER_TF=15m | GD2: MTF_ARMED_ENTRIES_FILTER_TF=OFF | GE2: MTF_ARMED_ENTRIES_FILTER_TF=D | GF2: MTF_ARMED_ENTRIES_FILTER_TF=4h | GG2: MTF_ARMED_ENTRIES_FILTER_TF=1h | GH2: MTF_ARMED_ENTRIES_FILTER_TF=15m | GI2: MTF_ATR_TRAIL_FILTER_TF=OFF | GJ2: MTF_ATR_TRAIL_FILTER_TF=D | GK2: MTF_ATR_TRAIL_FILTER_TF=4h | GL2: MTF_ATR_TRAIL_FILTER_TF=1h | GM2: MTF_ATR_TRAIL_FILTER_TF=15m | GN2: MTF_DC_REJECT_FILTER_TF=OFF | GO2: MTF_DC_REJECT_FILTER_TF=D | GP2: MTF_DC_REJECT_FILTER_TF=4h | GQ2: MTF_DC_REJECT_FILTER_TF=1h | GR2: MTF_DC_REJECT_FILTER_TF=15m | GS2: NEWBORN_LOSS_KILL_FILTER_TF=OFF | GT2: NEWBORN_LOSS_KILL_FILTER_TF=D | GU2: NEWBORN_LOSS_KILL_FILTER_TF=4h | GV2: NEWBORN_LOSS_KILL_FILTER_TF=1h | GW2: NEWBORN_LOSS_KILL_FILTER_TF=15m | GX2: NEWBORN_PROTECT_FILTER_TF=OFF | GY2: NEWBORN_PROTECT_FILTER_TF=D | GZ2: NEWBORN_PROTECT_FILTER_TF=4h | HA2: NEWBORN_PROTECT_FILTER_TF=1h | HB2: NEWBORN_PROTECT_FILTER_TF=15m | HC2: NOLOSS_BYPASS_WT5OF5_FILTER_TF=OFF | HD2: NOLOSS_BYPASS_WT5OF5_FILTER_TF=D | HE2: NOLOSS_BYPASS_WT5OF5_FILTER_TF=4h | HF2: NOLOSS_BYPASS_WT5OF5_FILTER_TF=1h | HG2: NOLOSS_BYPASS_WT5OF5_FILTER_TF=15m | HH2: OPEN_INTENT_SIZE_GATES_FILTER_TF=OFF | HI2: OPEN_INTENT_SIZE_GATES_FILTER_TF=D | HJ2: OPEN_INTENT_SIZE_GATES_FILTER_TF=4h | HK2: OPEN_INTENT_SIZE_GATES_FILTER_TF=1h | HL2: OPEN_INTENT_SIZE_GATES_FILTER_TF=15m | HM2: PARTIAL_PROFIT_LOCK_V2_FILTER_TF=OFF | HN2: PARTIAL_PROFIT_LOCK_V2_FILTER_TF=D | HO2: PARTIAL_PROFIT_LOCK_V2_FILTER_TF=4h | HP2: PARTIAL_PROFIT_LOCK_V2_FILTER_TF=1h | HQ2: PARTIAL_PROFIT_LOCK_V2_FILTER_TF=15m | HR2: PEAK_GIVEBACK_BE_EROSION_FILTER_TF=OFF | HS2: PEAK_GIVEBACK_BE_EROSION_FILTER_TF=D | HT2: PEAK_GIVEBACK_BE_EROSION_FILTER_TF=4h | HU2: PEAK_GIVEBACK_BE_EROSION_FILTER_TF=1h | HV2: PEAK_GIVEBACK_BE_EROSION_FILTER_TF=15m | HW2: WT_15M_BOUNCE_BB_MAX=0.95 | HX2: WT_15M_BOUNCE_BB_MAX=0.9 | HY2: WT_15M_BOUNCE_BB_MAX=0.8 | HZ2: WT_15M_BOUNCE_BB_MIN=0.05 | IA2: WT_15M_BOUNCE_BB_MIN=0.1 | IB2: WT_15M_BOUNCE_BB_MIN=0.2 | IC2: WT_15M_BOUNCE_HIGH_1H_GT_PREV=True | ID2: WT_15M_BOUNCE_HIGH_1H_GT_PREV=False | IE2: WT_15M_BOUNCE_LOW_1H_GT_PREV=True | IF2: WT_15M_BOUNCE_LOW_1H_GT_PREV=False | IG2: WT_15M_BOUNCE_REL_VOL_GT_1=True | IH2: WT_15M_BOUNCE_REL_VOL_GT_1=False | II2: Live Location | IJ2: Vec Hook | IK2: Type | IL2: Correct Options
A3: GR_FILTER_ALL_ENTRIES | B3: 0.0 | E3: =MAX('ENTRY_BREAKOUT_CHANNEL'!E:E) | F3: -1.8934256 | G3: -3.5495795 | H3: =IFERROR(VLOOKUP($A3,Results_30d_Deltas!$A$2:$H$5000,6,FALSE),"") | K3: =IF(B3=C3,"YES","NO") | IJ3: ez_manage.py:4768 top() | IK3: v12_quick_engine.py:1912 x3
A4: GR_FILTER_ALL_ENTRIES | B4: 0.0_ALT | C4: GR_FILTER_ALL_ENTRIES=0.0_ALT + EXIT_TO_REDUCE_ADAPTER_FILTER_TF=4h + BB_WT_TF=15m + GR=18 + BB_RECOVERY_FILTER_TF=OFF + DC_BREAK_FILTER_TF=1h | E4: =IF(F4="",E3,IF(F4>0,E3+F4,E3)) | F4: -1.8934256 | G4: -3.5495795 | H4: =IFERROR(VLOOKUP($A4,Results_30d_Deltas!$A$2:$H$5000,6,FALSE),"") | K4: =IF(B4=C4,"YES","NO") | IJ4: ez_manage.py:4768 top() | IK4: v12_quick_engine.py:1912 x3
A5: GR_FILTER_VEC_ENABLED | B5: False | E5: =IF(F5="",E4,IF(F5>0,E4+F5,E4)) | F5: =IFERROR(VLOOKUP($A5&"="&$B5,Results_30d_Deltas!$A$2:$H$5000,5,FALSE),"") | G5: =IFERROR(VLOOKUP($A5,Results_30d_Deltas!$A$2:$H$5000,7,FALSE)-E4,"") | H5: =IFERROR(VLOOKUP($A5,Results_30d_Deltas!$A$2:$H$5000,6,FALSE),"") | K5: =IF(B5=C5,"YES","NO") | IJ5: ez_manage.py:6003 top() | IK5: v12_quick_engine.py:4261 x2
A6: GR_FILTER_VEC_ENABLED | B6: True | E6: =IF(F6="",E5,IF(F6>0,E5+F6,E5)) | F6: -1.8526111 | G6: -3.508765 | H6: =IFERROR(VLOOKUP($A6,Results_30d_Deltas!$A$2:$H$5000,6,FALSE),"") | K6: =IF(B6=C6,"YES","NO") | IJ6: ez_manage.py:6003 top() | IK6: v12_quick_engine.py:4261 x2
A7: GR_FILTER_VEC_FILTER_TF | B7: OFF | E7: =IF(F7="",E6,IF(F7>0,E6+F7,E6)) | F7: -2.0610562 | G7: -3.7172101 | H7: =IFERROR(VLOOKUP($A7,Results_30d_Deltas!$A$2:$H$5000,6,FALSE),"") | K7: =IF(B7=C7,"YES","NO") | IJ7: ez_manage.py:6004 top() | IK7: v12_quick_engine.py:112 x3
A8: GR_FILTER_VEC_FILTER_TF | B8: D | E8: =IF(F8="",E7,IF(F8>0,E7+F8,E7)) | F8: -1.8136634 | G8: -3.4698173 | H8: =IFERROR(VLOOKUP($A8,Results_30d_Deltas!$A$2:$H$5000,6,FALSE),"") | K8: =IF(B8=C8,"YES","NO") | IJ8: ez_manage.py:6004 top() | IK8: v12_quick_engine.py:112 x3
A9: GR_FILTER_VEC_FILTER_TF | B9: 4h | E9: =IF(F9="",E8,IF(F9>0,E8+F9,E8)) | F9: -1.8526111 | G9: -3.508765 | H9: =IFERROR(VLOOKUP($A9,Results_30d_Deltas!$A$2:$H$5000,6,FALSE),"") | K9: =IF(B9=C9,"YES","NO") | IJ9: ez_manage.py:6004 top() | IK9: v12_quick_engine.py:112 x3
A10: GR_FILTER_VEC_FILTER_TF | B10: 1h | E10: =IF(F10="",E9,IF(F10>0,E9+F10,E9)) | F10: -2.0245238 | G10: -3.6806777 | H10: =IFERROR(VLOOKUP($A10,Results_30d_Deltas!$A$2:$H$5000,6,FALSE),"") | K10: =IF(B10=C10,"YES","NO") | IJ10: ez_manage.py:6004 top() | IK10: v12_quick_engine.py:112 x3
A11: GR_FILTER_VEC_FILTER_TF | B11: 15m | E11: =IF(F11="",E10,IF(F11>0,E10+F11,E10)) | F11: =IFERROR(VLOOKUP($A11&"="&$B11,Results_30d_Deltas!$A$2:$H$5000,5,FALSE),"") | G11: =IFERROR(VLOOKUP($A11,Results_30d_Deltas!$A$2:$H$5000,7,FALSE)-E10,"") | H11: =IFERROR(VLOOKUP($A11,Results_30d_Deltas!$A$2:$H$5000,6,FALSE),"") | K11: =IF(B11=C11,"YES","NO") | IJ11: ez_manage.py:6004 top() | IK11: v12_quick_engine.py:112 x3
A12: WT_AGAINST_FILTER_ENABLED | B12: False | E12: =IF(F12="",E11,IF(F12>0,E11+F12,E11)) | F12: =IFERROR(VLOOKUP($A12&"="&$B12,Results_30d_Deltas!$A$2:$H$5000,5,FALSE),"") | G12: =IFERROR(VLOOKUP($A12,Results_30d_Deltas!$A$2:$H$5000,7,FALSE)-E11,"") | H12: =IFERROR(VLOOKUP($A12,Results_30d_Deltas!$A$2:$H$5000,6,FALSE),"") | K12: =IF(B12=C12,"YES","NO") | IJ12: ez_manage.py:6084 top() | IK12: v12_quick_engine.py:4291 x2
A13: WT_AGAINST_FILTER_ENABLED | B13: True | E13: =IF(F13="",E12,IF(F13>0,E12+F13,E12)) | F13: 0 | G13: -1.6561539 | H13: =IFERROR(VLOOKUP($A13,Results_30d_Deltas!$A$2:$H$5000,6,FALSE),"") | K13: =IF(B13=C13,"YES","NO") | IJ13: ez_manage.py:6084 top() | IK13: v12_quick_engine.py:4291 x2

Sheet EXIT_STRUCTURAL
A1: 04 EXIT_STRUCTURAL - 2 bases -> 6 rows - 231 per-row FULLY CONNECTED
A2: Switch | B2: default | C2: override | D2: Family | E2: BASELINE | F2: VECTOR_DELTA | G2: LIVE_DELTA | H2: LIVE_SHARPE | I2: REAL_COMPLETE | J2: PER_ROW_FILTERS | K2: is_default (backup if bold lost) | L2: ATR_TRAIL_FILTER_TF=OFF | M2: ATR_TRAIL_FILTER_TF=D | N2: ATR_TRAIL_FILTER_TF=4h | O2: ATR_TRAIL_FILTER_TF=1h | P2: ATR_TRAIL_FILTER_TF=15m | Q2: BAR_PATTERNS_FILTER_TF=OFF | R2: BAR_PATTERNS_FILTER_TF=D | S2: BAR_PATTERNS_FILTER_TF=4h | T2: BAR_PATTERNS_FILTER_TF=1h | U2: BAR_PATTERNS_FILTER_TF=15m | V2: BB_PULLBACK_GATE_FILTER_TF=OFF | W2: BB_PULLBACK_GATE_FILTER_TF=D | X2: BB_PULLBACK_GATE_FILTER_TF=4h | Y2: BB_PULLBACK_GATE_FILTER_TF=1h | Z2: BB_PULLBACK_GATE_FILTER_TF=15m | AA2: BB_RECOVERY_ENTRY_FILTER_TF=OFF | AB2: BB_RECOVERY_ENTRY_FILTER_TF=D | AC2: BB_RECOVERY_ENTRY_FILTER_TF=4h | AD2: BB_RECOVERY_ENTRY_FILTER_TF=1h | AE2: BB_RECOVERY_ENTRY_FILTER_TF=15m | AF2: BB_RECOVERY_FILTER_TF=OFF | AG2: BB_RECOVERY_FILTER_TF=D | AH2: BB_RECOVERY_FILTER_TF=4h | AI2: BB_RECOVERY_FILTER_TF=1h | AJ2: BB_RECOVERY_FILTER_TF=15m | AK2: BREAKEVEN_GAIN_EROSION_FILTER_TF=OFF | AL2: BREAKEVEN_GAIN_EROSION_FILTER_TF=D | AM2: BREAKEVEN_GAIN_EROSION_FILTER_TF=4h | AN2: BREAKEVEN_GAIN_EROSION_FILTER_TF=1h | AO2: BREAKEVEN_GAIN_EROSION_FILTER_TF=15m | AP2: BREAKOUT_RETEST_FILTER_TF=OFF | AQ2: BREAKOUT_RETEST_FILTER_TF=D | AR2: BREAKOUT_RETEST_FILTER_TF=4h | AS2: BREAKOUT_RETEST_FILTER_TF=1h | AT2: BREAKOUT_RETEST_FILTER_TF=15m | AU2: BT_WT_CROSS_LADDER_FILTER_TF=OFF | AV2: BT_WT_CROSS_LADDER_FILTER_TF=D | AW2: BT_WT_CROSS_LADDER_FILTER_TF=4h | AX2: BT_WT_CROSS_LADDER_FILTER_TF=1h | AY2: BT_WT_CROSS_LADDER_FILTER_TF=15m | AZ2: CANDLE_PATTERN_STOPS_FILTER_TF=OFF | BA2: CANDLE_PATTERN_STOPS_FILTER_TF=D | BB2: CANDLE_PATTERN_STOPS_FILTER_TF=4h | BC2: CANDLE_PATTERN_STOPS_FILTER_TF=1h | BD2: CANDLE_PATTERN_STOPS_FILTER_TF=15m | BE2: CIRCUIT_SHARPE_GATES_FILTER_TF=OFF | BF2: CIRCUIT_SHARPE_GATES_FILTER_TF=D | BG2: CIRCUIT_SHARPE_GATES_FILTER_TF=4h | BH2: CIRCUIT_SHARPE_GATES_FILTER_TF=1h | BI2: CIRCUIT_SHARPE_GATES_FILTER_TF=15m | BJ2: DC_BREACH_REDUCE_FILTER_TF=OFF | BK2: DC_BREACH_REDUCE_FILTER_TF=D | BL2: DC_BREACH_REDUCE_FILTER_TF=4h | BM2: DC_BREACH_REDUCE_FILTER_TF=1h | BN2: DC_BREACH_REDUCE_FILTER_TF=15m | BO2: DC_BREAK_FILTER_TF=OFF | BP2: DC_BREAK_FILTER_TF=D | BQ2: DC_BREAK_FILTER_TF=4h | BR2: DC_BREAK_FILTER_TF=1h | BS2: DC_BREAK_FILTER_TF=15m | BT2: DC_MOMENTUM_BOTA_SCORER_FILTER_TF=OFF | BU2: DC_MOMENTUM_BOTA_SCORER_FILTER_TF=D | BV2: DC_MOMENTUM_BOTA_SCORER_FILTER_TF=4h | BW2: DC_MOMENTUM_BOTA_SCORER_FILTER_TF=1h | BX2: DC_MOMENTUM_BOTA_SCORER_FILTER_TF=15m | BY2: DELTA_ENGINE_FILTER_TF=OFF | BZ2: DELTA_ENGINE_FILTER_TF=D | CA2: DELTA_ENGINE_FILTER_TF=4h | CB2: DELTA_ENGINE_FILTER_TF=1h | CC2: DELTA_ENGINE_FILTER_TF=15m | CD2: EMA_9_21_FILTER_FILTER_TF=OFF | CE2: EMA_9_21_FILTER_FILTER_TF=D | CF2: EMA_9_21_FILTER_FILTER_TF=4h | CG2: EMA_9_21_FILTER_FILTER_TF=1h | CH2: EMA_9_21_FILTER_FILTER_TF=15m | CI2: EMA_BLANKET_FILTER_FILTER_TF=OFF | CJ2: EMA_BLANKET_FILTER_FILTER_TF=D | CK2: EMA_BLANKET_FILTER_FILTER_TF=4h | CL2: EMA_BLANKET_FILTER_FILTER_TF=1h | CM2: EMA_BLANKET_FILTER_FILTER_TF=15m | CN2: EMERGENCY_BRAKE_FILTER_TF=OFF | CO2: EMERGENCY_BRAKE_FILTER_TF=D | CP2: EMERGENCY_BRAKE_FILTER_TF=4h | CQ2: EMERGENCY_BRAKE_FILTER_TF=1h | CR2: EMERGENCY_BRAKE_FILTER_TF=15m | CS2: EXIT_R1_R2_FILTER_TF=OFF | CT2: EXIT_R1_R2_FILTER_TF=D | CU2: EXIT_R1_R2_FILTER_TF=4h | CV2: EXIT_R1_R2_FILTER_TF=1h | CW2: EXIT_R1_R2_FILTER_TF=15m | CX2: EXIT_TIGHT_BREAKOUT_SCORER_FILTER_TF=OFF | CY2: EXIT_TIGHT_BREAKOUT_SCORER_FILTER_TF=D | CZ2: EXIT_TIGHT_BREAKOUT_SCORER_FILTER_TF=4h | DA2: EXIT_TIGHT_BREAKOUT_SCORER_FILTER_TF=1h | DB2: EXIT_TIGHT_BREAKOUT_SCORER_FILTER_TF=15m | DC2: EXIT_TOP_FADE_FILTER_TF=OFF | DD2: EXIT_TOP_FADE_FILTER_TF=D | DE2: EXIT_TOP_FADE_FILTER_TF=4h | DF2: EXIT_TOP_FADE_FILTER_TF=1h | DG2: EXIT_TOP_FADE_FILTER_TF=15m | DH2: EXIT_TO_REDUCE_ADAPTER_FILTER_TF=OFF | DI2: EXIT_TO_REDUCE_ADAPTER_FILTER_TF=D | DJ2: EXIT_TO_REDUCE_ADAPTER_FILTER_TF=4h | DK2: EXIT_TO_REDUCE_ADAPTER_FILTER_TF=1h | DL2: EXIT_TO_REDUCE_ADAPTER_FILTER_TF=15m | DM2: FAST_RISER_FILTER_TF=OFF | DN2: FAST_RISER_FILTER_TF=D | DO2: FAST_RISER_FILTER_TF=4h | DP2: FAST_RISER_FILTER_TF=1h | DQ2: FAST_RISER_FILTER_TF=15m | DR2: FH_MOMENTUM_FILTER_TF=OFF | DS2: FH_MOMENTUM_FILTER_TF=D | DT2: FH_MOMENTUM_FILTER_TF=4h | DU2: FH_MOMENTUM_FILTER_TF=1h | DV2: FH_MOMENTUM_FILTER_TF=15m | DW2: FIRST_OPEN_THROTTLE_FILTER_TF=OFF | DX2: FIRST_OPEN_THROTTLE_FILTER_TF=D | DY2: FIRST_OPEN_THROTTLE_FILTER_TF=4h | DZ2: FIRST_OPEN_THROTTLE_FILTER_TF=1h | EA2: FIRST_OPEN_THROTTLE_FILTER_TF=15m | EB2: FROZEN_STOP_FILTER_TF=OFF | EC2: FROZEN_STOP_FILTER_TF=D | ED2: FROZEN_STOP_FILTER_TF=4h | EE2: FROZEN_STOP_FILTER_TF=1h | EF2: FROZEN_STOP_FILTER_TF=15m | EG2: GOLDEN_RULE_ENFORCE_FILTER_TF=OFF | EH2: GOLDEN_RULE_ENFORCE_FILTER_TF=D | EI2: GOLDEN_RULE_ENFORCE_FILTER_TF=4h | EJ2: GOLDEN_RULE_ENFORCE_FILTER_TF=1h | EK2: GOLDEN_RULE_ENFORCE_FILTER_TF=15m | EL2: GOLDEN_RULE_HTF_VOTE_FILTER_TF=OFF | EM2: GOLDEN_RULE_HTF_VOTE_FILTER_TF=D | EN2: GOLDEN_RULE_HTF_VOTE_FILTER_TF=4h | EO2: GOLDEN_RULE_HTF_VOTE_FILTER_TF=1h | EP2: GOLDEN_RULE_HTF_VOTE_FILTER_TF=15m | EQ2: GR_FILTER_VEC_FILTER_TF=OFF | ER2: GR_FILTER_VEC_FILTER_TF=D | ES2: GR_FILTER_VEC_FILTER_TF=4h | ET2: GR_FILTER_VEC_FILTER_TF=1h | EU2: GR_FILTER_VEC_FILTER_TF=15m | EV2: GR_V5_STATE_FILTER_TF=OFF | EW2: GR_V5_STATE_FILTER_TF=D | EX2: GR_V5_STATE_FILTER_TF=4h | EY2: GR_V5_STATE_FILTER_TF=1h | EZ2: GR_V5_STATE_FILTER_TF=15m | FA2: HAIKU_WINNER_FILTER_TF=OFF | FB2: HAIKU_WINNER_FILTER_TF=D | FC2: HAIKU_WINNER_FILTER_TF=4h | FD2: HAIKU_WINNER_FILTER_TF=1h | FE2: HAIKU_WINNER_FILTER_TF=15m | FF2: LH_HL_FILTER_TF_REQ=2 | FG2: LH_HL_FILTER_TF_REQ=2_ALT | FH2: LIVE_ENTRY_ENGINE_FILTER_TF=OFF | FI2: LIVE_ENTRY_ENGINE_FILTER_TF=D | FJ2: LIVE_ENTRY_ENGINE_FILTER_TF=4h | FK2: LIVE_ENTRY_ENGINE_FILTER_TF=1h | FL2: LIVE_ENTRY_ENGINE_FILTER_TF=15m | FM2: LIVE_ONLY_SIGNALS_BATCH5_FILTER_TF=OFF | FN2: LIVE_ONLY_SIGNALS_BATCH5_FILTER_TF=D | FO2: LIVE_ONLY_SIGNALS_BATCH5_FILTER_TF=4h | FP2: LIVE_ONLY_SIGNALS_BATCH5_FILTER_TF=1h | FQ2: LIVE_ONLY_SIGNALS_BATCH5_FILTER_TF=15m | FR2: MANDATORY_REENTRY_WT_FILTER_TF_MODE=15m_only | FS2: MANDATORY_REENTRY_WT_FILTER_TF_MODE=15m_only_ALT | FT2: MOM3_FILTER_TF=OFF | FU2: MOM3_FILTER_TF=D | FV2: MOM3_FILTER_TF=4h | FW2: MOM3_FILTER_TF=1h | FX2: MOM3_FILTER_TF=15m | FY2: MOMENTUM_BREAKOUT_FILTER_TF=OFF | FZ2: MOMENTUM_BREAKOUT_FILTER_TF=D | GA2: MOMENTUM_BREAKOUT_FILTER_TF=4h | GB2: MOMENTUM_BREAKOUT_FILTER_TF=1h | GC2: MOMENTUM_BREAKOUT_FILTER_TF=15m | GD2: MTF_ARMED_ENTRIES_FILTER_TF=OFF | GE2: MTF_ARMED_ENTRIES_FILTER_TF=D | GF2: MTF_ARMED_ENTRIES_FILTER_TF=4h | GG2: MTF_ARMED_ENTRIES_FILTER_TF=1h | GH2: MTF_ARMED_ENTRIES_FILTER_TF=15m | GI2: MTF_ATR_TRAIL_FILTER_TF=OFF | GJ2: MTF_ATR_TRAIL_FILTER_TF=D | GK2: MTF_ATR_TRAIL_FILTER_TF=4h | GL2: MTF_ATR_TRAIL_FILTER_TF=1h | GM2: MTF_ATR_TRAIL_FILTER_TF=15m | GN2: MTF_DC_REJECT_FILTER_TF=OFF | GO2: MTF_DC_REJECT_FILTER_TF=D | GP2: MTF_DC_REJECT_FILTER_TF=4h | GQ2: MTF_DC_REJECT_FILTER_TF=1h | GR2: MTF_DC_REJECT_FILTER_TF=15m | GS2: NEWBORN_LOSS_KILL_FILTER_TF=OFF | GT2: NEWBORN_LOSS_KILL_FILTER_TF=D | GU2: NEWBORN_LOSS_KILL_FILTER_TF=4h | GV2: NEWBORN_LOSS_KILL_FILTER_TF=1h | GW2: NEWBORN_LOSS_KILL_FILTER_TF=15m | GX2: NEWBORN_PROTECT_FILTER_TF=OFF | GY2: NEWBORN_PROTECT_FILTER_TF=D | GZ2: NEWBORN_PROTECT_FILTER_TF=4h | HA2: NEWBORN_PROTECT_FILTER_TF=1h | HB2: NEWBORN_PROTECT_FILTER_TF=15m | HC2: NOLOSS_BYPASS_WT5OF5_FILTER_TF=OFF | HD2: NOLOSS_BYPASS_WT5OF5_FILTER_TF=D | HE2: NOLOSS_BYPASS_WT5OF5_FILTER_TF=4h | HF2: NOLOSS_BYPASS_WT5OF5_FILTER_TF=1h | HG2: NOLOSS_BYPASS_WT5OF5_FILTER_TF=15m | HH2: OPEN_INTENT_SIZE_GATES_FILTER_TF=OFF | HI2: OPEN_INTENT_SIZE_GATES_FILTER_TF=D | HJ2: OPEN_INTENT_SIZE_GATES_FILTER_TF=4h | HK2: OPEN_INTENT_SIZE_GATES_FILTER_TF=1h | HL2: OPEN_INTENT_SIZE_GATES_FILTER_TF=15m | HM2: PARTIAL_PROFIT_LOCK_V2_FILTER_TF=OFF | HN2: PARTIAL_PROFIT_LOCK_V2_FILTER_TF=D | HO2: PARTIAL_PROFIT_LOCK_V2_FILTER_TF=4h | HP2: PARTIAL_PROFIT_LOCK_V2_FILTER_TF=1h | HQ2: PARTIAL_PROFIT_LOCK_V2_FILTER_TF=15m | HR2: PEAK_GIVEBACK_BE_EROSION_FILTER_TF=OFF | HS2: PEAK_GIVEBACK_BE_EROSION_FILTER_TF=D | HT2: PEAK_GIVEBACK_BE_EROSION_FILTER_TF=4h | HU2: PEAK_GIVEBACK_BE_EROSION_FILTER_TF=1h | HV2: PEAK_GIVEBACK_BE_EROSION_FILTER_TF=15m | HW2: WT_15M_BOUNCE_BB_MAX=0.95 | HX2: WT_15M_BOUNCE_BB_MAX=0.9 | HY2: WT_15M_BOUNCE_BB_MAX=0.8 | HZ2: WT_15M_BOUNCE_BB_MIN=0.05 | IA2: WT_15M_BOUNCE_BB_MIN=0.1 | IB2: WT_15M_BOUNCE_BB_MIN=0.2 | IC2: WT_15M_BOUNCE_HIGH_1H_GT_PREV=True | ID2: WT_15M_BOUNCE_HIGH_1H_GT_PREV=False | IE2: WT_15M_BOUNCE_LOW_1H_GT_PREV=True | IF2: WT_15M_BOUNCE_LOW_1H_GT_PREV=False | IG2: WT_15M_BOUNCE_REL_VOL_GT_1=True | IH2: WT_15M_BOUNCE_REL_VOL_GT_1=False | II2: Live Location | IJ2: Vec Hook | IK2: Type | IL2: Correct Options
A3: STDEV_BREAKOUT_EXIT_PCTB_FAIL | B3: 0 | E3: =MAX('ENTRY_CONFIRMATION_GATES'!E:E) | F3: 0 | G3: -1.6561539 | H3: =IFERROR(VLOOKUP($A3,Results_30d_Deltas!$A$2:$H$5000,6,FALSE),"") | K3: =IF(B3=C3,"YES","NO") | IJ3: ez_manage.py:4040 top() | IK3: v12_quick_engine.py:3276 x2
A4: STDEV_BREAKOUT_EXIT_PCTB_FAIL | B4: 0.5 | E4: =IF(F4="",E3,IF(F4>0,E3+F4,E3)) | F4: -2.0245238 | G4: -3.6806777 | H4: =IFERROR(VLOOKUP($A4,Results_30d_Deltas!$A$2:$H$5000,6,FALSE),"") | K4: =IF(B4=C4,"YES","NO") | IJ4: ez_manage.py:4040 top() | IK4: v12_quick_engine.py:3276 x2
A5: STDEV_BREAKOUT_EXIT_PCTB_FAIL | B5: 1.0 | E5: =IF(F5="",E4,IF(F5>0,E4+F5,E4)) | F5: -2.0610562 | G5: -3.7172101 | H5: =IFERROR(VLOOKUP($A5,Results_30d_Deltas!$A$2:$H$5000,6,FALSE),"") | K5: =IF(B5=C5,"YES","NO") | IJ5: ez_manage.py:4040 top() | IK5: v12_quick_engine.py:3276 x2
A6: STDEV_BREAKOUT_EXIT_PCTB_FAIL | B6: 2.0 | E6: =IF(F6="",E5,IF(F6>0,E5+F6,E5)) | F6: 0 | G6: -1.6561539 | H6: =IFERROR(VLOOKUP($A6,Results_30d_Deltas!$A$2:$H$5000,6,FALSE),"") | K6: =IF(B6=C6,"YES","NO") | IJ6: ez_manage.py:4040 top() | IK6: v12_quick_engine.py:3276 x2
A7: ALL_TF_AGAINST_CLOSE_ENABLED | B7: False | E7: =IF(F7="",E6,IF(F7>0,E6+F7,E6)) | F7: 0 | G7: -1.6561539 | H7: =IFERROR(VLOOKUP($A7,Results_30d_Deltas!$A$2:$H$5000,6,FALSE),"") | K7: =IF(B7=C7,"YES","NO") | IJ7: ez_manage.py:4325 top() | IK7: v12_quick_engine.py:174 x6
A8: ALL_TF_AGAINST_CLOSE_ENABLED | B8: True | E8: =IF(F8="",E7,IF(F8>0,E7+F8,E7)) | F8: =IFERROR(VLOOKUP($A8&"="&$B8,Results_30d_Deltas!$A$2:$H$5000,5,FALSE),"") | G8: =IFERROR(VLOOKUP($A8,Results_30d_Deltas!$A$2:$H$5000,7,FALSE)-E7,"") | H8: =IFERROR(VLOOKUP($A8,Results_30d_Deltas!$A$2:$H$5000,6,FALSE),"") | K8: =IF(B8=C8,"YES","NO") | IJ8: ez_manage.py:4325 top() | IK8: v12_quick_engine.py:174 x6

Sheet EXIT_VELOCITY
A1: 05 EXIT_VELOCITY - 26 bases -> 80 rows - 231 per-row FULLY CONNECTED
A2: Switch | B2: default | C2: override | D2: Family | E2: BASELINE | F2: VECTOR_DELTA | G2: LIVE_DELTA | H2: LIVE_SHARPE | I2: REAL_COMPLETE | J2: PER_ROW_FILTERS | K2: is_default (backup if bold lost) | L2: ATR_TRAIL_FILTER_TF=OFF | M2: ATR_TRAIL_FILTER_TF=D | N2: ATR_TRAIL_FILTER_TF=4h | O2: ATR_TRAIL_FILTER_TF=1h | P2: ATR_TRAIL_FILTER_TF=15m | Q2: BAR_PATTERNS_FILTER_TF=OFF | R2: BAR_PATTERNS_FILTER_TF=D | S2: BAR_PATTERNS_FILTER_TF=4h | T2: BAR_PATTERNS_FILTER_TF=1h | U2: BAR_PATTERNS_FILTER_TF=15m | V2: BB_PULLBACK_GATE_FILTER_TF=OFF | W2: BB_PULLBACK_GATE_FILTER_TF=D | X2: BB_PULLBACK_GATE_FILTER_TF=4h | Y2: BB_PULLBACK_GATE_FILTER_TF=1h | Z2: BB_PULLBACK_GATE_FILTER_TF=15m | AA2: BB_RECOVERY_ENTRY_FILTER_TF=OFF | AB2: BB_RECOVERY_ENTRY_FILTER_TF=D | AC2: BB_RECOVERY_ENTRY_FILTER_TF=4h | AD2: BB_RECOVERY_ENTRY_FILTER_TF=1h | AE2: BB_RECOVERY_ENTRY_FILTER_TF=15m | AF2: BB_RECOVERY_FILTER_TF=OFF | AG2: BB_RECOVERY_FILTER_TF=D | AH2: BB_RECOVERY_FILTER_TF=4h | AI2: BB_RECOVERY_FILTER_TF=1h | AJ2: BB_RECOVERY_FILTER_TF=15m | AK2: BREAKEVEN_GAIN_EROSION_FILTER_TF=OFF | AL2: BREAKEVEN_GAIN_EROSION_FILTER_TF=D | AM2: BREAKEVEN_GAIN_EROSION_FILTER_TF=4h | AN2: BREAKEVEN_GAIN_EROSION_FILTER_TF=1h | AO2: BREAKEVEN_GAIN_EROSION_FILTER_TF=15m | AP2: BREAKOUT_RETEST_FILTER_TF=OFF | AQ2: BREAKOUT_RETEST_FILTER_TF=D | AR2: BREAKOUT_RETEST_FILTER_TF=4h | AS2: BREAKOUT_RETEST_FILTER_TF=1h | AT2: BREAKOUT_RETEST_FILTER_TF=15m | AU2: BT_WT_CROSS_LADDER_FILTER_TF=OFF | AV2: BT_WT_CROSS_LADDER_FILTER_TF=D | AW2: BT_WT_CROSS_LADDER_FILTER_TF=4h | AX2: BT_WT_CROSS_LADDER_FILTER_TF=1h | AY2: BT_WT_CROSS_LADDER_FILTER_TF=15m | AZ2: CANDLE_PATTERN_STOPS_FILTER_TF=OFF | BA2: CANDLE_PATTERN_STOPS_FILTER_TF=D | BB2: CANDLE_PATTERN_STOPS_FILTER_TF=4h | BC2: CANDLE_PATTERN_STOPS_FILTER_TF=1h | BD2: CANDLE_PATTERN_STOPS_FILTER_TF=15m | BE2: CIRCUIT_SHARPE_GATES_FILTER_TF=OFF | BF2: CIRCUIT_SHARPE_GATES_FILTER_TF=D | BG2: CIRCUIT_SHARPE_GATES_FILTER_TF=4h | BH2: CIRCUIT_SHARPE_GATES_FILTER_TF=1h | BI2: CIRCUIT_SHARPE_GATES_FILTER_TF=15m | BJ2: DC_BREACH_REDUCE_FILTER_TF=OFF | BK2: DC_BREACH_REDUCE_FILTER_TF=D | BL2: DC_BREACH_REDUCE_FILTER_TF=4h | BM2: DC_BREACH_REDUCE_FILTER_TF=1h | BN2: DC_BREACH_REDUCE_FILTER_TF=15m | BO2: DC_BREAK_FILTER_TF=OFF | BP2: DC_BREAK_FILTER_TF=D | BQ2: DC_BREAK_FILTER_TF=4h | BR2: DC_BREAK_FILTER_TF=1h | BS2: DC_BREAK_FILTER_TF=15m | BT2: DC_MOMENTUM_BOTA_SCORER_FILTER_TF=OFF | BU2: DC_MOMENTUM_BOTA_SCORER_FILTER_TF=D | BV2: DC_MOMENTUM_BOTA_SCORER_FILTER_TF=4h | BW2: DC_MOMENTUM_BOTA_SCORER_FILTER_TF=1h | BX2: DC_MOMENTUM_BOTA_SCORER_FILTER_TF=15m | BY2: DELTA_ENGINE_FILTER_TF=OFF | BZ2: DELTA_ENGINE_FILTER_TF=D | CA2: DELTA_ENGINE_FILTER_TF=4h | CB2: DELTA_ENGINE_FILTER_TF=1h | CC2: DELTA_ENGINE_FILTER_TF=15m | CD2: EMA_9_21_FILTER_FILTER_TF=OFF | CE2: EMA_9_21_FILTER_FILTER_TF=D | CF2: EMA_9_21_FILTER_FILTER_TF=4h | CG2: EMA_9_21_FILTER_FILTER_TF=1h | CH2: EMA_9_21_FILTER_FILTER_TF=15m | CI2: EMA_BLANKET_FILTER_FILTER_TF=OFF | CJ2: EMA_BLANKET_FILTER_FILTER_TF=D | CK2: EMA_BLANKET_FILTER_FILTER_TF=4h | CL2: EMA_BLANKET_FILTER_FILTER_TF=1h | CM2: EMA_BLANKET_FILTER_FILTER_TF=15m | CN2: EMERGENCY_BRAKE_FILTER_TF=OFF | CO2: EMERGENCY_BRAKE_FILTER_TF=D | CP2: EMERGENCY_BRAKE_FILTER_TF=4h | CQ2: EMERGENCY_BRAKE_FILTER_TF=1h | CR2: EMERGENCY_BRAKE_FILTER_TF=15m | CS2: EXIT_R1_R2_FILTER_TF=OFF | CT2: EXIT_R1_R2_FILTER_TF=D | CU2: EXIT_R1_R2_FILTER_TF=4h | CV2: EXIT_R1_R2_FILTER_TF=1h | CW2: EXIT_R1_R2_FILTER_TF=15m | CX2: EXIT_TIGHT_BREAKOUT_SCORER_FILTER_TF=OFF | CY2: EXIT_TIGHT_BREAKOUT_SCORER_FILTER_TF=D | CZ2: EXIT_TIGHT_BREAKOUT_SCORER_FILTER_TF=4h | DA2: EXIT_TIGHT_BREAKOUT_SCORER_FILTER_TF=1h | DB2: EXIT_TIGHT_BREAKOUT_SCORER_FILTER_TF=15m | DC2: EXIT_TOP_FADE_FILTER_TF=OFF | DD2: EXIT_TOP_FADE_FILTER_TF=D | DE2: EXIT_TOP_FADE_FILTER_TF=4h | DF2: EXIT_TOP_FADE_FILTER_TF=1h | DG2: EXIT_TOP_FADE_FILTER_TF=15m | DH2: EXIT_TO_REDUCE_ADAPTER_FILTER_TF=OFF | DI2: EXIT_TO_REDUCE_ADAPTER_FILTER_TF=D | DJ2: EXIT_TO_REDUCE_ADAPTER_FILTER_TF=4h | DK2: EXIT_TO_REDUCE_ADAPTER_FILTER_TF=1h | DL2: EXIT_TO_REDUCE_ADAPTER_FILTER_TF=15m | DM2: FAST_RISER_FILTER_TF=OFF | DN2: FAST_RISER_FILTER_TF=D | DO2: FAST_RISER_FILTER_TF=4h | DP2: FAST_RISER_FILTER_TF=1h | DQ2: FAST_RISER_FILTER_TF=15m | DR2: FH_MOMENTUM_FILTER_TF=OFF | DS2: FH_MOMENTUM_FILTER_TF=D | DT2: FH_MOMENTUM_FILTER_TF=4h | DU2: FH_MOMENTUM_FILTER_TF=1h | DV2: FH_MOMENTUM_FILTER_TF=15m | DW2: FIRST_OPEN_THROTTLE_FILTER_TF=OFF | DX2: FIRST_OPEN_THROTTLE_FILTER_TF=D | DY2: FIRST_OPEN_THROTTLE_FILTER_TF=4h | DZ2: FIRST_OPEN_THROTTLE_FILTER_TF=1h | EA2: FIRST_OPEN_THROTTLE_FILTER_TF=15m | EB2: FROZEN_STOP_FILTER_TF=OFF | EC2: FROZEN_STOP_FILTER_TF=D | ED2: FROZEN_STOP_FILTER_TF=4h | EE2: FROZEN_STOP_FILTER_TF=1h | EF2: FROZEN_STOP_FILTER_TF=15m | EG2: GOLDEN_RULE_ENFORCE_FILTER_TF=OFF | EH2: GOLDEN_RULE_ENFORCE_FILTER_TF=D | EI2: GOLDEN_RULE_ENFORCE_FILTER_TF=4h | EJ2: GOLDEN_RULE_ENFORCE_FILTER_TF=1h | EK2: GOLDEN_RULE_ENFORCE_FILTER_TF=15m | EL2: GOLDEN_RULE_HTF_VOTE_FILTER_TF=OFF | EM2: GOLDEN_RULE_HTF_VOTE_FILTER_TF=D | EN2: GOLDEN_RULE_HTF_VOTE_FILTER_TF=4h | EO2: GOLDEN_RULE_HTF_VOTE_FILTER_TF=1h | EP2: GOLDEN_RULE_HTF_VOTE_FILTER_TF=15m | EQ2: GR_FILTER_VEC_FILTER_TF=OFF | ER2: GR_FILTER_VEC_FILTER_TF=D | ES2: GR_FILTER_VEC_FILTER_TF=4h | ET2: GR_FILTER_VEC_FILTER_TF=1h | EU2: GR_FILTER_VEC_FILTER_TF=15m | EV2: GR_V5_STATE_FILTER_TF=OFF | EW2: GR_V5_STATE_FILTER_TF=D | EX2: GR_V5_STATE_FILTER_TF=4h | EY2: GR_V5_STATE_FILTER_TF=1h | EZ2: GR_V5_STATE_FILTER_TF=15m | FA2: HAIKU_WINNER_FILTER_TF=OFF | FB2: HAIKU_WINNER_FILTER_TF=D | FC2: HAIKU_WINNER_FILTER_TF=4h | FD2: HAIKU_WINNER_FILTER_TF=1h | FE2: HAIKU_WINNER_FILTER_TF=15m | FF2: LH_HL_FILTER_TF_REQ=2 | FG2: LH_HL_FILTER_TF_REQ=2_ALT | FH2: LIVE_ENTRY_ENGINE_FILTER_TF=OFF | FI2: LIVE_ENTRY_ENGINE_FILTER_TF=D | FJ2: LIVE_ENTRY_ENGINE_FILTER_TF=4h | FK2: LIVE_ENTRY_ENGINE_FILTER_TF=1h | FL2: LIVE_ENTRY_ENGINE_FILTER_TF=15m | FM2: LIVE_ONLY_SIGNALS_BATCH5_FILTER_TF=OFF | FN2: LIVE_ONLY_SIGNALS_BATCH5_FILTER_TF=D | FO2: LIVE_ONLY_SIGNALS_BATCH5_FILTER_TF=4h | FP2: LIVE_ONLY_SIGNALS_BATCH5_FILTER_TF=1h | FQ2: LIVE_ONLY_SIGNALS_BATCH5_FILTER_TF=15m | FR2: MANDATORY_REENTRY_WT_FILTER_TF_MODE=15m_only | FS2: MANDATORY_REENTRY_WT_FILTER_TF_MODE=15m_only_ALT | FT2: MOM3_FILTER_TF=OFF | FU2: MOM3_FILTER_TF=D | FV2: MOM3_FILTER_TF=4h | FW2: MOM3_FILTER_TF=1h | FX2: MOM3_FILTER_TF=15m | FY2: MOMENTUM_BREAKOUT_FILTER_TF=OFF | FZ2: MOMENTUM_BREAKOUT_FILTER_TF=D | GA2: MOMENTUM_BREAKOUT_FILTER_TF=4h | GB2: MOMENTUM_BREAKOUT_FILTER_TF=1h | GC2: MOMENTUM_BREAKOUT_FILTER_TF=15m | GD2: MTF_ARMED_ENTRIES_FILTER_TF=OFF | GE2: MTF_ARMED_ENTRIES_FILTER_TF=D | GF2: MTF_ARMED_ENTRIES_FILTER_TF=4h | GG2: MTF_ARMED_ENTRIES_FILTER_TF=1h | GH2: MTF_ARMED_ENTRIES_FILTER_TF=15m | GI2: MTF_ATR_TRAIL_FILTER_TF=OFF | GJ2: MTF_ATR_TRAIL_FILTER_TF=D | GK2: MTF_ATR_TRAIL_FILTER_TF=4h | GL2: MTF_ATR_TRAIL_FILTER_TF=1h | GM2: MTF_ATR_TRAIL_FILTER_TF=15m | GN2: MTF_DC_REJECT_FILTER_TF=OFF | GO2: MTF_DC_REJECT_FILTER_TF=D | GP2: MTF_DC_REJECT_FILTER_TF=4h | GQ2: MTF_DC_REJECT_FILTER_TF=1h | GR2: MTF_DC_REJECT_FILTER_TF=15m | GS2: NEWBORN_LOSS_KILL_FILTER_TF=OFF | GT2: NEWBORN_LOSS_KILL_FILTER_TF=D | GU2: NEWBORN_LOSS_KILL_FILTER_TF=4h | GV2: NEWBORN_LOSS_KILL_FILTER_TF=1h | GW2: NEWBORN_LOSS_KILL_FILTER_TF=15m | GX2: NEWBORN_PROTECT_FILTER_TF=OFF | GY2: NEWBORN_PROTECT_FILTER_TF=D | GZ2: NEWBORN_PROTECT_FILTER_TF=4h | HA2: NEWBORN_PROTECT_FILTER_TF=1h | HB2: NEWBORN_PROTECT_FILTER_TF=15m | HC2: NOLOSS_BYPASS_WT5OF5_FILTER_TF=OFF | HD2: NOLOSS_BYPASS_WT5OF5_FILTER_TF=D | HE2: NOLOSS_BYPASS_WT5OF5_FILTER_TF=4h | HF2: NOLOSS_BYPASS_WT5OF5_FILTER_TF=1h | HG2: NOLOSS_BYPASS_WT5OF5_FILTER_TF=15m | HH2: OPEN_INTENT_SIZE_GATES_FILTER_TF=OFF | HI2: OPEN_INTENT_SIZE_GATES_FILTER_TF=D | HJ2: OPEN_INTENT_SIZE_GATES_FILTER_TF=4h | HK2: OPEN_INTENT_SIZE_GATES_FILTER_TF=1h | HL2: OPEN_INTENT_SIZE_GATES_FILTER_TF=15m | HM2: PARTIAL_PROFIT_LOCK_V2_FILTER_TF=OFF | HN2: PARTIAL_PROFIT_LOCK_V2_FILTER_TF=D | HO2: PARTIAL_PROFIT_LOCK_V2_FILTER_TF=4h | HP2: PARTIAL_PROFIT_LOCK_V2_FILTER_TF=1h | HQ2: PARTIAL_PROFIT_LOCK_V2_FILTER_TF=15m | HR2: PEAK_GIVEBACK_BE_EROSION_FILTER_TF=OFF | HS2: PEAK_GIVEBACK_BE_EROSION_FILTER_TF=D | HT2: PEAK_GIVEBACK_BE_EROSION_FILTER_TF=4h | HU2: PEAK_GIVEBACK_BE_EROSION_FILTER_TF=1h | HV2: PEAK_GIVEBACK_BE_EROSION_FILTER_TF=15m | HW2: WT_15M_BOUNCE_BB_MAX=0.95 | HX2: WT_15M_BOUNCE_BB_MAX=0.9 | HY2: WT_15M_BOUNCE_BB_MAX=0.8 | HZ2: WT_15M_BOUNCE_BB_MIN=0.05 | IA2: WT_15M_BOUNCE_BB_MIN=0.1 | IB2: WT_15M_BOUNCE_BB_MIN=0.2 | IC2: WT_15M_BOUNCE_HIGH_1H_GT_PREV=True | ID2: WT_15M_BOUNCE_HIGH_1H_GT_PREV=False | IE2: WT_15M_BOUNCE_LOW_1H_GT_PREV=True | IF2: WT_15M_BOUNCE_LOW_1H_GT_PREV=False | IG2: WT_15M_BOUNCE_REL_VOL_GT_1=True | IH2: WT_15M_BOUNCE_REL_VOL_GT_1=False | II2: Live Location | IJ2: Vec Hook | IK2: Type | IL2: Correct Options
A3: WT_CROSS_EXIT_ENABLED | B3: False | E3: =MAX('EXIT_STRUCTURAL'!E:E) | F3: =IFERROR(VLOOKUP($A3&"="&$B3,Results_30d_Deltas!$A$2:$H$5000,5,FALSE),"") | G3: =IFERROR(VLOOKUP($A3,Results_30d_Deltas!$A$2:$H$5000,7,FALSE)-E3,"") | H3: =IFERROR(VLOOKUP($A3,Results_30d_Deltas!$A$2:$H$5000,6,FALSE),"") | K3: =IF(B3=C3,"YES","NO") | IJ3: ez_manage.py:1751 top() | IK3: v12_quick_engine.py:2439 x5
A4: WT_CROSS_EXIT_ENABLED | B4: True | E4: =IF(F4="",E3,IF(F4>0,E3+F4,E3)) | F4: -1.7240473 | G4: -3.3802012 | H4: =IFERROR(VLOOKUP($A4,Results_30d_Deltas!$A$2:$H$5000,6,FALSE),"") | K4: =IF(B4=C4,"YES","NO") | IJ4: ez_manage.py:1751 top() | IK4: v12_quick_engine.py:2439 x5
A5: BB_SQUEEZE_EXIT_ENABLED | B5: False | E5: =IF(F5="",E4,IF(F5>0,E4+F5,E4)) | F5: =IFERROR(VLOOKUP($A5&"="&$B5,Results_30d_Deltas!$A$2:$H$5000,5,FALSE),"") | G5: =IFERROR(VLOOKUP($A5,Results_30d_Deltas!$A$2:$H$5000,7,FALSE)-E4,"") | H5: =IFERROR(VLOOKUP($A5,Results_30d_Deltas!$A$2:$H$5000,6,FALSE),"") | K5: =IF(B5=C5,"YES","NO") | IJ5: ez_manage.py:6163 top() | IK5: v12_quick_engine.py:891 x4
A6: BB_SQUEEZE_EXIT_ENABLED | B6: True | E6: =IF(F6="",E5,IF(F6>0,E5+F6,E5)) | F6: 0 | G6: -1.6561539 | H6: =IFERROR(VLOOKUP($A6,Results_30d_Deltas!$A$2:$H$5000,6,FALSE),"") | K6: =IF(B6=C6,"YES","NO") | IJ6: ez_manage.py:6163 top() | IK6: v12_quick_engine.py:891 x4
A7: BTC_DIVERGENCE_EXIT_AGAINST | B7: 0 | E7: =IF(F7="",E6,IF(F7>0,E6+F7,E6)) | F7: -1.8787217 | G7: -3.5348756 | H7: =IFERROR(VLOOKUP($A7,Results_30d_Deltas!$A$2:$H$5000,6,FALSE),"") | K7: =IF(B7=C7,"YES","NO") | IJ7: ez_manage.py:4448 top() | IK7: v12_quick_engine.py:408 x8
A8: BTC_DIVERGENCE_EXIT_AGAINST | B8: 0.5 | E8: =IF(F8="",E7,IF(F8>0,E7+F8,E7)) | F8: 0 | G8: -1.6561539 | H8: =IFERROR(VLOOKUP($A8,Results_30d_Deltas!$A$2:$H$5000,6,FALSE),"") | K8: =IF(B8=C8,"YES","NO") | IJ8: ez_manage.py:4448 top() | IK8: v12_quick_engine.py:408 x8
A9: BTC_DIVERGENCE_EXIT_AGAINST | B9: 1.0 | E9: =IF(F9="",E8,IF(F9>0,E8+F9,E8)) | F9: 0 | G9: -1.6561539 | H9: =IFERROR(VLOOKUP($A9,Results_30d_Deltas!$A$2:$H$5000,6,FALSE),"") | K9: =IF(B9=C9,"YES","NO") | IJ9: ez_manage.py:4448 top() | IK9: v12_quick_engine.py:408 x8
A10: BTC_DIVERGENCE_EXIT_AGAINST | B10: 2.0 | E10: =IF(F10="",E9,IF(F10>0,E9+F10,E9)) | F10: -2.4538266 | G10: -4.1099804 | H10: =IFERROR(VLOOKUP($A10,Results_30d_Deltas!$A$2:$H$5000,6,FALSE),"") | K10: =IF(B10=C10,"YES","NO") | IJ10: ez_manage.py:4448 top() | IK10: v12_quick_engine.py:408 x8
A11: DELTA_EXIT_DC_FLOOR | B11: False | E11: =IF(F11="",E10,IF(F11>0,E10+F11,E10)) | F11: -2.4538266 | G11: -4.1099804 | H11: =IFERROR(VLOOKUP($A11,Results_30d_Deltas!$A$2:$H$5000,6,FALSE),"") | K11: =IF(B11=C11,"YES","NO") | IJ11: ez_manage.py:4596 top() | IK11: v12_quick_engine.py:967 x8
A12: DELTA_EXIT_DC_FLOOR | B12: True | E12: =IF(F12="",E11,IF(F12>0,E11+F12,E11)) | F12: =IFERROR(VLOOKUP($A12&"="&$B12,Results_30d_Deltas!$A$2:$H$5000,5,FALSE),"") | G12: =IFERROR(VLOOKUP($A12,Results_30d_Deltas!$A$2:$H$5000,7,FALSE)-E11,"") | H12: =IFERROR(VLOOKUP($A12,Results_30d_Deltas!$A$2:$H$5000,6,FALSE),"") | K12: =IF(B12=C12,"YES","NO") | IJ12: ez_manage.py:4596 top() | IK12: v12_quick_engine.py:967 x8
A13: E_1_WT_EXIT_USE_DELTA_ENABLED | B13: False | E13: =IF(F13="",E12,IF(F13>0,E12+F13,E12)) | F13: =IFERROR(VLOOKUP($A13&"="&$B13,Results_30d_Deltas!$A$2:$H$5000,5,FALSE),"") | G13: =IFERROR(VLOOKUP($A13,Results_30d_Deltas!$A$2:$H$5000,7,FALSE)-E12,"") | H13: =IFERROR(VLOOKUP($A13,Results_30d_Deltas!$A$2:$H$5000,6,FALSE),"") | K13: =IF(B13=C13,"YES","NO") | IJ13: ez_manage.py:4699 top() | IK13: v12_quick_engine.py:1818 x7
A14: E_1_WT_EXIT_USE_DELTA_ENABLED | B14: True | E14: =IF(F14="",E13,IF(F14>0,E13+F14,E13)) | F14: -1.8787217 | G14: -3.5348756 | H14: =IFERROR(VLOOKUP($A14,Results_30d_Deltas!$A$2:$H$5000,6,FALSE),"") | K14: =IF(B14=C14,"YES","NO") | IJ14: ez_manage.py:4699 top() | IK14: v12_quick_engine.py:1818 x7
A15: E_3_USE_WT_STRUCTURE_EXIT_MODE | B15: 0 | E15: =IF(F15="",E14,IF(F15>0,E14+F15,E14)) | F15: 0 | G15: -1.6561539 | H15: =IFERROR(VLOOKUP($A15,Results_30d_Deltas!$A$2:$H$5000,6,FALSE),"") | K15: =IF(B15=C15,"YES","NO") | IJ15: ez_manage.py:4700 top() | IK15: v12_quick_engine.py:1819 x8
A16: E_3_USE_WT_STRUCTURE_EXIT_MODE | B16: 0.5 | E16: =IF(F16="",E15,IF(F16>0,E15+F16,E15)) | F16: -1.8542583 | G16: -3.5104122 | H16: =IFERROR(VLOOKUP($A16,Results_30d_Deltas!$A$2:$H$5000,6,FALSE),"") | K16: =IF(B16=C16,"YES","NO") | IJ16: ez_manage.py:4700 top() | IK16: v12_quick_engine.py:1819 x8
A17: E_3_USE_WT_STRUCTURE_EXIT_MODE | B17: 1.0 | E17: =IF(F17="",E16,IF(F17>0,E16+F17,E16)) | F17: -1.8526111 | G17: -3.508765 | H17: =IFERROR(VLOOKUP($A17,Results_30d_Deltas!$A$2:$H$5000,6,FALSE),"") | K17: =IF(B17=C17,"YES","NO") | IJ17: ez_manage.py:4700 top() | IK17: v12_quick_engine.py:1819 x8
A18: E_3_USE_WT_STRUCTURE_EXIT_MODE | B18: 2.0 | E18: =IF(F18="",E17,IF(F18>0,E17+F18,E17)) | F18: 0 | G18: -1.6561539 | H18: =IFERROR(VLOOKUP($A18,Results_30d_Deltas!$A$2:$H$5000,6,FALSE),"") | K18: =IF(B18=C18,"YES","NO") | IJ18: ez_manage.py:4700 top() | IK18: v12_quick_engine.py:1819 x8
A19: HARD_BREAKEVEN_FLOOR_ENABLED | B19: False | E19: =IF(F19="",E18,IF(F19>0,E18+F19,E18)) | F19: -2.0610562 | G19: -3.7172101 | H19: =IFERROR(VLOOKUP($A19,Results_30d_Deltas!$A$2:$H$5000,6,FALSE),"") | K19: =IF(B19=C19,"YES","NO") | IJ19: ez_manage.py:4783 top() | IK19: v12_quick_engine.py:856 x6
A20: HARD_BREAKEVEN_FLOOR_ENABLED | B20: True | E20: =IF(F20="",E19,IF(F20>0,E19+F20,E19)) | F20: =IFERROR(VLOOKUP($A20&"="&$B20,Results_30d_Deltas!$A$2:$H$5000,5,FALSE),"") | G20: =IFERROR(VLOOKUP($A20,Results_30d_Deltas!$A$2:$H$5000,7,FALSE)-E19,"") | H20: =IFERROR(VLOOKUP($A20,Results_30d_Deltas!$A$2:$H$5000,6,FALSE),"") | K20: =IF(B20=C20,"YES","NO") | IJ20: ez_manage.py:4783 top() | IK20: v12_quick_engine.py:856 x6
A21: HARD_BREAKEVEN_MIN_PEAK_PCT | B21: 0.25 | E21: =IF(F21="",E20,IF(F21>0,E20+F21,E20)) | F21: -2.0610562 | G21: -3.7172101 | H21: =IFERROR(VLOOKUP($A21,Results_30d_Deltas!$A$2:$H$5000,6,FALSE),"") | K21: =IF(B21=C21,"YES","NO") | IJ21: ez_manage.py:4784 top() | IK21: v12_quick_engine.py:858 x8
A22: HARD_BREAKEVEN_MIN_PEAK_PCT | B22: 0.375 | E22: =IF(F22="",E21,IF(F22>0,E21+F22,E21)) | F22: -1.0393426 | G22: -2.6954965 | H22: =IFERROR(VLOOKUP($A22,Results_30d_Deltas!$A$2:$H$5000,6,FALSE),"") | K22: =IF(B22=C22,"YES","NO") | IJ22: ez_manage.py:4784 top() | IK22: v12_quick_engine.py:858 x8
A23: HARD_BREAKEVEN_MIN_PEAK_PCT | B23: 0.5 | E23: =IF(F23="",E22,IF(F23>0,E22+F23,E22)) | F23: -2.471381 | G23: -4.1275348 | H23: =IFERROR(VLOOKUP($A23,Results_30d_Deltas!$A$2:$H$5000,6,FALSE),"") | K23: =IF(B23=C23,"YES","NO") | IJ23: ez_manage.py:4784 top() | IK23: v12_quick_engine.py:858 x8
A24: HARD_BREAKEVEN_MIN_PEAK_PCT | B24: 0.625 | E24: =IF(F24="",E23,IF(F24>0,E23+F24,E23)) | F24: -1.8787217 | G24: -3.5348756 | H24: =IFERROR(VLOOKUP($A24,Results_30d_Deltas!$A$2:$H$5000,6,FALSE),"") | K24: =IF(B24=C24,"YES","NO") | IJ24: ez_manage.py:4784 top() | IK24: v12_quick_engine.py:858 x8
A25: HARD_BREAKEVEN_MIN_PEAK_PCT | B25: 0.75 | E25: =IF(F25="",E24,IF(F25>0,E24+F25,E24)) | F25: 0 | G25: -1.6561539 | H25: =IFERROR(VLOOKUP($A25,Results_30d_Deltas!$A$2:$H$5000,6,FALSE),"") | K25: =IF(B25=C25,"YES","NO") | IJ25: ez_manage.py:4784 top() | IK25: v12_quick_engine.py:858 x8
A26: LOSS_TECHNICAL_EXIT_NO_STALE_BLOCK | B26: 0 | E26: =IF(F26="",E25,IF(F26>0,E25+F26,E25)) | F26: 0 | G26: -1.6561539 | H26: =IFERROR(VLOOKUP($A26,Results_30d_Deltas!$A$2:$H$5000,6,FALSE),"") | K26: =IF(B26=C26,"YES","NO") | IJ26: ez_manage.py:4933 top() | IK26: v12_quick_engine.py:2172 x2
A27: LOSS_TECHNICAL_EXIT_NO_STALE_BLOCK | B27: 0.5 | E27: =IF(F27="",E26,IF(F27>0,E26+F27,E26)) | F27: -1.7240473 | G27: -3.3802012 | H27: =IFERROR(VLOOKUP($A27,Results_30d_Deltas!$A$2:$H$5000,6,FALSE),"") | K27: =IF(B27=C27,"YES","NO") | IJ27: ez_manage.py:4933 top() | IK27: v12_quick_engine.py:2172 x2
A28: LOSS_TECHNICAL_EXIT_NO_STALE_BLOCK | B28: 1.0 | E28: =IF(F28="",E27,IF(F28>0,E27+F28,E27)) | F28: -2.4538266 | G28: -4.1099804 | H28: =IFERROR(VLOOKUP($A28,Results_30d_Deltas!$A$2:$H$5000,6,FALSE),"") | K28: =IF(B28=C28,"YES","NO") | IJ28: ez_manage.py:4933 top() | IK28: v12_quick_engine.py:2172 x2
A29: LOSS_TECHNICAL_EXIT_NO_STALE_BLOCK | B29: 2.0 | E29: =IF(F29="",E28,IF(F29>0,E28+F29,E28)) | F29: 0 | G29: -1.6561539 | H29: =IFERROR(VLOOKUP($A29,Results_30d_Deltas!$A$2:$H$5000,6,FALSE),"") | K29: =IF(B29=C29,"YES","NO") | IJ29: ez_manage.py:4933 top() | IK29: v12_quick_engine.py:2172 x2
A30: MI_STRUCT_EXIT_ENABLED | B30: False | E30: =IF(F30="",E29,IF(F30>0,E29+F30,E29)) | F30: =IFERROR(VLOOKUP($A30&"="&$B30,Results_30d_Deltas!$A$2:$H$5000,5,FALSE),"") | G30: =IFERROR(VLOOKUP($A30,Results_30d_Deltas!$A$2:$H$5000,7,FALSE)-E29,"") | H30: =IFERROR(VLOOKUP($A30,Results_30d_Deltas!$A$2:$H$5000,6,FALSE),"") | K30: =IF(B30=C30,"YES","NO") | IJ30: ez_manage.py:3566 top() | IK30: v12_quick_engine.py:2344 x8
A31: MI_STRUCT_EXIT_ENABLED | B31: True | E31: =IF(F31="",E30,IF(F31>0,E30+F31,E30)) | F31: -2.4538266 | G31: -4.1099804 | H31: =IFERROR(VLOOKUP($A31,Results_30d_Deltas!$A$2:$H$5000,6,FALSE),"") | K31: =IF(B31=C31,"YES","NO") | IJ31: ez_manage.py:3566 top() | IK31: v12_quick_engine.py:2344 x8
A32: MI_VELOCITY_EXIT_ENABLED | B32: False | E32: =IF(F32="",E31,IF(F32>0,E31+F32,E31)) | F32: =IFERROR(VLOOKUP($A32&"="&$B32,Results_30d_Deltas!$A$2:$H$5000,5,FALSE),"") | G32: =IFERROR(VLOOKUP($A32,Results_30d_Deltas!$A$2:$H$5000,7,FALSE)-E31,"") | H32: =IFERROR(VLOOKUP($A32,Results_30d_Deltas!$A$2:$H$5000,6,FALSE),"") | K32: =IF(B32=C32,"YES","NO") | IJ32: ez_manage.py:3568 top() | IK32: v12_quick_engine.py:2347 x8
A33: MI_VELOCITY_EXIT_ENABLED | B33: True | E33: =IF(F33="",E32,IF(F33>0,E32+F33,E32)) | F33: -1.7345709 | G33: -3.3907247 | H33: =IFERROR(VLOOKUP($A33,Results_30d_Deltas!$A$2:$H$5000,6,FALSE),"") | K33: =IF(B33=C33,"YES","NO") | IJ33: ez_manage.py:3568 top() | IK33: v12_quick_engine.py:2347 x8
A34: MI_WAVE_EXIT_ENABLED | B34: False | E34: =IF(F34="",E33,IF(F34>0,E33+F34,E33)) | F34: =IFERROR(VLOOKUP($A34&"="&$B34,Results_30d_Deltas!$A$2:$H$5000,5,FALSE),"") | G34: =IFERROR(VLOOKUP($A34,Results_30d_Deltas!$A$2:$H$5000,7,FALSE)-E33,"") | H34: =IFERROR(VLOOKUP($A34,Results_30d_Deltas!$A$2:$H$5000,6,FALSE),"") | K34: =IF(B34=C34,"YES","NO") | IJ34: ez_manage.py:3569 top() | IK34: v12_quick_engine.py:2349 x8
A35: MI_WAVE_EXIT_ENABLED | B35: True | E35: =IF(F35="",E34,IF(F35>0,E34+F35,E34)) | F35: -2.471381 | G35: -4.1275348 | H35: =IFERROR(VLOOKUP($A35,Results_30d_Deltas!$A$2:$H$5000,6,FALSE),"") | K35: =IF(B35=C35,"YES","NO") | IJ35: ez_manage.py:3569 top() | IK35: v12_quick_engine.py:2349 x8
A36: MU_CORRECTION_EXIT_ENABLED | B36: False | E36: =IF(F36="",E35,IF(F36>0,E35+F36,E35)) | F36: =IFERROR(VLOOKUP($A36&"="&$B36,Results_30d_Deltas!$A$2:$H$5000,5,FALSE),"") | G36: =IFERROR(VLOOKUP($A36,Results_30d_Deltas!$A$2:$H$5000,7,FALSE)-E35,"") | H36: =IFERROR(VLOOKUP($A36,Results_30d_Deltas!$A$2:$H$5000,6,FALSE),"") | K36: =IF(B36=C36,"YES","NO") | IJ36: ez_manage.py:5068 top() | IK36: v12_quick_engine.py:2454 x3
A37: MU_CORRECTION_EXIT_ENABLED | B37: True | E37: =IF(F37="",E36,IF(F37>0,E36+F37,E36)) | F37: 0 | G37: -1.6561539 | H37: =IFERROR(VLOOKUP($A37,Results_30d_Deltas!$A$2:$H$5000,6,FALSE),"") | K37: =IF(B37=C37,"YES","NO") | IJ37: ez_manage.py:5068 top() | IK37: v12_quick_engine.py:2454 x3
A38: RULE_B_3M_EXIT_ENABLED | B38: False | E38: =IF(F38="",E37,IF(F38>0,E37+F38,E37)) | F38: =IFERROR(VLOOKUP($A38&"="&$B38,Results_30d_Deltas!$A$2:$H$5000,5,FALSE),"") | G38: =IFERROR(VLOOKUP($A38,Results_30d_Deltas!$A$2:$H$5000,7,FALSE)-E37,"") | H38: =IFERROR(VLOOKUP($A38,Results_30d_Deltas!$A$2:$H$5000,6,FALSE),"") | K38: =IF(B38=C38,"YES","NO") | IJ38: ez_manage.py:5395 top() | IK38: v12_quick_engine.py:3009 x4
A39: RULE_B_3M_EXIT_ENABLED | B39: True | E39: =IF(F39="",E38,IF(F39>0,E38+F39,E38)) | F39: 0 | G39: -1.6561539 | H39: =IFERROR(VLOOKUP($A39,Results_30d_Deltas!$A$2:$H$5000,6,FALSE),"") | K39: =IF(B39=C39,"YES","NO") | IJ39: ez_manage.py:5395 top() | IK39: v12_quick_engine.py:3009 x4
A40: SCALP_V3_K_OB_EXIT_ENABLED | B40: False | E40: =IF(F40="",E39,IF(F40>0,E39+F40,E39)) | F40: =IFERROR(VLOOKUP($A40&"="&$B40,Results_30d_Deltas!$A$2:$H$5000,5,FALSE),"") | G40: =IFERROR(VLOOKUP($A40,Results_30d_Deltas!$A$2:$H$5000,7,FALSE)-E39,"") | H40: =IFERROR(VLOOKUP($A40,Results_30d_Deltas!$A$2:$H$5000,6,FALSE),"") | K40: =IF(B40=C40,"YES","NO") | IJ40: ez_manage.py:5550 top() | IK40: v12_quick_engine.py:3178 x4
A41: SCALP_V3_K_OB_EXIT_ENABLED | B41: True | E41: =IF(F41="",E40,IF(F41>0,E40+F41,E40)) | F41: 0 | G41: -1.6561539 | H41: =IFERROR(VLOOKUP($A41,Results_30d_Deltas!$A$2:$H$5000,6,FALSE),"") | K41: =IF(B41=C41,"YES","NO") | IJ41: ez_manage.py:5550 top() | IK41: v12_quick_engine.py:3178 x4
A42: SCALP_V3_PROTECTIVE_EXIT_ENABLED | B42: False | E42: =IF(F42="",E41,IF(F42>0,E41+F42,E41)) | F42: =IFERROR(VLOOKUP($A42&"="&$B42,Results_30d_Deltas!$A$2:$H$5000,5,FALSE),"") | G42: =IFERROR(VLOOKUP($A42,Results_30d_Deltas!$A$2:$H$5000,7,FALSE)-E41,"") | H42: =IFERROR(VLOOKUP($A42,Results_30d_Deltas!$A$2:$H$5000,6,FALSE),"") | K42: =IF(B42=C42,"YES","NO") | IJ42: ez_manage.py:5586 top() | IK42: v12_quick_engine.py:3192 x4
A43: SCALP_V3_PROTECTIVE_EXIT_ENABLED | B43: True | E43: =IF(F43="",E42,IF(F43>0,E42+F43,E42)) | F43: 0 | G43: -1.6561539 | H43: =IFERROR(VLOOKUP($A43,Results_30d_Deltas!$A$2:$H$5000,6,FALSE),"") | K43: =IF(B43=C43,"YES","NO") | IJ43: ez_manage.py:5586 top() | IK43: v12_quick_engine.py:3192 x4
A44: STDEV_REJECT_EXIT_TF | B44: OFF | E44: =IF(F44="",E43,IF(F44>0,E43+F44,E43)) | F44: -1.7073607 | G44: -3.3635146 | H44: =IFERROR(VLOOKUP($A44,Results_30d_Deltas!$A$2:$H$5000,6,FALSE),"") | K44: =IF(B44=C44,"YES","NO") | IJ44: ez_manage.py:4058 top() | IK44: v12_quick_engine.py:3298 x3
A45: STDEV_REJECT_EXIT_TF | B45: D | E45: =IF(F45="",E44,IF(F45>0,E44+F45,E44)) | F45: 0 | G45: -1.6561539 | H45: =IFERROR(VLOOKUP($A45,Results_30d_Deltas!$A$2:$H$5000,6,FALSE),"") | K45: =IF(B45=C45,"YES","NO") | IJ45: ez_manage.py:4058 top() | IK45: v12_quick_engine.py:3298 x3
A46: STDEV_REJECT_EXIT_TF | B46: 4h | E46: =IF(F46="",E45,IF(F46>0,E45+F46,E45)) | F46: 0 | G46: -1.6561539 | H46: =IFERROR(VLOOKUP($A46,Results_30d_Deltas!$A$2:$H$5000,6,FALSE),"") | K46: =IF(B46=C46,"YES","NO") | IJ46: ez_manage.py:4058 top() | IK46: v12_quick_engine.py:3298 x3
A47: STDEV_REJECT_EXIT_TF | B47: 1h | E47: =IF(F47="",E46,IF(F47>0,E46+F47,E46)) | F47: -1.7240473 | G47: -3.3802012 | H47: =IFERROR(VLOOKUP($A47,Results_30d_Deltas!$A$2:$H$5000,6,FALSE),"") | K47: =IF(B47=C47,"YES","NO") | IJ47: ez_manage.py:4058 top() | IK47: v12_quick_engine.py:3298 x3
A48: STDEV_REJECT_EXIT_TF | B48: 15m | E48: =IF(F48="",E47,IF(F48>0,E47+F48,E47)) | F48: =IFERROR(VLOOKUP($A48&"="&$B48,Results_30d_Deltas!$A$2:$H$5000,5,FALSE),"") | G48: =IFERROR(VLOOKUP($A48,Results_30d_Deltas!$A$2:$H$5000,7,FALSE)-E47,"") | H48: =IFERROR(VLOOKUP($A48,Results_30d_Deltas!$A$2:$H$5000,6,FALSE),"") | K48: =IF(B48=C48,"YES","NO") | IJ48: ez_manage.py:4058 top() | IK48: v12_quick_engine.py:3298 x3
A49: TREND_EXIT_SCORE_FLIP | B49: 0 | E49: =IF(F49="",E48,IF(F49>0,E48+F49,E48)) | F49: -1.8787217 | G49: -3.5348756 | H49: =IFERROR(VLOOKUP($A49,Results_30d_Deltas!$A$2:$H$5000,6,FALSE),"") | K49: =IF(B49=C49,"YES","NO") | IJ49: ez_manage.py:4200 top() | IK49: v12_quick_engine.py:3540 x2
A50: TREND_EXIT_SCORE_FLIP | B50: 0.5 | E50: =IF(F50="",E49,IF(F50>0,E49+F50,E49)) | F50: 0 | G50: -1.6561539 | H50: =IFERROR(VLOOKUP($A50,Results_30d_Deltas!$A$2:$H$5000,6,FALSE),"") | K50: =IF(B50=C50,"YES","NO") | IJ50: ez_manage.py:4200 top() | IK50: v12_quick_engine.py:3540 x2
A51: TREND_EXIT_SCORE_FLIP | B51: 1.0 | E51: =IF(F51="",E50,IF(F51>0,E50+F51,E50)) | F51: 0 | G51: -1.6561539 | H51: =IFERROR(VLOOKUP($A51,Results_30d_Deltas!$A$2:$H$5000,6,FALSE),"") | K51: =IF(B51=C51,"YES","NO") | IJ51: ez_manage.py:4200 top() | IK51: v12_quick_engine.py:3540 x2
A52: TREND_EXIT_SCORE_FLIP | B52: 2.0 | E52: =IF(F52="",E51,IF(F52>0,E51+F52,E51)) | F52: -1.8934256 | G52: -3.5495795 | H52: =IFERROR(VLOOKUP($A52,Results_30d_Deltas!$A$2:$H$5000,6,FALSE),"") | K52: =IF(B52=C52,"YES","NO") | IJ52: ez_manage.py:4200 top() | IK52: v12_quick_engine.py:3540 x2
A53: WT_4H_VEL_EXIT_ENABLED | B53: False | E53: =IF(F53="",E52,IF(F53>0,E52+F53,E52)) | F53: =IFERROR(VLOOKUP($A53&"="&$B53,Results_30d_Deltas!$A$2:$H$5000,5,FALSE),"") | G53: =IFERROR(VLOOKUP($A53,Results_30d_Deltas!$A$2:$H$5000,7,FALSE)-E52,"") | H53: =IFERROR(VLOOKUP($A53,Results_30d_Deltas!$A$2:$H$5000,6,FALSE),"") | K53: =IF(B53=C53,"YES","NO") | IJ53: ez_manage.py:5876 top() | IK53: v12_quick_engine.py:3695 x5
A54: WT_4H_VEL_EXIT_ENABLED | B54: True | E54: =IF(F54="",E53,IF(F54>0,E53+F54,E53)) | F54: -1.7240473 | G54: -3.3802012 | H54: =IFERROR(VLOOKUP($A54,Results_30d_Deltas!$A$2:$H$5000,6,FALSE),"") | K54: =IF(B54=C54,"YES","NO") | IJ54: ez_manage.py:5876 top() | IK54: v12_quick_engine.py:3695 x5
A55: WT_4H_VEL_EXIT_K_EXTREME_HIGH | B55: 0 | E55: =IF(F55="",E54,IF(F55>0,E54+F55,E54)) | F55: -1.8542583 | G55: -3.5104122 | H55: =IFERROR(VLOOKUP($A55,Results_30d_Deltas!$A$2:$H$5000,6,FALSE),"") | K55: =IF(B55=C55,"YES","NO") | IJ55: ez_manage.py:5877 top() | IK55: v12_quick_engine.py:3696 x5
A56: WT_4H_VEL_EXIT_K_EXTREME_HIGH | B56: 0.5 | E56: =IF(F56="",E55,IF(F56>0,E55+F56,E55)) | F56: 0 | G56: -1.6561539 | H56: =IFERROR(VLOOKUP($A56,Results_30d_Deltas!$A$2:$H$5000,6,FALSE),"") | K56: =IF(B56=C56,"YES","NO") | IJ56: ez_manage.py:5877 top() | IK56: v12_quick_engine.py:3696 x5
A57: WT_4H_VEL_EXIT_K_EXTREME_HIGH | B57: 1.0 | E57: =IF(F57="",E56,IF(F57>0,E56+F57,E56)) | F57: 0 | G57: -1.6561539 | H57: =IFERROR(VLOOKUP($A57,Results_30d_Deltas!$A$2:$H$5000,6,FALSE),"") | K57: =IF(B57=C57,"YES","NO") | IJ57: ez_manage.py:5877 top() | IK57: v12_quick_engine.py:3696 x5
A58: WT_4H_VEL_EXIT_K_EXTREME_HIGH | B58: 2.0 | E58: =IF(F58="",E57,IF(F58>0,E57+F58,E57)) | F58: -1.7345709 | G58: -3.3907247 | H58: =IFERROR(VLOOKUP($A58,Results_30d_Deltas!$A$2:$H$5000,6,FALSE),"") | K58: =IF(B58=C58,"YES","NO") | IJ58: ez_manage.py:5877 top() | IK58: v12_quick_engine.py:3696 x5
A59: WT_4H_VEL_EXIT_K_EXTREME_LOW | B59: 0 | E59: =IF(F59="",E58,IF(F59>0,E58+F59,E58)) | F59: -1.7073607 | G59: -3.3635146 | H59: =IFERROR(VLOOKUP($A59,Results_30d_Deltas!$A$2:$H$5000,6,FALSE),"") | K59: =IF(B59=C59,"YES","NO") | IJ59: ez_manage.py:5878 top() | IK59: v12_quick_engine.py:3697 x5
A60: WT_4H_VEL_EXIT_K_EXTREME_LOW | B60: 0.5 | E60: =IF(F60="",E59,IF(F60>0,E59+F60,E59)) | F60: -0.15388231 | G60: -1.8100362 | H60: =IFERROR(VLOOKUP($A60,Results_30d_Deltas!$A$2:$H$5000,6,FALSE),"") | K60: =IF(B60=C60,"YES","NO") | IJ60: ez_manage.py:5878 top() | IK60: v12_quick_engine.py:3697 x5
A61: WT_4H_VEL_EXIT_K_EXTREME_LOW | B61: 1.0 | E61: =IF(F61="",E60,IF(F61>0,E60+F61,E60)) | F61: -0.15388231 | G61: -1.8100362 | H61: =IFERROR(VLOOKUP($A61,Results_30d_Deltas!$A$2:$H$5000,6,FALSE),"") | K61: =IF(B61=C61,"YES","NO") | IJ61: ez_manage.py:5878 top() | IK61: v12_quick_engine.py:3697 x5
A62: WT_4H_VEL_EXIT_K_EXTREME_LOW | B62: 2.0 | E62: =IF(F62="",E61,IF(F62>0,E61+F62,E61)) | F62: -2.0610562 | G62: -3.7172101 | H62: =IFERROR(VLOOKUP($A62,Results_30d_Deltas!$A$2:$H$5000,6,FALSE),"") | K62: =IF(B62=C62,"YES","NO") | IJ62: ez_manage.py:5878 top() | IK62: v12_quick_engine.py:3697 x5
A63: WT_4H_VEL_EXIT_REQUIRE_K_EXTREME | B63: 0 | E63: =IF(F63="",E62,IF(F63>0,E62+F63,E62)) | F63: 0 | G63: -1.6561539 | H63: =IFERROR(VLOOKUP($A63,Results_30d_Deltas!$A$2:$H$5000,6,FALSE),"") | K63: =IF(B63=C63,"YES","NO") | IJ63: ez_manage.py:5880 top() | IK63: v12_quick_engine.py:3699 x5
A64: WT_4H_VEL_EXIT_REQUIRE_K_EXTREME | B64: 0.5 | E64: =IF(F64="",E63,IF(F64>0,E63+F64,E63)) | F64: -2.4538266 | G64: -4.1099804 | H64: =IFERROR(VLOOKUP($A64,Results_30d_Deltas!$A$2:$H$5000,6,FALSE),"") | K64: =IF(B64=C64,"YES","NO") | IJ64: ez_manage.py:5880 top() | IK64: v12_quick_engine.py:3699 x5
A65: WT_4H_VEL_EXIT_REQUIRE_K_EXTREME | B65: 1.0 | E65: =IF(F65="",E64,IF(F65>0,E64+F65,E64)) | F65: -1.7240473 | G65: -3.3802012 | H65: =IFERROR(VLOOKUP($A65,Results_30d_Deltas!$A$2:$H$5000,6,FALSE),"") | K65: =IF(B65=C65,"YES","NO") | IJ65: ez_manage.py:5880 top() | IK65: v12_quick_engine.py:3699 x5
... A82: WT_CROSS_EXIT_REQUIRE_15M_CONFIRM | B82: 2.0 | E82: =IF(F82="",E81,IF(F82>0,E81+F82,E81)) | F82: -0.15388231 | G82: -1.8100362 | H82: =IFERROR(VLOOKUP($A82,Results_30d_Deltas!$A$2:$H$5000,6,FALSE),"") | K82: =IF(B82=C82,"YES","NO") | IJ82: ez_manage.py:5904 top() | IK82: v12_quick_engine.py:3725 x5

Sheet REENTRY_WINDOWED
A1: 06 REENTRY_WINDOWED - 68 bases -> 249 rows - 231 per-row FULLY CONNECTED
A2: Switch | B2: default | C2: override | D2: Family | E2: BASELINE | F2: VECTOR_DELTA | G2: LIVE_DELTA | H2: LIVE_SHARPE | I2: REAL_COMPLETE | J2: PER_ROW_FILTERS | K2: is_default (backup if bold lost) | L2: ATR_TRAIL_FILTER_TF=OFF | M2: ATR_TRAIL_FILTER_TF=D | N2: ATR_TRAIL_FILTER_TF=4h | O2: ATR_TRAIL_FILTER_TF=1h | P2: ATR_TRAIL_FILTER_TF=15m | Q2: BAR_PATTERNS_FILTER_TF=OFF | R2: BAR_PATTERNS_FILTER_TF=D | S2: BAR_PATTERNS_FILTER_TF=4h | T2: BAR_PATTERNS_FILTER_TF=1h | U2: BAR_PATTERNS_FILTER_TF=15m | V2: BB_PULLBACK_GATE_FILTER_TF=OFF | W2: BB_PULLBACK_GATE_FILTER_TF=D | X2: BB_PULLBACK_GATE_FILTER_TF=4h | Y2: BB_PULLBACK_GATE_FILTER_TF=1h | Z2: BB_PULLBACK_GATE_FILTER_TF=15m | AA2: BB_RECOVERY_ENTRY_FILTER_TF=OFF | AB2: BB_RECOVERY_ENTRY_FILTER_TF=D | AC2: BB_RECOVERY_ENTRY_FILTER_TF=4h | AD2: BB_RECOVERY_ENTRY_FILTER_TF=1h | AE2: BB_RECOVERY_ENTRY_FILTER_TF=15m | AF2: BB_RECOVERY_FILTER_TF=OFF | AG2: BB_RECOVERY_FILTER_TF=D | AH2: BB_RECOVERY_FILTER_TF=4h | AI2: BB_RECOVERY_FILTER_TF=1h | AJ2: BB_RECOVERY_FILTER_TF=15m | AK2: BREAKEVEN_GAIN_EROSION_FILTER_TF=OFF | AL2: BREAKEVEN_GAIN_EROSION_FILTER_TF=D | AM2: BREAKEVEN_GAIN_EROSION_FILTER_TF=4h | AN2: BREAKEVEN_GAIN_EROSION_FILTER_TF=1h | AO2: BREAKEVEN_GAIN_EROSION_FILTER_TF=15m | AP2: BREAKOUT_RETEST_FILTER_TF=OFF | AQ2: BREAKOUT_RETEST_FILTER_TF=D | AR2: BREAKOUT_RETEST_FILTER_TF=4h | AS2: BREAKOUT_RETEST_FILTER_TF=1h | AT2: BREAKOUT_RETEST_FILTER_TF=15m | AU2: BT_WT_CROSS_LADDER_FILTER_TF=OFF | AV2: BT_WT_CROSS_LADDER_FILTER_TF=D | AW2: BT_WT_CROSS_LADDER_FILTER_TF=4h | AX2: BT_WT_CROSS_LADDER_FILTER_TF=1h | AY2: BT_WT_CROSS_LADDER_FILTER_TF=15m | AZ2: CANDLE_PATTERN_STOPS_FILTER_TF=OFF | BA2: CANDLE_PATTERN_STOPS_FILTER_TF=D | BB2: CANDLE_PATTERN_STOPS_FILTER_TF=4h | BC2: CANDLE_PATTERN_STOPS_FILTER_TF=1h | BD2: CANDLE_PATTERN_STOPS_FILTER_TF=15m | BE2: CIRCUIT_SHARPE_GATES_FILTER_TF=OFF | BF2: CIRCUIT_SHARPE_GATES_FILTER_TF=D | BG2: CIRCUIT_SHARPE_GATES_FILTER_TF=4h | BH2: CIRCUIT_SHARPE_GATES_FILTER_TF=1h | BI2: CIRCUIT_SHARPE_GATES_FILTER_TF=15m | BJ2: DC_BREACH_REDUCE_FILTER_TF=OFF | BK2: DC_BREACH_REDUCE_FILTER_TF=D | BL2: DC_BREACH_REDUCE_FILTER_TF=4h | BM2: DC_BREACH_REDUCE_FILTER_TF=1h | BN2: DC_BREACH_REDUCE_FILTER_TF=15m | BO2: DC_BREAK_FILTER_TF=OFF | BP2: DC_BREAK_FILTER_TF=D | BQ2: DC_BREAK_FILTER_TF=4h | BR2: DC_BREAK_FILTER_TF=1h | BS2: DC_BREAK_FILTER_TF=15m | BT2: DC_MOMENTUM_BOTA_SCORER_FILTER_TF=OFF | BU2: DC_MOMENTUM_BOTA_SCORER_FILTER_TF=D | BV2: DC_MOMENTUM_BOTA_SCORER_FILTER_TF=4h | BW2: DC_MOMENTUM_BOTA_SCORER_FILTER_TF=1h | BX2: DC_MOMENTUM_BOTA_SCORER_FILTER_TF=15m | BY2: DELTA_ENGINE_FILTER_TF=OFF | BZ2: DELTA_ENGINE_FILTER_TF=D | CA2: DELTA_ENGINE_FILTER_TF=4h | CB2: DELTA_ENGINE_FILTER_TF=1h | CC2: DELTA_ENGINE_FILTER_TF=15m | CD2: EMA_9_21_FILTER_FILTER_TF=OFF | CE2: EMA_9_21_FILTER_FILTER_TF=D | CF2: EMA_9_21_FILTER_FILTER_TF=4h | CG2: EMA_9_21_FILTER_FILTER_TF=1h | CH2: EMA_9_21_FILTER_FILTER_TF=15m | CI2: EMA_BLANKET_FILTER_FILTER_TF=OFF | CJ2: EMA_BLANKET_FILTER_FILTER_TF=D | CK2: EMA_BLANKET_FILTER_FILTER_TF=4h | CL2: EMA_BLANKET_FILTER_FILTER_TF=1h | CM2: EMA_BLANKET_FILTER_FILTER_TF=15m | CN2: EMERGENCY_BRAKE_FILTER_TF=OFF | CO2: EMERGENCY_BRAKE_FILTER_TF=D | CP2: EMERGENCY_BRAKE_FILTER_TF=4h | CQ2: EMERGENCY_BRAKE_FILTER_TF=1h | CR2: EMERGENCY_BRAKE_FILTER_TF=15m | CS2: EXIT_R1_R2_FILTER_TF=OFF | CT2: EXIT_R1_R2_FILTER_TF=D | CU2: EXIT_R1_R2_FILTER_TF=4h | CV2: EXIT_R1_R2_FILTER_TF=1h | CW2: EXIT_R1_R2_FILTER_TF=15m | CX2: EXIT_TIGHT_BREAKOUT_SCORER_FILTER_TF=OFF | CY2: EXIT_TIGHT_BREAKOUT_SCORER_FILTER_TF=D | CZ2: EXIT_TIGHT_BREAKOUT_SCORER_FILTER_TF=4h | DA2: EXIT_TIGHT_BREAKOUT_SCORER_FILTER_TF=1h | DB2: EXIT_TIGHT_BREAKOUT_SCORER_FILTER_TF=15m | DC2: EXIT_TOP_FADE_FILTER_TF=OFF | DD2: EXIT_TOP_FADE_FILTER_TF=D | DE2: EXIT_TOP_FADE_FILTER_TF=4h | DF2: EXIT_TOP_FADE_FILTER_TF=1h | DG2: EXIT_TOP_FADE_FILTER_TF=15m | DH2: EXIT_TO_REDUCE_ADAPTER_FILTER_TF=OFF | DI2: EXIT_TO_REDUCE_ADAPTER_FILTER_TF=D | DJ2: EXIT_TO_REDUCE_ADAPTER_FILTER_TF=4h | DK2: EXIT_TO_REDUCE_ADAPTER_FILTER_TF=1h | DL2: EXIT_TO_REDUCE_ADAPTER_FILTER_TF=15m | DM2: FAST_RISER_FILTER_TF=OFF | DN2: FAST_RISER_FILTER_TF=D | DO2: FAST_RISER_FILTER_TF=4h | DP2: FAST_RISER_FILTER_TF=1h | DQ2: FAST_RISER_FILTER_TF=15m | DR2: FH_MOMENTUM_FILTER_TF=OFF | DS2: FH_MOMENTUM_FILTER_TF=D | DT2: FH_MOMENTUM_FILTER_TF=4h | DU2: FH_MOMENTUM_FILTER_TF=1h | DV2: FH_MOMENTUM_FILTER_TF=15m | DW2: FIRST_OPEN_THROTTLE_FILTER_TF=OFF | DX2: FIRST_OPEN_THROTTLE_FILTER_TF=D | DY2: FIRST_OPEN_THROTTLE_FILTER_TF=4h | DZ2: FIRST_OPEN_THROTTLE_FILTER_TF=1h | EA2: FIRST_OPEN_THROTTLE_FILTER_TF=15m | EB2: FROZEN_STOP_FILTER_TF=OFF | EC2: FROZEN_STOP_FILTER_TF=D | ED2: FROZEN_STOP_FILTER_TF=4h | EE2: FROZEN_STOP_FILTER_TF=1h | EF2: FROZEN_STOP_FILTER_TF=15m | EG2: GOLDEN_RULE_ENFORCE_FILTER_TF=OFF | EH2: GOLDEN_RULE_ENFORCE_FILTER_TF=D | EI2: GOLDEN_RULE_ENFORCE_FILTER_TF=4h | EJ2: GOLDEN_RULE_ENFORCE_FILTER_TF=1h | EK2: GOLDEN_RULE_ENFORCE_FILTER_TF=15m | EL2: GOLDEN_RULE_HTF_VOTE_FILTER_TF=OFF | EM2: GOLDEN_RULE_HTF_VOTE_FILTER_TF=D | EN2: GOLDEN_RULE_HTF_VOTE_FILTER_TF=4h | EO2: GOLDEN_RULE_HTF_VOTE_FILTER_TF=1h | EP2: GOLDEN_RULE_HTF_VOTE_FILTER_TF=15m | EQ2: GR_FILTER_VEC_FILTER_TF=OFF | ER2: GR_FILTER_VEC_FILTER_TF=D | ES2: GR_FILTER_VEC_FILTER_TF=4h | ET2: GR_FILTER_VEC_FILTER_TF=1h | EU2: GR_FILTER_VEC_FILTER_TF=15m | EV2: GR_V5_STATE_FILTER_TF=OFF | EW2: GR_V5_STATE_FILTER_TF=D | EX2: GR_V5_STATE_FILTER_TF=4h | EY2: GR_V5_STATE_FILTER_TF=1h | EZ2: GR_V5_STATE_FILTER_TF=15m | FA2: HAIKU_WINNER_FILTER_TF=OFF | FB2: HAIKU_WINNER_FILTER_TF=D | FC2: HAIKU_WINNER_FILTER_TF=4h | FD2: HAIKU_WINNER_FILTER_TF=1h | FE2: HAIKU_WINNER_FILTER_TF=15m | FF2: LH_HL_FILTER_TF_REQ=2 | FG2: LH_HL_FILTER_TF_REQ=2_ALT | FH2: LIVE_ENTRY_ENGINE_FILTER_TF=OFF | FI2: LIVE_ENTRY_ENGINE_FILTER_TF=D | FJ2: LIVE_ENTRY_ENGINE_FILTER_TF=4h | FK2: LIVE_ENTRY_ENGINE_FILTER_TF=1h | FL2: LIVE_ENTRY_ENGINE_FILTER_TF=15m | FM2: LIVE_ONLY_SIGNALS_BATCH5_FILTER_TF=OFF | FN2: LIVE_ONLY_SIGNALS_BATCH5_FILTER_TF=D | FO2: LIVE_ONLY_SIGNALS_BATCH5_FILTER_TF=4h | FP2: LIVE_ONLY_SIGNALS_BATCH5_FILTER_TF=1h | FQ2: LIVE_ONLY_SIGNALS_BATCH5_FILTER_TF=15m | FR2: MANDATORY_REENTRY_WT_FILTER_TF_MODE=15m_only | FS2: MANDATORY_REENTRY_WT_FILTER_TF_MODE=15m_only_ALT | FT2: MOM3_FILTER_TF=OFF | FU2: MOM3_FILTER_TF=D | FV2: MOM3_FILTER_TF=4h | FW2: MOM3_FILTER_TF=1h | FX2: MOM3_FILTER_TF=15m | FY2: MOMENTUM_BREAKOUT_FILTER_TF=OFF | FZ2: MOMENTUM_BREAKOUT_FILTER_TF=D | GA2: MOMENTUM_BREAKOUT_FILTER_TF=4h | GB2: MOMENTUM_BREAKOUT_FILTER_TF=1h | GC2: MOMENTUM_BREAKOUT_FILTER_TF=15m | GD2: MTF_ARMED_ENTRIES_FILTER_TF=OFF | GE2: MTF_ARMED_ENTRIES_FILTER_TF=D | GF2: MTF_ARMED_ENTRIES_FILTER_TF=4h | GG2: MTF_ARMED_ENTRIES_FILTER_TF=1h | GH2: MTF_ARMED_ENTRIES_FILTER_TF=15m | GI2: MTF_ATR_TRAIL_FILTER_TF=OFF | GJ2: MTF_ATR_TRAIL_FILTER_TF=D | GK2: MTF_ATR_TRAIL_FILTER_TF=4h | GL2: MTF_ATR_TRAIL_FILTER_TF=1h | GM2: MTF_ATR_TRAIL_FILTER_TF=15m | GN2: MTF_DC_REJECT_FILTER_TF=OFF | GO2: MTF_DC_REJECT_FILTER_TF=D | GP2: MTF_DC_REJECT_FILTER_TF=4h | GQ2: MTF_DC_REJECT_FILTER_TF=1h | GR2: MTF_DC_REJECT_FILTER_TF=15m | GS2: NEWBORN_LOSS_KILL_FILTER_TF=OFF | GT2: NEWBORN_LOSS_KILL_FILTER_TF=D | GU2: NEWBORN_LOSS_KILL_FILTER_TF=4h | GV2: NEWBORN_LOSS_KILL_FILTER_TF=1h | GW2: NEWBORN_LOSS_KILL_FILTER_TF=15m | GX2: NEWBORN_PROTECT_FILTER_TF=OFF | GY2: NEWBORN_PROTECT_FILTER_TF=D | GZ2: NEWBORN_PROTECT_FILTER_TF=4h | HA2: NEWBORN_PROTECT_FILTER_TF=1h | HB2: NEWBORN_PROTECT_FILTER_TF=15m | HC2: NOLOSS_BYPASS_WT5OF5_FILTER_TF=OFF | HD2: NOLOSS_BYPASS_WT5OF5_FILTER_TF=D | HE2: NOLOSS_BYPASS_WT5OF5_FILTER_TF=4h | HF2: NOLOSS_BYPASS_WT5OF5_FILTER_TF=1h | HG2: NOLOSS_BYPASS_WT5OF5_FILTER_TF=15m | HH2: OPEN_INTENT_SIZE_GATES_FILTER_TF=OFF | HI2: OPEN_INTENT_SIZE_GATES_FILTER_TF=D | HJ2: OPEN_INTENT_SIZE_GATES_FILTER_TF=4h | HK2: OPEN_INTENT_SIZE_GATES_FILTER_TF=1h | HL2: OPEN_INTENT_SIZE_GATES_FILTER_TF=15m | HM2: PARTIAL_PROFIT_LOCK_V2_FILTER_TF=OFF | HN2: PARTIAL_PROFIT_LOCK_V2_FILTER_TF=D | HO2: PARTIAL_PROFIT_LOCK_V2_FILTER_TF=4h | HP2: PARTIAL_PROFIT_LOCK_V2_FILTER_TF=1h | HQ2: PARTIAL_PROFIT_LOCK_V2_FILTER_TF=15m | HR2: PEAK_GIVEBACK_BE_EROSION_FILTER_TF=OFF | HS2: PEAK_GIVEBACK_BE_EROSION_FILTER_TF=D | HT2: PEAK_GIVEBACK_BE_EROSION_FILTER_TF=4h | HU2: PEAK_GIVEBACK_BE_EROSION_FILTER_TF=1h | HV2: PEAK_GIVEBACK_BE_EROSION_FILTER_TF=15m | HW2: WT_15M_BOUNCE_BB_MAX=0.95 | HX2: WT_15M_BOUNCE_BB_MAX=0.9 | HY2: WT_15M_BOUNCE_BB_MAX=0.8 | HZ2: WT_15M_BOUNCE_BB_MIN=0.05 | IA2: WT_15M_BOUNCE_BB_MIN=0.1 | IB2: WT_15M_BOUNCE_BB_MIN=0.2 | IC2: WT_15M_BOUNCE_HIGH_1H_GT_PREV=True | ID2: WT_15M_BOUNCE_HIGH_1H_GT_PREV=False | IE2: WT_15M_BOUNCE_LOW_1H_GT_PREV=True | IF2: WT_15M_BOUNCE_LOW_1H_GT_PREV=False | IG2: WT_15M_BOUNCE_REL_VOL_GT_1=True | IH2: WT_15M_BOUNCE_REL_VOL_GT_1=False | II2: Live Location | IJ2: Vec Hook | IK2: Type | IL2: Correct Options
A3: GUARANTEED_REENTRY_K_FAVORABLE_HIGH | B3: 35.0 | E3: =MAX('EXIT_VELOCITY'!E:E) | F3: 0 | G3: -1.6561539 | H3: =IFERROR(VLOOKUP($A3,Results_30d_Deltas!$A$2:$H$5000,6,FALSE),"") | K3: =IF(B3=C3,"YES","NO") | IJ3: ez_manage.py:4774 top() | IK3: v12_quick_engine.py:1941 x4
A4: GUARANTEED_REENTRY_K_FAVORABLE_HIGH | B4: 52.5 | E4: =IF(F4="",E3,IF(F4>0,E3+F4,E3)) | F4: 0 | G4: -1.6561539 | H4: =IFERROR(VLOOKUP($A4,Results_30d_Deltas!$A$2:$H$5000,6,FALSE),"") | K4: =IF(B4=C4,"YES","NO") | IJ4: ez_manage.py:4774 top() | IK4: v12_quick_engine.py:1941 x4
A5: GUARANTEED_REENTRY_K_FAVORABLE_HIGH | B5: 70.0 | E5: =IF(F5="",E4,IF(F5>0,E4+F5,E4)) | F5: -2.0610562 | G5: -3.7172101 | H5: =IFERROR(VLOOKUP($A5,Results_30d_Deltas!$A$2:$H$5000,6,FALSE),"") | K5: =IF(B5=C5,"YES","NO") | IJ5: ez_manage.py:4774 top() | IK5: v12_quick_engine.py:1941 x4
A6: GUARANTEED_REENTRY_K_FAVORABLE_HIGH | B6: 87.5 | E6: =IF(F6="",E5,IF(F6>0,E5+F6,E5)) | F6: 0 | G6: -1.6561539 | H6: =IFERROR(VLOOKUP($A6,Results_30d_Deltas!$A$2:$H$5000,6,FALSE),"") | K6: =IF(B6=C6,"YES","NO") | IJ6: ez_manage.py:4774 top() | IK6: v12_quick_engine.py:1941 x4
A7: GUARANTEED_REENTRY_K_FAVORABLE_HIGH | B7: 105.0 | E7: =IF(F7="",E6,IF(F7>0,E6+F7,E6)) | F7: 0 | G7: -1.6561539 | H7: =IFERROR(VLOOKUP($A7,Results_30d_Deltas!$A$2:$H$5000,6,FALSE),"") | K7: =IF(B7=C7,"YES","NO") | IJ7: ez_manage.py:4774 top() | IK7: v12_quick_engine.py:1941 x4
A8: GUARANTEED_REENTRY_K_FAVORABLE_LOW | B8: 15.0 | E8: =IF(F8="",E7,IF(F8>0,E7+F8,E7)) | F8: 0 | G8: -1.6561539 | H8: =IFERROR(VLOOKUP($A8,Results_30d_Deltas!$A$2:$H$5000,6,FALSE),"") | K8: =IF(B8=C8,"YES","NO") | IJ8: ez_manage.py:4775 top() | IK8: v12_quick_engine.py:1942 x4
A9: GUARANTEED_REENTRY_K_FAVORABLE_LOW | B9: 22.5 | E9: =IF(F9="",E8,IF(F9>0,E8+F9,E8)) | F9: -1.8542583 | G9: -3.5104122 | H9: =IFERROR(VLOOKUP($A9,Results_30d_Deltas!$A$2:$H$5000,6,FALSE),"") | K9: =IF(B9=C9,"YES","NO") | IJ9: ez_manage.py:4775 top() | IK9: v12_quick_engine.py:1942 x4
A10: GUARANTEED_REENTRY_K_FAVORABLE_LOW | B10: 30.0 | E10: =IF(F10="",E9,IF(F10>0,E9+F10,E9)) | F10: -1.8526111 | G10: -3.508765 | H10: =IFERROR(VLOOKUP($A10,Results_30d_Deltas!$A$2:$H$5000,6,FALSE),"") | K10: =IF(B10=C10,"YES","NO") | IJ10: ez_manage.py:4775 top() | IK10: v12_quick_engine.py:1942 x4
A11: GUARANTEED_REENTRY_K_FAVORABLE_LOW | B11: 37.5 | E11: =IF(F11="",E10,IF(F11>0,E10+F11,E10)) | F11: -1.8934256 | G11: -3.5495795 | H11: =IFERROR(VLOOKUP($A11,Results_30d_Deltas!$A$2:$H$5000,6,FALSE),"") | K11: =IF(B11=C11,"YES","NO") | IJ11: ez_manage.py:4775 top() | IK11: v12_quick_engine.py:1942 x4
A12: GUARANTEED_REENTRY_K_FAVORABLE_LOW | B12: 45.0 | E12: =IF(F12="",E11,IF(F12>0,E11+F12,E11)) | F12: -1.7240473 | G12: -3.3802012 | H12: =IFERROR(VLOOKUP($A12,Results_30d_Deltas!$A$2:$H$5000,6,FALSE),"") | K12: =IF(B12=C12,"YES","NO") | IJ12: ez_manage.py:4775 top() | IK12: v12_quick_engine.py:1942 x4
A13: BOUNCE_REENTRY_ENABLED | B13: False | E13: =IF(F13="",E12,IF(F13>0,E12+F13,E12)) | F13: =IFERROR(VLOOKUP($A13&"="&$B13,Results_30d_Deltas!$A$2:$H$5000,5,FALSE),"") | G13: =IFERROR(VLOOKUP($A13,Results_30d_Deltas!$A$2:$H$5000,7,FALSE)-E12,"") | H13: =IFERROR(VLOOKUP($A13,Results_30d_Deltas!$A$2:$H$5000,6,FALSE),"") | K13: =IF(B13=C13,"YES","NO") | IJ13: ez_manage.py:2985 top() | IK13: v12_quick_engine.py:315 x14
A14: BOUNCE_REENTRY_ENABLED | B14: True | E14: =IF(F14="",E13,IF(F14>0,E13+F14,E13)) | F14: 0 | G14: -1.6561539 | H14: =IFERROR(VLOOKUP($A14,Results_30d_Deltas!$A$2:$H$5000,6,FALSE),"") | K14: =IF(B14=C14,"YES","NO") | IJ14: ez_manage.py:2985 top() | IK14: v12_quick_engine.py:315 x14
A15: DELTA_EXIT_MANDATORY_REENTRY_ENABLED | B15: False | E15: =IF(F15="",E14,IF(F15>0,E14+F15,E14)) | F15: =IFERROR(VLOOKUP($A15&"="&$B15,Results_30d_Deltas!$A$2:$H$5000,5,FALSE),"") | G15: =IFERROR(VLOOKUP($A15,Results_30d_Deltas!$A$2:$H$5000,7,FALSE)-E14,"") | H15: =IFERROR(VLOOKUP($A15,Results_30d_Deltas!$A$2:$H$5000,6,FALSE),"") | K15: =IF(B15=C15,"YES","NO") | IJ15: ez_manage.py:5975 top() | IK15: v12_quick_engine.py:4235 x4
A16: DELTA_EXIT_MANDATORY_REENTRY_ENABLED | B16: True | E16: =IF(F16="",E15,IF(F16>0,E15+F16,E15)) | F16: -1.8136634 | G16: -3.4698173 | H16: =IFERROR(VLOOKUP($A16,Results_30d_Deltas!$A$2:$H$5000,6,FALSE),"") | K16: =IF(B16=C16,"YES","NO") | IJ16: ez_manage.py:5975 top() | IK16: v12_quick_engine.py:4235 x4
A17: BOUNCE_REENTRY_K_RESET_LONG | B17: 0 | E17: =IF(F17="",E16,IF(F17>0,E16+F17,E16)) | F17: -1.0393426 | G17: -2.6954965 | H17: =IFERROR(VLOOKUP($A17,Results_30d_Deltas!$A$2:$H$5000,6,FALSE),"") | K17: =IF(B17=C17,"YES","NO") | IJ17: ez_manage.py:2986 top() | IK17: v12_quick_engine.py:321 x13
A18: BOUNCE_REENTRY_K_RESET_LONG | B18: 0.5 | E18: =IF(F18="",E17,IF(F18>0,E17+F18,E17)) | F18: 0 | G18: -1.6561539 | H18: =IFERROR(VLOOKUP($A18,Results_30d_Deltas!$A$2:$H$5000,6,FALSE),"") | K18: =IF(B18=C18,"YES","NO") | IJ18: ez_manage.py:2986 top() | IK18: v12_quick_engine.py:321 x13
A19: BOUNCE_REENTRY_K_RESET_LONG | B19: 1.0 | E19: =IF(F19="",E18,IF(F19>0,E18+F19,E18)) | F19: 0 | G19: -1.6561539 | H19: =IFERROR(VLOOKUP($A19,Results_30d_Deltas!$A$2:$H$5000,6,FALSE),"") | K19: =IF(B19=C19,"YES","NO") | IJ19: ez_manage.py:2986 top() | IK19: v12_quick_engine.py:321 x13
A20: BOUNCE_REENTRY_K_RESET_LONG | B20: 2.0 | E20: =IF(F20="",E19,IF(F20>0,E19+F20,E19)) | F20: -1.8526111 | G20: -3.508765 | H20: =IFERROR(VLOOKUP($A20,Results_30d_Deltas!$A$2:$H$5000,6,FALSE),"") | K20: =IF(B20=C20,"YES","NO") | IJ20: ez_manage.py:2986 top() | IK20: v12_quick_engine.py:321 x13
A21: BOUNCE_REENTRY_K_RESET_SHORT | B21: 0 | E21: =IF(F21="",E20,IF(F21>0,E20+F21,E20)) | F21: -1.7240473 | G21: -3.3802012 | H21: =IFERROR(VLOOKUP($A21,Results_30d_Deltas!$A$2:$H$5000,6,FALSE),"") | K21: =IF(B21=C21,"YES","NO") | IJ21: ez_manage.py:2987 top() | IK21: v12_quick_engine.py:327 x13
A22: BOUNCE_REENTRY_K_RESET_SHORT | B22: 0.5 | E22: =IF(F22="",E21,IF(F22>0,E21+F22,E21)) | F22: 0 | G22: -1.6561539 | H22: =IFERROR(VLOOKUP($A22,Results_30d_Deltas!$A$2:$H$5000,6,FALSE),"") | K22: =IF(B22=C22,"YES","NO") | IJ22: ez_manage.py:2987 top() | IK22: v12_quick_engine.py:327 x13
A23: BOUNCE_REENTRY_K_RESET_SHORT | B23: 1.0 | E23: =IF(F23="",E22,IF(F23>0,E22+F23,E22)) | F23: 0 | G23: -1.6561539 | H23: =IFERROR(VLOOKUP($A23,Results_30d_Deltas!$A$2:$H$5000,6,FALSE),"") | K23: =IF(B23=C23,"YES","NO") | IJ23: ez_manage.py:2987 top() | IK23: v12_quick_engine.py:327 x13
A24: BOUNCE_REENTRY_K_RESET_SHORT | B24: 2.0 | E24: =IF(F24="",E23,IF(F24>0,E23+F24,E23)) | F24: -1.8136634 | G24: -3.4698173 | H24: =IFERROR(VLOOKUP($A24,Results_30d_Deltas!$A$2:$H$5000,6,FALSE),"") | K24: =IF(B24=C24,"YES","NO") | IJ24: ez_manage.py:2987 top() | IK24: v12_quick_engine.py:327 x13
A25: BTC_GUARANTEED_REENTRY_ENABLED | B25: False | E25: =IF(F25="",E24,IF(F25>0,E24+F25,E24)) | F25: =IFERROR(VLOOKUP($A25&"="&$B25,Results_30d_Deltas!$A$2:$H$5000,5,FALSE),"") | G25: =IFERROR(VLOOKUP($A25,Results_30d_Deltas!$A$2:$H$5000,7,FALSE)-E24,"") | H25: =IFERROR(VLOOKUP($A25,Results_30d_Deltas!$A$2:$H$5000,6,FALSE),"") | K25: =IF(B25=C25,"YES","NO") | IJ25: ez_manage.py:4470 top() | IK25: v12_quick_engine.py:415 x8
A26: BTC_GUARANTEED_REENTRY_ENABLED | B26: True | E26: =IF(F26="",E25,IF(F26>0,E25+F26,E25)) | F26: 0 | G26: -1.6561539 | H26: =IFERROR(VLOOKUP($A26,Results_30d_Deltas!$A$2:$H$5000,6,FALSE),"") | K26: =IF(B26=C26,"YES","NO") | IJ26: ez_manage.py:4470 top() | IK26: v12_quick_engine.py:415 x8
A27: BTC_GUARANTEED_REENTRY_MAX_AGE_BARS | B27: 0 | E27: =IF(F27="",E26,IF(F27>0,E26+F27,E26)) | F27: 0 | G27: -1.6561539 | H27: =IFERROR(VLOOKUP($A27,Results_30d_Deltas!$A$2:$H$5000,6,FALSE),"") | K27: =IF(B27=C27,"YES","NO") | IJ27: ez_manage.py:4471 top() | IK27: v12_quick_engine.py:422 x8
A28: BTC_GUARANTEED_REENTRY_MAX_AGE_BARS | B28: 0.5 | E28: =IF(F28="",E27,IF(F28>0,E27+F28,E27)) | F28: -1.7240473 | G28: -3.3802012 | H28: =IFERROR(VLOOKUP($A28,Results_30d_Deltas!$A$2:$H$5000,6,FALSE),"") | K28: =IF(B28=C28,"YES","NO") | IJ28: ez_manage.py:4471 top() | IK28: v12_quick_engine.py:422 x8
A29: BTC_GUARANTEED_REENTRY_MAX_AGE_BARS | B29: 1.0 | E29: =IF(F29="",E28,IF(F29>0,E28+F29,E28)) | F29: -2.0245238 | G29: -3.6806777 | H29: =IFERROR(VLOOKUP($A29,Results_30d_Deltas!$A$2:$H$5000,6,FALSE),"") | K29: =IF(B29=C29,"YES","NO") | IJ29: ez_manage.py:4471 top() | IK29: v12_quick_engine.py:422 x8
A30: BTC_GUARANTEED_REENTRY_MAX_AGE_BARS | B30: 2.0 | E30: =IF(F30="",E29,IF(F30>0,E29+F30,E29)) | F30: 0 | G30: -1.6561539 | H30: =IFERROR(VLOOKUP($A30,Results_30d_Deltas!$A$2:$H$5000,6,FALSE),"") | K30: =IF(B30=C30,"YES","NO") | IJ30: ez_manage.py:4471 top() | IK30: v12_quick_engine.py:422 x8
A31: BTC_GUARANTEED_REENTRY_MIN_GAP_BARS | B31: 2 | E31: =IF(F31="",E30,IF(F31>0,E30+F31,E30)) | F31: -2.0245238 | G31: -3.6806777 | H31: =IFERROR(VLOOKUP($A31,Results_30d_Deltas!$A$2:$H$5000,6,FALSE),"") | K31: =IF(B31=C31,"YES","NO") | IJ31: ez_manage.py:4472 top() | IK31: v12_quick_engine.py:429 x8
A32: BTC_GUARANTEED_REENTRY_MIN_GAP_BARS | B32: 4 | E32: =IF(F32="",E31,IF(F32>0,E31+F32,E31)) | F32: -1.8526111 | G32: -3.508765 | H32: =IFERROR(VLOOKUP($A32,Results_30d_Deltas!$A$2:$H$5000,6,FALSE),"") | K32: =IF(B32=C32,"YES","NO") | IJ32: ez_manage.py:4472 top() | IK32: v12_quick_engine.py:429 x8
A33: BTC_GUARANTEED_REENTRY_MIN_GAP_BARS | B33: 5 | E33: =IF(F33="",E32,IF(F33>0,E32+F33,E32)) | F33: 0 | G33: -1.6561539 | H33: =IFERROR(VLOOKUP($A33,Results_30d_Deltas!$A$2:$H$5000,6,FALSE),"") | K33: =IF(B33=C33,"YES","NO") | IJ33: ez_manage.py:4472 top() | IK33: v12_quick_engine.py:429 x8
A34: BTC_GUARANTEED_REENTRY_MIN_GAP_BARS | B34: 6 | E34: =IF(F34="",E33,IF(F34>0,E33+F34,E33)) | F34: -2.0610562 | G34: -3.7172101 | H34: =IFERROR(VLOOKUP($A34,Results_30d_Deltas!$A$2:$H$5000,6,FALSE),"") | K34: =IF(B34=C34,"YES","NO") | IJ34: ez_manage.py:4472 top() | IK34: v12_quick_engine.py:429 x8
A35: BTC_GUARANTEED_REENTRY_MIN_GAP_BARS | B35: 8 | E35: =IF(F35="",E34,IF(F35>0,E34+F35,E34)) | F35: -1.7073607 | G35: -3.3635146 | H35: =IFERROR(VLOOKUP($A35,Results_30d_Deltas!$A$2:$H$5000,6,FALSE),"") | K35: =IF(B35=C35,"YES","NO") | IJ35: ez_manage.py:4472 top() | IK35: v12_quick_engine.py:429 x8
A36: DELTA_REENTRY_Z_THRESHOLD | B36: 0.5 | E36: =IF(F36="",E35,IF(F36>0,E35+F36,E35)) | F36: 0 | G36: -1.6561539 | H36: =IFERROR(VLOOKUP($A36,Results_30d_Deltas!$A$2:$H$5000,6,FALSE),"") | K36: =IF(B36=C36,"YES","NO") | IJ36: ez_manage.py:196 check_reentry_delta_tolerant() | IK36: v12_quick_engine.py:1647 x7
A37: DELTA_REENTRY_Z_THRESHOLD | B37: 0.75 | E37: =IF(F37="",E36,IF(F37>0,E36+F37,E36)) | F37: -2.471381 | G37: -4.1275348 | H37: =IFERROR(VLOOKUP($A37,Results_30d_Deltas!$A$2:$H$5000,6,FALSE),"") | K37: =IF(B37=C37,"YES","NO") | IJ37: ez_manage.py:196 check_reentry_delta_tolerant() | IK37: v12_quick_engine.py:1647 x7
... A40: DELTA_REENTRY_Z_THRESHOLD | B40: 1.5 | E40: =IF(F40="",E39,IF(F40>0,E39+F40,E39)) | F40: -1.8526111 | G40: -3.508765 | H40: =IFERROR(VLOOKUP($A40,Results_30d_Deltas!$A$2:$H$5000,6,FALSE),"") | K40: =IF(B40=C40,"YES","NO") | IJ40: ez_manage.py:196 check_reentry_delta_tolerant() | IK40: v12_quick_engine.py:1647 x7
A41: DIRECTION_FAVORABLE_REENTRY_ENABLED | B41: False | E41: =IF(F41="",E40,IF(F41>0,E40+F41,E40)) | F41: =IFERROR(VLOOKUP($A41&"="&$B41,Results_30d_Deltas!$A$2:$H$5000,5,FALSE),"") | G41: =IFERROR(VLOOKUP($A41,Results_30d_Deltas!$A$2:$H$5000,7,FALSE)-E40,"") | H41: =IFERROR(VLOOKUP($A41,Results_30d_Deltas!$A$2:$H$5000,6,FALSE),"") | K41: =IF(B41=C41,"YES","NO") | IJ41: ez_manage.py:5976 top() | IK41: v12_quick_engine.py:979 x6
A42: DIRECTION_FAVORABLE_REENTRY_ENABLED | B42: True | E42: =IF(F42="",E41,IF(F42>0,E41+F42,E41)) | F42: 0 | G42: -1.6561539 | H42: =IFERROR(VLOOKUP($A42,Results_30d_Deltas!$A$2:$H$5000,6,FALSE),"") | K42: =IF(B42=C42,"YES","NO") | IJ42: ez_manage.py:5976 top() | IK42: v12_quick_engine.py:979 x6
A43: FOLLOW_THROUGH_REENTRY_ENABLED | B43: False | E43: =IF(F43="",E42,IF(F43>0,E42+F43,E42)) | F43: =IFERROR(VLOOKUP($A43&"="&$B43,Results_30d_Deltas!$A$2:$H$5000,5,FALSE),"") | G43: =IFERROR(VLOOKUP($A43,Results_30d_Deltas!$A$2:$H$5000,7,FALSE)-E42,"") | H43: =IFERROR(VLOOKUP($A43,Results_30d_Deltas!$A$2:$H$5000,6,FALSE),"") | K43: =IF(B43=C43,"YES","NO") | IJ43: ez_manage.py:1189 top() | IK43: v12_quick_engine.py:1394 x5
A44: FOLLOW_THROUGH_REENTRY_ENABLED | B44: True | E44: =IF(F44="",E43,IF(F44>0,E43+F44,E43)) | F44: -1.8934256 | G44: -3.5495795 | H44: =IFERROR(VLOOKUP($A44,Results_30d_Deltas!$A$2:$H$5000,6,FALSE),"") | K44: =IF(B44=C44,"YES","NO") | IJ44: ez_manage.py:1189 top() | IK44: v12_quick_engine.py:1394 x5
A45: GUARANTEED_REENTRY_DELTA_GATE_ENABLED | B45: False | E45: =IF(F45="",E44,IF(F45>0,E44+F45,E44)) | F45: =IFERROR(VLOOKUP($A45&"="&$B45,Results_30d_Deltas!$A$2:$H$5000,5,FALSE),"") | G45: =IFERROR(VLOOKUP($A45,Results_30d_Deltas!$A$2:$H$5000,7,FALSE)-E44,"") | H45: =IFERROR(VLOOKUP($A45,Results_30d_Deltas!$A$2:$H$5000,6,FALSE),"") | K45: =IF(B45=C45,"YES","NO") | IJ45: ez_manage.py:4773 top() | IK45: v12_quick_engine.py:1939 x4
A46: GUARANTEED_REENTRY_DELTA_GATE_ENABLED | B46: True | E46: =IF(F46="",E45,IF(F46>0,E45+F46,E45)) | F46: -2.0245238 | G46: -3.6806777 | H46: =IFERROR(VLOOKUP($A46,Results_30d_Deltas!$A$2:$H$5000,6,FALSE),"") | K46: =IF(B46=C46,"YES","NO") | IJ46: ez_manage.py:4773 top() | IK46: v12_quick_engine.py:1939 x4
A47: GUARANTEED_REENTRY_K_HIGH_BLOCK | B47: 40.0 | E47: =IF(F47="",E46,IF(F47>0,E46+F47,E46)) | F47: -1.7240473 | G47: -3.3802012 | H47: =IFERROR(VLOOKUP($A47,Results_30d_Deltas!$A$2:$H$5000,6,FALSE),"") | K47: =IF(B47=C47,"YES","NO") | IJ47: ez_manage.py:4776 top() | IK47: v12_quick_engine.py:1943 x4
A48: GUARANTEED_REENTRY_K_HIGH_BLOCK | B48: 60.0 | E48: =IF(F48="",E47,IF(F48>0,E47+F48,E47)) | F48: -2.4538266 | G48: -4.1099804 | H48: =IFERROR(VLOOKUP($A48,Results_30d_Deltas!$A$2:$H$5000,6,FALSE),"") | K48: =IF(B48=C48,"YES","NO") | IJ48: ez_manage.py:4776 top() | IK48: v12_quick_engine.py:1943 x4
A49: GUARANTEED_REENTRY_K_HIGH_BLOCK | B49: 80.0 | E49: =IF(F49="",E48,IF(F49>0,E48+F49,E48)) | F49: -1.8526111 | G49: -3.508765 | H49: =IFERROR(VLOOKUP($A49,Results_30d_Deltas!$A$2:$H$5000,6,FALSE),"") | K49: =IF(B49=C49,"YES","NO") | IJ49: ez_manage.py:4776 top() | IK49: v12_quick_engine.py:1943 x4
A50: GUARANTEED_REENTRY_K_HIGH_BLOCK | B50: 100.0 | E50: =IF(F50="",E49,IF(F50>0,E49+F50,E49)) | F50: 0 | G50: -1.6561539 | H50: =IFERROR(VLOOKUP($A50,Results_30d_Deltas!$A$2:$H$5000,6,FALSE),"") | K50: =IF(B50=C50,"YES","NO") | IJ50: ez_manage.py:4776 top() | IK50: v12_quick_engine.py:1943 x4
A51: GUARANTEED_REENTRY_K_HIGH_BLOCK | B51: 120.0 | E51: =IF(F51="",E50,IF(F51>0,E50+F51,E50)) | F51: 0 | G51: -1.6561539 | H51: =IFERROR(VLOOKUP($A51,Results_30d_Deltas!$A$2:$H$5000,6,FALSE),"") | K51: =IF(B51=C51,"YES","NO") | IJ51: ez_manage.py:4776 top() | IK51: v12_quick_engine.py:1943 x4
A52: GUARANTEED_REENTRY_K_LOW_BLOCK | B52: 10.0 | E52: =IF(F52="",E51,IF(F52>0,E51+F52,E51)) | F52: 0 | G52: -1.6561539 | H52: =IFERROR(VLOOKUP($A52,Results_30d_Deltas!$A$2:$H$5000,6,FALSE),"") | K52: =IF(B52=C52,"YES","NO") | IJ52: ez_manage.py:4777 top() | IK52: v12_quick_engine.py:1944 x4
A53: GUARANTEED_REENTRY_K_LOW_BLOCK | B53: 15.0 | E53: =IF(F53="",E52,IF(F53>0,E52+F53,E52)) | F53: -1.8542583 | G53: -3.5104122 | H53: =IFERROR(VLOOKUP($A53,Results_30d_Deltas!$A$2:$H$5000,6,FALSE),"") | K53: =IF(B53=C53,"YES","NO") | IJ53: ez_manage.py:4777 top() | IK53: v12_quick_engine.py:1944 x4
A54: GUARANTEED_REENTRY_K_LOW_BLOCK | B54: 20.0 | E54: =IF(F54="",E53,IF(F54>0,E53+F54,E53)) | F54: -1.8136634 | G54: -3.4698173 | H54: =IFERROR(VLOOKUP($A54,Results_30d_Deltas!$A$2:$H$5000,6,FALSE),"") | K54: =IF(B54=C54,"YES","NO") | IJ54: ez_manage.py:4777 top() | IK54: v12_quick_engine.py:1944 x4
A55: GUARANTEED_REENTRY_K_LOW_BLOCK | B55: 25.0 | E55: =IF(F55="",E54,IF(F55>0,E54+F55,E54)) | F55: 0 | G55: -1.6561539 | H55: =IFERROR(VLOOKUP($A55,Results_30d_Deltas!$A$2:$H$5000,6,FALSE),"") | K55: =IF(B55=C55,"YES","NO") | IJ55: ez_manage.py:4777 top() | IK55: v12_quick_engine.py:1944 x4
A56: GUARANTEED_REENTRY_K_LOW_BLOCK | B56: 30.0 | E56: =IF(F56="",E55,IF(F56>0,E55+F56,E55)) | F56: 0 | G56: -1.6561539 | H56: =IFERROR(VLOOKUP($A56,Results_30d_Deltas!$A$2:$H$5000,6,FALSE),"") | K56: =IF(B56=C56,"YES","NO") | IJ56: ez_manage.py:4777 top() | IK56: v12_quick_engine.py:1944 x4
A57: GUARANTEED_REENTRY_STRICT_CONFIRMATION | B57: False | E57: =IF(F57="",E56,IF(F57>0,E56+F57,E56)) | F57: -1.8526111 | G57: -3.508765 | H57: =IFERROR(VLOOKUP($A57,Results_30d_Deltas!$A$2:$H$5000,6,FALSE),"") | K57: =IF(B57=C57,"YES","NO") | IJ57: ez_manage.py:4778 top() | IK57: v12_quick_engine.py:1946 x6
A58: GUARANTEED_REENTRY_STRICT_CONFIRMATION | B58: True | E58: =IF(F58="",E57,IF(F58>0,E57+F58,E57)) | F58: =IFERROR(VLOOKUP($A58&"="&$B58,Results_30d_Deltas!$A$2:$H$5000,5,FALSE),"") | G58: =IFERROR(VLOOKUP($A58,Results_30d_Deltas!$A$2:$H$5000,7,FALSE)-E57,"") | H58: =IFERROR(VLOOKUP($A58,Results_30d_Deltas!$A$2:$H$5000,6,FALSE),"") | K58: =IF(B58=C58,"YES","NO") | IJ58: ez_manage.py:4778 top() | IK58: v12_quick_engine.py:1946 x6
A59: GUARANTEED_REENTRY_TIGHT_STOP_ENABLED | B59: False | E59: =IF(F59="",E58,IF(F59>0,E58+F59,E58)) | F59: -2.4538266 | G59: -4.1099804 | H59: =IFERROR(VLOOKUP($A59,Results_30d_Deltas!$A$2:$H$5000,6,FALSE),"") | K59: =IF(B59=C59,"YES","NO") | IJ59: ez_manage.py:4779 top() | IK59: v12_quick_engine.py:1947 x3
A60: GUARANTEED_REENTRY_TIGHT_STOP_ENABLED | B60: True | E60: =IF(F60="",E59,IF(F60>0,E59+F60,E59)) | F60: =IFERROR(VLOOKUP($A60&"="&$B60,Results_30d_Deltas!$A$2:$H$5000,5,FALSE),"") | G60: =IFERROR(VLOOKUP($A60,Results_30d_Deltas!$A$2:$H$5000,7,FALSE)-E59,"") | H60: =IFERROR(VLOOKUP($A60,Results_30d_Deltas!$A$2:$H$5000,6,FALSE),"") | K60: =IF(B60=C60,"YES","NO") | IJ60: ez_manage.py:4779 top() | IK60: v12_quick_engine.py:1947 x3
A61: GUARANTEED_REENTRY_TIGHT_STOP_MAX_AGE_S | B61: 900.0 | E61: =IF(F61="",E60,IF(F61>0,E60+F61,E60)) | F61: 0 | G61: -1.6561539 | H61: =IFERROR(VLOOKUP($A61,Results_30d_Deltas!$A$2:$H$5000,6,FALSE),"") | K61: =IF(B61=C61,"YES","NO") | IJ61: ez_manage.py:4780 top() | IK61: v12_quick_engine.py:1948 x4
A62: GUARANTEED_REENTRY_TIGHT_STOP_MAX_AGE_S | B62: 1350.0 | E62: =IF(F62="",E61,IF(F62>0,E61+F62,E61)) | F62: 0 | G62: -1.6561539 | H62: =IFERROR(VLOOKUP($A62,Results_30d_Deltas!$A$2:$H$5000,6,FALSE),"") | K62: =IF(B62=C62,"YES","NO") | IJ62: ez_manage.py:4780 top() | IK62: v12_quick_engine.py:1948 x4
A63: GUARANTEED_REENTRY_TIGHT_STOP_MAX_AGE_S | B63: 1800.0 | E63: =IF(F63="",E62,IF(F63>0,E62+F63,E62)) | F63: 0 | G63: -1.6561539 | H63: =IFERROR(VLOOKUP($A63,Results_30d_Deltas!$A$2:$H$5000,6,FALSE),"") | K63: =IF(B63=C63,"YES","NO") | IJ63: ez_manage.py:4780 top() | IK63: v12_quick_engine.py:1948 x4
A64: GUARANTEED_REENTRY_TIGHT_STOP_MAX_AGE_S | B64: 2250.0 | E64: =IF(F64="",E63,IF(F64>0,E63+F64,E63)) | F64: 0 | G64: -1.6561539 | H64: =IFERROR(VLOOKUP($A64,Results_30d_Deltas!$A$2:$H$5000,6,FALSE),"") | K64: =IF(B64=C64,"YES","NO") | IJ64: ez_manage.py:4780 top() | IK64: v12_quick_engine.py:1948 x4
A65: GUARANTEED_REENTRY_TIGHT_STOP_MAX_AGE_S | B65: 2700.0 | E65: =IF(F65="",E64,IF(F65>0,E64+F65,E64)) | F65: 0 | G65: -1.6561539 | H65: =IFERROR(VLOOKUP($A65,Results_30d_Deltas!$A$2:$H$5000,6,FALSE),"") | K65: =IF(B65=C65,"YES","NO") | IJ65: ez_manage.py:4780 top() | IK65: v12_quick_engine.py:1948 x4
A66: GUARANTEED_REENTRY_TIGHT_STOP_MIN_AGE_S | B66: 30.0 | E66: =IF(F66="",E65,IF(F66>0,E65+F66,E65)) | F66: 0 | G66: -1.6561539 | H66: =IFERROR(VLOOKUP($A66,Results_30d_Deltas!$A$2:$H$5000,6,FALSE),"") | K66: =IF(B66=C66,"YES","NO") | IJ66: ez_manage.py:4781 top() | IK66: v12_quick_engine.py:1949 x4
A67: GUARANTEED_REENTRY_TIGHT_STOP_MIN_AGE_S | B67: 45.0 | E67: =IF(F67="",E66,IF(F67>0,E66+F67,E66)) | F67: 0 | G67: -1.6561539 | H67: =IFERROR(VLOOKUP($A67,Results_30d_Deltas!$A$2:$H$5000,6,FALSE),"") | K67: =IF(B67=C67,"YES","NO") | IJ67: ez_manage.py:4781 top() | IK67: v12_quick_engine.py:1949 x4
A68: GUARANTEED_REENTRY_TIGHT_STOP_MIN_AGE_S | B68: 60.0 | E68: =IF(F68="",E67,IF(F68>0,E67+F68,E67)) | F68: -2.471381 | G68: -4.1275348 | H68: =IFERROR(VLOOKUP($A68,Results_30d_Deltas!$A$2:$H$5000,6,FALSE),"") | K68: =IF(B68=C68,"YES","NO") | IJ68: ez_manage.py:4781 top() | IK68: v12_quick_engine.py:1949 x4
A69: GUARANTEED_REENTRY_TIGHT_STOP_MIN_AGE_S | B69: 75.0 | E69: =IF(F69="",E68,IF(F69>0,E68+F69,E68)) | F69: -2.0245238 | G69: -3.6806777 | H69: =IFERROR(VLOOKUP($A69,Results_30d_Deltas!$A$2:$H$5000,6,FALSE),"") | K69: =IF(B69=C69,"YES","NO") | IJ69: ez_manage.py:4781 top() | IK69: v12_quick_engine.py:1949 x4
A70: GUARANTEED_REENTRY_TIGHT_STOP_MIN_AGE_S | B70: 90.0 | E70: =IF(F70="",E69,IF(F70>0,E69+F70,E69)) | F70: 0 | G70: -1.6561539 | H70: =IFERROR(VLOOKUP($A70,Results_30d_Deltas!$A$2:$H$5000,6,FALSE),"") | K70: =IF(B70=C70,"YES","NO") | IJ70: ez_manage.py:4781 top() | IK70: v12_quick_engine.py:1949 x4
A71: GUARANTEED_REENTRY_TIGHT_STOP_PCT | B71: 0.25 | E71: =IF(F71="",E70,IF(F71>0,E70+F71,E70)) | F71: -1.8526111 | G71: -3.508765 | H71: =IFERROR(VLOOKUP($A71,Results_30d_Deltas!$A$2:$H$5000,6,FALSE),"") | K71: =IF(B71=C71,"YES","NO") | IJ71: ez_manage.py:4782 top() | IK71: v12_quick_engine.py:1950 x7
A72: GUARANTEED_REENTRY_TIGHT_STOP_PCT | B72: 0.375 | E72: =IF(F72="",E71,IF(F72>0,E71+F72,E71)) | F72: -1.8542583 | G72: -3.5104122 | H72: =IFERROR(VLOOKUP($A72,Results_30d_Deltas!$A$2:$H$5000,6,FALSE),"") | K72: =IF(B72=C72,"YES","NO") | IJ72: ez_manage.py:4782 top() | IK72: v12_quick_engine.py:1950 x7
... A111: MANDATORY_REENTRY_REQUIRE_K_NOT_EXTREME | B111: 2.0 | E111: =IF(F111="",E110,IF(F111>0,E110+F111,E110)) | F111: 0 | G111: -1.6561539 | H111: =IFERROR(VLOOKUP($A111,Results_30d_Deltas!$A$2:$H$5000,6,FALSE),"") | K111: =IF(B111=C111,"YES","NO") | IJ111: ez_manage.py:4964 top() | IK111: v12_quick_engine.py:2250 x2
A112: MU_CORRECTION_REENTRY_ENABLED | B112: False | E112: =IF(F112="",E111,IF(F112>0,E111+F112,E111)) | F112: =IFERROR(VLOOKUP($A112&"="&$B112,Results_30d_Deltas!$A$2:$H$5000,5,FALSE),"") | G112: =IFERROR(VLOOKUP($A112,Results_30d_Deltas!$A$2:$H$5000,7,FALSE)-E111,"") | H112: =IFERROR(VLOOKUP($A112,Results_30d_Deltas!$A$2:$H$5000,6,FALSE),"") | K112: =IF(B112=C112,"YES","NO") | IJ112: ez_manage.py:5077 top() | IK112: v12_quick_engine.py:2463 x3
A113: MU_CORRECTION_REENTRY_ENABLED | B113: True | E113: =IF(F113="",E112,IF(F113>0,E112+F113,E112)) | F113: -2.4538266 | G113: -4.1099804 | H113: =IFERROR(VLOOKUP($A113,Results_30d_Deltas!$A$2:$H$5000,6,FALSE),"") | K113: =IF(B113=C113,"YES","NO") | IJ113: ez_manage.py:5077 top() | IK113: v12_quick_engine.py:2463 x3
A114: OBLIGATORY_REENTRY_DEFAULT_SIZE_MULT | B114: 0 | E114: =IF(F114="",E113,IF(F114>0,E113+F114,E113)) | F114: -1.7345709 | G114: -3.3907247 | H114: =IFERROR(VLOOKUP($A114,Results_30d_Deltas!$A$2:$H$5000,6,FALSE),"") | K114: =IF(B114=C114,"YES","NO") | IJ114: ez_manage.py:5108 top() | IK114: v12_quick_engine.py:2499 x2
A115: OBLIGATORY_REENTRY_DEFAULT_SIZE_MULT | B115: 0.5 | E115: =IF(F115="",E114,IF(F115>0,E114+F115,E114)) | F115: 0 | G115: -1.6561539 | H115: =IFERROR(VLOOKUP($A115,Results_30d_Deltas!$A$2:$H$5000,6,FALSE),"") | K115: =IF(B115=C115,"YES","NO") | IJ115: ez_manage.py:5108 top() | IK115: v12_quick_engine.py:2499 x2
A116: OBLIGATORY_REENTRY_DEFAULT_SIZE_MULT | B116: 1.0 | E116: =IF(F116="",E115,IF(F116>0,E115+F116,E115)) | F116: 0 | G116: -1.6561539 | H116: =IFERROR(VLOOKUP($A116,Results_30d_Deltas!$A$2:$H$5000,6,FALSE),"") | K116: =IF(B116=C116,"YES","NO") | IJ116: ez_manage.py:5108 top() | IK116: v12_quick_engine.py:2499 x2
A117: OBLIGATORY_REENTRY_DEFAULT_SIZE_MULT | B117: 2.0 | E117: =IF(F117="",E116,IF(F117>0,E116+F117,E116)) | F117: -1.0393426 | G117: -2.6954965 | H117: =IFERROR(VLOOKUP($A117,Results_30d_Deltas!$A$2:$H$5000,6,FALSE),"") | K117: =IF(B117=C117,"YES","NO") | IJ117: ez_manage.py:5108 top() | IK117: v12_quick_engine.py:2499 x2
A118: OBLIGATORY_REENTRY_ENABLED | B118: False | E118: =IF(F118="",E117,IF(F118>0,E117+F118,E117)) | F118: =IFERROR(VLOOKUP($A118&"="&$B118,Results_30d_Deltas!$A$2:$H$5000,5,FALSE),"") | G118: =IFERROR(VLOOKUP($A118,Results_30d_Deltas!$A$2:$H$5000,7,FALSE)-E117,"") | H118: =IFERROR(VLOOKUP($A118,Results_30d_Deltas!$A$2:$H$5000,6,FALSE),"") | K118: =IF(B118=C118,"YES","NO") | IJ118: ez_manage.py:5109 top() | IK118: v12_quick_engine.py:2500 x2
A119: OBLIGATORY_REENTRY_ENABLED | B119: True | E119: =IF(F119="",E118,IF(F119>0,E118+F119,E118)) | F119: 0 | G119: -1.6561539 | H119: =IFERROR(VLOOKUP($A119,Results_30d_Deltas!$A$2:$H$5000,6,FALSE),"") | K119: =IF(B119=C119,"YES","NO") | IJ119: ez_manage.py:5109 top() | IK119: v12_quick_engine.py:2500 x2
A120: OBLIGATORY_REENTRY_K15_HIGH_BLOCK | B120: 0 | E120: =IF(F120="",E119,IF(F120>0,E119+F120,E119)) | F120: -1.8526111 | G120: -3.508765 | H120: =IFERROR(VLOOKUP($A120,Results_30d_Deltas!$A$2:$H$5000,6,FALSE),"") | K120: =IF(B120=C120,"YES","NO") | IJ120: ez_manage.py:5110 top() | IK120: v12_quick_engine.py:2501 x4
A121: OBLIGATORY_REENTRY_K15_HIGH_BLOCK | B121: 0.5 | E121: =IF(F121="",E120,IF(F121>0,E120+F121,E120)) | F121: 0 | G121: -1.6561539 | H121: =IFERROR(VLOOKUP($A121,Results_30d_Deltas!$A$2:$H$5000,6,FALSE),"") | K121: =IF(B121=C121,"YES","NO") | IJ121: ez_manage.py:5110 top() | IK121: v12_quick_engine.py:2501 x4
A122: OBLIGATORY_REENTRY_K15_HIGH_BLOCK | B122: 1.0 | E122: =IF(F122="",E121,IF(F122>0,E121+F122,E121)) | F122: 0 | G122: -1.6561539 | H122: =IFERROR(VLOOKUP($A122,Results_30d_Deltas!$A$2:$H$5000,6,FALSE),"") | K122: =IF(B122=C122,"YES","NO") | IJ122: ez_manage.py:5110 top() | IK122: v12_quick_engine.py:2501 x4
A123: OBLIGATORY_REENTRY_K15_HIGH_BLOCK | B123: 2.0 | E123: =IF(F123="",E122,IF(F123>0,E122+F123,E122)) | F123: -2.471381 | G123: -4.1275348 | H123: =IFERROR(VLOOKUP($A123,Results_30d_Deltas!$A$2:$H$5000,6,FALSE),"") | K123: =IF(B123=C123,"YES","NO") | IJ123: ez_manage.py:5110 top() | IK123: v12_quick_engine.py:2501 x4
A124: OBLIGATORY_REENTRY_K15_HIGH_SIZE_FRAC | B124: 0 | E124: =IF(F124="",E123,IF(F124>0,E123+F124,E123)) | F124: 0 | G124: -1.6561539 | H124: =IFERROR(VLOOKUP($A124,Results_30d_Deltas!$A$2:$H$5000,6,FALSE),"") | K124: =IF(B124=C124,"YES","NO") | IJ124: ez_manage.py:5111 top() | IK124: v12_quick_engine.py:2502 x4
A125: OBLIGATORY_REENTRY_K15_HIGH_SIZE_FRAC | B125: 0.5 | E125: =IF(F125="",E124,IF(F125>0,E124+F125,E124)) | F125: -2.471381 | G125: -4.1275348 | H125: =IFERROR(VLOOKUP($A125,Results_30d_Deltas!$A$2:$H$5000,6,FALSE),"") | K125: =IF(B125=C125,"YES","NO") | IJ125: ez_manage.py:5111 top() | IK125: v12_quick_engine.py:2502 x4
A126: OBLIGATORY_REENTRY_K15_HIGH_SIZE_FRAC | B126: 1.0 | E126: =IF(F126="",E125,IF(F126>0,E125+F126,E125)) | F126: -1.8787217 | G126: -3.5348756 | H126: =IFERROR(VLOOKUP($A126,Results_30d_Deltas!$A$2:$H$5000,6,FALSE),"") | K126: =IF(B126=C126,"YES","NO") | IJ126: ez_manage.py:5111 top() | IK126: v12_quick_engine.py:2502 x4
A127: OBLIGATORY_REENTRY_K15_HIGH_SIZE_FRAC | B127: 2.0 | E127: =IF(F127="",E126,IF(F127>0,E126+F127,E126)) | F127: 0 | G127: -1.6561539 | H127: =IFERROR(VLOOKUP($A127,Results_30d_Deltas!$A$2:$H$5000,6,FALSE),"") | K127: =IF(B127=C127,"YES","NO") | IJ127: ez_manage.py:5111 top() | IK127: v12_quick_engine.py:2502 x4
A128: OBLIGATORY_REENTRY_SCORE_TIER1 | B128: 0 | E128: =IF(F128="",E127,IF(F128>0,E127+F128,E127)) | F128: -1.8934256 | G128: -3.5495795 | H128: =IFERROR(VLOOKUP($A128,Results_30d_Deltas!$A$2:$H$5000,6,FALSE),"") | K128: =IF(B128=C128,"YES","NO") | IJ128: ez_manage.py:5113 top() | IK128: v12_quick_engine.py:2504 x4
A129: OBLIGATORY_REENTRY_SCORE_TIER1 | B129: 0.5 | E129: =IF(F129="",E128,IF(F129>0,E128+F129,E128)) | F129: 0 | G129: -1.6561539 | H129: =IFERROR(VLOOKUP($A129,Results_30d_Deltas!$A$2:$H$5000,6,FALSE),"") | K129: =IF(B129=C129,"YES","NO") | IJ129: ez_manage.py:5113 top() | IK129: v12_quick_engine.py:2504 x4
A130: OBLIGATORY_REENTRY_SCORE_TIER1 | B130: 1.0 | E130: =IF(F130="",E129,IF(F130>0,E129+F130,E129)) | F130: 0 | G130: -1.6561539 | H130: =IFERROR(VLOOKUP($A130,Results_30d_Deltas!$A$2:$H$5000,6,FALSE),"") | K130: =IF(B130=C130,"YES","NO") | IJ130: ez_manage.py:5113 top() | IK130: v12_quick_engine.py:2504 x4
... A155: OBLIGATORY_REENTRY_SMA_TF | B155: 1h | E155: =IF(F155="",E154,IF(F155>0,E154+F155,E154)) | F155: 0 | G155: -1.6561539 | H155: =IFERROR(VLOOKUP($A155,Results_30d_Deltas!$A$2:$H$5000,6,FALSE),"") | K155: =IF(B155=C155,"YES","NO") | IJ155: ez_manage.py:5122 top() | IK155: v12_quick_engine.py:2513 x2
A156: OBLIGATORY_REENTRY_SMA_TF | B156: 15m | E156: =IF(F156="",E155,IF(F156>0,E155+F156,E155)) | F156: =IFERROR(VLOOKUP($A156&"="&$B156,Results_30d_Deltas!$A$2:$H$5000,5,FALSE),"") | G156: =IFERROR(VLOOKUP($A156,Results_30d_Deltas!$A$2:$H$5000,7,FALSE)-E155,"") | H156: =IFERROR(VLOOKUP($A156,Results_30d_Deltas!$A$2:$H$5000,6,FALSE),"") | K156: =IF(B156=C156,"YES","NO") | IJ156: ez_manage.py:5122 top() | IK156: v12_quick_engine.py:2513 x2
A157: OBLIGATORY_REENTRY_TIER1_HTF_REQUIRED | B157: 0 | E157: =IF(F157="",E156,IF(F157>0,E156+F157,E156)) | F157: -2.4538266 | G157: -4.1099804 | H157: =IFERROR(VLOOKUP($A157,Results_30d_Deltas!$A$2:$H$5000,6,FALSE),"") | K157: =IF(B157=C157,"YES","NO") | IJ157: ez_manage.py:5123 top() | IK157: v12_quick_engine.py:2514 x4
A158: OBLIGATORY_REENTRY_TIER1_HTF_REQUIRED | B158: 0.5 | E158: =IF(F158="",E157,IF(F158>0,E157+F158,E157)) | F158: 0 | G158: -1.6561539 | H158: =IFERROR(VLOOKUP($A158,Results_30d_Deltas!$A$2:$H$5000,6,FALSE),"") | K158: =IF(B158=C158,"YES","NO") | IJ158: ez_manage.py:5123 top() | IK158: v12_quick_engine.py:2514 x4
A159: OBLIGATORY_REENTRY_TIER1_HTF_REQUIRED | B159: 1.0 | E159: =IF(F159="",E158,IF(F159>0,E158+F159,E158)) | F159: 0 | G159: -1.6561539 | H159: =IFERROR(VLOOKUP($A159,Results_30d_Deltas!$A$2:$H$5000,6,FALSE),"") | K159: =IF(B159=C159,"YES","NO") | IJ159: ez_manage.py:5123 top() | IK159: v12_quick_engine.py:2514 x4
A160: OBLIGATORY_REENTRY_TIER1_HTF_REQUIRED | B160: 2.0 | E160: =IF(F160="",E159,IF(F160>0,E159+F160,E159)) | F160: -2.0245238 | G160: -3.6806777 | H160: =IFERROR(VLOOKUP($A160,Results_30d_Deltas!$A$2:$H$5000,6,FALSE),"") | K160: =IF(B160=C160,"YES","NO") | IJ160: ez_manage.py:5123 top() | IK160: v12_quick_engine.py:2514 x4
A161: OBLIGATORY_REENTRY_TIER2_HTF_REQUIRED | B161: 0 | E161: =IF(F161="",E160,IF(F161>0,E160+F161,E160)) | F161: 0 | G161: -1.6561539 | H161: =IFERROR(VLOOKUP($A161,Results_30d_Deltas!$A$2:$H$5000,6,FALSE),"") | K161: =IF(B161=C161,"YES","NO") | IJ161: ez_manage.py:5124 top() | IK161: v12_quick_engine.py:2515 x4
A162: OBLIGATORY_REENTRY_TIER2_HTF_REQUIRED | B162: 0.5 | E162: =IF(F162="",E161,IF(F162>0,E161+F162,E161)) | F162: -1.8787217 | G162: -3.5348756 | H162: =IFERROR(VLOOKUP($A162,Results_30d_Deltas!$A$2:$H$5000,6,FALSE),"") | K162: =IF(B162=C162,"YES","NO") | IJ162: ez_manage.py:5124 top() | IK162: v12_quick_engine.py:2515 x4
A163: OBLIGATORY_REENTRY_TIER2_HTF_REQUIRED | B163: 1.0 | E163: =IF(F163="",E162,IF(F163>0,E162+F163,E162)) | F163: -2.0245238 | G163: -3.6806777 | H163: =IFERROR(VLOOKUP($A163,Results_30d_Deltas!$A$2:$H$5000,6,FALSE),"") | K163: =IF(B163=C163,"YES","NO") | IJ163: ez_manage.py:5124 top() | IK163: v12_quick_engine.py:2515 x4
A164: OBLIGATORY_REENTRY_TIER2_HTF_REQUIRED | B164: 2.0 | E164: =IF(F164="",E163,IF(F164>0,E163+F164,E163)) | F164: 0 | G164: -1.6561539 | H164: =IFERROR(VLOOKUP($A164,Results_30d_Deltas!$A$2:$H$5000,6,FALSE),"") | K164: =IF(B164=C164,"YES","NO") | IJ164: ez_manage.py:5124 top() | IK164: v12_quick_engine.py:2515 x4
...

Sheet REENTRY_ADAPTIVE
A1: 07 REENTRY_ADAPTIVE - 10 bases -> 38 rows - 231 per-row FULLY CONNECTED
A2: Switch | B2: default | C2: override | D2: Family | E2: BASELINE | F2: VECTOR_DELTA | G2: LIVE_DELTA | H2: LIVE_SHARPE | I2: REAL_COMPLETE | J2: PER_ROW_FILTERS | K2: is_default (backup if bold lost) | L2: ATR_TRAIL_FILTER_TF=OFF | M2: ATR_TRAIL_FILTER_TF=D | N2: ATR_TRAIL_FILTER_TF=4h | O2: ATR_TRAIL_FILTER_TF=1h | P2: ATR_TRAIL_FILTER_TF=15m | Q2: BAR_PATTERNS_FILTER_TF=OFF | R2: BAR_PATTERNS_FILTER_TF=D | S2: BAR_PATTERNS_FILTER_TF=4h | T2: BAR_PATTERNS_FILTER_TF=1h | U2: BAR_PATTERNS_FILTER_TF=15m | V2: BB_PULLBACK_GATE_FILTER_TF=OFF | W2: BB_PULLBACK_GATE_FILTER_TF=D | X2: BB_PULLBACK_GATE_FILTER_TF=4h | Y2: BB_PULLBACK_GATE_FILTER_TF=1h | Z2: BB_PULLBACK_GATE_FILTER_TF=15m | AA2: BB_RECOVERY_ENTRY_FILTER_TF=OFF | AB2: BB_RECOVERY_ENTRY_FILTER_TF=D | AC2: BB_RECOVERY_ENTRY_FILTER_TF=4h | AD2: BB_RECOVERY_ENTRY_FILTER_TF=1h | AE2: BB_RECOVERY_ENTRY_FILTER_TF=15m | AF2: BB_RECOVERY_FILTER_TF=OFF | AG2: BB_RECOVERY_FILTER_TF=D | AH2: BB_RECOVERY_FILTER_TF=4h | AI2: BB_RECOVERY_FILTER_TF=1h | AJ2: BB_RECOVERY_FILTER_TF=15m | AK2: BREAKEVEN_GAIN_EROSION_FILTER_TF=OFF | AL2: BREAKEVEN_GAIN_EROSION_FILTER_TF=D | AM2: BREAKEVEN_GAIN_EROSION_FILTER_TF=4h | AN2: BREAKEVEN_GAIN_EROSION_FILTER_TF=1h | AO2: BREAKEVEN_GAIN_EROSION_FILTER_TF=15m | AP2: BREAKOUT_RETEST_FILTER_TF=OFF | AQ2: BREAKOUT_RETEST_FILTER_TF=D | AR2: BREAKOUT_RETEST_FILTER_TF=4h | AS2: BREAKOUT_RETEST_FILTER_TF=1h | AT2: BREAKOUT_RETEST_FILTER_TF=15m | AU2: BT_WT_CROSS_LADDER_FILTER_TF=OFF | AV2: BT_WT_CROSS_LADDER_FILTER_TF=D | AW2: BT_WT_CROSS_LADDER_FILTER_TF=4h | AX2: BT_WT_CROSS_LADDER_FILTER_TF=1h | AY2: BT_WT_CROSS_LADDER_FILTER_TF=15m | AZ2: CANDLE_PATTERN_STOPS_FILTER_TF=OFF | BA2: CANDLE_PATTERN_STOPS_FILTER_TF=D | BB2: CANDLE_PATTERN_STOPS_FILTER_TF=4h | BC2: CANDLE_PATTERN_STOPS_FILTER_TF=1h | BD2: CANDLE_PATTERN_STOPS_FILTER_TF=15m | BE2: CIRCUIT_SHARPE_GATES_FILTER_TF=OFF | BF2: CIRCUIT_SHARPE_GATES_FILTER_TF=D | BG2: CIRCUIT_SHARPE_GATES_FILTER_TF=4h | BH2: CIRCUIT_SHARPE_GATES_FILTER_TF=1h | BI2: CIRCUIT_SHARPE_GATES_FILTER_TF=15m | BJ2: DC_BREACH_REDUCE_FILTER_TF=OFF | BK2: DC_BREACH_REDUCE_FILTER_TF=D | BL2: DC_BREACH_REDUCE_FILTER_TF=4h | BM2: DC_BREACH_REDUCE_FILTER_TF=1h | BN2: DC_BREACH_REDUCE_FILTER_TF=15m | BO2: DC_BREAK_FILTER_TF=OFF | BP2: DC_BREAK_FILTER_TF=D | BQ2: DC_BREAK_FILTER_TF=4h | BR2: DC_BREAK_FILTER_TF=1h | BS2: DC_BREAK_FILTER_TF=15m | BT2: DC_MOMENTUM_BOTA_SCORER_FILTER_TF=OFF | BU2: DC_MOMENTUM_BOTA_SCORER_FILTER_TF=D | BV2: DC_MOMENTUM_BOTA_SCORER_FILTER_TF=4h | BW2: DC_MOMENTUM_BOTA_SCORER_FILTER_TF=1h | BX2: DC_MOMENTUM_BOTA_SCORER_FILTER_TF=15m | BY2: DELTA_ENGINE_FILTER_TF=OFF | BZ2: DELTA_ENGINE_FILTER_TF=D | CA2: DELTA_ENGINE_FILTER_TF=4h | CB2: DELTA_ENGINE_FILTER_TF=1h | CC2: DELTA_ENGINE_FILTER_TF=15m | CD2: EMA_9_21_FILTER_FILTER_TF=OFF | CE2: EMA_9_21_FILTER_FILTER_TF=D | CF2: EMA_9_21_FILTER_FILTER_TF=4h | CG2: EMA_9_21_FILTER_FILTER_TF=1h | CH2: EMA_9_21_FILTER_FILTER_TF=15m | CI2: EMA_BLANKET_FILTER_FILTER_TF=OFF | CJ2: EMA_BLANKET_FILTER_FILTER_TF=D | CK2: EMA_BLANKET_FILTER_FILTER_TF=4h | CL2: EMA_BLANKET_FILTER_FILTER_TF=1h | CM2: EMA_BLANKET_FILTER_FILTER_TF=15m | CN2: EMERGENCY_BRAKE_FILTER_TF=OFF | CO2: EMERGENCY_BRAKE_FILTER_TF=D | CP2: EMERGENCY_BRAKE_FILTER_TF=4h | CQ2: EMERGENCY_BRAKE_FILTER_TF=1h | CR2: EMERGENCY_BRAKE_FILTER_TF=15m | CS2: EXIT_R1_R2_FILTER_TF=OFF | CT2: EXIT_R1_R2_FILTER_TF=D | CU2: EXIT_R1_R2_FILTER_TF=4h | CV2: EXIT_R1_R2_FILTER_TF=1h | CW2: EXIT_R1_R2_FILTER_TF=15m | CX2: EXIT_TIGHT_BREAKOUT_SCORER_FILTER_TF=OFF | CY2: EXIT_TIGHT_BREAKOUT_SCORER_FILTER_TF=D | CZ2: EXIT_TIGHT_BREAKOUT_SCORER_FILTER_TF=4h | DA2: EXIT_TIGHT_BREAKOUT_SCORER_FILTER_TF=1h | DB2: EXIT_TIGHT_BREAKOUT_SCORER_FILTER_TF=15m | DC2: EXIT_TOP_FADE_FILTER_TF=OFF | DD2: EXIT_TOP_FADE_FILTER_TF=D | DE2: EXIT_TOP_FADE_FILTER_TF=4h | DF2: EXIT_TOP_FADE_FILTER_TF=1h | DG2: EXIT_TOP_FADE_FILTER_TF=15m | DH2: EXIT_TO_REDUCE_ADAPTER_FILTER_TF=OFF | DI2: EXIT_TO_REDUCE_ADAPTER_FILTER_TF=D | DJ2: EXIT_TO_REDUCE_ADAPTER_FILTER_TF=4h | DK2: EXIT_TO_REDUCE_ADAPTER_FILTER_TF=1h | DL2: EXIT_TO_REDUCE_ADAPTER_FILTER_TF=15m | DM2: FAST_RISER_FILTER_TF=OFF | DN2: FAST_RISER_FILTER_TF=D | DO2: FAST_RISER_FILTER_TF=4h | DP2: FAST_RISER_FILTER_TF=1h | DQ2: FAST_RISER_FILTER_TF=15m | DR2: FH_MOMENTUM_FILTER_TF=OFF | DS2: FH_MOMENTUM_FILTER_TF=D | DT2: FH_MOMENTUM_FILTER_TF=4h | DU2: FH_MOMENTUM_FILTER_TF=1h | DV2: FH_MOMENTUM_FILTER_TF=15m | DW2: FIRST_OPEN_THROTTLE_FILTER_TF=OFF | DX2: FIRST_OPEN_THROTTLE_FILTER_TF=D | DY2: FIRST_OPEN_THROTTLE_FILTER_TF=4h | DZ2: FIRST_OPEN_THROTTLE_FILTER_TF=1h | EA2: FIRST_OPEN_THROTTLE_FILTER_TF=15m | EB2: FROZEN_STOP_FILTER_TF=OFF | EC2: FROZEN_STOP_FILTER_TF=D | ED2: FROZEN_STOP_FILTER_TF=4h | EE2: FROZEN_STOP_FILTER_TF=1h | EF2: FROZEN_STOP_FILTER_TF=15m | EG2: GOLDEN_RULE_ENFORCE_FILTER_TF=OFF | EH2: GOLDEN_RULE_ENFORCE_FILTER_TF=D | EI2: GOLDEN_RULE_ENFORCE_FILTER_TF=4h | EJ2: GOLDEN_RULE_ENFORCE_FILTER_TF=1h | EK2: GOLDEN_RULE_ENFORCE_FILTER_TF=15m | EL2: GOLDEN_RULE_HTF_VOTE_FILTER_TF=OFF | EM2: GOLDEN_RULE_HTF_VOTE_FILTER_TF=D | EN2: GOLDEN_RULE_HTF_VOTE_FILTER_TF=4h | EO2: GOLDEN_RULE_HTF_VOTE_FILTER_TF=1h | EP2: GOLDEN_RULE_HTF_VOTE_FILTER_TF=15m | EQ2: GR_FILTER_VEC_FILTER_TF=OFF | ER2: GR_FILTER_VEC_FILTER_TF=D | ES2: GR_FILTER_VEC_FILTER_TF=4h | ET2: GR_FILTER_VEC_FILTER_TF=1h | EU2: GR_FILTER_VEC_FILTER_TF=15m | EV2: GR_V5_STATE_FILTER_TF=OFF | EW2: GR_V5_STATE_FILTER_TF=D | EX2: GR_V5_STATE_FILTER_TF=4h | EY2: GR_V5_STATE_FILTER_TF=1h | EZ2: GR_V5_STATE_FILTER_TF=15m | FA2: HAIKU_WINNER_FILTER_TF=OFF | FB2: HAIKU_WINNER_FILTER_TF=D | FC2: HAIKU_WINNER_FILTER_TF=4h | FD2: HAIKU_WINNER_FILTER_TF=1h | FE2: HAIKU_WINNER_FILTER_TF=15m | FF2: LH_HL_FILTER_TF_REQ=2 | FG2: LH_HL_FILTER_TF_REQ=2_ALT | FH2: LIVE_ENTRY_ENGINE_FILTER_TF=OFF | FI2: LIVE_ENTRY_ENGINE_FILTER_TF=D | FJ2: LIVE_ENTRY_ENGINE_FILTER_TF=4h | FK2: LIVE_ENTRY_ENGINE_FILTER_TF=1h | FL2: LIVE_ENTRY_ENGINE_FILTER_TF=15m | FM2: LIVE_ONLY_SIGNALS_BATCH5_FILTER_TF=OFF | FN2: LIVE_ONLY_SIGNALS_BATCH5_FILTER_TF=D | FO2: LIVE_ONLY_SIGNALS_BATCH5_FILTER_TF=4h | FP2: LIVE_ONLY_SIGNALS_BATCH5_FILTER_TF=1h | FQ2: LIVE_ONLY_SIGNALS_BATCH5_FILTER_TF=15m | FR2: MANDATORY_REENTRY_WT_FILTER_TF_MODE=15m_only | FS2: MANDATORY_REENTRY_WT_FILTER_TF_MODE=15m_only_ALT | FT2: MOM3_FILTER_TF=OFF | FU2: MOM3_FILTER_TF=D | FV2: MOM3_FILTER_TF=4h | FW2: MOM3_FILTER_TF=1h | FX2: MOM3_FILTER_TF=15m | FY2: MOMENTUM_BREAKOUT_FILTER_TF=OFF | FZ2: MOMENTUM_BREAKOUT_FILTER_TF=D | GA2: MOMENTUM_BREAKOUT_FILTER_TF=4h | GB2: MOMENTUM_BREAKOUT_FILTER_TF=1h | GC2: MOMENTUM_BREAKOUT_FILTER_TF=15m | GD2: MTF_ARMED_ENTRIES_FILTER_TF=OFF | GE2: MTF_ARMED_ENTRIES_FILTER_TF=D | GF2: MTF_ARMED_ENTRIES_FILTER_TF=4h | GG2: MTF_ARMED_ENTRIES_FILTER_TF=1h | GH2: MTF_ARMED_ENTRIES_FILTER_TF=15m | GI2: MTF_ATR_TRAIL_FILTER_TF=OFF | GJ2: MTF_ATR_TRAIL_FILTER_TF=D | GK2: MTF_ATR_TRAIL_FILTER_TF=4h | GL2: MTF_ATR_TRAIL_FILTER_TF=1h | GM2: MTF_ATR_TRAIL_FILTER_TF=15m | GN2: MTF_DC_REJECT_FILTER_TF=OFF | GO2: MTF_DC_REJECT_FILTER_TF=D | GP2: MTF_DC_REJECT_FILTER_TF=4h | GQ2: MTF_DC_REJECT_FILTER_TF=1h | GR2: MTF_DC_REJECT_FILTER_TF=15m | GS2: NEWBORN_LOSS_KILL_FILTER_TF=OFF | GT2: NEWBORN_LOSS_KILL_FILTER_TF=D | GU2: NEWBORN_LOSS_KILL_FILTER_TF=4h | GV2: NEWBORN_LOSS_KILL_FILTER_TF=1h | GW2: NEWBORN_LOSS_KILL_FILTER_TF=15m | GX2: NEWBORN_PROTECT_FILTER_TF=OFF | GY2: NEWBORN_PROTECT_FILTER_TF=D | GZ2: NEWBORN_PROTECT_FILTER_TF=4h | HA2: NEWBORN_PROTECT_FILTER_TF=1h | HB2: NEWBORN_PROTECT_FILTER_TF=15m | HC2: NOLOSS_BYPASS_WT5OF5_FILTER_TF=OFF | HD2: NOLOSS_BYPASS_WT5OF5_FILTER_TF=D | HE2: NOLOSS_BYPASS_WT5OF5_FILTER_TF=4h | HF2: NOLOSS_BYPASS_WT5OF5_FILTER_TF=1h | HG2: NOLOSS_BYPASS_WT5OF5_FILTER_TF=15m | HH2: OPEN_INTENT_SIZE_GATES_FILTER_TF=OFF | HI2: OPEN_INTENT_SIZE_GATES_FILTER_TF=D | HJ2: OPEN_INTENT_SIZE_GATES_FILTER_TF=4h | HK2: OPEN_INTENT_SIZE_GATES_FILTER_TF=1h | HL2: OPEN_INTENT_SIZE_GATES_FILTER_TF=15m | HM2: PARTIAL_PROFIT_LOCK_V2_FILTER_TF=OFF | HN2: PARTIAL_PROFIT_LOCK_V2_FILTER_TF=D | HO2: PARTIAL_PROFIT_LOCK_V2_FILTER_TF=4h | HP2: PARTIAL_PROFIT_LOCK_V2_FILTER_TF=1h | HQ2: PARTIAL_PROFIT_LOCK_V2_FILTER_TF=15m | HR2: PEAK_GIVEBACK_BE_EROSION_FILTER_TF=OFF | HS2: PEAK_GIVEBACK_BE_EROSION_FILTER_TF=D | HT2: PEAK_GIVEBACK_BE_EROSION_FILTER_TF=4h | HU2: PEAK_GIVEBACK_BE_EROSION_FILTER_TF=1h | HV2: PEAK_GIVEBACK_BE_EROSION_FILTER_TF=15m | HW2: WT_15M_BOUNCE_BB_MAX=0.95 | HX2: WT_15M_BOUNCE_BB_MAX=0.9 | HY2: WT_15M_BOUNCE_BB_MAX=0.8 | HZ2: WT_15M_BOUNCE_BB_MIN=0.05 | IA2: WT_15M_BOUNCE_BB_MIN=0.1 | IB2: WT_15M_BOUNCE_BB_MIN=0.2 | IC2: WT_15M_BOUNCE_HIGH_1H_GT_PREV=True | ID2: WT_15M_BOUNCE_HIGH_1H_GT_PREV=False | IE2: WT_15M_BOUNCE_LOW_1H_GT_PREV=True | IF2: WT_15M_BOUNCE_LOW_1H_GT_PREV=False | IG2: WT_15M_BOUNCE_REL_VOL_GT_1=True | IH2: WT_15M_BOUNCE_REL_VOL_GT_1=False | II2: Live Location | IJ2: Vec Hook | IK2: Type | IL2: Correct Options
A3: HLR_REENTRY_MULT_1H | B3: 0.75 | E3: =MAX('REENTRY_WINDOWED'!E:E) | F3: -1.8787217 | G3: -3.5348756 | H3: =IFERROR(VLOOKUP($A3,Results_30d_Deltas!$A$2:$H$5000,6,FALSE),"") | K3: =IF(B3=C3,"YES","NO") | IJ3: ez_manage.py:4846 top() | IK3: v12_quick_engine.py:2026 x7
A4: HLR_REENTRY_MULT_1H | B4: 1.125 | E4: =IF(F4="",E3,IF(F4>0,E3+F4,E3)) | F4: 0 | G4: -1.6561539 | H4: =IFERROR(VLOOKUP($A4,Results_30d_Deltas!$A$2:$H$5000,6,FALSE),"") | K4: =IF(B4=C4,"YES","NO") | IJ4: ez_manage.py:4846 top() | IK4: v12_quick_engine.py:2026 x7
A5: HLR_REENTRY_MULT_1H | B5: 1.5 | E5: =IF(F5="",E4,IF(F5>0,E4+F5,E4)) | F5: -1.8934256 | G5: -3.5495795 | H5: =IFERROR(VLOOKUP($A5,Results_30d_Deltas!$A$2:$H$5000,6,FALSE),"") | K5: =IF(B5=C5,"YES","NO") | IJ5: ez_manage.py:4846 top() | IK5: v12_quick_engine.py:2026 x7
A6: HLR_REENTRY_MULT_1H | B6: 1.875 | E6: =IF(F6="",E5,IF(F6>0,E5+F6,E5)) | F6: 0 | G6: -1.6561539 | H6: =IFERROR(VLOOKUP($A6,Results_30d_Deltas!$A$2:$H$5000,6,FALSE),"") | K6: =IF(B6=C6,"YES","NO") | IJ6: ez_manage.py:4846 top() | IK6: v12_quick_engine.py:2026 x7
A7: HLR_REENTRY_MULT_1H | B7: 2.25 | E7: =IF(F7="",E6,IF(F7>0,E6+F7,E6)) | F7: 0 | G7: -1.6561539 | H7: =IFERROR(VLOOKUP($A7,Results_30d_Deltas!$A$2:$H$5000,6,FALSE),"") | K7: =IF(B7=C7,"YES","NO") | IJ7: ez_manage.py:4846 top() | IK7: v12_quick_engine.py:2026 x7
A8: CHANNEL_REENTRY_STOP_ENABLED | B8: False | E8: =IF(F8="",E7,IF(F8>0,E7+F8,E7)) | F8: =IFERROR(VLOOKUP($A8&"="&$B8,Results_30d_Deltas!$A$2:$H$5000,5,FALSE),"") | G8: =IFERROR(VLOOKUP($A8,Results_30d_Deltas!$A$2:$H$5000,7,FALSE)-E7,"") | H8: =IFERROR(VLOOKUP($A8,Results_30d_Deltas!$A$2:$H$5000,6,FALSE),"") | K8: =IF(B8=C8,"YES","NO") | IJ8: ez_manage.py:5968 top() | IK8: v12_quick_engine.py:482 x8
A9: CHANNEL_REENTRY_STOP_ENABLED | B9: True | E9: =IF(F9="",E8,IF(F9>0,E8+F9,E8)) | F9: 0 | G9: -1.6561539 | H9: =IFERROR(VLOOKUP($A9,Results_30d_Deltas!$A$2:$H$5000,6,FALSE),"") | K9: =IF(B9=C9,"YES","NO") | IJ9: ez_manage.py:5968 top() | IK9: v12_quick_engine.py:482 x8
A10: DAEMON_REENTRY_STALE_EXIT_ENABLED | B10: False | E10: =IF(F10="",E9,IF(F10>0,E9+F10,E9)) | F10: =IFERROR(VLOOKUP($A10&"="&$B10,Results_30d_Deltas!$A$2:$H$5000,5,FALSE),"") | G10: =IFERROR(VLOOKUP($A10,Results_30d_Deltas!$A$2:$H$5000,7,FALSE)-E9,"") | H10: =IFERROR(VLOOKUP($A10,Results_30d_Deltas!$A$2:$H$5000,6,FALSE),"") | K10: =IF(B10=C10,"YES","NO") | IJ10: ez_manage.py:4561 top() | IK10: v12_quick_engine.py:519 x9
A11: DAEMON_REENTRY_STALE_EXIT_ENABLED | B11: True | E11: =IF(F11="",E10,IF(F11>0,E10+F11,E10)) | F11: -1.8526111 | G11: -3.508765 | H11: =IFERROR(VLOOKUP($A11,Results_30d_Deltas!$A$2:$H$5000,6,FALSE),"") | K11: =IF(B11=C11,"YES","NO") | IJ11: ez_manage.py:4561 top() | IK11: v12_quick_engine.py:519 x9
A12: BREAKOUT_LEASH_REENTRY_MULT | B12: 0 | E12: =IF(F12="",E11,IF(F12>0,E11+F12,E11)) | F12: 0 | G12: -1.6561539 | H12: =IFERROR(VLOOKUP($A12,Results_30d_Deltas!$A$2:$H$5000,6,FALSE),"") | K12: =IF(B12=C12,"YES","NO") | IJ12: ez_manage.py:2999 top() | IK12: v12_quick_engine.py:371 x12
A13: BREAKOUT_LEASH_REENTRY_MULT | B13: 0.5 | E13: =IF(F13="",E12,IF(F13>0,E12+F13,E12)) | F13: -2.4538266 | G13: -4.1099804 | H13: =IFERROR(VLOOKUP($A13,Results_30d_Deltas!$A$2:$H$5000,6,FALSE),"") | K13: =IF(B13=C13,"YES","NO") | IJ13: ez_manage.py:2999 top() | IK13: v12_quick_engine.py:371 x12
A14: BREAKOUT_LEASH_REENTRY_MULT | B14: 1.0 | E14: =IF(F14="",E13,IF(F14>0,E13+F14,E13)) | F14: -2.0245238 | G14: -3.6806777 | H14: =IFERROR(VLOOKUP($A14,Results_30d_Deltas!$A$2:$H$5000,6,FALSE),"") | K14: =IF(B14=C14,"YES","NO") | IJ14: ez_manage.py:2999 top() | IK14: v12_quick_engine.py:371 x12
A15: BREAKOUT_LEASH_REENTRY_MULT | B15: 2.0 | E15: =IF(F15="",E14,IF(F15>0,E14+F15,E14)) | F15: 0 | G15: -1.6561539 | H15: =IFERROR(VLOOKUP($A15,Results_30d_Deltas!$A$2:$H$5000,6,FALSE),"") | K15: =IF(B15=C15,"YES","NO") | IJ15: ez_manage.py:2999 top() | IK15: v12_quick_engine.py:371 x12
A16: DAEMON_REENTRY_SHORT_WT_XUNDER_GATE_ENABLED | B16: False | E16: =IF(F16="",E15,IF(F16>0,E15+F16,E15)) | F16: =IFERROR(VLOOKUP($A16&"="&$B16,Results_30d_Deltas!$A$2:$H$5000,5,FALSE),"") | G16: =IFERROR(VLOOKUP($A16,Results_30d_Deltas!$A$2:$H$5000,7,FALSE)-E15,"") | H16: =IFERROR(VLOOKUP($A16,Results_30d_Deltas!$A$2:$H$5000,6,FALSE),"") | K16: =IF(B16=C16,"YES","NO") | IJ16: ez_manage.py:4560 top() | IK16: v12_quick_engine.py:513 x9
A17: DAEMON_REENTRY_SHORT_WT_XUNDER_GATE_ENABLED | B17: True | E17: =IF(F17="",E16,IF(F17>0,E16+F17,E16)) | F17: 0 | G17: -1.6561539 | H17: =IFERROR(VLOOKUP($A17,Results_30d_Deltas!$A$2:$H$5000,6,FALSE),"") | K17: =IF(B17=C17,"YES","NO") | IJ17: ez_manage.py:4560 top() | IK17: v12_quick_engine.py:513 x9
A18: HLR_REENTRY_MAX_AGE_S | B18: 0 | E18: =IF(F18="",E17,IF(F18>0,E17+F18,E17)) | F18: -1.0393426 | G18: -2.6954965 | H18: =IFERROR(VLOOKUP($A18,Results_30d_Deltas!$A$2:$H$5000,6,FALSE),"") | K18: =IF(B18=C18,"YES","NO") | IJ18: ez_manage.py:4844 top() | IK18: v12_quick_engine.py:2024 x4
A19: HLR_REENTRY_MAX_AGE_S | B19: 0.5 | E19: =IF(F19="",E18,IF(F19>0,E18+F19,E18)) | F19: 0 | G19: -1.6561539 | H19: =IFERROR(VLOOKUP($A19,Results_30d_Deltas!$A$2:$H$5000,6,FALSE),"") | K19: =IF(B19=C19,"YES","NO") | IJ19: ez_manage.py:4844 top() | IK19: v12_quick_engine.py:2024 x4
A20: HLR_REENTRY_MAX_AGE_S | B20: 1.0 | E20: =IF(F20="",E19,IF(F20>0,E19+F20,E19)) | F20: 0 | G20: -1.6561539 | H20: =IFERROR(VLOOKUP($A20,Results_30d_Deltas!$A$2:$H$5000,6,FALSE),"") | K20: =IF(B20=C20,"YES","NO") | IJ20: ez_manage.py:4844 top() | IK20: v12_quick_engine.py:2024 x4
A21: HLR_REENTRY_MAX_AGE_S | B21: 2.0 | E21: =IF(F21="",E20,IF(F21>0,E20+F21,E20)) | F21: -1.7345709 | G21: -3.3907247 | H21: =IFERROR(VLOOKUP($A21,Results_30d_Deltas!$A$2:$H$5000,6,FALSE),"") | K21: =IF(B21=C21,"YES","NO") | IJ21: ez_manage.py:4844 top() | IK21: v12_quick_engine.py:2024 x4
A22: HLR_REENTRY_MULT_4H | B22: 1.0 | E22: =IF(F22="",E21,IF(F22>0,E21+F22,E21)) | F22: -1.7240473 | G22: -3.3802012 | H22: =IFERROR(VLOOKUP($A22,Results_30d_Deltas!$A$2:$H$5000,6,FALSE),"") | K22: =IF(B22=C22,"YES","NO") | IJ22: ez_manage.py:4847 top() | IK22: v12_quick_engine.py:2027 x6
A23: HLR_REENTRY_MULT_4H | B23: 1.5 | E23: =IF(F23="",E22,IF(F23>0,E22+F23,E22)) | F23: 0 | G23: -1.6561539 | H23: =IFERROR(VLOOKUP($A23,Results_30d_Deltas!$A$2:$H$5000,6,FALSE),"") | K23: =IF(B23=C23,"YES","NO") | IJ23: ez_manage.py:4847 top() | IK23: v12_quick_engine.py:2027 x6
A24: HLR_REENTRY_MULT_4H | B24: 2.0 | E24: =IF(F24="",E23,IF(F24>0,E23+F24,E23)) | F24: 0 | G24: -1.6561539 | H24: =IFERROR(VLOOKUP($A24,Results_30d_Deltas!$A$2:$H$5000,6,FALSE),"") | K24: =IF(B24=C24,"YES","NO") | IJ24: ez_manage.py:4847 top() | IK24: v12_quick_engine.py:2027 x6
A25: HLR_REENTRY_MULT_4H | B25: 2.5 | E25: =IF(F25="",E24,IF(F25>0,E24+F25,E24)) | F25: -2.4538266 | G25: -4.1099804 | H25: =IFERROR(VLOOKUP($A25,Results_30d_Deltas!$A$2:$H$5000,6,FALSE),"") | K25: =IF(B25=C25,"YES","NO") | IJ25: ez_manage.py:4847 top() | IK25: v12_quick_engine.py:2027 x6
A26: HLR_REENTRY_MULT_4H | B26: 3.0 | E26: =IF(F26="",E25,IF(F26>0,E25+F26,E25)) | F26: -1.0393426 | G26: -2.6954965 | H26: =IFERROR(VLOOKUP($A26,Results_30d_Deltas!$A$2:$H$5000,6,FALSE),"") | K26: =IF(B26=C26,"YES","NO") | IJ26: ez_manage.py:4847 top() | IK26: v12_quick_engine.py:2027 x6
A27: HLR_REENTRY_MULT_D | B27: 1.25 | E27: =IF(F27="",E26,IF(F27>0,E26+F27,E26)) | F27: 0 | G27: -1.6561539 | H27: =IFERROR(VLOOKUP($A27,Results_30d_Deltas!$A$2:$H$5000,6,FALSE),"") | K27: =IF(B27=C27,"YES","NO") | IJ27: ez_manage.py:4848 top() | IK27: v12_quick_engine.py:2028 x4
A28: HLR_REENTRY_MULT_D | B28: 1.875 | E28: =IF(F28="",E27,IF(F28>0,E27+F28,E27)) | F28: -1.7073607 | G28: -3.3635146 | H28: =IFERROR(VLOOKUP($A28,Results_30d_Deltas!$A$2:$H$5000,6,FALSE),"") | K28: =IF(B28=C28,"YES","NO") | IJ28: ez_manage.py:4848 top() | IK28: v12_quick_engine.py:2028 x4
... A40: REENTRY_SIZE_BREAKOUT_MULT | B40: 2.0 | E40: =IF(F40="",E39,IF(F40>0,E39+F40,E39)) | F40: 0 | G40: -1.6561539 | H40: =IFERROR(VLOOKUP($A40,Results_30d_Deltas!$A$2:$H$5000,6,FALSE),"") | K40: =IF(B40=C40,"YES","NO") | IJ40: ez_manage.py:3870 top() | IK40: v12_quick_engine.py:2903 x3

Sheet AUGMENT_TREND
A1: 08 AUGMENT_TREND - 5 bases -> 24 rows - 231 per-row FULLY CONNECTED
A2: Switch | B2: default | C2: override | D2: Family | E2: BASELINE | F2: VECTOR_DELTA | G2: LIVE_DELTA | H2: LIVE_SHARPE | I2: REAL_COMPLETE | J2: PER_ROW_FILTERS | K2: is_default (backup if bold lost) | L2: ATR_TRAIL_FILTER_TF=OFF | M2: ATR_TRAIL_FILTER_TF=D | N2: ATR_TRAIL_FILTER_TF=4h | O2: ATR_TRAIL_FILTER_TF=1h | P2: ATR_TRAIL_FILTER_TF=15m | Q2: BAR_PATTERNS_FILTER_TF=OFF | R2: BAR_PATTERNS_FILTER_TF=D | S2: BAR_PATTERNS_FILTER_TF=4h | T2: BAR_PATTERNS_FILTER_TF=1h | U2: BAR_PATTERNS_FILTER_TF=15m | V2: BB_PULLBACK_GATE_FILTER_TF=OFF | W2: BB_PULLBACK_GATE_FILTER_TF=D | X2: BB_PULLBACK_GATE_FILTER_TF=4h | Y2: BB_PULLBACK_GATE_FILTER_TF=1h | Z2: BB_PULLBACK_GATE_FILTER_TF=15m | AA2: BB_RECOVERY_ENTRY_FILTER_TF=OFF | AB2: BB_RECOVERY_ENTRY_FILTER_TF=D | AC2: BB_RECOVERY_ENTRY_FILTER_TF=4h | AD2: BB_RECOVERY_ENTRY_FILTER_TF=1h | AE2: BB_RECOVERY_ENTRY_FILTER_TF=15m | AF2: BB_RECOVERY_FILTER_TF=OFF | AG2: BB_RECOVERY_FILTER_TF=D | AH2: BB_RECOVERY_FILTER_TF=4h | AI2: BB_RECOVERY_FILTER_TF=1h | AJ2: BB_RECOVERY_FILTER_TF=15m | AK2: BREAKEVEN_GAIN_EROSION_FILTER_TF=OFF | AL2: BREAKEVEN_GAIN_EROSION_FILTER_TF=D | AM2: BREAKEVEN_GAIN_EROSION_FILTER_TF=4h | AN2: BREAKEVEN_GAIN_EROSION_FILTER_TF=1h | AO2: BREAKEVEN_GAIN_EROSION_FILTER_TF=15m | AP2: BREAKOUT_RETEST_FILTER_TF=OFF | AQ2: BREAKOUT_RETEST_FILTER_TF=D | AR2: BREAKOUT_RETEST_FILTER_TF=4h | AS2: BREAKOUT_RETEST_FILTER_TF=1h | AT2: BREAKOUT_RETEST_FILTER_TF=15m | AU2: BT_WT_CROSS_LADDER_FILTER_TF=OFF | AV2: BT_WT_CROSS_LADDER_FILTER_TF=D | AW2: BT_WT_CROSS_LADDER_FILTER_TF=4h | AX2: BT_WT_CROSS_LADDER_FILTER_TF=1h | AY2: BT_WT_CROSS_LADDER_FILTER_TF=15m | AZ2: CANDLE_PATTERN_STOPS_FILTER_TF=OFF | BA2: CANDLE_PATTERN_STOPS_FILTER_TF=D | BB2: CANDLE_PATTERN_STOPS_FILTER_TF=4h | BC2: CANDLE_PATTERN_STOPS_FILTER_TF=1h | BD2: CANDLE_PATTERN_STOPS_FILTER_TF=15m | BE2: CIRCUIT_SHARPE_GATES_FILTER_TF=OFF | BF2: CIRCUIT_SHARPE_GATES_FILTER_TF=D | BG2: CIRCUIT_SHARPE_GATES_FILTER_TF=4h | BH2: CIRCUIT_SHARPE_GATES_FILTER_TF=1h | BI2: CIRCUIT_SHARPE_GATES_FILTER_TF=15m | BJ2: DC_BREACH_REDUCE_FILTER_TF=OFF | BK2: DC_BREACH_REDUCE_FILTER_TF=D | BL2: DC_BREACH_REDUCE_FILTER_TF=4h | BM2: DC_BREACH_REDUCE_FILTER_TF=1h | BN2: DC_BREACH_REDUCE_FILTER_TF=15m | BO2: DC_BREAK_FILTER_TF=OFF | BP2: DC_BREAK_FILTER_TF=D | BQ2: DC_BREAK_FILTER_TF=4h | BR2: DC_BREAK_FILTER_TF=1h | BS2: DC_BREAK_FILTER_TF=15m | BT2: DC_MOMENTUM_BOTA_SCORER_FILTER_TF=OFF | BU2: DC_MOMENTUM_BOTA_SCORER_FILTER_TF=D | BV2: DC_MOMENTUM_BOTA_SCORER_FILTER_TF=4h | BW2: DC_MOMENTUM_BOTA_SCORER_FILTER_TF=1h | BX2: DC_MOMENTUM_BOTA_SCORER_FILTER_TF=15m | BY2: DELTA_ENGINE_FILTER_TF=OFF | BZ2: DELTA_ENGINE_FILTER_TF=D | CA2: DELTA_ENGINE_FILTER_TF=4h | CB2: DELTA_ENGINE_FILTER_TF=1h | CC2: DELTA_ENGINE_FILTER_TF=15m | CD2: EMA_9_21_FILTER_FILTER_TF=OFF | CE2: EMA_9_21_FILTER_FILTER_TF=D | CF2: EMA_9_21_FILTER_FILTER_TF=4h | CG2: EMA_9_21_FILTER_FILTER_TF=1h | CH2: EMA_9_21_FILTER_FILTER_TF=15m | CI2: EMA_BLANKET_FILTER_FILTER_TF=OFF | CJ2: EMA_BLANKET_FILTER_FILTER_TF=D | CK2: EMA_BLANKET_FILTER_FILTER_TF=4h | CL2: EMA_BLANKET_FILTER_FILTER_TF=1h | CM2: EMA_BLANKET_FILTER_FILTER_TF=15m | CN2: EMERGENCY_BRAKE_FILTER_TF=OFF | CO2: EMERGENCY_BRAKE_FILTER_TF=D | CP2: EMERGENCY_BRAKE_FILTER_TF=4h | CQ2: EMERGENCY_BRAKE_FILTER_TF=1h | CR2: EMERGENCY_BRAKE_FILTER_TF=15m | CS2: EXIT_R1_R2_FILTER_TF=OFF | CT2: EXIT_R1_R2_FILTER_TF=D | CU2: EXIT_R1_R2_FILTER_TF=4h | CV2: EXIT_R1_R2_FILTER_TF=1h | CW2: EXIT_R1_R2_FILTER_TF=15m | CX2: EXIT_TIGHT_BREAKOUT_SCORER_FILTER_TF=OFF | CY2: EXIT_TIGHT_BREAKOUT_SCORER_FILTER_TF=D | CZ2: EXIT_TIGHT_BREAKOUT_SCORER_FILTER_TF=4h | DA2: EXIT_TIGHT_BREAKOUT_SCORER_FILTER_TF=1h | DB2: EXIT_TIGHT_BREAKOUT_SCORER_FILTER_TF=15m | DC2: EXIT_TOP_FADE_FILTER_TF=OFF | DD2: EXIT_TOP_FADE_FILTER_TF=D | DE2: EXIT_TOP_FADE_FILTER_TF=4h | DF2: EXIT_TOP_FADE_FILTER_TF=1h | DG2: EXIT_TOP_FADE_FILTER_TF=15m | DH2: EXIT_TO_REDUCE_ADAPTER_FILTER_TF=OFF | DI2: EXIT_TO_REDUCE_ADAPTER_FILTER_TF=D | DJ2: EXIT_TO_REDUCE_ADAPTER_FILTER_TF=4h | DK2: EXIT_TO_REDUCE_ADAPTER_FILTER_TF=1h | DL2: EXIT_TO_REDUCE_ADAPTER_FILTER_TF=15m | DM2: FAST_RISER_FILTER_TF=OFF | DN2: FAST_RISER_FILTER_TF=D | DO2: FAST_RISER_FILTER_TF=4h | DP2: FAST_RISER_FILTER_TF=1h | DQ2: FAST_RISER_FILTER_TF=15m | DR2: FH_MOMENTUM_FILTER_TF=OFF | DS2: FH_MOMENTUM_FILTER_TF=D | DT2: FH_MOMENTUM_FILTER_TF=4h | DU2: FH_MOMENTUM_FILTER_TF=1h | DV2: FH_MOMENTUM_FILTER_TF=15m | DW2: FIRST_OPEN_THROTTLE_FILTER_TF=OFF | DX2: FIRST_OPEN_THROTTLE_FILTER_TF=D | DY2: FIRST_OPEN_THROTTLE_FILTER_TF=4h | DZ2: FIRST_OPEN_THROTTLE_FILTER_TF=1h | EA2: FIRST_OPEN_THROTTLE_FILTER_TF=15m | EB2: FROZEN_STOP_FILTER_TF=OFF | EC2: FROZEN_STOP_FILTER_TF=D | ED2: FROZEN_STOP_FILTER_TF=4h | EE2: FROZEN_STOP_FILTER_TF=1h | EF2: FROZEN_STOP_FILTER_TF=15m | EG2: GOLDEN_RULE_ENFORCE_FILTER_TF=OFF | EH2: GOLDEN_RULE_ENFORCE_FILTER_TF=D | EI2: GOLDEN_RULE_ENFORCE_FILTER_TF=4h | EJ2: GOLDEN_RULE_ENFORCE_FILTER_TF=1h | EK2: GOLDEN_RULE_ENFORCE_FILTER_TF=15m | EL2: GOLDEN_RULE_HTF_VOTE_FILTER_TF=OFF | EM2: GOLDEN_RULE_HTF_VOTE_FILTER_TF=D | EN2: GOLDEN_RULE_HTF_VOTE_FILTER_TF=4h | EO2: GOLDEN_RULE_HTF_VOTE_FILTER_TF=1h | EP2: GOLDEN_RULE_HTF_VOTE_FILTER_TF=15m | EQ2: GR_FILTER_VEC_FILTER_TF=OFF | ER2: GR_FILTER_VEC_FILTER_TF=D | ES2: GR_FILTER_VEC_FILTER_TF=4h | ET2: GR_FILTER_VEC_FILTER_TF=1h | EU2: GR_FILTER_VEC_FILTER_TF=15m | EV2: GR_V5_STATE_FILTER_TF=OFF | EW2: GR_V5_STATE_FILTER_TF=D | EX2: GR_V5_STATE_FILTER_TF=4h | EY2: GR_V5_STATE_FILTER_TF=1h | EZ2: GR_V5_STATE_FILTER_TF=15m | FA2: HAIKU_WINNER_FILTER_TF=OFF | FB2: HAIKU_WINNER_FILTER_TF=D | FC2: HAIKU_WINNER_FILTER_TF=4h | FD2: HAIKU_WINNER_FILTER_TF=1h | FE2: HAIKU_WINNER_FILTER_TF=15m | FF2: LH_HL_FILTER_TF_REQ=2 | FG2: LH_HL_FILTER_TF_REQ=2_ALT | FH2: LIVE_ENTRY_ENGINE_FILTER_TF=OFF | FI2: LIVE_ENTRY_ENGINE_FILTER_TF=D | FJ2: LIVE_ENTRY_ENGINE_FILTER_TF=4h | FK2: LIVE_ENTRY_ENGINE_FILTER_TF=1h | FL2: LIVE_ENTRY_ENGINE_FILTER_TF=15m | FM2: LIVE_ONLY_SIGNALS_BATCH5_FILTER_TF=OFF | FN2: LIVE_ONLY_SIGNALS_BATCH5_FILTER_TF=D | FO2: LIVE_ONLY_SIGNALS_BATCH5_FILTER_TF=4h | FP2: LIVE_ONLY_SIGNALS_BATCH5_FILTER_TF=1h | FQ2: LIVE_ONLY_SIGNALS_BATCH5_FILTER_TF=15m | FR2: MANDATORY_REENTRY_WT_FILTER_TF_MODE=15m_only | FS2: MANDATORY_REENTRY_WT_FILTER_TF_MODE=15m_only_ALT | FT2: MOM3_FILTER_TF=OFF | FU2: MOM3_FILTER_TF=D | FV2: MOM3_FILTER_TF=4h | FW2: MOM3_FILTER_TF=1h | FX2: MOM3_FILTER_TF=15m | FY2: MOMENTUM_BREAKOUT_FILTER_TF=OFF | FZ2: MOMENTUM_BREAKOUT_FILTER_TF=D | GA2: MOMENTUM_BREAKOUT_FILTER_TF=4h | GB2: MOMENTUM_BREAKOUT_FILTER_TF=1h | GC2: MOMENTUM_BREAKOUT_FILTER_TF=15m | GD2: MTF_ARMED_ENTRIES_FILTER_TF=OFF | GE2: MTF_ARMED_ENTRIES_FILTER_TF=D | GF2: MTF_ARMED_ENTRIES_FILTER_TF=4h | GG2: MTF_ARMED_ENTRIES_FILTER_TF=1h | GH2: MTF_ARMED_ENTRIES_FILTER_TF=15m | GI2: MTF_ATR_TRAIL_FILTER_TF=OFF | GJ2: MTF_ATR_TRAIL_FILTER_TF=D | GK2: MTF_ATR_TRAIL_FILTER_TF=4h | GL2: MTF_ATR_TRAIL_FILTER_TF=1h | GM2: MTF_ATR_TRAIL_FILTER_TF=15m | GN2: MTF_DC_REJECT_FILTER_TF=OFF | GO2: MTF_DC_REJECT_FILTER_TF=D | GP2: MTF_DC_REJECT_FILTER_TF=4h | GQ2: MTF_DC_REJECT_FILTER_TF=1h | GR2: MTF_DC_REJECT_FILTER_TF=15m | GS2: NEWBORN_LOSS_KILL_FILTER_TF=OFF | GT2: NEWBORN_LOSS_KILL_FILTER_TF=D | GU2: NEWBORN_LOSS_KILL_FILTER_TF=4h | GV2: NEWBORN_LOSS_KILL_FILTER_TF=1h | GW2: NEWBORN_LOSS_KILL_FILTER_TF=15m | GX2: NEWBORN_PROTECT_FILTER_TF=OFF | GY2: NEWBORN_PROTECT_FILTER_TF=D | GZ2: NEWBORN_PROTECT_FILTER_TF=4h | HA2: NEWBORN_PROTECT_FILTER_TF=1h | HB2: NEWBORN_PROTECT_FILTER_TF=15m | HC2: NOLOSS_BYPASS_WT5OF5_FILTER_TF=OFF | HD2: NOLOSS_BYPASS_WT5OF5_FILTER_TF=D | HE2: NOLOSS_BYPASS_WT5OF5_FILTER_TF=4h | HF2: NOLOSS_BYPASS_WT5OF5_FILTER_TF=1h | HG2: NOLOSS_BYPASS_WT5OF5_FILTER_TF=15m | HH2: OPEN_INTENT_SIZE_GATES_FILTER_TF=OFF | HI2: OPEN_INTENT_SIZE_GATES_FILTER_TF=D | HJ2: OPEN_INTENT_SIZE_GATES_FILTER_TF=4h | HK2: OPEN_INTENT_SIZE_GATES_FILTER_TF=1h | HL2: OPEN_INTENT_SIZE_GATES_FILTER_TF=15m | HM2: PARTIAL_PROFIT_LOCK_V2_FILTER_TF=OFF | HN2: PARTIAL_PROFIT_LOCK_V2_FILTER_TF=D | HO2: PARTIAL_PROFIT_LOCK_V2_FILTER_TF=4h | HP2: PARTIAL_PROFIT_LOCK_V2_FILTER_TF=1h | HQ2: PARTIAL_PROFIT_LOCK_V2_FILTER_TF=15m | HR2: PEAK_GIVEBACK_BE_EROSION_FILTER_TF=OFF | HS2: PEAK_GIVEBACK_BE_EROSION_FILTER_TF=D | HT2: PEAK_GIVEBACK_BE_EROSION_FILTER_TF=4h | HU2: PEAK_GIVEBACK_BE_EROSION_FILTER_TF=1h | HV2: PEAK_GIVEBACK_BE_EROSION_FILTER_TF=15m | HW2: WT_15M_BOUNCE_BB_MAX=0.95 | HX2: WT_15M_BOUNCE_BB_MAX=0.9 | HY2: WT_15M_BOUNCE_BB_MAX=0.8 | HZ2: WT_15M_BOUNCE_BB_MIN=0.05 | IA2: WT_15M_BOUNCE_BB_MIN=0.1 | IB2: WT_15M_BOUNCE_BB_MIN=0.2 | IC2: WT_15M_BOUNCE_HIGH_1H_GT_PREV=True | ID2: WT_15M_BOUNCE_HIGH_1H_GT_PREV=False | IE2: WT_15M_BOUNCE_LOW_1H_GT_PREV=True | IF2: WT_15M_BOUNCE_LOW_1H_GT_PREV=False | IG2: WT_15M_BOUNCE_REL_VOL_GT_1=True | IH2: WT_15M_BOUNCE_REL_VOL_GT_1=False | II2: Live Location | IJ2: Vec Hook | IK2: Type | IL2: Correct Options
A3: AUGMENT_MIN_GAIN_PCT | B3: 0.25 | E3: =MAX('REENTRY_ADAPTIVE'!E:E) | F3: 5.2559977 | G3: 3.5998438 | H3: =IFERROR(VLOOKUP($A3,Results_30d_Deltas!$A$2:$H$5000,6,FALSE),"") | K3: =IF(B3=C3,"YES","NO") | IJ3: ez_manage.py:30417 top() | IK3: v12_quick_engine.py:4874 x5
A4: AUGMENT_MIN_GAIN_PCT | B4: 0.375 | E4: =IF(F4="",E3,IF(F4>0,E3+F4,E3)) | F4: 4.8859491 | G4: 3.2297952 | H4: =IFERROR(VLOOKUP($A4,Results_30d_Deltas!$A$2:$H$5000,6,FALSE),"") | K4: =IF(B4=C4,"YES","NO") | IJ4: ez_manage.py:30417 top() | IK4: v12_quick_engine.py:4874 x5
A5: AUGMENT_MIN_GAIN_PCT | B5: 0.5 | E5: =IF(F5="",E4,IF(F5>0,E4+F5,E4)) | F5: -1.7073607 | G5: -3.3635146 | H5: =IFERROR(VLOOKUP($A5,Results_30d_Deltas!$A$2:$H$5000,6,FALSE),"") | K5: =IF(B5=C5,"YES","NO") | IJ5: ez_manage.py:30417 top() | IK5: v12_quick_engine.py:4874 x5
A6: AUGMENT_MIN_GAIN_PCT | B6: 0.625 | E6: =IF(F6="",E5,IF(F6>0,E5+F6,E5)) | F6: 5.0570863 | G6: 3.4009324 | H6: =IFERROR(VLOOKUP($A6,Results_30d_Deltas!$A$2:$H$5000,6,FALSE),"") | K6: =IF(B6=C6,"YES","NO") | IJ6: ez_manage.py:30417 top() | IK6: v12_quick_engine.py:4874 x5
A7: AUGMENT_MIN_GAIN_PCT | B7: 0.75 | E7: =IF(F7="",E6,IF(F7>0,E6+F7,E6)) | F7: 5.2280546 | G7: 3.5719007 | H7: =IFERROR(VLOOKUP($A7,Results_30d_Deltas!$A$2:$H$5000,6,FALSE),"") | K7: =IF(B7=C7,"YES","NO") | IJ7: ez_manage.py:30417 top() | IK7: v12_quick_engine.py:4874 x5
A8: BOUNCE_AUGMENT_MIN_LOSS_PCT | B8: -0.75 | E8: =IF(F8="",E7,IF(F8>0,E7+F8,E7)) | F8: 0 | G8: -1.6561539 | H8: =IFERROR(VLOOKUP($A8,Results_30d_Deltas!$A$2:$H$5000,6,FALSE),"") | K8: =IF(B8=C8,"YES","NO") | IJ8: ez_manage.py:4390 top() | IK8: v12_quick_engine.py:1310 x9
A9: BOUNCE_AUGMENT_MIN_LOSS_PCT | B9: -0.625 | E9: =IF(F9="",E8,IF(F9>0,E8+F9,E8)) | F9: -1.8787217 | G9: -3.5348756 | H9: =IFERROR(VLOOKUP($A9,Results_30d_Deltas!$A$2:$H$5000,6,FALSE),"") | K9: =IF(B9=C9,"YES","NO") | IJ9: ez_manage.py:4390 top() | IK9: v12_quick_engine.py:1310 x9
A10: BOUNCE_AUGMENT_MIN_LOSS_PCT | B10: -0.5 | E10: =IF(F10="",E9,IF(F10>0,E9+F10,E9)) | F10: -1.7345709 | G10: -3.3907247 | H10: =IFERROR(VLOOKUP($A10,Results_30d_Deltas!$A$2:$H$5000,6,FALSE),"") | K10: =IF(B10=C10,"YES","NO") | IJ10: ez_manage.py:4390 top() | IK10: v12_quick_engine.py:1310 x9
A11: BOUNCE_AUGMENT_MIN_LOSS_PCT | B11: -0.375 | E11: =IF(F11="",E10,IF(F11>0,E10+F11,E10)) | F11: -1.0393426 | G11: -2.6954965 | H11: =IFERROR(VLOOKUP($A11,Results_30d_Deltas!$A$2:$H$5000,6,FALSE),"") | K11: =IF(B11=C11,"YES","NO") | IJ11: ez_manage.py:4390 top() | IK11: v12_quick_engine.py:1310 x9
A12: BOUNCE_AUGMENT_MIN_LOSS_PCT | B12: -0.25 | E12: =IF(F12="",E11,IF(F12>0,E11+F12,E11)) | F12: -1.8136634 | G12: -3.4698173 | H12: =IFERROR(VLOOKUP($A12,Results_30d_Deltas!$A$2:$H$5000,6,FALSE),"") | K12: =IF(B12=C12,"YES","NO") | IJ12: ez_manage.py:4390 top() | IK12: v12_quick_engine.py:1310 x9
A13: AUGMENT_BOUNCE_MIN_GAIN_PCT | B13: 0.25 | E13: =IF(F13="",E12,IF(F13>0,E12+F13,E12)) | F13: 3.239949 | G13: 1.5837952 | H13: =IFERROR(VLOOKUP($A13,Results_30d_Deltas!$A$2:$H$5000,6,FALSE),"") | K13: =IF(B13=C13,"YES","NO") | IJ13: ez_manage.py:56856 top() | IK13: v12_quick_engine.py:4872 x2
A14: AUGMENT_BOUNCE_MIN_GAIN_PCT | B14: 0.375 | E14: =IF(F14="",E13,IF(F14>0,E13+F14,E13)) | F14: 3.239949 | G14: 1.5837952 | H14: =IFERROR(VLOOKUP($A14,Results_30d_Deltas!$A$2:$H$5000,6,FALSE),"") | K14: =IF(B14=C14,"YES","NO") | IJ14: ez_manage.py:56856 top() | IK14: v12_quick_engine.py:4872 x2
A15: AUGMENT_BOUNCE_MIN_GAIN_PCT | B15: 0.5 | E15: =IF(F15="",E14,IF(F15>0,E14+F15,E14)) | F15: 0 | G15: -1.6561539 | H15: =IFERROR(VLOOKUP($A15,Results_30d_Deltas!$A$2:$H$5000,6,FALSE),"") | K15: =IF(B15=C15,"YES","NO") | IJ15: ez_manage.py:56856 top() | IK15: v12_quick_engine.py:4872 x2
... A26: HTF_GATE_APPLY_TO_AUGMENT | B26: 2.0 | E26: =IF(F26="",E25,IF(F26>0,E25+F26,E25)) | F26: -1.7073607 | G26: -3.3635146 | H26: =IFERROR(VLOOKUP($A26,Results_30d_Deltas!$A$2:$H$5000,6,FALSE),"") | K26: =IF(B26=C26,"YES","NO") | IJ26: ez_manage.py:4876 top() | IK26: v12_quick_engine.py:2052 x6

Sheet AUGMENT_RISK_SIZING
A1: 09 AUGMENT_RISK_SIZING - 17 bases -> 56 rows - 231 per-row FULLY CONNECTED
A2: Switch | B2: default | C2: override | D2: Family | E2: BASELINE | F2: VECTOR_DELTA | G2: LIVE_DELTA | H2: LIVE_SHARPE | I2: REAL_COMPLETE | J2: PER_ROW_FILTERS | K2: is_default (backup if bold lost) | L2: ATR_TRAIL_FILTER_TF=OFF | M2: ATR_TRAIL_FILTER_TF=D | N2: ATR_TRAIL_FILTER_TF=4h | O2: ATR_TRAIL_FILTER_TF=1h | P2: ATR_TRAIL_FILTER_TF=15m | Q2: BAR_PATTERNS_FILTER_TF=OFF | R2: BAR_PATTERNS_FILTER_TF=D | S2: BAR_PATTERNS_FILTER_TF=4h | T2: BAR_PATTERNS_FILTER_TF=1h | U2: BAR_PATTERNS_FILTER_TF=15m | V2: BB_PULLBACK_GATE_FILTER_TF=OFF | W2: BB_PULLBACK_GATE_FILTER_TF=D | X2: BB_PULLBACK_GATE_FILTER_TF=4h | Y2: BB_PULLBACK_GATE_FILTER_TF=1h | Z2: BB_PULLBACK_GATE_FILTER_TF=15m | AA2: BB_RECOVERY_ENTRY_FILTER_TF=OFF | AB2: BB_RECOVERY_ENTRY_FILTER_TF=D | AC2: BB_RECOVERY_ENTRY_FILTER_TF=4h | AD2: BB_RECOVERY_ENTRY_FILTER_TF=1h | AE2: BB_RECOVERY_ENTRY_FILTER_TF=15m | AF2: BB_RECOVERY_FILTER_TF=OFF | AG2: BB_RECOVERY_FILTER_TF=D | AH2: BB_RECOVERY_FILTER_TF=4h | AI2: BB_RECOVERY_FILTER_TF=1h | AJ2: BB_RECOVERY_FILTER_TF=15m | AK2: BREAKEVEN_GAIN_EROSION_FILTER_TF=OFF | AL2: BREAKEVEN_GAIN_EROSION_FILTER_TF=D | AM2: BREAKEVEN_GAIN_EROSION_FILTER_TF=4h | AN2: BREAKEVEN_GAIN_EROSION_FILTER_TF=1h | AO2: BREAKEVEN_GAIN_EROSION_FILTER_TF=15m | AP2: BREAKOUT_RETEST_FILTER_TF=OFF | AQ2: BREAKOUT_RETEST_FILTER_TF=D | AR2: BREAKOUT_RETEST_FILTER_TF=4h | AS2: BREAKOUT_RETEST_FILTER_TF=1h | AT2: BREAKOUT_RETEST_FILTER_TF=15m | AU2: BT_WT_CROSS_LADDER_FILTER_TF=OFF | AV2: BT_WT_CROSS_LADDER_FILTER_TF=D | AW2: BT_WT_CROSS_LADDER_FILTER_TF=4h | AX2: BT_WT_CROSS_LADDER_FILTER_TF=1h | AY2: BT_WT_CROSS_LADDER_FILTER_TF=15m | AZ2: CANDLE_PATTERN_STOPS_FILTER_TF=OFF | BA2: CANDLE_PATTERN_STOPS_FILTER_TF=D | BB2: CANDLE_PATTERN_STOPS_FILTER_TF=4h | BC2: CANDLE_PATTERN_STOPS_FILTER_TF=1h | BD2: CANDLE_PATTERN_STOPS_FILTER_TF=15m | BE2: CIRCUIT_SHARPE_GATES_FILTER_TF=OFF | BF2: CIRCUIT_SHARPE_GATES_FILTER_TF=D | BG2: CIRCUIT_SHARPE_GATES_FILTER_TF=4h | BH2: CIRCUIT_SHARPE_GATES_FILTER_TF=1h | BI2: CIRCUIT_SHARPE_GATES_FILTER_TF=15m | BJ2: DC_BREACH_REDUCE_FILTER_TF=OFF | BK2: DC_BREACH_REDUCE_FILTER_TF=D | BL2: DC_BREACH_REDUCE_FILTER_TF=4h | BM2: DC_BREACH_REDUCE_FILTER_TF=1h | BN2: DC_BREACH_REDUCE_FILTER_TF=15m | BO2: DC_BREAK_FILTER_TF=OFF | BP2: DC_BREAK_FILTER_TF=D | BQ2: DC_BREAK_FILTER_TF=4h | BR2: DC_BREAK_FILTER_TF=1h | BS2: DC_BREAK_FILTER_TF=15m | BT2: DC_MOMENTUM_BOTA_SCORER_FILTER_TF=OFF | BU2: DC_MOMENTUM_BOTA_SCORER_FILTER_TF=D | BV2: DC_MOMENTUM_BOTA_SCORER_FILTER_TF=4h | BW2: DC_MOMENTUM_BOTA_SCORER_FILTER_TF=1h | BX2: DC_MOMENTUM_BOTA_SCORER_FILTER_TF=15m | BY2: DELTA_ENGINE_FILTER_TF=OFF | BZ2: DELTA_ENGINE_FILTER_TF=D | CA2: DELTA_ENGINE_FILTER_TF=4h | CB2: DELTA_ENGINE_FILTER_TF=1h | CC2: DELTA_ENGINE_FILTER_TF=15m | CD2: EMA_9_21_FILTER_FILTER_TF=OFF | CE2: EMA_9_21_FILTER_FILTER_TF=D | CF2: EMA_9_21_FILTER_FILTER_TF=4h | CG2: EMA_9_21_FILTER_FILTER_TF=1h | CH2: EMA_9_21_FILTER_FILTER_TF=15m | CI2: EMA_BLANKET_FILTER_FILTER_TF=OFF | CJ2: EMA_BLANKET_FILTER_FILTER_TF=D | CK2: EMA_BLANKET_FILTER_FILTER_TF=4h | CL2: EMA_BLANKET_FILTER_FILTER_TF=1h | CM2: EMA_BLANKET_FILTER_FILTER_TF=15m | CN2: EMERGENCY_BRAKE_FILTER_TF=OFF | CO2: EMERGENCY_BRAKE_FILTER_TF=D | CP2: EMERGENCY_BRAKE_FILTER_TF=4h | CQ2: EMERGENCY_BRAKE_FILTER_TF=1h | CR2: EMERGENCY_BRAKE_FILTER_TF=15m | CS2: EXIT_R1_R2_FILTER_TF=OFF | CT2: EXIT_R1_R2_FILTER_TF=D | CU2: EXIT_R1_R2_FILTER_TF=4h | CV2: EXIT_R1_R2_FILTER_TF=1h | CW2: EXIT_R1_R2_FILTER_TF=15m | CX2: EXIT_TIGHT_BREAKOUT_SCORER_FILTER_TF=OFF | CY2: EXIT_TIGHT_BREAKOUT_SCORER_FILTER_TF=D | CZ2: EXIT_TIGHT_BREAKOUT_SCORER_FILTER_TF=4h | DA2: EXIT_TIGHT_BREAKOUT_SCORER_FILTER_TF=1h | DB2: EXIT_TIGHT_BREAKOUT_SCORER_FILTER_TF=15m | DC2: EXIT_TOP_FADE_FILTER_TF=OFF | DD2: EXIT_TOP_FADE_FILTER_TF=D | DE2: EXIT_TOP_FADE_FILTER_TF=4h | DF2: EXIT_TOP_FADE_FILTER_TF=1h | DG2: EXIT_TOP_FADE_FILTER_TF=15m | DH2: EXIT_TO_REDUCE_ADAPTER_FILTER_TF=OFF | DI2: EXIT_TO_REDUCE_ADAPTER_FILTER_TF=D | DJ2: EXIT_TO_REDUCE_ADAPTER_FILTER_TF=4h | DK2: EXIT_TO_REDUCE_ADAPTER_FILTER_TF=1h | DL2: EXIT_TO_REDUCE_ADAPTER_FILTER_TF=15m | DM2: FAST_RISER_FILTER_TF=OFF | DN2: FAST_RISER_FILTER_TF=D | DO2: FAST_RISER_FILTER_TF=4h | DP2: FAST_RISER_FILTER_TF=1h | DQ2: FAST_RISER_FILTER_TF=15m | DR2: FH_MOMENTUM_FILTER_TF=OFF | DS2: FH_MOMENTUM_FILTER_TF=D | DT2: FH_MOMENTUM_FILTER_TF=4h | DU2: FH_MOMENTUM_FILTER_TF=1h | DV2: FH_MOMENTUM_FILTER_TF=15m | DW2: FIRST_OPEN_THROTTLE_FILTER_TF=OFF | DX2: FIRST_OPEN_THROTTLE_FILTER_TF=D | DY2: FIRST_OPEN_THROTTLE_FILTER_TF=4h | DZ2: FIRST_OPEN_THROTTLE_FILTER_TF=1h | EA2: FIRST_OPEN_THROTTLE_FILTER_TF=15m | EB2: FROZEN_STOP_FILTER_TF=OFF | EC2: FROZEN_STOP_FILTER_TF=D | ED2: FROZEN_STOP_FILTER_TF=4h | EE2: FROZEN_STOP_FILTER_TF=1h | EF2: FROZEN_STOP_FILTER_TF=15m | EG2: GOLDEN_RULE_ENFORCE_FILTER_TF=OFF | EH2: GOLDEN_RULE_ENFORCE_FILTER_TF=D | EI2: GOLDEN_RULE_ENFORCE_FILTER_TF=4h | EJ2: GOLDEN_RULE_ENFORCE_FILTER_TF=1h | EK2: GOLDEN_RULE_ENFORCE_FILTER_TF=15m | EL2: GOLDEN_RULE_HTF_VOTE_FILTER_TF=OFF | EM2: GOLDEN_RULE_HTF_VOTE_FILTER_TF=D | EN2: GOLDEN_RULE_HTF_VOTE_FILTER_TF=4h | EO2: GOLDEN_RULE_HTF_VOTE_FILTER_TF=1h | EP2: GOLDEN_RULE_HTF_VOTE_FILTER_TF=15m | EQ2: GR_FILTER_VEC_FILTER_TF=OFF | ER2: GR_FILTER_VEC_FILTER_TF=D | ES2: GR_FILTER_VEC_FILTER_TF=4h | ET2: GR_FILTER_VEC_FILTER_TF=1h | EU2: GR_FILTER_VEC_FILTER_TF=15m | EV2: GR_V5_STATE_FILTER_TF=OFF | EW2: GR_V5_STATE_FILTER_TF=D | EX2: GR_V5_STATE_FILTER_TF=4h | EY2: GR_V5_STATE_FILTER_TF=1h | EZ2: GR_V5_STATE_FILTER_TF=15m | FA2: HAIKU_WINNER_FILTER_TF=OFF | FB2: HAIKU_WINNER_FILTER_TF=D | FC2: HAIKU_WINNER_FILTER_TF=4h | FD2: HAIKU_WINNER_FILTER_TF=1h | FE2: HAIKU_WINNER_FILTER_TF=15m | FF2: LH_HL_FILTER_TF_REQ=2 | FG2: LH_HL_FILTER_TF_REQ=2_ALT | FH2: LIVE_ENTRY_ENGINE_FILTER_TF=OFF | FI2: LIVE_ENTRY_ENGINE_FILTER_TF=D | FJ2: LIVE_ENTRY_ENGINE_FILTER_TF=4h | FK2: LIVE_ENTRY_ENGINE_FILTER_TF=1h | FL2: LIVE_ENTRY_ENGINE_FILTER_TF=15m | FM2: LIVE_ONLY_SIGNALS_BATCH5_FILTER_TF=OFF | FN2: LIVE_ONLY_SIGNALS_BATCH5_FILTER_TF=D | FO2: LIVE_ONLY_SIGNALS_BATCH5_FILTER_TF=4h | FP2: LIVE_ONLY_SIGNALS_BATCH5_FILTER_TF=1h | FQ2: LIVE_ONLY_SIGNALS_BATCH5_FILTER_TF=15m | FR2: MANDATORY_REENTRY_WT_FILTER_TF_MODE=15m_only | FS2: MANDATORY_REENTRY_WT_FILTER_TF_MODE=15m_only_ALT | FT2: MOM3_FILTER_TF=OFF | FU2: MOM3_FILTER_TF=D | FV2: MOM3_FILTER_TF=4h | FW2: MOM3_FILTER_TF=1h | FX2: MOM3_FILTER_TF=15m | FY2: MOMENTUM_BREAKOUT_FILTER_TF=OFF | FZ2: MOMENTUM_BREAKOUT_FILTER_TF=D | GA2: MOMENTUM_BREAKOUT_FILTER_TF=4h | GB2: MOMENTUM_BREAKOUT_FILTER_TF=1h | GC2: MOMENTUM_BREAKOUT_FILTER_TF=15m | GD2: MTF_ARMED_ENTRIES_FILTER_TF=OFF | GE2: MTF_ARMED_ENTRIES_FILTER_TF=D | GF2: MTF_ARMED_ENTRIES_FILTER_TF=4h | GG2: MTF_ARMED_ENTRIES_FILTER_TF=1h | GH2: MTF_ARMED_ENTRIES_FILTER_TF=15m | GI2: MTF_ATR_TRAIL_FILTER_TF=OFF | GJ2: MTF_ATR_TRAIL_FILTER_TF=D | GK2: MTF_ATR_TRAIL_FILTER_TF=4h | GL2: MTF_ATR_TRAIL_FILTER_TF=1h | GM2: MTF_ATR_TRAIL_FILTER_TF=15m | GN2: MTF_DC_REJECT_FILTER_TF=OFF | GO2: MTF_DC_REJECT_FILTER_TF=D | GP2: MTF_DC_REJECT_FILTER_TF=4h | GQ2: MTF_DC_REJECT_FILTER_TF=1h | GR2: MTF_DC_REJECT_FILTER_TF=15m | GS2: NEWBORN_LOSS_KILL_FILTER_TF=OFF | GT2: NEWBORN_LOSS_KILL_FILTER_TF=D | GU2: NEWBORN_LOSS_KILL_FILTER_TF=4h | GV2: NEWBORN_LOSS_KILL_FILTER_TF=1h | GW2: NEWBORN_LOSS_KILL_FILTER_TF=15m | GX2: NEWBORN_PROTECT_FILTER_TF=OFF | GY2: NEWBORN_PROTECT_FILTER_TF=D | GZ2: NEWBORN_PROTECT_FILTER_TF=4h | HA2: NEWBORN_PROTECT_FILTER_TF=1h | HB2: NEWBORN_PROTECT_FILTER_TF=15m | HC2: NOLOSS_BYPASS_WT5OF5_FILTER_TF=OFF | HD2: NOLOSS_BYPASS_WT5OF5_FILTER_TF=D | HE2: NOLOSS_BYPASS_WT5OF5_FILTER_TF=4h | HF2: NOLOSS_BYPASS_WT5OF5_FILTER_TF=1h | HG2: NOLOSS_BYPASS_WT5OF5_FILTER_TF=15m | HH2: OPEN_INTENT_SIZE_GATES_FILTER_TF=OFF | HI2: OPEN_INTENT_SIZE_GATES_FILTER_TF=D | HJ2: OPEN_INTENT_SIZE_GATES_FILTER_TF=4h | HK2: OPEN_INTENT_SIZE_GATES_FILTER_TF=1h | HL2: OPEN_INTENT_SIZE_GATES_FILTER_TF=15m | HM2: PARTIAL_PROFIT_LOCK_V2_FILTER_TF=OFF | HN2: PARTIAL_PROFIT_LOCK_V2_FILTER_TF=D | HO2: PARTIAL_PROFIT_LOCK_V2_FILTER_TF=4h | HP2: PARTIAL_PROFIT_LOCK_V2_FILTER_TF=1h | HQ2: PARTIAL_PROFIT_LOCK_V2_FILTER_TF=15m | HR2: PEAK_GIVEBACK_BE_EROSION_FILTER_TF=OFF | HS2: PEAK_GIVEBACK_BE_EROSION_FILTER_TF=D | HT2: PEAK_GIVEBACK_BE_EROSION_FILTER_TF=4h | HU2: PEAK_GIVEBACK_BE_EROSION_FILTER_TF=1h | HV2: PEAK_GIVEBACK_BE_EROSION_FILTER_TF=15m | HW2: WT_15M_BOUNCE_BB_MAX=0.95 | HX2: WT_15M_BOUNCE_BB_MAX=0.9 | HY2: WT_15M_BOUNCE_BB_MAX=0.8 | HZ2: WT_15M_BOUNCE_BB_MIN=0.05 | IA2: WT_15M_BOUNCE_BB_MIN=0.1 | IB2: WT_15M_BOUNCE_BB_MIN=0.2 | IC2: WT_15M_BOUNCE_HIGH_1H_GT_PREV=True | ID2: WT_15M_BOUNCE_HIGH_1H_GT_PREV=False | IE2: WT_15M_BOUNCE_LOW_1H_GT_PREV=True | IF2: WT_15M_BOUNCE_LOW_1H_GT_PREV=False | IG2: WT_15M_BOUNCE_REL_VOL_GT_1=True | IH2: WT_15M_BOUNCE_REL_VOL_GT_1=False | II2: Live Location | IJ2: Vec Hook | IK2: Type | IL2: Correct Options
A3: DD_BOUNCE_ENABLED | B3: True | E3: =MAX('AUGMENT_TREND'!E:E) | F3: -1.8934256 | G3: -3.5495795 | H3: =IFERROR(VLOOKUP($A3,Results_30d_Deltas!$A$2:$H$5000,6,FALSE),"") | K3: =IF(B3=C3,"YES","NO") | IJ3: ez_manage.py:4586 top() | IK3: v12_quick_engine.py:567 x9
A4: MAX_AUGMENTS_PER_POSITION | B4: 0 | E4: =IF(F4="",E3,IF(F4>0,E3+F4,E3)) | F4: -2.4538266 | G4: -4.1099804 | H4: =IFERROR(VLOOKUP($A4,Results_30d_Deltas!$A$2:$H$5000,6,FALSE),"") | K4: =IF(B4=C4,"YES","NO") | IJ4: ez_manage.py:3521 top() | IK4: v12_quick_engine.py:2267 x7
A5: MAX_AUGMENTS_PER_POSITION | B5: 0.5 | E5: =IF(F5="",E4,IF(F5>0,E4+F5,E4)) | F5: 0 | G5: -1.6561539 | H5: =IFERROR(VLOOKUP($A5,Results_30d_Deltas!$A$2:$H$5000,6,FALSE),"") | K5: =IF(B5=C5,"YES","NO") | IJ5: ez_manage.py:3521 top() | IK5: v12_quick_engine.py:2267 x7
A6: MAX_AUGMENTS_PER_POSITION | B6: 1.0 | E6: =IF(F6="",E5,IF(F6>0,E5+F6,E5)) | F6: 0 | G6: -1.6561539 | H6: =IFERROR(VLOOKUP($A6,Results_30d_Deltas!$A$2:$H$5000,6,FALSE),"") | K6: =IF(B6=C6,"YES","NO") | IJ6: ez_manage.py:3521 top() | IK6: v12_quick_engine.py:2267 x7
A7: MAX_AUGMENTS_PER_POSITION | B7: 2.0 | E7: =IF(F7="",E6,IF(F7>0,E6+F7,E6)) | F7: -2.0245238 | G7: -3.6806777 | H7: =IFERROR(VLOOKUP($A7,Results_30d_Deltas!$A$2:$H$5000,6,FALSE),"") | K7: =IF(B7=C7,"YES","NO") | IJ7: ez_manage.py:3521 top() | IK7: v12_quick_engine.py:2267 x7
A8: AUGMENTED_POSITIONS_GUARD_FLOOR_MULT | B8: 0 | E8: =IF(F8="",E7,IF(F8>0,E7+F8,E7)) | F8: -2.471381 | G8: -4.1275348 | H8: =IFERROR(VLOOKUP($A8,Results_30d_Deltas!$A$2:$H$5000,6,FALSE),"") | K8: =IF(B8=C8,"YES","NO") | IJ8: ez_manage.py:4336 top() | IK8: v12_quick_engine.py:221 x13
A9: AUGMENTED_POSITIONS_GUARD_FLOOR_MULT | B9: 0.5 | E9: =IF(F9="",E8,IF(F9>0,E8+F9,E8)) | F9: 0 | G9: -1.6561539 | H9: =IFERROR(VLOOKUP($A9,Results_30d_Deltas!$A$2:$H$5000,6,FALSE),"") | K9: =IF(B9=C9,"YES","NO") | IJ9: ez_manage.py:4336 top() | IK9: v12_quick_engine.py:221 x13
A10: AUGMENTED_POSITIONS_GUARD_FLOOR_MULT | B10: 1.0 | E10: =IF(F10="",E9,IF(F10>0,E9+F10,E9)) | F10: 0 | G10: -1.6561539 | H10: =IFERROR(VLOOKUP($A10,Results_30d_Deltas!$A$2:$H$5000,6,FALSE),"") | K10: =IF(B10=C10,"YES","NO") | IJ10: ez_manage.py:4336 top() | IK10: v12_quick_engine.py:221 x13
A11: AUGMENTED_POSITIONS_GUARD_FLOOR_MULT | B11: 2.0 | E11: =IF(F11="",E10,IF(F11>0,E10+F11,E10)) | F11: -1.7345709 | G11: -3.3907247 | H11: =IFERROR(VLOOKUP($A11,Results_30d_Deltas!$A$2:$H$5000,6,FALSE),"") | K11: =IF(B11=C11,"YES","NO") | IJ11: ez_manage.py:4336 top() | IK11: v12_quick_engine.py:221 x13
A12: AUGMENT_AT_LOSS_ENABLED | B12: False | E12: =IF(F12="",E11,IF(F12>0,E11+F12,E11)) | F12: =IFERROR(VLOOKUP($A12&"="&$B12,Results_30d_Deltas!$A$2:$H$5000,5,FALSE),"") | G12: =IFERROR(VLOOKUP($A12,Results_30d_Deltas!$A$2:$H$5000,7,FALSE)-E11,"") | H12: =IFERROR(VLOOKUP($A12,Results_30d_Deltas!$A$2:$H$5000,6,FALSE),"") | K12: =IF(B12=C12,"YES","NO") | IJ12: ez_manage.py:5956 top() | IK12: v12_quick_engine.py:228 x5
A13: AUGMENT_AT_LOSS_ENABLED | B13: True | E13: =IF(F13="",E12,IF(F13>0,E12+F13,E12)) | F13: -1.7240473 | G13: -3.3802012 | H13: =IFERROR(VLOOKUP($A13,Results_30d_Deltas!$A$2:$H$5000,6,FALSE),"") | K13: =IF(B13=C13,"YES","NO") | IJ13: ez_manage.py:5956 top() | IK13: v12_quick_engine.py:228 x5
A14: AUGMENT_FALLBACK_GAIN_PCT | B14: 0.5 | E14: =IF(F14="",E13,IF(F14>0,E13+F14,E13)) | F14: 4.7465121 | G14: 3.0903582 | H14: =IFERROR(VLOOKUP($A14,Results_30d_Deltas!$A$2:$H$5000,6,FALSE),"") | K14: =IF(B14=C14,"YES","NO") | IJ14: ez_manage.py:56864 top() | IK14: v12_quick_engine.py:4990 x4
A15: AUGMENT_FALLBACK_GAIN_PCT | B15: 0.75 | E15: =IF(F15="",E14,IF(F15>0,E14+F15,E14)) | F15: 5.2280546 | G15: 3.5719007 | H15: =IFERROR(VLOOKUP($A15,Results_30d_Deltas!$A$2:$H$5000,6,FALSE),"") | K15: =IF(B15=C15,"YES","NO") | IJ15: ez_manage.py:56864 top() | IK15: v12_quick_engine.py:4990 x4
A16: AUGMENT_FALLBACK_GAIN_PCT | B16: 1.0 | E16: =IF(F16="",E15,IF(F16>0,E15+F16,E15)) | F16: -1.8136634 | G16: -3.4698173 | H16: =IFERROR(VLOOKUP($A16,Results_30d_Deltas!$A$2:$H$5000,6,FALSE),"") | K16: =IF(B16=C16,"YES","NO") | IJ16: ez_manage.py:56864 top() | IK16: v12_quick_engine.py:4990 x4
A17: AUGMENT_FALLBACK_GAIN_PCT | B17: 1.25 | E17: =IF(F17="",E16,IF(F17>0,E16+F17,E16)) | F17: 5.2280546 | G17: 3.5719007 | H17: =IFERROR(VLOOKUP($A17,Results_30d_Deltas!$A$2:$H$5000,6,FALSE),"") | K17: =IF(B17=C17,"YES","NO") | IJ17: ez_manage.py:56864 top() | IK17: v12_quick_engine.py:4990 x4
A18: AUGMENT_FALLBACK_GAIN_PCT | B18: 1.5 | E18: =IF(F18="",E17,IF(F18>0,E17+F18,E17)) | F18: 5.2280546 | G18: 3.5719007 | H18: =IFERROR(VLOOKUP($A18,Results_30d_Deltas!$A$2:$H$5000,6,FALSE),"") | K18: =IF(B18=C18,"YES","NO") | IJ18: ez_manage.py:56864 top() | IK18: v12_quick_engine.py:4990 x4
A19: AUGMENT_FALLBACK_REDUCE_ENABLED | B19: False | E19: =IF(F19="",E18,IF(F19>0,E18+F19,E18)) | F19: =IFERROR(VLOOKUP($A19&"="&$B19,Results_30d_Deltas!$A$2:$H$5000,5,FALSE),"") | G19: =IFERROR(VLOOKUP($A19,Results_30d_Deltas!$A$2:$H$5000,7,FALSE)-E18,"") | H19: =IFERROR(VLOOKUP($A19,Results_30d_Deltas!$A$2:$H$5000,6,FALSE),"") | K19: =IF(B19=C19,"YES","NO") | IJ19: ez_manage.py:56872 top() | IK19: v12_quick_engine.py:4988 x3
A20: AUGMENT_FALLBACK_REDUCE_ENABLED | B20: True | E20: =IF(F20="",E19,IF(F20>0,E19+F20,E19)) | F20: -1.7073607 | G20: -3.3635146 | H20: =IFERROR(VLOOKUP($A20,Results_30d_Deltas!$A$2:$H$5000,6,FALSE),"") | K20: =IF(B20=C20,"YES","NO") | IJ20: ez_manage.py:56872 top() | IK20: v12_quick_engine.py:4988 x3
