Workbook

Sheet INSTRUCTIONS
A1: TEMPLATE_30d_matrix -- CRYSTAL CLEAR INSTRUCTIONS (2026-09-11) -- ANY DUMB AGENT CAN EXECUTE *** ON S1 NEVER ON MACBOOK *** If you are reading this, YOU MUST FOLLOW EVERY LINE. No skipping, no guessing, no inventing numbers. This tab + FILTER_DICTIONARY_V2 + v14_sequential_filler.py + v12_quick_engine/backtest_v12_engine are LAW.
A2: ⚠️ MACHINE RULE -- MAC ONLY TRADES LIVE (ez_manage / tradier_manage) AND NEVER TESTS. MAC has 5 NPZs and NO NVDA.npz / NO CRWD.npz → any S1 vector returns 'no NPZ' in 0.2s. S1 = 157.180.125.52 (s1-int via gateway 157.90.168.35) has 1000+ NPZs (42-49M) and is ONLY test host (S2 for mega sweeps only). If on MacBook, SSH FIRST: ssh 157.180.125.52 OR ssh -fNT s1-sftp && ssh s1-int. Verify: ls /home/niels/binance-sandbox/backtest_v8/indicators/NVDA.npz must exist. If not, STOP.
A3: ⚠️ SYNC & BACKUP RULE -- KEEP ALL FIXES synced Mac <-> S1 via rsync -avz -e 'ssh -p 2201' and KEEP BACKUPS before EVERY edit: cp <file> backups/before_<desc>_$(date +%Y%m%d%H%M).py . Autosave launchd commits git every 15min. /backups/ ONLY reliable history. After BACKTEST_BIBLE.md edit run tools/sync_backtest_bible.sh (SHA256). NEVER edit S1 copy directly without rsync back.
A4: ⚠️ INSTRUCTIONS ARE LAW -- v12_pilot.py, v12_pilot_sheet_runner.py, v14_sequential_filler.py, ANY agent MUST READ THIS TAB AT STARTUP and FOLLOW IT. This tab wins over code if conflict after 2026-09-11. Also read BACKTEST_BIBLE.md, QuickConfig (v12_quick_engine:5893 1118 fields, 851 causal), and FILTER_DICTIONARY_V2 (426 rows).
A5: 0) PRECONDITION -- DO NOT START UNTIL DEFAULTS ARE BOLD. Every row where B == live default (config.py Config for crypto / config_tradier.py TradierConfig for stocks = 1118 fields) must have A and B bold. ~50% rows bold. NEVER edit B (candidate value in col B). You only write C (override), E (baseline gain), F (delta vs E), G (variant gain), and L:BI per-filter deltas.
A6: 1) CREATE BASELINE WITH per_sym OVERRIDES for EXACT sym_side. GET OVERRIDES = union of data/hourly_reconfig/trb/active_config.json AND data/hourly_reconfig/per_sym_active_config.json for YOUR EXACT SYM_SIDE (SYMBOL+_LONG vs _SHORT are DIFFERENT, NEVER reuse). Example NVDA_LONG 8 overrides (BOUNCE_AUGMENT...), CRWD_SHORT 0. For each switch in union, find row where A==switch name and write override into C, BOLD GREEN font 006100 on fill C6EFCE. Do ALL overrides BEFORE baseline calc. Then baseline = vector_evaluate(sym_side, overrides) AND live_evaluate(sym_side, overrides) — they must parity (trades 0.80..1.25, gain 0.5pp|15%, sharpe 0.25). Write META_LONG_BASELINE_METRICS!B2 = gain, B? = bh. Verify WT_15M_BOUNCE True adds >100 trades/mo (fix in v12_quick_engine:5894 MAX_BARS_AGO=100). If trades 0 or <30, STOP and spawn agent to fix v12_quick_engine (6817/9010).
A7: 1b) BASELINE E2 = META_LONG_BASELINE_METRICS!B2 (gain). E3 = IF(F3>0,E2+F3,"") chain. Never repeat E. First pilot: WT_15M_BOUNCE True must be first positive delta or calculation BROKEN.
A8: 2) FOR EVERY ROW (EVERY SWITCH) TEST EVERY APPLICABLE FILTER × EVERY SETTING. MANDATORY until >100 sym_sides tested (see rule 9). Applicable = FILTER_DICTIONARY_V2 row where (sheets_app contains this tab lifecycle ENTRY/EXIT/REENTRY/AUGMENT/REDUCE or GLOBAL_CHECK) AND (gates token overlap with this switch OR rec is GENERAL). Use get_opportune_filters(switch, sheet) — it already implements this. For WT_15M_BOUNCE_OPEN_ENABLED True you MUST test its 12 sub-filters (BB_MIN 0.05/0.1/0.2, BB_MAX 0.95/0.9/0.8, LOW_1H True/False, HIGH_1H True/False, REL_VOL True/False) even if WT alone delta is NEG — they are FILTERS in FILTER_DICTIONARY, not switches. Do NOT discard. COL J lists per-switch opportune filters (up to 6 shown), COL L:BI holds per-filter deltas (one column per filter=opt).
A9: 2a) EVALUATION: For this row, build candidates: [switch alone] + [switch+each single filter distinct opt (skip opt==cur)] . If best single delta <=0, also test ALL combos of 2 and 3 among top-8 singles (C8,2=28 + C8,3=56 =84 combos). Each candidate = sanitize_overrides(variant, defaults) then vector_evaluate via prepare_batch/evaluate_prepared_sanitized (70-136ms, million/hour). NEVER use per-cell load_npz (3.65s) — use prepare_batch once per sym_side. Log every candidate: [CANDIDATE] switch=cand[+filter=opt] vec_gain delta vs cum trades sharpe. Pick MAX delta (beating-ideas-to-death, not first positive).
A10: 2b) DUPLICATE/0.0 CHECK — Immediately flag DUPLICATE (same delta for 2 different switches → formula bug, e.g. shared adx gate) or 0.0 (dead switch or >5s VECTOR_STALL). If duplicate/0.0, revise v12_quick_engine wiring to exact live numpy (622 not-causal) and run live_evaluate for parity. Fix before promoting.
A11: 2c) PROGRESS REPORT every 5min: count filled F cells per sheet (e.g. NVDA 2790/2823=98.8% — one baseline empty per sheet expected). Write data/reports/lifecycle_pilot/*_pilot_progress.json and SPREADSHEETS/*_pilot_progress.html refreshed 60s. Also log [ROW] sheet!r switch=cand[+filter] delta vs cum -> NEG/POSITIVE candidate.
A12: 3) PROMOTION: Only if best delta >0 AND live_evaluate parity passes (trades 0.80..1.25, gain 0.5pp|15%, sharpe 0.25) AND (vector_only deferred → final cumulative live check). Then write C = cand (bold green 006100 on C6EFCE), cumulative_gain = vec_gain, cumulative_overrides[switch]=cand and if filter best exists also [filter]=fval. Write Results_30d_Deltas row: key=switch=cand, col5=delta, col6=variant_gain, col8=variant_gain, col10=trades, col11=max_dd, col12=tim. Also batch write L:BI deltas for this row (one col per filter=opt = delta). E for this row = IF(F>0,Eprev+F,Eprev) — only F>0 gets bold green E/F/G and C. F/G written even if <=0 for audit, but E stays empty.
... A23: 14) FINAL CHECK -- Before declaring done, verify: (a) every row has F via Results key=switch=cand VLOOKUP $A&"="&$B, (b) L:BI columns exist for every applicable filter (R-W, 40 col cap), (c) Results_30d_Deltas has delta, gain, trades, sharpe for every pos, (d) filename bh/gain correct, (e) v14 where applicable, (f) >100 sym_sides threshold respected, (g) colors green/blue/darker per provenance.

Sheet INSTRUCTIONS_V2
A1: TEMPLATE_V2_IDEA_GROUPED 231 per-row FULLY CONNECTED 2026-09-08 - every numpy identical to live
A2: Retraced from early today 231 L:IH (TEMPLATE.xlsx 1.7M) - Sep 5 114 per-row was synthetic/disconnected. This file keeps 231 per-row L:IH (every filter TF OFF/D/4h/1h/15m wired).
A3: 01. ENTRY_REVERSAL_BOUNCE - 8 bases -> 21 rows - 231 per-row
A4: 02. ENTRY_BREAKOUT_CHANNEL - 54 bases -> 210 rows - 231 per-row
A5: 03. ENTRY_CONFIRMATION_GATES - 4 bases -> 11 rows - 231 per-row
A6: 04. EXIT_STRUCTURAL - 2 bases -> 6 rows - 231 per-row
A7: 05. EXIT_VELOCITY - 26 bases -> 80 rows - 231 per-row
A8: 06. REENTRY_WINDOWED - 68 bases -> 249 rows - 231 per-row
A9: 07. REENTRY_ADAPTIVE - 10 bases -> 38 rows - 231 per-row
A10: 08. AUGMENT_TREND - 5 bases -> 24 rows - 231 per-row
A11: 09. AUGMENT_RISK_SIZING - 17 bases -> 56 rows - 231 per-row
A12: 10. REDUCE_PROFIT_LOCK - 19 bases -> 53 rows - 231 per-row
... A15: 2026-09-11 UPDATE: See INSTRUCTIONS tab rows 9,12,14 for >100 sym_sides threshold, blanket at end of each tab, and green/blue/darker proven colors. v14 implements get_opportune_filters + 84 combos + blanket GENERAL. ALL filters until 100, then useful per universe.

Sheet ENTRY_REVERSAL_BOUNCE
A1: 01 ENTRY_REVERSAL_BOUNCE - 8 bases -> 21 rows - 231 per-row FULLY CONNECTED
A2: Switch | B2: default | C2: override | D2: Family | E2: BASELINE | F2: VECTOR_DELTA | G2: LIVE_DELTA | H2: LIVE_SHARPE | I2: REAL_COMPLETE | J2: PER_ROW_FILTERS | K2: is_default (backup if bold lost) | L2: ATR_TRAIL_FILTER_TF=OFF | M2: ATR_TRAIL_FILTER_TF=D | N2: ATR_TRAIL_FILTER_TF=4h | O2: ATR_TRAIL_FILTER_TF=1h | P2: ATR_TRAIL_FILTER_TF=15m | Q2: BAR_PATTERNS_FILTER_TF=OFF | R2: BAR_PATTERNS_FILTER_TF=D | S2: BAR_PATTERNS_FILTER_TF=4h | T2: BAR_PATTERNS_FILTER_TF=1h | U2: BAR_PATTERNS_FILTER_TF=15m | V2: BB_PULLBACK_GATE_FILTER_TF=OFF | W2: BB_PULLBACK_GATE_FILTER_TF=D | X2: BB_PULLBACK_GATE_FILTER_TF=4h | Y2: BB_PULLBACK_GATE_FILTER_TF=1h | Z2: BB_PULLBACK_GATE_FILTER_TF=15m | AA2: BB_RECOVERY_ENTRY_FILTER_TF=OFF | AB2: BB_RECOVERY_ENTRY_FILTER_TF=D | AC2: BB_RECOVERY_ENTRY_FILTER_TF=4h | AD2: BB_RECOVERY_ENTRY_FILTER_TF=1h | AE2: BB_RECOVERY_ENTRY_FILTER_TF=15m | AF2: BB_RECOVERY_FILTER_TF=OFF | AG2: BB_RECOVERY_FILTER_TF=D | AH2: BB_RECOVERY_FILTER_TF=4h | AI2: BB_RECOVERY_FILTER_TF=1h | AJ2: BB_RECOVERY_FILTER_TF=15m | AK2: BREAKEVEN_GAIN_EROSION_FILTER_TF=OFF | AL2: BREAKEVEN_GAIN_EROSION_FILTER_TF=D | AM2: BREAKEVEN_GAIN_EROSION_FILTER_TF=4h | AN2: BREAKEVEN_GAIN_EROSION_FILTER_TF=1h | AO2: BREAKEVEN_GAIN_EROSION_FILTER_TF=15m | AP2: BREAKOUT_RETEST_FILTER_TF=OFF | AQ2: BREAKOUT_RETEST_FILTER_TF=D | AR2: BREAKOUT_RETEST_FILTER_TF=4h | AS2: BREAKOUT_RETEST_FILTER_TF=1h | AT2: BREAKOUT_RETEST_FILTER_TF=15m | AU2: BT_WT_CROSS_LADDER_FILTER_TF=OFF | AV2: BT_WT_CROSS_LADDER_FILTER_TF=D | AW2: BT_WT_CROSS_LADDER_FILTER_TF=4h | AX2: BT_WT_CROSS_LADDER_FILTER_TF=1h | AY2: BT_WT_CROSS_LADDER_FILTER_TF=15m | AZ2: CANDLE_PATTERN_STOPS_FILTER_TF=OFF | BA2: CANDLE_PATTERN_STOPS_FILTER_TF=D | BB2: CANDLE_PATTERN_STOPS_FILTER_TF=4h | BC2: CANDLE_PATTERN_STOPS_FILTER_TF=1h | BD2: CANDLE_PATTERN_STOPS_FILTER_TF=15m | BE2: CIRCUIT_SHARPE_GATES_FILTER_TF=OFF | BF2: CIRCUIT_SHARPE_GATES_FILTER_TF=D | BG2: CIRCUIT_SHARPE_GATES_FILTER_TF=4h | BH2: CIRCUIT_SHARPE_GATES_FILTER_TF=1h | BI2: CIRCUIT_SHARPE_GATES_FILTER_TF=15m | BJ2: DC_BREACH_REDUCE_FILTER_TF=OFF | BK2: DC_BREACH_REDUCE_FILTER_TF=D | BL2: DC_BREACH_REDUCE_FILTER_TF=4h | BM2: DC_BREACH_REDUCE_FILTER_TF=1h | BN2: DC_BREACH_REDUCE_FILTER_TF=15m | BO2: DC_BREAK_FILTER_TF=OFF | BP2: DC_BREAK_FILTER_TF=D | BQ2: DC_BREAK_FILTER_TF=4h | BR2: DC_BREAK_FILTER_TF=1h | BS2: DC_BREAK_FILTER_TF=15m | BT2: DC_MOMENTUM_BOTA_SCORER_FILTER_TF=OFF | BU2: DC_MOMENTUM_BOTA_SCORER_FILTER_TF=D | BV2: DC_MOMENTUM_BOTA_SCORER_FILTER_TF=4h | BW2: DC_MOMENTUM_BOTA_SCORER_FILTER_TF=1h | BX2: DC_MOMENTUM_BOTA_SCORER_FILTER_TF=15m | BY2: DELTA_ENGINE_FILTER_TF=OFF | BZ2: DELTA_ENGINE_FILTER_TF=D | CA2: DELTA_ENGINE_FILTER_TF=4h | CB2: DELTA_ENGINE_FILTER_TF=1h | CC2: DELTA_ENGINE_FILTER_TF=15m | CD2: EMA_9_21_FILTER_FILTER_TF=OFF | CE2: EMA_9_21_FILTER_FILTER_TF=D | CF2: EMA_9_21_FILTER_FILTER_TF=4h | CG2: EMA_9_21_FILTER_FILTER_TF=1h | CH2: EMA_9_21_FILTER_FILTER_TF=15m | CI2: EMA_BLANKET_FILTER_FILTER_TF=OFF | CJ2: EMA_BLANKET_FILTER_FILTER_TF=D | CK2: EMA_BLANKET_FILTER_FILTER_TF=4h | CL2: EMA_BLANKET_FILTER_FILTER_TF=1h | CM2: EMA_BLANKET_FILTER_FILTER_TF=15m | CN2: EMERGENCY_BRAKE_FILTER_TF=OFF | CO2: EMERGENCY_BRAKE_FILTER_TF=D | CP2: EMERGENCY_BRAKE_FILTER_TF=4h | CQ2: EMERGENCY_BRAKE_FILTER_TF=1h | CR2: EMERGENCY_BRAKE_FILTER_TF=15m | CS2: EXIT_R1_R2_FILTER_TF=OFF | CT2: EXIT_R1_R2_FILTER_TF=D | CU2: EXIT_R1_R2_FILTER_TF=4h | CV2: EXIT_R1_R2_FILTER_TF=1h | CW2: EXIT_R1_R2_FILTER_TF=15m | CX2: EXIT_TIGHT_BREAKOUT_SCORER_FILTER_TF=OFF | CY2: EXIT_TIGHT_BREAKOUT_SCORER_FILTER_TF=D | CZ2: EXIT_TIGHT_BREAKOUT_SCORER_FILTER_TF=4h | DA2: EXIT_TIGHT_BREAKOUT_SCORER_FILTER_TF=1h | DB2: EXIT_TIGHT_BREAKOUT_SCORER_FILTER_TF=15m | DC2: EXIT_TOP_FADE_FILTER_TF=OFF | DD2: EXIT_TOP_FADE_FILTER_TF=D | DE2: EXIT_TOP_FADE_FILTER_TF=4h | DF2: EXIT_TOP_FADE_FILTER_TF=1h | DG2: EXIT_TOP_FADE_FILTER_TF=15m | DH2: EXIT_TO_REDUCE_ADAPTER_FILTER_TF=OFF | DI2: EXIT_TO_REDUCE_ADAPTER_FILTER_TF=D | DJ2: EXIT_TO_REDUCE_ADAPTER_FILTER_TF=4h | DK2: EXIT_TO_REDUCE_ADAPTER_FILTER_TF=1h | DL2: EXIT_TO_REDUCE_ADAPTER_FILTER_TF=15m | DM2: FAST_RISER_FILTER_TF=OFF | DN2: FAST_RISER_FILTER_TF=D | DO2: FAST_RISER_FILTER_TF=4h | DP2: FAST_RISER_FILTER_TF=1h | DQ2: FAST_RISER_FILTER_TF=15m | DR2: FH_MOMENTUM_FILTER_TF=OFF | DS2: FH_MOMENTUM_FILTER_TF=D | DT2: FH_MOMENTUM_FILTER_TF=4h | DU2: FH_MOMENTUM_FILTER_TF=1h | DV2: FH_MOMENTUM_FILTER_TF=15m | DW2: FIRST_OPEN_THROTTLE_FILTER_TF=OFF | DX2: FIRST_OPEN_THROTTLE_FILTER_TF=D | DY2: FIRST_OPEN_THROTTLE_FILTER_TF=4h | DZ2: FIRST_OPEN_THROTTLE_FILTER_TF=1h | EA2: FIRST_OPEN_THROTTLE_FILTER_TF=15m | EB2: FROZEN_STOP_FILTER_TF=OFF | EC2: FROZEN_STOP_FILTER_TF=D | ED2: FROZEN_STOP_FILTER_TF=4h | EE2: FROZEN_STOP_FILTER_TF=1h | EF2: FROZEN_STOP_FILTER_TF=15m | EG2: GOLDEN_RULE_ENFORCE_FILTER_TF=OFF | EH2: GOLDEN_RULE_ENFORCE_FILTER_TF=D | EI2: GOLDEN_RULE_ENFORCE_FILTER_TF=4h | EJ2: GOLDEN_RULE_ENFORCE_FILTER_TF=1h | EK2: GOLDEN_RULE_ENFORCE_FILTER_TF=15m | EL2: GOLDEN_RULE_HTF_VOTE_FILTER_TF=OFF | EM2: GOLDEN_RULE_HTF_VOTE_FILTER_TF=D | EN2: GOLDEN_RULE_HTF_VOTE_FILTER_TF=4h | EO2: GOLDEN_RULE_HTF_VOTE_FILTER_TF=1h | EP2: GOLDEN_RULE_HTF_VOTE_FILTER_TF=15m | EQ2: GR_FILTER_VEC_FILTER_TF=OFF | ER2: GR_FILTER_VEC_FILTER_TF=D | ES2: GR_FILTER_VEC_FILTER_TF=4h | ET2: GR_FILTER_VEC_FILTER_TF=1h | EU2: GR_FILTER_VEC_FILTER_TF=15m | EV2: GR_V5_STATE_FILTER_TF=OFF | EW2: GR_V5_STATE_FILTER_TF=D | EX2: GR_V5_STATE_FILTER_TF=4h | EY2: GR_V5_STATE_FILTER_TF=1h | EZ2: GR_V5_STATE_FILTER_TF=15m | FA2: HAIKU_WINNER_FILTER_TF=OFF | FB2: HAIKU_WINNER_FILTER_TF=D | FC2: HAIKU_WINNER_FILTER_TF=4h | FD2: HAIKU_WINNER_FILTER_TF=1h | FE2: HAIKU_WINNER_FILTER_TF=15m | FF2: LH_HL_FILTER_TF_REQ=2 | FG2: LH_HL_FILTER_TF_REQ=2_ALT | FH2: LIVE_ENTRY_ENGINE_FILTER_TF=OFF | FI2: LIVE_ENTRY_ENGINE_FILTER_TF=D | FJ2: LIVE_ENTRY_ENGINE_FILTER_TF=4h | FK2: LIVE_ENTRY_ENGINE_FILTER_TF=1h | FL2: LIVE_ENTRY_ENGINE_FILTER_TF=15m | FM2: LIVE_ONLY_SIGNALS_BATCH5_FILTER_TF=OFF | FN2: LIVE_ONLY_SIGNALS_BATCH5_FILTER_TF=D | FO2: LIVE_ONLY_SIGNALS_BATCH5_FILTER_TF=4h | FP2: LIVE_ONLY_SIGNALS_BATCH5_FILTER_TF=1h | FQ2: LIVE_ONLY_SIGNALS_BATCH5_FILTER_TF=15m | FR2: MANDATORY_REENTRY_WT_FILTER_TF_MODE=15m_only | FS2: MANDATORY_REENTRY_WT_FILTER_TF_MODE=15m_only_ALT | FT2: MOM3_FILTER_TF=OFF | FU2: MOM3_FILTER_TF=D | FV2: MOM3_FILTER_TF=4h | FW2: MOM3_FILTER_TF=1h | FX2: MOM3_FILTER_TF=15m | FY2: MOMENTUM_BREAKOUT_FILTER_TF=OFF | FZ2: MOMENTUM_BREAKOUT_FILTER_TF=D | GA2: MOMENTUM_BREAKOUT_FILTER_TF=4h | GB2: MOMENTUM_BREAKOUT_FILTER_TF=1h | GC2: MOMENTUM_BREAKOUT_FILTER_TF=15m | GD2: MTF_ARMED_ENTRIES_FILTER_TF=OFF | GE2: MTF_ARMED_ENTRIES_FILTER_TF=D | GF2: MTF_ARMED_ENTRIES_FILTER_TF=4h | GG2: MTF_ARMED_ENTRIES_FILTER_TF=1h | GH2: MTF_ARMED_ENTRIES_FILTER_TF=15m | GI2: MTF_ATR_TRAIL_FILTER_TF=OFF | GJ2: MTF_ATR_TRAIL_FILTER_TF=D | GK2: MTF_ATR_TRAIL_FILTER_TF=4h | GL2: MTF_ATR_TRAIL_FILTER_TF=1h | GM2: MTF_ATR_TRAIL_FILTER_TF=15m | GN2: MTF_DC_REJECT_FILTER_TF=OFF | GO2: MTF_DC_REJECT_FILTER_TF=D | GP2: MTF_DC_REJECT_FILTER_TF=4h | GQ2: MTF_DC_REJECT_FILTER_TF=1h | GR2: MTF_DC_REJECT_FILTER_TF=15m | GS2: NEWBORN_LOSS_KILL_FILTER_TF=OFF | GT2: NEWBORN_LOSS_KILL_FILTER_TF=D | GU2: NEWBORN_LOSS_KILL_FILTER_TF=4h | GV2: NEWBORN_LOSS_KILL_FILTER_TF=1h | GW2: NEWBORN_LOSS_KILL_FILTER_TF=15m | GX2: NEWBORN_PROTECT_FILTER_TF=OFF | GY2: NEWBORN_PROTECT_FILTER_TF=D | GZ2: NEWBORN_PROTECT_FILTER_TF=4h | HA2: NEWBORN_PROTECT_FILTER_TF=1h | HB2: NEWBORN_PROTECT_FILTER_TF=15m | HC2: NOLOSS_BYPASS_WT5OF5_FILTER_TF=OFF | HD2: NOLOSS_BYPASS_WT5OF5_FILTER_TF=D | HE2: NOLOSS_BYPASS_WT5OF5_FILTER_TF=4h | HF2: NOLOSS_BYPASS_WT5OF5_FILTER_TF=1h | HG2: NOLOSS_BYPASS_WT5OF5_FILTER_TF=15m | HH2: OPEN_INTENT_SIZE_GATES_FILTER_TF=OFF | HI2: OPEN_INTENT_SIZE_GATES_FILTER_TF=D | HJ2: OPEN_INTENT_SIZE_GATES_FILTER_TF=4h | HK2: OPEN_INTENT_SIZE_GATES_FILTER_TF=1h | HL2: OPEN_INTENT_SIZE_GATES_FILTER_TF=15m | HM2: PARTIAL_PROFIT_LOCK_V2_FILTER_TF=OFF | HN2: PARTIAL_PROFIT_LOCK_V2_FILTER_TF=D | HO2: PARTIAL_PROFIT_LOCK_V2_FILTER_TF=4h | HP2: PARTIAL_PROFIT_LOCK_V2_FILTER_TF=1h | HQ2: PARTIAL_PROFIT_LOCK_V2_FILTER_TF=15m | HR2: PEAK_GIVEBACK_BE_EROSION_FILTER_TF=OFF | HS2: PEAK_GIVEBACK_BE_EROSION_FILTER_TF=D | HT2: PEAK_GIVEBACK_BE_EROSION_FILTER_TF=4h | HU2: PEAK_GIVEBACK_BE_EROSION_FILTER_TF=1h | HV2: PEAK_GIVEBACK_BE_EROSION_FILTER_TF=15m | HW2: WT_15M_BOUNCE_BB_MAX=0.95 | HX2: WT_15M_BOUNCE_BB_MAX=0.9 | HY2: WT_15M_BOUNCE_BB_MAX=0.8 | HZ2: WT_15M_BOUNCE_BB_MIN=0.05 | IA2: WT_15M_BOUNCE_BB_MIN=0.1 | IB2: WT_15M_BOUNCE_BB_MIN=0.2 | IC2: WT_15M_BOUNCE_HIGH_1H_GT_PREV=True | ID2: WT_15M_BOUNCE_HIGH_1H_GT_PREV=False | IE2: WT_15M_BOUNCE_LOW_1H_GT_PREV=True | IF2: WT_15M_BOUNCE_LOW_1H_GT_PREV=False | IG2: WT_15M_BOUNCE_REL_VOL_GT_1=True | IH2: WT_15M_BOUNCE_REL_VOL_GT_1=False | II2: Live Location | IJ2: Vec Hook | IK2: Type | IL2: Correct Options
A3: WT_15M_BOUNCE_OPEN_ENABLED | B3: False | C3: WT_15M_BOUNCE_OPEN_ENABLED=False + WT_15M_BOUNCE_BB_MAX=0.8 + BB_WT_TF=15m + GR=18 + BB_RECOVERY_FILTER_TF=OFF + DC_BREAK_FILTER_TF=1h | E3: ='META_LONG_BASELINE_METRICS'!B2 | F3: =IFERROR(VLOOKUP($A3&"="&$B3,Results_30d_Deltas!$A$2:$H$5000,5,FALSE),"") | G3: =IFERROR(VLOOKUP($A3,Results_30d_Deltas!$A$2:$H$5000,7,FALSE)-E3,"") | H3: =IFERROR(VLOOKUP($A3,Results_30d_Deltas!$A$2:$H$5000,6,FALSE),"") | K3: =IF(B3=C3,"YES","NO") | IJ3: ez_manage.py:6076 top() | IK3: v12_quick_engine.py:4288 x7
A4: WT_15M_BOUNCE_OPEN_ENABLED | B4: True | C4: WT_15M_BOUNCE_OPEN_ENABLED=True + WT_15M_BOUNCE_BB_MAX=0.8 + BB_WT_TF=15m + GR=18 + BB_RECOVERY_FILTER_TF=OFF + DC_BREAK_FILTER_TF=1h | E4: =IF(F4="",E3,IF(F4>0,E3+F4,E3)) | F4: -2.6134663 | G4: =IFERROR(VLOOKUP($A4,Results_30d_Deltas!$A$2:$H$5000,7,FALSE)-E3,"") | H4: =IFERROR(VLOOKUP($A4,Results_30d_Deltas!$A$2:$H$5000,6,FALSE),"") | K4: =IF(B4=C4,"YES","NO") | IJ4: ez_manage.py:6076 top() | IK4: v12_quick_engine.py:4288 x7
A5: BB_SQUEEZE_ENTRY_ENABLED | B5: True | C5: BB_SQUEEZE_ENTRY_ENABLED=True + ADX_RANGING_THRESHOLD=25 + BB_WT_TF=15m + GR=18 + BB_RECOVERY_FILTER_TF=OFF + DC_BREAK_FILTER_TF=1h | E5: =IF(F5="",E4,IF(F5>0,E4+F5,E4)) | F5: -2.6134663 | G5: =IFERROR(VLOOKUP($A5,Results_30d_Deltas!$A$2:$H$5000,7,FALSE)-E4,"") | H5: =IFERROR(VLOOKUP($A5,Results_30d_Deltas!$A$2:$H$5000,6,FALSE),"") | K5: =IF(B5=C5,"YES","NO") | IJ5: ez_manage.py:4371 top() | IK5: v12_quick_engine.py:889 x9
A6: BB_PULLBACK_GATE_TF | B6: OFF | C6: BB_PULLBACK_GATE_TF=OFF + MTS_BOTTOM_STRONG_THRESHOLD=20 + BB_WT_TF=15m + GR=18 + BB_RECOVERY_FILTER_TF=OFF + DC_BREAK_FILTER_TF=1h | E6: =IF(F6="",E5,IF(F6>0,E5+F6,E5)) | F6: -2.6134663 | G6: =IFERROR(VLOOKUP($A6,Results_30d_Deltas!$A$2:$H$5000,7,FALSE)-E5,"") | H6: =IFERROR(VLOOKUP($A6,Results_30d_Deltas!$A$2:$H$5000,6,FALSE),"") | K6: =IF(B6=C6,"YES","NO") | IJ6: ez_manage.py:4361 top() | IK6: v12_quick_engine.py:288 x12
A7: BB_PULLBACK_GATE_TF | B7: D | E7: =IF(F7="",E6,IF(F7>0,E6+F7,E6)) | F7: -2.6134663 | G7: =IFERROR(VLOOKUP($A7,Results_30d_Deltas!$A$2:$H$5000,7,FALSE)-E6,"") | H7: =IFERROR(VLOOKUP($A7,Results_30d_Deltas!$A$2:$H$5000,6,FALSE),"") | K7: =IF(B7=C7,"YES","NO") | IJ7: ez_manage.py:4361 top() | IK7: v12_quick_engine.py:288 x12
A8: BB_PULLBACK_GATE_TF | B8: 4h | E8: =IF(F8="",E7,IF(F8>0,E7+F8,E7)) | F8: -2.6134663 | G8: =IFERROR(VLOOKUP($A8,Results_30d_Deltas!$A$2:$H$5000,7,FALSE)-E7,"") | H8: =IFERROR(VLOOKUP($A8,Results_30d_Deltas!$A$2:$H$5000,6,FALSE),"") | K8: =IF(B8=C8,"YES","NO") | IJ8: ez_manage.py:4361 top() | IK8: v12_quick_engine.py:288 x12
A9: BB_PULLBACK_GATE_TF | B9: 1h | C9: BB_PULLBACK_GATE_TF=1h + MI_TF_AGREE_MIN=0.0_ALT + BB_WT_TF=15m + GR=18 + BB_RECOVERY_FILTER_TF=OFF + DC_BREAK_FILTER_TF=1h | E9: =IF(F9="",E8,IF(F9>0,E8+F9,E8)) | F9: -2.6134663 | G9: =IFERROR(VLOOKUP($A9,Results_30d_Deltas!$A$2:$H$5000,7,FALSE)-E8,"") | H9: =IFERROR(VLOOKUP($A9,Results_30d_Deltas!$A$2:$H$5000,6,FALSE),"") | K9: =IF(B9=C9,"YES","NO") | IJ9: ez_manage.py:4361 top() | IK9: v12_quick_engine.py:288 x12
A10: BB_PULLBACK_GATE_TF | B10: 15m | E10: =IF(F10="",E9,IF(F10>0,E9+F10,E9)) | F10: =IFERROR(VLOOKUP($A10&"="&$B10,Results_30d_Deltas!$A$2:$H$5000,5,FALSE),"") | G10: =IFERROR(VLOOKUP($A10,Results_30d_Deltas!$A$2:$H$5000,7,FALSE)-E9,"") | H10: =IFERROR(VLOOKUP($A10,Results_30d_Deltas!$A$2:$H$5000,6,FALSE),"") | K10: =IF(B10=C10,"YES","NO") | IJ10: ez_manage.py:4361 top() | IK10: v12_quick_engine.py:288 x12
A11: DELTA_GATE_BB_SQUEEZE | B11: True | E11: =IF(F11="",E10,IF(F11>0,E10+F11,E10)) | F11: =IFERROR(VLOOKUP($A11&"="&$B11,Results_30d_Deltas!$A$2:$H$5000,5,FALSE),"") | G11: =IFERROR(VLOOKUP($A11,Results_30d_Deltas!$A$2:$H$5000,7,FALSE)-E10,"") | H11: =IFERROR(VLOOKUP($A11,Results_30d_Deltas!$A$2:$H$5000,6,FALSE),"") | K11: =IF(B11=C11,"YES","NO") | IJ11: ez_manage.py:4603 top() | IK11: v12_quick_engine.py:969 x9
A12: BB_SQUEEZE_WIDTH_PERCENTILE | B12: 0.1 | E12: =IF(F12="",E11,IF(F12>0,E11+F12,E11)) | F12: -2.6134663 | G12: =IFERROR(VLOOKUP($A12,Results_30d_Deltas!$A$2:$H$5000,7,FALSE)-E11,"") | H12: =IFERROR(VLOOKUP($A12,Results_30d_Deltas!$A$2:$H$5000,6,FALSE),"") | K12: =IF(B12=C12,"YES","NO") | IJ12: ez_manage.py:4375 top() | IK12: v12_quick_engine.py:1285 x7
A13: BB_SQUEEZE_WIDTH_PERCENTILE | B13: 0.15 | E13: =IF(F13="",E12,IF(F13>0,E12+F13,E12)) | F13: -2.6134663 | G13: =IFERROR(VLOOKUP($A13,Results_30d_Deltas!$A$2:$H$5000,7,FALSE)-E12,"") | H13: =IFERROR(VLOOKUP($A13,Results_30d_Deltas!$A$2:$H$5000,6,FALSE),"") | K13: =IF(B13=C13,"YES","NO") | IJ13: ez_manage.py:4375 top() | IK13: v12_quick_engine.py:1285 x7
A14: BB_SQUEEZE_WIDTH_PERCENTILE | B14: 0.2 | E14: =IF(F14="",E13,IF(F14>0,E13+F14,E13)) | F14: -2.6134663 | G14: =IFERROR(VLOOKUP($A14,Results_30d_Deltas!$A$2:$H$5000,7,FALSE)-E13,"") | H14: =IFERROR(VLOOKUP($A14,Results_30d_Deltas!$A$2:$H$5000,6,FALSE),"") | K14: =IF(B14=C14,"YES","NO") | IJ14: ez_manage.py:4375 top() | IK14: v12_quick_engine.py:1285 x7
A15: BB_SQUEEZE_WIDTH_PERCENTILE | B15: 0.25 | E15: =IF(F15="",E14,IF(F15>0,E14+F15,E14)) | F15: -2.6134663 | G15: =IFERROR(VLOOKUP($A15,Results_30d_Deltas!$A$2:$H$5000,7,FALSE)-E14,"") | H15: =IFERROR(VLOOKUP($A15,Results_30d_Deltas!$A$2:$H$5000,6,FALSE),"") | K15: =IF(B15=C15,"YES","NO") | IJ15: ez_manage.py:4375 top() | IK15: v12_quick_engine.py:1285 x7
A16: BB_SQUEEZE_WIDTH_PERCENTILE | B16: 0.3 | E16: =IF(F16="",E15,IF(F16>0,E15+F16,E15)) | F16: -2.6134663 | G16: =IFERROR(VLOOKUP($A16,Results_30d_Deltas!$A$2:$H$5000,7,FALSE)-E15,"") | H16: =IFERROR(VLOOKUP($A16,Results_30d_Deltas!$A$2:$H$5000,6,FALSE),"") | K16: =IF(B16=C16,"YES","NO") | IJ16: ez_manage.py:4375 top() | IK16: v12_quick_engine.py:1285 x7
A17: WT_DIV_EXIT_ENABLED | B17: False | E17: =IF(F17="",E16,IF(F17>0,E16+F17,E16)) | F17: -2.6134663 | G17: =IFERROR(VLOOKUP($A17,Results_30d_Deltas!$A$2:$H$5000,7,FALSE)-E16,"") | H17: =IFERROR(VLOOKUP($A17,Results_30d_Deltas!$A$2:$H$5000,6,FALSE),"") | K17: =IF(B17=C17,"YES","NO") | IJ17: ez_manage.py:6086 top() | IK17: v12_quick_engine.py:4292 x3
A18: WT_DIV_EXIT_ENABLED | B18: True | E18: =IF(F18="",E17,IF(F18>0,E17+F18,E17)) | F18: =IFERROR(VLOOKUP($A18&"="&$B18,Results_30d_Deltas!$A$2:$H$5000,5,FALSE),"") | G18: =IFERROR(VLOOKUP($A18,Results_30d_Deltas!$A$2:$H$5000,7,FALSE)-E17,"") | H18: =IFERROR(VLOOKUP($A18,Results_30d_Deltas!$A$2:$H$5000,6,FALSE),"") | K18: =IF(B18=C18,"YES","NO") | IJ18: ez_manage.py:6086 top() | IK18: v12_quick_engine.py:4292 x3
A19: WT_MOMENTUM_EXIT_THRESHOLD | B19: 0 | E19: =IF(F19="",E18,IF(F19>0,E18+F19,E18)) | F19: -2.6134663 | G19: =IFERROR(VLOOKUP($A19,Results_30d_Deltas!$A$2:$H$5000,7,FALSE)-E18,"") | H19: =IFERROR(VLOOKUP($A19,Results_30d_Deltas!$A$2:$H$5000,6,FALSE),"") | K19: =IF(B19=C19,"YES","NO") | IJ19: ez_manage.py:6087 top() | IK19: v12_quick_engine.py:4293 x3
A20: WT_MOMENTUM_EXIT_THRESHOLD | B20: 1 | E20: =IF(F20="",E19,IF(F20>0,E19+F20,E19)) | F20: -2.6134663 | G20: =IFERROR(VLOOKUP($A20,Results_30d_Deltas!$A$2:$H$5000,7,FALSE)-E19,"") | H20: =IFERROR(VLOOKUP($A20,Results_30d_Deltas!$A$2:$H$5000,6,FALSE),"") | K20: =IF(B20=C20,"YES","NO") | IJ20: ez_manage.py:6087 top() | IK20: v12_quick_engine.py:4293 x3
A21: WT_MOMENTUM_EXIT_THRESHOLD | B21: 2 | E21: =IF(F21="",E20,IF(F21>0,E20+F21,E20)) | F21: -2.6134663 | G21: =IFERROR(VLOOKUP($A21,Results_30d_Deltas!$A$2:$H$5000,7,FALSE)-E20,"") | H21: =IFERROR(VLOOKUP($A21,Results_30d_Deltas!$A$2:$H$5000,6,FALSE),"") | K21: =IF(B21=C21,"YES","NO") | IJ21: ez_manage.py:6087 top() | IK21: v12_quick_engine.py:4293 x3
A22: WT_ACCEL_EXIT_ENABLED | B22: False | E22: =IF(F22="",E21,IF(F22>0,E21+F22,E21)) | F22: -2.6134663 | G22: =IFERROR(VLOOKUP($A22,Results_30d_Deltas!$A$2:$H$5000,7,FALSE)-E21,"") | H22: =IFERROR(VLOOKUP($A22,Results_30d_Deltas!$A$2:$H$5000,6,FALSE),"") | K22: =IF(B22=C22,"YES","NO") | IJ22: ez_manage.py:6083 top() | IK22: v12_quick_engine.py:4290 x3
A23: WT_ACCEL_EXIT_ENABLED | B23: True | E23: =IF(F23="",E22,IF(F23>0,E22+F23,E22)) | F23: =IFERROR(VLOOKUP($A23&"="&$B23,Results_30d_Deltas!$A$2:$H$5000,5,FALSE),"") | G23: =IFERROR(VLOOKUP($A23,Results_30d_Deltas!$A$2:$H$5000,7,FALSE)-E22,"") | H23: =IFERROR(VLOOKUP($A23,Results_30d_Deltas!$A$2:$H$5000,6,FALSE),"") | K23: =IF(B23=C23,"YES","NO") | IJ23: ez_manage.py:6083 top() | IK23: v12_quick_engine.py:4290 x3

Sheet ENTRY_BREAKOUT_CHANNEL
A1: 02 ENTRY_BREAKOUT_CHANNEL - 54 bases -> 210 rows - 231 per-row FULLY CONNECTED
A2: Switch | B2: default | C2: override | D2: Family | E2: =MAX('ENTRY_REVERSAL_BOUNCE'!E$2:E$5000) | F2: VECTOR_DELTA | G2: LIVE_DELTA | H2: LIVE_SHARPE | I2: REAL_COMPLETE | J2: PER_ROW_FILTERS | K2: is_default (backup if bold lost) | L2: ATR_TRAIL_FILTER_TF=OFF | M2: ATR_TRAIL_FILTER_TF=D | N2: ATR_TRAIL_FILTER_TF=4h | O2: ATR_TRAIL_FILTER_TF=1h | P2: ATR_TRAIL_FILTER_TF=15m | Q2: BAR_PATTERNS_FILTER_TF=OFF | R2: BAR_PATTERNS_FILTER_TF=D | S2: BAR_PATTERNS_FILTER_TF=4h | T2: BAR_PATTERNS_FILTER_TF=1h | U2: BAR_PATTERNS_FILTER_TF=15m | V2: BB_PULLBACK_GATE_FILTER_TF=OFF | W2: BB_PULLBACK_GATE_FILTER_TF=D | X2: BB_PULLBACK_GATE_FILTER_TF=4h | Y2: BB_PULLBACK_GATE_FILTER_TF=1h | Z2: BB_PULLBACK_GATE_FILTER_TF=15m | AA2: BB_RECOVERY_ENTRY_FILTER_TF=OFF | AB2: BB_RECOVERY_ENTRY_FILTER_TF=D | AC2: BB_RECOVERY_ENTRY_FILTER_TF=4h | AD2: BB_RECOVERY_ENTRY_FILTER_TF=1h | AE2: BB_RECOVERY_ENTRY_FILTER_TF=15m | AF2: BB_RECOVERY_FILTER_TF=OFF | AG2: BB_RECOVERY_FILTER_TF=D | AH2: BB_RECOVERY_FILTER_TF=4h | AI2: BB_RECOVERY_FILTER_TF=1h | AJ2: BB_RECOVERY_FILTER_TF=15m | AK2: BREAKEVEN_GAIN_EROSION_FILTER_TF=OFF | AL2: BREAKEVEN_GAIN_EROSION_FILTER_TF=D | AM2: BREAKEVEN_GAIN_EROSION_FILTER_TF=4h | AN2: BREAKEVEN_GAIN_EROSION_FILTER_TF=1h | AO2: BREAKEVEN_GAIN_EROSION_FILTER_TF=15m | AP2: BREAKOUT_RETEST_FILTER_TF=OFF | AQ2: BREAKOUT_RETEST_FILTER_TF=D | AR2: BREAKOUT_RETEST_FILTER_TF=4h | AS2: BREAKOUT_RETEST_FILTER_TF=1h | AT2: BREAKOUT_RETEST_FILTER_TF=15m | AU2: BT_WT_CROSS_LADDER_FILTER_TF=OFF | AV2: BT_WT_CROSS_LADDER_FILTER_TF=D | AW2: BT_WT_CROSS_LADDER_FILTER_TF=4h | AX2: BT_WT_CROSS_LADDER_FILTER_TF=1h | AY2: BT_WT_CROSS_LADDER_FILTER_TF=15m | AZ2: CANDLE_PATTERN_STOPS_FILTER_TF=OFF | BA2: CANDLE_PATTERN_STOPS_FILTER_TF=D | BB2: CANDLE_PATTERN_STOPS_FILTER_TF=4h | BC2: CANDLE_PATTERN_STOPS_FILTER_TF=1h | BD2: CANDLE_PATTERN_STOPS_FILTER_TF=15m | BE2: CIRCUIT_SHARPE_GATES_FILTER_TF=OFF | BF2: CIRCUIT_SHARPE_GATES_FILTER_TF=D | BG2: CIRCUIT_SHARPE_GATES_FILTER_TF=4h | BH2: CIRCUIT_SHARPE_GATES_FILTER_TF=1h | BI2: CIRCUIT_SHARPE_GATES_FILTER_TF=15m | BJ2: DC_BREACH_REDUCE_FILTER_TF=OFF | BK2: DC_BREACH_REDUCE_FILTER_TF=D | BL2: DC_BREACH_REDUCE_FILTER_TF=4h | BM2: DC_BREACH_REDUCE_FILTER_TF=1h | BN2: DC_BREACH_REDUCE_FILTER_TF=15m | BO2: DC_BREAK_FILTER_TF=OFF | BP2: DC_BREAK_FILTER_TF=D | BQ2: DC_BREAK_FILTER_TF=4h | BR2: DC_BREAK_FILTER_TF=1h | BS2: DC_BREAK_FILTER_TF=15m | BT2: DC_MOMENTUM_BOTA_SCORER_FILTER_TF=OFF | BU2: DC_MOMENTUM_BOTA_SCORER_FILTER_TF=D | BV2: DC_MOMENTUM_BOTA_SCORER_FILTER_TF=4h | BW2: DC_MOMENTUM_BOTA_SCORER_FILTER_TF=1h | BX2: DC_MOMENTUM_BOTA_SCORER_FILTER_TF=15m | BY2: DELTA_ENGINE_FILTER_TF=OFF | BZ2: DELTA_ENGINE_FILTER_TF=D | CA2: DELTA_ENGINE_FILTER_TF=4h | CB2: DELTA_ENGINE_FILTER_TF=1h | CC2: DELTA_ENGINE_FILTER_TF=15m | CD2: EMA_9_21_FILTER_FILTER_TF=OFF | CE2: EMA_9_21_FILTER_FILTER_TF=D | CF2: EMA_9_21_FILTER_FILTER_TF=4h | CG2: EMA_9_21_FILTER_FILTER_TF=1h | CH2: EMA_9_21_FILTER_FILTER_TF=15m | CI2: EMA_BLANKET_FILTER_FILTER_TF=OFF | CJ2: EMA_BLANKET_FILTER_FILTER_TF=D | CK2: EMA_BLANKET_FILTER_FILTER_TF=4h | CL2: EMA_BLANKET_FILTER_FILTER_TF=1h | CM2: EMA_BLANKET_FILTER_FILTER_TF=15m | CN2: EMERGENCY_BRAKE_FILTER_TF=OFF | CO2: EMERGENCY_BRAKE_FILTER_TF=D | CP2: EMERGENCY_BRAKE_FILTER_TF=4h | CQ2: EMERGENCY_BRAKE_FILTER_TF=1h | CR2: EMERGENCY_BRAKE_FILTER_TF=15m | CS2: EXIT_R1_R2_FILTER_TF=OFF | CT2: EXIT_R1_R2_FILTER_TF=D | CU2: EXIT_R1_R2_FILTER_TF=4h | CV2: EXIT_R1_R2_FILTER_TF=1h | CW2: EXIT_R1_R2_FILTER_TF=15m | CX2: EXIT_TIGHT_BREAKOUT_SCORER_FILTER_TF=OFF | CY2: EXIT_TIGHT_BREAKOUT_SCORER_FILTER_TF=D | CZ2: EXIT_TIGHT_BREAKOUT_SCORER_FILTER_TF=4h | DA2: EXIT_TIGHT_BREAKOUT_SCORER_FILTER_TF=1h | DB2: EXIT_TIGHT_BREAKOUT_SCORER_FILTER_TF=15m | DC2: EXIT_TOP_FADE_FILTER_TF=OFF | DD2: EXIT_TOP_FADE_FILTER_TF=D | DE2: EXIT_TOP_FADE_FILTER_TF=4h | DF2: EXIT_TOP_FADE_FILTER_TF=1h | DG2: EXIT_TOP_FADE_FILTER_TF=15m | DH2: EXIT_TO_REDUCE_ADAPTER_FILTER_TF=OFF | DI2: EXIT_TO_REDUCE_ADAPTER_FILTER_TF=D | DJ2: EXIT_TO_REDUCE_ADAPTER_FILTER_TF=4h | DK2: EXIT_TO_REDUCE_ADAPTER_FILTER_TF=1h | DL2: EXIT_TO_REDUCE_ADAPTER_FILTER_TF=15m | DM2: FAST_RISER_FILTER_TF=OFF | DN2: FAST_RISER_FILTER_TF=D | DO2: FAST_RISER_FILTER_TF=4h | DP2: FAST_RISER_FILTER_TF=1h | DQ2: FAST_RISER_FILTER_TF=15m | DR2: FH_MOMENTUM_FILTER_TF=OFF | DS2: FH_MOMENTUM_FILTER_TF=D | DT2: FH_MOMENTUM_FILTER_TF=4h | DU2: FH_MOMENTUM_FILTER_TF=1h | DV2: FH_MOMENTUM_FILTER_TF=15m | DW2: FIRST_OPEN_THROTTLE_FILTER_TF=OFF | DX2: FIRST_OPEN_THROTTLE_FILTER_TF=D | DY2: FIRST_OPEN_THROTTLE_FILTER_TF=4h | DZ2: FIRST_OPEN_THROTTLE_FILTER_TF=1h | EA2: FIRST_OPEN_THROTTLE_FILTER_TF=15m | EB2: FROZEN_STOP_FILTER_TF=OFF | EC2: FROZEN_STOP_FILTER_TF=D | ED2: FROZEN_STOP_FILTER_TF=4h | EE2: FROZEN_STOP_FILTER_TF=1h | EF2: FROZEN_STOP_FILTER_TF=15m | EG2: GOLDEN_RULE_ENFORCE_FILTER_TF=OFF | EH2: GOLDEN_RULE_ENFORCE_FILTER_TF=D | EI2: GOLDEN_RULE_ENFORCE_FILTER_TF=4h | EJ2: GOLDEN_RULE_ENFORCE_FILTER_TF=1h | EK2: GOLDEN_RULE_ENFORCE_FILTER_TF=15m | EL2: GOLDEN_RULE_HTF_VOTE_FILTER_TF=OFF | EM2: GOLDEN_RULE_HTF_VOTE_FILTER_TF=D | EN2: GOLDEN_RULE_HTF_VOTE_FILTER_TF=4h | EO2: GOLDEN_RULE_HTF_VOTE_FILTER_TF=1h | EP2: GOLDEN_RULE_HTF_VOTE_FILTER_TF=15m | EQ2: GR_FILTER_VEC_FILTER_TF=OFF | ER2: GR_FILTER_VEC_FILTER_TF=D | ES2: GR_FILTER_VEC_FILTER_TF=4h | ET2: GR_FILTER_VEC_FILTER_TF=1h | EU2: GR_FILTER_VEC_FILTER_TF=15m | EV2: GR_V5_STATE_FILTER_TF=OFF | EW2: GR_V5_STATE_FILTER_TF=D | EX2: GR_V5_STATE_FILTER_TF=4h | EY2: GR_V5_STATE_FILTER_TF=1h | EZ2: GR_V5_STATE_FILTER_TF=15m | FA2: HAIKU_WINNER_FILTER_TF=OFF | FB2: HAIKU_WINNER_FILTER_TF=D | FC2: HAIKU_WINNER_FILTER_TF=4h | FD2: HAIKU_WINNER_FILTER_TF=1h | FE2: HAIKU_WINNER_FILTER_TF=15m | FF2: LH_HL_FILTER_TF_REQ=2 | FG2: LH_HL_FILTER_TF_REQ=2_ALT | FH2: LIVE_ENTRY_ENGINE_FILTER_TF=OFF | FI2: LIVE_ENTRY_ENGINE_FILTER_TF=D | FJ2: LIVE_ENTRY_ENGINE_FILTER_TF=4h | FK2: LIVE_ENTRY_ENGINE_FILTER_TF=1h | FL2: LIVE_ENTRY_ENGINE_FILTER_TF=15m | FM2: LIVE_ONLY_SIGNALS_BATCH5_FILTER_TF=OFF | FN2: LIVE_ONLY_SIGNALS_BATCH5_FILTER_TF=D | FO2: LIVE_ONLY_SIGNALS_BATCH5_FILTER_TF=4h | FP2: LIVE_ONLY_SIGNALS_BATCH5_FILTER_TF=1h | FQ2: LIVE_ONLY_SIGNALS_BATCH5_FILTER_TF=15m | FR2: MANDATORY_REENTRY_WT_FILTER_TF_MODE=15m_only | FS2: MANDATORY_REENTRY_WT_FILTER_TF_MODE=15m_only_ALT | FT2: MOM3_FILTER_TF=OFF | FU2: MOM3_FILTER_TF=D | FV2: MOM3_FILTER_TF=4h | FW2: MOM3_FILTER_TF=1h | FX2: MOM3_FILTER_TF=15m | FY2: MOMENTUM_BREAKOUT_FILTER_TF=OFF | FZ2: MOMENTUM_BREAKOUT_FILTER_TF=D | GA2: MOMENTUM_BREAKOUT_FILTER_TF=4h | GB2: MOMENTUM_BREAKOUT_FILTER_TF=1h | GC2: MOMENTUM_BREAKOUT_FILTER_TF=15m | GD2: MTF_ARMED_ENTRIES_FILTER_TF=OFF | GE2: MTF_ARMED_ENTRIES_FILTER_TF=D | GF2: MTF_ARMED_ENTRIES_FILTER_TF=4h | GG2: MTF_ARMED_ENTRIES_FILTER_TF=1h | GH2: MTF_ARMED_ENTRIES_FILTER_TF=15m | GI2: MTF_ATR_TRAIL_FILTER_TF=OFF | GJ2: MTF_ATR_TRAIL_FILTER_TF=D | GK2: MTF_ATR_TRAIL_FILTER_TF=4h | GL2: MTF_ATR_TRAIL_FILTER_TF=1h | GM2: MTF_ATR_TRAIL_FILTER_TF=15m | GN2: MTF_DC_REJECT_FILTER_TF=OFF | GO2: MTF_DC_REJECT_FILTER_TF=D | GP2: MTF_DC_REJECT_FILTER_TF=4h | GQ2: MTF_DC_REJECT_FILTER_TF=1h | GR2: MTF_DC_REJECT_FILTER_TF=15m | GS2: NEWBORN_LOSS_KILL_FILTER_TF=OFF | GT2: NEWBORN_LOSS_KILL_FILTER_TF=D | GU2: NEWBORN_LOSS_KILL_FILTER_TF=4h | GV2: NEWBORN_LOSS_KILL_FILTER_TF=1h | GW2: NEWBORN_LOSS_KILL_FILTER_TF=15m | GX2: NEWBORN_PROTECT_FILTER_TF=OFF | GY2: NEWBORN_PROTECT_FILTER_TF=D | GZ2: NEWBORN_PROTECT_FILTER_TF=4h | HA2: NEWBORN_PROTECT_FILTER_TF=1h | HB2: NEWBORN_PROTECT_FILTER_TF=15m | HC2: NOLOSS_BYPASS_WT5OF5_FILTER_TF=OFF | HD2: NOLOSS_BYPASS_WT5OF5_FILTER_TF=D | HE2: NOLOSS_BYPASS_WT5OF5_FILTER_TF=4h | HF2: NOLOSS_BYPASS_WT5OF5_FILTER_TF=1h | HG2: NOLOSS_BYPASS_WT5OF5_FILTER_TF=15m | HH2: OPEN_INTENT_SIZE_GATES_FILTER_TF=OFF | HI2: OPEN_INTENT_SIZE_GATES_FILTER_TF=D | HJ2: OPEN_INTENT_SIZE_GATES_FILTER_TF=4h | HK2: OPEN_INTENT_SIZE_GATES_FILTER_TF=1h | HL2: OPEN_INTENT_SIZE_GATES_FILTER_TF=15m | HM2: PARTIAL_PROFIT_LOCK_V2_FILTER_TF=OFF | HN2: PARTIAL_PROFIT_LOCK_V2_FILTER_TF=D | HO2: PARTIAL_PROFIT_LOCK_V2_FILTER_TF=4h | HP2: PARTIAL_PROFIT_LOCK_V2_FILTER_TF=1h | HQ2: PARTIAL_PROFIT_LOCK_V2_FILTER_TF=15m | HR2: PEAK_GIVEBACK_BE_EROSION_FILTER_TF=OFF | HS2: PEAK_GIVEBACK_BE_EROSION_FILTER_TF=D | HT2: PEAK_GIVEBACK_BE_EROSION_FILTER_TF=4h | HU2: PEAK_GIVEBACK_BE_EROSION_FILTER_TF=1h | HV2: PEAK_GIVEBACK_BE_EROSION_FILTER_TF=15m | HW2: WT_15M_BOUNCE_BB_MAX=0.95 | HX2: WT_15M_BOUNCE_BB_MAX=0.9 | HY2: WT_15M_BOUNCE_BB_MAX=0.8 | HZ2: WT_15M_BOUNCE_BB_MIN=0.05 | IA2: WT_15M_BOUNCE_BB_MIN=0.1 | IB2: WT_15M_BOUNCE_BB_MIN=0.2 | IC2: WT_15M_BOUNCE_HIGH_1H_GT_PREV=True | ID2: WT_15M_BOUNCE_HIGH_1H_GT_PREV=False | IE2: WT_15M_BOUNCE_LOW_1H_GT_PREV=True | IF2: WT_15M_BOUNCE_LOW_1H_GT_PREV=False | IG2: WT_15M_BOUNCE_REL_VOL_GT_1=True | IH2: WT_15M_BOUNCE_REL_VOL_GT_1=False | II2: Live Location | IJ2: Vec Hook | IK2: Type | IL2: Correct Options
A3: DC_BREAKOUT_TF | B3: OFF | E3: =MAX('ENTRY_REVERSAL_BOUNCE'!E:E) | F3: -2.6134663 | G3: =IFERROR(VLOOKUP($A3,Results_30d_Deltas!$A$2:$H$5000,7,FALSE)-E3,"") | H3: =IFERROR(VLOOKUP($A3,Results_30d_Deltas!$A$2:$H$5000,6,FALSE),"") | K3: =IF(B3=C3,"YES","NO") | IJ3: ez_manage.py:3078 top() | IK3: v12_quick_engine.py:1518 x5
A4: DC_BREAKOUT_TF | B4: D | E4: =IF(F4="",E3,IF(F4>0,E3+F4,E3)) | F4: -2.6134663 | G4: =IFERROR(VLOOKUP($A4,Results_30d_Deltas!$A$2:$H$5000,7,FALSE)-E3,"") | H4: =IFERROR(VLOOKUP($A4,Results_30d_Deltas!$A$2:$H$5000,6,FALSE),"") | K4: =IF(B4=C4,"YES","NO") | IJ4: ez_manage.py:3078 top() | IK4: v12_quick_engine.py:1518 x5
A5: DC_BREAKOUT_TF | B5: 4h | E5: =IF(F5="",E4,IF(F5>0,E4+F5,E4)) | F5: -2.6134663 | G5: =IFERROR(VLOOKUP($A5,Results_30d_Deltas!$A$2:$H$5000,7,FALSE)-E4,"") | H5: =IFERROR(VLOOKUP($A5,Results_30d_Deltas!$A$2:$H$5000,6,FALSE),"") | K5: =IF(B5=C5,"YES","NO") | IJ5: ez_manage.py:3078 top() | IK5: v12_quick_engine.py:1518 x5
A6: DC_BREAKOUT_TF | B6: 1h | E6: =IF(F6="",E5,IF(F6>0,E5+F6,E5)) | F6: -2.6134663 | G6: =IFERROR(VLOOKUP($A6,Results_30d_Deltas!$A$2:$H$5000,7,FALSE)-E5,"") | H6: =IFERROR(VLOOKUP($A6,Results_30d_Deltas!$A$2:$H$5000,6,FALSE),"") | K6: =IF(B6=C6,"YES","NO") | IJ6: ez_manage.py:3078 top() | IK6: v12_quick_engine.py:1518 x5
A7: DC_BREAKOUT_TF | B7: 15m | E7: =IF(F7="",E6,IF(F7>0,E6+F7,E6)) | F7: =IFERROR(VLOOKUP($A7&"="&$B7,Results_30d_Deltas!$A$2:$H$5000,5,FALSE),"") | G7: =IFERROR(VLOOKUP($A7,Results_30d_Deltas!$A$2:$H$5000,7,FALSE)-E6,"") | H7: =IFERROR(VLOOKUP($A7,Results_30d_Deltas!$A$2:$H$5000,6,FALSE),"") | K7: =IF(B7=C7,"YES","NO") | IJ7: ez_manage.py:3078 top() | IK7: v12_quick_engine.py:1518 x5
A8: DC_BREAKOUT_SCORE | B8: 10 | E8: =IF(F8="",E7,IF(F8>0,E7+F8,E7)) | F8: -2.6134663 | G8: =IFERROR(VLOOKUP($A8,Results_30d_Deltas!$A$2:$H$5000,7,FALSE)-E7,"") | H8: =IFERROR(VLOOKUP($A8,Results_30d_Deltas!$A$2:$H$5000,6,FALSE),"") | K8: =IF(B8=C8,"YES","NO") | IJ8: ez_manage.py:3077 top() | IK8: v12_quick_engine.py:1517 x18
A9: DC_BREAKOUT_SCORE | B9: 15 | E9: =IF(F9="",E8,IF(F9>0,E8+F9,E8)) | F9: -2.6134663 | G9: =IFERROR(VLOOKUP($A9,Results_30d_Deltas!$A$2:$H$5000,7,FALSE)-E8,"") | H9: =IFERROR(VLOOKUP($A9,Results_30d_Deltas!$A$2:$H$5000,6,FALSE),"") | K9: =IF(B9=C9,"YES","NO") | IJ9: ez_manage.py:3077 top() | IK9: v12_quick_engine.py:1517 x18
A10: DC_BREAKOUT_SCORE | B10: 20 | E10: =IF(F10="",E9,IF(F10>0,E9+F10,E9)) | F10: -2.6134663 | G10: =IFERROR(VLOOKUP($A10,Results_30d_Deltas!$A$2:$H$5000,7,FALSE)-E9,"") | H10: =IFERROR(VLOOKUP($A10,Results_30d_Deltas!$A$2:$H$5000,6,FALSE),"") | K10: =IF(B10=C10,"YES","NO") | IJ10: ez_manage.py:3077 top() | IK10: v12_quick_engine.py:1517 x18
A11: DC_BREAKOUT_SCORE | B11: 25 | E11: =IF(F11="",E10,IF(F11>0,E10+F11,E10)) | F11: -2.6134663 | G11: =IFERROR(VLOOKUP($A11,Results_30d_Deltas!$A$2:$H$5000,7,FALSE)-E10,"") | H11: =IFERROR(VLOOKUP($A11,Results_30d_Deltas!$A$2:$H$5000,6,FALSE),"") | K11: =IF(B11=C11,"YES","NO") | IJ11: ez_manage.py:3077 top() | IK11: v12_quick_engine.py:1517 x18
A12: DC_BREAKOUT_SCORE | B12: 30 | E12: =IF(F12="",E11,IF(F12>0,E11+F12,E11)) | F12: -2.6134663 | G12: =IFERROR(VLOOKUP($A12,Results_30d_Deltas!$A$2:$H$5000,7,FALSE)-E11,"") | H12: =IFERROR(VLOOKUP($A12,Results_30d_Deltas!$A$2:$H$5000,6,FALSE),"") | K12: =IF(B12=C12,"YES","NO") | IJ12: ez_manage.py:3077 top() | IK12: v12_quick_engine.py:1517 x18
A13: BB_BREAKOUT_SCORE | B13: 10 | E13: =IF(F13="",E12,IF(F13>0,E12+F13,E12)) | F13: -2.6134663 | G13: =IFERROR(VLOOKUP($A13,Results_30d_Deltas!$A$2:$H$5000,7,FALSE)-E12,"") | H13: =IFERROR(VLOOKUP($A13,Results_30d_Deltas!$A$2:$H$5000,6,FALSE),"") | K13: =IF(B13=C13,"YES","NO") | IJ13: ez_manage.py:2963 top() | IK13: v12_quick_engine.py:1255 x6
A14: BB_BREAKOUT_SCORE | B14: 15 | E14: =IF(F14="",E13,IF(F14>0,E13+F14,E13)) | F14: -2.6134663 | G14: =IFERROR(VLOOKUP($A14,Results_30d_Deltas!$A$2:$H$5000,7,FALSE)-E13,"") | H14: =IFERROR(VLOOKUP($A14,Results_30d_Deltas!$A$2:$H$5000,6,FALSE),"") | K14: =IF(B14=C14,"YES","NO") | IJ14: ez_manage.py:2963 top() | IK14: v12_quick_engine.py:1255 x6
A15: BB_BREAKOUT_SCORE | B15: 20 | E15: =IF(F15="",E14,IF(F15>0,E14+F15,E14)) | F15: -2.6134663 | G15: =IFERROR(VLOOKUP($A15,Results_30d_Deltas!$A$2:$H$5000,7,FALSE)-E14,"") | H15: =IFERROR(VLOOKUP($A15,Results_30d_Deltas!$A$2:$H$5000,6,FALSE),"") | K15: =IF(B15=C15,"YES","NO") | IJ15: ez_manage.py:2963 top() | IK15: v12_quick_engine.py:1255 x6
A16: BB_BREAKOUT_SCORE | B16: 25 | E16: =IF(F16="",E15,IF(F16>0,E15+F16,E15)) | F16: -2.6134663 | G16: =IFERROR(VLOOKUP($A16,Results_30d_Deltas!$A$2:$H$5000,7,FALSE)-E15,"") | H16: =IFERROR(VLOOKUP($A16,Results_30d_Deltas!$A$2:$H$5000,6,FALSE),"") | K16: =IF(B16=C16,"YES","NO") | IJ16: ez_manage.py:2963 top() | IK16: v12_quick_engine.py:1255 x6
A17: BB_BREAKOUT_SCORE | B17: 30 | E17: =IF(F17="",E16,IF(F17>0,E16+F17,E16)) | F17: -2.6134663 | G17: =IFERROR(VLOOKUP($A17,Results_30d_Deltas!$A$2:$H$5000,7,FALSE)-E16,"") | H17: =IFERROR(VLOOKUP($A17,Results_30d_Deltas!$A$2:$H$5000,6,FALSE),"") | K17: =IF(B17=C17,"YES","NO") | IJ17: ez_manage.py:2963 top() | IK17: v12_quick_engine.py:1255 x6
A18: STDEV_BREAKOUT_ENABLED | B18: False | E18: =IF(F18="",E17,IF(F18>0,E17+F18,E17)) | F18: =IFERROR(VLOOKUP($A18&"="&$B18,Results_30d_Deltas!$A$2:$H$5000,5,FALSE),"") | G18: =IFERROR(VLOOKUP($A18,Results_30d_Deltas!$A$2:$H$5000,7,FALSE)-E17,"") | H18: =IFERROR(VLOOKUP($A18,Results_30d_Deltas!$A$2:$H$5000,6,FALSE),"") | K18: =IF(B18=C18,"YES","NO") | IJ18: ez_manage.py:4039 top() | IK18: v12_quick_engine.py:3275 x6
A19: STDEV_BREAKOUT_ENABLED | B19: True | E19: =IF(F19="",E18,IF(F19>0,E18+F19,E18)) | F19: -2.6134663 | G19: =IFERROR(VLOOKUP($A19,Results_30d_Deltas!$A$2:$H$5000,7,FALSE)-E18,"") | H19: =IFERROR(VLOOKUP($A19,Results_30d_Deltas!$A$2:$H$5000,6,FALSE),"") | K19: =IF(B19=C19,"YES","NO") | IJ19: ez_manage.py:4039 top() | IK19: v12_quick_engine.py:3275 x6
A20: BTC_BREAKOUT_ENTRY_ENABLED | B20: False | E20: =IF(F20="",E19,IF(F20>0,E19+F20,E19)) | F20: =IFERROR(VLOOKUP($A20&"="&$B20,Results_30d_Deltas!$A$2:$H$5000,5,FALSE),"") | G20: =IFERROR(VLOOKUP($A20,Results_30d_Deltas!$A$2:$H$5000,7,FALSE)-E19,"") | H20: =IFERROR(VLOOKUP($A20,Results_30d_Deltas!$A$2:$H$5000,6,FALSE),"") | K20: =IF(B20=C20,"YES","NO") | IJ20: ez_manage.py:4432 top() | IK20: v12_quick_engine.py:393 x8
A21: BTC_BREAKOUT_ENTRY_ENABLED | B21: True | E21: =IF(F21="",E20,IF(F21>0,E20+F21,E20)) | F21: -2.6134663 | G21: =IFERROR(VLOOKUP($A21,Results_30d_Deltas!$A$2:$H$5000,7,FALSE)-E20,"") | H21: =IFERROR(VLOOKUP($A21,Results_30d_Deltas!$A$2:$H$5000,6,FALSE),"") | K21: =IF(B21=C21,"YES","NO") | IJ21: ez_manage.py:4432 top() | IK21: v12_quick_engine.py:393 x8
A22: RZ_BREAKOUT_ENTRY_ENABLED | B22: False | E22: =IF(F22="",E21,IF(F22>0,E21+F22,E21)) | F22: =IFERROR(VLOOKUP($A22&"="&$B22,Results_30d_Deltas!$A$2:$H$5000,5,FALSE),"") | G22: =IFERROR(VLOOKUP($A22,Results_30d_Deltas!$A$2:$H$5000,7,FALSE)-E21,"") | H22: =IFERROR(VLOOKUP($A22,Results_30d_Deltas!$A$2:$H$5000,6,FALSE),"") | K22: =IF(B22=C22,"YES","NO") | IJ22: ez_manage.py:5398 top() | IK22: v12_quick_engine.py:3021 x3
A23: RZ_BREAKOUT_ENTRY_ENABLED | B23: True | E23: =IF(F23="",E22,IF(F23>0,E22+F23,E22)) | F23: -2.6134663 | G23: =IFERROR(VLOOKUP($A23,Results_30d_Deltas!$A$2:$H$5000,7,FALSE)-E22,"") | H23: =IFERROR(VLOOKUP($A23,Results_30d_Deltas!$A$2:$H$5000,6,FALSE),"") | K23: =IF(B23=C23,"YES","NO") | IJ23: ez_manage.py:5398 top() | IK23: v12_quick_engine.py:3021 x3
A24: ATR_ADAPTIVE_SIZING_TARGET_PCT | B24: 1.0 | E24: =IF(F24="",E23,IF(F24>0,E23+F24,E23)) | F24: -2.6134663 | G24: =IFERROR(VLOOKUP($A24,Results_30d_Deltas!$A$2:$H$5000,7,FALSE)-E23,"") | H24: =IFERROR(VLOOKUP($A24,Results_30d_Deltas!$A$2:$H$5000,6,FALSE),"") | K24: =IF(B24=C24,"YES","NO") | IJ24: ez_manage.py:4327 top() | IK24: v12_quick_engine.py:1209 x7
A25: ATR_ADAPTIVE_SIZING_TARGET_PCT | B25: 1.5 | E25: =IF(F25="",E24,IF(F25>0,E24+F25,E24)) | F25: -2.6134663 | G25: =IFERROR(VLOOKUP($A25,Results_30d_Deltas!$A$2:$H$5000,7,FALSE)-E24,"") | H25: =IFERROR(VLOOKUP($A25,Results_30d_Deltas!$A$2:$H$5000,6,FALSE),"") | K25: =IF(B25=C25,"YES","NO") | IJ25: ez_manage.py:4327 top() | IK25: v12_quick_engine.py:1209 x7
A26: ATR_ADAPTIVE_SIZING_TARGET_PCT | B26: 2.0 | E26: =IF(F26="",E25,IF(F26>0,E25+F26,E25)) | F26: -2.6134663 | G26: =IFERROR(VLOOKUP($A26,Results_30d_Deltas!$A$2:$H$5000,7,FALSE)-E25,"") | H26: =IFERROR(VLOOKUP($A26,Results_30d_Deltas!$A$2:$H$5000,6,FALSE),"") | K26: =IF(B26=C26,"YES","NO") | IJ26: ez_manage.py:4327 top() | IK26: v12_quick_engine.py:1209 x7
A27: ATR_ADAPTIVE_SIZING_TARGET_PCT | B27: 2.5 | E27: =IF(F27="",E26,IF(F27>0,E26+F27,E26)) | F27: -2.6134663 | G27: =IFERROR(VLOOKUP($A27,Results_30d_Deltas!$A$2:$H$5000,7,FALSE)-E26,"") | H27: =IFERROR(VLOOKUP($A27,Results_30d_Deltas!$A$2:$H$5000,6,FALSE),"") | K27: =IF(B27=C27,"YES","NO") | IJ27: ez_manage.py:4327 top() | IK27: v12_quick_engine.py:1209 x7
A28: ATR_ADAPTIVE_SIZING_TARGET_PCT | B28: 3.0 | E28: =IF(F28="",E27,IF(F28>0,E27+F28,E27)) | F28: -2.6134663 | G28: =IFERROR(VLOOKUP($A28,Results_30d_Deltas!$A$2:$H$5000,7,FALSE)-E27,"") | H28: =IFERROR(VLOOKUP($A28,Results_30d_Deltas!$A$2:$H$5000,6,FALSE),"") | K28: =IF(B28=C28,"YES","NO") | IJ28: ez_manage.py:4327 top() | IK28: v12_quick_engine.py:1209 x7
A29: ATR_ADAPTIVE_STOP_MULT | B29: 1.0 | E29: =IF(F29="",E28,IF(F29>0,E28+F29,E28)) | F29: -2.6134663 | G29: =IFERROR(VLOOKUP($A29,Results_30d_Deltas!$A$2:$H$5000,7,FALSE)-E28,"") | H29: =IFERROR(VLOOKUP($A29,Results_30d_Deltas!$A$2:$H$5000,6,FALSE),"") | K29: =IF(B29=C29,"YES","NO") | IJ29: ez_manage.py:4329 top() | IK29: v12_quick_engine.py:1211 x6
A30: ATR_ADAPTIVE_STOP_MULT | B30: 1.5 | E30: =IF(F30="",E29,IF(F30>0,E29+F30,E29)) | F30: -2.6134663 | G30: =IFERROR(VLOOKUP($A30,Results_30d_Deltas!$A$2:$H$5000,7,FALSE)-E29,"") | H30: =IFERROR(VLOOKUP($A30,Results_30d_Deltas!$A$2:$H$5000,6,FALSE),"") | K30: =IF(B30=C30,"YES","NO") | IJ30: ez_manage.py:4329 top() | IK30: v12_quick_engine.py:1211 x6
A31: ATR_ADAPTIVE_STOP_MULT | B31: 2.0 | E31: =IF(F31="",E30,IF(F31>0,E30+F31,E30)) | F31: -2.6134663 | G31: =IFERROR(VLOOKUP($A31,Results_30d_Deltas!$A$2:$H$5000,7,FALSE)-E30,"") | H31: =IFERROR(VLOOKUP($A31,Results_30d_Deltas!$A$2:$H$5000,6,FALSE),"") | K31: =IF(B31=C31,"YES","NO") | IJ31: ez_manage.py:4329 top() | IK31: v12_quick_engine.py:1211 x6
A32: ATR_ADAPTIVE_STOP_MULT | B32: 2.5 | E32: =IF(F32="",E31,IF(F32>0,E31+F32,E31)) | F32: -2.6134663 | G32: =IFERROR(VLOOKUP($A32,Results_30d_Deltas!$A$2:$H$5000,7,FALSE)-E31,"") | H32: =IFERROR(VLOOKUP($A32,Results_30d_Deltas!$A$2:$H$5000,6,FALSE),"") | K32: =IF(B32=C32,"YES","NO") | IJ32: ez_manage.py:4329 top() | IK32: v12_quick_engine.py:1211 x6
A33: ATR_ADAPTIVE_STOP_MULT | B33: 3.0 | E33: =IF(F33="",E32,IF(F33>0,E32+F33,E32)) | F33: -2.6134663 | G33: =IFERROR(VLOOKUP($A33,Results_30d_Deltas!$A$2:$H$5000,7,FALSE)-E32,"") | H33: =IFERROR(VLOOKUP($A33,Results_30d_Deltas!$A$2:$H$5000,6,FALSE),"") | K33: =IF(B33=C33,"YES","NO") | IJ33: ez_manage.py:4329 top() | IK33: v12_quick_engine.py:1211 x6
A34: ATR_LONG_WINDOW | B34: 50 | E34: =IF(F34="",E33,IF(F34>0,E33+F34,E33)) | F34: -2.6134663 | G34: =IFERROR(VLOOKUP($A34,Results_30d_Deltas!$A$2:$H$5000,7,FALSE)-E33,"") | H34: =IFERROR(VLOOKUP($A34,Results_30d_Deltas!$A$2:$H$5000,6,FALSE),"") | K34: =IF(B34=C34,"YES","NO") | IJ34: ez_manage.py:4330 top() | IK34: v12_quick_engine.py:199 x5
... A48: ENTRY_PRIMARY_TF | B48: D | E48: =IF(F48="",E47,IF(F48>0,E47+F48,E47)) | F48: -2.6134663 | G48: =IFERROR(VLOOKUP($A48,Results_30d_Deltas!$A$2:$H$5000,7,FALSE)-E47,"") | H48: =IFERROR(VLOOKUP($A48,Results_30d_Deltas!$A$2:$H$5000,6,FALSE),"") | K48: =IF(B48=C48,"YES","NO") | IJ48: ez_manage.py:3216 top() | IK48: v12_quick_engine.py:1728 x4
A49: ENTRY_PRIMARY_TF | B49: 4h | E49: =IF(F49="",E48,IF(F49>0,E48+F49,E48)) | F49: =IFERROR(VLOOKUP($A49&"="&$B49,Results_30d_Deltas!$A$2:$H$5000,5,FALSE),"") | G49: =IFERROR(VLOOKUP($A49,Results_30d_Deltas!$A$2:$H$5000,7,FALSE)-E48,"") | H49: =IFERROR(VLOOKUP($A49,Results_30d_Deltas!$A$2:$H$5000,6,FALSE),"") | K49: =IF(B49=C49,"YES","NO") | IJ49: ez_manage.py:3216 top() | IK49: v12_quick_engine.py:1728 x4
A50: ENTRY_PRIMARY_TF | B50: 1h | E50: =IF(F50="",E49,IF(F50>0,E49+F50,E49)) | F50: -2.6134663 | G50: =IFERROR(VLOOKUP($A50,Results_30d_Deltas!$A$2:$H$5000,7,FALSE)-E49,"") | H50: =IFERROR(VLOOKUP($A50,Results_30d_Deltas!$A$2:$H$5000,6,FALSE),"") | K50: =IF(B50=C50,"YES","NO") | IJ50: ez_manage.py:3216 top() | IK50: v12_quick_engine.py:1728 x4
A51: ENTRY_PRIMARY_TF | B51: 15m | E51: =IF(F51="",E50,IF(F51>0,E50+F51,E50)) | F51: -2.6134663 | G51: =IFERROR(VLOOKUP($A51,Results_30d_Deltas!$A$2:$H$5000,7,FALSE)-E50,"") | H51: =IFERROR(VLOOKUP($A51,Results_30d_Deltas!$A$2:$H$5000,6,FALSE),"") | K51: =IF(B51=C51,"YES","NO") | IJ51: ez_manage.py:3216 top() | IK51: v12_quick_engine.py:1728 x4
A52: ENTRY_SCORE_THRESHOLD | B52: 9.0 | E52: =IF(F52="",E51,IF(F52>0,E51+F52,E51)) | F52: -2.6134663 | G52: =IFERROR(VLOOKUP($A52,Results_30d_Deltas!$A$2:$H$5000,7,FALSE)-E51,"") | H52: =IFERROR(VLOOKUP($A52,Results_30d_Deltas!$A$2:$H$5000,6,FALSE),"") | K52: =IF(B52=C52,"YES","NO") | IJ52: ez_manage.py:4644 top() | IK52: v12_quick_engine.py:3394 x9
A53: ENTRY_SCORE_THRESHOLD | B53: 13.5 | E53: =IF(F53="",E52,IF(F53>0,E52+F53,E52)) | F53: -2.6134663 | G53: =IFERROR(VLOOKUP($A53,Results_30d_Deltas!$A$2:$H$5000,7,FALSE)-E52,"") | H53: =IFERROR(VLOOKUP($A53,Results_30d_Deltas!$A$2:$H$5000,6,FALSE),"") | K53: =IF(B53=C53,"YES","NO") | IJ53: ez_manage.py:4644 top() | IK53: v12_quick_engine.py:3394 x9
A54: ENTRY_SCORE_THRESHOLD | B54: 18.0 | E54: =IF(F54="",E53,IF(F54>0,E53+F54,E53)) | F54: -2.6134663 | G54: =IFERROR(VLOOKUP($A54,Results_30d_Deltas!$A$2:$H$5000,7,FALSE)-E53,"") | H54: =IFERROR(VLOOKUP($A54,Results_30d_Deltas!$A$2:$H$5000,6,FALSE),"") | K54: =IF(B54=C54,"YES","NO") | IJ54: ez_manage.py:4644 top() | IK54: v12_quick_engine.py:3394 x9
A55: ENTRY_SCORE_THRESHOLD | B55: 22.5 | E55: =IF(F55="",E54,IF(F55>0,E54+F55,E54)) | F55: -2.6134663 | G55: =IFERROR(VLOOKUP($A55,Results_30d_Deltas!$A$2:$H$5000,7,FALSE)-E54,"") | H55: =IFERROR(VLOOKUP($A55,Results_30d_Deltas!$A$2:$H$5000,6,FALSE),"") | K55: =IF(B55=C55,"YES","NO") | IJ55: ez_manage.py:4644 top() | IK55: v12_quick_engine.py:3394 x9
A56: ENTRY_SCORE_THRESHOLD | B56: 27.0 | E56: =IF(F56="",E55,IF(F56>0,E55+F56,E55)) | F56: -2.6134663 | G56: =IFERROR(VLOOKUP($A56,Results_30d_Deltas!$A$2:$H$5000,7,FALSE)-E55,"") | H56: =IFERROR(VLOOKUP($A56,Results_30d_Deltas!$A$2:$H$5000,6,FALSE),"") | K56: =IF(B56=C56,"YES","NO") | IJ56: ez_manage.py:4644 top() | IK56: v12_quick_engine.py:3394 x9
A57: EXIT_SCORER_DC_EXTREME | B57: 0.2 | E57: =IF(F57="",E56,IF(F57>0,E56+F57,E56)) | F57: -2.6134663 | G57: =IFERROR(VLOOKUP($A57,Results_30d_Deltas!$A$2:$H$5000,7,FALSE)-E56,"") | H57: =IFERROR(VLOOKUP($A57,Results_30d_Deltas!$A$2:$H$5000,6,FALSE),"") | K57: =IF(B57=C57,"YES","NO") | IJ57: ez_manage.py:3252 top() | IK57: v12_quick_engine.py:1781 x6
A58: EXIT_SCORER_DC_EXTREME | B58: 0.3 | E58: =IF(F58="",E57,IF(F58>0,E57+F58,E57)) | F58: -2.6134663 | G58: =IFERROR(VLOOKUP($A58,Results_30d_Deltas!$A$2:$H$5000,7,FALSE)-E57,"") | H58: =IFERROR(VLOOKUP($A58,Results_30d_Deltas!$A$2:$H$5000,6,FALSE),"") | K58: =IF(B58=C58,"YES","NO") | IJ58: ez_manage.py:3252 top() | IK58: v12_quick_engine.py:1781 x6
A59: EXIT_SCORER_DC_EXTREME | B59: 0.4 | E59: =IF(F59="",E58,IF(F59>0,E58+F59,E58)) | F59: -2.6134663 | G59: =IFERROR(VLOOKUP($A59,Results_30d_Deltas!$A$2:$H$5000,7,FALSE)-E58,"") | H59: =IFERROR(VLOOKUP($A59,Results_30d_Deltas!$A$2:$H$5000,6,FALSE),"") | K59: =IF(B59=C59,"YES","NO") | IJ59: ez_manage.py:3252 top() | IK59: v12_quick_engine.py:1781 x6
A60: EXIT_SCORER_DC_EXTREME | B60: 0.5 | E60: =IF(F60="",E59,IF(F60>0,E59+F60,E59)) | F60: -2.6134663 | G60: =IFERROR(VLOOKUP($A60,Results_30d_Deltas!$A$2:$H$5000,7,FALSE)-E59,"") | H60: =IFERROR(VLOOKUP($A60,Results_30d_Deltas!$A$2:$H$5000,6,FALSE),"") | K60: =IF(B60=C60,"YES","NO") | IJ60: ez_manage.py:3252 top() | IK60: v12_quick_engine.py:1781 x6
A61: EXIT_SCORER_DC_EXTREME | B61: 0.6 | E61: =IF(F61="",E60,IF(F61>0,E60+F61,E60)) | F61: -2.6134663 | G61: =IFERROR(VLOOKUP($A61,Results_30d_Deltas!$A$2:$H$5000,7,FALSE)-E60,"") | H61: =IFERROR(VLOOKUP($A61,Results_30d_Deltas!$A$2:$H$5000,6,FALSE),"") | K61: =IF(B61=C61,"YES","NO") | IJ61: ez_manage.py:3252 top() | IK61: v12_quick_engine.py:1781 x6
A62: E_1_EXIT_DELTA_THR | B62: 0 | E62: =IF(F62="",E61,IF(F62>0,E61+F62,E61)) | F62: -2.6134663 | G62: =IFERROR(VLOOKUP($A62,Results_30d_Deltas!$A$2:$H$5000,7,FALSE)-E61,"") | H62: =IFERROR(VLOOKUP($A62,Results_30d_Deltas!$A$2:$H$5000,6,FALSE),"") | K62: =IF(B62=C62,"YES","NO") | IJ62: ez_manage.py:4698 top() | IK62: v12_quick_engine.py:1817 x9
A63: E_1_EXIT_DELTA_THR | B63: 0.5 | E63: =IF(F63="",E62,IF(F63>0,E62+F63,E62)) | F63: =IFERROR(VLOOKUP($A63&"="&$B63,Results_30d_Deltas!$A$2:$H$5000,5,FALSE),"") | G63: =IFERROR(VLOOKUP($A63,Results_30d_Deltas!$A$2:$H$5000,7,FALSE)-E62,"") | H63: =IFERROR(VLOOKUP($A63,Results_30d_Deltas!$A$2:$H$5000,6,FALSE),"") | K63: =IF(B63=C63,"YES","NO") | IJ63: ez_manage.py:4698 top() | IK63: v12_quick_engine.py:1817 x9
A64: E_1_EXIT_DELTA_THR | B64: 1.0 | E64: =IF(F64="",E63,IF(F64>0,E63+F64,E63)) | F64: -2.6134663 | G64: =IFERROR(VLOOKUP($A64,Results_30d_Deltas!$A$2:$H$5000,7,FALSE)-E63,"") | H64: =IFERROR(VLOOKUP($A64,Results_30d_Deltas!$A$2:$H$5000,6,FALSE),"") | K64: =IF(B64=C64,"YES","NO") | IJ64: ez_manage.py:4698 top() | IK64: v12_quick_engine.py:1817 x9
A65: E_1_EXIT_DELTA_THR | B65: 2.0 | E65: =IF(F65="",E64,IF(F65>0,E64+F65,E64)) | F65: -2.6134663 | G65: =IFERROR(VLOOKUP($A65,Results_30d_Deltas!$A$2:$H$5000,7,FALSE)-E64,"") | H65: =IFERROR(VLOOKUP($A65,Results_30d_Deltas!$A$2:$H$5000,6,FALSE),"") | K65: =IF(B65=C65,"YES","NO") | IJ65: ez_manage.py:4698 top() | IK65: v12_quick_engine.py:1817 x9
A66: HAIKU_ENTRY_GATE_ENABLED | B66: False | E66: =IF(F66="",E65,IF(F66>0,E65+F66,E65)) | F66: =IFERROR(VLOOKUP($A66&"="&$B66,Results_30d_Deltas!$A$2:$H$5000,5,FALSE),"") | G66: =IFERROR(VLOOKUP($A66,Results_30d_Deltas!$A$2:$H$5000,7,FALSE)-E65,"") | H66: =IFERROR(VLOOKUP($A66,Results_30d_Deltas!$A$2:$H$5000,6,FALSE),"") | K66: =IF(B66=C66,"YES","NO") | IJ66: ez_manage.py:6007 top() | IK66: v12_quick_engine.py:4265 x2
A67: HAIKU_ENTRY_GATE_ENABLED | B67: True | E67: =IF(F67="",E66,IF(F67>0,E66+F67,E66)) | F67: -2.6134663 | G67: =IFERROR(VLOOKUP($A67,Results_30d_Deltas!$A$2:$H$5000,7,FALSE)-E66,"") | H67: =IFERROR(VLOOKUP($A67,Results_30d_Deltas!$A$2:$H$5000,6,FALSE),"") | K67: =IF(B67=C67,"YES","NO") | IJ67: ez_manage.py:6007 top() | IK67: v12_quick_engine.py:4265 x2
A68: HTF_GATE_SIGNALS_SMA200D | B68: False | E68: =IF(F68="",E67,IF(F68>0,E67+F68,E67)) | F68: -2.6134663 | G68: =IFERROR(VLOOKUP($A68,Results_30d_Deltas!$A$2:$H$5000,7,FALSE)-E67,"") | H68: =IFERROR(VLOOKUP($A68,Results_30d_Deltas!$A$2:$H$5000,6,FALSE),"") | K68: =IF(B68=C68,"YES","NO") | IJ68: ez_manage.py:4881 top() | IK68: v12_quick_engine.py:2057 x7
A69: HTF_GATE_SIGNALS_SMA200D | B69: True | E69: =IF(F69="",E68,IF(F69>0,E68+F69,E68)) | F69: =IFERROR(VLOOKUP($A69&"="&$B69,Results_30d_Deltas!$A$2:$H$5000,5,FALSE),"") | G69: =IFERROR(VLOOKUP($A69,Results_30d_Deltas!$A$2:$H$5000,7,FALSE)-E68,"") | H69: =IFERROR(VLOOKUP($A69,Results_30d_Deltas!$A$2:$H$5000,6,FALSE),"") | K69: =IF(B69=C69,"YES","NO") | IJ69: ez_manage.py:4881 top() | IK69: v12_quick_engine.py:2057 x7
A70: INTRADAY_SESSION_FORCE_EXIT_UTC | B70: 0 | E70: =IF(F70="",E69,IF(F70>0,E69+F70,E69)) | F70: =IFERROR(VLOOKUP($A70&"="&$B70,Results_30d_Deltas!$A$2:$H$5000,5,FALSE),"") | G70: =IFERROR(VLOOKUP($A70,Results_30d_Deltas!$A$2:$H$5000,7,FALSE)-E69,"") | H70: =IFERROR(VLOOKUP($A70,Results_30d_Deltas!$A$2:$H$5000,6,FALSE),"") | K70: =IF(B70=C70,"YES","NO") | IJ70: ez_manage.py:6014 top() | IK70: v12_quick_engine.py:4267 x4
A71: INTRADAY_SESSION_FORCE_EXIT_UTC | B71: 0.5 | E71: =IF(F71="",E70,IF(F71>0,E70+F71,E70)) | F71: =IFERROR(VLOOKUP($A71&"="&$B71,Results_30d_Deltas!$A$2:$H$5000,5,FALSE),"") | G71: =IFERROR(VLOOKUP($A71,Results_30d_Deltas!$A$2:$H$5000,7,FALSE)-E70,"") | H71: =IFERROR(VLOOKUP($A71,Results_30d_Deltas!$A$2:$H$5000,6,FALSE),"") | K71: =IF(B71=C71,"YES","NO") | IJ71: ez_manage.py:6014 top() | IK71: v12_quick_engine.py:4267 x4
A72: INTRADAY_SESSION_FORCE_EXIT_UTC | B72: 1.0 | E72: =IF(F72="",E71,IF(F72>0,E71+F72,E71)) | F72: =IFERROR(VLOOKUP($A72&"="&$B72,Results_30d_Deltas!$A$2:$H$5000,5,FALSE),"") | G72: =IFERROR(VLOOKUP($A72,Results_30d_Deltas!$A$2:$H$5000,7,FALSE)-E71,"") | H72: =IFERROR(VLOOKUP($A72,Results_30d_Deltas!$A$2:$H$5000,6,FALSE),"") | K72: =IF(B72=C72,"YES","NO") | IJ72: ez_manage.py:6014 top() | IK72: v12_quick_engine.py:4267 x4
A73: INTRADAY_SESSION_FORCE_EXIT_UTC | B73: 2.0 | E73: =IF(F73="",E72,IF(F73>0,E72+F73,E72)) | F73: =IFERROR(VLOOKUP($A73&"="&$B73,Results_30d_Deltas!$A$2:$H$5000,5,FALSE),"") | G73: =IFERROR(VLOOKUP($A73,Results_30d_Deltas!$A$2:$H$5000,7,FALSE)-E72,"") | H73: =IFERROR(VLOOKUP($A73,Results_30d_Deltas!$A$2:$H$5000,6,FALSE),"") | K73: =IF(B73=C73,"YES","NO") | IJ73: ez_manage.py:6014 top() | IK73: v12_quick_engine.py:4267 x4
A74: MACD_ZERO_CROSS_ENABLED | B74: False | E74: =IF(F74="",E73,IF(F74>0,E73+F74,E73)) | F74: =IFERROR(VLOOKUP($A74&"="&$B74,Results_30d_Deltas!$A$2:$H$5000,5,FALSE),"") | G74: =IFERROR(VLOOKUP($A74,Results_30d_Deltas!$A$2:$H$5000,7,FALSE)-E73,"") | H74: =IFERROR(VLOOKUP($A74,Results_30d_Deltas!$A$2:$H$5000,6,FALSE),"") | K74: =IF(B74=C74,"YES","NO") | IJ74: ez_manage.py:3499 top() | IK74: v12_quick_engine.py:2234 x2
A75: MACD_ZERO_CROSS_ENABLED | B75: True | E75: =IF(F75="",E74,IF(F75>0,E74+F75,E74)) | F75: =IFERROR(VLOOKUP($A75&"="&$B75,Results_30d_Deltas!$A$2:$H$5000,5,FALSE),"") | G75: =IFERROR(VLOOKUP($A75,Results_30d_Deltas!$A$2:$H$5000,7,FALSE)-E74,"") | H75: =IFERROR(VLOOKUP($A75,Results_30d_Deltas!$A$2:$H$5000,6,FALSE),"") | K75: =IF(B75=C75,"YES","NO") | IJ75: ez_manage.py:3499 top() | IK75: v12_quick_engine.py:2234 x2
A76: MACD_ZERO_CROSS_SCORE | B76: 8 | E76: =IF(F76="",E75,IF(F76>0,E75+F76,E75)) | F76: =IFERROR(VLOOKUP($A76&"="&$B76,Results_30d_Deltas!$A$2:$H$5000,5,FALSE),"") | G76: =IFERROR(VLOOKUP($A76,Results_30d_Deltas!$A$2:$H$5000,7,FALSE)-E75,"") | H76: =IFERROR(VLOOKUP($A76,Results_30d_Deltas!$A$2:$H$5000,6,FALSE),"") | K76: =IF(B76=C76,"YES","NO") | IJ76: ez_manage.py:3500 top() | IK76: v12_quick_engine.py:2235 x2
A77: MACD_ZERO_CROSS_SCORE | B77: 11 | E77: =IF(F77="",E76,IF(F77>0,E76+F77,E76)) | F77: =IFERROR(VLOOKUP($A77&"="&$B77,Results_30d_Deltas!$A$2:$H$5000,5,FALSE),"") | G77: =IFERROR(VLOOKUP($A77,Results_30d_Deltas!$A$2:$H$5000,7,FALSE)-E76,"") | H77: =IFERROR(VLOOKUP($A77,Results_30d_Deltas!$A$2:$H$5000,6,FALSE),"") | K77: =IF(B77=C77,"YES","NO") | IJ77: ez_manage.py:3500 top() | IK77: v12_quick_engine.py:2235 x2
A78: MACD_ZERO_CROSS_SCORE | B78: 15 | E78: =IF(F78="",E77,IF(F78>0,E77+F78,E77)) | F78: =IFERROR(VLOOKUP($A78&"="&$B78,Results_30d_Deltas!$A$2:$H$5000,5,FALSE),"") | G78: =IFERROR(VLOOKUP($A78,Results_30d_Deltas!$A$2:$H$5000,7,FALSE)-E77,"") | H78: =IFERROR(VLOOKUP($A78,Results_30d_Deltas!$A$2:$H$5000,6,FALSE),"") | K78: =IF(B78=C78,"YES","NO") | IJ78: ez_manage.py:3500 top() | IK78: v12_quick_engine.py:2235 x2
A79: MACD_ZERO_CROSS_SCORE | B79: 19 | E79: =IF(F79="",E78,IF(F79>0,E78+F79,E78)) | F79: =IFERROR(VLOOKUP($A79&"="&$B79,Results_30d_Deltas!$A$2:$H$5000,5,FALSE),"") | G79: =IFERROR(VLOOKUP($A79,Results_30d_Deltas!$A$2:$H$5000,7,FALSE)-E78,"") | H79: =IFERROR(VLOOKUP($A79,Results_30d_Deltas!$A$2:$H$5000,6,FALSE),"") | K79: =IF(B79=C79,"YES","NO") | IJ79: ez_manage.py:3500 top() | IK79: v12_quick_engine.py:2235 x2
A80: MACD_ZERO_CROSS_SCORE | B80: 22 | E80: =IF(F80="",E79,IF(F80>0,E79+F80,E79)) | F80: =IFERROR(VLOOKUP($A80&"="&$B80,Results_30d_Deltas!$A$2:$H$5000,5,FALSE),"") | G80: =IFERROR(VLOOKUP($A80,Results_30d_Deltas!$A$2:$H$5000,7,FALSE)-E79,"") | H80: =IFERROR(VLOOKUP($A80,Results_30d_Deltas!$A$2:$H$5000,6,FALSE),"") | K80: =IF(B80=C80,"YES","NO") | IJ80: ez_manage.py:3500 top() | IK80: v12_quick_engine.py:2235 x2
... A212: WT_DIV_ENTRY_GATE_ENABLED | B212: True | E212: =IF(F212="",E211,IF(F212>0,E211+F212,E211)) | F212: =IFERROR(VLOOKUP($A212&"="&$B212,Results_30d_Deltas!$A$2:$H$5000,5,FALSE),"") | G212: =IFERROR(VLOOKUP($A212,Results_30d_Deltas!$A$2:$H$5000,7,FALSE)-E211,"") | H212: =IFERROR(VLOOKUP($A212,Results_30d_Deltas!$A$2:$H$5000,6,FALSE),"") | K212: =IF(B212=C212,"YES","NO") | IJ212: ez_manage.py:5913 top() | IK212: v12_quick_engine.py:3743 x2

Sheet ENTRY_CONFIRMATION_GATES
A1: 03 ENTRY_CONFIRMATION_GATES - 4 bases -> 11 rows - 231 per-row FULLY CONNECTED
A2: Switch | B2: default | C2: override | D2: Family | E2: =MAX('ENTRY_BREAKOUT_CHANNEL'!E$2:E$5000) | F2: VECTOR_DELTA | G2: LIVE_DELTA | H2: LIVE_SHARPE | I2: REAL_COMPLETE | J2: PER_ROW_FILTERS | K2: is_default (backup if bold lost) | L2: ATR_TRAIL_FILTER_TF=OFF | M2: ATR_TRAIL_FILTER_TF=D | N2: ATR_TRAIL_FILTER_TF=4h | O2: ATR_TRAIL_FILTER_TF=1h | P2: ATR_TRAIL_FILTER_TF=15m | Q2: BAR_PATTERNS_FILTER_TF=OFF | R2: BAR_PATTERNS_FILTER_TF=D | S2: BAR_PATTERNS_FILTER_TF=4h | T2: BAR_PATTERNS_FILTER_TF=1h | U2: BAR_PATTERNS_FILTER_TF=15m | V2: BB_PULLBACK_GATE_FILTER_TF=OFF | W2: BB_PULLBACK_GATE_FILTER_TF=D | X2: BB_PULLBACK_GATE_FILTER_TF=4h | Y2: BB_PULLBACK_GATE_FILTER_TF=1h | Z2: BB_PULLBACK_GATE_FILTER_TF=15m | AA2: BB_RECOVERY_ENTRY_FILTER_TF=OFF | AB2: BB_RECOVERY_ENTRY_FILTER_TF=D | AC2: BB_RECOVERY_ENTRY_FILTER_TF=4h | AD2: BB_RECOVERY_ENTRY_FILTER_TF=1h | AE2: BB_RECOVERY_ENTRY_FILTER_TF=15m | AF2: BB_RECOVERY_FILTER_TF=OFF | AG2: BB_RECOVERY_FILTER_TF=D | AH2: BB_RECOVERY_FILTER_TF=4h | AI2: BB_RECOVERY_FILTER_TF=1h | AJ2: BB_RECOVERY_FILTER_TF=15m | AK2: BREAKEVEN_GAIN_EROSION_FILTER_TF=OFF | AL2: BREAKEVEN_GAIN_EROSION_FILTER_TF=D | AM2: BREAKEVEN_GAIN_EROSION_FILTER_TF=4h | AN2: BREAKEVEN_GAIN_EROSION_FILTER_TF=1h | AO2: BREAKEVEN_GAIN_EROSION_FILTER_TF=15m | AP2: BREAKOUT_RETEST_FILTER_TF=OFF | AQ2: BREAKOUT_RETEST_FILTER_TF=D | AR2: BREAKOUT_RETEST_FILTER_TF=4h | AS2: BREAKOUT_RETEST_FILTER_TF=1h | AT2: BREAKOUT_RETEST_FILTER_TF=15m | AU2: BT_WT_CROSS_LADDER_FILTER_TF=OFF | AV2: BT_WT_CROSS_LADDER_FILTER_TF=D | AW2: BT_WT_CROSS_LADDER_FILTER_TF=4h | AX2: BT_WT_CROSS_LADDER_FILTER_TF=1h | AY2: BT_WT_CROSS_LADDER_FILTER_TF=15m | AZ2: CANDLE_PATTERN_STOPS_FILTER_TF=OFF | BA2: CANDLE_PATTERN_STOPS_FILTER_TF=D | BB2: CANDLE_PATTERN_STOPS_FILTER_TF=4h | BC2: CANDLE_PATTERN_STOPS_FILTER_TF=1h | BD2: CANDLE_PATTERN_STOPS_FILTER_TF=15m | BE2: CIRCUIT_SHARPE_GATES_FILTER_TF=OFF | BF2: CIRCUIT_SHARPE_GATES_FILTER_TF=D | BG2: CIRCUIT_SHARPE_GATES_FILTER_TF=4h | BH2: CIRCUIT_SHARPE_GATES_FILTER_TF=1h | BI2: CIRCUIT_SHARPE_GATES_FILTER_TF=15m | BJ2: DC_BREACH_REDUCE_FILTER_TF=OFF | BK2: DC_BREACH_REDUCE_FILTER_TF=D | BL2: DC_BREACH_REDUCE_FILTER_TF=4h | BM2: DC_BREACH_REDUCE_FILTER_TF=1h | BN2: DC_BREACH_REDUCE_FILTER_TF=15m | BO2: DC_BREAK_FILTER_TF=OFF | BP2: DC_BREAK_FILTER_TF=D | BQ2: DC_BREAK_FILTER_TF=4h | BR2: DC_BREAK_FILTER_TF=1h | BS2: DC_BREAK_FILTER_TF=15m | BT2: DC_MOMENTUM_BOTA_SCORER_FILTER_TF=OFF | BU2: DC_MOMENTUM_BOTA_SCORER_FILTER_TF=D | BV2: DC_MOMENTUM_BOTA_SCORER_FILTER_TF=4h | BW2: DC_MOMENTUM_BOTA_SCORER_FILTER_TF=1h | BX2: DC_MOMENTUM_BOTA_SCORER_FILTER_TF=15m | BY2: DELTA_ENGINE_FILTER_TF=OFF | BZ2: DELTA_ENGINE_FILTER_TF=D | CA2: DELTA_ENGINE_FILTER_TF=4h | CB2: DELTA_ENGINE_FILTER_TF=1h | CC2: DELTA_ENGINE_FILTER_TF=15m | CD2: EMA_9_21_FILTER_FILTER_TF=OFF | CE2: EMA_9_21_FILTER_FILTER_TF=D | CF2: EMA_9_21_FILTER_FILTER_TF=4h | CG2: EMA_9_21_FILTER_FILTER_TF=1h | CH2: EMA_9_21_FILTER_FILTER_TF=15m | CI2: EMA_BLANKET_FILTER_FILTER_TF=OFF | CJ2: EMA_BLANKET_FILTER_FILTER_TF=D | CK2: EMA_BLANKET_FILTER_FILTER_TF=4h | CL2: EMA_BLANKET_FILTER_FILTER_TF=1h | CM2: EMA_BLANKET_FILTER_FILTER_TF=15m | CN2: EMERGENCY_BRAKE_FILTER_TF=OFF | CO2: EMERGENCY_BRAKE_FILTER_TF=D | CP2: EMERGENCY_BRAKE_FILTER_TF=4h | CQ2: EMERGENCY_BRAKE_FILTER_TF=1h | CR2: EMERGENCY_BRAKE_FILTER_TF=15m | CS2: EXIT_R1_R2_FILTER_TF=OFF | CT2: EXIT_R1_R2_FILTER_TF=D | CU2: EXIT_R1_R2_FILTER_TF=4h | CV2: EXIT_R1_R2_FILTER_TF=1h | CW2: EXIT_R1_R2_FILTER_TF=15m | CX2: EXIT_TIGHT_BREAKOUT_SCORER_FILTER_TF=OFF | CY2: EXIT_TIGHT_BREAKOUT_SCORER_FILTER_TF=D | CZ2: EXIT_TIGHT_BREAKOUT_SCORER_FILTER_TF=4h | DA2: EXIT_TIGHT_BREAKOUT_SCORER_FILTER_TF=1h | DB2: EXIT_TIGHT_BREAKOUT_SCORER_FILTER_TF=15m | DC2: EXIT_TOP_FADE_FILTER_TF=OFF | DD2: EXIT_TOP_FADE_FILTER_TF=D | DE2: EXIT_TOP_FADE_FILTER_TF=4h | DF2: EXIT_TOP_FADE_FILTER_TF=1h | DG2: EXIT_TOP_FADE_FILTER_TF=15m | DH2: EXIT_TO_REDUCE_ADAPTER_FILTER_TF=OFF | DI2: EXIT_TO_REDUCE_ADAPTER_FILTER_TF=D | DJ2: EXIT_TO_REDUCE_ADAPTER_FILTER_TF=4h | DK2: EXIT_TO_REDUCE_ADAPTER_FILTER_TF=1h | DL2: EXIT_TO_REDUCE_ADAPTER_FILTER_TF=15m | DM2: FAST_RISER_FILTER_TF=OFF | DN2: FAST_RISER_FILTER_TF=D | DO2: FAST_RISER_FILTER_TF=4h | DP2: FAST_RISER_FILTER_TF=1h | DQ2: FAST_RISER_FILTER_TF=15m | DR2: FH_MOMENTUM_FILTER_TF=OFF | DS2: FH_MOMENTUM_FILTER_TF=D | DT2: FH_MOMENTUM_FILTER_TF=4h | DU2: FH_MOMENTUM_FILTER_TF=1h | DV2: FH_MOMENTUM_FILTER_TF=15m | DW2: FIRST_OPEN_THROTTLE_FILTER_TF=OFF | DX2: FIRST_OPEN_THROTTLE_FILTER_TF=D | DY2: FIRST_OPEN_THROTTLE_FILTER_TF=4h | DZ2: FIRST_OPEN_THROTTLE_FILTER_TF=1h | EA2: FIRST_OPEN_THROTTLE_FILTER_TF=15m | EB2: FROZEN_STOP_FILTER_TF=OFF | EC2: FROZEN_STOP_FILTER_TF=D | ED2: FROZEN_STOP_FILTER_TF=4h | EE2: FROZEN_STOP_FILTER_TF=1h | EF2: FROZEN_STOP_FILTER_TF=15m | EG2: GOLDEN_RULE_ENFORCE_FILTER_TF=OFF | EH2: GOLDEN_RULE_ENFORCE_FILTER_TF=D | EI2: GOLDEN_RULE_ENFORCE_FILTER_TF=4h | EJ2: GOLDEN_RULE_ENFORCE_FILTER_TF=1h | EK2: GOLDEN_RULE_ENFORCE_FILTER_TF=15m | EL2: GOLDEN_RULE_HTF_VOTE_FILTER_TF=OFF | EM2: GOLDEN_RULE_HTF_VOTE_FILTER_TF=D | EN2: GOLDEN_RULE_HTF_VOTE_FILTER_TF=4h | EO2: GOLDEN_RULE_HTF_VOTE_FILTER_TF=1h | EP2: GOLDEN_RULE_HTF_VOTE_FILTER_TF=15m | EQ2: GR_FILTER_VEC_FILTER_TF=OFF | ER2: GR_FILTER_VEC_FILTER_TF=D | ES2: GR_FILTER_VEC_FILTER_TF=4h | ET2: GR_FILTER_VEC_FILTER_TF=1h | EU2: GR_FILTER_VEC_FILTER_TF=15m | EV2: GR_V5_STATE_FILTER_TF=OFF | EW2: GR_V5_STATE_FILTER_TF=D | EX2: GR_V5_STATE_FILTER_TF=4h | EY2: GR_V5_STATE_FILTER_TF=1h | EZ2: GR_V5_STATE_FILTER_TF=15m | FA2: HAIKU_WINNER_FILTER_TF=OFF | FB2: HAIKU_WINNER_FILTER_TF=D | FC2: HAIKU_WINNER_FILTER_TF=4h | FD2: HAIKU_WINNER_FILTER_TF=1h | FE2: HAIKU_WINNER_FILTER_TF=15m | FF2: LH_HL_FILTER_TF_REQ=2 | FG2: LH_HL_FILTER_TF_REQ=2_ALT | FH2: LIVE_ENTRY_ENGINE_FILTER_TF=OFF | FI2: LIVE_ENTRY_ENGINE_FILTER_TF=D | FJ2: LIVE_ENTRY_ENGINE_FILTER_TF=4h | FK2: LIVE_ENTRY_ENGINE_FILTER_TF=1h | FL2: LIVE_ENTRY_ENGINE_FILTER_TF=15m | FM2: LIVE_ONLY_SIGNALS_BATCH5_FILTER_TF=OFF | FN2: LIVE_ONLY_SIGNALS_BATCH5_FILTER_TF=D | FO2: LIVE_ONLY_SIGNALS_BATCH5_FILTER_TF=4h | FP2: LIVE_ONLY_SIGNALS_BATCH5_FILTER_TF=1h | FQ2: LIVE_ONLY_SIGNALS_BATCH5_FILTER_TF=15m | FR2: MANDATORY_REENTRY_WT_FILTER_TF_MODE=15m_only | FS2: MANDATORY_REENTRY_WT_FILTER_TF_MODE=15m_only_ALT | FT2: MOM3_FILTER_TF=OFF | FU2: MOM3_FILTER_TF=D | FV2: MOM3_FILTER_TF=4h | FW2: MOM3_FILTER_TF=1h | FX2: MOM3_FILTER_TF=15m | FY2: MOMENTUM_BREAKOUT_FILTER_TF=OFF | FZ2: MOMENTUM_BREAKOUT_FILTER_TF=D | GA2: MOMENTUM_BREAKOUT_FILTER_TF=4h | GB2: MOMENTUM_BREAKOUT_FILTER_TF=1h | GC2: MOMENTUM_BREAKOUT_FILTER_TF=15m | GD2: MTF_ARMED_ENTRIES_FILTER_TF=OFF | GE2: MTF_ARMED_ENTRIES_FILTER_TF=D | GF2: MTF_ARMED_ENTRIES_FILTER_TF=4h | GG2: MTF_ARMED_ENTRIES_FILTER_TF=1h | GH2: MTF_ARMED_ENTRIES_FILTER_TF=15m | GI2: MTF_ATR_TRAIL_FILTER_TF=OFF | GJ2: MTF_ATR_TRAIL_FILTER_TF=D | GK2: MTF_ATR_TRAIL_FILTER_TF=4h | GL2: MTF_ATR_TRAIL_FILTER_TF=1h | GM2: MTF_ATR_TRAIL_FILTER_TF=15m | GN2: MTF_DC_REJECT_FILTER_TF=OFF | GO2: MTF_DC_REJECT_FILTER_TF=D | GP2: MTF_DC_REJECT_FILTER_TF=4h | GQ2: MTF_DC_REJECT_FILTER_TF=1h | GR2: MTF_DC_REJECT_FILTER_TF=15m | GS2: NEWBORN_LOSS_KILL_FILTER_TF=OFF | GT2: NEWBORN_LOSS_KILL_FILTER_TF=D | GU2: NEWBORN_LOSS_KILL_FILTER_TF=4h | GV2: NEWBORN_LOSS_KILL_FILTER_TF=1h | GW2: NEWBORN_LOSS_KILL_FILTER_TF=15m | GX2: NEWBORN_PROTECT_FILTER_TF=OFF | GY2: NEWBORN_PROTECT_FILTER_TF=D | GZ2: NEWBORN_PROTECT_FILTER_TF=4h | HA2: NEWBORN_PROTECT_FILTER_TF=1h | HB2: NEWBORN_PROTECT_FILTER_TF=15m | HC2: NOLOSS_BYPASS_WT5OF5_FILTER_TF=OFF | HD2: NOLOSS_BYPASS_WT5OF5_FILTER_TF=D | HE2: NOLOSS_BYPASS_WT5OF5_FILTER_TF=4h | HF2: NOLOSS_BYPASS_WT5OF5_FILTER_TF=1h | HG2: NOLOSS_BYPASS_WT5OF5_FILTER_TF=15m | HH2: OPEN_INTENT_SIZE_GATES_FILTER_TF=OFF | HI2: OPEN_INTENT_SIZE_GATES_FILTER_TF=D | HJ2: OPEN_INTENT_SIZE_GATES_FILTER_TF=4h | HK2: OPEN_INTENT_SIZE_GATES_FILTER_TF=1h | HL2: OPEN_INTENT_SIZE_GATES_FILTER_TF=15m | HM2: PARTIAL_PROFIT_LOCK_V2_FILTER_TF=OFF | HN2: PARTIAL_PROFIT_LOCK_V2_FILTER_TF=D | HO2: PARTIAL_PROFIT_LOCK_V2_FILTER_TF=4h | HP2: PARTIAL_PROFIT_LOCK_V2_FILTER_TF=1h | HQ2: PARTIAL_PROFIT_LOCK_V2_FILTER_TF=15m | HR2: PEAK_GIVEBACK_BE_EROSION_FILTER_TF=OFF | HS2: PEAK_GIVEBACK_BE_EROSION_FILTER_TF=D | HT2: PEAK_GIVEBACK_BE_EROSION_FILTER_TF=4h | HU2: PEAK_GIVEBACK_BE_EROSION_FILTER_TF=1h | HV2: PEAK_GIVEBACK_BE_EROSION_FILTER_TF=15m | HW2: WT_15M_BOUNCE_BB_MAX=0.95 | HX2: WT_15M_BOUNCE_BB_MAX=0.9 | HY2: WT_15M_BOUNCE_BB_MAX=0.8 | HZ2: WT_15M_BOUNCE_BB_MIN=0.05 | IA2: WT_15M_BOUNCE_BB_MIN=0.1 | IB2: WT_15M_BOUNCE_BB_MIN=0.2 | IC2: WT_15M_BOUNCE_HIGH_1H_GT_PREV=True | ID2: WT_15M_BOUNCE_HIGH_1H_GT_PREV=False | IE2: WT_15M_BOUNCE_LOW_1H_GT_PREV=True | IF2: WT_15M_BOUNCE_LOW_1H_GT_PREV=False | IG2: WT_15M_BOUNCE_REL_VOL_GT_1=True | IH2: WT_15M_BOUNCE_REL_VOL_GT_1=False | II2: Live Location | IJ2: Vec Hook | IK2: Type | IL2: Correct Options
A3: GR_FILTER_ALL_ENTRIES | B3: 0.0 | E3: =MAX('ENTRY_BREAKOUT_CHANNEL'!E:E) | F3: =IFERROR(VLOOKUP($A3&"="&$B3,Results_30d_Deltas!$A$2:$H$5000,5,FALSE),"") | G3: =IFERROR(VLOOKUP($A3,Results_30d_Deltas!$A$2:$H$5000,7,FALSE)-E3,"") | H3: =IFERROR(VLOOKUP($A3,Results_30d_Deltas!$A$2:$H$5000,6,FALSE),"") | K3: =IF(B3=C3,"YES","NO") | IJ3: ez_manage.py:4768 top() | IK3: v12_quick_engine.py:1912 x3
A4: GR_FILTER_ALL_ENTRIES | B4: 0.0_ALT | C4: GR_FILTER_ALL_ENTRIES=0.0_ALT + EXIT_TO_REDUCE_ADAPTER_FILTER_TF=4h + BB_WT_TF=15m + GR=18 + BB_RECOVERY_FILTER_TF=OFF + DC_BREAK_FILTER_TF=1h | E4: =IF(F4="",E3,IF(F4>0,E3+F4,E3)) | F4: =IFERROR(VLOOKUP($A4&"="&$B4,Results_30d_Deltas!$A$2:$H$5000,5,FALSE),"") | G4: =IFERROR(VLOOKUP($A4,Results_30d_Deltas!$A$2:$H$5000,7,FALSE)-E3,"") | H4: =IFERROR(VLOOKUP($A4,Results_30d_Deltas!$A$2:$H$5000,6,FALSE),"") | K4: =IF(B4=C4,"YES","NO") | IJ4: ez_manage.py:4768 top() | IK4: v12_quick_engine.py:1912 x3
A5: GR_FILTER_VEC_ENABLED | B5: False | E5: =IF(F5="",E4,IF(F5>0,E4+F5,E4)) | F5: =IFERROR(VLOOKUP($A5&"="&$B5,Results_30d_Deltas!$A$2:$H$5000,5,FALSE),"") | G5: =IFERROR(VLOOKUP($A5,Results_30d_Deltas!$A$2:$H$5000,7,FALSE)-E4,"") | H5: =IFERROR(VLOOKUP($A5,Results_30d_Deltas!$A$2:$H$5000,6,FALSE),"") | K5: =IF(B5=C5,"YES","NO") | IJ5: ez_manage.py:6003 top() | IK5: v12_quick_engine.py:4261 x2
A6: GR_FILTER_VEC_ENABLED | B6: True | E6: =IF(F6="",E5,IF(F6>0,E5+F6,E5)) | F6: =IFERROR(VLOOKUP($A6&"="&$B6,Results_30d_Deltas!$A$2:$H$5000,5,FALSE),"") | G6: =IFERROR(VLOOKUP($A6,Results_30d_Deltas!$A$2:$H$5000,7,FALSE)-E5,"") | H6: =IFERROR(VLOOKUP($A6,Results_30d_Deltas!$A$2:$H$5000,6,FALSE),"") | K6: =IF(B6=C6,"YES","NO") | IJ6: ez_manage.py:6003 top() | IK6: v12_quick_engine.py:4261 x2
A7: GR_FILTER_VEC_FILTER_TF | B7: OFF | E7: =IF(F7="",E6,IF(F7>0,E6+F7,E6)) | F7: =IFERROR(VLOOKUP($A7&"="&$B7,Results_30d_Deltas!$A$2:$H$5000,5,FALSE),"") | G7: =IFERROR(VLOOKUP($A7,Results_30d_Deltas!$A$2:$H$5000,7,FALSE)-E6,"") | H7: =IFERROR(VLOOKUP($A7,Results_30d_Deltas!$A$2:$H$5000,6,FALSE),"") | K7: =IF(B7=C7,"YES","NO") | IJ7: ez_manage.py:6004 top() | IK7: v12_quick_engine.py:112 x3
A8: GR_FILTER_VEC_FILTER_TF | B8: D | E8: =IF(F8="",E7,IF(F8>0,E7+F8,E7)) | F8: =IFERROR(VLOOKUP($A8&"="&$B8,Results_30d_Deltas!$A$2:$H$5000,5,FALSE),"") | G8: =IFERROR(VLOOKUP($A8,Results_30d_Deltas!$A$2:$H$5000,7,FALSE)-E7,"") | H8: =IFERROR(VLOOKUP($A8,Results_30d_Deltas!$A$2:$H$5000,6,FALSE),"") | K8: =IF(B8=C8,"YES","NO") | IJ8: ez_manage.py:6004 top() | IK8: v12_quick_engine.py:112 x3
A9: GR_FILTER_VEC_FILTER_TF | B9: 4h | E9: =IF(F9="",E8,IF(F9>0,E8+F9,E8)) | F9: =IFERROR(VLOOKUP($A9&"="&$B9,Results_30d_Deltas!$A$2:$H$5000,5,FALSE),"") | G9: =IFERROR(VLOOKUP($A9,Results_30d_Deltas!$A$2:$H$5000,7,FALSE)-E8,"") | H9: =IFERROR(VLOOKUP($A9,Results_30d_Deltas!$A$2:$H$5000,6,FALSE),"") | K9: =IF(B9=C9,"YES","NO") | IJ9: ez_manage.py:6004 top() | IK9: v12_quick_engine.py:112 x3
A10: GR_FILTER_VEC_FILTER_TF | B10: 1h | E10: =IF(F10="",E9,IF(F10>0,E9+F10,E9)) | F10: =IFERROR(VLOOKUP($A10&"="&$B10,Results_30d_Deltas!$A$2:$H$5000,5,FALSE),"") | G10: =IFERROR(VLOOKUP($A10,Results_30d_Deltas!$A$2:$H$5000,7,FALSE)-E9,"") | H10: =IFERROR(VLOOKUP($A10,Results_30d_Deltas!$A$2:$H$5000,6,FALSE),"") | K10: =IF(B10=C10,"YES","NO") | IJ10: ez_manage.py:6004 top() | IK10: v12_quick_engine.py:112 x3
A11: GR_FILTER_VEC_FILTER_TF | B11: 15m | E11: =IF(F11="",E10,IF(F11>0,E10+F11,E10)) | F11: =IFERROR(VLOOKUP($A11&"="&$B11,Results_30d_Deltas!$A$2:$H$5000,5,FALSE),"") | G11: =IFERROR(VLOOKUP($A11,Results_30d_Deltas!$A$2:$H$5000,7,FALSE)-E10,"") | H11: =IFERROR(VLOOKUP($A11,Results_30d_Deltas!$A$2:$H$5000,6,FALSE),"") | K11: =IF(B11=C11,"YES","NO") | IJ11: ez_manage.py:6004 top() | IK11: v12_quick_engine.py:112 x3
A12: WT_AGAINST_FILTER_ENABLED | B12: False | E12: =IF(F12="",E11,IF(F12>0,E11+F12,E11)) | F12: =IFERROR(VLOOKUP($A12&"="&$B12,Results_30d_Deltas!$A$2:$H$5000,5,FALSE),"") | G12: =IFERROR(VLOOKUP($A12,Results_30d_Deltas!$A$2:$H$5000,7,FALSE)-E11,"") | H12: =IFERROR(VLOOKUP($A12,Results_30d_Deltas!$A$2:$H$5000,6,FALSE),"") | K12: =IF(B12=C12,"YES","NO") | IJ12: ez_manage.py:6084 top() | IK12: v12_quick_engine.py:4291 x2
A13: WT_AGAINST_FILTER_ENABLED | B13: True | E13: =IF(F13="",E12,IF(F13>0,E12+F13,E12)) | F13: =IFERROR(VLOOKUP($A13&"="&$B13,Results_30d_Deltas!$A$2:$H$5000,5,FALSE),"") | G13: =IFERROR(VLOOKUP($A13,Results_30d_Deltas!$A$2:$H$5000,7,FALSE)-E12,"") | H13: =IFERROR(VLOOKUP($A13,Results_30d_Deltas!$A$2:$H$5000,6,FALSE),"") | K13: =IF(B13=C13,"YES","NO") | IJ13: ez_manage.py:6084 top() | IK13: v12_quick_engine.py:4291 x2

Sheet EXIT_STRUCTURAL
A1: 04 EXIT_STRUCTURAL - 2 bases -> 6 rows - 231 per-row FULLY CONNECTED
A2: Switch | B2: default | C2: override | D2: Family | E2: =MAX('ENTRY_CONFIRMATION_GATES'!E$2:E$5000) | F2: VECTOR_DELTA | G2: LIVE_DELTA | H2: LIVE_SHARPE | I2: REAL_COMPLETE | J2: PER_ROW_FILTERS | K2: is_default (backup if bold lost) | L2: ATR_TRAIL_FILTER_TF=OFF | M2: ATR_TRAIL_FILTER_TF=D | N2: ATR_TRAIL_FILTER_TF=4h | O2: ATR_TRAIL_FILTER_TF=1h | P2: ATR_TRAIL_FILTER_TF=15m | Q2: BAR_PATTERNS_FILTER_TF=OFF | R2: BAR_PATTERNS_FILTER_TF=D | S2: BAR_PATTERNS_FILTER_TF=4h | T2: BAR_PATTERNS_FILTER_TF=1h | U2: BAR_PATTERNS_FILTER_TF=15m | V2: BB_PULLBACK_GATE_FILTER_TF=OFF | W2: BB_PULLBACK_GATE_FILTER_TF=D | X2: BB_PULLBACK_GATE_FILTER_TF=4h | Y2: BB_PULLBACK_GATE_FILTER_TF=1h | Z2: BB_PULLBACK_GATE_FILTER_TF=15m | AA2: BB_RECOVERY_ENTRY_FILTER_TF=OFF | AB2: BB_RECOVERY_ENTRY_FILTER_TF=D | AC2: BB_RECOVERY_ENTRY_FILTER_TF=4h | AD2: BB_RECOVERY_ENTRY_FILTER_TF=1h | AE2: BB_RECOVERY_ENTRY_FILTER_TF=15m | AF2: BB_RECOVERY_FILTER_TF=OFF | AG2: BB_RECOVERY_FILTER_TF=D | AH2: BB_RECOVERY_FILTER_TF=4h | AI2: BB_RECOVERY_FILTER_TF=1h | AJ2: BB_RECOVERY_FILTER_TF=15m | AK2: BREAKEVEN_GAIN_EROSION_FILTER_TF=OFF | AL2: BREAKEVEN_GAIN_EROSION_FILTER_TF=D | AM2: BREAKEVEN_GAIN_EROSION_FILTER_TF=4h | AN2: BREAKEVEN_GAIN_EROSION_FILTER_TF=1h | AO2: BREAKEVEN_GAIN_EROSION_FILTER_TF=15m | AP2: BREAKOUT_RETEST_FILTER_TF=OFF | AQ2: BREAKOUT_RETEST_FILTER_TF=D | AR2: BREAKOUT_RETEST_FILTER_TF=4h | AS2: BREAKOUT_RETEST_FILTER_TF=1h | AT2: BREAKOUT_RETEST_FILTER_TF=15m | AU2: BT_WT_CROSS_LADDER_FILTER_TF=OFF | AV2: BT_WT_CROSS_LADDER_FILTER_TF=D | AW2: BT_WT_CROSS_LADDER_FILTER_TF=4h | AX2: BT_WT_CROSS_LADDER_FILTER_TF=1h | AY2: BT_WT_CROSS_LADDER_FILTER_TF=15m | AZ2: CANDLE_PATTERN_STOPS_FILTER_TF=OFF | BA2: CANDLE_PATTERN_STOPS_FILTER_TF=D | BB2: CANDLE_PATTERN_STOPS_FILTER_TF=4h | BC2: CANDLE_PATTERN_STOPS_FILTER_TF=1h | BD2: CANDLE_PATTERN_STOPS_FILTER_TF=15m | BE2: CIRCUIT_SHARPE_GATES_FILTER_TF=OFF | BF2: CIRCUIT_SHARPE_GATES_FILTER_TF=D | BG2: CIRCUIT_SHARPE_GATES_FILTER_TF=4h | BH2: CIRCUIT_SHARPE_GATES_FILTER_TF=1h | BI2: CIRCUIT_SHARPE_GATES_FILTER_TF=15m | BJ2: DC_BREACH_REDUCE_FILTER_TF=OFF | BK2: DC_BREACH_REDUCE_FILTER_TF=D | BL2: DC_BREACH_REDUCE_FILTER_TF=4h | BM2: DC_BREACH_REDUCE_FILTER_TF=1h | BN2: DC_BREACH_REDUCE_FILTER_TF=15m | BO2: DC_BREAK_FILTER_TF=OFF | BP2: DC_BREAK_FILTER_TF=D | BQ2: DC_BREAK_FILTER_TF=4h | BR2: DC_BREAK_FILTER_TF=1h | BS2: DC_BREAK_FILTER_TF=15m | BT2: DC_MOMENTUM_BOTA_SCORER_FILTER_TF=OFF | BU2: DC_MOMENTUM_BOTA_SCORER_FILTER_TF=D | BV2: DC_MOMENTUM_BOTA_SCORER_FILTER_TF=4h | BW2: DC_MOMENTUM_BOTA_SCORER_FILTER_TF=1h | BX2: DC_MOMENTUM_BOTA_SCORER_FILTER_TF=15m | BY2: DELTA_ENGINE_FILTER_TF=OFF | BZ2: DELTA_ENGINE_FILTER_TF=D | CA2: DELTA_ENGINE_FILTER_TF=4h | CB2: DELTA_ENGINE_FILTER_TF=1h | CC2: DELTA_ENGINE_FILTER_TF=15m | CD2: EMA_9_21_FILTER_FILTER_TF=OFF | CE2: EMA_9_21_FILTER_FILTER_TF=D | CF2: EMA_9_21_FILTER_FILTER_TF=4h | CG2: EMA_9_21_FILTER_FILTER_TF=1h | CH2: EMA_9_21_FILTER_FILTER_TF=15m | CI2: EMA_BLANKET_FILTER_FILTER_TF=OFF | CJ2: EMA_BLANKET_FILTER_FILTER_TF=D | CK2: EMA_BLANKET_FILTER_FILTER_TF=4h | CL2: EMA_BLANKET_FILTER_FILTER_TF=1h | CM2: EMA_BLANKET_FILTER_FILTER_TF=15m | CN2: EMERGENCY_BRAKE_FILTER_TF=OFF | CO2: EMERGENCY_BRAKE_FILTER_TF=D | CP2: EMERGENCY_BRAKE_FILTER_TF=4h | CQ2: EMERGENCY_BRAKE_FILTER_TF=1h | CR2: EMERGENCY_BRAKE_FILTER_TF=15m | CS2: EXIT_R1_R2_FILTER_TF=OFF | CT2: EXIT_R1_R2_FILTER_TF=D | CU2: EXIT_R1_R2_FILTER_TF=4h | CV2: EXIT_R1_R2_FILTER_TF=1h | CW2: EXIT_R1_R2_FILTER_TF=15m | CX2: EXIT_TIGHT_BREAKOUT_SCORER_FILTER_TF=OFF | CY2: EXIT_TIGHT_BREAKOUT_SCORER_FILTER_TF=D | CZ2: EXIT_TIGHT_BREAKOUT_SCORER_FILTER_TF=4h | DA2: EXIT_TIGHT_BREAKOUT_SCORER_FILTER_TF=1h | DB2: EXIT_TIGHT_BREAKOUT_SCORER_FILTER_TF=15m | DC2: EXIT_TOP_FADE_FILTER_TF=OFF | DD2: EXIT_TOP_FADE_FILTER_TF=D | DE2: EXIT_TOP_FADE_FILTER_TF=4h | DF2: EXIT_TOP_FADE_FILTER_TF=1h | DG2: EXIT_TOP_FADE_FILTER_TF=15m | DH2: EXIT_TO_REDUCE_ADAPTER_FILTER_TF=OFF | DI2: EXIT_TO_REDUCE_ADAPTER_FILTER_TF=D | DJ2: EXIT_TO_REDUCE_ADAPTER_FILTER_TF=4h | DK2: EXIT_TO_REDUCE_ADAPTER_FILTER_TF=1h | DL2: EXIT_TO_REDUCE_ADAPTER_FILTER_TF=15m | DM2: FAST_RISER_FILTER_TF=OFF | DN2: FAST_RISER_FILTER_TF=D | DO2: FAST_RISER_FILTER_TF=4h | DP2: FAST_RISER_FILTER_TF=1h | DQ2: FAST_RISER_FILTER_TF=15m | DR2: FH_MOMENTUM_FILTER_TF=OFF | DS2: FH_MOMENTUM_FILTER_TF=D | DT2: FH_MOMENTUM_FILTER_TF=4h | DU2: FH_MOMENTUM_FILTER_TF=1h | DV2: FH_MOMENTUM_FILTER_TF=15m | DW2: FIRST_OPEN_THROTTLE_FILTER_TF=OFF | DX2: FIRST_OPEN_THROTTLE_FILTER_TF=D | DY2: FIRST_OPEN_THROTTLE_FILTER_TF=4h | DZ2: FIRST_OPEN_THROTTLE_FILTER_TF=1h | EA2: FIRST_OPEN_THROTTLE_FILTER_TF=15m | EB2: FROZEN_STOP_FILTER_TF=OFF | EC2: FROZEN_STOP_FILTER_TF=D | ED2: FROZEN_STOP_FILTER_TF=4h | EE2: FROZEN_STOP_FILTER_TF=1h | EF2: FROZEN_STOP_FILTER_TF=15m | EG2: GOLDEN_RULE_ENFORCE_FILTER_TF=OFF | EH2: GOLDEN_RULE_ENFORCE_FILTER_TF=D | EI2: GOLDEN_RULE_ENFORCE_FILTER_TF=4h | EJ2: GOLDEN_RULE_ENFORCE_FILTER_TF=1h | EK2: GOLDEN_RULE_ENFORCE_FILTER_TF=15m | EL2: GOLDEN_RULE_HTF_VOTE_FILTER_TF=OFF | EM2: GOLDEN_RULE_HTF_VOTE_FILTER_TF=D | EN2: GOLDEN_RULE_HTF_VOTE_FILTER_TF=4h | EO2: GOLDEN_RULE_HTF_VOTE_FILTER_TF=1h | EP2: GOLDEN_RULE_HTF_VOTE_FILTER_TF=15m | EQ2: GR_FILTER_VEC_FILTER_TF=OFF | ER2: GR_FILTER_VEC_FILTER_TF=D | ES2: GR_FILTER_VEC_FILTER_TF=4h | ET2: GR_FILTER_VEC_FILTER_TF=1h | EU2: GR_FILTER_VEC_FILTER_TF=15m | EV2: GR_V5_STATE_FILTER_TF=OFF | EW2: GR_V5_STATE_FILTER_TF=D | EX2: GR_V5_STATE_FILTER_TF=4h | EY2: GR_V5_STATE_FILTER_TF=1h | EZ2: GR_V5_STATE_FILTER_TF=15m | FA2: HAIKU_WINNER_FILTER_TF=OFF | FB2: HAIKU_WINNER_FILTER_TF=D | FC2: HAIKU_WINNER_FILTER_TF=4h | FD2: HAIKU_WINNER_FILTER_TF=1h | FE2: HAIKU_WINNER_FILTER_TF=15m | FF2: LH_HL_FILTER_TF_REQ=2 | FG2: LH_HL_FILTER_TF_REQ=2_ALT | FH2: LIVE_ENTRY_ENGINE_FILTER_TF=OFF | FI2: LIVE_ENTRY_ENGINE_FILTER_TF=D | FJ2: LIVE_ENTRY_ENGINE_FILTER_TF=4h | FK2: LIVE_ENTRY_ENGINE_FILTER_TF=1h | FL2: LIVE_ENTRY_ENGINE_FILTER_TF=15m | FM2: LIVE_ONLY_SIGNALS_BATCH5_FILTER_TF=OFF | FN2: LIVE_ONLY_SIGNALS_BATCH5_FILTER_TF=D | FO2: LIVE_ONLY_SIGNALS_BATCH5_FILTER_TF=4h | FP2: LIVE_ONLY_SIGNALS_BATCH5_FILTER_TF=1h | FQ2: LIVE_ONLY_SIGNALS_BATCH5_FILTER_TF=15m | FR2: MANDATORY_REENTRY_WT_FILTER_TF_MODE=15m_only | FS2: MANDATORY_REENTRY_WT_FILTER_TF_MODE=15m_only_ALT | FT2: MOM3_FILTER_TF=OFF | FU2: MOM3_FILTER_TF=D | FV2: MOM3_FILTER_TF=4h | FW2: MOM3_FILTER_TF=1h | FX2: MOM3_FILTER_TF=15m | FY2: MOMENTUM_BREAKOUT_FILTER_TF=OFF | FZ2: MOMENTUM_BREAKOUT_FILTER_TF=D | GA2: MOMENTUM_BREAKOUT_FILTER_TF=4h | GB2: MOMENTUM_BREAKOUT_FILTER_TF=1h | GC2: MOMENTUM_BREAKOUT_FILTER_TF=15m | GD2: MTF_ARMED_ENTRIES_FILTER_TF=OFF | GE2: MTF_ARMED_ENTRIES_FILTER_TF=D | GF2: MTF_ARMED_ENTRIES_FILTER_TF=4h | GG2: MTF_ARMED_ENTRIES_FILTER_TF=1h | GH2: MTF_ARMED_ENTRIES_FILTER_TF=15m | GI2: MTF_ATR_TRAIL_FILTER_TF=OFF | GJ2: MTF_ATR_TRAIL_FILTER_TF=D | GK2: MTF_ATR_TRAIL_FILTER_TF=4h | GL2: MTF_ATR_TRAIL_FILTER_TF=1h | GM2: MTF_ATR_TRAIL_FILTER_TF=15m | GN2: MTF_DC_REJECT_FILTER_TF=OFF | GO2: MTF_DC_REJECT_FILTER_TF=D | GP2: MTF_DC_REJECT_FILTER_TF=4h | GQ2: MTF_DC_REJECT_FILTER_TF=1h | GR2: MTF_DC_REJECT_FILTER_TF=15m | GS2: NEWBORN_LOSS_KILL_FILTER_TF=OFF | GT2: NEWBORN_LOSS_KILL_FILTER_TF=D | GU2: NEWBORN_LOSS_KILL_FILTER_TF=4h | GV2: NEWBORN_LOSS_KILL_FILTER_TF=1h | GW2: NEWBORN_LOSS_KILL_FILTER_TF=15m | GX2: NEWBORN_PROTECT_FILTER_TF=OFF | GY2: NEWBORN_PROTECT_FILTER_TF=D | GZ2: NEWBORN_PROTECT_FILTER_TF=4h | HA2: NEWBORN_PROTECT_FILTER_TF=1h | HB2: NEWBORN_PROTECT_FILTER_TF=15m | HC2: NOLOSS_BYPASS_WT5OF5_FILTER_TF=OFF | HD2: NOLOSS_BYPASS_WT5OF5_FILTER_TF=D | HE2: NOLOSS_BYPASS_WT5OF5_FILTER_TF=4h | HF2: NOLOSS_BYPASS_WT5OF5_FILTER_TF=1h | HG2: NOLOSS_BYPASS_WT5OF5_FILTER_TF=15m | HH2: OPEN_INTENT_SIZE_GATES_FILTER_TF=OFF | HI2: OPEN_INTENT_SIZE_GATES_FILTER_TF=D | HJ2: OPEN_INTENT_SIZE_GATES_FILTER_TF=4h | HK2: OPEN_INTENT_SIZE_GATES_FILTER_TF=1h | HL2: OPEN_INTENT_SIZE_GATES_FILTER_TF=15m | HM2: PARTIAL_PROFIT_LOCK_V2_FILTER_TF=OFF | HN2: PARTIAL_PROFIT_LOCK_V2_FILTER_TF=D | HO2: PARTIAL_PROFIT_LOCK_V2_FILTER_TF=4h | HP2: PARTIAL_PROFIT_LOCK_V2_FILTER_TF=1h | HQ2: PARTIAL_PROFIT_LOCK_V2_FILTER_TF=15m | HR2: PEAK_GIVEBACK_BE_EROSION_FILTER_TF=OFF | HS2: PEAK_GIVEBACK_BE_EROSION_FILTER_TF=D | HT2: PEAK_GIVEBACK_BE_EROSION_FILTER_TF=4h | HU2: PEAK_GIVEBACK_BE_EROSION_FILTER_TF=1h | HV2: PEAK_GIVEBACK_BE_EROSION_FILTER_TF=15m | HW2: WT_15M_BOUNCE_BB_MAX=0.95 | HX2: WT_15M_BOUNCE_BB_MAX=0.9 | HY2: WT_15M_BOUNCE_BB_MAX=0.8 | HZ2: WT_15M_BOUNCE_BB_MIN=0.05 | IA2: WT_15M_BOUNCE_BB_MIN=0.1 | IB2: WT_15M_BOUNCE_BB_MIN=0.2 | IC2: WT_15M_BOUNCE_HIGH_1H_GT_PREV=True | ID2: WT_15M_BOUNCE_HIGH_1H_GT_PREV=False | IE2: WT_15M_BOUNCE_LOW_1H_GT_PREV=True | IF2: WT_15M_BOUNCE_LOW_1H_GT_PREV=False | IG2: WT_15M_BOUNCE_REL_VOL_GT_1=True | IH2: WT_15M_BOUNCE_REL_VOL_GT_1=False | II2: Live Location | IJ2: Vec Hook | IK2: Type | IL2: Correct Options
A3: STDEV_BREAKOUT_EXIT_PCTB_FAIL | B3: 0 | E3: =MAX('ENTRY_CONFIRMATION_GATES'!E:E) | F3: =IFERROR(VLOOKUP($A3&"="&$B3,Results_30d_Deltas!$A$2:$H$5000,5,FALSE),"") | G3: =IFERROR(VLOOKUP($A3,Results_30d_Deltas!$A$2:$H$5000,7,FALSE)-E3,"") | H3: =IFERROR(VLOOKUP($A3,Results_30d_Deltas!$A$2:$H$5000,6,FALSE),"") | K3: =IF(B3=C3,"YES","NO") | IJ3: ez_manage.py:4040 top() | IK3: v12_quick_engine.py:3276 x2
A4: STDEV_BREAKOUT_EXIT_PCTB_FAIL | B4: 0.5 | E4: =IF(F4="",E3,IF(F4>0,E3+F4,E3)) | F4: =IFERROR(VLOOKUP($A4&"="&$B4,Results_30d_Deltas!$A$2:$H$5000,5,FALSE),"") | G4: =IFERROR(VLOOKUP($A4,Results_30d_Deltas!$A$2:$H$5000,7,FALSE)-E3,"") | H4: =IFERROR(VLOOKUP($A4,Results_30d_Deltas!$A$2:$H$5000,6,FALSE),"") | K4: =IF(B4=C4,"YES","NO") | IJ4: ez_manage.py:4040 top() | IK4: v12_quick_engine.py:3276 x2
A5: STDEV_BREAKOUT_EXIT_PCTB_FAIL | B5: 1.0 | E5: =IF(F5="",E4,IF(F5>0,E4+F5,E4)) | F5: =IFERROR(VLOOKUP($A5&"="&$B5,Results_30d_Deltas!$A$2:$H$5000,5,FALSE),"") | G5: =IFERROR(VLOOKUP($A5,Results_30d_Deltas!$A$2:$H$5000,7,FALSE)-E4,"") | H5: =IFERROR(VLOOKUP($A5,Results_30d_Deltas!$A$2:$H$5000,6,FALSE),"") | K5: =IF(B5=C5,"YES","NO") | IJ5: ez_manage.py:4040 top() | IK5: v12_quick_engine.py:3276 x2
A6: STDEV_BREAKOUT_EXIT_PCTB_FAIL | B6: 2.0 | E6: =IF(F6="",E5,IF(F6>0,E5+F6,E5)) | F6: =IFERROR(VLOOKUP($A6&"="&$B6,Results_30d_Deltas!$A$2:$H$5000,5,FALSE),"") | G6: =IFERROR(VLOOKUP($A6,Results_30d_Deltas!$A$2:$H$5000,7,FALSE)-E5,"") | H6: =IFERROR(VLOOKUP($A6,Results_30d_Deltas!$A$2:$H$5000,6,FALSE),"") | K6: =IF(B6=C6,"YES","NO") | IJ6: ez_manage.py:4040 top() | IK6: v12_quick_engine.py:3276 x2
A7: ALL_TF_AGAINST_CLOSE_ENABLED | B7: False | E7: =IF(F7="",E6,IF(F7>0,E6+F7,E6)) | F7: =IFERROR(VLOOKUP($A7&"="&$B7,Results_30d_Deltas!$A$2:$H$5000,5,FALSE),"") | G7: =IFERROR(VLOOKUP($A7,Results_30d_Deltas!$A$2:$H$5000,7,FALSE)-E6,"") | H7: =IFERROR(VLOOKUP($A7,Results_30d_Deltas!$A$2:$H$5000,6,FALSE),"") | K7: =IF(B7=C7,"YES","NO") | IJ7: ez_manage.py:4325 top() | IK7: v12_quick_engine.py:174 x6
A8: ALL_TF_AGAINST_CLOSE_ENABLED | B8: True | E8: =IF(F8="",E7,IF(F8>0,E7+F8,E7)) | F8: =IFERROR(VLOOKUP($A8&"="&$B8,Results_30d_Deltas!$A$2:$H$5000,5,FALSE),"") | G8: =IFERROR(VLOOKUP($A8,Results_30d_Deltas!$A$2:$H$5000,7,FALSE)-E7,"") | H8: =IFERROR(VLOOKUP($A8,Results_30d_Deltas!$A$2:$H$5000,6,FALSE),"") | K8: =IF(B8=C8,"YES","NO") | IJ8: ez_manage.py:4325 top() | IK8: v12_quick_engine.py:174 x6

Sheet EXIT_VELOCITY
A1: 05 EXIT_VELOCITY - 26 bases -> 80 rows - 231 per-row FULLY CONNECTED
A2: Switch | B2: default | C2: override | D2: Family | E2: =MAX('EXIT_STRUCTURAL'!E$2:E$5000) | F2: VECTOR_DELTA | G2: LIVE_DELTA | H2: LIVE_SHARPE | I2: REAL_COMPLETE | J2: PER_ROW_FILTERS | K2: is_default (backup if bold lost) | L2: ATR_TRAIL_FILTER_TF=OFF | M2: ATR_TRAIL_FILTER_TF=D | N2: ATR_TRAIL_FILTER_TF=4h | O2: ATR_TRAIL_FILTER_TF=1h | P2: ATR_TRAIL_FILTER_TF=15m | Q2: BAR_PATTERNS_FILTER_TF=OFF | R2: BAR_PATTERNS_FILTER_TF=D | S2: BAR_PATTERNS_FILTER_TF=4h | T2: BAR_PATTERNS_FILTER_TF=1h | U2: BAR_PATTERNS_FILTER_TF=15m | V2: BB_PULLBACK_GATE_FILTER_TF=OFF | W2: BB_PULLBACK_GATE_FILTER_TF=D | X2: BB_PULLBACK_GATE_FILTER_TF=4h | Y2: BB_PULLBACK_GATE_FILTER_TF=1h | Z2: BB_PULLBACK_GATE_FILTER_TF=15m | AA2: BB_RECOVERY_ENTRY_FILTER_TF=OFF | AB2: BB_RECOVERY_ENTRY_FILTER_TF=D | AC2: BB_RECOVERY_ENTRY_FILTER_TF=4h | AD2: BB_RECOVERY_ENTRY_FILTER_TF=1h | AE2: BB_RECOVERY_ENTRY_FILTER_TF=15m | AF2: BB_RECOVERY_FILTER_TF=OFF | AG2: BB_RECOVERY_FILTER_TF=D | AH2: BB_RECOVERY_FILTER_TF=4h | AI2: BB_RECOVERY_FILTER_TF=1h | AJ2: BB_RECOVERY_FILTER_TF=15m | AK2: BREAKEVEN_GAIN_EROSION_FILTER_TF=OFF | AL2: BREAKEVEN_GAIN_EROSION_FILTER_TF=D | AM2: BREAKEVEN_GAIN_EROSION_FILTER_TF=4h | AN2: BREAKEVEN_GAIN_EROSION_FILTER_TF=1h | AO2: BREAKEVEN_GAIN_EROSION_FILTER_TF=15m | AP2: BREAKOUT_RETEST_FILTER_TF=OFF | AQ2: BREAKOUT_RETEST_FILTER_TF=D | AR2: BREAKOUT_RETEST_FILTER_TF=4h | AS2: BREAKOUT_RETEST_FILTER_TF=1h | AT2: BREAKOUT_RETEST_FILTER_TF=15m | AU2: BT_WT_CROSS_LADDER_FILTER_TF=OFF | AV2: BT_WT_CROSS_LADDER_FILTER_TF=D | AW2: BT_WT_CROSS_LADDER_FILTER_TF=4h | AX2: BT_WT_CROSS_LADDER_FILTER_TF=1h | AY2: BT_WT_CROSS_LADDER_FILTER_TF=15m | AZ2: CANDLE_PATTERN_STOPS_FILTER_TF=OFF | BA2: CANDLE_PATTERN_STOPS_FILTER_TF=D | BB2: CANDLE_PATTERN_STOPS_FILTER_TF=4h | BC2: CANDLE_PATTERN_STOPS_FILTER_TF=1h | BD2: CANDLE_PATTERN_STOPS_FILTER_TF=15m | BE2: CIRCUIT_SHARPE_GATES_FILTER_TF=OFF | BF2: CIRCUIT_SHARPE_GATES_FILTER_TF=D | BG2: CIRCUIT_SHARPE_GATES_FILTER_TF=4h | BH2: CIRCUIT_SHARPE_GATES_FILTER_TF=1h | BI2: CIRCUIT_SHARPE_GATES_FILTER_TF=15m | BJ2: DC_BREACH_REDUCE_FILTER_TF=OFF | BK2: DC_BREACH_REDUCE_FILTER_TF=D | BL2: DC_BREACH_REDUCE_FILTER_TF=4h | BM2: DC_BREACH_REDUCE_FILTER_TF=1h | BN2: DC_BREACH_REDUCE_FILTER_TF=15m | BO2: DC_BREAK_FILTER_TF=OFF | BP2: DC_BREAK_FILTER_TF=D | BQ2: DC_BREAK_FILTER_TF=4h | BR2: DC_BREAK_FILTER_TF=1h | BS2: DC_BREAK_FILTER_TF=15m | BT2: DC_MOMENTUM_BOTA_SCORER_FILTER_TF=OFF | BU2: DC_MOMENTUM_BOTA_SCORER_FILTER_TF=D | BV2: DC_MOMENTUM_BOTA_SCORER_FILTER_TF=4h | BW2: DC_MOMENTUM_BOTA_SCORER_FILTER_TF=1h | BX2: DC_MOMENTUM_BOTA_SCORER_FILTER_TF=15m | BY2: DELTA_ENGINE_FILTER_TF=OFF | BZ2: DELTA_ENGINE_FILTER_TF=D | CA2: DELTA_ENGINE_FILTER_TF=4h | CB2: DELTA_ENGINE_FILTER_TF=1h | CC2: DELTA_ENGINE_FILTER_TF=15m | CD2: EMA_9_21_FILTER_FILTER_TF=OFF | CE2: EMA_9_21_FILTER_FILTER_TF=D | CF2: EMA_9_21_FILTER_FILTER_TF=4h | CG2: EMA_9_21_FILTER_FILTER_TF=1h | CH2: EMA_9_21_FILTER_FILTER_TF=15m | CI2: EMA_BLANKET_FILTER_FILTER_TF=OFF | CJ2: EMA_BLANKET_FILTER_FILTER_TF=D | CK2: EMA_BLANKET_FILTER_FILTER_TF=4h | CL2: EMA_BLANKET_FILTER_FILTER_TF=1h | CM2: EMA_BLANKET_FILTER_FILTER_TF=15m | CN2: EMERGENCY_BRAKE_FILTER_TF=OFF | CO2: EMERGENCY_BRAKE_FILTER_TF=D | CP2: EMERGENCY_BRAKE_FILTER_TF=4h | CQ2: EMERGENCY_BRAKE_FILTER_TF=1h | CR2: EMERGENCY_BRAKE_FILTER_TF=15m | CS2: EXIT_R1_R2_FILTER_TF=OFF | CT2: EXIT_R1_R2_FILTER_TF=D | CU2: EXIT_R1_R2_FILTER_TF=4h | CV2: EXIT_R1_R2_FILTER_TF=1h | CW2: EXIT_R1_R2_FILTER_TF=15m | CX2: EXIT_TIGHT_BREAKOUT_SCORER_FILTER_TF=OFF | CY2: EXIT_TIGHT_BREAKOUT_SCORER_FILTER_TF=D | CZ2: EXIT_TIGHT_BREAKOUT_SCORER_FILTER_TF=4h | DA2: EXIT_TIGHT_BREAKOUT_SCORER_FILTER_TF=1h | DB2: EXIT_TIGHT_BREAKOUT_SCORER_FILTER_TF=15m | DC2: EXIT_TOP_FADE_FILTER_TF=OFF | DD2: EXIT_TOP_FADE_FILTER_TF=D | DE2: EXIT_TOP_FADE_FILTER_TF=4h | DF2: EXIT_TOP_FADE_FILTER_TF=1h | DG2: EXIT_TOP_FADE_FILTER_TF=15m | DH2: EXIT_TO_REDUCE_ADAPTER_FILTER_TF=OFF | DI2: EXIT_TO_REDUCE_ADAPTER_FILTER_TF=D | DJ2: EXIT_TO_REDUCE_ADAPTER_FILTER_TF=4h | DK2: EXIT_TO_REDUCE_ADAPTER_FILTER_TF=1h | DL2: EXIT_TO_REDUCE_ADAPTER_FILTER_TF=15m | DM2: FAST_RISER_FILTER_TF=OFF | DN2: FAST_RISER_FILTER_TF=D | DO2: FAST_RISER_FILTER_TF=4h | DP2: FAST_RISER_FILTER_TF=1h | DQ2: FAST_RISER_FILTER_TF=15m | DR2: FH_MOMENTUM_FILTER_TF=OFF | DS2: FH_MOMENTUM_FILTER_TF=D | DT2: FH_MOMENTUM_FILTER_TF=4h | DU2: FH_MOMENTUM_FILTER_TF=1h | DV2: FH_MOMENTUM_FILTER_TF=15m | DW2: FIRST_OPEN_THROTTLE_FILTER_TF=OFF | DX2: FIRST_OPEN_THROTTLE_FILTER_TF=D | DY2: FIRST_OPEN_THROTTLE_FILTER_TF=4h | DZ2: FIRST_OPEN_THROTTLE_FILTER_TF=1h | EA2: FIRST_OPEN_THROTTLE_FILTER_TF=15m | EB2: FROZEN_STOP_FILTER_TF=OFF | EC2: FROZEN_STOP_FILTER_TF=D | ED2: FROZEN_STOP_FILTER_TF=4h | EE2: FROZEN_STOP_FILTER_TF=1h | EF2: FROZEN_STOP_FILTER_TF=15m | EG2: GOLDEN_RULE_ENFORCE_FILTER_TF=OFF | EH2: GOLDEN_RULE_ENFORCE_FILTER_TF=D | EI2: GOLDEN_RULE_ENFORCE_FILTER_TF=4h | EJ2: GOLDEN_RULE_ENFORCE_FILTER_TF=1h | EK2: GOLDEN_RULE_ENFORCE_FILTER_TF=15m | EL2: GOLDEN_RULE_HTF_VOTE_FILTER_TF=OFF | EM2: GOLDEN_RULE_HTF_VOTE_FILTER_TF=D | EN2: GOLDEN_RULE_HTF_VOTE_FILTER_TF=4h | EO2: GOLDEN_RULE_HTF_VOTE_FILTER_TF=1h | EP2: GOLDEN_RULE_HTF_VOTE_FILTER_TF=15m | EQ2: GR_FILTER_VEC_FILTER_TF=OFF | ER2: GR_FILTER_VEC_FILTER_TF=D | ES2: GR_FILTER_VEC_FILTER_TF=4h | ET2: GR_FILTER_VEC_FILTER_TF=1h | EU2: GR_FILTER_VEC_FILTER_TF=15m | EV2: GR_V5_STATE_FILTER_TF=OFF | EW2: GR_V5_STATE_FILTER_TF=D | EX2: GR_V5_STATE_FILTER_TF=4h | EY2: GR_V5_STATE_FILTER_TF=1h | EZ2: GR_V5_STATE_FILTER_TF=15m | FA2: HAIKU_WINNER_FILTER_TF=OFF | FB2: HAIKU_WINNER_FILTER_TF=D | FC2: HAIKU_WINNER_FILTER_TF=4h | FD2: HAIKU_WINNER_FILTER_TF=1h | FE2: HAIKU_WINNER_FILTER_TF=15m | FF2: LH_HL_FILTER_TF_REQ=2 | FG2: LH_HL_FILTER_TF_REQ=2_ALT | FH2: LIVE_ENTRY_ENGINE_FILTER_TF=OFF | FI2: LIVE_ENTRY_ENGINE_FILTER_TF=D | FJ2: LIVE_ENTRY_ENGINE_FILTER_TF=4h | FK2: LIVE_ENTRY_ENGINE_FILTER_TF=1h | FL2: LIVE_ENTRY_ENGINE_FILTER_TF=15m | FM2: LIVE_ONLY_SIGNALS_BATCH5_FILTER_TF=OFF | FN2: LIVE_ONLY_SIGNALS_BATCH5_FILTER_TF=D | FO2: LIVE_ONLY_SIGNALS_BATCH5_FILTER_TF=4h | FP2: LIVE_ONLY_SIGNALS_BATCH5_FILTER_TF=1h | FQ2: LIVE_ONLY_SIGNALS_BATCH5_FILTER_TF=15m | FR2: MANDATORY_REENTRY_WT_FILTER_TF_MODE=15m_only | FS2: MANDATORY_REENTRY_WT_FILTER_TF_MODE=15m_only_ALT | FT2: MOM3_FILTER_TF=OFF | FU2: MOM3_FILTER_TF=D | FV2: MOM3_FILTER_TF=4h | FW2: MOM3_FILTER_TF=1h | FX2: MOM3_FILTER_TF=15m | FY2: MOMENTUM_BREAKOUT_FILTER_TF=OFF | FZ2: MOMENTUM_BREAKOUT_FILTER_TF=D | GA2: MOMENTUM_BREAKOUT_FILTER_TF=4h | GB2: MOMENTUM_BREAKOUT_FILTER_TF=1h | GC2: MOMENTUM_BREAKOUT_FILTER_TF=15m | GD2: MTF_ARMED_ENTRIES_FILTER_TF=OFF | GE2: MTF_ARMED_ENTRIES_FILTER_TF=D | GF2: MTF_ARMED_ENTRIES_FILTER_TF=4h | GG2: MTF_ARMED_ENTRIES_FILTER_TF=1h | GH2: MTF_ARMED_ENTRIES_FILTER_TF=15m | GI2: MTF_ATR_TRAIL_FILTER_TF=OFF | GJ2: MTF_ATR_TRAIL_FILTER_TF=D | GK2: MTF_ATR_TRAIL_FILTER_TF=4h | GL2: MTF_ATR_TRAIL_FILTER_TF=1h | GM2: MTF_ATR_TRAIL_FILTER_TF=15m | GN2: MTF_DC_REJECT_FILTER_TF=OFF | GO2: MTF_DC_REJECT_FILTER_TF=D | GP2: MTF_DC_REJECT_FILTER_TF=4h | GQ2: MTF_DC_REJECT_FILTER_TF=1h | GR2: MTF_DC_REJECT_FILTER_TF=15m | GS2: NEWBORN_LOSS_KILL_FILTER_TF=OFF | GT2: NEWBORN_LOSS_KILL_FILTER_TF=D | GU2: NEWBORN_LOSS_KILL_FILTER_TF=4h | GV2: NEWBORN_LOSS_KILL_FILTER_TF=1h | GW2: NEWBORN_LOSS_KILL_FILTER_TF=15m | GX2: NEWBORN_PROTECT_FILTER_TF=OFF | GY2: NEWBORN_PROTECT_FILTER_TF=D | GZ2: NEWBORN_PROTECT_FILTER_TF=4h | HA2: NEWBORN_PROTECT_FILTER_TF=1h | HB2: NEWBORN_PROTECT_FILTER_TF=15m | HC2: NOLOSS_BYPASS_WT5OF5_FILTER_TF=OFF | HD2: NOLOSS_BYPASS_WT5OF5_FILTER_TF=D | HE2: NOLOSS_BYPASS_WT5OF5_FILTER_TF=4h | HF2: NOLOSS_BYPASS_WT5OF5_FILTER_TF=1h | HG2: NOLOSS_BYPASS_WT5OF5_FILTER_TF=15m | HH2: OPEN_INTENT_SIZE_GATES_FILTER_TF=OFF | HI2: OPEN_INTENT_SIZE_GATES_FILTER_TF=D | HJ2: OPEN_INTENT_SIZE_GATES_FILTER_TF=4h | HK2: OPEN_INTENT_SIZE_GATES_FILTER_TF=1h | HL2: OPEN_INTENT_SIZE_GATES_FILTER_TF=15m | HM2: PARTIAL_PROFIT_LOCK_V2_FILTER_TF=OFF | HN2: PARTIAL_PROFIT_LOCK_V2_FILTER_TF=D | HO2: PARTIAL_PROFIT_LOCK_V2_FILTER_TF=4h | HP2: PARTIAL_PROFIT_LOCK_V2_FILTER_TF=1h | HQ2: PARTIAL_PROFIT_LOCK_V2_FILTER_TF=15m | HR2: PEAK_GIVEBACK_BE_EROSION_FILTER_TF=OFF | HS2: PEAK_GIVEBACK_BE_EROSION_FILTER_TF=D | HT2: PEAK_GIVEBACK_BE_EROSION_FILTER_TF=4h | HU2: PEAK_GIVEBACK_BE_EROSION_FILTER_TF=1h | HV2: PEAK_GIVEBACK_BE_EROSION_FILTER_TF=15m | HW2: WT_15M_BOUNCE_BB_MAX=0.95 | HX2: WT_15M_BOUNCE_BB_MAX=0.9 | HY2: WT_15M_BOUNCE_BB_MAX=0.8 | HZ2: WT_15M_BOUNCE_BB_MIN=0.05 | IA2: WT_15M_BOUNCE_BB_MIN=0.1 | IB2: WT_15M_BOUNCE_BB_MIN=0.2 | IC2: WT_15M_BOUNCE_HIGH_1H_GT_PREV=True | ID2: WT_15M_BOUNCE_HIGH_1H_GT_PREV=False | IE2: WT_15M_BOUNCE_LOW_1H_GT_PREV=True | IF2: WT_15M_BOUNCE_LOW_1H_GT_PREV=False | IG2: WT_15M_BOUNCE_REL_VOL_GT_1=True | IH2: WT_15M_BOUNCE_REL_VOL_GT_1=False | II2: Live Location | IJ2: Vec Hook | IK2: Type | IL2: Correct Options
A3: WT_CROSS_EXIT_ENABLED | B3: False | E3: =MAX('EXIT_STRUCTURAL'!E:E) | F3: =IFERROR(VLOOKUP($A3&"="&$B3,Results_30d_Deltas!$A$2:$H$5000,5,FALSE),"") | G3: =IFERROR(VLOOKUP($A3,Results_30d_Deltas!$A$2:$H$5000,7,FALSE)-E3,"") | H3: =IFERROR(VLOOKUP($A3,Results_30d_Deltas!$A$2:$H$5000,6,FALSE),"") | K3: =IF(B3=C3,"YES","NO") | IJ3: ez_manage.py:1751 top() | IK3: v12_quick_engine.py:2439 x5
A4: WT_CROSS_EXIT_ENABLED | B4: True | E4: =IF(F4="",E3,IF(F4>0,E3+F4,E3)) | F4: =IFERROR(VLOOKUP($A4&"="&$B4,Results_30d_Deltas!$A$2:$H$5000,5,FALSE),"") | G4: =IFERROR(VLOOKUP($A4,Results_30d_Deltas!$A$2:$H$5000,7,FALSE)-E3,"") | H4: =IFERROR(VLOOKUP($A4,Results_30d_Deltas!$A$2:$H$5000,6,FALSE),"") | K4: =IF(B4=C4,"YES","NO") | IJ4: ez_manage.py:1751 top() | IK4: v12_quick_engine.py:2439 x5
A5: BB_SQUEEZE_EXIT_ENABLED | B5: False | E5: =IF(F5="",E4,IF(F5>0,E4+F5,E4)) | F5: =IFERROR(VLOOKUP($A5&"="&$B5,Results_30d_Deltas!$A$2:$H$5000,5,FALSE),"") | G5: =IFERROR(VLOOKUP($A5,Results_30d_Deltas!$A$2:$H$5000,7,FALSE)-E4,"") | H5: =IFERROR(VLOOKUP($A5,Results_30d_Deltas!$A$2:$H$5000,6,FALSE),"") | K5: =IF(B5=C5,"YES","NO") | IJ5: ez_manage.py:6163 top() | IK5: v12_quick_engine.py:891 x4
A6: BB_SQUEEZE_EXIT_ENABLED | B6: True | E6: =IF(F6="",E5,IF(F6>0,E5+F6,E5)) | F6: =IFERROR(VLOOKUP($A6&"="&$B6,Results_30d_Deltas!$A$2:$H$5000,5,FALSE),"") | G6: =IFERROR(VLOOKUP($A6,Results_30d_Deltas!$A$2:$H$5000,7,FALSE)-E5,"") | H6: =IFERROR(VLOOKUP($A6,Results_30d_Deltas!$A$2:$H$5000,6,FALSE),"") | K6: =IF(B6=C6,"YES","NO") | IJ6: ez_manage.py:6163 top() | IK6: v12_quick_engine.py:891 x4
A7: BTC_DIVERGENCE_EXIT_AGAINST | B7: 0 | E7: =IF(F7="",E6,IF(F7>0,E6+F7,E6)) | F7: =IFERROR(VLOOKUP($A7&"="&$B7,Results_30d_Deltas!$A$2:$H$5000,5,FALSE),"") | G7: =IFERROR(VLOOKUP($A7,Results_30d_Deltas!$A$2:$H$5000,7,FALSE)-E6,"") | H7: =IFERROR(VLOOKUP($A7,Results_30d_Deltas!$A$2:$H$5000,6,FALSE),"") | K7: =IF(B7=C7,"YES","NO") | IJ7: ez_manage.py:4448 top() | IK7: v12_quick_engine.py:408 x8
A8: BTC_DIVERGENCE_EXIT_AGAINST | B8: 0.5 | E8: =IF(F8="",E7,IF(F8>0,E7+F8,E7)) | F8: =IFERROR(VLOOKUP($A8&"="&$B8,Results_30d_Deltas!$A$2:$H$5000,5,FALSE),"") | G8: =IFERROR(VLOOKUP($A8,Results_30d_Deltas!$A$2:$H$5000,7,FALSE)-E7,"") | H8: =IFERROR(VLOOKUP($A8,Results_30d_Deltas!$A$2:$H$5000,6,FALSE),"") | K8: =IF(B8=C8,"YES","NO") | IJ8: ez_manage.py:4448 top() | IK8: v12_quick_engine.py:408 x8
A9: BTC_DIVERGENCE_EXIT_AGAINST | B9: 1.0 | E9: =IF(F9="",E8,IF(F9>0,E8+F9,E8)) | F9: =IFERROR(VLOOKUP($A9&"="&$B9,Results_30d_Deltas!$A$2:$H$5000,5,FALSE),"") | G9: =IFERROR(VLOOKUP($A9,Results_30d_Deltas!$A$2:$H$5000,7,FALSE)-E8,"") | H9: =IFERROR(VLOOKUP($A9,Results_30d_Deltas!$A$2:$H$5000,6,FALSE),"") | K9: =IF(B9=C9,"YES","NO") | IJ9: ez_manage.py:4448 top() | IK9: v12_quick_engine.py:408 x8
A10: BTC_DIVERGENCE_EXIT_AGAINST | B10: 2.0 | E10: =IF(F10="",E9,IF(F10>0,E9+F10,E9)) | F10: =IFERROR(VLOOKUP($A10&"="&$B10,Results_30d_Deltas!$A$2:$H$5000,5,FALSE),"") | G10: =IFERROR(VLOOKUP($A10,Results_30d_Deltas!$A$2:$H$5000,7,FALSE)-E9,"") | H10: =IFERROR(VLOOKUP($A10,Results_30d_Deltas!$A$2:$H$5000,6,FALSE),"") | K10: =IF(B10=C10,"YES","NO") | IJ10: ez_manage.py:4448 top() | IK10: v12_quick_engine.py:408 x8
A11: DELTA_EXIT_DC_FLOOR | B11: False | E11: =IF(F11="",E10,IF(F11>0,E10+F11,E10)) | F11: =IFERROR(VLOOKUP($A11&"="&$B11,Results_30d_Deltas!$A$2:$H$5000,5,FALSE),"") | G11: =IFERROR(VLOOKUP($A11,Results_30d_Deltas!$A$2:$H$5000,7,FALSE)-E10,"") | H11: =IFERROR(VLOOKUP($A11,Results_30d_Deltas!$A$2:$H$5000,6,FALSE),"") | K11: =IF(B11=C11,"YES","NO") | IJ11: ez_manage.py:4596 top() | IK11: v12_quick_engine.py:967 x8
A12: DELTA_EXIT_DC_FLOOR | B12: True | E12: =IF(F12="",E11,IF(F12>0,E11+F12,E11)) | F12: =IFERROR(VLOOKUP($A12&"="&$B12,Results_30d_Deltas!$A$2:$H$5000,5,FALSE),"") | G12: =IFERROR(VLOOKUP($A12,Results_30d_Deltas!$A$2:$H$5000,7,FALSE)-E11,"") | H12: =IFERROR(VLOOKUP($A12,Results_30d_Deltas!$A$2:$H$5000,6,FALSE),"") | K12: =IF(B12=C12,"YES","NO") | IJ12: ez_manage.py:4596 top() | IK12: v12_quick_engine.py:967 x8
A13: E_1_WT_EXIT_USE_DELTA_ENABLED | B13: False | E13: =IF(F13="",E12,IF(F13>0,E12+F13,E12)) | F13: =IFERROR(VLOOKUP($A13&"="&$B13,Results_30d_Deltas!$A$2:$H$5000,5,FALSE),"") | G13: =IFERROR(VLOOKUP($A13,Results_30d_Deltas!$A$2:$H$5000,7,FALSE)-E12,"") | H13: =IFERROR(VLOOKUP($A13,Results_30d_Deltas!$A$2:$H$5000,6,FALSE),"") | K13: =IF(B13=C13,"YES","NO") | IJ13: ez_manage.py:4699 top() | IK13: v12_quick_engine.py:1818 x7
A14: E_1_WT_EXIT_USE_DELTA_ENABLED | B14: True | E14: =IF(F14="",E13,IF(F14>0,E13+F14,E13)) | F14: =IFERROR(VLOOKUP($A14&"="&$B14,Results_30d_Deltas!$A$2:$H$5000,5,FALSE),"") | G14: =IFERROR(VLOOKUP($A14,Results_30d_Deltas!$A$2:$H$5000,7,FALSE)-E13,"") | H14: =IFERROR(VLOOKUP($A14,Results_30d_Deltas!$A$2:$H$5000,6,FALSE),"") | K14: =IF(B14=C14,"YES","NO") | IJ14: ez_manage.py:4699 top() | IK14: v12_quick_engine.py:1818 x7
A15: E_3_USE_WT_STRUCTURE_EXIT_MODE | B15: 0 | E15: =IF(F15="",E14,IF(F15>0,E14+F15,E14)) | F15: =IFERROR(VLOOKUP($A15&"="&$B15,Results_30d_Deltas!$A$2:$H$5000,5,FALSE),"") | G15: =IFERROR(VLOOKUP($A15,Results_30d_Deltas!$A$2:$H$5000,7,FALSE)-E14,"") | H15: =IFERROR(VLOOKUP($A15,Results_30d_Deltas!$A$2:$H$5000,6,FALSE),"") | K15: =IF(B15=C15,"YES","NO") | IJ15: ez_manage.py:4700 top() | IK15: v12_quick_engine.py:1819 x8
... A82: WT_CROSS_EXIT_REQUIRE_15M_CONFIRM | B82: 2.0 | E82: =IF(F82="",E81,IF(F82>0,E81+F82,E81)) | F82: =IFERROR(VLOOKUP($A82&"="&$B82,Results_30d_Deltas!$A$2:$H$5000,5,FALSE),"") | G82: =IFERROR(VLOOKUP($A82,Results_30d_Deltas!$A$2:$H$5000,7,FALSE)-E81,"") | H82: =IFERROR(VLOOKUP($A82,Results_30d_Deltas!$A$2:$H$5000,6,FALSE),"") | K82: =IF(B82=C82,"YES","NO") | IJ82: ez_manage.py:5904 top() | IK82: v12_quick_engine.py:3725 x5

Sheet REENTRY_WINDOWED
A1: 06 REENTRY_WINDOWED - 68 bases -> 249 rows - 231 per-row FULLY CONNECTED
A2: Switch | B2: default | C2: override | D2: Family | E2: =MAX('EXIT_VELOCITY'!E$2:E$5000) | F2: VECTOR_DELTA | G2: LIVE_DELTA | H2: LIVE_SHARPE | I2: REAL_COMPLETE | J2: PER_ROW_FILTERS | K2: is_default (backup if bold lost) | L2: ATR_TRAIL_FILTER_TF=OFF | M2: ATR_TRAIL_FILTER_TF=D | N2: ATR_TRAIL_FILTER_TF=4h | O2: ATR_TRAIL_FILTER_TF=1h | P2: ATR_TRAIL_FILTER_TF=15m | Q2: BAR_PATTERNS_FILTER_TF=OFF | R2: BAR_PATTERNS_FILTER_TF=D | S2: BAR_PATTERNS_FILTER_TF=4h | T2: BAR_PATTERNS_FILTER_TF=1h | U2: BAR_PATTERNS_FILTER_TF=15m | V2: BB_PULLBACK_GATE_FILTER_TF=OFF | W2: BB_PULLBACK_GATE_FILTER_TF=D | X2: BB_PULLBACK_GATE_FILTER_TF=4h | Y2: BB_PULLBACK_GATE_FILTER_TF=1h | Z2: BB_PULLBACK_GATE_FILTER_TF=15m | AA2: BB_RECOVERY_ENTRY_FILTER_TF=OFF | AB2: BB_RECOVERY_ENTRY_FILTER_TF=D | AC2: BB_RECOVERY_ENTRY_FILTER_TF=4h | AD2: BB_RECOVERY_ENTRY_FILTER_TF=1h | AE2: BB_RECOVERY_ENTRY_FILTER_TF=15m | AF2: BB_RECOVERY_FILTER_TF=OFF | AG2: BB_RECOVERY_FILTER_TF=D | AH2: BB_RECOVERY_FILTER_TF=4h | AI2: BB_RECOVERY_FILTER_TF=1h | AJ2: BB_RECOVERY_FILTER_TF=15m | AK2: BREAKEVEN_GAIN_EROSION_FILTER_TF=OFF | AL2: BREAKEVEN_GAIN_EROSION_FILTER_TF=D | AM2: BREAKEVEN_GAIN_EROSION_FILTER_TF=4h | AN2: BREAKEVEN_GAIN_EROSION_FILTER_TF=1h | AO2: BREAKEVEN_GAIN_EROSION_FILTER_TF=15m | AP2: BREAKOUT_RETEST_FILTER_TF=OFF | AQ2: BREAKOUT_RETEST_FILTER_TF=D | AR2: BREAKOUT_RETEST_FILTER_TF=4h | AS2: BREAKOUT_RETEST_FILTER_TF=1h | AT2: BREAKOUT_RETEST_FILTER_TF=15m | AU2: BT_WT_CROSS_LADDER_FILTER_TF=OFF | AV2: BT_WT_CROSS_LADDER_FILTER_TF=D | AW2: BT_WT_CROSS_LADDER_FILTER_TF=4h | AX2: BT_WT_CROSS_LADDER_FILTER_TF=1h | AY2: BT_WT_CROSS_LADDER_FILTER_TF=15m | AZ2: CANDLE_PATTERN_STOPS_FILTER_TF=OFF | BA2: CANDLE_PATTERN_STOPS_FILTER_TF=D | BB2: CANDLE_PATTERN_STOPS_FILTER_TF=4h | BC2: CANDLE_PATTERN_STOPS_FILTER_TF=1h | BD2: CANDLE_PATTERN_STOPS_FILTER_TF=15m | BE2: CIRCUIT_SHARPE_GATES_FILTER_TF=OFF | BF2: CIRCUIT_SHARPE_GATES_FILTER_TF=D | BG2: CIRCUIT_SHARPE_GATES_FILTER_TF=4h | BH2: CIRCUIT_SHARPE_GATES_FILTER_TF=1h | BI2: CIRCUIT_SHARPE_GATES_FILTER_TF=15m | BJ2: DC_BREACH_REDUCE_FILTER_TF=OFF | BK2: DC_BREACH_REDUCE_FILTER_TF=D | BL2: DC_BREACH_REDUCE_FILTER_TF=4h | BM2: DC_BREACH_REDUCE_FILTER_TF=1h | BN2: DC_BREACH_REDUCE_FILTER_TF=15m | BO2: DC_BREAK_FILTER_TF=OFF | BP2: DC_BREAK_FILTER_TF=D | BQ2: DC_BREAK_FILTER_TF=4h | BR2: DC_BREAK_FILTER_TF=1h | BS2: DC_BREAK_FILTER_TF=15m | BT2: DC_MOMENTUM_BOTA_SCORER_FILTER_TF=OFF | BU2: DC_MOMENTUM_BOTA_SCORER_FILTER_TF=D | BV2: DC_MOMENTUM_BOTA_SCORER_FILTER_TF=4h | BW2: DC_MOMENTUM_BOTA_SCORER_FILTER_TF=1h | BX2: DC_MOMENTUM_BOTA_SCORER_FILTER_TF=15m | BY2: DELTA_ENGINE_FILTER_TF=OFF | BZ2: DELTA_ENGINE_FILTER_TF=D | CA2: DELTA_ENGINE_FILTER_TF=4h | CB2: DELTA_ENGINE_FILTER_TF=1h | CC2: DELTA_ENGINE_FILTER_TF=15m | CD2: EMA_9_21_FILTER_FILTER_TF=OFF | CE2: EMA_9_21_FILTER_FILTER_TF=D | CF2: EMA_9_21_FILTER_FILTER_TF=4h | CG2: EMA_9_21_FILTER_FILTER_TF=1h | CH2: EMA_9_21_FILTER_FILTER_TF=15m | CI2: EMA_BLANKET_FILTER_FILTER_TF=OFF | CJ2: EMA_BLANKET_FILTER_FILTER_TF=D | CK2: EMA_BLANKET_FILTER_FILTER_TF=4h | CL2: EMA_BLANKET_FILTER_FILTER_TF=1h | CM2: EMA_BLANKET_FILTER_FILTER_TF=15m | CN2: EMERGENCY_BRAKE_FILTER_TF=OFF | CO2: EMERGENCY_BRAKE_FILTER_TF=D | CP2: EMERGENCY_BRAKE_FILTER_TF=4h | CQ2: EMERGENCY_BRAKE_FILTER_TF=1h | CR2: EMERGENCY_BRAKE_FILTER_TF=15m | CS2: EXIT_R1_R2_FILTER_TF=OFF | CT2: EXIT_R1_R2_FILTER_TF=D | CU2: EXIT_R1_R2_FILTER_TF=4h | CV2: EXIT_R1_R2_FILTER_TF=1h | CW2: EXIT_R1_R2_FILTER_TF=15m | CX2: EXIT_TIGHT_BREAKOUT_SCORER_FILTER_TF=OFF | CY2: EXIT_TIGHT_BREAKOUT_SCORER_FILTER_TF=D | CZ2: EXIT_TIGHT_BREAKOUT_SCORER_FILTER_TF=4h | DA2: EXIT_TIGHT_BREAKOUT_SCORER_FILTER_TF=1h | DB2: EXIT_TIGHT_BREAKOUT_SCORER_FILTER_TF=15m | DC2: EXIT_TOP_FADE_FILTER_TF=OFF | DD2: EXIT_TOP_FADE_FILTER_TF=D | DE2: EXIT_TOP_FADE_FILTER_TF=4h | DF2: EXIT_TOP_FADE_FILTER_TF=1h | DG2: EXIT_TOP_FADE_FILTER_TF=15m | DH2: EXIT_TO_REDUCE_ADAPTER_FILTER_TF=OFF | DI2: EXIT_TO_REDUCE_ADAPTER_FILTER_TF=D | DJ2: EXIT_TO_REDUCE_ADAPTER_FILTER_TF=4h | DK2: EXIT_TO_REDUCE_ADAPTER_FILTER_TF=1h | DL2: EXIT_TO_REDUCE_ADAPTER_FILTER_TF=15m | DM2: FAST_RISER_FILTER_TF=OFF | DN2: FAST_RISER_FILTER_TF=D | DO2: FAST_RISER_FILTER_TF=4h | DP2: FAST_RISER_FILTER_TF=1h | DQ2: FAST_RISER_FILTER_TF=15m | DR2: FH_MOMENTUM_FILTER_TF=OFF | DS2: FH_MOMENTUM_FILTER_TF=D | DT2: FH_MOMENTUM_FILTER_TF=4h | DU2: FH_MOMENTUM_FILTER_TF=1h | DV2: FH_MOMENTUM_FILTER_TF=15m | DW2: FIRST_OPEN_THROTTLE_FILTER_TF=OFF | DX2: FIRST_OPEN_THROTTLE_FILTER_TF=D | DY2: FIRST_OPEN_THROTTLE_FILTER_TF=4h | DZ2: FIRST_OPEN_THROTTLE_FILTER_TF=1h | EA2: FIRST_OPEN_THROTTLE_FILTER_TF=15m | EB2: FROZEN_STOP_FILTER_TF=OFF | EC2: FROZEN_STOP_FILTER_TF=D | ED2: FROZEN_STOP_FILTER_TF=4h | EE2: FROZEN_STOP_FILTER_TF=1h | EF2: FROZEN_STOP_FILTER_TF=15m | EG2: GOLDEN_RULE_ENFORCE_FILTER_TF=OFF | EH2: GOLDEN_RULE_ENFORCE_FILTER_TF=D | EI2: GOLDEN_RULE_ENFORCE_FILTER_TF=4h | EJ2: GOLDEN_RULE_ENFORCE_FILTER_TF=1h | EK2: GOLDEN_RULE_ENFORCE_FILTER_TF=15m | EL2: GOLDEN_RULE_HTF_VOTE_FILTER_TF=OFF | EM2: GOLDEN_RULE_HTF_VOTE_FILTER_TF=D | EN2: GOLDEN_RULE_HTF_VOTE_FILTER_TF=4h | EO2: GOLDEN_RULE_HTF_VOTE_FILTER_TF=1h | EP2: GOLDEN_RULE_HTF_VOTE_FILTER_TF=15m | EQ2: GR_FILTER_VEC_FILTER_TF=OFF | ER2: GR_FILTER_VEC_FILTER_TF=D | ES2: GR_FILTER_VEC_FILTER_TF=4h | ET2: GR_FILTER_VEC_FILTER_TF=1h | EU2: GR_FILTER_VEC_FILTER_TF=15m | EV2: GR_V5_STATE_FILTER_TF=OFF | EW2: GR_V5_STATE_FILTER_TF=D | EX2: GR_V5_STATE_FILTER_TF=4h | EY2: GR_V5_STATE_FILTER_TF=1h | EZ2: GR_V5_STATE_FILTER_TF=15m | FA2: HAIKU_WINNER_FILTER_TF=OFF | FB2: HAIKU_WINNER_FILTER_TF=D | FC2: HAIKU_WINNER_FILTER_TF=4h | FD2: HAIKU_WINNER_FILTER_TF=1h | FE2: HAIKU_WINNER_FILTER_TF=15m | FF2: LH_HL_FILTER_TF_REQ=2 | FG2: LH_HL_FILTER_TF_REQ=2_ALT | FH2: LIVE_ENTRY_ENGINE_FILTER_TF=OFF | FI2: LIVE_ENTRY_ENGINE_FILTER_TF=D | FJ2: LIVE_ENTRY_ENGINE_FILTER_TF=4h | FK2: LIVE_ENTRY_ENGINE_FILTER_TF=1h | FL2: LIVE_ENTRY_ENGINE_FILTER_TF=15m | FM2: LIVE_ONLY_SIGNALS_BATCH5_FILTER_TF=OFF | FN2: LIVE_ONLY_SIGNALS_BATCH5_FILTER_TF=D | FO2: LIVE_ONLY_SIGNALS_BATCH5_FILTER_TF=4h | FP2: LIVE_ONLY_SIGNALS_BATCH5_FILTER_TF=1h | FQ2: LIVE_ONLY_SIGNALS_BATCH5_FILTER_TF=15m | FR2: MANDATORY_REENTRY_WT_FILTER_TF_MODE=15m_only | FS2: MANDATORY_REENTRY_WT_FILTER_TF_MODE=15m_only_ALT | FT2: MOM3_FILTER_TF=OFF | FU2: MOM3_FILTER_TF=D | FV2: MOM3_FILTER_TF=4h | FW2: MOM3_FILTER_TF=1h | FX2: MOM3_FILTER_TF=15m | FY2: MOMENTUM_BREAKOUT_FILTER_TF=OFF | FZ2: MOMENTUM_BREAKOUT_FILTER_TF=D | GA2: MOMENTUM_BREAKOUT_FILTER_TF=4h | GB2: MOMENTUM_BREAKOUT_FILTER_TF=1h | GC2: MOMENTUM_BREAKOUT_FILTER_TF=15m | GD2: MTF_ARMED_ENTRIES_FILTER_TF=OFF | GE2: MTF_ARMED_ENTRIES_FILTER_TF=D | GF2: MTF_ARMED_ENTRIES_FILTER_TF=4h | GG2: MTF_ARMED_ENTRIES_FILTER_TF=1h | GH2: MTF_ARMED_ENTRIES_FILTER_TF=15m | GI2: MTF_ATR_TRAIL_FILTER_TF=OFF | GJ2: MTF_ATR_TRAIL_FILTER_TF=D | GK2: MTF_ATR_TRAIL_FILTER_TF=4h | GL2: MTF_ATR_TRAIL_FILTER_TF=1h | GM2: MTF_ATR_TRAIL_FILTER_TF=15m | GN2: MTF_DC_REJECT_FILTER_TF=OFF | GO2: MTF_DC_REJECT_FILTER_TF=D | GP2: MTF_DC_REJECT_FILTER_TF=4h | GQ2: MTF_DC_REJECT_FILTER_TF=1h | GR2: MTF_DC_REJECT_FILTER_TF=15m | GS2: NEWBORN_LOSS_KILL_FILTER_TF=OFF | GT2: NEWBORN_LOSS_KILL_FILTER_TF=D | GU2: NEWBORN_LOSS_KILL_FILTER_TF=4h | GV2: NEWBORN_LOSS_KILL_FILTER_TF=1h | GW2: NEWBORN_LOSS_KILL_FILTER_TF=15m | GX2: NEWBORN_PROTECT_FILTER_TF=OFF | GY2: NEWBORN_PROTECT_FILTER_TF=D | GZ2: NEWBORN_PROTECT_FILTER_TF=4h | HA2: NEWBORN_PROTECT_FILTER_TF=1h | HB2: NEWBORN_PROTECT_FILTER_TF=15m | HC2: NOLOSS_BYPASS_WT5OF5_FILTER_TF=OFF | HD2: NOLOSS_BYPASS_WT5OF5_FILTER_TF=D | HE2: NOLOSS_BYPASS_WT5OF5_FILTER_TF=4h | HF2: NOLOSS_BYPASS_WT5OF5_FILTER_TF=1h | HG2: NOLOSS_BYPASS_WT5OF5_FILTER_TF=15m | HH2: OPEN_INTENT_SIZE_GATES_FILTER_TF=OFF | HI2: OPEN_INTENT_SIZE_GATES_FILTER_TF=D | HJ2: OPEN_INTENT_SIZE_GATES_FILTER_TF=4h | HK2: OPEN_INTENT_SIZE_GATES_FILTER_TF=1h | HL2: OPEN_INTENT_SIZE_GATES_FILTER_TF=15m | HM2: PARTIAL_PROFIT_LOCK_V2_FILTER_TF=OFF | HN2: PARTIAL_PROFIT_LOCK_V2_FILTER_TF=D | HO2: PARTIAL_PROFIT_LOCK_V2_FILTER_TF=4h | HP2: PARTIAL_PROFIT_LOCK_V2_FILTER_TF=1h | HQ2: PARTIAL_PROFIT_LOCK_V2_FILTER_TF=15m | HR2: PEAK_GIVEBACK_BE_EROSION_FILTER_TF=OFF | HS2: PEAK_GIVEBACK_BE_EROSION_FILTER_TF=D | HT2: PEAK_GIVEBACK_BE_EROSION_FILTER_TF=4h | HU2: PEAK_GIVEBACK_BE_EROSION_FILTER_TF=1h | HV2: PEAK_GIVEBACK_BE_EROSION_FILTER_TF=15m | HW2: WT_15M_BOUNCE_BB_MAX=0.95 | HX2: WT_15M_BOUNCE_BB_MAX=0.9 | HY2: WT_15M_BOUNCE_BB_MAX=0.8 | HZ2: WT_15M_BOUNCE_BB_MIN=0.05 | IA2: WT_15M_BOUNCE_BB_MIN=0.1 | IB2: WT_15M_BOUNCE_BB_MIN=0.2 | IC2: WT_15M_BOUNCE_HIGH_1H_GT_PREV=True | ID2: WT_15M_BOUNCE_HIGH_1H_GT_PREV=False | IE2: WT_15M_BOUNCE_LOW_1H_GT_PREV=True | IF2: WT_15M_BOUNCE_LOW_1H_GT_PREV=False | IG2: WT_15M_BOUNCE_REL_VOL_GT_1=True | IH2: WT_15M_BOUNCE_REL_VOL_GT_1=False | II2: Live Location | IJ2: Vec Hook | IK2: Type | IL2: Correct Options
A3: GUARANTEED_REENTRY_K_FAVORABLE_HIGH | B3: 35.0 | E3: =MAX('EXIT_VELOCITY'!E:E) | F3: =IFERROR(VLOOKUP($A3&"="&$B3,Results_30d_Deltas!$A$2:$H$5000,5,FALSE),"") | G3: =IFERROR(VLOOKUP($A3,Results_30d_Deltas!$A$2:$H$5000,7,FALSE)-E3,"") | H3: =IFERROR(VLOOKUP($A3,Results_30d_Deltas!$A$2:$H$5000,6,FALSE),"") | K3: =IF(B3=C3,"YES","NO") | IJ3: ez_manage.py:4774 top() | IK3: v12_quick_engine.py:1941 x4
A4: GUARANTEED_REENTRY_K_FAVORABLE_HIGH | B4: 52.5 | E4: =IF(F4="",E3,IF(F4>0,E3+F4,E3)) | F4: =IFERROR(VLOOKUP($A4&"="&$B4,Results_30d_Deltas!$A$2:$H$5000,5,FALSE),"") | G4: =IFERROR(VLOOKUP($A4,Results_30d_Deltas!$A$2:$H$5000,7,FALSE)-E3,"") | H4: =IFERROR(VLOOKUP($A4,Results_30d_Deltas!$A$2:$H$5000,6,FALSE),"") | K4: =IF(B4=C4,"YES","NO") | IJ4: ez_manage.py:4774 top() | IK4: v12_quick_engine.py:1941 x4
A5: GUARANTEED_REENTRY_K_FAVORABLE_HIGH | B5: 70.0 | E5: =IF(F5="",E4,IF(F5>0,E4+F5,E4)) | F5: =IFERROR(VLOOKUP($A5&"="&$B5,Results_30d_Deltas!$A$2:$H$5000,5,FALSE),"") | G5: =IFERROR(VLOOKUP($A5,Results_30d_Deltas!$A$2:$H$5000,7,FALSE)-E4,"") | H5: =IFERROR(VLOOKUP($A5,Results_30d_Deltas!$A$2:$H$5000,6,FALSE),"") | K5: =IF(B5=C5,"YES","NO") | IJ5: ez_manage.py:4774 top() | IK5: v12_quick_engine.py:1941 x4
A6: GUARANTEED_REENTRY_K_FAVORABLE_HIGH | B6: 87.5 | E6: =IF(F6="",E5,IF(F6>0,E5+F6,E5)) | F6: =IFERROR(VLOOKUP($A6&"="&$B6,Results_30d_Deltas!$A$2:$H$5000,5,FALSE),"") | G6: =IFERROR(VLOOKUP($A6,Results_30d_Deltas!$A$2:$H$5000,7,FALSE)-E5,"") | H6: =IFERROR(VLOOKUP($A6,Results_30d_Deltas!$A$2:$H$5000,6,FALSE),"") | K6: =IF(B6=C6,"YES","NO") | IJ6: ez_manage.py:4774 top() | IK6: v12_quick_engine.py:1941 x4
A7: GUARANTEED_REENTRY_K_FAVORABLE_HIGH | B7: 105.0 | E7: =IF(F7="",E6,IF(F7>0,E6+F7,E6)) | F7: =IFERROR(VLOOKUP($A7&"="&$B7,Results_30d_Deltas!$A$2:$H$5000,5,FALSE),"") | G7: =IFERROR(VLOOKUP($A7,Results_30d_Deltas!$A$2:$H$5000,7,FALSE)-E6,"") | H7: =IFERROR(VLOOKUP($A7,Results_30d_Deltas!$A$2:$H$5000,6,FALSE),"") | K7: =IF(B7=C7,"YES","NO") | IJ7: ez_manage.py:4774 top() | IK7: v12_quick_engine.py:1941 x4
A8: GUARANTEED_REENTRY_K_FAVORABLE_LOW | B8: 15.0 | E8: =IF(F8="",E7,IF(F8>0,E7+F8,E7)) | F8: =IFERROR(VLOOKUP($A8&"="&$B8,Results_30d_Deltas!$A$2:$H$5000,5,FALSE),"") | G8: =IFERROR(VLOOKUP($A8,Results_30d_Deltas!$A$2:$H$5000,7,FALSE)-E7,"") | H8: =IFERROR(VLOOKUP($A8,Results_30d_Deltas!$A$2:$H$5000,6,FALSE),"") | K8: =IF(B8=C8,"YES","NO") | IJ8: ez_manage.py:4775 top() | IK8: v12_quick_engine.py:1942 x4
A9: GUARANTEED_REENTRY_K_FAVORABLE_LOW | B9: 22.5 | E9: =IF(F9="",E8,IF(F9>0,E8+F9,E8)) | F9: =IFERROR(VLOOKUP($A9&"="&$B9,Results_30d_Deltas!$A$2:$H$5000,5,FALSE),"") | G9: =IFERROR(VLOOKUP($A9,Results_30d_Deltas!$A$2:$H$5000,7,FALSE)-E8,"") | H9: =IFERROR(VLOOKUP($A9,Results_30d_Deltas!$A$2:$H$5000,6,FALSE),"") | K9: =IF(B9=C9,"YES","NO") | IJ9: ez_manage.py:4775 top() | IK9: v12_quick_engine.py:1942 x4
A10: GUARANTEED_REENTRY_K_FAVORABLE_LOW | B10: 30.0 | E10: =IF(F10="",E9,IF(F10>0,E9+F10,E9)) | F10: =IFERROR(VLOOKUP($A10&"="&$B10,Results_30d_Deltas!$A$2:$H$5000,5,FALSE),"") | G10: =IFERROR(VLOOKUP($A10,Results_30d_Deltas!$A$2:$H$5000,7,FALSE)-E9,"") | H10: =IFERROR(VLOOKUP($A10,Results_30d_Deltas!$A$2:$H$5000,6,FALSE),"") | K10: =IF(B10=C10,"YES","NO") | IJ10: ez_manage.py:4775 top() | IK10: v12_quick_engine.py:1942 x4
A11: GUARANTEED_REENTRY_K_FAVORABLE_LOW | B11: 37.5 | E11: =IF(F11="",E10,IF(F11>0,E10+F11,E10)) | F11: =IFERROR(VLOOKUP($A11&"="&$B11,Results_30d_Deltas!$A$2:$H$5000,5,FALSE),"") | G11: =IFERROR(VLOOKUP($A11,Results_30d_Deltas!$A$2:$H$5000,7,FALSE)-E10,"") | H11: =IFERROR(VLOOKUP($A11,Results_30d_Deltas!$A$2:$H$5000,6,FALSE),"") | K11: =IF(B11=C11,"YES","NO") | IJ11: ez_manage.py:4775 top() | IK11: v12_quick_engine.py:1942 x4
A12: GUARANTEED_REENTRY_K_FAVORABLE_LOW | B12: 45.0 | E12: =IF(F12="",E11,IF(F12>0,E11+F12,E11)) | F12: =IFERROR(VLOOKUP($A12&"="&$B12,Results_30d_Deltas!$A$2:$H$5000,5,FALSE),"") | G12: =IFERROR(VLOOKUP($A12,Results_30d_Deltas!$A$2:$H$5000,7,FALSE)-E11,"") | H12: =IFERROR(VLOOKUP($A12,Results_30d_Deltas!$A$2:$H$5000,6,FALSE),"") | K12: =IF(B12=C12,"YES","NO") | IJ12: ez_manage.py:4775 top() | IK12: v12_quick_engine.py:1942 x4
A13: BOUNCE_REENTRY_ENABLED | B13: False | E13: =IF(F13="",E12,IF(F13>0,E12+F13,E12)) | F13: =IFERROR(VLOOKUP($A13&"="&$B13,Results_30d_Deltas!$A$2:$H$5000,5,FALSE),"") | G13: =IFERROR(VLOOKUP($A13,Results_30d_Deltas!$A$2:$H$5000,7,FALSE)-E12,"") | H13: =IFERROR(VLOOKUP($A13,Results_30d_Deltas!$A$2:$H$5000,6,FALSE),"") | K13: =IF(B13=C13,"YES","NO") | IJ13: ez_manage.py:2985 top() | IK13: v12_quick_engine.py:315 x14
A14: BOUNCE_REENTRY_ENABLED | B14: True | E14: =IF(F14="",E13,IF(F14>0,E13+F14,E13)) | F14: =IFERROR(VLOOKUP($A14&"="&$B14,Results_30d_Deltas!$A$2:$H$5000,5,FALSE),"") | G14: =IFERROR(VLOOKUP($A14,Results_30d_Deltas!$A$2:$H$5000,7,FALSE)-E13,"") | H14: =IFERROR(VLOOKUP($A14,Results_30d_Deltas!$A$2:$H$5000,6,FALSE),"") | K14: =IF(B14=C14,"YES","NO") | IJ14: ez_manage.py:2985 top() | IK14: v12_quick_engine.py:315 x14
A15: DELTA_EXIT_MANDATORY_REENTRY_ENABLED | B15: False | E15: =IF(F15="",E14,IF(F15>0,E14+F15,E14)) | F15: =IFERROR(VLOOKUP($A15&"="&$B15,Results_30d_Deltas!$A$2:$H$5000,5,FALSE),"") | G15: =IFERROR(VLOOKUP($A15,Results_30d_Deltas!$A$2:$H$5000,7,FALSE)-E14,"") | H15: =IFERROR(VLOOKUP($A15,Results_30d_Deltas!$A$2:$H$5000,6,FALSE),"") | K15: =IF(B15=C15,"YES","NO") | IJ15: ez_manage.py:5975 top() | IK15: v12_quick_engine.py:4235 x4
... A251: VEC_REENTRY_DC4_EXITPRICE_ENABLED | B251: True | E251: =IF(F251="",E250,IF(F251>0,E250+F251,E250)) | F251: =IFERROR(VLOOKUP($A251&"="&$B251,Results_30d_Deltas!$A$2:$H$5000,5,FALSE),"") | G251: =IFERROR(VLOOKUP($A251,Results_30d_Deltas!$A$2:$H$5000,7,FALSE)-E250,"") | H251: =IFERROR(VLOOKUP($A251,Results_30d_Deltas!$A$2:$H$5000,6,FALSE),"") | K251: =IF(B251=C251,"YES","NO") | IJ251: ez_manage.py:6075 top() | IK251: v12_quick_engine.py:4287 x4

Sheet REENTRY_ADAPTIVE
A1: 07 REENTRY_ADAPTIVE - 10 bases -> 38 rows - 231 per-row FULLY CONNECTED
A2: Switch | B2: default | C2: override | D2: Family | E2: =MAX('REENTRY_WINDOWED'!E$2:E$5000) | F2: VECTOR_DELTA | G2: LIVE_DELTA | H2: LIVE_SHARPE | I2: REAL_COMPLETE | J2: PER_ROW_FILTERS | K2: is_default (backup if bold lost) | L2: ATR_TRAIL_FILTER_TF=OFF | M2: ATR_TRAIL_FILTER_TF=D | N2: ATR_TRAIL_FILTER_TF=4h | O2: ATR_TRAIL_FILTER_TF=1h | P2: ATR_TRAIL_FILTER_TF=15m | Q2: BAR_PATTERNS_FILTER_TF=OFF | R2: BAR_PATTERNS_FILTER_TF=D | S2: BAR_PATTERNS_FILTER_TF=4h | T2: BAR_PATTERNS_FILTER_TF=1h | U2: BAR_PATTERNS_FILTER_TF=15m | V2: BB_PULLBACK_GATE_FILTER_TF=OFF | W2: BB_PULLBACK_GATE_FILTER_TF=D | X2: BB_PULLBACK_GATE_FILTER_TF=4h | Y2: BB_PULLBACK_GATE_FILTER_TF=1h | Z2: BB_PULLBACK_GATE_FILTER_TF=15m | AA2: BB_RECOVERY_ENTRY_FILTER_TF=OFF | AB2: BB_RECOVERY_ENTRY_FILTER_TF=D | AC2: BB_RECOVERY_ENTRY_FILTER_TF=4h | AD2: BB_RECOVERY_ENTRY_FILTER_TF=1h | AE2: BB_RECOVERY_ENTRY_FILTER_TF=15m | AF2: BB_RECOVERY_FILTER_TF=OFF | AG2: BB_RECOVERY_FILTER_TF=D | AH2: BB_RECOVERY_FILTER_TF=4h | AI2: BB_RECOVERY_FILTER_TF=1h | AJ2: BB_RECOVERY_FILTER_TF=15m | AK2: BREAKEVEN_GAIN_EROSION_FILTER_TF=OFF | AL2: BREAKEVEN_GAIN_EROSION_FILTER_TF=D | AM2: BREAKEVEN_GAIN_EROSION_FILTER_TF=4h | AN2: BREAKEVEN_GAIN_EROSION_FILTER_TF=1h | AO2: BREAKEVEN_GAIN_EROSION_FILTER_TF=15m | AP2: BREAKOUT_RETEST_FILTER_TF=OFF | AQ2: BREAKOUT_RETEST_FILTER_TF=D | AR2: BREAKOUT_RETEST_FILTER_TF=4h | AS2: BREAKOUT_RETEST_FILTER_TF=1h | AT2: BREAKOUT_RETEST_FILTER_TF=15m | AU2: BT_WT_CROSS_LADDER_FILTER_TF=OFF | AV2: BT_WT_CROSS_LADDER_FILTER_TF=D | AW2: BT_WT_CROSS_LADDER_FILTER_TF=4h | AX2: BT_WT_CROSS_LADDER_FILTER_TF=1h | AY2: BT_WT_CROSS_LADDER_FILTER_TF=15m | AZ2: CANDLE_PATTERN_STOPS_FILTER_TF=OFF | BA2: CANDLE_PATTERN_STOPS_FILTER_TF=D | BB2: CANDLE_PATTERN_STOPS_FILTER_TF=4h | BC2: CANDLE_PATTERN_STOPS_FILTER_TF=1h | BD2: CANDLE_PATTERN_STOPS_FILTER_TF=15m | BE2: CIRCUIT_SHARPE_GATES_FILTER_TF=OFF | BF2: CIRCUIT_SHARPE_GATES_FILTER_TF=D | BG2: CIRCUIT_SHARPE_GATES_FILTER_TF=4h | BH2: CIRCUIT_SHARPE_GATES_FILTER_TF=1h | BI2: CIRCUIT_SHARPE_GATES_FILTER_TF=15m | BJ2: DC_BREACH_REDUCE_FILTER_TF=OFF | BK2: DC_BREACH_REDUCE_FILTER_TF=D | BL2: DC_BREACH_REDUCE_FILTER_TF=4h | BM2: DC_BREACH_REDUCE_FILTER_TF=1h | BN2: DC_BREACH_REDUCE_FILTER_TF=15m | BO2: DC_BREAK_FILTER_TF=OFF | BP2: DC_BREAK_FILTER_TF=D | BQ2: DC_BREAK_FILTER_TF=4h | BR2: DC_BREAK_FILTER_TF=1h | BS2: DC_BREAK_FILTER_TF=15m | BT2: DC_MOMENTUM_BOTA_SCORER_FILTER_TF=OFF | BU2: DC_MOMENTUM_BOTA_SCORER_FILTER_TF=D | BV2: DC_MOMENTUM_BOTA_SCORER_FILTER_TF=4h | BW2: DC_MOMENTUM_BOTA_SCORER_FILTER_TF=1h | BX2: DC_MOMENTUM_BOTA_SCORER_FILTER_TF=15m | BY2: DELTA_ENGINE_FILTER_TF=OFF | BZ2: DELTA_ENGINE_FILTER_TF=D | CA2: DELTA_ENGINE_FILTER_TF=4h | CB2: DELTA_ENGINE_FILTER_TF=1h | CC2: DELTA_ENGINE_FILTER_TF=15m | CD2: EMA_9_21_FILTER_FILTER_TF=OFF | CE2: EMA_9_21_FILTER_FILTER_TF=D | CF2: EMA_9_21_FILTER_FILTER_TF=4h | CG2: EMA_9_21_FILTER_FILTER_TF=1h | CH2: EMA_9_21_FILTER_FILTER_TF=15m | CI2: EMA_BLANKET_FILTER_FILTER_TF=OFF | CJ2: EMA_BLANKET_FILTER_FILTER_TF=D | CK2: EMA_BLANKET_FILTER_FILTER_TF=4h | CL2: EMA_BLANKET_FILTER_FILTER_TF=1h | CM2: EMA_BLANKET_FILTER_FILTER_TF=15m | CN2: EMERGENCY_BRAKE_FILTER_TF=OFF | CO2: EMERGENCY_BRAKE_FILTER_TF=D | CP2: EMERGENCY_BRAKE_FILTER_TF=4h | CQ2: EMERGENCY_BRAKE_FILTER_TF=1h | CR2: EMERGENCY_BRAKE_FILTER_TF=15m | CS2: EXIT_R1_R2_FILTER_TF=OFF | CT2: EXIT_R1_R2_FILTER_TF=D | CU2: EXIT_R1_R2_FILTER_TF=4h | CV2: EXIT_R1_R2_FILTER_TF=1h | CW2: EXIT_R1_R2_FILTER_TF=15m | CX2: EXIT_TIGHT_BREAKOUT_SCORER_FILTER_TF=OFF | CY2: EXIT_TIGHT_BREAKOUT_SCORER_FILTER_TF=D | CZ2: EXIT_TIGHT_BREAKOUT_SCORER_FILTER_TF=4h | DA2: EXIT_TIGHT_BREAKOUT_SCORER_FILTER_TF=1h | DB2: EXIT_TIGHT_BREAKOUT_SCORER_FILTER_TF=15m | DC2: EXIT_TOP_FADE_FILTER_TF=OFF | DD2: EXIT_TOP_FADE_FILTER_TF=D | DE2: EXIT_TOP_FADE_FILTER_TF=4h | DF2: EXIT_TOP_FADE_FILTER_TF=1h | DG2: EXIT_TOP_FADE_FILTER_TF=15m | DH2: EXIT_TO_REDUCE_ADAPTER_FILTER_TF=OFF | DI2: EXIT_TO_REDUCE_ADAPTER_FILTER_TF=D | DJ2: EXIT_TO_REDUCE_ADAPTER_FILTER_TF=4h | DK2: EXIT_TO_REDUCE_ADAPTER_FILTER_TF=1h | DL2: EXIT_TO_REDUCE_ADAPTER_FILTER_TF=15m | DM2: FAST_RISER_FILTER_TF=OFF | DN2: FAST_RISER_FILTER_TF=D | DO2: FAST_RISER_FILTER_TF=4h | DP2: FAST_RISER_FILTER_TF=1h | DQ2: FAST_RISER_FILTER_TF=15m | DR2: FH_MOMENTUM_FILTER_TF=OFF | DS2: FH_MOMENTUM_FILTER_TF=D | DT2: FH_MOMENTUM_FILTER_TF=4h | DU2: FH_MOMENTUM_FILTER_TF=1h | DV2: FH_MOMENTUM_FILTER_TF=15m | DW2: FIRST_OPEN_THROTTLE_FILTER_TF=OFF | DX2: FIRST_OPEN_THROTTLE_FILTER_TF=D | DY2: FIRST_OPEN_THROTTLE_FILTER_TF=4h | DZ2: FIRST_OPEN_THROTTLE_FILTER_TF=1h | EA2: FIRST_OPEN_THROTTLE_FILTER_TF=15m | EB2: FROZEN_STOP_FILTER_TF=OFF | EC2: FROZEN_STOP_FILTER_TF=D | ED2: FROZEN_STOP_FILTER_TF=4h | EE2: FROZEN_STOP_FILTER_TF=1h | EF2: FROZEN_STOP_FILTER_TF=15m | EG2: GOLDEN_RULE_ENFORCE_FILTER_TF=OFF | EH2: GOLDEN_RULE_ENFORCE_FILTER_TF=D | EI2: GOLDEN_RULE_ENFORCE_FILTER_TF=4h | EJ2: GOLDEN_RULE_ENFORCE_FILTER_TF=1h | EK2: GOLDEN_RULE_ENFORCE_FILTER_TF=15m | EL2: GOLDEN_RULE_HTF_VOTE_FILTER_TF=OFF | EM2: GOLDEN_RULE_HTF_VOTE_FILTER_TF=D | EN2: GOLDEN_RULE_HTF_VOTE_FILTER_TF=4h | EO2: GOLDEN_RULE_HTF_VOTE_FILTER_TF=1h | EP2: GOLDEN_RULE_HTF_VOTE_FILTER_TF=15m | EQ2: GR_FILTER_VEC_FILTER_TF=OFF | ER2: GR_FILTER_VEC_FILTER_TF=D | ES2: GR_FILTER_VEC_FILTER_TF=4h | ET2: GR_FILTER_VEC_FILTER_TF=1h | EU2: GR_FILTER_VEC_FILTER_TF=15m | EV2: GR_V5_STATE_FILTER_TF=OFF | EW2: GR_V5_STATE_FILTER_TF=D | EX2: GR_V5_STATE_FILTER_TF=4h | EY2: GR_V5_STATE_FILTER_TF=1h | EZ2: GR_V5_STATE_FILTER_TF=15m | FA2: HAIKU_WINNER_FILTER_TF=OFF | FB2: HAIKU_WINNER_FILTER_TF=D | FC2: HAIKU_WINNER_FILTER_TF=4h | FD2: HAIKU_WINNER_FILTER_TF=1h | FE2: HAIKU_WINNER_FILTER_TF=15m | FF2: LH_HL_FILTER_TF_REQ=2 | FG2: LH_HL_FILTER_TF_REQ=2_ALT | FH2: LIVE_ENTRY_ENGINE_FILTER_TF=OFF | FI2: LIVE_ENTRY_ENGINE_FILTER_TF=D | FJ2: LIVE_ENTRY_ENGINE_FILTER_TF=4h | FK2: LIVE_ENTRY_ENGINE_FILTER_TF=1h | FL2: LIVE_ENTRY_ENGINE_FILTER_TF=15m | FM2: LIVE_ONLY_SIGNALS_BATCH5_FILTER_TF=OFF | FN2: LIVE_ONLY_SIGNALS_BATCH5_FILTER_TF=D | FO2: LIVE_ONLY_SIGNALS_BATCH5_FILTER_TF=4h | FP2: LIVE_ONLY_SIGNALS_BATCH5_FILTER_TF=1h | FQ2: LIVE_ONLY_SIGNALS_BATCH5_FILTER_TF=15m | FR2: MANDATORY_REENTRY_WT_FILTER_TF_MODE=15m_only | FS2: MANDATORY_REENTRY_WT_FILTER_TF_MODE=15m_only_ALT | FT2: MOM3_FILTER_TF=OFF | FU2: MOM3_FILTER_TF=D | FV2: MOM3_FILTER_TF=4h | FW2: MOM3_FILTER_TF=1h | FX2: MOM3_FILTER_TF=15m | FY2: MOMENTUM_BREAKOUT_FILTER_TF=OFF | FZ2: MOMENTUM_BREAKOUT_FILTER_TF=D | GA2: MOMENTUM_BREAKOUT_FILTER_TF=4h | GB2: MOMENTUM_BREAKOUT_FILTER_TF=1h | GC2: MOMENTUM_BREAKOUT_FILTER_TF=15m | GD2: MTF_ARMED_ENTRIES_FILTER_TF=OFF | GE2: MTF_ARMED_ENTRIES_FILTER_TF=D | GF2: MTF_ARMED_ENTRIES_FILTER_TF=4h | GG2: MTF_ARMED_ENTRIES_FILTER_TF=1h | GH2: MTF_ARMED_ENTRIES_FILTER_TF=15m | GI2: MTF_ATR_TRAIL_FILTER_TF=OFF | GJ2: MTF_ATR_TRAIL_FILTER_TF=D | GK2: MTF_ATR_TRAIL_FILTER_TF=4h | GL2: MTF_ATR_TRAIL_FILTER_TF=1h | GM2: MTF_ATR_TRAIL_FILTER_TF=15m | GN2: MTF_DC_REJECT_FILTER_TF=OFF | GO2: MTF_DC_REJECT_FILTER_TF=D | GP2: MTF_DC_REJECT_FILTER_TF=4h | GQ2: MTF_DC_REJECT_FILTER_TF=1h | GR2: MTF_DC_REJECT_FILTER_TF=15m | GS2: NEWBORN_LOSS_KILL_FILTER_TF=OFF | GT2: NEWBORN_LOSS_KILL_FILTER_TF=D | GU2: NEWBORN_LOSS_KILL_FILTER_TF=4h | GV2: NEWBORN_LOSS_KILL_FILTER_TF=1h | GW2: NEWBORN_LOSS_KILL_FILTER_TF=15m | GX2: NEWBORN_PROTECT_FILTER_TF=OFF | GY2: NEWBORN_PROTECT_FILTER_TF=D | GZ2: NEWBORN_PROTECT_FILTER_TF=4h | HA2: NEWBORN_PROTECT_FILTER_TF=1h | HB2: NEWBORN_PROTECT_FILTER_TF=15m | HC2: NOLOSS_BYPASS_WT5OF5_FILTER_TF=OFF | HD2: NOLOSS_BYPASS_WT5OF5_FILTER_TF=D | HE2: NOLOSS_BYPASS_WT5OF5_FILTER_TF=4h | HF2: NOLOSS_BYPASS_WT5OF5_FILTER_TF=1h | HG2: NOLOSS_BYPASS_WT5OF5_FILTER_TF=15m | HH2: OPEN_INTENT_SIZE_GATES_FILTER_TF=OFF | HI2: OPEN_INTENT_SIZE_GATES_FILTER_TF=D | HJ2: OPEN_INTENT_SIZE_GATES_FILTER_TF=4h | HK2: OPEN_INTENT_SIZE_GATES_FILTER_TF=1h | HL2: OPEN_INTENT_SIZE_GATES_FILTER_TF=15m | HM2: PARTIAL_PROFIT_LOCK_V2_FILTER_TF=OFF | HN2: PARTIAL_PROFIT_LOCK_V2_FILTER_TF=D | HO2: PARTIAL_PROFIT_LOCK_V2_FILTER_TF=4h | HP2: PARTIAL_PROFIT_LOCK_V2_FILTER_TF=1h | HQ2: PARTIAL_PROFIT_LOCK_V2_FILTER_TF=15m | HR2: PEAK_GIVEBACK_BE_EROSION_FILTER_TF=OFF | HS2: PEAK_GIVEBACK_BE_EROSION_FILTER_TF=D | HT2: PEAK_GIVEBACK_BE_EROSION_FILTER_TF=4h | HU2: PEAK_GIVEBACK_BE_EROSION_FILTER_TF=1h | HV2: PEAK_GIVEBACK_BE_EROSION_FILTER_TF=15m | HW2: WT_15M_BOUNCE_BB_MAX=0.95 | HX2: WT_15M_BOUNCE_BB_MAX=0.9 | HY2: WT_15M_BOUNCE_BB_MAX=0.8 | HZ2: WT_15M_BOUNCE_BB_MIN=0.05 | IA2: WT_15M_BOUNCE_BB_MIN=0.1 | IB2: WT_15M_BOUNCE_BB_MIN=0.2 | IC2: WT_15M_BOUNCE_HIGH_1H_GT_PREV=True | ID2: WT_15M_BOUNCE_HIGH_1H_GT_PREV=False | IE2: WT_15M_BOUNCE_LOW_1H_GT_PREV=True | IF2: WT_15M_BOUNCE_LOW_1H_GT_PREV=False | IG2: WT_15M_BOUNCE_REL_VOL_GT_1=True | IH2: WT_15M_BOUNCE_REL_VOL_GT_1=False | II2: Live Location | IJ2: Vec Hook | IK2: Type | IL2: Correct Options
A3: HLR_REENTRY_MULT_1H | B3: 0.75 | E3: =MAX('REENTRY_WINDOWED'!E:E) | F3: =IFERROR(VLOOKUP($A3&"="&$B3,Results_30d_Deltas!$A$2:$H$5000,5,FALSE),"") | G3: =IFERROR(VLOOKUP($A3,Results_30d_Deltas!$A$2:$H$5000,7,FALSE)-E3,"") | H3: =IFERROR(VLOOKUP($A3,Results_30d_Deltas!$A$2:$H$5000,6,FALSE),"") | K3: =IF(B3=C3,"YES","NO") | IJ3: ez_manage.py:4846 top() | IK3: v12_quick_engine.py:2026 x7
A4: HLR_REENTRY_MULT_1H | B4: 1.125 | E4: =IF(F4="",E3,IF(F4>0,E3+F4,E3)) | F4: =IFERROR(VLOOKUP($A4&"="&$B4,Results_30d_Deltas!$A$2:$H$5000,5,FALSE),"") | G4: =IFERROR(VLOOKUP($A4,Results_30d_Deltas!$A$2:$H$5000,7,FALSE)-E3,"") | H4: =IFERROR(VLOOKUP($A4,Results_30d_Deltas!$A$2:$H$5000,6,FALSE),"") | K4: =IF(B4=C4,"YES","NO") | IJ4: ez_manage.py:4846 top() | IK4: v12_quick_engine.py:2026 x7
A5: HLR_REENTRY_MULT_1H | B5: 1.5 | E5: =IF(F5="",E4,IF(F5>0,E4+F5,E4)) | F5: =IFERROR(VLOOKUP($A5&"="&$B5,Results_30d_Deltas!$A$2:$H$5000,5,FALSE),"") | G5: =IFERROR(VLOOKUP($A5,Results_30d_Deltas!$A$2:$H$5000,7,FALSE)-E4,"") | H5: =IFERROR(VLOOKUP($A5,Results_30d_Deltas!$A$2:$H$5000,6,FALSE),"") | K5: =IF(B5=C5,"YES","NO") | IJ5: ez_manage.py:4846 top() | IK5: v12_quick_engine.py:2026 x7
A6: HLR_REENTRY_MULT_1H | B6: 1.875 | E6: =IF(F6="",E5,IF(F6>0,E5+F6,E5)) | F6: =IFERROR(VLOOKUP($A6&"="&$B6,Results_30d_Deltas!$A$2:$H$5000,5,FALSE),"") | G6: =IFERROR(VLOOKUP($A6,Results_30d_Deltas!$A$2:$H$5000,7,FALSE)-E5,"") | H6: =IFERROR(VLOOKUP($A6,Results_30d_Deltas!$A$2:$H$5000,6,FALSE),"") | K6: =IF(B6=C6,"YES","NO") | IJ6: ez_manage.py:4846 top() | IK6: v12_quick_engine.py:2026 x7
A7: HLR_REENTRY_MULT_1H | B7: 2.25 | E7: =IF(F7="",E6,IF(F7>0,E6+F7,E6)) | F7: =IFERROR(VLOOKUP($A7&"="&$B7,Results_30d_Deltas!$A$2:$H$5000,5,FALSE),"") | G7: =IFERROR(VLOOKUP($A7,Results_30d_Deltas!$A$2:$H$5000,7,FALSE)-E6,"") | H7: =IFERROR(VLOOKUP($A7,Results_30d_Deltas!$A$2:$H$5000,6,FALSE),"") | K7: =IF(B7=C7,"YES","NO") | IJ7: ez_manage.py:4846 top() | IK7: v12_quick_engine.py:2026 x7
A8: CHANNEL_REENTRY_STOP_ENABLED | B8: False | E8: =IF(F8="",E7,IF(F8>0,E7+F8,E7)) | F8: =IFERROR(VLOOKUP($A8&"="&$B8,Results_30d_Deltas!$A$2:$H$5000,5,FALSE),"") | G8: =IFERROR(VLOOKUP($A8,Results_30d_Deltas!$A$2:$H$5000,7,FALSE)-E7,"") | H8: =IFERROR(VLOOKUP($A8,Results_30d_Deltas!$A$2:$H$5000,6,FALSE),"") | K8: =IF(B8=C8,"YES","NO") | IJ8: ez_manage.py:5968 top() | IK8: v12_quick_engine.py:482 x8
A9: CHANNEL_REENTRY_STOP_ENABLED | B9: True | E9: =IF(F9="",E8,IF(F9>0,E8+F9,E8)) | F9: =IFERROR(VLOOKUP($A9&"="&$B9,Results_30d_Deltas!$A$2:$H$5000,5,FALSE),"") | G9: =IFERROR(VLOOKUP($A9,Results_30d_Deltas!$A$2:$H$5000,7,FALSE)-E8,"") | H9: =IFERROR(VLOOKUP($A9,Results_30d_Deltas!$A$2:$H$5000,6,FALSE),"") | K9: =IF(B9=C9,"YES","NO") | IJ9: ez_manage.py:5968 top() | IK9: v12_quick_engine.py:482 x8
A10: DAEMON_REENTRY_STALE_EXIT_ENABLED | B10: False | E10: =IF(F10="",E9,IF(F10>0,E9+F10,E9)) | F10: =IFERROR(VLOOKUP($A10&"="&$B10,Results_30d_Deltas!$A$2:$H$5000,5,FALSE),"") | G10: =IFERROR(VLOOKUP($A10,Results_30d_Deltas!$A$2:$H$5000,7,FALSE)-E9,"") | H10: =IFERROR(VLOOKUP($A10,Results_30d_Deltas!$A$2:$H$5000,6,FALSE),"") | K10: =IF(B10=C10,"YES","NO") | IJ10: ez_manage.py:4561 top() | IK10: v12_quick_engine.py:519 x9
A11: DAEMON_REENTRY_STALE_EXIT_ENABLED | B11: True | E11: =IF(F11="",E10,IF(F11>0,E10+F11,E10)) | F11: =IFERROR(VLOOKUP($A11&"="&$B11,Results_30d_Deltas!$A$2:$H$5000,5,FALSE),"") | G11: =IFERROR(VLOOKUP($A11,Results_30d_Deltas!$A$2:$H$5000,7,FALSE)-E10,"") | H11: =IFERROR(VLOOKUP($A11,Results_30d_Deltas!$A$2:$H$5000,6,FALSE),"") | K11: =IF(B11=C11,"YES","NO") | IJ11: ez_manage.py:4561 top() | IK11: v12_quick_engine.py:519 x9
A12: BREAKOUT_LEASH_REENTRY_MULT | B12: 0 | E12: =IF(F12="",E11,IF(F12>0,E11+F12,E11)) | F12: =IFERROR(VLOOKUP($A12&"="&$B12,Results_30d_Deltas!$A$2:$H$5000,5,FALSE),"") | G12: =IFERROR(VLOOKUP($A12,Results_30d_Deltas!$A$2:$H$5000,7,FALSE)-E11,"") | H12: =IFERROR(VLOOKUP($A12,Results_30d_Deltas!$A$2:$H$5000,6,FALSE),"") | K12: =IF(B12=C12,"YES","NO") | IJ12: ez_manage.py:2999 top() | IK12: v12_quick_engine.py:371 x12
A13: BREAKOUT_LEASH_REENTRY_MULT | B13: 0.5 | E13: =IF(F13="",E12,IF(F13>0,E12+F13,E12)) | F13: =IFERROR(VLOOKUP($A13&"="&$B13,Results_30d_Deltas!$A$2:$H$5000,5,FALSE),"") | G13: =IFERROR(VLOOKUP($A13,Results_30d_Deltas!$A$2:$H$5000,7,FALSE)-E12,"") | H13: =IFERROR(VLOOKUP($A13,Results_30d_Deltas!$A$2:$H$5000,6,FALSE),"") | K13: =IF(B13=C13,"YES","NO") | IJ13: ez_manage.py:2999 top() | IK13: v12_quick_engine.py:371 x12
A14: BREAKOUT_LEASH_REENTRY_MULT | B14: 1.0 | E14: =IF(F14="",E13,IF(F14>0,E13+F14,E13)) | F14: =IFERROR(VLOOKUP($A14&"="&$B14,Results_30d_Deltas!$A$2:$H$5000,5,FALSE),"") | G14: =IFERROR(VLOOKUP($A14,Results_30d_Deltas!$A$2:$H$5000,7,FALSE)-E13,"") | H14: =IFERROR(VLOOKUP($A14,Results_30d_Deltas!$A$2:$H$5000,6,FALSE),"") | K14: =IF(B14=C14,"YES","NO") | IJ14: ez_manage.py:2999 top() | IK14: v12_quick_engine.py:371 x12
A15: BREAKOUT_LEASH_REENTRY_MULT | B15: 2.0 | E15: =IF(F15="",E14,IF(F15>0,E14+F15,E14)) | F15: =IFERROR(VLOOKUP($A15&"="&$B15,Results_30d_Deltas!$A$2:$H$5000,5,FALSE),"") | G15: =IFERROR(VLOOKUP($A15,Results_30d_Deltas!$A$2:$H$5000,7,FALSE)-E14,"") | H15: =IFERROR(VLOOKUP($A15,Results_30d_Deltas!$A$2:$H$5000,6,FALSE),"") | K15: =IF(B15=C15,"YES","NO") | IJ15: ez_manage.py:2999 top() | IK15: v12_quick_engine.py:371 x12
... A40: REENTRY_SIZE_BREAKOUT_MULT | B40: 2.0 | E40: =IF(F40="",E39,IF(F40>0,E39+F40,E39)) | F40: =IFERROR(VLOOKUP($A40&"="&$B40,Results_30d_Deltas!$A$2:$H$5000,5,FALSE),"") | G40: =IFERROR(VLOOKUP($A40,Results_30d_Deltas!$A$2:$H$5000,7,FALSE)-E39,"") | H40: =IFERROR(VLOOKUP($A40,Results_30d_Deltas!$A$2:$H$5000,6,FALSE),"") | K40: =IF(B40=C40,"YES","NO") | IJ40: ez_manage.py:3870 top() | IK40: v12_quick_engine.py:2903 x3

Sheet AUGMENT_TREND
A1: 08 AUGMENT_TREND - 5 bases -> 24 rows - 231 per-row FULLY CONNECTED
A2: Switch | B2: default | C2: override | D2: Family | E2: =MAX('REENTRY_ADAPTIVE'!E$2:E$5000) | F2: VECTOR_DELTA | G2: LIVE_DELTA | H2: LIVE_SHARPE | I2: REAL_COMPLETE | J2: PER_ROW_FILTERS | K2: is_default (backup if bold lost) | L2: ATR_TRAIL_FILTER_TF=OFF | M2: ATR_TRAIL_FILTER_TF=D | N2: ATR_TRAIL_FILTER_TF=4h | O2: ATR_TRAIL_FILTER_TF=1h | P2: ATR_TRAIL_FILTER_TF=15m | Q2: BAR_PATTERNS_FILTER_TF=OFF | R2: BAR_PATTERNS_FILTER_TF=D | S2: BAR_PATTERNS_FILTER_TF=4h | T2: BAR_PATTERNS_FILTER_TF=1h | U2: BAR_PATTERNS_FILTER_TF=15m | V2: BB_PULLBACK_GATE_FILTER_TF=OFF | W2: BB_PULLBACK_GATE_FILTER_TF=D | X2: BB_PULLBACK_GATE_FILTER_TF=4h | Y2: BB_PULLBACK_GATE_FILTER_TF=1h | Z2: BB_PULLBACK_GATE_FILTER_TF=15m | AA2: BB_RECOVERY_ENTRY_FILTER_TF=OFF | AB2: BB_RECOVERY_ENTRY_FILTER_TF=D | AC2: BB_RECOVERY_ENTRY_FILTER_TF=4h | AD2: BB_RECOVERY_ENTRY_FILTER_TF=1h | AE2: BB_RECOVERY_ENTRY_FILTER_TF=15m | AF2: BB_RECOVERY_FILTER_TF=OFF | AG2: BB_RECOVERY_FILTER_TF=D | AH2: BB_RECOVERY_FILTER_TF=4h | AI2: BB_RECOVERY_FILTER_TF=1h | AJ2: BB_RECOVERY_FILTER_TF=15m | AK2: BREAKEVEN_GAIN_EROSION_FILTER_TF=OFF | AL2: BREAKEVEN_GAIN_EROSION_FILTER_TF=D | AM2: BREAKEVEN_GAIN_EROSION_FILTER_TF=4h | AN2: BREAKEVEN_GAIN_EROSION_FILTER_TF=1h | AO2: BREAKEVEN_GAIN_EROSION_FILTER_TF=15m | AP2: BREAKOUT_RETEST_FILTER_TF=OFF | AQ2: BREAKOUT_RETEST_FILTER_TF=D | AR2: BREAKOUT_RETEST_FILTER_TF=4h | AS2: BREAKOUT_RETEST_FILTER_TF=1h | AT2: BREAKOUT_RETEST_FILTER_TF=15m | AU2: BT_WT_CROSS_LADDER_FILTER_TF=OFF | AV2: BT_WT_CROSS_LADDER_FILTER_TF=D | AW2: BT_WT_CROSS_LADDER_FILTER_TF=4h | AX2: BT_WT_CROSS_LADDER_FILTER_TF=1h | AY2: BT_WT_CROSS_LADDER_FILTER_TF=15m | AZ2: CANDLE_PATTERN_STOPS_FILTER_TF=OFF | BA2: CANDLE_PATTERN_STOPS_FILTER_TF=D | BB2: CANDLE_PATTERN_STOPS_FILTER_TF=4h | BC2: CANDLE_PATTERN_STOPS_FILTER_TF=1h | BD2: CANDLE_PATTERN_STOPS_FILTER_TF=15m | BE2: CIRCUIT_SHARPE_GATES_FILTER_TF=OFF | BF2: CIRCUIT_SHARPE_GATES_FILTER_TF=D | BG2: CIRCUIT_SHARPE_GATES_FILTER_TF=4h | BH2: CIRCUIT_SHARPE_GATES_FILTER_TF=1h | BI2: CIRCUIT_SHARPE_GATES_FILTER_TF=15m | BJ2: DC_BREACH_REDUCE_FILTER_TF=OFF | BK2: DC_BREACH_REDUCE_FILTER_TF=D | BL2: DC_BREACH_REDUCE_FILTER_TF=4h | BM2: DC_BREACH_REDUCE_FILTER_TF=1h | BN2: DC_BREACH_REDUCE_FILTER_TF=15m | BO2: DC_BREAK_FILTER_TF=OFF | BP2: DC_BREAK_FILTER_TF=D | BQ2: DC_BREAK_FILTER_TF=4h | BR2: DC_BREAK_FILTER_TF=1h | BS2: DC_BREAK_FILTER_TF=15m | BT2: DC_MOMENTUM_BOTA_SCORER_FILTER_TF=OFF | BU2: DC_MOMENTUM_BOTA_SCORER_FILTER_TF=D | BV2: DC_MOMENTUM_BOTA_SCORER_FILTER_TF=4h | BW2: DC_MOMENTUM_BOTA_SCORER_FILTER_TF=1h | BX2: DC_MOMENTUM_BOTA_SCORER_FILTER_TF=15m | BY2: DELTA_ENGINE_FILTER_TF=OFF | BZ2: DELTA_ENGINE_FILTER_TF=D | CA2: DELTA_ENGINE_FILTER_TF=4h | CB2: DELTA_ENGINE_FILTER_TF=1h | CC2: DELTA_ENGINE_FILTER_TF=15m | CD2: EMA_9_21_FILTER_FILTER_TF=OFF | CE2: EMA_9_21_FILTER_FILTER_TF=D | CF2: EMA_9_21_FILTER_FILTER_TF=4h | CG2: EMA_9_21_FILTER_FILTER_TF=1h | CH2: EMA_9_21_FILTER_FILTER_TF=15m | CI2: EMA_BLANKET_FILTER_FILTER_TF=OFF | CJ2: EMA_BLANKET_FILTER_FILTER_TF=D | CK2: EMA_BLANKET_FILTER_FILTER_TF=4h | CL2: EMA_BLANKET_FILTER_FILTER_TF=1h | CM2: EMA_BLANKET_FILTER_FILTER_TF=15m | CN2: EMERGENCY_BRAKE_FILTER_TF=OFF | CO2: EMERGENCY_BRAKE_FILTER_TF=D | CP2: EMERGENCY_BRAKE_FILTER_TF=4h | CQ2: EMERGENCY_BRAKE_FILTER_TF=1h | CR2: EMERGENCY_BRAKE_FILTER_TF=15m | CS2: EXIT_R1_R2_FILTER_TF=OFF | CT2: EXIT_R1_R2_FILTER_TF=D | CU2: EXIT_R1_R2_FILTER_TF=4h | CV2: EXIT_R1_R2_FILTER_TF=1h | CW2: EXIT_R1_R2_FILTER_TF=15m | CX2: EXIT_TIGHT_BREAKOUT_SCORER_FILTER_TF=OFF | CY2: EXIT_TIGHT_BREAKOUT_SCORER_FILTER_TF=D | CZ2: EXIT_TIGHT_BREAKOUT_SCORER_FILTER_TF=4h | DA2: EXIT_TIGHT_BREAKOUT_SCORER_FILTER_TF=1h | DB2: EXIT_TIGHT_BREAKOUT_SCORER_FILTER_TF=15m | DC2: EXIT_TOP_FADE_FILTER_TF=OFF | DD2: EXIT_TOP_FADE_FILTER_TF=D | DE2: EXIT_TOP_FADE_FILTER_TF=4h | DF2: EXIT_TOP_FADE_FILTER_TF=1h | DG2: EXIT_TOP_FADE_FILTER_TF=15m | DH2: EXIT_TO_REDUCE_ADAPTER_FILTER_TF=OFF | DI2: EXIT_TO_REDUCE_ADAPTER_FILTER_TF=D | DJ2: EXIT_TO_REDUCE_ADAPTER_FILTER_TF=4h | DK2: EXIT_TO_REDUCE_ADAPTER_FILTER_TF=1h | DL2: EXIT_TO_REDUCE_ADAPTER_FILTER_TF=15m | DM2: FAST_RISER_FILTER_TF=OFF | DN2: FAST_RISER_FILTER_TF=D | DO2: FAST_RISER_FILTER_TF=4h | DP2: FAST_RISER_FILTER_TF=1h | DQ2: FAST_RISER_FILTER_TF=15m | DR2: FH_MOMENTUM_FILTER_TF=OFF | DS2: FH_MOMENTUM_FILTER_TF=D | DT2: FH_MOMENTUM_FILTER_TF=4h | DU2: FH_MOMENTUM_FILTER_TF=1h | DV2: FH_MOMENTUM_FILTER_TF=15m | DW2: FIRST_OPEN_THROTTLE_FILTER_TF=OFF | DX2: FIRST_OPEN_THROTTLE_FILTER_TF=D | DY2: FIRST_OPEN_THROTTLE_FILTER_TF=4h | DZ2: FIRST_OPEN_THROTTLE_FILTER_TF=1h | EA2: FIRST_OPEN_THROTTLE_FILTER_TF=15m | EB2: FROZEN_STOP_FILTER_TF=OFF | EC2: FROZEN_STOP_FILTER_TF=D | ED2: FROZEN_STOP_FILTER_TF=4h | EE2: FROZEN_STOP_FILTER_TF=1h | EF2: FROZEN_STOP_FILTER_TF=15m | EG2: GOLDEN_RULE_ENFORCE_FILTER_TF=OFF | EH2: GOLDEN_RULE_ENFORCE_FILTER_TF=D | EI2: GOLDEN_RULE_ENFORCE_FILTER_TF=4h | EJ2: GOLDEN_RULE_ENFORCE_FILTER_TF=1h | EK2: GOLDEN_RULE_ENFORCE_FILTER_TF=15m | EL2: GOLDEN_RULE_HTF_VOTE_FILTER_TF=OFF | EM2: GOLDEN_RULE_HTF_VOTE_FILTER_TF=D | EN2: GOLDEN_RULE_HTF_VOTE_FILTER_TF=4h | EO2: GOLDEN_RULE_HTF_VOTE_FILTER_TF=1h | EP2: GOLDEN_RULE_HTF_VOTE_FILTER_TF=15m | EQ2: GR_FILTER_VEC_FILTER_TF=OFF | ER2: GR_FILTER_VEC_FILTER_TF=D | ES2: GR_FILTER_VEC_FILTER_TF=4h | ET2: GR_FILTER_VEC_FILTER_TF=1h | EU2: GR_FILTER_VEC_FILTER_TF=15m | EV2: GR_V5_STATE_FILTER_TF=OFF | EW2: GR_V5_STATE_FILTER_TF=D | EX2: GR_V5_STATE_FILTER_TF=4h | EY2: GR_V5_STATE_FILTER_TF=1h | EZ2: GR_V5_STATE_FILTER_TF=15m | FA2: HAIKU_WINNER_FILTER_TF=OFF | FB2: HAIKU_WINNER_FILTER_TF=D | FC2: HAIKU_WINNER_FILTER_TF=4h | FD2: HAIKU_WINNER_FILTER_TF=1h | FE2: HAIKU_WINNER_FILTER_TF=15m | FF2: LH_HL_FILTER_TF_REQ=2 | FG2: LH_HL_FILTER_TF_REQ=2_ALT | FH2: LIVE_ENTRY_ENGINE_FILTER_TF=OFF | FI2: LIVE_ENTRY_ENGINE_FILTER_TF=D | FJ2: LIVE_ENTRY_ENGINE_FILTER_TF=4h | FK2: LIVE_ENTRY_ENGINE_FILTER_TF=1h | FL2: LIVE_ENTRY_ENGINE_FILTER_TF=15m | FM2: LIVE_ONLY_SIGNALS_BATCH5_FILTER_TF=OFF | FN2: LIVE_ONLY_SIGNALS_BATCH5_FILTER_TF=D | FO2: LIVE_ONLY_SIGNALS_BATCH5_FILTER_TF=4h | FP2: LIVE_ONLY_SIGNALS_BATCH5_FILTER_TF=1h | FQ2: LIVE_ONLY_SIGNALS_BATCH5_FILTER_TF=15m | FR2: MANDATORY_REENTRY_WT_FILTER_TF_MODE=15m_only | FS2: MANDATORY_REENTRY_WT_FILTER_TF_MODE=15m_only_ALT | FT2: MOM3_FILTER_TF=OFF | FU2: MOM3_FILTER_TF=D | FV2: MOM3_FILTER_TF=4h | FW2: MOM3_FILTER_TF=1h | FX2: MOM3_FILTER_TF=15m | FY2: MOMENTUM_BREAKOUT_FILTER_TF=OFF | FZ2: MOMENTUM_BREAKOUT_FILTER_TF=D | GA2: MOMENTUM_BREAKOUT_FILTER_TF=4h | GB2: MOMENTUM_BREAKOUT_FILTER_TF=1h | GC2: MOMENTUM_BREAKOUT_FILTER_TF=15m | GD2: MTF_ARMED_ENTRIES_FILTER_TF=OFF | GE2: MTF_ARMED_ENTRIES_FILTER_TF=D | GF2: MTF_ARMED_ENTRIES_FILTER_TF=4h | GG2: MTF_ARMED_ENTRIES_FILTER_TF=1h | GH2: MTF_ARMED_ENTRIES_FILTER_TF=15m | GI2: MTF_ATR_TRAIL_FILTER_TF=OFF | GJ2: MTF_ATR_TRAIL_FILTER_TF=D | GK2: MTF_ATR_TRAIL_FILTER_TF=4h | GL2: MTF_ATR_TRAIL_FILTER_TF=1h | GM2: MTF_ATR_TRAIL_FILTER_TF=15m | GN2: MTF_DC_REJECT_FILTER_TF=OFF | GO2: MTF_DC_REJECT_FILTER_TF=D | GP2: MTF_DC_REJECT_FILTER_TF=4h | GQ2: MTF_DC_REJECT_FILTER_TF=1h | GR2: MTF_DC_REJECT_FILTER_TF=15m | GS2: NEWBORN_LOSS_KILL_FILTER_TF=OFF | GT2: NEWBORN_LOSS_KILL_FILTER_TF=D | GU2: NEWBORN_LOSS_KILL_FILTER_TF=4h | GV2: NEWBORN_LOSS_KILL_FILTER_TF=1h | GW2: NEWBORN_LOSS_KILL_FILTER_TF=15m | GX2: NEWBORN_PROTECT_FILTER_TF=OFF | GY2: NEWBORN_PROTECT_FILTER_TF=D | GZ2: NEWBORN_PROTECT_FILTER_TF=4h | HA2: NEWBORN_PROTECT_FILTER_TF=1h | HB2: NEWBORN_PROTECT_FILTER_TF=15m | HC2: NOLOSS_BYPASS_WT5OF5_FILTER_TF=OFF | HD2: NOLOSS_BYPASS_WT5OF5_FILTER_TF=D | HE2: NOLOSS_BYPASS_WT5OF5_FILTER_TF=4h | HF2: NOLOSS_BYPASS_WT5OF5_FILTER_TF=1h | HG2: NOLOSS_BYPASS_WT5OF5_FILTER_TF=15m | HH2: OPEN_INTENT_SIZE_GATES_FILTER_TF=OFF | HI2: OPEN_INTENT_SIZE_GATES_FILTER_TF=D | HJ2: OPEN_INTENT_SIZE_GATES_FILTER_TF=4h | HK2: OPEN_INTENT_SIZE_GATES_FILTER_TF=1h | HL2: OPEN_INTENT_SIZE_GATES_FILTER_TF=15m | HM2: PARTIAL_PROFIT_LOCK_V2_FILTER_TF=OFF | HN2: PARTIAL_PROFIT_LOCK_V2_FILTER_TF=D | HO2: PARTIAL_PROFIT_LOCK_V2_FILTER_TF=4h | HP2: PARTIAL_PROFIT_LOCK_V2_FILTER_TF=1h | HQ2: PARTIAL_PROFIT_LOCK_V2_FILTER_TF=15m | HR2: PEAK_GIVEBACK_BE_EROSION_FILTER_TF=OFF | HS2: PEAK_GIVEBACK_BE_EROSION_FILTER_TF=D | HT2: PEAK_GIVEBACK_BE_EROSION_FILTER_TF=4h | HU2: PEAK_GIVEBACK_BE_EROSION_FILTER_TF=1h | HV2: PEAK_GIVEBACK_BE_EROSION_FILTER_TF=15m | HW2: WT_15M_BOUNCE_BB_MAX=0.95 | HX2: WT_15M_BOUNCE_BB_MAX=0.9 | HY2: WT_15M_BOUNCE_BB_MAX=0.8 | HZ2: WT_15M_BOUNCE_BB_MIN=0.05 | IA2: WT_15M_BOUNCE_BB_MIN=0.1 | IB2: WT_15M_BOUNCE_BB_MIN=0.2 | IC2: WT_15M_BOUNCE_HIGH_1H_GT_PREV=True | ID2: WT_15M_BOUNCE_HIGH_1H_GT_PREV=False | IE2: WT_15M_BOUNCE_LOW_1H_GT_PREV=True | IF2: WT_15M_BOUNCE_LOW_1H_GT_PREV=False | IG2: WT_15M_BOUNCE_REL_VOL_GT_1=True | IH2: WT_15M_BOUNCE_REL_VOL_GT_1=False | II2: Live Location | IJ2: Vec Hook | IK2: Type | IL2: Correct Options
A3: AUGMENT_MIN_GAIN_PCT | B3: 0.25 | E3: =MAX('REENTRY_ADAPTIVE'!E:E) | F3: =IFERROR(VLOOKUP($A3&"="&$B3,Results_30d_Deltas!$A$2:$H$5000,5,FALSE),"") | G3: =IFERROR(VLOOKUP($A3,Results_30d_Deltas!$A$2:$H$5000,7,FALSE)-E3,"") | H3: =IFERROR(VLOOKUP($A3,Results_30d_Deltas!$A$2:$H$5000,6,FALSE),"") | K3: =IF(B3=C3,"YES","NO") | IJ3: ez_manage.py:30417 top() | IK3: v12_quick_engine.py:4874 x5
A4: AUGMENT_MIN_GAIN_PCT | B4: 0.375 | E4: =IF(F4="",E3,IF(F4>0,E3+F4,E3)) | F4: =IFERROR(VLOOKUP($A4&"="&$B4,Results_30d_Deltas!$A$2:$H$5000,5,FALSE),"") | G4: =IFERROR(VLOOKUP($A4,Results_30d_Deltas!$A$2:$H$5000,7,FALSE)-E3,"") | H4: =IFERROR(VLOOKUP($A4,Results_30d_Deltas!$A$2:$H$5000,6,FALSE),"") | K4: =IF(B4=C4,"YES","NO") | IJ4: ez_manage.py:30417 top() | IK4: v12_quick_engine.py:4874 x5
A5: AUGMENT_MIN_GAIN_PCT | B5: 0.5 | E5: =IF(F5="",E4,IF(F5>0,E4+F5,E4)) | F5: =IFERROR(VLOOKUP($A5&"="&$B5,Results_30d_Deltas!$A$2:$H$5000,5,FALSE),"") | G5: =IFERROR(VLOOKUP($A5,Results_30d_Deltas!$A$2:$H$5000,7,FALSE)-E4,"") | H5: =IFERROR(VLOOKUP($A5,Results_30d_Deltas!$A$2:$H$5000,6,FALSE),"") | K5: =IF(B5=C5,"YES","NO") | IJ5: ez_manage.py:30417 top() | IK5: v12_quick_engine.py:4874 x5
A6: AUGMENT_MIN_GAIN_PCT | B6: 0.625 | E6: =IF(F6="",E5,IF(F6>0,E5+F6,E5)) | F6: =IFERROR(VLOOKUP($A6&"="&$B6,Results_30d_Deltas!$A$2:$H$5000,5,FALSE),"") | G6: =IFERROR(VLOOKUP($A6,Results_30d_Deltas!$A$2:$H$5000,7,FALSE)-E5,"") | H6: =IFERROR(VLOOKUP($A6,Results_30d_Deltas!$A$2:$H$5000,6,FALSE),"") | K6: =IF(B6=C6,"YES","NO") | IJ6: ez_manage.py:30417 top() | IK6: v12_quick_engine.py:4874 x5
A7: AUGMENT_MIN_GAIN_PCT | B7: 0.75 | E7: =IF(F7="",E6,IF(F7>0,E6+F7,E6)) | F7: =IFERROR(VLOOKUP($A7&"="&$B7,Results_30d_Deltas!$A$2:$H$5000,5,FALSE),"") | G7: =IFERROR(VLOOKUP($A7,Results_30d_Deltas!$A$2:$H$5000,7,FALSE)-E6,"") | H7: =IFERROR(VLOOKUP($A7,Results_30d_Deltas!$A$2:$H$5000,6,FALSE),"") | K7: =IF(B7=C7,"YES","NO") | IJ7: ez_manage.py:30417 top() | IK7: v12_quick_engine.py:4874 x5
A8: BOUNCE_AUGMENT_MIN_LOSS_PCT | B8: -0.75 | E8: =IF(F8="",E7,IF(F8>0,E7+F8,E7)) | F8: =IFERROR(VLOOKUP($A8&"="&$B8,Results_30d_Deltas!$A$2:$H$5000,5,FALSE),"") | G8: =IFERROR(VLOOKUP($A8,Results_30d_Deltas!$A$2:$H$5000,7,FALSE)-E7,"") | H8: =IFERROR(VLOOKUP($A8,Results_30d_Deltas!$A$2:$H$5000,6,FALSE),"") | K8: =IF(B8=C8,"YES","NO") | IJ8: ez_manage.py:4390 top() | IK8: v12_quick_engine.py:1310 x9
A9: BOUNCE_AUGMENT_MIN_LOSS_PCT | B9: -0.625 | E9: =IF(F9="",E8,IF(F9>0,E8+F9,E8)) | F9: =IFERROR(VLOOKUP($A9&"="&$B9,Results_30d_Deltas!$A$2:$H$5000,5,FALSE),"") | G9: =IFERROR(VLOOKUP($A9,Results_30d_Deltas!$A$2:$H$5000,7,FALSE)-E8,"") | H9: =IFERROR(VLOOKUP($A9,Results_30d_Deltas!$A$2:$H$5000,6,FALSE),"") | K9: =IF(B9=C9,"YES","NO") | IJ9: ez_manage.py:4390 top() | IK9: v12_quick_engine.py:1310 x9
A10: BOUNCE_AUGMENT_MIN_LOSS_PCT | B10: -0.5 | E10: =IF(F10="",E9,IF(F10>0,E9+F10,E9)) | F10: =IFERROR(VLOOKUP($A10&"="&$B10,Results_30d_Deltas!$A$2:$H$5000,5,FALSE),"") | G10: =IFERROR(VLOOKUP($A10,Results_30d_Deltas!$A$2:$H$5000,7,FALSE)-E9,"") | H10: =IFERROR(VLOOKUP($A10,Results_30d_Deltas!$A$2:$H$5000,6,FALSE),"") | K10: =IF(B10=C10,"YES","NO") | IJ10: ez_manage.py:4390 top() | IK10: v12_quick_engine.py:1310 x9
A11: BOUNCE_AUGMENT_MIN_LOSS_PCT | B11: -0.375 | E11: =IF(F11="",E10,IF(F11>0,E10+F11,E10)) | F11: =IFERROR(VLOOKUP($A11&"="&$B11,Results_30d_Deltas!$A$2:$H$5000,5,FALSE),"") | G11: =IFERROR(VLOOKUP($A11,Results_30d_Deltas!$A$2:$H$5000,7,FALSE)-E10,"") | H11: =IFERROR(VLOOKUP($A11,Results_30d_Deltas!$A$2:$H$5000,6,FALSE),"") | K11: =IF(B11=C11,"YES","NO") | IJ11: ez_manage.py:4390 top() | IK11: v12_quick_engine.py:1310 x9
A12: BOUNCE_AUGMENT_MIN_LOSS_PCT | B12: -0.25 | E12: =IF(F12="",E11,IF(F12>0,E11+F12,E11)) | F12: =IFERROR(VLOOKUP($A12&"="&$B12,Results_30d_Deltas!$A$2:$H$5000,5,FALSE),"") | G12: =IFERROR(VLOOKUP($A12,Results_30d_Deltas!$A$2:$H$5000,7,FALSE)-E11,"") | H12: =IFERROR(VLOOKUP($A12,Results_30d_Deltas!$A$2:$H$5000,6,FALSE),"") | K12: =IF(B12=C12,"YES","NO") | IJ12: ez_manage.py:4390 top() | IK12: v12_quick_engine.py:1310 x9
A13: AUGMENT_BOUNCE_MIN_GAIN_PCT | B13: 0.25 | E13: =IF(F13="",E12,IF(F13>0,E12+F13,E12)) | F13: =IFERROR(VLOOKUP($A13&"="&$B13,Results_30d_Deltas!$A$2:$H$5000,5,FALSE),"") | G13: =IFERROR(VLOOKUP($A13,Results_30d_Deltas!$A$2:$H$5000,7,FALSE)-E12,"") | H13: =IFERROR(VLOOKUP($A13,Results_30d_Deltas!$A$2:$H$5000,6,FALSE),"") | K13: =IF(B13=C13,"YES","NO") | IJ13: ez_manage.py:56856 top() | IK13: v12_quick_engine.py:4872 x2
A14: AUGMENT_BOUNCE_MIN_GAIN_PCT | B14: 0.375 | E14: =IF(F14="",E13,IF(F14>0,E13+F14,E13)) | F14: =IFERROR(VLOOKUP($A14&"="&$B14,Results_30d_Deltas!$A$2:$H$5000,5,FALSE),"") | G14: =IFERROR(VLOOKUP($A14,Results_30d_Deltas!$A$2:$H$5000,7,FALSE)-E13,"") | H14: =IFERROR(VLOOKUP($A14,Results_30d_Deltas!$A$2:$H$5000,6,FALSE),"") | K14: =IF(B14=C14,"YES","NO") | IJ14: ez_manage.py:56856 top() | IK14: v12_quick_engine.py:4872 x2
A15: AUGMENT_BOUNCE_MIN_GAIN_PCT | B15: 0.5 | E15: =IF(F15="",E14,IF(F15>0,E14+F15,E14)) | F15: =IFERROR(VLOOKUP($A15&"="&$B15,Results_30d_Deltas!$A$2:$H$5000,5,FALSE),"") | G15: =IFERROR(VLOOKUP($A15,Results_30d_Deltas!$A$2:$H$5000,7,FALSE)-E14,"") | H15: =IFERROR(VLOOKUP($A15,Results_30d_Deltas!$A$2:$H$5000,6,FALSE),"") | K15: =IF(B15=C15,"YES","NO") | IJ15: ez_manage.py:56856 top() | IK15: v12_quick_engine.py:4872 x2
... A26: HTF_GATE_APPLY_TO_AUGMENT | B26: 2.0 | E26: =IF(F26="",E25,IF(F26>0,E25+F26,E25)) | F26: =IFERROR(VLOOKUP($A26&"="&$B26,Results_30d_Deltas!$A$2:$H$5000,5,FALSE),"") | G26: =IFERROR(VLOOKUP($A26,Results_30d_Deltas!$A$2:$H$5000,7,FALSE)-E25,"") | H26: =IFERROR(VLOOKUP($A26,Results_30d_Deltas!$A$2:$H$5000,6,FALSE),"") | K26: =IF(B26=C26,"YES","NO") | IJ26: ez_manage.py:4876 top() | IK26: v12_quick_engine.py:2052 x6

Sheet AUGMENT_RISK_SIZING
A1: 09 AUGMENT_RISK_SIZING - 17 bases -> 56 rows - 231 per-row FULLY CONNECTED
A2: Switch | B2: default | C2: override | D2: Family | E2: =MAX('AUGMENT_TREND'!E$2:E$5000) | F2: VECTOR_DELTA | G2: LIVE_DELTA | H2: LIVE_SHARPE | I2: REAL_COMPLETE | J2: PER_ROW_FILTERS | K2: is_default (backup if bold lost) | L2: ATR_TRAIL_FILTER_TF=OFF | M2: ATR_TRAIL_FILTER_TF=D | N2: ATR_TRAIL_FILTER_TF=4h | O2: ATR_TRAIL_FILTER_TF=1h | P2: ATR_TRAIL_FILTER_TF=15m | Q2: BAR_PATTERNS_FILTER_TF=OFF | R2: BAR_PATTERNS_FILTER_TF=D | S2: BAR_PATTERNS_FILTER_TF=4h | T2: BAR_PATTERNS_FILTER_TF=1h | U2: BAR_PATTERNS_FILTER_TF=15m | V2: BB_PULLBACK_GATE_FILTER_TF=OFF | W2: BB_PULLBACK_GATE_FILTER_TF=D | X2: BB_PULLBACK_GATE_FILTER_TF=4h | Y2: BB_PULLBACK_GATE_FILTER_TF=1h | Z2: BB_PULLBACK_GATE_FILTER_TF=15m | AA2: BB_RECOVERY_ENTRY_FILTER_TF=OFF | AB2: BB_RECOVERY_ENTRY_FILTER_TF=D | AC2: BB_RECOVERY_ENTRY_FILTER_TF=4h | AD2: BB_RECOVERY_ENTRY_FILTER_TF=1h | AE2: BB_RECOVERY_ENTRY_FILTER_TF=15m | AF2: BB_RECOVERY_FILTER_TF=OFF | AG2: BB_RECOVERY_FILTER_TF=D | AH2: BB_RECOVERY_FILTER_TF=4h | AI2: BB_RECOVERY_FILTER_TF=1h | AJ2: BB_RECOVERY_FILTER_TF=15m | AK2: BREAKEVEN_GAIN_EROSION_FILTER_TF=OFF | AL2: BREAKEVEN_GAIN_EROSION_FILTER_TF=D | AM2: BREAKEVEN_GAIN_EROSION_FILTER_TF=4h | AN2: BREAKEVEN_GAIN_EROSION_FILTER_TF=1h | AO2: BREAKEVEN_GAIN_EROSION_FILTER_TF=15m | AP2: BREAKOUT_RETEST_FILTER_TF=OFF | AQ2: BREAKOUT_RETEST_FILTER_TF=D | AR2: BREAKOUT_RETEST_FILTER_TF=4h | AS2: BREAKOUT_RETEST_FILTER_TF=1h | AT2: BREAKOUT_RETEST_FILTER_TF=15m | AU2: BT_WT_CROSS_LADDER_FILTER_TF=OFF | AV2: BT_WT_CROSS_LADDER_FILTER_TF=D | AW2: BT_WT_CROSS_LADDER_FILTER_TF=4h | AX2: BT_WT_CROSS_LADDER_FILTER_TF=1h | AY2: BT_WT_CROSS_LADDER_FILTER_TF=15m | AZ2: CANDLE_PATTERN_STOPS_FILTER_TF=OFF | BA2: CANDLE_PATTERN_STOPS_FILTER_TF=D | BB2: CANDLE_PATTERN_STOPS_FILTER_TF=4h | BC2: CANDLE_PATTERN_STOPS_FILTER_TF=1h | BD2: CANDLE_PATTERN_STOPS_FILTER_TF=15m | BE2: CIRCUIT_SHARPE_GATES_FILTER_TF=OFF | BF2: CIRCUIT_SHARPE_GATES_FILTER_TF=D | BG2: CIRCUIT_SHARPE_GATES_FILTER_TF=4h | BH2: CIRCUIT_SHARPE_GATES_FILTER_TF=1h | BI2: CIRCUIT_SHARPE_GATES_FILTER_TF=15m | BJ2: DC_BREACH_REDUCE_FILTER_TF=OFF | BK2: DC_BREACH_REDUCE_FILTER_TF=D | BL2: DC_BREACH_REDUCE_FILTER_TF=4h | BM2: DC_BREACH_REDUCE_FILTER_TF=1h | BN2: DC_BREACH_REDUCE_FILTER_TF=15m | BO2: DC_BREAK_FILTER_TF=OFF | BP2: DC_BREAK_FILTER_TF=D | BQ2: DC_BREAK_FILTER_TF=4h | BR2: DC_BREAK_FILTER_TF=1h | BS2: DC_BREAK_FILTER_TF=15m | BT2: DC_MOMENTUM_BOTA_SCORER_FILTER_TF=OFF | BU2: DC_MOMENTUM_BOTA_SCORER_FILTER_TF=D | BV2: DC_MOMENTUM_BOTA_SCORER_FILTER_TF=4h | BW2: DC_MOMENTUM_BOTA_SCORER_FILTER_TF=1h | BX2: DC_MOMENTUM_BOTA_SCORER_FILTER_TF=15m | BY2: DELTA_ENGINE_FILTER_TF=OFF | BZ2: DELTA_ENGINE_FILTER_TF=D | CA2: DELTA_ENGINE_FILTER_TF=4h | CB2: DELTA_ENGINE_FILTER_TF=1h | CC2: DELTA_ENGINE_FILTER_TF=15m | CD2: EMA_9_21_FILTER_FILTER_TF=OFF | CE2: EMA_9_21_FILTER_FILTER_TF=D | CF2: EMA_9_21_FILTER_FILTER_TF=4h | CG2: EMA_9_21_FILTER_FILTER_TF=1h | CH2: EMA_9_21_FILTER_FILTER_TF=15m | CI2: EMA_BLANKET_FILTER_FILTER_TF=OFF | CJ2: EMA_BLANKET_FILTER_FILTER_TF=D | CK2: EMA_BLANKET_FILTER_FILTER_TF=4h | CL2: EMA_BLANKET_FILTER_FILTER_TF=1h | CM2: EMA_BLANKET_FILTER_FILTER_TF=15m | CN2: EMERGENCY_BRAKE_FILTER_TF=OFF | CO2: EMERGENCY_BRAKE_FILTER_TF=D | CP2: EMERGENCY_BRAKE_FILTER_TF=4h | CQ2: EMERGENCY_BRAKE_FILTER_TF=1h | CR2: EMERGENCY_BRAKE_FILTER_TF=15m | CS2: EXIT_R1_R2_FILTER_TF=OFF | CT2: EXIT_R1_R2_FILTER_TF=D | CU2: EXIT_R1_R2_FILTER_TF=4h | CV2: EXIT_R1_R2_FILTER_TF=1h | CW2: EXIT_R1_R2_FILTER_TF=15m | CX2: EXIT_TIGHT_BREAKOUT_SCORER_FILTER_TF=OFF | CY2: EXIT_TIGHT_BREAKOUT_SCORER_FILTER_TF=D | CZ2: EXIT_TIGHT_BREAKOUT_SCORER_FILTER_TF=4h | DA2: EXIT_TIGHT_BREAKOUT_SCORER_FILTER_TF=1h | DB2: EXIT_TIGHT_BREAKOUT_SCORER_FILTER_TF=15m | DC2: EXIT_TOP_FADE_FILTER_TF=OFF | DD2: EXIT_TOP_FADE_FILTER_TF=D | DE2: EXIT_TOP_FADE_FILTER_TF=4h | DF2: EXIT_TOP_FADE_FILTER_TF=1h | DG2: EXIT_TOP_FADE_FILTER_TF=15m | DH2: EXIT_TO_REDUCE_ADAPTER_FILTER_TF=OFF | DI2: EXIT_TO_REDUCE_ADAPTER_FILTER_TF=D | DJ2: EXIT_TO_REDUCE_ADAPTER_FILTER_TF=4h | DK2: EXIT_TO_REDUCE_ADAPTER_FILTER_TF=1h | DL2: EXIT_TO_REDUCE_ADAPTER_FILTER_TF=15m | DM2: FAST_RISER_FILTER_TF=OFF | DN2: FAST_RISER_FILTER_TF=D | DO2: FAST_RISER_FILTER_TF=4h | DP2: FAST_RISER_FILTER_TF=1h | DQ2: FAST_RISER_FILTER_TF=15m | DR2: FH_MOMENTUM_FILTER_TF=OFF | DS2: FH_MOMENTUM_FILTER_TF=D | DT2: FH_MOMENTUM_FILTER_TF=4h | DU2: FH_MOMENTUM_FILTER_TF=1h | DV2: FH_MOMENTUM_FILTER_TF=15m | DW2: FIRST_OPEN_THROTTLE_FILTER_TF=OFF | DX2: FIRST_OPEN_THROTTLE_FILTER_TF=D | DY2: FIRST_OPEN_THROTTLE_FILTER_TF=4h | DZ2: FIRST_OPEN_THROTTLE_FILTER_TF=1h | EA2: FIRST_OPEN_THROTTLE_FILTER_TF=15m | EB2: FROZEN_STOP_FILTER_TF=OFF | EC2: FROZEN_STOP_FILTER_TF=D | ED2: FROZEN_STOP_FILTER_TF=4h | EE2: FROZEN_STOP_FILTER_TF=1h | EF2: FROZEN_STOP_FILTER_TF=15m | EG2: GOLDEN_RULE_ENFORCE_FILTER_TF=OFF | EH2: GOLDEN_RULE_ENFORCE_FILTER_TF=D | EI2: GOLDEN_RULE_ENFORCE_FILTER_TF=4h | EJ2: GOLDEN_RULE_ENFORCE_FILTER_TF=1h | EK2: GOLDEN_RULE_ENFORCE_FILTER_TF=15m | EL2: GOLDEN_RULE_HTF_VOTE_FILTER_TF=OFF | EM2: GOLDEN_RULE_HTF_VOTE_FILTER_TF=D | EN2: GOLDEN_RULE_HTF_VOTE_FILTER_TF=4h | EO2: GOLDEN_RULE_HTF_VOTE_FILTER_TF=1h | EP2: GOLDEN_RULE_HTF_VOTE_FILTER_TF=15m | EQ2: GR_FILTER_VEC_FILTER_TF=OFF | ER2: GR_FILTER_VEC_FILTER_TF=D | ES2: GR_FILTER_VEC_FILTER_TF=4h | ET2: GR_FILTER_VEC_FILTER_TF=1h | EU2: GR_FILTER_VEC_FILTER_TF=15m | EV2: GR_V5_STATE_FILTER_TF=OFF | EW2: GR_V5_STATE_FILTER_TF=D | EX2: GR_V5_STATE_FILTER_TF=4h | EY2: GR_V5_STATE_FILTER_TF=1h | EZ2: GR_V5_STATE_FILTER_TF=15m | FA2: HAIKU_WINNER_FILTER_TF=OFF | FB2: HAIKU_WINNER_FILTER_TF=D | FC2: HAIKU_WINNER_FILTER_TF=4h | FD2: HAIKU_WINNER_FILTER_TF=1h | FE2: HAIKU_WINNER_FILTER_TF=15m | FF2: LH_HL_FILTER_TF_REQ=2 | FG2: LH_HL_FILTER_TF_REQ=2_ALT | FH2: LIVE_ENTRY_ENGINE_FILTER_TF=OFF | FI2: LIVE_ENTRY_ENGINE_FILTER_TF=D | FJ2: LIVE_ENTRY_ENGINE_FILTER_TF=4h | FK2: LIVE_ENTRY_ENGINE_FILTER_TF=1h | FL2: LIVE_ENTRY_ENGINE_FILTER_TF=15m | FM2: LIVE_ONLY_SIGNALS_BATCH5_FILTER_TF=OFF | FN2: LIVE_ONLY_SIGNALS_BATCH5_FILTER_TF=D | FO2: LIVE_ONLY_SIGNALS_BATCH5_FILTER_TF=4h | FP2: LIVE_ONLY_SIGNALS_BATCH5_FILTER_TF=1h | FQ2: LIVE_ONLY_SIGNALS_BATCH5_FILTER_TF=15m | FR2: MANDATORY_REENTRY_WT_FILTER_TF_MODE=15m_only | FS2: MANDATORY_REENTRY_WT_FILTER_TF_MODE=15m_only_ALT | FT2: MOM3_FILTER_TF=OFF | FU2: MOM3_FILTER_TF=D | FV2: MOM3_FILTER_TF=4h | FW2: MOM3_FILTER_TF=1h | FX2: MOM3_FILTER_TF=15m | FY2: MOMENTUM_BREAKOUT_FILTER_TF=OFF | FZ2: MOMENTUM_BREAKOUT_FILTER_TF=D | GA2: MOMENTUM_BREAKOUT_FILTER_TF=4h | GB2: MOMENTUM_BREAKOUT_FILTER_TF=1h | GC2: MOMENTUM_BREAKOUT_FILTER_TF=15m | GD2: MTF_ARMED_ENTRIES_FILTER_TF=OFF | GE2: MTF_ARMED_ENTRIES_FILTER_TF=D | GF2: MTF_ARMED_ENTRIES_FILTER_TF=4h | GG2: MTF_ARMED_ENTRIES_FILTER_TF=1h | GH2: MTF_ARMED_ENTRIES_FILTER_TF=15m | GI2: MTF_ATR_TRAIL_FILTER_TF=OFF | GJ2: MTF_ATR_TRAIL_FILTER_TF=D | GK2: MTF_ATR_TRAIL_FILTER_TF=4h | GL2: MTF_ATR_TRAIL_FILTER_TF=1h | GM2: MTF_ATR_TRAIL_FILTER_TF=15m | GN2: MTF_DC_REJECT_FILTER_TF=OFF | GO2: MTF_DC_REJECT_FILTER_TF=D | GP2: MTF_DC_REJECT_FILTER_TF=4h | GQ2: MTF_DC_REJECT_FILTER_TF=1h | GR2: MTF_DC_REJECT_FILTER_TF=15m | GS2: NEWBORN_LOSS_KILL_FILTER_TF=OFF | GT2: NEWBORN_LOSS_KILL_FILTER_TF=D | GU2: NEWBORN_LOSS_KILL_FILTER_TF=4h | GV2: NEWBORN_LOSS_KILL_FILTER_TF=1h | GW2: NEWBORN_LOSS_KILL_FILTER_TF=15m | GX2: NEWBORN_PROTECT_FILTER_TF=OFF | GY2: NEWBORN_PROTECT_FILTER_TF=D | GZ2: NEWBORN_PROTECT_FILTER_TF=4h | HA2: NEWBORN_PROTECT_FILTER_TF=1h | HB2: NEWBORN_PROTECT_FILTER_TF=15m | HC2: NOLOSS_BYPASS_WT5OF5_FILTER_TF=OFF | HD2: NOLOSS_BYPASS_WT5OF5_FILTER_TF=D | HE2: NOLOSS_BYPASS_WT5OF5_FILTER_TF=4h | HF2: NOLOSS_BYPASS_WT5OF5_FILTER_TF=1h | HG2: NOLOSS_BYPASS_WT5OF5_FILTER_TF=15m | HH2: OPEN_INTENT_SIZE_GATES_FILTER_TF=OFF | HI2: OPEN_INTENT_SIZE_GATES_FILTER_TF=D | HJ2: OPEN_INTENT_SIZE_GATES_FILTER_TF=4h | HK2: OPEN_INTENT_SIZE_GATES_FILTER_TF=1h | HL2: OPEN_INTENT_SIZE_GATES_FILTER_TF=15m | HM2: PARTIAL_PROFIT_LOCK_V2_FILTER_TF=OFF | HN2: PARTIAL_PROFIT_LOCK_V2_FILTER_TF=D | HO2: PARTIAL_PROFIT_LOCK_V2_FILTER_TF=4h | HP2: PARTIAL_PROFIT_LOCK_V2_FILTER_TF=1h | HQ2: PARTIAL_PROFIT_LOCK_V2_FILTER_TF=15m | HR2: PEAK_GIVEBACK_BE_EROSION_FILTER_TF=OFF | HS2: PEAK_GIVEBACK_BE_EROSION_FILTER_TF=D | HT2: PEAK_GIVEBACK_BE_EROSION_FILTER_TF=4h | HU2: PEAK_GIVEBACK_BE_EROSION_FILTER_TF=1h | HV2: PEAK_GIVEBACK_BE_EROSION_FILTER_TF=15m | HW2: WT_15M_BOUNCE_BB_MAX=0.95 | HX2: WT_15M_BOUNCE_BB_MAX=0.9 | HY2: WT_15M_BOUNCE_BB_MAX=0.8 | HZ2: WT_15M_BOUNCE_BB_MIN=0.05 | IA2: WT_15M_BOUNCE_BB_MIN=0.1 | IB2: WT_15M_BOUNCE_BB_MIN=0.2 | IC2: WT_15M_BOUNCE_HIGH_1H_GT_PREV=True | ID2: WT_15M_BOUNCE_HIGH_1H_GT_PREV=False | IE2: WT_15M_BOUNCE_LOW_1H_GT_PREV=True | IF2: WT_15M_BOUNCE_LOW_1H_GT_PREV=False | IG2: WT_15M_BOUNCE_REL_VOL_GT_1=True | IH2: WT_15M_BOUNCE_REL_VOL_GT_1=False | II2: Live Location | IJ2: Vec Hook | IK2: Type | IL2: Correct Options
A3: DD_BOUNCE_ENABLED | B3: True | E3: =MAX('AUGMENT_TREND'!E:E) | F3: =IFERROR(VLOOKUP($A3&"="&$B3,Results_30d_Deltas!$A$2:$H$5000,5,FALSE),"") | G3: =IFERROR(VLOOKUP($A3,Results_30d_Deltas!$A$2:$H$5000,7,FALSE)-E3,"") | H3: =IFERROR(VLOOKUP($A3,Results_30d_Deltas!$A$2:$H$5000,6,FALSE),"") | K3: =IF(B3=C3,"YES","NO") | IJ3: ez_manage.py:4586 top() | IK3: v12_quick_engine.py:567 x9
A4: MAX_AUGMENTS_PER_POSITION | B4: 0 | E4: =IF(F4="",E3,IF(F4>0,E3+F4,E3)) | F4: =IFERROR(VLOOKUP($A4&"="&$B4,Results_30d_Deltas!$A$2:$H$5000,5,FALSE),"") | G4: =IFERROR(VLOOKUP($A4,Results_30d_Deltas!$A$2:$H$5000,7,FALSE)-E3,"") | H4: =IFERROR(VLOOKUP($A4,Results_30d_Deltas!$A$2:$H$5000,6,FALSE),"") | K4: =IF(B4=C4,"YES","NO") | IJ4: ez_manage.py:3521 top() | IK4: v12_quick_engine.py:2267 x7
A5: MAX_AUGMENTS_PER_POSITION | B5: 0.5 | E5: =IF(F5="",E4,IF(F5>0,E4+F5,E4)) | F5: =IFERROR(VLOOKUP($A5&"="&$B5,Results_30d_Deltas!$A$2:$H$5000,5,FALSE),"") | G5: =IFERROR(VLOOKUP($A5,Results_30d_Deltas!$A$2:$H$5000,7,FALSE)-E4,"") | H5: =IFERROR(VLOOKUP($A5,Results_30d_Deltas!$A$2:$H$5000,6,FALSE),"") | K5: =IF(B5=C5,"YES","NO") | IJ5: ez_manage.py:3521 top() | IK5: v12_quick_engine.py:2267 x7
A6: MAX_AUGMENTS_PER_POSITION | B6: 1.0 | E6: =IF(F6="",E5,IF(F6>0,E5+F6,E5)) | F6: =IFERROR(VLOOKUP($A6&"="&$B6,Results_30d_Deltas!$A$2:$H$5000,5,FALSE),"") | G6: =IFERROR(VLOOKUP($A6,Results_30d_Deltas!$A$2:$H$5000,7,FALSE)-E5,"") | H6: =IFERROR(VLOOKUP($A6,Results_30d_Deltas!$A$2:$H$5000,6,FALSE),"") | K6: =IF(B6=C6,"YES","NO") | IJ6: ez_manage.py:3521 top() | IK6: v12_quick_engine.py:2267 x7
A7: MAX_AUGMENTS_PER_POSITION | B7: 2.0 | E7: =IF(F7="",E6,IF(F7>0,E6+F7,E6)) | F7: =IFERROR(VLOOKUP($A7&"="&$B7,Results_30d_Deltas!$A$2:$H$5000,5,FALSE),"") | G7: =IFERROR(VLOOKUP($A7,Results_30d_Deltas!$A$2:$H$5000,7,FALSE)-E6,"") | H7: =IFERROR(VLOOKUP($A7,Results_30d_Deltas!$A$2:$H$5000,6,FALSE),"") | K7: =IF(B7=C7,"YES","NO") | IJ7: ez_manage.py:3521 top() | IK7: v12_quick_engine.py:2267 x7
A8: AUGMENTED_POSITIONS_GUARD_FLOOR_MULT | B8: 0 | E8: =IF(F8="",E7,IF(F8>0,E7+F8,E7)) | F8: =IFERROR(VLOOKUP($A8&"="&$B8,Results_30d_Deltas!$A$2:$H$5000,5,FALSE),"") | G8: =IFERROR(VLOOKUP($A8,Results_30d_Deltas!$A$2:$H$5000,7,FALSE)-E7,"") | H8: =IFERROR(VLOOKUP($A8,Results_30d_Deltas!$A$2:$H$5000,6,FALSE),"") | K8: =IF(B8=C8,"YES","NO") | IJ8: ez_manage.py:4336 top() | IK8: v12_quick_engine.py:221 x13
A9: AUGMENTED_POSITIONS_GUARD_FLOOR_MULT | B9: 0.5 | E9: =IF(F9="",E8,IF(F9>0,E8+F9,E8)) | F9: =IFERROR(VLOOKUP($A9&"="&$B9,Results_30d_Deltas!$A$2:$H$5000,5,FALSE),"") | G9: =IFERROR(VLOOKUP($A9,Results_30d_Deltas!$A$2:$H$5000,7,FALSE)-E8,"") | H9: =IFERROR(VLOOKUP($A9,Results_30d_Deltas!$A$2:$H$5000,6,FALSE),"") | K9: =IF(B9=C9,"YES","NO") | IJ9: ez_manage.py:4336 top() | IK9: v12_quick_engine.py:221 x13
A10: AUGMENTED_POSITIONS_GUARD_FLOOR_MULT | B10: 1.0 | E10: =IF(F10="",E9,IF(F10>0,E9+F10,E9)) | F10: =IFERROR(VLOOKUP($A10&"="&$B10,Results_30d_Deltas!$A$2:$H$5000,5,FALSE),"") | G10: =IFERROR(VLOOKUP($A10,Results_30d_Deltas!$A$2:$H$5000,7,FALSE)-E9,"") | H10: =IFERROR(VLOOKUP($A10,Results_30d_Deltas!$A$2:$H$5000,6,FALSE),"") | K10: =IF(B10=C10,"YES","NO") | IJ10: ez_manage.py:4336 top() | IK10: v12_quick_engine.py:221 x13
A11: AUGMENTED_POSITIONS_GUARD_FLOOR_MULT | B11: 2.0 | E11: =IF(F11="",E10,IF(F11>0,E10+F11,E10)) | F11: =IFERROR(VLOOKUP($A11&"="&$B11,Results_30d_Deltas!$A$2:$H$5000,5,FALSE),"") | G11: =IFERROR(VLOOKUP($A11,Results_30d_Deltas!$A$2:$H$5000,7,FALSE)-E10,"") | H11: =IFERROR(VLOOKUP($A11,Results_30d_Deltas!$A$2:$H$5000,6,FALSE),"") | K11: =IF(B11=C11,"YES","NO") | IJ11: ez_manage.py:4336 top() | IK11: v12_quick_engine.py:221 x13
A12: AUGMENT_AT_LOSS_ENABLED | B12: False | E12: =IF(F12="",E11,IF(F12>0,E11+F12,E11)) | F12: =IFERROR(VLOOKUP($A12&"="&$B12,Results_30d_Deltas!$A$2:$H$5000,5,FALSE),"") | G12: =IFERROR(VLOOKUP($A12,Results_30d_Deltas!$A$2:$H$5000,7,FALSE)-E11,"") | H12: =IFERROR(VLOOKUP($A12,Results_30d_Deltas!$A$2:$H$5000,6,FALSE),"") | K12: =IF(B12=C12,"YES","NO") | IJ12: ez_manage.py:5956 top() | IK12: v12_quick_engine.py:228 x5
A13: AUGMENT_AT_LOSS_ENABLED | B13: True | E13: =IF(F13="",E12,IF(F13>0,E12+F13,E12)) | F13: =IFERROR(VLOOKUP($A13&"="&$B13,Results_30d_Deltas!$A$2:$H$5000,5,FALSE),"") | G13: =IFERROR(VLOOKUP($A13,Results_30d_Deltas!$A$2:$H$5000,7,FALSE)-E12,"") | H13: =IFERROR(VLOOKUP($A13,Results_30d_Deltas!$A$2:$H$5000,6,FALSE),"") | K13: =IF(B13=C13,"YES","NO") | IJ13: ez_manage.py:5956 top() | IK13: v12_quick_engine.py:228 x5
A14: AUGMENT_FALLBACK_GAIN_PCT | B14: 0.5 | E14: =IF(F14="",E13,IF(F14>0,E13+F14,E13)) | F14: =IFERROR(VLOOKUP($A14&"="&$B14,Results_30d_Deltas!$A$2:$H$5000,5,FALSE),"") | G14: =IFERROR(VLOOKUP($A14,Results_30d_Deltas!$A$2:$H$5000,7,FALSE)-E13,"") | H14: =IFERROR(VLOOKUP($A14,Results_30d_Deltas!$A$2:$H$5000,6,FALSE),"") | K14: =IF(B14=C14,"YES","NO") | IJ14: ez_manage.py:56864 top() | IK14: v12_quick_engine.py:4990 x4
A15: AUGMENT_FALLBACK_GAIN_PCT | B15: 0.75 | E15: =IF(F15="",E14,IF(F15>0,E14+F15,E14)) | F15: =IFERROR(VLOOKUP($A15&"="&$B15,Results_30d_Deltas!$A$2:$H$5000,5,FALSE),"") | G15: =IFERROR(VLOOKUP($A15,Results_30d_Deltas!$A$2:$H$5000,7,FALSE)-E14,"") | H15: =IFERROR(VLOOKUP($A15,Results_30d_Deltas!$A$2:$H$5000,6,FALSE),"") | K15: =IF(B15=C15,"YES","NO") | IJ15: ez_manage.py:56864 top() | IK15: v12_quick_engine.py:4990 x4
... A58: UNIVERSAL_AUGMENT_GAIN_GATE_ENABLED | B58: True | E58: =IF(F58="",E57,IF(F58>0,E57+F58,E57)) | F58: =IFERROR(VLOOKUP($A58&"="&$B58,Results_30d_Deltas!$A$2:$H$5000,5,FALSE),"") | G58: =IFERROR(VLOOKUP($A58,Results_30d_Deltas!$A$2:$H$5000,7,FALSE)-E57,"") | H58: =IFERROR(VLOOKUP($A58,Results_30d_Deltas!$A$2:$H$5000,6,FALSE),"") | K58: =IF(B58=C58,"YES","NO") | IJ58: ez_manage.py:5804 top() | IK58: v12_quick_engine.py:3581 x3

Sheet REDUCE_PROFIT_LOCK
A1: 10 REDUCE_PROFIT_LOCK - 19 bases -> 53 rows - 231 per-row FULLY CONNECTED
A2: Switch | B2: default | C2: override | D2: Family | E2: =MAX('AUGMENT_RISK_SIZING'!E$2:E$5000) | F2: VECTOR_DELTA | G2: LIVE_DELTA | H2: LIVE_SHARPE | I2: REAL_COMPLETE | J2: PER_ROW_FILTERS | K2: is_default (backup if bold lost) | L2: ATR_TRAIL_FILTER_TF=OFF | M2: ATR_TRAIL_FILTER_TF=D | N2: ATR_TRAIL_FILTER_TF=4h | O2: ATR_TRAIL_FILTER_TF=1h | P2: ATR_TRAIL_FILTER_TF=15m | Q2: BAR_PATTERNS_FILTER_TF=OFF | R2: BAR_PATTERNS_FILTER_TF=D | S2: BAR_PATTERNS_FILTER_TF=4h | T2: BAR_PATTERNS_FILTER_TF=1h | U2: BAR_PATTERNS_FILTER_TF=15m | V2: BB_PULLBACK_GATE_FILTER_TF=OFF | W2: BB_PULLBACK_GATE_FILTER_TF=D | X2: BB_PULLBACK_GATE_FILTER_TF=4h | Y2: BB_PULLBACK_GATE_FILTER_TF=1h | Z2: BB_PULLBACK_GATE_FILTER_TF=15m | AA2: BB_RECOVERY_ENTRY_FILTER_TF=OFF | AB2: BB_RECOVERY_ENTRY_FILTER_TF=D | AC2: BB_RECOVERY_ENTRY_FILTER_TF=4h | AD2: BB_RECOVERY_ENTRY_FILTER_TF=1h | AE2: BB_RECOVERY_ENTRY_FILTER_TF=15m | AF2: BB_RECOVERY_FILTER_TF=OFF | AG2: BB_RECOVERY_FILTER_TF=D | AH2: BB_RECOVERY_FILTER_TF=4h | AI2: BB_RECOVERY_FILTER_TF=1h | AJ2: BB_RECOVERY_FILTER_TF=15m | AK2: BREAKEVEN_GAIN_EROSION_FILTER_TF=OFF | AL2: BREAKEVEN_GAIN_EROSION_FILTER_TF=D | AM2: BREAKEVEN_GAIN_EROSION_FILTER_TF=4h | AN2: BREAKEVEN_GAIN_EROSION_FILTER_TF=1h | AO2: BREAKEVEN_GAIN_EROSION_FILTER_TF=15m | AP2: BREAKOUT_RETEST_FILTER_TF=OFF | AQ2: BREAKOUT_RETEST_FILTER_TF=D | AR2: BREAKOUT_RETEST_FILTER_TF=4h | AS2: BREAKOUT_RETEST_FILTER_TF=1h | AT2: BREAKOUT_RETEST_FILTER_TF=15m | AU2: BT_WT_CROSS_LADDER_FILTER_TF=OFF | AV2: BT_WT_CROSS_LADDER_FILTER_TF=D | AW2: BT_WT_CROSS_LADDER_FILTER_TF=4h | AX2: BT_WT_CROSS_LADDER_FILTER_TF=1h | AY2: BT_WT_CROSS_LADDER_FILTER_TF=15m | AZ2: CANDLE_PATTERN_STOPS_FILTER_TF=OFF | BA2: CANDLE_PATTERN_STOPS_FILTER_TF=D | BB2: CANDLE_PATTERN_STOPS_FILTER_TF=4h | BC2: CANDLE_PATTERN_STOPS_FILTER_TF=1h | BD2: CANDLE_PATTERN_STOPS_FILTER_TF=15m | BE2: CIRCUIT_SHARPE_GATES_FILTER_TF=OFF | BF2: CIRCUIT_SHARPE_GATES_FILTER_TF=D | BG2: CIRCUIT_SHARPE_GATES_FILTER_TF=4h | BH2: CIRCUIT_SHARPE_GATES_FILTER_TF=1h | BI2: CIRCUIT_SHARPE_GATES_FILTER_TF=15m | BJ2: DC_BREACH_REDUCE_FILTER_TF=OFF | BK2: DC_BREACH_REDUCE_FILTER_TF=D | BL2: DC_BREACH_REDUCE_FILTER_TF=4h | BM2: DC_BREACH_REDUCE_FILTER_TF=1h | BN2: DC_BREACH_REDUCE_FILTER_TF=15m | BO2: DC_BREAK_FILTER_TF=OFF | BP2: DC_BREAK_FILTER_TF=D | BQ2: DC_BREAK_FILTER_TF=4h | BR2: DC_BREAK_FILTER_TF=1h | BS2: DC_BREAK_FILTER_TF=15m | BT2: DC_MOMENTUM_BOTA_SCORER_FILTER_TF=OFF | BU2: DC_MOMENTUM_BOTA_SCORER_FILTER_TF=D | BV2: DC_MOMENTUM_BOTA_SCORER_FILTER_TF=4h | BW2: DC_MOMENTUM_BOTA_SCORER_FILTER_TF=1h | BX2: DC_MOMENTUM_BOTA_SCORER_FILTER_TF=15m | BY2: DELTA_ENGINE_FILTER_TF=OFF | BZ2: DELTA_ENGINE_FILTER_TF=D | CA2: DELTA_ENGINE_FILTER_TF=4h | CB2: DELTA_ENGINE_FILTER_TF=1h | CC2: DELTA_ENGINE_FILTER_TF=15m | CD2: EMA_9_21_FILTER_FILTER_TF=OFF | CE2: EMA_9_21_FILTER_FILTER_TF=D | CF2: EMA_9_21_FILTER_FILTER_TF=4h | CG2: EMA_9_21_FILTER_FILTER_TF=1h | CH2: EMA_9_21_FILTER_FILTER_TF=15m | CI2: EMA_BLANKET_FILTER_FILTER_TF=OFF | CJ2: EMA_BLANKET_FILTER_FILTER_TF=D | CK2: EMA_BLANKET_FILTER_FILTER_TF=4h | CL2: EMA_BLANKET_FILTER_FILTER_TF=1h | CM2: EMA_BLANKET_FILTER_FILTER_TF=15m | CN2: EMERGENCY_BRAKE_FILTER_TF=OFF | CO2: EMERGENCY_BRAKE_FILTER_TF=D | CP2: EMERGENCY_BRAKE_FILTER_TF=4h | CQ2: EMERGENCY_BRAKE_FILTER_TF=1h | CR2: EMERGENCY_BRAKE_FILTER_TF=15m | CS2: EXIT_R1_R2_FILTER_TF=OFF | CT2: EXIT_R1_R2_FILTER_TF=D | CU2: EXIT_R1_R2_FILTER_TF=4h | CV2: EXIT_R1_R2_FILTER_TF=1h | CW2: EXIT_R1_R2_FILTER_TF=15m | CX2: EXIT_TIGHT_BREAKOUT_SCORER_FILTER_TF=OFF | CY2: EXIT_TIGHT_BREAKOUT_SCORER_FILTER_TF=D | CZ2: EXIT_TIGHT_BREAKOUT_SCORER_FILTER_TF=4h | DA2: EXIT_TIGHT_BREAKOUT_SCORER_FILTER_TF=1h | DB2: EXIT_TIGHT_BREAKOUT_SCORER_FILTER_TF=15m | DC2: EXIT_TOP_FADE_FILTER_TF=OFF | DD2: EXIT_TOP_FADE_FILTER_TF=D | DE2: EXIT_TOP_FADE_FILTER_TF=4h | DF2: EXIT_TOP_FADE_FILTER_TF=1h | DG2: EXIT_TOP_FADE_FILTER_TF=15m | DH2: EXIT_TO_REDUCE_ADAPTER_FILTER_TF=OFF | DI2: EXIT_TO_REDUCE_ADAPTER_FILTER_TF=D | DJ2: EXIT_TO_REDUCE_ADAPTER_FILTER_TF=4h | DK2: EXIT_TO_REDUCE_ADAPTER_FILTER_TF=1h | DL2: EXIT_TO_REDUCE_ADAPTER_FILTER_TF=15m | DM2: FAST_RISER_FILTER_TF=OFF | DN2: FAST_RISER_FILTER_TF=D | DO2: FAST_RISER_FILTER_TF=4h | DP2: FAST_RISER_FILTER_TF=1h | DQ2: FAST_RISER_FILTER_TF=15m | DR2: FH_MOMENTUM_FILTER_TF=OFF | DS2: FH_MOMENTUM_FILTER_TF=D | DT2: FH_MOMENTUM_FILTER_TF=4h | DU2: FH_MOMENTUM_FILTER_TF=1h | DV2: FH_MOMENTUM_FILTER_TF=15m | DW2: FIRST_OPEN_THROTTLE_FILTER_TF=OFF | DX2: FIRST_OPEN_THROTTLE_FILTER_TF=D | DY2: FIRST_OPEN_THROTTLE_FILTER_TF=4h | DZ2: FIRST_OPEN_THROTTLE_FILTER_TF=1h | EA2: FIRST_OPEN_THROTTLE_FILTER_TF=15m | EB2: FROZEN_STOP_FILTER_TF=OFF | EC2: FROZEN_STOP_FILTER_TF=D | ED2: FROZEN_STOP_FILTER_TF=4h | EE2: FROZEN_STOP_FILTER_TF=1h | EF2: FROZEN_STOP_FILTER_TF=15m | EG2: GOLDEN_RULE_ENFORCE_FILTER_TF=OFF | EH2: GOLDEN_RULE_ENFORCE_FILTER_TF=D | EI2: GOLDEN_RULE_ENFORCE_FILTER_TF=4h | EJ2: GOLDEN_RULE_ENFORCE_FILTER_TF=1h | EK2: GOLDEN_RULE_ENFORCE_FILTER_TF=15m | EL2: GOLDEN_RULE_HTF_VOTE_FILTER_TF=OFF | EM2: GOLDEN_RULE_HTF_VOTE_FILTER_TF=D | EN2: GOLDEN_RULE_HTF_VOTE_FILTER_TF=4h | EO2: GOLDEN_RULE_HTF_VOTE_FILTER_TF=1h | EP2: GOLDEN_RULE_HTF_VOTE_FILTER_TF=15m | EQ2: GR_FILTER_VEC_FILTER_TF=OFF | ER2: GR_FILTER_VEC_FILTER_TF=D | ES2: GR_FILTER_VEC_FILTER_TF=4h | ET2: GR_FILTER_VEC_FILTER_TF=1h | EU2: GR_FILTER_VEC_FILTER_TF=15m | EV2: GR_V5_STATE_FILTER_TF=OFF | EW2: GR_V5_STATE_FILTER_TF=D | EX2: GR_V5_STATE_FILTER_TF=4h | EY2: GR_V5_STATE_FILTER_TF=1h | EZ2: GR_V5_STATE_FILTER_TF=15m | FA2: HAIKU_WINNER_FILTER_TF=OFF | FB2: HAIKU_WINNER_FILTER_TF=D | FC2: HAIKU_WINNER_FILTER_TF=4h | FD2: HAIKU_WINNER_FILTER_TF=1h | FE2: HAIKU_WINNER_FILTER_TF=15m | FF2: LH_HL_FILTER_TF_REQ=2 | FG2: LH_HL_FILTER_TF_REQ=2_ALT | FH2: LIVE_ENTRY_ENGINE_FILTER_TF=OFF | FI2: LIVE_ENTRY_ENGINE_FILTER_TF=D | FJ2: LIVE_ENTRY_ENGINE_FILTER_TF=4h | FK2: LIVE_ENTRY_ENGINE_FILTER_TF=1h | FL2: LIVE_ENTRY_ENGINE_FILTER_TF=15m | FM2: LIVE_ONLY_SIGNALS_BATCH5_FILTER_TF=OFF | FN2: LIVE_ONLY_SIGNALS_BATCH5_FILTER_TF=D | FO2: LIVE_ONLY_SIGNALS_BATCH5_FILTER_TF=4h | FP2: LIVE_ONLY_SIGNALS_BATCH5_FILTER_TF=1h | FQ2: LIVE_ONLY_SIGNALS_BATCH5_FILTER_TF=15m | FR2: MANDATORY_REENTRY_WT_FILTER_TF_MODE=15m_only | FS2: MANDATORY_REENTRY_WT_FILTER_TF_MODE=15m_only_ALT | FT2: MOM3_FILTER_TF=OFF | FU2: MOM3_FILTER_TF=D | FV2: MOM3_FILTER_TF=4h | FW2: MOM3_FILTER_TF=1h | FX2: MOM3_FILTER_TF=15m | FY2: MOMENTUM_BREAKOUT_FILTER_TF=OFF | FZ2: MOMENTUM_BREAKOUT_FILTER_TF=D | GA2: MOMENTUM_BREAKOUT_FILTER_TF=4h | GB2: MOMENTUM_BREAKOUT_FILTER_TF=1h | GC2: MOMENTUM_BREAKOUT_FILTER_TF=15m | GD2: MTF_ARMED_ENTRIES_FILTER_TF=OFF | GE2: MTF_ARMED_ENTRIES_FILTER_TF=D | GF2: MTF_ARMED_ENTRIES_FILTER_TF=4h | GG2: MTF_ARMED_ENTRIES_FILTER_TF=1h | GH2: MTF_ARMED_ENTRIES_FILTER_TF=15m | GI2: MTF_ATR_TRAIL_FILTER_TF=OFF | GJ2: MTF_ATR_TRAIL_FILTER_TF=D | GK2: MTF_ATR_TRAIL_FILTER_TF=4h | GL2: MTF_ATR_TRAIL_FILTER_TF=1h | GM2: MTF_ATR_TRAIL_FILTER_TF=15m | GN2: MTF_DC_REJECT_FILTER_TF=OFF | GO2: MTF_DC_REJECT_FILTER_TF=D | GP2: MTF_DC_REJECT_FILTER_TF=4h | GQ2: MTF_DC_REJECT_FILTER_TF=1h | GR2: MTF_DC_REJECT_FILTER_TF=15m | GS2: NEWBORN_LOSS_KILL_FILTER_TF=OFF | GT2: NEWBORN_LOSS_KILL_FILTER_TF=D | GU2: NEWBORN_LOSS_KILL_FILTER_TF=4h | GV2: NEWBORN_LOSS_KILL_FILTER_TF=1h | GW2: NEWBORN_LOSS_KILL_FILTER_TF=15m | GX2: NEWBORN_PROTECT_FILTER_TF=OFF | GY2: NEWBORN_PROTECT_FILTER_TF=D | GZ2: NEWBORN_PROTECT_FILTER_TF=4h | HA2: NEWBORN_PROTECT_FILTER_TF=1h | HB2: NEWBORN_PROTECT_FILTER_TF=15m | HC2: NOLOSS_BYPASS_WT5OF5_FILTER_TF=OFF | HD2: NOLOSS_BYPASS_WT5OF5_FILTER_TF=D | HE2: NOLOSS_BYPASS_WT5OF5_FILTER_TF=4h | HF2: NOLOSS_BYPASS_WT5OF5_FILTER_TF=1h | HG2: NOLOSS_BYPASS_WT5OF5_FILTER_TF=15m | HH2: OPEN_INTENT_SIZE_GATES_FILTER_TF=OFF | HI2: OPEN_INTENT_SIZE_GATES_FILTER_TF=D | HJ2: OPEN_INTENT_SIZE_GATES_FILTER_TF=4h | HK2: OPEN_INTENT_SIZE_GATES_FILTER_TF=1h | HL2: OPEN_INTENT_SIZE_GATES_FILTER_TF=15m | HM2: PARTIAL_PROFIT_LOCK_V2_FILTER_TF=OFF | HN2: PARTIAL_PROFIT_LOCK_V2_FILTER_TF=D | HO2: PARTIAL_PROFIT_LOCK_V2_FILTER_TF=4h | HP2: PARTIAL_PROFIT_LOCK_V2_FILTER_TF=1h | HQ2: PARTIAL_PROFIT_LOCK_V2_FILTER_TF=15m | HR2: PEAK_GIVEBACK_BE_EROSION_FILTER_TF=OFF | HS2: PEAK_GIVEBACK_BE_EROSION_FILTER_TF=D | HT2: PEAK_GIVEBACK_BE_EROSION_FILTER_TF=4h | HU2: PEAK_GIVEBACK_BE_EROSION_FILTER_TF=1h | HV2: PEAK_GIVEBACK_BE_EROSION_FILTER_TF=15m | HW2: WT_15M_BOUNCE_BB_MAX=0.95 | HX2: WT_15M_BOUNCE_BB_MAX=0.9 | HY2: WT_15M_BOUNCE_BB_MAX=0.8 | HZ2: WT_15M_BOUNCE_BB_MIN=0.05 | IA2: WT_15M_BOUNCE_BB_MIN=0.1 | IB2: WT_15M_BOUNCE_BB_MIN=0.2 | IC2: WT_15M_BOUNCE_HIGH_1H_GT_PREV=True | ID2: WT_15M_BOUNCE_HIGH_1H_GT_PREV=False | IE2: WT_15M_BOUNCE_LOW_1H_GT_PREV=True | IF2: WT_15M_BOUNCE_LOW_1H_GT_PREV=False | IG2: WT_15M_BOUNCE_REL_VOL_GT_1=True | IH2: WT_15M_BOUNCE_REL_VOL_GT_1=False | II2: Live Location | IJ2: Vec Hook | IK2: Type | IL2: Correct Options
A3: PEAK_GIVEBACK_DROP_TRIGGER_ENABLED | B3: False | E3: =MAX('AUGMENT_RISK_SIZING'!E:E) | F3: =IFERROR(VLOOKUP($A3&"="&$B3,Results_30d_Deltas!$A$2:$H$5000,5,FALSE),"") | G3: =IFERROR(VLOOKUP($A3,Results_30d_Deltas!$A$2:$H$5000,7,FALSE)-E3,"") | H3: =IFERROR(VLOOKUP($A3,Results_30d_Deltas!$A$2:$H$5000,6,FALSE),"") | K3: =IF(B3=C3,"YES","NO") | IJ3: ez_manage.py:5168 top() | IK3: v12_quick_engine.py:2682 x3
A4: PEAK_GIVEBACK_DROP_TRIGGER_ENABLED | B4: True | E4: =IF(F4="",E3,IF(F4>0,E3+F4,E3)) | F4: =IFERROR(VLOOKUP($A4&"="&$B4,Results_30d_Deltas!$A$2:$H$5000,5,FALSE),"") | G4: =IFERROR(VLOOKUP($A4,Results_30d_Deltas!$A$2:$H$5000,7,FALSE)-E3,"") | H4: =IFERROR(VLOOKUP($A4,Results_30d_Deltas!$A$2:$H$5000,6,FALSE),"") | K4: =IF(B4=C4,"YES","NO") | IJ4: ez_manage.py:5168 top() | IK4: v12_quick_engine.py:2682 x3
A5: PARTIAL_PROFIT_LOCK_FRAC | B5: 0 | E5: =IF(F5="",E4,IF(F5>0,E4+F5,E4)) | F5: =IFERROR(VLOOKUP($A5&"="&$B5,Results_30d_Deltas!$A$2:$H$5000,5,FALSE),"") | G5: =IFERROR(VLOOKUP($A5,Results_30d_Deltas!$A$2:$H$5000,7,FALSE)-E4,"") | H5: =IFERROR(VLOOKUP($A5,Results_30d_Deltas!$A$2:$H$5000,6,FALSE),"") | K5: =IF(B5=C5,"YES","NO") | IJ5: ez_manage.py:5158 top() | IK5: v12_quick_engine.py:2674 x7
A6: PARTIAL_PROFIT_LOCK_FRAC | B6: 0.5 | E6: =IF(F6="",E5,IF(F6>0,E5+F6,E5)) | F6: =IFERROR(VLOOKUP($A6&"="&$B6,Results_30d_Deltas!$A$2:$H$5000,5,FALSE),"") | G6: =IFERROR(VLOOKUP($A6,Results_30d_Deltas!$A$2:$H$5000,7,FALSE)-E5,"") | H6: =IFERROR(VLOOKUP($A6,Results_30d_Deltas!$A$2:$H$5000,6,FALSE),"") | K6: =IF(B6=C6,"YES","NO") | IJ6: ez_manage.py:5158 top() | IK6: v12_quick_engine.py:2674 x7
A7: PARTIAL_PROFIT_LOCK_FRAC | B7: 1.0 | E7: =IF(F7="",E6,IF(F7>0,E6+F7,E6)) | F7: =IFERROR(VLOOKUP($A7&"="&$B7,Results_30d_Deltas!$A$2:$H$5000,5,FALSE),"") | G7: =IFERROR(VLOOKUP($A7,Results_30d_Deltas!$A$2:$H$5000,7,FALSE)-E6,"") | H7: =IFERROR(VLOOKUP($A7,Results_30d_Deltas!$A$2:$H$5000,6,FALSE),"") | K7: =IF(B7=C7,"YES","NO") | IJ7: ez_manage.py:5158 top() | IK7: v12_quick_engine.py:2674 x7
A8: PARTIAL_PROFIT_LOCK_FRAC | B8: 2.0 | E8: =IF(F8="",E7,IF(F8>0,E7+F8,E7)) | F8: =IFERROR(VLOOKUP($A8&"="&$B8,Results_30d_Deltas!$A$2:$H$5000,5,FALSE),"") | G8: =IFERROR(VLOOKUP($A8,Results_30d_Deltas!$A$2:$H$5000,7,FALSE)-E7,"") | H8: =IFERROR(VLOOKUP($A8,Results_30d_Deltas!$A$2:$H$5000,6,FALSE),"") | K8: =IF(B8=C8,"YES","NO") | IJ8: ez_manage.py:5158 top() | IK8: v12_quick_engine.py:2674 x7
A9: MIN_HOLD_BARS_BEFORE_EXIT | B9: 16 | E9: =IF(F9="",E8,IF(F9>0,E8+F9,E8)) | F9: =IFERROR(VLOOKUP($A9&"="&$B9,Results_30d_Deltas!$A$2:$H$5000,5,FALSE),"") | G9: =IFERROR(VLOOKUP($A9,Results_30d_Deltas!$A$2:$H$5000,7,FALSE)-E8,"") | H9: =IFERROR(VLOOKUP($A9,Results_30d_Deltas!$A$2:$H$5000,6,FALSE),"") | K9: =IF(B9=C9,"YES","NO") | IJ9: ez_manage.py:4990 top() | IK9: v12_quick_engine.py:2309 x7
A10: MIN_HOLD_BARS_BEFORE_EXIT | B10: 24 | E10: =IF(F10="",E9,IF(F10>0,E9+F10,E9)) | F10: =IFERROR(VLOOKUP($A10&"="&$B10,Results_30d_Deltas!$A$2:$H$5000,5,FALSE),"") | G10: =IFERROR(VLOOKUP($A10,Results_30d_Deltas!$A$2:$H$5000,7,FALSE)-E9,"") | H10: =IFERROR(VLOOKUP($A10,Results_30d_Deltas!$A$2:$H$5000,6,FALSE),"") | K10: =IF(B10=C10,"YES","NO") | IJ10: ez_manage.py:4990 top() | IK10: v12_quick_engine.py:2309 x7
A11: MIN_HOLD_BARS_BEFORE_EXIT | B11: 32 | E11: =IF(F11="",E10,IF(F11>0,E10+F11,E10)) | F11: =IFERROR(VLOOKUP($A11&"="&$B11,Results_30d_Deltas!$A$2:$H$5000,5,FALSE),"") | G11: =IFERROR(VLOOKUP($A11,Results_30d_Deltas!$A$2:$H$5000,7,FALSE)-E10,"") | H11: =IFERROR(VLOOKUP($A11,Results_30d_Deltas!$A$2:$H$5000,6,FALSE),"") | K11: =IF(B11=C11,"YES","NO") | IJ11: ez_manage.py:4990 top() | IK11: v12_quick_engine.py:2309 x7
A12: MIN_HOLD_BARS_BEFORE_EXIT | B12: 40 | E12: =IF(F12="",E11,IF(F12>0,E11+F12,E11)) | F12: =IFERROR(VLOOKUP($A12&"="&$B12,Results_30d_Deltas!$A$2:$H$5000,5,FALSE),"") | G12: =IFERROR(VLOOKUP($A12,Results_30d_Deltas!$A$2:$H$5000,7,FALSE)-E11,"") | H12: =IFERROR(VLOOKUP($A12,Results_30d_Deltas!$A$2:$H$5000,6,FALSE),"") | K12: =IF(B12=C12,"YES","NO") | IJ12: ez_manage.py:4990 top() | IK12: v12_quick_engine.py:2309 x7
A13: MIN_HOLD_BARS_BEFORE_EXIT | B13: 48 | E13: =IF(F13="",E12,IF(F13>0,E12+F13,E12)) | F13: =IFERROR(VLOOKUP($A13&"="&$B13,Results_30d_Deltas!$A$2:$H$5000,5,FALSE),"") | G13: =IFERROR(VLOOKUP($A13,Results_30d_Deltas!$A$2:$H$5000,7,FALSE)-E12,"") | H13: =IFERROR(VLOOKUP($A13,Results_30d_Deltas!$A$2:$H$5000,6,FALSE),"") | K13: =IF(B13=C13,"YES","NO") | IJ13: ez_manage.py:4990 top() | IK13: v12_quick_engine.py:2309 x7
A14: BREAKEVEN_GAIN_EROSION_ENABLED | B14: False | E14: =IF(F14="",E13,IF(F14>0,E13+F14,E13)) | F14: =IFERROR(VLOOKUP($A14&"="&$B14,Results_30d_Deltas!$A$2:$H$5000,5,FALSE),"") | G14: =IFERROR(VLOOKUP($A14,Results_30d_Deltas!$A$2:$H$5000,7,FALSE)-E13,"") | H14: =IFERROR(VLOOKUP($A14,Results_30d_Deltas!$A$2:$H$5000,6,FALSE),"") | K14: =IF(B14=C14,"YES","NO") | IJ14: ez_manage.py:4400 top() | IK14: v12_quick_engine.py:341 x8
A15: BREAKEVEN_GAIN_EROSION_ENABLED | B15: True | E15: =IF(F15="",E14,IF(F15>0,E14+F15,E14)) | F15: =IFERROR(VLOOKUP($A15&"="&$B15,Results_30d_Deltas!$A$2:$H$5000,5,FALSE),"") | G15: =IFERROR(VLOOKUP($A15,Results_30d_Deltas!$A$2:$H$5000,7,FALSE)-E14,"") | H15: =IFERROR(VLOOKUP($A15,Results_30d_Deltas!$A$2:$H$5000,6,FALSE),"") | K15: =IF(B15=C15,"YES","NO") | IJ15: ez_manage.py:4400 top() | IK15: v12_quick_engine.py:341 x8
... A55: SIMPLE_TP_PCT | B55: 2.0 | E55: =IF(F55="",E54,IF(F55>0,E54+F55,E54)) | F55: =IFERROR(VLOOKUP($A55&"="&$B55,Results_30d_Deltas!$A$2:$H$5000,5,FALSE),"") | G55: =IFERROR(VLOOKUP($A55,Results_30d_Deltas!$A$2:$H$5000,7,FALSE)-E54,"") | H55: =IFERROR(VLOOKUP($A55,Results_30d_Deltas!$A$2:$H$5000,6,FALSE),"") | K55: =IF(B55=C55,"YES","NO") | IJ55: ez_manage.py:4002 top() | IK55: v12_quick_engine.py:3228 x2

Sheet REDUCE_SIGNAL_RATER
A1: 11 REDUCE_SIGNAL_RATER - 42 bases -> 143 rows - 231 per-row FULLY CONNECTED
A2: Switch | B2: default | C2: override | D2: Family | E2: =MAX('REDUCE_PROFIT_LOCK'!E$2:E$5000) | F2: VECTOR_DELTA | G2: LIVE_DELTA | H2: LIVE_SHARPE | I2: REAL_COMPLETE | J2: PER_ROW_FILTERS | K2: is_default (backup if bold lost) | L2: ATR_TRAIL_FILTER_TF=OFF | M2: ATR_TRAIL_FILTER_TF=D | N2: ATR_TRAIL_FILTER_TF=4h | O2: ATR_TRAIL_FILTER_TF=1h | P2: ATR_TRAIL_FILTER_TF=15m | Q2: BAR_PATTERNS_FILTER_TF=OFF | R2: BAR_PATTERNS_FILTER_TF=D | S2: BAR_PATTERNS_FILTER_TF=4h | T2: BAR_PATTERNS_FILTER_TF=1h | U2: BAR_PATTERNS_FILTER_TF=15m | V2: BB_PULLBACK_GATE_FILTER_TF=OFF | W2: BB_PULLBACK_GATE_FILTER_TF=D | X2: BB_PULLBACK_GATE_FILTER_TF=4h | Y2: BB_PULLBACK_GATE_FILTER_TF=1h | Z2: BB_PULLBACK_GATE_FILTER_TF=15m | AA2: BB_RECOVERY_ENTRY_FILTER_TF=OFF | AB2: BB_RECOVERY_ENTRY_FILTER_TF=D | AC2: BB_RECOVERY_ENTRY_FILTER_TF=4h | AD2: BB_RECOVERY_ENTRY_FILTER_TF=1h | AE2: BB_RECOVERY_ENTRY_FILTER_TF=15m | AF2: BB_RECOVERY_FILTER_TF=OFF | AG2: BB_RECOVERY_FILTER_TF=D | AH2: BB_RECOVERY_FILTER_TF=4h | AI2: BB_RECOVERY_FILTER_TF=1h | AJ2: BB_RECOVERY_FILTER_TF=15m | AK2: BREAKEVEN_GAIN_EROSION_FILTER_TF=OFF | AL2: BREAKEVEN_GAIN_EROSION_FILTER_TF=D | AM2: BREAKEVEN_GAIN_EROSION_FILTER_TF=4h | AN2: BREAKEVEN_GAIN_EROSION_FILTER_TF=1h | AO2: BREAKEVEN_GAIN_EROSION_FILTER_TF=15m | AP2: BREAKOUT_RETEST_FILTER_TF=OFF | AQ2: BREAKOUT_RETEST_FILTER_TF=D | AR2: BREAKOUT_RETEST_FILTER_TF=4h | AS2: BREAKOUT_RETEST_FILTER_TF=1h | AT2: BREAKOUT_RETEST_FILTER_TF=15m | AU2: BT_WT_CROSS_LADDER_FILTER_TF=OFF | AV2: BT_WT_CROSS_LADDER_FILTER_TF=D | AW2: BT_WT_CROSS_LADDER_FILTER_TF=4h | AX2: BT_WT_CROSS_LADDER_FILTER_TF=1h | AY2: BT_WT_CROSS_LADDER_FILTER_TF=15m | AZ2: CANDLE_PATTERN_STOPS_FILTER_TF=OFF | BA2: CANDLE_PATTERN_STOPS_FILTER_TF=D | BB2: CANDLE_PATTERN_STOPS_FILTER_TF=4h | BC2: CANDLE_PATTERN_STOPS_FILTER_TF=1h | BD2: CANDLE_PATTERN_STOPS_FILTER_TF=15m | BE2: CIRCUIT_SHARPE_GATES_FILTER_TF=OFF | BF2: CIRCUIT_SHARPE_GATES_FILTER_TF=D | BG2: CIRCUIT_SHARPE_GATES_FILTER_TF=4h | BH2: CIRCUIT_SHARPE_GATES_FILTER_TF=1h | BI2: CIRCUIT_SHARPE_GATES_FILTER_TF=15m | BJ2: DC_BREACH_REDUCE_FILTER_TF=OFF | BK2: DC_BREACH_REDUCE_FILTER_TF=D | BL2: DC_BREACH_REDUCE_FILTER_TF=4h | BM2: DC_BREACH_REDUCE_FILTER_TF=1h | BN2: DC_BREACH_REDUCE_FILTER_TF=15m | BO2: DC_BREAK_FILTER_TF=OFF | BP2: DC_BREAK_FILTER_TF=D | BQ2: DC_BREAK_FILTER_TF=4h | BR2: DC_BREAK_FILTER_TF=1h | BS2: DC_BREAK_FILTER_TF=15m | BT2: DC_MOMENTUM_BOTA_SCORER_FILTER_TF=OFF | BU2: DC_MOMENTUM_BOTA_SCORER_FILTER_TF=D | BV2: DC_MOMENTUM_BOTA_SCORER_FILTER_TF=4h | BW2: DC_MOMENTUM_BOTA_SCORER_FILTER_TF=1h | BX2: DC_MOMENTUM_BOTA_SCORER_FILTER_TF=15m | BY2: DELTA_ENGINE_FILTER_TF=OFF | BZ2: DELTA_ENGINE_FILTER_TF=D | CA2: DELTA_ENGINE_FILTER_TF=4h | CB2: DELTA_ENGINE_FILTER_TF=1h | CC2: DELTA_ENGINE_FILTER_TF=15m | CD2: EMA_9_21_FILTER_FILTER_TF=OFF | CE2: EMA_9_21_FILTER_FILTER_TF=D | CF2: EMA_9_21_FILTER_FILTER_TF=4h | CG2: EMA_9_21_FILTER_FILTER_TF=1h | CH2: EMA_9_21_FILTER_FILTER_TF=15m | CI2: EMA_BLANKET_FILTER_FILTER_TF=OFF | CJ2: EMA_BLANKET_FILTER_FILTER_TF=D | CK2: EMA_BLANKET_FILTER_FILTER_TF=4h | CL2: EMA_BLANKET_FILTER_FILTER_TF=1h | CM2: EMA_BLANKET_FILTER_FILTER_TF=15m | CN2: EMERGENCY_BRAKE_FILTER_TF=OFF | CO2: EMERGENCY_BRAKE_FILTER_TF=D | CP2: EMERGENCY_BRAKE_FILTER_TF=4h | CQ2: EMERGENCY_BRAKE_FILTER_TF=1h | CR2: EMERGENCY_BRAKE_FILTER_TF=15m | CS2: EXIT_R1_R2_FILTER_TF=OFF | CT2: EXIT_R1_R2_FILTER_TF=D | CU2: EXIT_R1_R2_FILTER_TF=4h | CV2: EXIT_R1_R2_FILTER_TF=1h | CW2: EXIT_R1_R2_FILTER_TF=15m | CX2: EXIT_TIGHT_BREAKOUT_SCORER_FILTER_TF=OFF | CY2: EXIT_TIGHT_BREAKOUT_SCORER_FILTER_TF=D | CZ2: EXIT_TIGHT_BREAKOUT_SCORER_FILTER_TF=4h | DA2: EXIT_TIGHT_BREAKOUT_SCORER_FILTER_TF=1h | DB2: EXIT_TIGHT_BREAKOUT_SCORER_FILTER_TF=15m | DC2: EXIT_TOP_FADE_FILTER_TF=OFF | DD2: EXIT_TOP_FADE_FILTER_TF=D | DE2: EXIT_TOP_FADE_FILTER_TF=4h | DF2: EXIT_TOP_FADE_FILTER_TF=1h | DG2: EXIT_TOP_FADE_FILTER_TF=15m | DH2: EXIT_TO_REDUCE_ADAPTER_FILTER_TF=OFF | DI2: EXIT_TO_REDUCE_ADAPTER_FILTER_TF=D | DJ2: EXIT_TO_REDUCE_ADAPTER_FILTER_TF=4h | DK2: EXIT_TO_REDUCE_ADAPTER_FILTER_TF=1h | DL2: EXIT_TO_REDUCE_ADAPTER_FILTER_TF=15m | DM2: FAST_RISER_FILTER_TF=OFF | DN2: FAST_RISER_FILTER_TF=D | DO2: FAST_RISER_FILTER_TF=4h | DP2: FAST_RISER_FILTER_TF=1h | DQ2: FAST_RISER_FILTER_TF=15m | DR2: FH_MOMENTUM_FILTER_TF=OFF | DS2: FH_MOMENTUM_FILTER_TF=D | DT2: FH_MOMENTUM_FILTER_TF=4h | DU2: FH_MOMENTUM_FILTER_TF=1h | DV2: FH_MOMENTUM_FILTER_TF=15m | DW2: FIRST_OPEN_THROTTLE_FILTER_TF=OFF | DX2: FIRST_OPEN_THROTTLE_FILTER_TF=D | DY2: FIRST_OPEN_THROTTLE_FILTER_TF=4h | DZ2: FIRST_OPEN_THROTTLE_FILTER_TF=1h | EA2: FIRST_OPEN_THROTTLE_FILTER_TF=15m | EB2: FROZEN_STOP_FILTER_TF=OFF | EC2: FROZEN_STOP_FILTER_TF=D | ED2: FROZEN_STOP_FILTER_TF=4h | EE2: FROZEN_STOP_FILTER_TF=1h | EF2: FROZEN_STOP_FILTER_TF=15m | EG2: GOLDEN_RULE_ENFORCE_FILTER_TF=OFF | EH2: GOLDEN_RULE_ENFORCE_FILTER_TF=D | EI2: GOLDEN_RULE_ENFORCE_FILTER_TF=4h | EJ2: GOLDEN_RULE_ENFORCE_FILTER_TF=1h | EK2: GOLDEN_RULE_ENFORCE_FILTER_TF=15m | EL2: GOLDEN_RULE_HTF_VOTE_FILTER_TF=OFF | EM2: GOLDEN_RULE_HTF_VOTE_FILTER_TF=D | EN2: GOLDEN_RULE_HTF_VOTE_FILTER_TF=4h | EO2: GOLDEN_RULE_HTF_VOTE_FILTER_TF=1h | EP2: GOLDEN_RULE_HTF_VOTE_FILTER_TF=15m | EQ2: GR_FILTER_VEC_FILTER_TF=OFF | ER2: GR_FILTER_VEC_FILTER_TF=D | ES2: GR_FILTER_VEC_FILTER_TF=4h | ET2: GR_FILTER_VEC_FILTER_TF=1h | EU2: GR_FILTER_VEC_FILTER_TF=15m | EV2: GR_V5_STATE_FILTER_TF=OFF | EW2: GR_V5_STATE_FILTER_TF=D | EX2: GR_V5_STATE_FILTER_TF=4h | EY2: GR_V5_STATE_FILTER_TF=1h | EZ2: GR_V5_STATE_FILTER_TF=15m | FA2: HAIKU_WINNER_FILTER_TF=OFF | FB2: HAIKU_WINNER_FILTER_TF=D | FC2: HAIKU_WINNER_FILTER_TF=4h | FD2: HAIKU_WINNER_FILTER_TF=1h | FE2: HAIKU_WINNER_FILTER_TF=15m | FF2: LH_HL_FILTER_TF_REQ=2 | FG2: LH_HL_FILTER_TF_REQ=2_ALT | FH2: LIVE_ENTRY_ENGINE_FILTER_TF=OFF | FI2: LIVE_ENTRY_ENGINE_FILTER_TF=D | FJ2: LIVE_ENTRY_ENGINE_FILTER_TF=4h | FK2: LIVE_ENTRY_ENGINE_FILTER_TF=1h | FL2: LIVE_ENTRY_ENGINE_FILTER_TF=15m | FM2: LIVE_ONLY_SIGNALS_BATCH5_FILTER_TF=OFF | FN2: LIVE_ONLY_SIGNALS_BATCH5_FILTER_TF=D | FO2: LIVE_ONLY_SIGNALS_BATCH5_FILTER_TF=4h | FP2: LIVE_ONLY_SIGNALS_BATCH5_FILTER_TF=1h | FQ2: LIVE_ONLY_SIGNALS_BATCH5_FILTER_TF=15m | FR2: MANDATORY_REENTRY_WT_FILTER_TF_MODE=15m_only | FS2: MANDATORY_REENTRY_WT_FILTER_TF_MODE=15m_only_ALT | FT2: MOM3_FILTER_TF=OFF | FU2: MOM3_FILTER_TF=D | FV2: MOM3_FILTER_TF=4h | FW2: MOM3_FILTER_TF=1h | FX2: MOM3_FILTER_TF=15m | FY2: MOMENTUM_BREAKOUT_FILTER_TF=OFF | FZ2: MOMENTUM_BREAKOUT_FILTER_TF=D | GA2: MOMENTUM_BREAKOUT_FILTER_TF=4h | GB2: MOMENTUM_BREAKOUT_FILTER_TF=1h | GC2: MOMENTUM_BREAKOUT_FILTER_TF=15m | GD2: MTF_ARMED_ENTRIES_FILTER_TF=OFF | GE2: MTF_ARMED_ENTRIES_FILTER_TF=D | GF2: MTF_ARMED_ENTRIES_FILTER_TF=4h | GG2: MTF_ARMED_ENTRIES_FILTER_TF=1h | GH2: MTF_ARMED_ENTRIES_FILTER_TF=15m | GI2: MTF_ATR_TRAIL_FILTER_TF=OFF | GJ2: MTF_ATR_TRAIL_FILTER_TF=D | GK2: MTF_ATR_TRAIL_FILTER_TF=4h | GL2: MTF_ATR_TRAIL_FILTER_TF=1h | GM2: MTF_ATR_TRAIL_FILTER_TF=15m | GN2: MTF_DC_REJECT_FILTER_TF=OFF | GO2: MTF_DC_REJECT_FILTER_TF=D | GP2: MTF_DC_REJECT_FILTER_TF=4h | GQ2: MTF_DC_REJECT_FILTER_TF=1h | GR2: MTF_DC_REJECT_FILTER_TF=15m | GS2: NEWBORN_LOSS_KILL_FILTER_TF=OFF | GT2: NEWBORN_LOSS_KILL_FILTER_TF=D | GU2: NEWBORN_LOSS_KILL_FILTER_TF=4h | GV2: NEWBORN_LOSS_KILL_FILTER_TF=1h | GW2: NEWBORN_LOSS_KILL_FILTER_TF=15m | GX2: NEWBORN_PROTECT_FILTER_TF=OFF | GY2: NEWBORN_PROTECT_FILTER_TF=D | GZ2: NEWBORN_PROTECT_FILTER_TF=4h | HA2: NEWBORN_PROTECT_FILTER_TF=1h | HB2: NEWBORN_PROTECT_FILTER_TF=15m | HC2: NOLOSS_BYPASS_WT5OF5_FILTER_TF=OFF | HD2: NOLOSS_BYPASS_WT5OF5_FILTER_TF=D | HE2: NOLOSS_BYPASS_WT5OF5_FILTER_TF=4h | HF2: NOLOSS_BYPASS_WT5OF5_FILTER_TF=1h | HG2: NOLOSS_BYPASS_WT5OF5_FILTER_TF=15m | HH2: OPEN_INTENT_SIZE_GATES_FILTER_TF=OFF | HI2: OPEN_INTENT_SIZE_GATES_FILTER_TF=D | HJ2: OPEN_INTENT_SIZE_GATES_FILTER_TF=4h | HK2: OPEN_INTENT_SIZE_GATES_FILTER_TF=1h | HL2: OPEN_INTENT_SIZE_GATES_FILTER_TF=15m | HM2: PARTIAL_PROFIT_LOCK_V2_FILTER_TF=OFF | HN2: PARTIAL_PROFIT_LOCK_V2_FILTER_TF=D | HO2: PARTIAL_PROFIT_LOCK_V2_FILTER_TF=4h | HP2: PARTIAL_PROFIT_LOCK_V2_FILTER_TF=1h | HQ2: PARTIAL_PROFIT_LOCK_V2_FILTER_TF=15m | HR2: PEAK_GIVEBACK_BE_EROSION_FILTER_TF=OFF | HS2: PEAK_GIVEBACK_BE_EROSION_FILTER_TF=D | HT2: PEAK_GIVEBACK_BE_EROSION_FILTER_TF=4h | HU2: PEAK_GIVEBACK_BE_EROSION_FILTER_TF=1h | HV2: PEAK_GIVEBACK_BE_EROSION_FILTER_TF=15m | HW2: WT_15M_BOUNCE_BB_MAX=0.95 | HX2: WT_15M_BOUNCE_BB_MAX=0.9 | HY2: WT_15M_BOUNCE_BB_MAX=0.8 | HZ2: WT_15M_BOUNCE_BB_MIN=0.05 | IA2: WT_15M_BOUNCE_BB_MIN=0.1 | IB2: WT_15M_BOUNCE_BB_MIN=0.2 | IC2: WT_15M_BOUNCE_HIGH_1H_GT_PREV=True | ID2: WT_15M_BOUNCE_HIGH_1H_GT_PREV=False | IE2: WT_15M_BOUNCE_LOW_1H_GT_PREV=True | IF2: WT_15M_BOUNCE_LOW_1H_GT_PREV=False | IG2: WT_15M_BOUNCE_REL_VOL_GT_1=True | IH2: WT_15M_BOUNCE_REL_VOL_GT_1=False | II2: Live Location | IJ2: Vec Hook | IK2: Type | IL2: Correct Options
A3: QUICK_REDUCE_TECHNICAL_ONLY | B3: 0 | E3: =MAX('REDUCE_PROFIT_LOCK'!E:E) | F3: =IFERROR(VLOOKUP($A3&"="&$B3,Results_30d_Deltas!$A$2:$H$5000,5,FALSE),"") | G3: =IFERROR(VLOOKUP($A3,Results_30d_Deltas!$A$2:$H$5000,7,FALSE)-E3,"") | H3: =IFERROR(VLOOKUP($A3,Results_30d_Deltas!$A$2:$H$5000,6,FALSE),"") | K3: =IF(B3=C3,"YES","NO") | IJ3: ez_manage.py:5218 top() | IK3: v12_quick_engine.py:2747 x2
A4: QUICK_REDUCE_TECHNICAL_ONLY | B4: 0.5 | E4: =IF(F4="",E3,IF(F4>0,E3+F4,E3)) | F4: =IFERROR(VLOOKUP($A4&"="&$B4,Results_30d_Deltas!$A$2:$H$5000,5,FALSE),"") | G4: =IFERROR(VLOOKUP($A4,Results_30d_Deltas!$A$2:$H$5000,7,FALSE)-E3,"") | H4: =IFERROR(VLOOKUP($A4,Results_30d_Deltas!$A$2:$H$5000,6,FALSE),"") | K4: =IF(B4=C4,"YES","NO") | IJ4: ez_manage.py:5218 top() | IK4: v12_quick_engine.py:2747 x2
A5: QUICK_REDUCE_TECHNICAL_ONLY | B5: 1.0 | E5: =IF(F5="",E4,IF(F5>0,E4+F5,E4)) | F5: =IFERROR(VLOOKUP($A5&"="&$B5,Results_30d_Deltas!$A$2:$H$5000,5,FALSE),"") | G5: =IFERROR(VLOOKUP($A5,Results_30d_Deltas!$A$2:$H$5000,7,FALSE)-E4,"") | H5: =IFERROR(VLOOKUP($A5,Results_30d_Deltas!$A$2:$H$5000,6,FALSE),"") | K5: =IF(B5=C5,"YES","NO") | IJ5: ez_manage.py:5218 top() | IK5: v12_quick_engine.py:2747 x2
A6: QUICK_REDUCE_TECHNICAL_ONLY | B6: 2.0 | E6: =IF(F6="",E5,IF(F6>0,E5+F6,E5)) | F6: =IFERROR(VLOOKUP($A6&"="&$B6,Results_30d_Deltas!$A$2:$H$5000,5,FALSE),"") | G6: =IFERROR(VLOOKUP($A6,Results_30d_Deltas!$A$2:$H$5000,7,FALSE)-E5,"") | H6: =IFERROR(VLOOKUP($A6,Results_30d_Deltas!$A$2:$H$5000,6,FALSE),"") | K6: =IF(B6=C6,"YES","NO") | IJ6: ez_manage.py:5218 top() | IK6: v12_quick_engine.py:2747 x2
A7: ALL_TF_AGAINST_CLOSE_MIN_TFS | B7: 0 | E7: =IF(F7="",E6,IF(F7>0,E6+F7,E6)) | F7: =IFERROR(VLOOKUP($A7&"="&$B7,Results_30d_Deltas!$A$2:$H$5000,5,FALSE),"") | G7: =IFERROR(VLOOKUP($A7,Results_30d_Deltas!$A$2:$H$5000,7,FALSE)-E6,"") | H7: =IFERROR(VLOOKUP($A7,Results_30d_Deltas!$A$2:$H$5000,6,FALSE),"") | K7: =IF(B7=C7,"YES","NO") | IJ7: ez_manage.py:2932 top() | IK7: v12_quick_engine.py:181 x11
A8: ALL_TF_AGAINST_CLOSE_MIN_TFS | B8: 0.5 | E8: =IF(F8="",E7,IF(F8>0,E7+F8,E7)) | F8: =IFERROR(VLOOKUP($A8&"="&$B8,Results_30d_Deltas!$A$2:$H$5000,5,FALSE),"") | G8: =IFERROR(VLOOKUP($A8,Results_30d_Deltas!$A$2:$H$5000,7,FALSE)-E7,"") | H8: =IFERROR(VLOOKUP($A8,Results_30d_Deltas!$A$2:$H$5000,6,FALSE),"") | K8: =IF(B8=C8,"YES","NO") | IJ8: ez_manage.py:2932 top() | IK8: v12_quick_engine.py:181 x11
A9: ALL_TF_AGAINST_CLOSE_MIN_TFS | B9: 1.0 | E9: =IF(F9="",E8,IF(F9>0,E8+F9,E8)) | F9: =IFERROR(VLOOKUP($A9&"="&$B9,Results_30d_Deltas!$A$2:$H$5000,5,FALSE),"") | G9: =IFERROR(VLOOKUP($A9,Results_30d_Deltas!$A$2:$H$5000,7,FALSE)-E8,"") | H9: =IFERROR(VLOOKUP($A9,Results_30d_Deltas!$A$2:$H$5000,6,FALSE),"") | K9: =IF(B9=C9,"YES","NO") | IJ9: ez_manage.py:2932 top() | IK9: v12_quick_engine.py:181 x11
A10: ALL_TF_AGAINST_CLOSE_MIN_TFS | B10: 2.0 | E10: =IF(F10="",E9,IF(F10>0,E9+F10,E9)) | F10: =IFERROR(VLOOKUP($A10&"="&$B10,Results_30d_Deltas!$A$2:$H$5000,5,FALSE),"") | G10: =IFERROR(VLOOKUP($A10,Results_30d_Deltas!$A$2:$H$5000,7,FALSE)-E9,"") | H10: =IFERROR(VLOOKUP($A10,Results_30d_Deltas!$A$2:$H$5000,6,FALSE),"") | K10: =IF(B10=C10,"YES","NO") | IJ10: ez_manage.py:2932 top() | IK10: v12_quick_engine.py:181 x11
A11: SATOSHIT_EXIT_LONG_RSI_MIN_TRADIER | B11: 27.5 | E11: =IF(F11="",E10,IF(F11>0,E10+F11,E10)) | F11: =IFERROR(VLOOKUP($A11&"="&$B11,Results_30d_Deltas!$A$2:$H$5000,5,FALSE),"") | G11: =IFERROR(VLOOKUP($A11,Results_30d_Deltas!$A$2:$H$5000,7,FALSE)-E10,"") | H11: =IFERROR(VLOOKUP($A11,Results_30d_Deltas!$A$2:$H$5000,6,FALSE),"") | K11: =IF(B11=C11,"YES","NO") | IJ11: ez_manage.py:5452 top() | IK11: v12_quick_engine.py:3061 x7
A12: SATOSHIT_EXIT_LONG_RSI_MIN_TRADIER | B12: 41.25 | E12: =IF(F12="",E11,IF(F12>0,E11+F12,E11)) | F12: =IFERROR(VLOOKUP($A12&"="&$B12,Results_30d_Deltas!$A$2:$H$5000,5,FALSE),"") | G12: =IFERROR(VLOOKUP($A12,Results_30d_Deltas!$A$2:$H$5000,7,FALSE)-E11,"") | H12: =IFERROR(VLOOKUP($A12,Results_30d_Deltas!$A$2:$H$5000,6,FALSE),"") | K12: =IF(B12=C12,"YES","NO") | IJ12: ez_manage.py:5452 top() | IK12: v12_quick_engine.py:3061 x7
A13: SATOSHIT_EXIT_LONG_RSI_MIN_TRADIER | B13: 55.0 | E13: =IF(F13="",E12,IF(F13>0,E12+F13,E12)) | F13: =IFERROR(VLOOKUP($A13&"="&$B13,Results_30d_Deltas!$A$2:$H$5000,5,FALSE),"") | G13: =IFERROR(VLOOKUP($A13,Results_30d_Deltas!$A$2:$H$5000,7,FALSE)-E12,"") | H13: =IFERROR(VLOOKUP($A13,Results_30d_Deltas!$A$2:$H$5000,6,FALSE),"") | K13: =IF(B13=C13,"YES","NO") | IJ13: ez_manage.py:5452 top() | IK13: v12_quick_engine.py:3061 x7
A14: SATOSHIT_EXIT_LONG_RSI_MIN_TRADIER | B14: 68.75 | E14: =IF(F14="",E13,IF(F14>0,E13+F14,E13)) | F14: =IFERROR(VLOOKUP($A14&"="&$B14,Results_30d_Deltas!$A$2:$H$5000,5,FALSE),"") | G14: =IFERROR(VLOOKUP($A14,Results_30d_Deltas!$A$2:$H$5000,7,FALSE)-E13,"") | H14: =IFERROR(VLOOKUP($A14,Results_30d_Deltas!$A$2:$H$5000,6,FALSE),"") | K14: =IF(B14=C14,"YES","NO") | IJ14: ez_manage.py:5452 top() | IK14: v12_quick_engine.py:3061 x7
A15: SATOSHIT_EXIT_LONG_RSI_MIN_TRADIER | B15: 82.5 | E15: =IF(F15="",E14,IF(F15>0,E14+F15,E14)) | F15: =IFERROR(VLOOKUP($A15&"="&$B15,Results_30d_Deltas!$A$2:$H$5000,5,FALSE),"") | G15: =IFERROR(VLOOKUP($A15,Results_30d_Deltas!$A$2:$H$5000,7,FALSE)-E14,"") | H15: =IFERROR(VLOOKUP($A15,Results_30d_Deltas!$A$2:$H$5000,6,FALSE),"") | K15: =IF(B15=C15,"YES","NO") | IJ15: ez_manage.py:5452 top() | IK15: v12_quick_engine.py:3061 x7
... A145: WT_REDUCE_FRAC_MED | B145: 2.0 | E145: =IF(F145="",E144,IF(F145>0,E144+F145,E144)) | F145: =IFERROR(VLOOKUP($A145&"="&$B145,Results_30d_Deltas!$A$2:$H$5000,5,FALSE),"") | G145: =IFERROR(VLOOKUP($A145,Results_30d_Deltas!$A$2:$H$5000,7,FALSE)-E144,"") | H145: =IFERROR(VLOOKUP($A145,Results_30d_Deltas!$A$2:$H$5000,6,FALSE),"") | K145: =IF(B145=C145,"YES","NO") | IJ145: ez_manage.py:4309 top() | IK145: v12_quick_engine.py:2949 x14

Sheet GLOBAL_RISK_GATES
A1: 12 GLOBAL_RISK_GATES - 17 bases -> 38 rows - 231 per-row FULLY CONNECTED
A2: Switch | B2: default | C2: override | D2: Family | E2: =MAX('REDUCE_SIGNAL_RATER'!E$2:E$5000) | F2: VECTOR_DELTA | G2: LIVE_DELTA | H2: LIVE_SHARPE | I2: REAL_COMPLETE | J2: PER_ROW_FILTERS | K2: is_default (backup if bold lost) | L2: ATR_TRAIL_FILTER_TF=OFF | M2: ATR_TRAIL_FILTER_TF=D | N2: ATR_TRAIL_FILTER_TF=4h | O2: ATR_TRAIL_FILTER_TF=1h | P2: ATR_TRAIL_FILTER_TF=15m | Q2: BAR_PATTERNS_FILTER_TF=OFF | R2: BAR_PATTERNS_FILTER_TF=D | S2: BAR_PATTERNS_FILTER_TF=4h | T2: BAR_PATTERNS_FILTER_TF=1h | U2: BAR_PATTERNS_FILTER_TF=15m | V2: BB_PULLBACK_GATE_FILTER_TF=OFF | W2: BB_PULLBACK_GATE_FILTER_TF=D | X2: BB_PULLBACK_GATE_FILTER_TF=4h | Y2: BB_PULLBACK_GATE_FILTER_TF=1h | Z2: BB_PULLBACK_GATE_FILTER_TF=15m | AA2: BB_RECOVERY_ENTRY_FILTER_TF=OFF | AB2: BB_RECOVERY_ENTRY_FILTER_TF=D | AC2: BB_RECOVERY_ENTRY_FILTER_TF=4h | AD2: BB_RECOVERY_ENTRY_FILTER_TF=1h | AE2: BB_RECOVERY_ENTRY_FILTER_TF=15m | AF2: BB_RECOVERY_FILTER_TF=OFF | AG2: BB_RECOVERY_FILTER_TF=D | AH2: BB_RECOVERY_FILTER_TF=4h | AI2: BB_RECOVERY_FILTER_TF=1h | AJ2: BB_RECOVERY_FILTER_TF=15m | AK2: BREAKEVEN_GAIN_EROSION_FILTER_TF=OFF | AL2: BREAKEVEN_GAIN_EROSION_FILTER_TF=D | AM2: BREAKEVEN_GAIN_EROSION_FILTER_TF=4h | AN2: BREAKEVEN_GAIN_EROSION_FILTER_TF=1h | AO2: BREAKEVEN_GAIN_EROSION_FILTER_TF=15m | AP2: BREAKOUT_RETEST_FILTER_TF=OFF | AQ2: BREAKOUT_RETEST_FILTER_TF=D | AR2: BREAKOUT_RETEST_FILTER_TF=4h | AS2: BREAKOUT_RETEST_FILTER_TF=1h | AT2: BREAKOUT_RETEST_FILTER_TF=15m | AU2: BT_WT_CROSS_LADDER_FILTER_TF=OFF | AV2: BT_WT_CROSS_LADDER_FILTER_TF=D | AW2: BT_WT_CROSS_LADDER_FILTER_TF=4h | AX2: BT_WT_CROSS_LADDER_FILTER_TF=1h | AY2: BT_WT_CROSS_LADDER_FILTER_TF=15m | AZ2: CANDLE_PATTERN_STOPS_FILTER_TF=OFF | BA2: CANDLE_PATTERN_STOPS_FILTER_TF=D | BB2: CANDLE_PATTERN_STOPS_FILTER_TF=4h | BC2: CANDLE_PATTERN_STOPS_FILTER_TF=1h | BD2: CANDLE_PATTERN_STOPS_FILTER_TF=15m | BE2: CIRCUIT_SHARPE_GATES_FILTER_TF=OFF | BF2: CIRCUIT_SHARPE_GATES_FILTER_TF=D | BG2: CIRCUIT_SHARPE_GATES_FILTER_TF=4h | BH2: CIRCUIT_SHARPE_GATES_FILTER_TF=1h | BI2: CIRCUIT_SHARPE_GATES_FILTER_TF=15m | BJ2: DC_BREACH_REDUCE_FILTER_TF=OFF | BK2: DC_BREACH_REDUCE_FILTER_TF=D | BL2: DC_BREACH_REDUCE_FILTER_TF=4h | BM2: DC_BREACH_REDUCE_FILTER_TF=1h | BN2: DC_BREACH_REDUCE_FILTER_TF=15m | BO2: DC_BREAK_FILTER_TF=OFF | BP2: DC_BREAK_FILTER_TF=D | BQ2: DC_BREAK_FILTER_TF=4h | BR2: DC_BREAK_FILTER_TF=1h | BS2: DC_BREAK_FILTER_TF=15m | BT2: DC_MOMENTUM_BOTA_SCORER_FILTER_TF=OFF | BU2: DC_MOMENTUM_BOTA_SCORER_FILTER_TF=D | BV2: DC_MOMENTUM_BOTA_SCORER_FILTER_TF=4h | BW2: DC_MOMENTUM_BOTA_SCORER_FILTER_TF=1h | BX2: DC_MOMENTUM_BOTA_SCORER_FILTER_TF=15m | BY2: DELTA_ENGINE_FILTER_TF=OFF | BZ2: DELTA_ENGINE_FILTER_TF=D | CA2: DELTA_ENGINE_FILTER_TF=4h | CB2: DELTA_ENGINE_FILTER_TF=1h | CC2: DELTA_ENGINE_FILTER_TF=15m | CD2: EMA_9_21_FILTER_FILTER_TF=OFF | CE2: EMA_9_21_FILTER_FILTER_TF=D | CF2: EMA_9_21_FILTER_FILTER_TF=4h | CG2: EMA_9_21_FILTER_FILTER_TF=1h | CH2: EMA_9_21_FILTER_FILTER_TF=15m | CI2: EMA_BLANKET_FILTER_FILTER_TF=OFF | CJ2: EMA_BLANKET_FILTER_FILTER_TF=D | CK2: EMA_BLANKET_FILTER_FILTER_TF=4h | CL2: EMA_BLANKET_FILTER_FILTER_TF=1h | CM2: EMA_BLANKET_FILTER_FILTER_TF=15m | CN2: EMERGENCY_BRAKE_FILTER_TF=OFF | CO2: EMERGENCY_BRAKE_FILTER_TF=D | CP2: EMERGENCY_BRAKE_FILTER_TF=4h | CQ2: EMERGENCY_BRAKE_FILTER_TF=1h | CR2: EMERGENCY_BRAKE_FILTER_TF=15m | CS2: EXIT_R1_R2_FILTER_TF=OFF | CT2: EXIT_R1_R2_FILTER_TF=D | CU2: EXIT_R1_R2_FILTER_TF=4h | CV2: EXIT_R1_R2_FILTER_TF=1h | CW2: EXIT_R1_R2_FILTER_TF=15m | CX2: EXIT_TIGHT_BREAKOUT_SCORER_FILTER_TF=OFF | CY2: EXIT_TIGHT_BREAKOUT_SCORER_FILTER_TF=D | CZ2: EXIT_TIGHT_BREAKOUT_SCORER_FILTER_TF=4h | DA2: EXIT_TIGHT_BREAKOUT_SCORER_FILTER_TF=1h | DB2: EXIT_TIGHT_BREAKOUT_SCORER_FILTER_TF=15m | DC2: EXIT_TOP_FADE_FILTER_TF=OFF | DD2: EXIT_TOP_FADE_FILTER_TF=D | DE2: EXIT_TOP_FADE_FILTER_TF=4h | DF2: EXIT_TOP_FADE_FILTER_TF=1h | DG2: EXIT_TOP_FADE_FILTER_TF=15m | DH2: EXIT_TO_REDUCE_ADAPTER_FILTER_TF=OFF | DI2: EXIT_TO_REDUCE_ADAPTER_FILTER_TF=D | DJ2: EXIT_TO_REDUCE_ADAPTER_FILTER_TF=4h | DK2: EXIT_TO_REDUCE_ADAPTER_FILTER_TF=1h | DL2: EXIT_TO_REDUCE_ADAPTER_FILTER_TF=15m | DM2: FAST_RISER_FILTER_TF=OFF | DN2: FAST_RISER_FILTER_TF=D | DO2: FAST_RISER_FILTER_TF=4h | DP2: FAST_RISER_FILTER_TF=1h | DQ2: FAST_RISER_FILTER_TF=15m | DR2: FH_MOMENTUM_FILTER_TF=OFF | DS2: FH_MOMENTUM_FILTER_TF=D | DT2: FH_MOMENTUM_FILTER_TF=4h | DU2: FH_MOMENTUM_FILTER_TF=1h | DV2: FH_MOMENTUM_FILTER_TF=15m | DW2: FIRST_OPEN_THROTTLE_FILTER_TF=OFF | DX2: FIRST_OPEN_THROTTLE_FILTER_TF=D | DY2: FIRST_OPEN_THROTTLE_FILTER_TF=4h | DZ2: FIRST_OPEN_THROTTLE_FILTER_TF=1h | EA2: FIRST_OPEN_THROTTLE_FILTER_TF=15m | EB2: FROZEN_STOP_FILTER_TF=OFF | EC2: FROZEN_STOP_FILTER_TF=D | ED2: FROZEN_STOP_FILTER_TF=4h | EE2: FROZEN_STOP_FILTER_TF=1h | EF2: FROZEN_STOP_FILTER_TF=15m | EG2: GOLDEN_RULE_ENFORCE_FILTER_TF=OFF | EH2: GOLDEN_RULE_ENFORCE_FILTER_TF=D | EI2: GOLDEN_RULE_ENFORCE_FILTER_TF=4h | EJ2: GOLDEN_RULE_ENFORCE_FILTER_TF=1h | EK2: GOLDEN_RULE_ENFORCE_FILTER_TF=15m | EL2: GOLDEN_RULE_HTF_VOTE_FILTER_TF=OFF | EM2: GOLDEN_RULE_HTF_VOTE_FILTER_TF=D | EN2: GOLDEN_RULE_HTF_VOTE_FILTER_TF=4h | EO2: GOLDEN_RULE_HTF_VOTE_FILTER_TF=1h | EP2: GOLDEN_RULE_HTF_VOTE_FILTER_TF=15m | EQ2: GR_FILTER_VEC_FILTER_TF=OFF | ER2: GR_FILTER_VEC_FILTER_TF=D | ES2: GR_FILTER_VEC_FILTER_TF=4h | ET2: GR_FILTER_VEC_FILTER_TF=1h | EU2: GR_FILTER_VEC_FILTER_TF=15m | EV2: GR_V5_STATE_FILTER_TF=OFF | EW2: GR_V5_STATE_FILTER_TF=D | EX2: GR_V5_STATE_FILTER_TF=4h | EY2: GR_V5_STATE_FILTER_TF=1h | EZ2: GR_V5_STATE_FILTER_TF=15m | FA2: HAIKU_WINNER_FILTER_TF=OFF | FB2: HAIKU_WINNER_FILTER_TF=D | FC2: HAIKU_WINNER_FILTER_TF=4h | FD2: HAIKU_WINNER_FILTER_TF=1h | FE2: HAIKU_WINNER_FILTER_TF=15m | FF2: LH_HL_FILTER_TF_REQ=2 | FG2: LH_HL_FILTER_TF_REQ=2_ALT | FH2: LIVE_ENTRY_ENGINE_FILTER_TF=OFF | FI2: LIVE_ENTRY_ENGINE_FILTER_TF=D | FJ2: LIVE_ENTRY_ENGINE_FILTER_TF=4h | FK2: LIVE_ENTRY_ENGINE_FILTER_TF=1h | FL2: LIVE_ENTRY_ENGINE_FILTER_TF=15m | FM2: LIVE_ONLY_SIGNALS_BATCH5_FILTER_TF=OFF | FN2: LIVE_ONLY_SIGNALS_BATCH5_FILTER_TF=D | FO2: LIVE_ONLY_SIGNALS_BATCH5_FILTER_TF=4h | FP2: LIVE_ONLY_SIGNALS_BATCH5_FILTER_TF=1h | FQ2: LIVE_ONLY_SIGNALS_BATCH5_FILTER_TF=15m | FR2: MANDATORY_REENTRY_WT_FILTER_TF_MODE=15m_only | FS2: MANDATORY_REENTRY_WT_FILTER_TF_MODE=15m_only_ALT | FT2: MOM3_FILTER_TF=OFF | FU2: MOM3_FILTER_TF=D | FV2: MOM3_FILTER_TF=4h | FW2: MOM3_FILTER_TF=1h | FX2: MOM3_FILTER_TF=15m | FY2: MOMENTUM_BREAKOUT_FILTER_TF=OFF | FZ2: MOMENTUM_BREAKOUT_FILTER_TF=D | GA2: MOMENTUM_BREAKOUT_FILTER_TF=4h | GB2: MOMENTUM_BREAKOUT_FILTER_TF=1h | GC2: MOMENTUM_BREAKOUT_FILTER_TF=15m | GD2: MTF_ARMED_ENTRIES_FILTER_TF=OFF | GE2: MTF_ARMED_ENTRIES_FILTER_TF=D | GF2: MTF_ARMED_ENTRIES_FILTER_TF=4h | GG2: MTF_ARMED_ENTRIES_FILTER_TF=1h | GH2: MTF_ARMED_ENTRIES_FILTER_TF=15m | GI2: MTF_ATR_TRAIL_FILTER_TF=OFF | GJ2: MTF_ATR_TRAIL_FILTER_TF=D | GK2: MTF_ATR_TRAIL_FILTER_TF=4h | GL2: MTF_ATR_TRAIL_FILTER_TF=1h | GM2: MTF_ATR_TRAIL_FILTER_TF=15m | GN2: MTF_DC_REJECT_FILTER_TF=OFF | GO2: MTF_DC_REJECT_FILTER_TF=D | GP2: MTF_DC_REJECT_FILTER_TF=4h | GQ2: MTF_DC_REJECT_FILTER_TF=1h | GR2: MTF_DC_REJECT_FILTER_TF=15m | GS2: NEWBORN_LOSS_KILL_FILTER_TF=OFF | GT2: NEWBORN_LOSS_KILL_FILTER_TF=D | GU2: NEWBORN_LOSS_KILL_FILTER_TF=4h | GV2: NEWBORN_LOSS_KILL_FILTER_TF=1h | GW2: NEWBORN_LOSS_KILL_FILTER_TF=15m | GX2: NEWBORN_PROTECT_FILTER_TF=OFF | GY2: NEWBORN_PROTECT_FILTER_TF=D | GZ2: NEWBORN_PROTECT_FILTER_TF=4h | HA2: NEWBORN_PROTECT_FILTER_TF=1h | HB2: NEWBORN_PROTECT_FILTER_TF=15m | HC2: NOLOSS_BYPASS_WT5OF5_FILTER_TF=OFF | HD2: NOLOSS_BYPASS_WT5OF5_FILTER_TF=D | HE2: NOLOSS_BYPASS_WT5OF5_FILTER_TF=4h | HF2: NOLOSS_BYPASS_WT5OF5_FILTER_TF=1h | HG2: NOLOSS_BYPASS_WT5OF5_FILTER_TF=15m | HH2: OPEN_INTENT_SIZE_GATES_FILTER_TF=OFF | HI2: OPEN_INTENT_SIZE_GATES_FILTER_TF=D | HJ2: OPEN_INTENT_SIZE_GATES_FILTER_TF=4h | HK2: OPEN_INTENT_SIZE_GATES_FILTER_TF=1h | HL2: OPEN_INTENT_SIZE_GATES_FILTER_TF=15m | HM2: PARTIAL_PROFIT_LOCK_V2_FILTER_TF=OFF | HN2: PARTIAL_PROFIT_LOCK_V2_FILTER_TF=D | HO2: PARTIAL_PROFIT_LOCK_V2_FILTER_TF=4h | HP2: PARTIAL_PROFIT_LOCK_V2_FILTER_TF=1h | HQ2: PARTIAL_PROFIT_LOCK_V2_FILTER_TF=15m | HR2: PEAK_GIVEBACK_BE_EROSION_FILTER_TF=OFF | HS2: PEAK_GIVEBACK_BE_EROSION_FILTER_TF=D | HT2: PEAK_GIVEBACK_BE_EROSION_FILTER_TF=4h | HU2: PEAK_GIVEBACK_BE_EROSION_FILTER_TF=1h | HV2: PEAK_GIVEBACK_BE_EROSION_FILTER_TF=15m | HW2: WT_15M_BOUNCE_BB_MAX=0.95 | HX2: WT_15M_BOUNCE_BB_MAX=0.9 | HY2: WT_15M_BOUNCE_BB_MAX=0.8 | HZ2: WT_15M_BOUNCE_BB_MIN=0.05 | IA2: WT_15M_BOUNCE_BB_MIN=0.1 | IB2: WT_15M_BOUNCE_BB_MIN=0.2 | IC2: WT_15M_BOUNCE_HIGH_1H_GT_PREV=True | ID2: WT_15M_BOUNCE_HIGH_1H_GT_PREV=False | IE2: WT_15M_BOUNCE_LOW_1H_GT_PREV=True | IF2: WT_15M_BOUNCE_LOW_1H_GT_PREV=False | IG2: WT_15M_BOUNCE_REL_VOL_GT_1=True | IH2: WT_15M_BOUNCE_REL_VOL_GT_1=False | II2: Live Location | IJ2: Vec Hook | IK2: Type | IL2: Correct Options
A3: UNIVERSAL_NOLOSS_GATE | B3: False | E3: =MAX('REDUCE_SIGNAL_RATER'!E:E) | F3: =IFERROR(VLOOKUP($A3&"="&$B3,Results_30d_Deltas!$A$2:$H$5000,5,FALSE),"") | G3: =IFERROR(VLOOKUP($A3,Results_30d_Deltas!$A$2:$H$5000,7,FALSE)-E3,"") | H3: =IFERROR(VLOOKUP($A3,Results_30d_Deltas!$A$2:$H$5000,6,FALSE),"") | K3: =IF(B3=C3,"YES","NO") | IJ3: ez_manage.py:4233 top() | IK3: v12_quick_engine.py:837 x18
A4: UNIVERSAL_NOLOSS_GATE | B4: True | E4: =IF(F4="",E3,IF(F4>0,E3+F4,E3)) | F4: =IFERROR(VLOOKUP($A4&"="&$B4,Results_30d_Deltas!$A$2:$H$5000,5,FALSE),"") | G4: =IFERROR(VLOOKUP($A4,Results_30d_Deltas!$A$2:$H$5000,7,FALSE)-E3,"") | H4: =IFERROR(VLOOKUP($A4,Results_30d_Deltas!$A$2:$H$5000,6,FALSE),"") | K4: =IF(B4=C4,"YES","NO") | IJ4: ez_manage.py:4233 top() | IK4: v12_quick_engine.py:837 x18
A5: COUNTER_TREND_ADD_BLOCK_ENABLED | B5: False | E5: =IF(F5="",E4,IF(F5>0,E4+F5,E4)) | F5: =IFERROR(VLOOKUP($A5&"="&$B5,Results_30d_Deltas!$A$2:$H$5000,5,FALSE),"") | G5: =IFERROR(VLOOKUP($A5,Results_30d_Deltas!$A$2:$H$5000,7,FALSE)-E4,"") | H5: =IFERROR(VLOOKUP($A5,Results_30d_Deltas!$A$2:$H$5000,6,FALSE),"") | K5: =IF(B5=C5,"YES","NO") | IJ5: ez_manage.py:3055 top() | IK5: v12_quick_engine.py:1469 x2
A6: COUNTER_TREND_ADD_BLOCK_ENABLED | B6: True | E6: =IF(F6="",E5,IF(F6>0,E5+F6,E5)) | F6: =IFERROR(VLOOKUP($A6&"="&$B6,Results_30d_Deltas!$A$2:$H$5000,5,FALSE),"") | G6: =IFERROR(VLOOKUP($A6,Results_30d_Deltas!$A$2:$H$5000,7,FALSE)-E5,"") | H6: =IFERROR(VLOOKUP($A6,Results_30d_Deltas!$A$2:$H$5000,6,FALSE),"") | K6: =IF(B6=C6,"YES","NO") | IJ6: ez_manage.py:3055 top() | IK6: v12_quick_engine.py:1469 x2
A7: RECENT_REDUCTION_GUARD_ENABLED | B7: False | E7: =IF(F7="",E6,IF(F7>0,E6+F7,E6)) | F7: =IFERROR(VLOOKUP($A7&"="&$B7,Results_30d_Deltas!$A$2:$H$5000,5,FALSE),"") | G7: =IFERROR(VLOOKUP($A7,Results_30d_Deltas!$A$2:$H$5000,7,FALSE)-E6,"") | H7: =IFERROR(VLOOKUP($A7,Results_30d_Deltas!$A$2:$H$5000,6,FALSE),"") | K7: =IF(B7=C7,"YES","NO") | IJ7: ez_manage.py:5264 top() | IK7: v12_quick_engine.py:2806 x1
A8: RECENT_REDUCTION_GUARD_ENABLED | B8: True | E8: =IF(F8="",E7,IF(F8>0,E7+F8,E7)) | F8: =IFERROR(VLOOKUP($A8&"="&$B8,Results_30d_Deltas!$A$2:$H$5000,5,FALSE),"") | G8: =IFERROR(VLOOKUP($A8,Results_30d_Deltas!$A$2:$H$5000,7,FALSE)-E7,"") | H8: =IFERROR(VLOOKUP($A8,Results_30d_Deltas!$A$2:$H$5000,6,FALSE),"") | K8: =IF(B8=C8,"YES","NO") | IJ8: ez_manage.py:5264 top() | IK8: v12_quick_engine.py:2806 x1
A9: ABSOLUTE_OPEN_LOCK_SEC | E9: =IF(F9="",E8,IF(F9>0,E8+F9,E8)) | F9: =IFERROR(VLOOKUP($A9&"="&$B9,Results_30d_Deltas!$A$2:$H$5000,5,FALSE),"") | G9: =IFERROR(VLOOKUP($A9,Results_30d_Deltas!$A$2:$H$5000,7,FALSE)-E8,"") | H9: =IFERROR(VLOOKUP($A9,Results_30d_Deltas!$A$2:$H$5000,6,FALSE),"") | K9: =IF(B9=C9,"YES","NO") | IJ9: config only | IK9: not declared
A10: BALANCE_FLOOR_USD | E10: =IF(F10="",E9,IF(F10>0,E9+F10,E9)) | F10: =IFERROR(VLOOKUP($A10&"="&$B10,Results_30d_Deltas!$A$2:$H$5000,5,FALSE),"") | G10: =IFERROR(VLOOKUP($A10,Results_30d_Deltas!$A$2:$H$5000,7,FALSE)-E9,"") | H10: =IFERROR(VLOOKUP($A10,Results_30d_Deltas!$A$2:$H$5000,6,FALSE),"") | K10: =IF(B10=C10,"YES","NO") | IJ10: config only | IK10: not declared
A11: BLACKLIST_SYMBOLS | B11: () | E11: =IF(F11="",E10,IF(F11>0,E10+F11,E10)) | F11: =IFERROR(VLOOKUP($A11&"="&$B11,Results_30d_Deltas!$A$2:$H$5000,5,FALSE),"") | G11: =IFERROR(VLOOKUP($A11,Results_30d_Deltas!$A$2:$H$5000,7,FALSE)-E10,"") | H11: =IFERROR(VLOOKUP($A11,Results_30d_Deltas!$A$2:$H$5000,6,FALSE),"") | K11: =IF(B11=C11,"YES","NO") | IJ11: ez_manage.py:4377 top() | IK11: v12_quick_engine.py:3798 x5
A12: CIRCUIT_BREAKER_THRESHOLD_PCT | E12: =IF(F12="",E11,IF(F12>0,E11+F12,E11)) | F12: =IFERROR(VLOOKUP($A12&"="&$B12,Results_30d_Deltas!$A$2:$H$5000,5,FALSE),"") | G12: =IFERROR(VLOOKUP($A12,Results_30d_Deltas!$A$2:$H$5000,7,FALSE)-E11,"") | H12: =IFERROR(VLOOKUP($A12,Results_30d_Deltas!$A$2:$H$5000,6,FALSE),"") | K12: =IF(B12=C12,"YES","NO") | IJ12: config only | IK12: not declared
